Workbook
Name FleetRatio: 'Box Consensus'!$D$4
Name NExp: 'DCF Cyclicals'!$H$23
Name TVx: 'DCF Cyclicals'!$H$24

Sheet DCF Cyclicals
B1: Cyclicals - DCF by sub-box with the analysts' cash-flow method (end-2027)
B2: Cash to shareholders = net income + D&A - capex +/- NWC (the analysts' bridge, net debt constant): consensus 2026-28, then sales, margin, D&A and capex projected for each sub-box. Two sub-boxes, summed. Ke unified with the other boxes.
B3: Legend: | C3: input | D3: assumption | E3: formula
B5: 1. Inputs
B6: Item | C6: W&E | D6: Ex | P6: Source / note
B7: Index points today | C7: ='Box Consensus'!D61 -> 10204.555 | D7: ='Box Consensus'!D62 -> 16066.52 | P7: W&E = WEG & Embraer; Ex = Cyclicals ex-WEG & Embraer (Box Consensus).
B8: Long-term IPCA | C8: 0.04 | P8: House and the analysts' Macro sheets.
B9: Share of the risk free kept after tax | C9: 0.85 | P9: As the analysts: risk free = (NTN-B + IPCA) x 0.85.
B10: Equity risk premium, the same for every box | C10: 0.055 | P10: Unified (Caio, Oct-8-2026).
B11: Earnings shock per 1% of the Ibovespa ex-Commodities shock (beta x normalization) | C11: 0.15085806 | D11: 1.7925093 | P11: Box Earnings!I13:I14 x I16 of the main model (WEG & Embraer 0.13, ex 1.51, normalized by 1.19).
B12: Working capital, % of sales | C12: 0.04 | P12: House assumption.
B13: Net margin from 2029 (blank = FY28 consensus of the sub-box) | P13: Typed value replaces the sub-box margin.
B14: Capex / D&A in the last explicit year (capex % of sales goes linearly from FY28 to it) | C14: 1 | D14: 1 | P14: Caio, Oct-8-2026: capex converges to D&A (maintenance) by the last explicit year, so the perpetuity does not carry expansion capex forever.
B15: D&A, % of sales, from 2029 (blank = FY28 consensus) | P15: Typed value replaces the sub-box ratio.
B16: Growth after 2028 starts from the 2028 consensus sales growth and goes linearly to g in the last explicit year | P16: As the analysts: the top line drives the model; margins and capital intensity at FY28.
B17: WEG & Embraer (global part): Brazil share of the real risk free | C17: 0.27917606 | P17: Analysts' weights by revenue geography: WEG 35% Brazil (DCF & Sensitivity C55), Embraer 20% (C66); weighted by index points.
B18: US real risk free | C18: 0.021 | P18: Analysts: WEG 2.08% (F56), Embraer 2.51% (F69).
B19: 2. House vs. analysts, variable by variable (choice: 1 = house, 2 = analysts)
B20: Variable | C20: House W&E | D20: House Ex | E20: Analysts / GDP W&E | F20: Analysts / GDP Ex | G20: Choice | H20: Used W&E | I20: Used Ex | P20: House / analysts
B21: Beta | C21: 0.7214 | D21: 1.324 | E21: 0.89 | F21: 1.02 | G21: 1 | H21: =IF($G21=1,C21,E21) -> 0.7214 | I21: =IF($G21=1,D21,F21) -> 1.324 | P21: House: sub-box betas, weekly 5 years from the local indices (Box Betas). Analysts: WEG 0.8 / Embraer 1.0; ex: Localiza 0.95, Rumo 1.0, Motiva 0.92, Renner 0.95, Totvs 0.8, Cyrela 1.46.
B22: Long-term real growth (g = IPCA + real growth) | C22: 0.007 | D22: 0.007 | E22: 0.02 | F22: 0.02 | G22: 2 | H22: =IF($G22=1,C22,E22) -> 0.02 | I22: =IF($G22=1,D22,F22) -> 0.02 | P22: Long-term real growth. House: g 4.7% = about 0.7% real over a 4% IPCA. Nominal GDP (Caio, Oct-8-2026): real GDP 2%, as Financials - Cyclicals sell to the domestic economy and should grow with nominal GDP in the perpetuity.
B23: Explicit years after the value date | C23: 4 | D23: 4 | E23: 8 | F23: 8 | G23: 2 | H23: =IF($G23=1,C23,E23) -> 8 | I23: =IF($G23=1,D23,F23) -> 8 | P23: Explicit years after end-2027. House: 2028-31. Analysts: to 2035.
B24: Extra periods in the discount of the terminal value | C24: 1 | D24: 1 | E24: 0 | F24: 0 | G24: 2 | H24: =IF($G24=1,C24,E24) -> 0 | I24: =IF($G24=1,D24,F24) -> 0 | P24: Extra periods in the discount of the terminal value. House: one more than the last flow. Analysts: none.
B25: g used = IPCA + real growth (choice 2 = nominal GDP 6.0%, as Financials) | H25: =$C$8+H22 -> 0.06 | I25: =$C$8+I22 -> 0.06
B27: 3. Cost of equity by scenario
B28: Item | C28: Bear | D28: Base | E28: Bull | P28: How it is calculated
B29: 5-year real rate (NTN-B) | C29: 0.085 | D29: 0.0676 | E29: 0.055 | P29: Same scenarios as the other boxes.
B30: Risk free, Brazil = (NTN-B + IPCA) x share kept after tax | C30: =(C29+$C$8)*$C$9 -> 0.10625 | D30: =(D29+$C$8)*$C$9 -> 0.09146 | E30: =(E29+$C$8)*$C$9 -> 0.08075 | P30: The rest of the index (unified).
B31: Risk free, global (WEG & Embraer) = (Brazil share x NTN-B + US share x US real + IPCA) x share kept | C31: =($C$17*C29+(1-$C$17)*$C$18+$C$8)*$C$9 -> 0.067037178 | D31: =($C$17*D29+(1-$C$17)*$C$18+$C$8)*$C$9 -> 0.062908164 | E31: =($C$17*E29+(1-$C$17)*$C$18+$C$8)*$C$9 -> 0.059918188 | P31: As the WEG and Embraer analysts: real risk free weighted by revenue geography; nominal in R$ with the IPCA.
B32: Ke, WEG & Embraer = global risk free + beta x ERP | C32: =C31+$H$21*$C$10 -> 0.10671418 | D32: =D31+$H$21*$C$10 -> 0.10258516 | E32: =E31+$H$21*$C$10 -> 0.099595188
B33: Ke, Cyclicals ex-WEG & Embraer = Brazil risk free + beta x ERP | C33: =C30+$I$21*$C$10 -> 0.17907 | D33: =D30+$I$21*$C$10 -> 0.16428 | E33: =E30+$I$21*$C$10 -> 0.15357
B35: 4a. WEG & Embraer: projection (index points)
B36: Line | C36: 2026 | D36: 2027 | E36: 2028 | F36: 2029 | G36: 2030 | H36: 2031 | I36: 2032 | J36: 2033 | K36: 2034 | L36: 2035 | M36: 2036 | N36: 2037 | P36: How it is calculated / source
B37: Years after end-2027 (grey = after the explicit years) | E37: =2028-2027 -> 1 | F37: =2029-2027 -> 2 | G37: =2030-2027 -> 3 | H37: =2031-2027 -> 4 | I37: =2032-2027 -> 5 | J37: =2033-2027 -> 6 | K37: =2034-2027 -> 7 | L37: =2035-2027 -> 8 | M37: =2036-2027 -> 9 | N37: =2037-2027 -> 10
B38: Sales growth: 2027-28 consensus; then from the 2028 growth linearly to g in the last explicit year | D38: =D39/C39-1 -> 0.12959741 | E38: =E39/D39-1 -> 0.1225765 | F38: =IF(F37>=NExp,$H$25,$E$38+($H$25-$E$38)*(F37-1)/(NExp-1)) -> 0.113637 | G38: =IF(G37>=NExp,$H$25,$E$38+($H$25-$E$38)*(G37-1)/(NExp-1)) -> 0.1046975 | H38: =IF(H37>=NExp,$H$25,$E$38+($H$25-$E$38)*(H37-1)/(NExp-1)) -> 0.095758 | I38: =IF(I37>=NExp,$H$25,$E$38+($H$25-$E$38)*(I37-1)/(NExp-1)) -> 0.0868185 | J38: =IF(J37>=NExp,$H$25,$E$38+($H$25-$E$38)*(J37-1)/(NExp-1)) -> 0.077879 | K38: =IF(K37>=NExp,$H$25,$E$38+($H$25-$E$38)*(K37-1)/(NExp-1)) -> 0.0689395 | L38: =IF(L37>=NExp,$H$25,$E$38+($H$25-$E$38)*(L37-1)/(NExp-1)) -> 0.06 | M38: =IF(M37>=NExp,$H$25,$E$38+($H$25-$E$38)*(M37-1)/(NExp-1)) -> 0.06 | N38: =IF(N37>=NExp,$H$25,$E$38+($H$25-$E$38)*(N37-1)/(NExp-1)) -> 0.06
B39: Sales | C39: ='Box Consensus'!F61 -> 4279.3755 | D39: ='Box Consensus'!G61 -> 4833.9715 | E39: ='Box Consensus'!H61 -> 5426.5028 | F39: =E39*(1+F38) -> 6043.1543 | G39: =F39*(1+G38) -> 6675.8574 | H39: =G39*(1+H38) -> 7315.1242 | I39: =H39*(1+I38) -> 7950.2123 | J39: =I39*(1+J38) -> 8569.3668 | K39: =J39*(1+K38) -> 9160.1347 | L39: =K39*(1+L38) -> 9709.7428 | M39: =L39*(1+M38) -> 10292.327 | N39: =M39*(1+N38) -> 10909.867 | P39: 2026-28: Box Consensus (sum of the members).
B40: Net margin (consensus; held at FY28 unless typed in the inputs) | C40: ='Box Consensus'!O61/'Box Consensus'!F61 -> 0.087764653 | D40: ='Box Consensus'!P61/'Box Consensus'!G61 -> 0.093459181 | E40: ='Box Consensus'!Q61/'Box Consensus'!H61 -> 0.099100679 | F40: =IF(ISNUMBER($C$13),$C$13,$E$40) -> 0.099100679 | G40: =IF(ISNUMBER($C$13),$C$13,$E$40) -> 0.099100679 | H40: =IF(ISNUMBER($C$13),$C$13,$E$40) -> 0.099100679 | I40: =IF(ISNUMBER($C$13),$C$13,$E$40) -> 0.099100679 | J40: =IF(ISNUMBER($C$13),$C$13,$E$40) -> 0.099100679 | K40: =IF(ISNUMBER($C$13),$C$13,$E$40) -> 0.099100679 | L40: =IF(ISNUMBER($C$13),$C$13,$E$40) -> 0.099100679 | M40: =IF(ISNUMBER($C$13),$C$13,$E$40) -> 0.099100679 | N40: =IF(ISNUMBER($C$13),$C$13,$E$40) -> 0.099100679
B41: Net income = sales x net margin | C41: =C39*C40 -> 375.5779 | D41: =D39*D40 -> 451.77901 | E41: =E39*E40 -> 537.77011 | F41: =F39*F40 -> 598.88069 | G41: =G39*G40 -> 661.582 | H41: =H39*H40 -> 724.93377 | I41: =I39*I40 -> 787.87144 | J41: =J39*J40 -> 849.23008 | ... N41: =N39*N40 -> 1081.1752
B42: D&A, % of sales (EBITDA - EBIT, consensus; held at FY28) | C42: =('Box Consensus'!I61-'Box Consensus'!L61)/'Box Consensus'!F61 -> 0.027878596 | D42: =('Box Consensus'!J61-'Box Consensus'!M61)/'Box Consensus'!G61 -> 0.026076899 | E42: =('Box Consensus'!K61-'Box Consensus'!N61)/'Box Consensus'!H61 -> 0.02626569 | F42: =IF(ISNUMBER($C$15),$C$15,$E$42) -> 0.02626569 | G42: =IF(ISNUMBER($C$15),$C$15,$E$42) -> 0.02626569 | H42: =IF(ISNUMBER($C$15),$C$15,$E$42) -> 0.02626569 | I42: =IF(ISNUMBER($C$15),$C$15,$E$42) -> 0.02626569 | J42: =IF(ISNUMBER($C$15),$C$15,$E$42) -> 0.02626569 | K42: =IF(ISNUMBER($C$15),$C$15,$E$42) -> 0.02626569 | L42: =IF(ISNUMBER($C$15),$C$15,$E$42) -> 0.02626569 | M42: =IF(ISNUMBER($C$15),$C$15,$E$42) -> 0.02626569 | N42: =IF(ISNUMBER($C$15),$C$15,$E$42) -> 0.02626569
B43: (+) D&A | C43: =C39*C42 -> 119.30298 | D43: =D39*D42 -> 126.05499 | E43: =E39*E42 -> 142.53084 | F43: =F39*F42 -> 158.72762 | G43: =G39*G42 -> 175.346 | H43: =H39*H42 -> 192.13679 | I43: =I39*I42 -> 208.81781 | J43: =J39*J42 -> 225.08034 | ... N43: =N39*N42 -> 286.55519
B44: Capex, % of sales (consensus; then linearly to D&A x C14 in the last explicit year) | C44: =-('Box Consensus'!R61+'Box Consensus'!U61)/'Box Consensus'!F61 -> 0.05132531 | D44: =-('Box Consensus'!S61+'Box Consensus'!V61)/'Box Consensus'!G61 -> 0.04610473 | E44: =-('Box Consensus'!T61+'Box Consensus'!W61)/'Box Consensus'!H61 -> 0.042876079 | F44: =IF(F37>=NExp,F42*$C$14,$E$44+(F42*$C$14-$E$44)*(F37-1)/(NExp-1)) -> 0.040503166 | G44: =IF(G37>=NExp,G42*$C$14,$E$44+(G42*$C$14-$E$44)*(G37-1)/(NExp-1)) -> 0.038130254 | H44: =IF(H37>=NExp,H42*$C$14,$E$44+(H42*$C$14-$E$44)*(H37-1)/(NExp-1)) -> 0.035757341 | I44: =IF(I37>=NExp,I42*$C$14,$E$44+(I42*$C$14-$E$44)*(I37-1)/(NExp-1)) -> 0.033384428 | J44: =IF(J37>=NExp,J42*$C$14,$E$44+(J42*$C$14-$E$44)*(J37-1)/(NExp-1)) -> 0.031011516 | K44: =IF(K37>=NExp,K42*$C$14,$E$44+(K42*$C$14-$E$44)*(K37-1)/(NExp-1)) -> 0.028638603 | L44: =IF(L37>=NExp,L42*$C$14,$E$44+(L42*$C$14-$E$44)*(L37-1)/(NExp-1)) -> 0.02626569 | M44: =IF(M37>=NExp,M42*$C$14,$E$44+(M42*$C$14-$E$44)*(M37-1)/(NExp-1)) -> 0.02626569 | N44: =IF(N37>=NExp,N42*$C$14,$E$44+(N42*$C$14-$E$44)*(N37-1)/(NExp-1)) -> 0.02626569
B45: (-) Capex | C45: =-C39*C44 -> -219.64027 | D45: =-D39*D44 -> -222.86895 | E45: =-E39*E44 -> -232.66716 | F45: =-F39*F44 -> -244.76688 | G45: =-G39*G44 -> -254.55214 | H45: =-H39*H44 -> -261.56939 | I45: =-I39*I44 -> -265.41329 | J45: =-J39*J44 -> -265.74905 | ... N45: =-N39*N44 -> -286.55519
B46: (+/-) Change in working capital = -NWC % x change in sales | D46: =-$C$12*(D39-C39) -> -22.183839 | E46: =-$C$12*(E39-D39) -> -23.701252 | F46: =-$C$12*(F39-E39) -> -24.66606 | G46: =-$C$12*(G39-F39) -> -25.308126 | H46: =-$C$12*(H39-G39) -> -25.57067 | I46: =-$C$12*(I39-H39) -> -25.403524 | J46: =-$C$12*(J39-I39) -> -24.766183 | K46: =-$C$12*(K39-J39) -> -23.630715 | ... N46: =-$C$12*(N39-M39) -> -24.701586
B47: Cash to shareholders = net income + D&A - capex +/- NWC | D47: =D41+D43+D45+D46 -> 332.78121 | E47: =E41+E43+E45+E46 -> 423.93254 | F47: =F41+F43+F45+F46 -> 488.17537 | G47: =G41+G43+G45+G46 -> 557.06774 | H47: =H41+H43+H45+H46 -> 629.9305 | I47: =I41+I43+I45+I46 -> 705.87243 | J47: =J41+J43+J45+J46 -> 783.79517 | K47: =K41+K43+K45+K46 -> 862.40866 | ... N47: =N41+N43+N45+N46 -> 1056.4736 | P47: The analysts' bridge, with net debt held constant (no new debt funds the capex); leases pending the Bloomberg pull.
B48: Cash to shareholders / net income | D48: =D47/D41 -> 0.73660175 | E48: =E47/E41 -> 0.78831554 | F48: =F47/F41 -> 0.81514628 | G48: =G47/G41 -> 0.84202373 | H48: =H47/H41 -> 0.86894903 | I48: =I47/I41 -> 0.89592337 | J48: =J47/J41 -> 0.92294797 | K48: =K47/K41 -> 0.95002409 | ... N48: =N47/N41 -> 0.97715302
B49: Memo: ROE (consensus) | C49: ='Box Consensus'!O61/'Box Consensus'!X61 -> 0.20467262 | D49: ='Box Consensus'!P61/'Box Consensus'!Y61 -> 0.21162501 | E49: ='Box Consensus'!Q61/'Box Consensus'!Z61 -> 0.21584493 | P49: Sum of net income / sum of book value (net income / BEST_ROE).
B50: Memo: implied return on reinvestment = sales growth / (1 - cash / net income) | F50: =IFERROR(F38/(1-F48),"") -> 0.61474013 | G50: =IFERROR(G38/(1-G48),"") -> 0.66274193 | H50: =IFERROR(H38/(1-H48),"") -> 0.7306928 | I50: =IFERROR(I38/(1-I48),"") -> 0.83417863 | J50: =IFERROR(J38/(1-J48),"") -> 1.0107326 | K50: =IFERROR(K38/(1-K48),"") -> 1.3794545 | L50: =IFERROR(L38/(1-L48),"") -> 2.626168 | M50: =IFERROR(M38/(1-M48),"") -> 2.626168 | N50: =IFERROR(N38/(1-N48),"") -> 2.626168 | P50: Sanity check of the perpetuity: the return the reinvested cash must earn to deliver the growth; compare with the ROE.
B52: 4b. Cyclicals ex-WEG & Embraer: projection (index points)
B53: Line | C53: 2026 | D53: 2027 | E53: 2028 | F53: 2029 | G53: 2030 | H53: 2031 | I53: 2032 | J53: 2033 | K53: 2034 | L53: 2035 | M53: 2036 | N53: 2037 | P53: How it is calculated / source
B54: Years after end-2027 (grey = after the explicit years) | E54: =2028-2027 -> 1 | F54: =2029-2027 -> 2 | G54: =2030-2027 -> 3 | H54: =2031-2027 -> 4 | I54: =2032-2027 -> 5 | J54: =2033-2027 -> 6 | K54: =2034-2027 -> 7 | L54: =2035-2027 -> 8 | M54: =2036-2027 -> 9 | N54: =2037-2027 -> 10
B55: Sales growth: 2027-28 consensus; then from the 2028 growth linearly to g in the last explicit year | D55: =D56/C56-1 -> 0.0827563 | E55: =E56/D56-1 -> 0.07121834 | F55: =IF(F54>=NExp,$I$25,$E$55+($I$25-$E$55)*(F54-1)/(NExp-1)) -> 0.06961572 | G55: =IF(G54>=NExp,$I$25,$E$55+($I$25-$E$55)*(G54-1)/(NExp-1)) -> 0.0680131 | H55: =IF(H54>=NExp,$I$25,$E$55+($I$25-$E$55)*(H54-1)/(NExp-1)) -> 0.06641048 | I55: =IF(I54>=NExp,$I$25,$E$55+($I$25-$E$55)*(I54-1)/(NExp-1)) -> 0.06480786 | J55: =IF(J54>=NExp,$I$25,$E$55+($I$25-$E$55)*(J54-1)/(NExp-1)) -> 0.06320524 | K55: =IF(K54>=NExp,$I$25,$E$55+($I$25-$E$55)*(K54-1)/(NExp-1)) -> 0.06160262 | L55: =IF(L54>=NExp,$I$25,$E$55+($I$25-$E$55)*(L54-1)/(NExp-1)) -> 0.06 | M55: =IF(M54>=NExp,$I$25,$E$55+($I$25-$E$55)*(M54-1)/(NExp-1)) -> 0.06 | N55: =IF(N54>=NExp,$I$25,$E$55+($I$25-$E$55)*(N54-1)/(NExp-1)) -> 0.06
B56: Sales | C56: ='Box Consensus'!F62 -> 12657.227 | D56: ='Box Consensus'!G62 -> 13704.692 | E56: ='Box Consensus'!H62 -> 14680.718 | F56: =E56*(1+F55) -> 15702.726 | G56: =F56*(1+G55) -> 16770.717 | H56: =G56*(1+H55) -> 17884.469 | I56: =H56*(1+I55) -> 19043.523 | J56: =I56*(1+J55) -> 20247.173 | K56: =J56*(1+K55) -> 21494.452 | L56: =K56*(1+L55) -> 22784.12 | M56: =L56*(1+M55) -> 24151.167 | N56: =M56*(1+N55) -> 25600.237 | P56: 2026-28: Box Consensus (sum of the members).
B57: Net margin (consensus; held at FY28 unless typed in the inputs) | C57: ='Box Consensus'!O62/'Box Consensus'!F62 -> 0.097293633 | D57: ='Box Consensus'!P62/'Box Consensus'!G62 -> 0.1089504 | E57: ='Box Consensus'!Q62/'Box Consensus'!H62 -> 0.12032998 | F57: =IF(ISNUMBER($D$13),$D$13,$E$57) -> 0.12032998 | G57: =IF(ISNUMBER($D$13),$D$13,$E$57) -> 0.12032998 | H57: =IF(ISNUMBER($D$13),$D$13,$E$57) -> 0.12032998 | I57: =IF(ISNUMBER($D$13),$D$13,$E$57) -> 0.12032998 | J57: =IF(ISNUMBER($D$13),$D$13,$E$57) -> 0.12032998 | K57: =IF(ISNUMBER($D$13),$D$13,$E$57) -> 0.12032998 | L57: =IF(ISNUMBER($D$13),$D$13,$E$57) -> 0.12032998 | M57: =IF(ISNUMBER($D$13),$D$13,$E$57) -> 0.12032998 | N57: =IF(ISNUMBER($D$13),$D$13,$E$57) -> 0.12032998
B58: Net income = sales x net margin | C58: =C56*C57 -> 1231.4676 | D58: =D56*D57 -> 1493.1316 | E58: =E56*E57 -> 1766.5305 | F58: =F56*F57 -> 1889.5088 | G58: =G56*G57 -> 2018.0202 | H58: =H56*H57 -> 2152.0379 | I58: =I56*I57 -> 2291.5068 | J58: =J56*J57 -> 2436.3421 | ... N58: =N56*N57 -> 3080.4761
B59: D&A, % of sales (EBITDA - EBIT, consensus; held at FY28) | C59: =('Box Consensus'!I62-'Box Consensus'!L62)/'Box Consensus'!F62 -> 0.087464845 | D59: =('Box Consensus'!J62-'Box Consensus'!M62)/'Box Consensus'!G62 -> 0.084916204 | E59: =('Box Consensus'!K62-'Box Consensus'!N62)/'Box Consensus'!H62 -> 0.082746171 | F59: =IF(ISNUMBER($D$15),$D$15,$E$59) -> 0.082746171 | G59: =IF(ISNUMBER($D$15),$D$15,$E$59) -> 0.082746171 | H59: =IF(ISNUMBER($D$15),$D$15,$E$59) -> 0.082746171 | I59: =IF(ISNUMBER($D$15),$D$15,$E$59) -> 0.082746171 | J59: =IF(ISNUMBER($D$15),$D$15,$E$59) -> 0.082746171 | K59: =IF(ISNUMBER($D$15),$D$15,$E$59) -> 0.082746171 | L59: =IF(ISNUMBER($D$15),$D$15,$E$59) -> 0.082746171 | M59: =IF(ISNUMBER($D$15),$D$15,$E$59) -> 0.082746171 | N59: =IF(ISNUMBER($D$15),$D$15,$E$59) -> 0.082746171
B60: (+) D&A | C60: =C56*C59 -> 1107.0624 | D60: =D56*D59 -> 1163.7504 | E60: =E56*E59 -> 1214.7732 | F60: =F56*F59 -> 1299.3405 | G60: =G56*G59 -> 1387.7127 | H60: =H56*H59 -> 1479.8713 | I60: =I56*I59 -> 1575.7786 | J60: =J56*J59 -> 1675.3761 | ... N60: =N56*N59 -> 2118.3216
B61: Capex, % of sales (consensus; then linearly to D&A x C14 in the last explicit year) | C61: =-('Box Consensus'!R62+'Box Consensus'!U62)/'Box Consensus'!F62 -> 0.12485421 | D61: =-('Box Consensus'!S62+'Box Consensus'!V62)/'Box Consensus'!G62 -> 0.11076816 | E61: =-('Box Consensus'!T62+'Box Consensus'!W62)/'Box Consensus'!H62 -> 0.10457347 | F61: =IF(F54>=NExp,F59*$D$14,$E$61+(F59*$D$14-$E$61)*(F54-1)/(NExp-1)) -> 0.10145529 | G61: =IF(G54>=NExp,G59*$D$14,$E$61+(G59*$D$14-$E$61)*(G54-1)/(NExp-1)) -> 0.098337101 | H61: =IF(H54>=NExp,H59*$D$14,$E$61+(H59*$D$14-$E$61)*(H54-1)/(NExp-1)) -> 0.095218915 | I61: =IF(I54>=NExp,I59*$D$14,$E$61+(I59*$D$14-$E$61)*(I54-1)/(NExp-1)) -> 0.092100729 | J61: =IF(J54>=NExp,J59*$D$14,$E$61+(J59*$D$14-$E$61)*(J54-1)/(NExp-1)) -> 0.088982543 | K61: =IF(K54>=NExp,K59*$D$14,$E$61+(K59*$D$14-$E$61)*(K54-1)/(NExp-1)) -> 0.085864357 | L61: =IF(L54>=NExp,L59*$D$14,$E$61+(L59*$D$14-$E$61)*(L54-1)/(NExp-1)) -> 0.082746171 | M61: =IF(M54>=NExp,M59*$D$14,$E$61+(M59*$D$14-$E$61)*(M54-1)/(NExp-1)) -> 0.082746171 | N61: =IF(N54>=NExp,N59*$D$14,$E$61+(N59*$D$14-$E$61)*(N54-1)/(NExp-1)) -> 0.082746171
B62: (-) Capex | C62: =-C56*C61 -> -1580.3081 | D62: =-D56*D61 -> -1518.0436 | E62: =-E56*E61 -> -1535.2136 | F62: =-F56*F61 -> -1593.1246 | G62: =-G56*G61 -> -1649.1837 | H62: =-H56*H61 -> -1702.9397 | I62: =-I56*I61 -> -1753.9224 | J62: =-J56*J61 -> -1801.645 | ... N62: =-N56*N61 -> -2118.3216
B63: (+/-) Change in working capital = -NWC % x change in sales | D63: =-$C$12*(D56-C56) -> -41.898611 | E63: =-$C$12*(E56-D56) -> -39.041017 | F63: =-$C$12*(F56-E56) -> -40.880349 | G63: =-$C$12*(G56-F56) -> -42.719644 | H63: =-$C$12*(H56-G56) -> -44.550056 | I63: =-$C$12*(I56-H56) -> -46.362166 | J63: =-$C$12*(J56-I56) -> -48.146018 | K63: =-$C$12*(K56-J56) -> -49.891157 | ... N63: =-$C$12*(N56-M56) -> -57.9628
B64: Cash to shareholders = net income + D&A - capex +/- NWC | D64: =D58+D60+D62+D63 -> 1096.9399 | E64: =E58+E60+E62+E63 -> 1407.0491 | F64: =F58+F60+F62+F63 -> 1554.8444 | G64: =G58+G60+G62+G63 -> 1713.8295 | H64: =H58+H60+H62+H63 -> 1884.4194 | I64: =I58+I60+I62+I63 -> 2067.0009 | J64: =J58+J60+J62+J63 -> 2261.9272 | K64: =K58+K60+K62+K63 -> 2469.5123 | ... N64: =N58+N60+N62+N63 -> 3022.5133 | P64: The analysts' bridge, with net debt held constant (no new debt funds the capex); leases pending the Bloomberg pull.
B65: Cash to shareholders / net income | D65: =D64/D58 -> 0.73465718 | E65: =E64/E58 -> 0.79650424 | F65: =F64/F58 -> 0.82288282 | G65: =G64/G58 -> 0.8492628 | H65: =H64/H58 -> 0.87564417 | I65: =I64/I58 -> 0.90202695 | J65: =J64/J58 -> 0.92841115 | K65: =K64/K58 -> 0.95479677 | ... N65: =N64/N58 -> 0.98118382
B66: Memo: ROE (consensus) | C66: ='Box Consensus'!O62/'Box Consensus'!X62 -> 0.13140243 | D66: ='Box Consensus'!P62/'Box Consensus'!Y62 -> 0.14802716 | E66: ='Box Consensus'!Q62/'Box Consensus'!Z62 -> 0.17023515 | P66: Sum of net income / sum of book value (net income / BEST_ROE).
B67: Memo: implied return on reinvestment = sales growth / (1 - cash / net income) | F67: =IFERROR(F55/(1-F65),"") -> 0.39304894 | G67: =IFERROR(G55/(1-G65),"") -> 0.45120314 | H67: =IFERROR(H55/(1-H65),"") -> 0.53403592 | I67: =IFERROR(I55/(1-I65),"") -> 0.66148663 | J67: =IFERROR(J55/(1-J65),"") -> 0.88289227 | K67: =IFERROR(K55/(1-K65),"") -> 1.3627925 | L67: =IFERROR(L55/(1-L65),"") -> 3.1887446 | M67: =IFERROR(M55/(1-M65),"") -> 3.1887446 | N67: =IFERROR(N55/(1-N65),"") -> 3.1887446 | P67: Sanity check of the perpetuity: the return the reinvested cash must earn to deliver the growth; compare with the ROE.
B69: 5. Valuation at the end of 2027
B70: Item | C70: Bear | D70: Base | E70: Bull | P70: How it is calculated
B71: Earnings shock of the Ibovespa ex-Commodities | C71: -0.2 | D71: 0 | E71: 0.2 | P71: Symmetric +/-20%, as the other boxes.
B72: WEG & Embraer: earnings shock = beta x normalization x shock | C72: =$C$11*C$71 -> -0.030171612 | D72: =$C$11*D$71 -> 0 | E72: =$C$11*E$71 -> 0.030171612
B73: WEG & Embraer: PV of the explicit flows (+ shock x PV of net income) | C73: =SUMPRODUCT($E$47:$N$47,--($E$37:$N$37<=NExp),1/(1+C32)^$E$37:$N$37)+C72*SUMPRODUCT($E$41:$N$41,--($E$37:$N$37<=NExp),1/(1+C32)^$E$37:$N$37) -> 3192.7588 | D73: =SUMPRODUCT($E$47:$N$47,--($E$37:$N$37<=NExp),1/(1+D32)^$E$37:$N$37)+D72*SUMPRODUCT($E$41:$N$41,--($E$37:$N$37<=NExp),1/(1+D32)^$E$37:$N$37) -> 3363.1146 | E73: =SUMPRODUCT($E$47:$N$47,--($E$37:$N$37<=NExp),1/(1+E32)^$E$37:$N$37)+E72*SUMPRODUCT($E$41:$N$41,--($E$37:$N$37<=NExp),1/(1+E32)^$E$37:$N$37) -> 3521.929
B74: WEG & Embraer: PV of the terminal value | C74: =(INDEX($E$47:$N$47,NExp)+C72*INDEX($E$41:$N$41,NExp))*(1+$H$25)/(C32-$H$25)/(1+C32)^(NExp+TVx) -> 9187.5387 | D74: =(INDEX($E$47:$N$47,NExp)+D72*INDEX($E$41:$N$41,NExp))*(1+$H$25)/(D32-$H$25)/(1+D32)^(NExp+TVx) -> 10715.127 | E74: =(INDEX($E$47:$N$47,NExp)+E72*INDEX($E$41:$N$41,NExp))*(1+$H$25)/(E32-$H$25)/(1+E32)^(NExp+TVx) -> 12141.005 | P74: Gordon on the last explicit flow.
B75: WEG & Embraer: fair value (index pts) | C75: =C73+C74 -> 12380.298 | D75: =D73+D74 -> 14078.242 | E75: =E73+E74 -> 15662.934
B76: WEG & Embraer: upside | C76: =C75/$C$7-1 -> 0.21321287 | D76: =D75/$C$7-1 -> 0.37960368 | E76: =E75/$C$7-1 -> 0.53489627
B78: Cyclicals ex-WEG & Embraer: earnings shock = beta x normalization x shock | C78: =$D$11*C$71 -> -0.35850186 | D78: =$D$11*D$71 -> 0 | E78: =$D$11*E$71 -> 0.35850186
B79: Cyclicals ex-WEG & Embraer: PV of the explicit flows (+ shock x PV of net income) | C79: =SUMPRODUCT($E$64:$N$64,--($E$54:$N$54<=NExp),1/(1+C33)^$E$54:$N$54)+C78*SUMPRODUCT($E$58:$N$58,--($E$54:$N$54<=NExp),1/(1+C33)^$E$54:$N$54) -> 4474.6604 | D79: =SUMPRODUCT($E$64:$N$64,--($E$54:$N$54<=NExp),1/(1+D33)^$E$54:$N$54)+D78*SUMPRODUCT($E$58:$N$58,--($E$54:$N$54<=NExp),1/(1+D33)^$E$54:$N$54) -> 7989.502 | E79: =SUMPRODUCT($E$64:$N$64,--($E$54:$N$54<=NExp),1/(1+E33)^$E$54:$N$54)+E78*SUMPRODUCT($E$58:$N$58,--($E$54:$N$54<=NExp),1/(1+E33)^$E$54:$N$54) -> 11699.114
B80: Cyclicals ex-WEG & Embraer: PV of the terminal value | C80: =(INDEX($E$64:$N$64,NExp)+C78*INDEX($E$58:$N$58,NExp))*(1+$I$25)/(C33-$I$25)/(1+C33)^(NExp+TVx) -> 4068.733 | D80: =(INDEX($E$64:$N$64,NExp)+D78*INDEX($E$58:$N$58,NExp))*(1+$I$25)/(D33-$I$25)/(1+D33)^(NExp+TVx) -> 8098.4487 | E80: =(INDEX($E$64:$N$64,NExp)+E78*INDEX($E$58:$N$58,NExp))*(1+$I$25)/(E33-$I$25)/(1+E33)^(NExp+TVx) -> 13268.647 | P80: Gordon on the last explicit flow.
B81: Cyclicals ex-WEG & Embraer: fair value (index pts) | C81: =C79+C80 -> 8543.3934 | D81: =D79+D80 -> 16087.951 | E81: =E79+E80 -> 24967.761
B82: Cyclicals ex-WEG & Embraer: upside | C82: =C81/$D$7-1 -> -0.46824865 | D82: =D81/$D$7-1 -> 0.0013338983 | E82: =E81/$D$7-1 -> 0.55402423
B84: Cyclicals: fair value (index pts) = sum of the parts (WEG & Embraer, global + the rest, unified) | C84: =C75+C81 -> 20923.691 | D84: =D75+D81 -> 30166.192 | E84: =E75+E81 -> 40630.694
B85: Cyclicals: upside vs. today | C85: =C84/($C$7+$D$7)-1 -> -0.20354644 | D85: =D84/($C$7+$D$7)-1 -> 0.1482664 | E85: =E84/($C$7+$D$7)-1 -> 0.5465943
B86: Memo: upside in the unified DCF by box (main model, v7b) | C86: -0.5811 | D86: -0.2218 | E86: 0.2317 | P86: Cyclicals_DCF_XP.xlsx.
B87: Memo: upside in the multiples model (Oct-6) | C87: 0.02 | D87: 0.4 | E87: 0.85 | P87: Ibov_valuation_by_box_model_XP.xlsx.
B89: 6. What is fixed (not switchable) and where it comes from
B90: Risk free nominal: (NTN-B + IPCA) x 0.85; ERP 5.5% for every box | P90: Unified (Caio)
B91: Sum of the parts: WEG & Embraer valued as a global part (risk free by revenue geography, as their analysts); the rest unified | P91: Caio, Oct-8-2026
B92: Consensus only (2026-28 sales, net income, EBITDA, EBIT, capex); no company-specific adjustments | P92: Caio
B93: Cash to shareholders = net income + D&A - capex +/- NWC, net debt constant (the analysts' bridge); perpetuity on the last explicit flow | P93: Analysts (Caio, Oct-8-2026)
B94: From 2029: sales from the 2028 growth to g; net margin and D&A % of sales at FY28; capex converges to D&A by the last explicit year | P94: Box level only (Caio)
B95: Scenario real rates 8.5% / today / 5.5%; earnings shock +/-20% x earnings beta, on net income | P95: House / main model
B96: Pending the Bloomberg pull: leases (IFRS 16) and concession fees | P96: Not in the consensus

Sheet Box Consensus
B1: Cyclicals - consensus 2026-28 of the members, summed into the two sub-boxes
B2: Bloomberg BEST consensus (Oct-7-2026, company totals in R$ mn; Members sheet of the main model; ROE from dcf_members.parquet). Index points = R$ mn x points / market cap. Only 2026-28 are built from the members.
B3: Legend: | C3: input | D3: assumption | E3: formula
B4: Fleet sales / gross capex (Localiza model, 2028) | D4: 0.72744691 | E4: Capex net of the used cars sold, as the analysts' bridge (Caio, Oct-8-2026): Localiza model 2028, book value of cars sold / gross capex = 73%; applied to Localiza and Vamos (rental fleets). 0 = gross capex.
B7: 1. Consensus by member (R$ mn; ROE in %)
B8: Member | C8: Sub-box | D8: Index points | E8: Points / market cap | F8: Sales 2026 | G8: Sales 2027 | H8: Sales 2028 | I8: EBITDA 2026 | J8: EBITDA 2027 | K8: EBITDA 2028 | L8: EBIT 2026 | M8: EBIT 2027 | N8: EBIT 2028 | O8: Net income 2026 | P8: Net income 2027 | Q8: Net income 2028 | R8: Capex 2026 | S8: Capex 2027 | T8: Capex 2028 | U8: Fleet sales 2026 | V8: Fleet sales 2027 | W8: Fleet sales 2028 | X8: ROE 2026 | Y8: ROE 2027 | Z8: ROE 2028
B9: Weg (WEGE3) | C9: WEG & Embraer | D9: 5386.7222 | E9: =D9/215196.49375746 -> 0.025031645 | F9: 41713.188 | G9: 48520.5 | H9: 56448.214 | I9: 9170.4667 | J9: 10852.267 | K9: 12863.5 | L9: 8084.6 | M9: 9588.0667 | N9: 11394.533 | O9: 6440.25 | P9: 7619.5 | Q9: 8928.143 | R9: -3553 | S9: -3328 | T9: -3328.1111 | U9: 0 | V9: 0 | W9: 0 | X9: 0.3417 | Y9: 0.32072 | Z9: 0.31405
B10: Embraer (EMBJ3) | C10: WEG & Embraer | D10: 4817.8329 | E10: =D10/66153.14703096 -> 0.072828476 | F10: 44422.538 | G10: 49697.917 | H10: 55109.091 | I10: 5802.5833 | J10: 6596.0833 | K10: 7501.4545 | L10: 4537.6667 | M10: 5299.75 | N10: 6049.2727 | O10: 2943.462 | P10: 3584.455 | Q10: 4315.4 | R10: -1794.6667 | S10: -1916.3333 | T10: -2050.8333 | U10: 0 | V10: 0 | W10: 0 | X10: 0.15725 | Y10: 0.1695 | Z10: 0.17658
B11: Localiza (RENT3) | C11: Cyclicals ex-WEG & Embraer | D11: 3528.9277 | E11: =D11/56927.4969252 -> 0.061989862 | F11: 50013.25 | G11: 53487.75 | H11: 57020.167 | I11: 15815.75 | J11: 17033.5 | K11: 18414.667 | L11: 10127 | M11: 10959.091 | N11: 12195.636 | O11: 4288.833 | P11: 4771.273 | Q11: 5818.455 | R11: -23848 | S11: -26666.8 | T11: -26482.5 | U11: =-R11*FleetRatio -> 17348.154 | V11: =-S11*FleetRatio -> 19398.681 | W11: =-T11*FleetRatio -> 19264.613 | X11: 0.15723 | Y11: 0.16306 | Z11: 0.18642
B12: Rumo (RAIL3) | C12: Cyclicals ex-WEG & Embraer | D12: 1897.6387 | E12: =D12/34406.91770067 -> 0.055152826 | F12: 14779.917 | G12: 15642.182 | H12: 16416.5 | I12: 8140.1818 | J12: 8991.9 | K12: 9504.7778 | L12: 5803.1 | M12: 6618 | N12: 6974.8 | O12: 1917.727 | P12: 2669.7 | Q12: 3229.4 | R12: -5817.6667 | S12: -4786.5 | T12: -4930.8333 | U12: 0 | V12: 0 | W12: 0 | X12: 0.12653 | Y12: 0.15813 | Z12: 0.16495
B13: Motiva (MOTV3) | C13: Cyclicals ex-WEG & Embraer | D13: 1406.9784 | E13: =D13/39895 -> 0.035267037 | F13: 18179.286 | G13: 19255 | H13: 21238.667 | I13: 10278.111 | J13: 11125.222 | K13: 12640.571 | L13: 7972.1111 | M13: 8459.8889 | N13: 9510.75 | O13: 2759.5 | P13: 2858.556 | Q13: 3504.429 | R13: -9351 | S13: -7625 | T13: -8095 | U13: 0 | V13: 0 | W13: 0 | X13: 0.14718 | Y13: 0.14652 | Z13: 0.17485
B14: TOTVS (TOTS3) | C14: Cyclicals ex-WEG & Embraer | D14: 1378.3571 | E14: =D14/23568.47016492 -> 0.058483096 | F14: 7675.8462 | G14: 8856.5 | H14: 9997.75 | I14: 2001.9091 | J14: 2357.0833 | K14: 2763.7143 | L14: 1487.2 | M14: 1881.8182 | N14: 2259.5 | O14: 1078 | P14: 1223.182 | Q14: 1570.5 | R14: -393.33333 | S14: -432.33333 | T14: -473.66667 | U14: 0 | V14: 0 | W14: 0 | X14: 0.21023 | Y14: 0.18546 | Z14: 0.22057
B15: Allos (ALOS3) | C15: Cyclicals ex-WEG & Embraer | D15: 1141.4957 | E15: =D15/17374.42003362 -> 0.065699785 | F15: 2994.875 | G15: 3153 | H15: 3296 | I15: 2219.4 | J15: 2344.6 | K15: 2453.25 | L15: 1619.25 | M15: 1754.75 | N15: 1841.8571 | O15: 916.222 | P15: 960 | Q15: 1078.714 | R15: -331 | S15: -436 | T15: -257 | U15: 0 | V15: 0 | W15: 0 | X15: 0.07269 | Y15: 0.07893 | Z15: 0.0939
B16: Lojas Renner (LREN3) | C16: Cyclicals ex-WEG & Embraer | D16: 951.12139 | E16: =D16/13521.92962585 -> 0.070339176 | F16: 16650.077 | G16: 17782.571 | H16: 19255.385 | I16: 3261.3 | J16: 3505.9 | K16: 3808.4 | L16: 1955.4667 | M16: 2136.3333 | N16: 2373.0667 | O16: 1553.2 | P16: 1645 | Q16: 1797.143 | R16: -968.44444 | S16: -1016.3333 | T16: -1078 | U16: 0 | V16: 0 | W16: 0 | X16: 0.14433 | Y16: 0.14791 | Z16: 0.15145
B17: Multiplan (MULT3) | C17: Cyclicals ex-WEG & Embraer | D17: 831.74581 | E17: =D17/18807.44964165 -> 0.044224274 | F17: 2912.3636 | G17: 2769.5455 | H17: 2903.2727 | I17: 2158.1667 | J17: 2094.1667 | K17: 2243.9091 | L17: 2057.0909 | M17: 1940.2727 | N17: 2066.7273 | O17: 1249.909 | P17: 1304.182 | Q17: 1490 | R17: -358.25 | S17: -317.50125 | T17: -320.6875 | U17: 0 | V17: 0 | W17: 0 | X17: 0.18429 | Y17: 0.1665 | Z17: 0.18486
B18: Smart Fit (SMFT3) | C18: Cyclicals ex-WEG & Embraer | D18: 831.72715 | E18: =D18/13764.34071496 -> 0.060426225 | F18: 8963.3636 | G18: 10786.364 | H18: 12481.2 | I18: 2917.8 | J18: 3546.7 | K18: 4144.4444 | L18: 1845.6364 | M18: 2303 | N18: 2748 | O18: 945.636 | P18: 1245.455 | Q18: 1540 | R18: -2710.5 | S18: -2494.5 | T18: -2363.75 | U18: 0 | V18: 0 | W18: 0 | X18: 0.14806 | Y18: 0.17758 | Z18: 0.20321
B19: Cyrela (CYRE3) | C19: Cyclicals ex-WEG & Embraer | D19: 614.64098 | E19: =D19/14967.384 -> 0.041065358 | F19: 10125 | G19: 11799.8 | H19: 12516.778 | I19: 2474.125 | J19: 2797.3333 | K19: 3031.625 | L19: 2099.3333 | M19: 2576.1111 | N19: 2830.5556 | O19: 1949.111 | P19: 2310.5 | Q19: 2554.111 | R19: -162 | S19: -229 | T19: -235 | U19: 0 | V19: 0 | W19: 0 | X19: 0.18201 | Y19: 0.18853 | Z19: 0.18666
B20: Iguatemi (IGTI11) | C20: Cyclicals ex-WEG & Embraer | D20: 488.82398 | E20: =D20/9053.50892735 -> 0.053992765 | F20: 1645.5 | G20: 1822.75 | H20: 2047.5 | I20: 1242.5 | J20: 1361.5 | K20: 1524 | L20: 1048.3333 | M20: 1132.3333 | N20: 1345 | O20: 576.857 | P20: 672.143 | Q20: 778.6 | R20: -512.5 | S20: -343 | T20: -255 | U20: 0 | V20: 0 | W20: 0 | X20: 0.11978 | Y20: 0.126 | Z20: 0.1411
B21: Cogna (COGN3) | C21: Cyclicals ex-WEG & Embraer | D21: 373.09241 | E21: =D21/6048.30181483 -> 0.061685481 | F21: 7984.7273 | G21: 8404 | H21: 8772.2222 | I21: 2465.1818 | J21: 2553.5455 | K21: 2652.3333 | L21: 1460.6 | M21: 1530.4 | N21: 1659 | O21: 724.909 | P21: 877.182 | Q21: 978.778 | R21: -580 | S21: -597.16667 | T21: -580.4 | U21: 0 | V21: 0 | W21: 0 | X21: 0.05468 | Y21: 0.0553 | Z21: 0.10336
B22: Cury (CURY3) | C22: Cyclicals ex-WEG & Embraer | D22: 351.67065 | E22: =D22/9940.69585838 -> 0.035376865 | F22: 6833.8182 | G22: 7942.0909 | H22: 8683.8 | I22: 1644.2 | J22: 1920.1 | K22: 2066.5556 | L22: 1626.1 | M22: 1893.3 | N22: 2037.2 | O22: 1230.182 | P22: 1453.909 | Q22: 1584.5 | R22: -54.666667 | S22: -89.466667 | T22: -94.4 | U22: 0 | V22: 0 | W22: 0 | X22: 0.79447 | Y22: 0.76168 | Z22: 0.71634
B23: Direcional (DIRR3) | C23: Cyclicals ex-WEG & Embraer | D23: 268.23831 | E23: =D23/6063.825 -> 0.044235827 | F23: 5291.1818 | G23: 6236.3636 | H23: 6622.8 | I23: 1398.9 | J23: 1624.6 | K23: 1709.3333 | L23: 1275.3 | M23: 1497.1 | N23: 1584.9 | O23: 919.818 | P23: 1113.364 | Q23: 1200 | R23: -115.8 | S23: -122.5 | T23: -128.75 | U23: 0 | V23: 0 | W23: 0 | X23: 0.40789 | Y23: 0.39338 | Z23: 0.36248
B24: Magazine Luiza (MGLU3) | C24: Cyclicals ex-WEG & Embraer | D24: 262.49334 | E24: =D24/7911.148704 -> 0.033180181 | F24: 39297.833 | G24: 41804.846 | H24: 43576.545 | I24: 2989.7778 | J24: 3277.3333 | K24: 3455 | L24: 1760.5 | M24: 1983.75 | N24: 2157.3333 | O24: 151.825 | P24: 437.5 | Q24: 651.273 | R24: -914.85714 | S24: -975 | T24: -1019.4286 | U24: 0 | V24: 0 | W24: 0 | X24: 0.00926 | Y24: 0.03424 | Z24: 0.04905
B25: Tenda (TEND3) | C25: Cyclicals ex-WEG & Embraer | D25: 251.0846 | E25: =D25/3709.21487952 -> 0.067692114 | F25: 5199.75 | G25: 6120.75 | H25: 6827 | I25: 910.14286 | J25: 1107.5714 | K25: 1252.1667 | L25: 835.42857 | M25: 1018.2857 | N25: 1164.1429 | O25: 665.125 | P25: 839 | Q25: 978.857 | R25: -96.4 | S25: -93.066667 | T25: -104.26667 | U25: 0 | V25: 0 | W25: 0 | X25: 0.45619 | Y25: 0.40308 | Z25: 0.38014
B26: Marcopolo (POMO4) | C26: Cyclicals ex-WEG & Embraer | D26: 246.63344 | E26: =D26/5792.71565000999 -> 0.042576479 | F26: 8959.125 | G26: 9651.75 | H26: 10269.875 | I26: 1432.875 | J26: 1585.625 | K26: 1695.625 | L26: 1239.125 | M26: 1366.625 | N26: 1460 | O26: 1081.5 | P26: 1122.5 | Q26: 1198.625 | R26: -307.85714 | S26: -327.57143 | T26: -352.42857 | U26: 0 | V26: 0 | W26: 0 | X26: 0.26397 | Y26: 0.24368 | Z26: 0.23972
B27: Vivara (VIVA3) | C27: Cyclicals ex-WEG & Embraer | D27: 246.62879 | E27: =D27/6632.43335351999 -> 0.037185264 | F27: 3356.4286 | G27: 3771.1429 | H27: 4169.2308 | I27: 904.07692 | J27: 1020.3846 | K27: 1169.5 | L27: 788.07692 | M27: 895.07692 | N27: 1003.8462 | O27: 623.143 | P27: 735.143 | Q27: 843.923 | R27: -128.3 | S27: -142 | T27: -141.9 | U27: 0 | V27: 0 | W27: 0 | X27: 0.19397 | Y27: 0.19895 | Z27: 0.20181
B28: YDUQS (YDUQ3) | C28: Cyclicals ex-WEG & Embraer | D28: 219.64421 | E28: =D28/3626.19549873 -> 0.06057153 | F28: 5699.0769 | G28: 5999.2308 | H28: 6283.5 | I28: 1850.4615 | J28: 1932.1538 | K28: 2008.1667 | L28: 1008.4 | M28: 1148.8182 | N28: 1231.8182 | O28: 354.222 | P28: 515.273 | Q28: 637.364 | R28: -427.4 | S28: -429.8 | T28: -441.8 | U28: 0 | V28: 0 | W28: 0 | X28: 0.10645 | Y28: 0.14985 | Z28: 0.16766
B29: Vamos (VAMO3) | C29: Cyclicals ex-WEG & Embraer | D29: 218.86239 | E29: =D29/7404.27080189999 -> 0.029558939 | F29: 6636.1 | G29: 7336.2 | H29: 7785.1111 | I29: 3936.9 | J29: 4261.8 | K29: 4599.5556 | L29: 2732.7778 | M29: 2898.1111 | N29: 3023.2222 | O29: 473.2 | P29: 731.9 | Q29: 1081.333 | R29: -2967.8333 | S29: -3416.5 | T29: -3910.8333 | U29: =-R29*FleetRatio -> 2158.9412 | V29: =-S29*FleetRatio -> 2485.3224 | W29: =-T29*FleetRatio -> 2844.9236 | X29: 0.15723 | Y29: 0.2093 | Z29: 0.26423
B30: Azzas 2154 (AZZA3) | C30: Cyclicals ex-WEG & Embraer | D30: 208.33727 | E30: =D30/4846.31591110999 -> 0.042988793 | F30: 11464 | G30: 12169.778 | H30: 12871.625 | I30: 1614.4286 | J30: 1817.2857 | K30: 1959.5 | L30: 1049.3333 | M30: 1218.375 | N30: 1417.375 | O30: 399.1 | P30: 575.9 | Q30: 710.556 | R30: -375.5 | S30: -375 | T30: -407 | U30: 0 | V30: 0 | W30: 0 | X30: 0.05738 | Y30: 0.0753 | Z30: 0.09116
B31: C&A Modas (CEAB3) | C31: Cyclicals ex-WEG & Embraer | D31: 180.49236 | E31: =D31/3868.4756034 -> 0.046657232 | F31: 8396.75 | G31: 9055.75 | H31: 9749.5 | I31: 1651.2222 | J31: 1699.5455 | K31: 1842.0909 | L31: 955.1 | M31: 1021.7 | N31: 1110.6 | O31: 517.636 | P31: 547.6 | Q31: 586.1 | R31: -632.14286 | S31: -701.25 | T31: -751.125 | U31: 0 | V31: 0 | W31: 0 | X31: 0.13163 | Y31: 0.12885 | Z31: 0.12423
B32: MRV (MRVE3) | C32: Cyclicals ex-WEG & Embraer | D32: 167.88482 | E32: =D32/3574.00714585 -> 0.046973835 | F32: 11757.5 | G32: 11928.286 | H32: 12097.714 | I32: 1198.8571 | J32: 2156.3333 | K32: 2112.3333 | L32: 819.33333 | M32: 1769 | N32: 1803.5 | O32: -394.6 | P32: 649.286 | Q32: 870.286 | R32: -146.7 | S32: -229.55 | T32: -270.05 | U32: 0 | V32: 0 | W32: 0 | X32: -0.0802 | Y32: 0.1406 | Z32: 0.14758
B35: 2. In index points (= R$ mn x points / market cap); book value = net income / ROE
B36: Member | C36: Sub-box | D36: Index points | E36: Points / market cap | F36: Sales 2026 | G36: Sales 2027 | H36: Sales 2028 | I36: EBITDA 2026 | J36: EBITDA 2027 | K36: EBITDA 2028 | L36: EBIT 2026 | M36: EBIT 2027 | N36: EBIT 2028 | O36: Net income 2026 | P36: Net income 2027 | Q36: Net income 2028 | R36: Capex 2026 | S36: Capex 2027 | T36: Capex 2028 | U36: Fleet sales 2026 | V36: Fleet sales 2027 | W36: Fleet sales 2028 | X36: Book value 2026 | Y36: Book value 2027 | Z36: Book value 2028
B37: Weg (WEGE3) | C37: =C9 -> WEG & Embraer | D37: =D9 -> 5386.7222 | F37: =F9*$E$9 -> 1044.1497 | G37: =G9*$E$9 -> 1214.5479 | H37: =H9*$E$9 -> 1412.9917 | I37: =I9*$E$9 -> 229.55187 | J37: =J9*$E$9 -> 271.65009 | K37: =K9*$E$9 -> 321.99456 | L37: =L9*$E$9 -> 202.37084 | M37: =M9*$E$9 -> 240.00508 | ... W37: =W9*$E$9 -> 0 | X37: =IF(ISNUMBER(X9),O9*$E$9/X9,0) -> 471.78827 | Y37: =IF(ISNUMBER(Y9),P9*$E$9/Y9,0) -> 594.68888 | Z37: =IF(ISNUMBER(Z9),Q9*$E$9/Z9,0) -> 711.62587
B38: Embraer (EMBJ3) | C38: =C10 -> WEG & Embraer | D38: =D10 -> 4817.8329 | F38: =F10*$E$10 -> 3235.2258 | G38: =G10*$E$10 -> 3619.4235 | H38: =H10*$E$10 -> 4013.5111 | I38: =I10*$E$10 -> 422.5933 | J38: =J10*$E$10 -> 480.3827 | K38: =K10*$E$10 -> 546.3195 | L38: =L10*$E$10 -> 330.47135 | M38: =M10*$E$10 -> 385.97272 | ... W38: =W10*$E$10 -> 0 | X38: =IF(ISNUMBER(X10),O10*$E$10/X10,0) -> 1363.2296 | Y38: =IF(ISNUMBER(Y10),P10*$E$10/Y10,0) -> 1540.1203 | Z38: =IF(ISNUMBER(Z10),Q10*$E$10/Z10,0) -> 1779.8392
B39: Localiza (RENT3) | C39: =C11 -> Cyclicals ex-WEG & Embraer | D39: =D11 -> 3528.9277 | F39: =F11*$E$11 -> 3100.3145 | G39: =G11*$E$11 -> 3315.6983 | H39: =H11*$E$11 -> 3534.6723 | I39: =I11*$E$11 -> 980.41617 | J39: =J11*$E$11 -> 1055.9043 | K39: =K11*$E$11 -> 1141.5227 | L39: =L11*$E$11 -> 627.77134 | M39: =M11*$E$11 -> 679.35254 | ... W39: =W11*$E$11 -> 1194.2107 | X39: =IF(ISNUMBER(X11),O11*$E$11/X11,0) -> 1690.9252 | Y39: =IF(ISNUMBER(Y11),P11*$E$11/Y11,0) -> 1813.8756 | Z39: =IF(ISNUMBER(Z11),Q11*$E$11/Z11,0) -> 1934.799
B40: Rumo (RAIL3) | C40: =C12 -> Cyclicals ex-WEG & Embraer | D40: =D12 -> 1897.6387 | F40: =F12*$E$12 -> 815.15417 | G40: =G12*$E$12 -> 862.71053 | H40: =H12*$E$12 -> 905.41637 | I40: =I12*$E$12 -> 448.95403 | J40: =J12*$E$12 -> 495.9287 | K40: =K12*$E$12 -> 524.21535 | L40: =L12*$E$12 -> 320.05736 | M40: =M12*$E$12 -> 365.0014 | ... W40: =W12*$E$12 -> 0 | X40: =IF(ISNUMBER(X12),O12*$E$12/X12,0) -> 835.91293 | Y40: =IF(ISNUMBER(Y12),P12*$E$12/Y12,0) -> 931.14209 | Z40: =IF(ISNUMBER(Z12),Q12*$E$12/Z12,0) -> 1079.785
B41: Motiva (MOTV3) | C41: =C13 -> Cyclicals ex-WEG & Embraer | D41: =D13 -> 1406.9784 | F41: =F13*$E$13 -> 641.12954 | G41: =G13*$E$13 -> 679.0668 | H41: =H13*$E$13 -> 749.02484 | I41: =I13*$E$13 -> 362.47852 | J41: =J13*$E$13 -> 392.35362 | K41: =K13*$E$13 -> 445.7955 | L41: =L13*$E$13 -> 281.15274 | M41: =M13*$E$13 -> 298.35521 | ... W41: =W13*$E$13 -> 0 | X41: =IF(ISNUMBER(X13),O13*$E$13/X13,0) -> 661.22699 | Y41: =IF(ISNUMBER(Y13),P13*$E$13/Y13,0) -> 688.04805 | Z41: =IF(ISNUMBER(Z13),Q13*$E$13/Z13,0) -> 706.83916
B42: TOTVS (TOTS3) | C42: =C14 -> Cyclicals ex-WEG & Embraer | D42: =D14 -> 1378.3571 | F42: =F14*$E$14 -> 448.90725 | G42: =G14*$E$14 -> 517.95554 | H42: =H14*$E$14 -> 584.69937 | I42: =I14*$E$14 -> 117.07784 | J42: =J14*$E$14 -> 137.84953 | K42: =K14*$E$14 -> 161.63057 | L42: =L14*$E$14 -> 86.976061 | M42: =M14*$E$14 -> 110.05455 | ... W42: =W14*$E$14 -> 0 | X42: =IF(ISNUMBER(X14),O14*$E$14/X14,0) -> 299.88478 | Y42: =IF(ISNUMBER(Y14),P14*$E$14/Y14,0) -> 385.71913 | Z42: =IF(ISNUMBER(Z14),Q14*$E$14/Z14,0) -> 416.41067
B43: Allos (ALOS3) | C43: =C15 -> Cyclicals ex-WEG & Embraer | D43: =D15 -> 1141.4957 | F43: =F15*$E$15 -> 196.76264 | G43: =G15*$E$15 -> 207.15142 | H43: =H15*$E$15 -> 216.54649 | I43: =I15*$E$15 -> 145.8141 | J43: =J15*$E$15 -> 154.03972 | K43: =K15*$E$15 -> 161.178 | L43: =L15*$E$15 -> 106.38438 | M43: =M15*$E$15 -> 115.2867 | ... W43: =W15*$E$15 -> 0 | X43: =IF(ISNUMBER(X15),O15*$E$15/X15,0) -> 828.11375 | Y43: =IF(ISNUMBER(Y15),P15*$E$15/Y15,0) -> 799.08518 | Z43: =IF(ISNUMBER(Z15),Q15*$E$15/Z15,0) -> 754.75269
B44: Lojas Renner (LREN3) | C44: =C16 -> Cyclicals ex-WEG & Embraer | D44: =D16 -> 951.12139 | F44: =F16*$E$16 -> 1171.1527 | G44: =G16*$E$16 -> 1250.8114 | H44: =H16*$E$16 -> 1354.4079 | I44: =I16*$E$16 -> 229.39716 | J44: =J16*$E$16 -> 246.60212 | K44: =K16*$E$16 -> 267.87972 | L44: =L16*$E$16 -> 137.54591 | M44: =M16*$E$16 -> 150.26793 | ... W44: =W16*$E$16 -> 0 | X44: =IF(ISNUMBER(X16),O16*$E$16/X16,0) -> 756.95149 | Y44: =IF(ISNUMBER(Y16),P16*$E$16/Y16,0) -> 782.28615 | Z44: =IF(ISNUMBER(Z16),Q16*$E$16/Z16,0) -> 834.66199
B45: Multiplan (MULT3) | C45: =C17 -> Cyclicals ex-WEG & Embraer | D45: =D17 -> 831.74581 | F45: =F17*$E$17 -> 128.79717 | G45: =G17*$E$17 -> 122.48114 | H45: =H17*$E$17 -> 128.39513 | I45: =I17*$E$17 -> 95.443354 | J45: =J17*$E$17 -> 92.613001 | K45: =K17*$E$17 -> 99.235251 | L45: =L17*$E$17 -> 90.973352 | M45: =M17*$E$17 -> 85.807153 | ... W45: =W17*$E$17 -> 0 | X45: =IF(ISNUMBER(X17),O17*$E$17/X17,0) -> 299.94204 | Y45: =IF(ISNUMBER(Y17),P17*$E$17/Y17,0) -> 346.40542 | Z45: =IF(ISNUMBER(Z17),Q17*$E$17/Z17,0) -> 356.45444
B46: Smart Fit (SMFT3) | C46: =C18 -> Cyclicals ex-WEG & Embraer | D46: =D18 -> 831.72715 | F46: =F18*$E$18 -> 541.62223 | G46: =G18*$E$18 -> 651.77924 | H46: =H18*$E$18 -> 754.1918 | I46: =I18*$E$18 -> 176.31164 | J46: =J18*$E$18 -> 214.31369 | K46: =K18*$E$18 -> 250.43313 | L46: =L18*$E$18 -> 111.52484 | M46: =M18*$E$18 -> 139.1616 | ... W46: =W18*$E$18 -> 0 | X46: =IF(ISNUMBER(X18),O18*$E$18/X18,0) -> 385.93282 | Y46: =IF(ISNUMBER(Y18),P18*$E$18/Y18,0) -> 423.79854 | Z46: =IF(ISNUMBER(Z18),Q18*$E$18/Z18,0) -> 457.93212
B47: Cyrela (CYRE3) | C47: =C19 -> Cyclicals ex-WEG & Embraer | D47: =D19 -> 614.64098 | F47: =F19*$E$19 -> 415.78675 | G47: =G19*$E$19 -> 484.56301 | H47: =H19*$E$19 -> 514.00596 | I47: =I19*$E$19 -> 101.60083 | J47: =J19*$E$19 -> 114.87349 | K47: =K19*$E$19 -> 124.49476 | L47: =L19*$E$19 -> 86.209874 | M47: =M19*$E$19 -> 105.78892 | ... W47: =W19*$E$19 -> 0 | X47: =IF(ISNUMBER(X19),O19*$E$19/X19,0) -> 439.76122 | Y47: =IF(ISNUMBER(Y19),P19*$E$19/Y19,0) -> 503.27008 | Z47: =IF(ISNUMBER(Z19),Q19*$E$19/Z19,0) -> 561.90658
B48: Iguatemi (IGTI11) | C48: =C20 -> Cyclicals ex-WEG & Embraer | D48: =D20 -> 488.82398 | F48: =F20*$E$20 -> 88.845094 | G48: =G20*$E$20 -> 98.415312 | H48: =H20*$E$20 -> 110.55019 | I48: =I20*$E$20 -> 67.08601 | J48: =J20*$E$20 -> 73.511149 | K48: =K20*$E$20 -> 82.284973 | L48: =L20*$E$20 -> 56.602415 | M48: =M20*$E$20 -> 61.137807 | ... W48: =W20*$E$20 -> 0 | X48: =IF(ISNUMBER(X20),O20*$E$20/X20,0) -> 260.02759 | Y48: =IF(ISNUMBER(Y20),P20*$E$20/Y20,0) -> 288.02269 | Z48: =IF(ISNUMBER(Z20),Q20*$E$20/Z20,0) -> 297.93598
B49: Cogna (COGN3) | C49: =C21 -> Cyclicals ex-WEG & Embraer | D49: =D21 -> 373.09241 | F49: =F21*$E$21 -> 492.54174 | G49: =G21*$E$21 -> 518.40478 | H49: =H21*$E$21 -> 541.11875 | I49: =I21*$E$21 -> 152.06593 | J49: =J21*$E$21 -> 157.51668 | K49: =K21*$E$21 -> 163.61046 | L49: =L21*$E$21 -> 90.097813 | M49: =M21*$E$21 -> 94.40346 | ... W49: =W21*$E$21 -> 0 | X49: =IF(ISNUMBER(X21),O21*$E$21/X21,0) -> 817.78274 | Y49: =IF(ISNUMBER(Y21),P21*$E$21/Y21,0) -> 978.47004 | Z49: =IF(ISNUMBER(Z21),Q21*$E$21/Z21,0) -> 584.13691
B50: Cury (CURY3) | C50: =C22 -> Cyclicals ex-WEG & Embraer | D50: =D22 -> 351.67065 | F50: =F22*$E$22 -> 241.75906 | G50: =G22*$E$22 -> 280.96627 | H50: =H22*$E$22 -> 307.20562 | I50: =I22*$E$22 -> 58.166641 | J50: =J22*$E$22 -> 67.927118 | K50: =K22*$E$22 -> 73.108256 | L50: =L22*$E$22 -> 57.526319 | M50: =M22*$E$22 -> 66.979018 | ... W50: =W22*$E$22 -> 0 | X50: =IF(ISNUMBER(X22),O22*$E$22/X22,0) -> 54.778635 | Y50: =IF(ISNUMBER(Y22),P22*$E$22/Y22,0) -> 67.528019 | Z50: =IF(ISNUMBER(Z22),Q22*$E$22/Z22,0) -> 78.251447
B51: Direcional (DIRR3) | C51: =C23 -> Cyclicals ex-WEG & Embraer | D51: =D23 -> 268.23831 | F51: =F23*$E$23 -> 234.0598 | G51: =G23*$E$23 -> 275.8707 | H51: =H23*$E$23 -> 292.96503 | I51: =I23*$E$23 -> 61.881498 | J51: =J23*$E$23 -> 71.865524 | K51: =K23*$E$23 -> 75.613773 | L51: =L23*$E$23 -> 56.41395 | M51: =M23*$E$23 -> 66.225456 | ... W51: =W23*$E$23 -> 0 | X51: =IF(ISNUMBER(X23),O23*$E$23/X23,0) -> 99.754615 | Y51: =IF(ISNUMBER(Y23),P23*$E$23/Y23,0) -> 125.19848 | Z51: =IF(ISNUMBER(Z23),Q23*$E$23/Z23,0) -> 146.44392
B52: Magazine Luiza (MGLU3) | C52: =C24 -> Cyclicals ex-WEG & Embraer | D52: =D24 -> 262.49334 | F52: =F24*$E$24 -> 1303.9092 | G52: =G24*$E$24 -> 1387.0923 | H52: =H24*$E$24 -> 1445.8776 | I52: =I24*$E$24 -> 99.201367 | J52: =J24*$E$24 -> 108.74251 | K52: =K24*$E$24 -> 114.63752 | L52: =L24*$E$24 -> 58.413708 | M52: =M24*$E$24 -> 65.821183 | ... W52: =W24*$E$24 -> 0 | X52: =IF(ISNUMBER(X24),O24*$E$24/X24,0) -> 544.01522 | Y52: =IF(ISNUMBER(Y24),P24*$E$24/Y24,0) -> 423.95821 | Z52: =IF(ISNUMBER(Z24),Q24*$E$24/Z24,0) -> 440.55771
B53: Tenda (TEND3) | C53: =C25 -> Cyclicals ex-WEG & Embraer | D53: =D25 -> 251.0846 | F53: =F25*$E$25 -> 351.98207 | G53: =G25*$E$25 -> 414.32651 | H53: =H25*$E$25 -> 462.13406 | I53: =I25*$E$25 -> 61.609494 | J53: =J25*$E$25 -> 74.973851 | K53: =K25*$E$25 -> 84.761809 | L53: =L25*$E$25 -> 56.551926 | M53: =M25*$E$25 -> 68.929913 | ... W53: =W25*$E$25 -> 0 | X53: =IF(ISNUMBER(X25),O25*$E$25/X25,0) -> 98.695099 | Y53: =IF(ISNUMBER(Y25),P25*$E$25/Y25,0) -> 140.89928 | Z53: =IF(ISNUMBER(Z25),Q25*$E$25/Z25,0) -> 174.30657
B54: Marcopolo (POMO4) | C54: =C26 -> Cyclicals ex-WEG & Embraer | D54: =D26 -> 246.63344 | F54: =F26*$E$26 -> 381.448 | G54: =G26*$E$26 -> 410.93753 | H54: =H26*$E$26 -> 437.25512 | I54: =I26*$E$26 -> 61.006773 | J54: =J26*$E$26 -> 67.51033 | K54: =K26*$E$26 -> 72.193743 | L54: =L26*$E$26 -> 52.75758 | M54: =M26*$E$26 -> 58.186081 | ... W54: =W26*$E$26 -> 0 | X54: =IF(ISNUMBER(X26),O26*$E$26/X26,0) -> 174.43824 | Y54: =IF(ISNUMBER(Y26),P26*$E$26/Y26,0) -> 196.12647 | Z54: =IF(ISNUMBER(Z26),Q26*$E$26/Z26,0) -> 212.88684
B55: Vivara (VIVA3) | C55: =C27 -> Cyclicals ex-WEG & Embraer | D55: =D27 -> 246.62879 | F55: =F27*$E$27 -> 124.80968 | G55: =G27*$E$27 -> 140.23094 | H55: =H27*$E$27 -> 155.03395 | I55: =I27*$E$27 -> 33.618339 | J55: =J27*$E$27 -> 37.943271 | K55: =K27*$E$27 -> 43.488166 | L55: =L27*$E$27 -> 29.304848 | M55: =M27*$E$27 -> 33.283672 | ... W55: =W27*$E$27 -> 0 | X55: =IF(ISNUMBER(X27),O27*$E$27/X27,0) -> 119.46042 | Y55: =IF(ISNUMBER(Y27),P27*$E$27/Y27,0) -> 137.4038 | Z55: =IF(ISNUMBER(Z27),Q27*$E$27/Z27,0) -> 155.50022
B56: YDUQS (YDUQ3) | C56: =C28 -> Cyclicals ex-WEG & Embraer | D56: =D28 -> 219.64421 | F56: =F28*$E$28 -> 345.20181 | G56: =G28*$E$28 -> 363.38258 | H56: =H28*$E$28 -> 380.60121 | I56: =I28*$E$28 -> 112.08529 | J56: =J28*$E$28 -> 117.03351 | K56: =K28*$E$28 -> 121.63773 | L56: =L28*$E$28 -> 61.08033 | M56: =M28*$E$28 -> 69.585675 | ... W56: =W28*$E$28 -> 0 | X56: =IF(ISNUMBER(X28),O28*$E$28/X28,0) -> 201.55724 | Y56: =IF(ISNUMBER(Y28),P28*$E$28/Y28,0) -> 208.28077 | Z56: =IF(ISNUMBER(Z28),Q28*$E$28/Z28,0) -> 230.2643
B57: Vamos (VAMO3) | C57: =C29 -> Cyclicals ex-WEG & Embraer | D57: =D29 -> 218.86239 | F57: =F29*$E$29 -> 196.15607 | G57: =G29*$E$29 -> 216.85029 | H57: =H29*$E$29 -> 230.11962 | I57: =I29*$E$29 -> 116.37059 | J57: =J29*$E$29 -> 125.97428 | K57: =K29*$E$29 -> 135.95798 | L57: =L29*$E$29 -> 80.77801 | M57: =M29*$E$29 -> 85.665088 | ... W57: =W29*$E$29 -> 84.092923 | X57: =IF(ISNUMBER(X29),O29*$E$29/X29,0) -> 88.960693 | Y57: =IF(ISNUMBER(Y29),P29*$E$29/Y29,0) -> 103.36449 | Z57: =IF(ISNUMBER(Z29),Q29*$E$29/Z29,0) -> 120.96679
B58: Azzas 2154 (AZZA3) | C58: =C30 -> Cyclicals ex-WEG & Embraer | D58: =D30 -> 208.33727 | F58: =F30*$E$30 -> 492.82352 | G58: =G30*$E$30 -> 523.16406 | H58: =H30*$E$30 -> 553.33562 | I58: =I30*$E$30 -> 69.402336 | J58: =J30*$E$30 -> 78.12292 | K58: =K30*$E$30 -> 84.23654 | L58: =L30*$E$30 -> 45.109574 | M58: =M30*$E$30 -> 52.376471 | ... W58: =W30*$E$30 -> 0 | X58: =IF(ISNUMBER(X30),O30*$E$30/X30,0) -> 299.00361 | Y58: =IF(ISNUMBER(Y30),P30*$E$30/Y30,0) -> 328.78149 | Z58: =IF(ISNUMBER(Z30),Q30*$E$30/Z30,0) -> 335.08057
B59: C&A Modas (CEAB3) | C59: =C31 -> Cyclicals ex-WEG & Embraer | D59: =D31 -> 180.49236 | F59: =F31*$E$31 -> 391.76911 | G59: =G31*$E$31 -> 422.51623 | H59: =H31*$E$31 -> 454.88468 | I59: =I31*$E$31 -> 77.041458 | J59: =J31*$E$31 -> 79.296087 | K59: =K31*$E$31 -> 85.946863 | L59: =L31*$E$31 -> 44.562322 | M59: =M31*$E$31 -> 47.669694 | ... W59: =W31*$E$31 -> 0 | X59: =IF(ISNUMBER(X31),O31*$E$31/X31,0) -> 183.47993 | Y59: =IF(ISNUMBER(Y31),P31*$E$31/Y31,0) -> 198.28871 | Z59: =IF(ISNUMBER(Z31),Q31*$E$31/Z31,0) -> 220.12238
B60: MRV (MRVE3) | C60: =C32 -> Cyclicals ex-WEG & Embraer | D60: =D32 -> 167.88482 | F60: =F32*$E$32 -> 552.29487 | G60: =G32*$E$32 -> 560.31733 | H60: =H32*$E$32 -> 568.27604 | I60: =I32*$E$32 -> 56.314918 | J60: =J32*$E$32 -> 101.29125 | K60: =K32*$E$32 -> 99.224398 | L60: =L32*$E$32 -> 38.487229 | M60: =M32*$E$32 -> 83.096715 | ... W60: =W32*$E$32 -> 0 | X60: =IF(ISNUMBER(X32),O32*$E$32/X32,0) -> 231.12064 | Y60: =IF(ISNUMBER(Y32),P32*$E$32/Y32,0) -> 216.92357 | Z60: =IF(ISNUMBER(Z32),Q32*$E$32/Z32,0) -> 277.00685
B61: WEG & Embraer | D61: =SUMIFS(D37:D60,$C$37:$C$60,"WEG & Embraer") -> 10204.555 | F61: =SUMIFS(F37:F60,$C$37:$C$60,"WEG & Embraer") -> 4279.3755 | G61: =SUMIFS(G37:G60,$C$37:$C$60,"WEG & Embraer") -> 4833.9715 | H61: =SUMIFS(H37:H60,$C$37:$C$60,"WEG & Embraer") -> 5426.5028 | I61: =SUMIFS(I37:I60,$C$37:$C$60,"WEG & Embraer") -> 652.14517 | J61: =SUMIFS(J37:J60,$C$37:$C$60,"WEG & Embraer") -> 752.03278 | K61: =SUMIFS(K37:K60,$C$37:$C$60,"WEG & Embraer") -> 868.31407 | L61: =SUMIFS(L37:L60,$C$37:$C$60,"WEG & Embraer") -> 532.84218 | M61: =SUMIFS(M37:M60,$C$37:$C$60,"WEG & Embraer") -> 625.9778 | ... Z61: =SUMIFS(Z37:Z60,$C$37:$C$60,"WEG & Embraer") -> 2491.4651
B62: Cyclicals ex-WEG & Embraer | D62: =SUMIFS(D37:D60,$C$37:$C$60,"Cyclicals ex-WEG & Embraer") -> 16066.52 | F62: =SUMIFS(F37:F60,$C$37:$C$60,"Cyclicals ex-WEG & Embraer") -> 12657.227 | G62: =SUMIFS(G37:G60,$C$37:$C$60,"Cyclicals ex-WEG & Embraer") -> 13704.692 | H62: =SUMIFS(H37:H60,$C$37:$C$60,"Cyclicals ex-WEG & Embraer") -> 14680.718 | I62: =SUMIFS(I37:I60,$C$37:$C$60,"Cyclicals ex-WEG & Embraer") -> 3683.3443 | J62: =SUMIFS(J37:J60,$C$37:$C$60,"Cyclicals ex-WEG & Embraer") -> 4066.1867 | K62: =SUMIFS(K37:K60,$C$37:$C$60,"Cyclicals ex-WEG & Embraer") -> 4413.0871 | L62: =SUMIFS(L37:L60,$C$37:$C$60,"Cyclicals ex-WEG & Embraer") -> 2576.2819 | M62: =SUMIFS(M37:M60,$C$37:$C$60,"Cyclicals ex-WEG & Embraer") -> 2902.4362 | ... Z62: =SUMIFS(Z37:Z60,$C$37:$C$60,"Cyclicals ex-WEG & Embraer") -> 10377.002
B63: Cyclicals | D63: =SUM(D37:D60) -> 26271.075 | F63: =SUM(F37:F60) -> 16936.602 | G63: =SUM(G37:G60) -> 18538.664 | H63: =SUM(H37:H60) -> 20107.22 | I63: =SUM(I37:I60) -> 4335.4894 | J63: =SUM(J37:J60) -> 4818.2195 | K63: =SUM(K37:K60) -> 5281.4012 | L63: =SUM(L37:L60) -> 3109.1241 | M63: =SUM(M37:M60) -> 3528.414 | ... Z63: =SUM(Z37:Z60) -> 12868.467
B64: Check: net income vs. Box Shares!M9:O9 (Cyclicals) of the main model | O64: =O63-1607.0455 -> -4.080541e-06 | P64: =P63-1944.9107 -> -3.6729367e-05 | Q64: =Q63-2304.3006 -> 4.1905272e-05
B66: Members without a BEST_ROE get book value 0: the sub-box ROE uses the members with an ROE (box ROE = sum of net income with ROE / sum of book value; see DCF Cyclicals). Leases (IFRS 16) and concession fees are not in the consensus: pending the Bloomberg pull.

Sheet Analyst Models
B1: Cyclicals - how the XP Cyclicals analysts value their companies (memo)
B2: Files in inputs/analyst_models/Cyclicals (DCF & Sensitivity / Valuation sheets), read on Oct-8-2026.
B3: Legend: | C3: input | D3: assumption | E3: formula
B5: Model (weight in the box) | C5: Currency / method | D5: Explicit to | E5: Perpetuity g | F5: Ke (beta) | G5: WACC | H5: Cash flow | I5: Note
B6: WEG (20.5%) | C6: BRL; FCFF - net debt | D6: 2035 | E6: 7.6% (about 3.4% real) | F6: 11.4% (0.8) | G6: 11.2% | H6: NOPAT + D&A - capex +/- NWC | I6: Permanent real growth
B7: Embraer (18.3%) | C7: USD; FCFF - net debt | D7: ~2035 | E7: 2.4% (real 0%) | F7: 10.6% (1.0) | G7: 9.8% | H7: NOPAT + D&A - capex +/- NWC | I7: Exporter
B8: Localiza (13.4%) | C8: BRL; FCFF / FCFE | D8: 2035 | E8: 6.1% (about 2% real, GDP-linked) | F8: 15.2% (0.95) | G8: 12.3% | H8: NOPAT + D&A - capex + BV of cars sold +/- NWC | I8: Fleet net of used-car sales (resale at 79% of purchase price)
B9: Rumo (7.2%) | C9: BRL; FCFE to concession end | D9: ~2070 | E9: 4.0% (real 0%) | F9: 15.3% (1.0) | G9: 11.7% | H9: FCFF - concession fees + net funding | I9: Lucas do Rio Verde project apart
B10: Motiva (5.4%) | C10: BRL; sum of concessions | D10: Each contract | E10: 0% (finite lives) | F10: 14.7% (0.92) | G10: 10.8% | H10: FCFF by concession | I10: No perpetuity
B11: Totvs (5.2%) | C11: BRL; FCFE | D11: 2035 | E11: Exit multiple on 2035 FCFE | F11: 14.4% (0.8) | G11: - | H11: Operating cash flow - capex - lease principal | I11: Ke without the 0.85
B12: Lojas Renner (3.6%) | C12: BRL; FCFF | D12: ~2035 | E12: 4.0% (real 0%) | F12: 14.1% (0.95) | G12: 13.4% | H12: EBIT - taxes + D&A - capex +/- NWC | I12: USD + country-risk Ke
B13: Cyrela (2.3%) | C13: BRL; FCFF | D13: - | E13: 4.5% (real 0%) | F13: 20.0% (1.46) | G13: 17.5% | H13: NOPAT + D&A - capex +/- NWC | I13: ERP 7.7%
