Workbook
Name BetaAn: 'Model Parameters'!$H$13
Name ERPAn: 'Model Parameters'!$G$13
Name g_: 'DDM Financials'!$C$13
Name gAn: 'DDM Financials'!$C$11

Sheet DDM Financials
B1: Financials - DDM with the analysts' logic and the consensus (end-2027)
B2: Dividends 2028-37 + Gordon perpetuity on the 2037 dividend, as the XP Financials models; numbers from the Bloomberg consensus member by member (Members DDM). Ke: the house rate by default.
B3: Legend: | C3: input | D3: assumption | E3: formula
B5: 1. Assumptions
B6: Item | C6: Value | P6: Source / note
B7: Financials, index points today | C7: 60927.304 | P7: Members' weight x Ibovespa close of Oct-5-2026 (Box Shares!C7 of the main model).
B8: Perpetuity growth, house (g) | C8: 0.047 | P8: House DCF (DCF Ibov 2026_Out.xlsx, Target!B54).
B9: Long-term IPCA | C9: 0.04 | P9: Analysts' Macro sheet and the house (Target!B63).
B10: Long-term real GDP growth | C10: 0.02 | P10: Analysts' Macro sheet.
B11: Perpetuity growth, analysts = IPCA + real GDP | C11: =C9+C10 -> 0.06 | P11: Analysts' rule (e.g., ITUB Valuation!F23).
B12: Convention: 1 = house (real rate + beta x ERP, house g); 2 = analysts ((NTN-B + IPCA) x 0.85 + beta x ERP, analysts' g) | C12: 1 | P12: 1 keeps Ke and g coherent with the other boxes and methods (Caio's choice). 2 reproduces the analysts' convention.
B13: g used | C13: =IF(C12=1,C8,C11) -> 0.047 | P13: Target of the growth fade (Members DDM) and the perpetuity.
B14: ERP, house | C14: 0.06 | P14: House ERP (Target!B57).
B15: Beta of Financials (weekly, 5 years, computed from the local box index) | C15: 1.1490637 | P15: Box Betas of the main model.
B16: Share of the risk free kept after tax (analysts' formula) | C16: 0.85 | P16: Analysts: (NTN-B + IPCA) x 0.85.
B17: Beta and ERP of the analysts' models (weighted by index points) | C17: =BetaAn -> 1.0747443 | D17: =ERPAn -> 0.055398885 | P17: Model Parameters.
B18: Earnings beta x normalization (domestic cycle) | C18: 0.732791 | D18: 1.1868588 | P18: Box Earnings!I7 and I16 of the main model: shock of Financials = C x D x the Ibovespa ex-Commodities shock.
B19: Projection: 1 = consensus with the analysts' logic (Members DDM); 2 = the analysts' own projections | C19: 1 | P19: 2 uses the analysts' aggregate growth and payout (Analyst Models) on the box consensus of 2026-28: a memo of what their numbers give.
B21: 2. Cost of equity by scenario
B22: Item | C22: Bear | D22: Base | E22: Bull | P22: How it is calculated
B23: 5-year real rate (NTN-B) | C23: 0.085 | D23: 0.0676 | E23: 0.055 | P23: Same scenarios as the other boxes.
B24: Ke, house = real rate + beta x ERP | C24: =C23+$C$15*$C$14 -> 0.15394382 | D24: =D23+$C$15*$C$14 -> 0.13654382 | E24: =E23+$C$15*$C$14 -> 0.12394382 | P24: Box Rates of the main model (CAPM).
B25: Ke, analysts = (real rate + IPCA) x 0.85 + beta x ERP | C25: =(C23+$C$9)*$C$16+$C$17*$D$17 -> 0.16578963 | D25: =(D23+$C$9)*$C$16+$C$17*$D$17 -> 0.15099963 | E25: =(E23+$C$9)*$C$16+$C$17*$D$17 -> 0.14028963
B26: Ke used | C26: =IF($C$12=1,C24,C25) -> 0.15394382 | D26: =IF($C$12=1,D24,D25) -> 0.13654382 | E26: =IF($C$12=1,E24,E25) -> 0.12394382
B27: Ke - g | C27: =(C26-g_)*100 -> 10.694382 | D27: =(D26-g_)*100 -> 8.954382 | E27: =(E26-g_)*100 -> 7.694382
B29: 3. Box projection (index points)
B30: Line | C30: 2026 | D30: 2027 | E30: 2028 | F30: 2029 | G30: 2030 | H30: 2031 | I30: 2032 | J30: 2033 | K30: 2034 | L30: 2035 | M30: 2036 | N30: 2037 | P30: How it is calculated / source
B31: Net income: consensus + analysts' logic (sum of the members) | C31: ='Members DDM'!C147 -> 5708.1181 | D31: ='Members DDM'!D147 -> 6447.8435 | E31: ='Members DDM'!E147 -> 7167.1074 | F31: ='Members DDM'!F147 -> 7926.3944 | G31: ='Members DDM'!G147 -> 8717.4464 | H31: ='Members DDM'!H147 -> 9529.7932 | I31: ='Members DDM'!I147 -> 10350.873 | J31: ='Members DDM'!J147 -> 11166.303 | ... N31: ='Members DDM'!N147 -> 14048.28 | P31: Members DDM.
B32: Net income growth | D32: =D31/C31-1 -> 0.12959182 | E32: =E31/D31-1 -> 0.11155109 | F32: =F31/E31-1 -> 0.1059405 | G32: =G31/F31-1 -> 0.099799727 | H32: =H31/G31-1 -> 0.093186326 | I32: =I31/H31-1 -> 0.086159216 | J32: =J31/I31-1 -> 0.07877894 | K32: =K31/J31-1 -> 0.071107816 | ... N32: =N31/M31-1 -> 0.047
B33: Dividends: consensus + analysts' logic | D33: ='Members DDM'!D148 -> 4337.0465 | E33: ='Members DDM'!E148 -> 4278.3379 | F33: ='Members DDM'!F148 -> 3864.243 | G33: ='Members DDM'!G148 -> 4474.0081 | H33: ='Members DDM'!H148 -> 5166.6557 | I33: ='Members DDM'!I148 -> 5942.8373 | J33: ='Members DDM'!J148 -> 6799.7019 | K33: ='Members DDM'!K148 -> 7730.2754 | ... N33: ='Members DDM'!N148 -> 10826.064
B34: Payout | D34: =D33/D31 -> 0.6726352 | E34: =E33/E31 -> 0.59694067 | F34: =F33/F31 -> 0.48751586 | G34: =G33/G31 -> 0.51322462 | H34: =H33/H31 -> 0.54215821 | I34: =I33/I31 -> 0.57413877 | J34: =J33/J31 -> 0.60894833 | K34: =K33/K31 -> 0.64632708 | ... N34: =N33/N31 -> 0.77063271
B35: ROE = net income / average book value | D35: =D31/AVERAGE('Members DDM'!C149,'Members DDM'!D149) -> 0.20605983 | E35: =E31/AVERAGE('Members DDM'!D149,'Members DDM'!E149) -> 0.21210167 | F35: =F31/AVERAGE('Members DDM'!E149,'Members DDM'!F149) -> 0.21269566 | G35: =G31/AVERAGE('Members DDM'!F149,'Members DDM'!G149) -> 0.21046893 | H35: =H31/AVERAGE('Members DDM'!G149,'Members DDM'!H149) -> 0.20842701 | I35: =I31/AVERAGE('Members DDM'!H149,'Members DDM'!I149) -> 0.20657111 | J35: =J31/AVERAGE('Members DDM'!I149,'Members DDM'!J149) -> 0.20490377 | K35: =K31/AVERAGE('Members DDM'!J149,'Members DDM'!K149) -> 0.2034286 | ... N35: =N31/AVERAGE('Members DDM'!M149,'Members DDM'!N149) -> 0.20020666
B36: Memo: analysts' aggregate net income growth | D36: ='Analyst Models'!D90 -> 0.14209296 | E36: ='Analyst Models'!E90 -> 0.12498035 | F36: ='Analyst Models'!F90 -> 0.099600603 | G36: ='Analyst Models'!G90 -> 0.091378032 | H36: ='Analyst Models'!H90 -> 0.083168313 | I36: ='Analyst Models'!I90 -> 0.075274289 | J36: ='Analyst Models'!J90 -> 0.071817703 | K36: ='Analyst Models'!K90 -> 0.066585954 | ... N36: ='Analyst Models'!N90 -> 0.059515705 | P36: Analyst Models.
B37: Memo: analysts' aggregate payout | C37: ='Analyst Models'!C91 -> 0.53677148 | D37: ='Analyst Models'!D91 -> 0.57363999 | E37: ='Analyst Models'!E91 -> 0.5989664 | F37: ='Analyst Models'!F91 -> 0.61404933 | G37: ='Analyst Models'!G91 -> 0.63785097 | H37: ='Analyst Models'!H91 -> 0.66424496 | I37: ='Analyst Models'!I91 -> 0.6824072 | J37: ='Analyst Models'!J91 -> 0.69850557 | ... N37: ='Analyst Models'!N91 -> 0.75906369 | P37: Analyst Models.
B38: Memo: net income on the analysts' path (consensus 2026-28, then their growth) | C38: =C31 -> 5708.1181 | D38: =D31 -> 6447.8435 | E38: =E31 -> 7167.1074 | F38: =E38*(1+F36) -> 7880.9556 | G38: =F38*(1+G36) -> 8601.1019 | H38: =G38*(1+H36) -> 9316.441 | I38: =H38*(1+I36) -> 10017.729 | J38: =I38*(1+J36) -> 10737.18 | K38: =J38*(1+K36) -> 11452.125 | L38: =K38*(1+L36) -> 12191.556 | M38: =L38*(1+M36) -> 12964.063 | N38: =M38*(1+N36) -> 13735.628
B39: Memo: dividends on the analysts' path | C39: =C38*C37 -> 3063.955 | D39: =D38*D37 -> 3698.7409 | E39: =E38*E37 -> 4292.8565 | F39: =F38*F37 -> 4839.2955 | G39: =G38*G37 -> 5486.2212 | H39: =H38*H37 -> 6188.399 | I39: =I38*I37 -> 6836.1707 | J39: =J38*J37 -> 7499.9798 | ... N39: =N38*N37 -> 10426.217
B40: Dividends used (switch in row 19) | D40: =IF($C$19=1,D33,D39) -> 4337.0465 | E40: =IF($C$19=1,E33,E39) -> 4278.3379 | F40: =IF($C$19=1,F33,F39) -> 3864.243 | G40: =IF($C$19=1,G33,G39) -> 4474.0081 | H40: =IF($C$19=1,H33,H39) -> 5166.6557 | I40: =IF($C$19=1,I33,I39) -> 5942.8373 | J40: =IF($C$19=1,J33,J39) -> 6799.7019 | K40: =IF($C$19=1,K33,K39) -> 7730.2754 | ... N40: =IF($C$19=1,N33,N39) -> 10826.064
B42: 4. Valuation at the end of 2027
B43: Item | C43: Bear | D43: Base | E43: Bull | P43: How it is calculated
B44: Ke used | C44: =C26 -> 0.15394382 | D44: =D26 -> 0.13654382 | E44: =E26 -> 0.12394382
B45: Earnings shock of the Ibovespa ex-Commodities | C45: -0.2 | D45: 0 | E45: 0.2 | P45: Symmetric +/-20%, as the other boxes.
B46: Earnings shock of Financials = beta x normalization x shock | C46: =$C$18*$D$18*C45 -> -0.17394389 | D46: =$C$18*$D$18*D45 -> 0 | E46: =$C$18*$D$18*E45 -> 0.17394389 | P46: Moves the dividends of every year.
B47: PV of dividends 2028-37 = (1 + shock) x NPV(Ke, dividends) | C47: =(1+C46)*NPV(C44,$E$40:$N$40) -> 24044.888 | D47: =(1+D46)*NPV(D44,$E$40:$N$40) -> 31572.426 | E47: =(1+E46)*NPV(E44,$E$40:$N$40) -> 39390.271 | P47: NPV: 2028 discounted one year (value at end-2027).
B48: Terminal value at end-2037 = dividend 2037 x (1 + shock) x (1 + g) / (Ke - g) | C48: =$N$40*(1+C46)*(1+g_)/(C44-g_) -> 87553.02 | D48: =$N$40*(1+D46)*(1+g_)/(D44-g_) -> 126584.83 | E48: =$N$40*(1+E46)*(1+g_)/(E44-g_) -> 172938.17 | P48: Gordon on the last explicit dividend, as the analysts.
B49: PV of the terminal value = TV / (1 + Ke) ^ 10 | C49: =C48/(1+C44)^10 -> 20913.392 | D49: =D48/(1+D44)^10 -> 35198.148 | E49: =E48/(1+E44)^10 -> 53758.215 | P49: The 2037 factor, as the analysts.
B50: Fair value of Financials at the end of 2027 (index pts) | C50: =C47+C49 -> 44958.28 | D50: =D47+D49 -> 66770.574 | E50: =E47+E49 -> 93148.486
B51: Upside vs. today | C51: =C50/$C$7-1 -> -0.26209963 | D51: =D50/$C$7-1 -> 0.095905614 | E51: =E50/$C$7-1 -> 0.52884635
B52: Perpetuity share of the value | C52: =C49/C50 -> 0.46517331 | D52: =D49/D50 -> 0.5271506 | E52: =E49/E50 -> 0.57712387 | P52: Analysts' models: 42-52% (Model Parameters).
B53: Memo: upside with the analysts' own projections (row 39), same Ke and g | C53: =((1+C46)*NPV(C44,$E$39:$N$39)+$N$39*(1+C46)*(1+g_)/(C44-g_)/(1+C44)^10)/$C$7-1 -> -0.23518506 | D53: =((1+D46)*NPV(D44,$E$39:$N$39)+$N$39*(1+D46)*(1+g_)/(D44-g_)/(1+D44)^10)/$C$7-1 -> 0.12532521 | E53: =((1+E46)*NPV(E44,$E$39:$N$39)+$N$39*(1+E46)*(1+g_)/(E44-g_)/(1+E44)^10)/$C$7-1 -> 0.55841851
B54: Memo: upside in the unified DCF by box (main model, v7b) | C54: -0.35434755 | D54: -0.061 | E54: 0.28808083 | P54: Ibov_house_2027_by_box_XP.xlsx, DCF by Box row 63 (FCFE, 4 explicit years, house g and rate).
B56: 5. Base upside (no earnings shock): Ke (rows) x perpetuity g (columns); dividends 2028-37 as projected
B57: Ke \ g | C57: 0.04 | D57: 0.047 | E57: 0.05 | F57: 0.055 | G57: 0.06
B58: 0.12 | C58: =(NPV($B58,$E$40:$N$40)+$N$40*(1+C$57)/($B58-C$57)/(1+$B58)^10)/$C$7-1 -> 0.3052524 | D58: =(NPV($B58,$E$40:$N$40)+$N$40*(1+D$57)/($B58-D$57)/(1+$B58)^10)/$C$7-1 -> 0.38205601 | E58: =(NPV($B58,$E$40:$N$40)+$N$40*(1+E$57)/($B58-E$57)/(1+$B58)^10)/$C$7-1 -> 0.4196741 | F58: =(NPV($B58,$E$40:$N$40)+$N$40*(1+F$57)/($B58-F$57)/(1+$B58)^10)/$C$7-1 -> 0.49008745 | G58: =(NPV($B58,$E$40:$N$40)+$N$40*(1+G$57)/($B58-G$57)/(1+$B58)^10)/$C$7-1 -> 0.57223637
B59: 0.13 | C59: =(NPV($B59,$E$40:$N$40)+$N$40*(1+C$57)/($B59-C$57)/(1+$B59)^10)/$C$7-1 -> 0.13959962 | D59: =(NPV($B59,$E$40:$N$40)+$N$40*(1+D$57)/($B59-D$57)/(1+$B59)^10)/$C$7-1 -> 0.19502774 | E59: =(NPV($B59,$E$40:$N$40)+$N$40*(1+E$57)/($B59-E$57)/(1+$B59)^10)/$C$7-1 -> 0.221752 | F59: =(NPV($B59,$E$40:$N$40)+$N$40*(1+F$57)/($B59-F$57)/(1+$B59)^10)/$C$7-1 -> 0.27104343 | G59: =(NPV($B59,$E$40:$N$40)+$N$40*(1+G$57)/($B59-G$57)/(1+$B59)^10)/$C$7-1 -> 0.32737649
B60: 0.1365 | C60: =(NPV($B60,$E$40:$N$40)+$N$40*(1+C$57)/($B60-C$57)/(1+$B60)^10)/$C$7-1 -> 0.050991221 | D60: =(NPV($B60,$E$40:$N$40)+$N$40*(1+D$57)/($B60-D$57)/(1+$B60)^10)/$C$7-1 -> 0.096519514 | E60: =(NPV($B60,$E$40:$N$40)+$N$40*(1+E$57)/($B60-E$57)/(1+$B60)^10)/$C$7-1 -> 0.11828738 | F60: =(NPV($B60,$E$40:$N$40)+$N$40*(1+F$57)/($B60-F$57)/(1+$B60)^10)/$C$7-1 -> 0.15812835 | G60: =(NPV($B60,$E$40:$N$40)+$N$40*(1+G$57)/($B60-G$57)/(1+$B60)^10)/$C$7-1 -> 0.2031773
B61: 0.14 | C61: =(NPV($B61,$E$40:$N$40)+$N$40*(1+C$57)/($B61-C$57)/(1+$B61)^10)/$C$7-1 -> 0.0082461015 | D61: =(NPV($B61,$E$40:$N$40)+$N$40*(1+D$57)/($B61-D$57)/(1+$B61)^10)/$C$7-1 -> 0.049373389 | E61: =(NPV($B61,$E$40:$N$40)+$N$40*(1+E$57)/($B61-E$57)/(1+$B61)^10)/$C$7-1 -> 0.068957811 | F61: =(NPV($B61,$E$40:$N$40)+$N$40*(1+F$57)/($B61-F$57)/(1+$B61)^10)/$C$7-1 -> 0.10467058 | G61: =(NPV($B61,$E$40:$N$40)+$N$40*(1+G$57)/($B61-G$57)/(1+$B61)^10)/$C$7-1 -> 0.14484745
B62: 0.15 | C62: =(NPV($B62,$E$40:$N$40)+$N$40*(1+C$57)/($B62-C$57)/(1+$B62)^10)/$C$7-1 -> -0.098241782 | D62: =(NPV($B62,$E$40:$N$40)+$N$40*(1+D$57)/($B62-D$57)/(1+$B62)^10)/$C$7-1 -> -0.0670352 | E62: =(NPV($B62,$E$40:$N$40)+$N$40*(1+E$57)/($B62-E$57)/(1+$B62)^10)/$C$7-1 -> -0.052323526 | F62: =(NPV($B62,$E$40:$N$40)+$N$40*(1+F$57)/($B62-F$57)/(1+$B62)^10)/$C$7-1 -> -0.025739273 | G62: =(NPV($B62,$E$40:$N$40)+$N$40*(1+G$57)/($B62-G$57)/(1+$B62)^10)/$C$7-1 -> 0.0037987869
B63: 0.16 | C63: =(NPV($B63,$E$40:$N$40)+$N$40*(1+C$57)/($B63-C$57)/(1+$B63)^10)/$C$7-1 -> -0.1861469 | D63: =(NPV($B63,$E$40:$N$40)+$N$40*(1+D$57)/($B63-D$57)/(1+$B63)^10)/$C$7-1 -> -0.16202703 | E63: =(NPV($B63,$E$40:$N$40)+$N$40*(1+E$57)/($B63-E$57)/(1+$B63)^10)/$C$7-1 -> -0.1507502 | F63: =(NPV($B63,$E$40:$N$40)+$N$40*(1+F$57)/($B63-F$57)/(1+$B63)^10)/$C$7-1 -> -0.13052352 | G63: =(NPV($B63,$E$40:$N$40)+$N$40*(1+G$57)/($B63-G$57)/(1+$B63)^10)/$C$7-1 -> -0.10827416
B65: 13.65% = house Ke in the base; ~15.1% = analysts' Ke in the base. 4.7% = house g; 6.0% = analysts' g.

Sheet Members DDM
B1: Financials - member by member, the analysts' logic on the consensus
B2: Consensus net income and ROE FY26-28 (R$ mn; Bloomberg BEST, Oct-7-2026, Members sheet and dcf_members.parquet). 2029-37: ROE held at FY28; growth fades linearly from the 2028 growth to g in 2037; dividend = net income - change in book value. Index points = R$ x points / market cap.
B3: Legend: | C3: input | D3: assumption | E3: formula
B5: Itaú Unibanco (ITUB4)
B6: Line | C6: 2026 | D6: 2027 | E6: 2028 | F6: 2029 | G6: 2030 | H6: 2031 | I6: 2032 | J6: 2033 | K6: 2034 | L6: 2035 | M6: 2036 | N6: 2037 | P6: How it is calculated / source
B7: Net income (R$ mn) | C7: 50677.333 | D7: 55448.917 | E7: 60687.636 | F7: =E7*(1+F8) -> 66101.151 | G7: =F7*(1+G8) -> 71648.859 | H7: =G7*(1+H8) -> 77284.199 | I7: =H7*(1+I8) -> 82955.069 | J7: =I7*(1+J8) -> 88604.43 | K7: =J7*(1+K8) -> 94171.101 | L7: =K7*(1+L8) -> 99590.716 | M7: =L7*(1+M8) -> 104796.86 | N7: =M7*(1+N8) -> 109722.31 | P7: 2026-28: consensus (BEST_NET_INCOME); then previous x (1 + growth).
B8: Net income growth | D8: =D7/C7-1 -> 0.094156178 | E8: =E7/D7-1 -> 0.094478293 | F8: =$E$8+(g_-$E$8)*1/9 -> 0.089202927 | G8: =$E$8+(g_-$E$8)*2/9 -> 0.083927561 | H8: =$E$8+(g_-$E$8)*3/9 -> 0.078652195 | I8: =$E$8+(g_-$E$8)*4/9 -> 0.073376829 | J8: =$E$8+(g_-$E$8)*5/9 -> 0.068101463 | K8: =$E$8+(g_-$E$8)*6/9 -> 0.062826098 | L8: =$E$8+(g_-$E$8)*7/9 -> 0.057550732 | M8: =$E$8+(g_-$E$8)*8/9 -> 0.052275366 | N8: =$E$8+(g_-$E$8)*9/9 -> 0.047 | P8: 2027-28: consensus; 2029-37: linear from the 2028 growth to g in 2037.
B9: ROE | C9: 0.24574 | D9: 0.24478 | E9: 0.24343 | F9: =$E$9 -> 0.24343 | G9: =$E$9 -> 0.24343 | H9: =$E$9 -> 0.24343 | I9: =$E$9 -> 0.24343 | J9: =$E$9 -> 0.24343 | K9: =$E$9 -> 0.24343 | L9: =$E$9 -> 0.24343 | M9: =$E$9 -> 0.24343 | N9: =$E$9 -> 0.24343 | P9: 2026-28: consensus (BEST_ROE); 2029-37: held at FY28, as the analysts keep ROE about flat.
B10: Book value = net income / ROE (R$ mn) | C10: =C7/C9 -> 206223.38 | D10: =D7/D9 -> 226525.52 | E10: =E7/E9 -> 249302.21 | F10: =F7/F9 -> 271540.69 | G10: =G7/G9 -> 294330.44 | H10: =H7/H9 -> 317480.18 | I10: =I7/I9 -> 340775.86 | J10: =J7/J9 -> 363983.2 | ... N10: =N7/N9 -> 450734.54
B11: Dividends = net income - change in book value (R$ mn) | D11: =D7-(D10-C10) -> 35146.774 | E11: =E7-(E10-D10) -> 37910.951 | F11: =F7-(F10-E10) -> 43862.664 | G11: =G7-(G10-F10) -> 48859.111 | H11: =H7-(H10-G10) -> 54134.464 | I11: =I7-(I10-H10) -> 59659.38 | J11: =J7-(J10-I10) -> 65397.095 | K11: =K7-(K10-J10) -> 71303.457 | ... N11: =N7-(N10-M10) -> 89488.763 | P11: Clean surplus: what is not retained to grow the book value is paid out (dividends, IoC, buybacks).
B12: Payout = dividends / net income | D12: =D11/D7 -> 0.63385863 | E12: =E11/E7 -> 0.62468986 | F12: =F11/F7 -> 0.66356885 | G12: =G11/G7 -> 0.68192448 | H12: =H11/H7 -> 0.70045966 | I12: =I11/I7 -> 0.71917703 | J12: =J11/J7 -> 0.73807929 | K12: =K11/K7 -> 0.7571692 | ... N12: =N11/N7 -> 0.81559314 | P12: Converges to about 1 - g / ROE as growth reaches g.
B13: Index points / market cap (R$ mn) | C13: 19089.265 | D13: 564225.23 | E13: =C13/D13 -> 0.033832704 | P13: Members sheet of the main model (Oct-5-2026).
B14: Net income (index pts) | C14: =C7*$E$13 -> 1714.5512 | D14: =D7*$E$13 -> 1875.9868 | E14: =E7*$E$13 -> 2053.2268 | F14: =F7*$E$13 -> 2236.3807 | G14: =G7*$E$13 -> 2424.0746 | H14: =H7*$E$13 -> 2614.7334 | I14: =I7*$E$13 -> 2806.5943 | J14: =J7*$E$13 -> 2997.7275 | ... N14: =N7*$E$13 -> 3712.2024
B15: Dividends (index pts) | D15: =D11*$E$13 -> 1189.1104 | E15: =E11*$E$13 -> 1282.63 | F15: =F11*$E$13 -> 1483.9925 | G15: =G11*$E$13 -> 1653.0358 | H15: =H11*$E$13 -> 1831.5153 | I15: =I11*$E$13 -> 2018.4381 | J15: =J11*$E$13 -> 2212.5606 | K15: =K11*$E$13 -> 2412.3887 | ... N15: =N11*$E$13 -> 3027.6468
B16: Book value (index pts) | C16: =C10*$E$13 -> 6977.0945 | D16: =D10*$E$13 -> 7663.9709 | E16: =E10*$E$13 -> 8434.5677 | F16: =F10*$E$13 -> 9186.9559 | G16: =G10*$E$13 -> 9957.9947 | H16: =H10*$E$13 -> 10741.213 | I16: =I10*$E$13 -> 11529.369 | J16: =J10*$E$13 -> 12314.536 | ... N16: =N10*$E$13 -> 15249.568
B19: Bradesco (BBDC4 + BBDC3)
B20: Line | C20: 2026 | D20: 2027 | E20: 2028 | F20: 2029 | G20: 2030 | H20: 2031 | I20: 2032 | J20: 2033 | K20: 2034 | L20: 2035 | M20: 2036 | N20: 2037 | P20: How it is calculated / source
B21: Net income (R$ mn) | C21: 27739.923 | D21: 30648.077 | E21: 33619.083 | F21: =E21*(1+F22) -> 36691.55 | G21: =F21*(1+G22) -> 39841.217 | H21: =G21*(1+H22) -> 43040.185 | I21: =H21*(1+I22) -> 46257.185 | J21: =I21*(1+J22) -> 49457.965 | K21: =J21*(1+K22) -> 52605.789 | L21: =K21*(1+L22) -> 55662.062 | M21: =L21*(1+M22) -> 58587.037 | N21: =M21*(1+N22) -> 61340.628 | P21: 2026-28: consensus (BEST_NET_INCOME); then previous x (1 + growth).
B22: Net income growth | D22: =D21/C21-1 -> 0.10483641 | E22: =E21/D21-1 -> 0.096939394 | F22: =$E$22+(g_-$E$22)*1/9 -> 0.091390572 | G22: =$E$22+(g_-$E$22)*2/9 -> 0.085841751 | H22: =$E$22+(g_-$E$22)*3/9 -> 0.080292929 | I22: =$E$22+(g_-$E$22)*4/9 -> 0.074744108 | J22: =$E$22+(g_-$E$22)*5/9 -> 0.069195286 | K22: =$E$22+(g_-$E$22)*6/9 -> 0.063646465 | L22: =$E$22+(g_-$E$22)*7/9 -> 0.058097643 | M22: =$E$22+(g_-$E$22)*8/9 -> 0.052548822 | N22: =$E$22+(g_-$E$22)*9/9 -> 0.047 | P22: 2027-28: consensus; 2029-37: linear from the 2028 growth to g in 2037.
B23: ROE | C23: 0.15379 | D23: 0.15855 | E23: 0.1615 | F23: =$E$23 -> 0.1615 | G23: =$E$23 -> 0.1615 | H23: =$E$23 -> 0.1615 | I23: =$E$23 -> 0.1615 | J23: =$E$23 -> 0.1615 | K23: =$E$23 -> 0.1615 | L23: =$E$23 -> 0.1615 | M23: =$E$23 -> 0.1615 | N23: =$E$23 -> 0.1615 | P23: 2026-28: consensus (BEST_ROE); 2029-37: held at FY28, as the analysts keep ROE about flat.
B24: Book value = net income / ROE (R$ mn) | C24: =C21/C23 -> 180375.34 | D24: =D21/D23 -> 193302.28 | E24: =E21/E23 -> 208167.7 | F24: =F21/F23 -> 227192.26 | G24: =G21/G23 -> 246694.84 | H24: =H21/H23 -> 266502.69 | I24: =I21/I23 -> 286422.2 | J24: =J21/J23 -> 306241.27 | ... N24: =N21/N23 -> 379818.13
B25: Dividends = net income - change in book value (R$ mn) | D25: =D21-(D24-C24) -> 17721.13 | E25: =E21-(E24-D24) -> 18753.67 | F25: =F21-(F24-E24) -> 17666.985 | G25: =G21-(G24-F24) -> 20338.636 | H25: =H21-(H24-G24) -> 23232.334 | I25: =I21-(I24-H24) -> 26337.679 | J25: =J21-(J24-I24) -> 29638.898 | K25: =K21-(K24-J24) -> 33114.615 | ... N25: =N21-(N24-M24) -> 44290.53 | P25: Clean surplus: what is not retained to grow the book value is paid out (dividends, IoC, buybacks).
B26: Payout = dividends / net income | D26: =D25/D21 -> 0.57821345 | E26: =E25/E21 -> 0.55782811 | F26: =F25/F21 -> 0.48150011 | G26: =G25/G21 -> 0.51049233 | H26: =H25/H21 -> 0.53978238 | I26: =I25/I21 -> 0.56937488 | J26: =J25/J21 -> 0.59927453 | K26: =K25/K21 -> 0.62948614 | ... N26: =N25/N21 -> 0.72204234 | P26: Converges to about 1 - g / ROE as growth reaches g.
B27: Index points / market cap (R$ mn) | C27: 10039.703 | D27: 226447.76 | E27: =C27/D27 -> 0.044335627 | P27: Members sheet of the main model (Oct-5-2026).
B28: Net income (index pts) | C28: =C21*$E$27 -> 1229.8669 | D28: =D21*$E$27 -> 1358.8017 | E28: =E21*$E$27 -> 1490.5231 | F28: =F21*$E$27 -> 1626.7429 | G28: =G21*$E$27 -> 1766.3853 | H28: =H21*$E$27 -> 1908.2136 | I28: =I21*$E$27 -> 2050.8413 | J28: =J21*$E$27 -> 2192.7499 | ... N28: =N21*$E$27 -> 2719.5752
B29: Dividends (index pts) | D29: =D25*$E$27 -> 785.67743 | E29: =E25*$E$27 -> 831.4557 | F29: =F25*$E$27 -> 783.27687 | G29: =G25*$E$27 -> 901.72617 | H29: =H25*$E$27 -> 1030.0201 | I29: =I25*$E$27 -> 1167.6975 | J29: =J25*$E$27 -> 1314.0592 | K29: =K25*$E$27 -> 1468.1572 | ... N29: =N25*$E$27 -> 1963.6484
B30: Book value (index pts) | C30: =C24*$E$27 -> 7997.0537 | D30: =D24*$E$27 -> 8570.1779 | E30: =E24*$E$27 -> 9229.2454 | F30: =F24*$E$27 -> 10072.711 | G30: =G24*$E$27 -> 10937.371 | H30: =H24*$E$27 -> 11815.564 | I30: =I24*$E$27 -> 12698.708 | J30: =J24*$E$27 -> 13577.399 | ... N30: =N24*$E$27 -> 16839.475
B33: B3 (B3SA3)
B34: Line | C34: 2026 | D34: 2027 | E34: 2028 | F34: 2029 | G34: 2030 | H34: 2031 | I34: 2032 | J34: 2033 | K34: 2034 | L34: 2035 | M34: 2036 | N34: 2037 | P34: How it is calculated / source
B35: Net income (R$ mn) | C35: 5982 | D35: 6425.4 | E35: 6561.222 | F35: =E35*(1+F36) -> 6718.7689 | G35: =F35*(1+G36) -> 6899.4053 | H35: =G35*(1+H36) -> 7104.7237 | I35: =H35*(1+I36) -> 7336.5678 | J35: =I35*(1+J36) -> 7597.0593 | K35: =J35*(1+K36) -> 7888.6301 | L35: =K35*(1+L36) -> 8214.0594 | M35: =L35*(1+M36) -> 8576.5169 | N35: =M35*(1+N36) -> 8979.6132 | P35: 2026-28: consensus (BEST_NET_INCOME); then previous x (1 + growth).
B36: Net income growth | D36: =D35/C35-1 -> 0.074122367 | E36: =E35/D35-1 -> 0.021138295 | F36: =$E$36+(g_-$E$36)*1/9 -> 0.024011818 | G36: =$E$36+(g_-$E$36)*2/9 -> 0.02688534 | H36: =$E$36+(g_-$E$36)*3/9 -> 0.029758863 | I36: =$E$36+(g_-$E$36)*4/9 -> 0.032632386 | J36: =$E$36+(g_-$E$36)*5/9 -> 0.035505909 | K36: =$E$36+(g_-$E$36)*6/9 -> 0.038379432 | L36: =$E$36+(g_-$E$36)*7/9 -> 0.041252954 | M36: =$E$36+(g_-$E$36)*8/9 -> 0.044126477 | N36: =$E$36+(g_-$E$36)*9/9 -> 0.047 | P36: 2027-28: consensus; 2029-37: linear from the 2028 growth to g in 2037.
B37: ROE | C37: 0.3363 | D37: 0.34744 | E37: 0.37809 | F37: =$E$37 -> 0.37809 | G37: =$E$37 -> 0.37809 | H37: =$E$37 -> 0.37809 | I37: =$E$37 -> 0.37809 | J37: =$E$37 -> 0.37809 | K37: =$E$37 -> 0.37809 | L37: =$E$37 -> 0.37809 | M37: =$E$37 -> 0.37809 | N37: =$E$37 -> 0.37809 | P37: 2026-28: consensus (BEST_ROE); 2029-37: held at FY28, as the analysts keep ROE about flat.
B38: Book value = net income / ROE (R$ mn) | C38: =C35/C37 -> 17787.69 | D38: =D35/D37 -> 18493.553 | E38: =E35/E37 -> 17353.598 | F38: =F35/F37 -> 17770.29 | G38: =G35/G37 -> 18248.05 | H38: =H35/H37 -> 18791.091 | I38: =I35/I37 -> 19404.289 | J38: =J35/J37 -> 20093.256 | ... N38: =N35/N37 -> 23749.936
B39: Dividends = net income - change in book value (R$ mn) | D39: =D35-(D38-C38) -> 5719.5367 | E39: =E35-(E38-D38) -> 7701.1765 | F39: =F35-(F38-E38) -> 6302.0774 | G39: =G35-(G38-F38) -> 6421.645 | H39: =H35-(H38-G38) -> 6561.6825 | I39: =I35-(I38-H38) -> 6723.3697 | J39: =J35-(J38-I38) -> 6908.0924 | K39: =K35-(K38-J38) -> 7117.4624 | ... N39: =N35-(N38-M38) -> 7913.4748 | P39: Clean surplus: what is not retained to grow the book value is paid out (dividends, IoC, buybacks).
B40: Payout = dividends / net income | D40: =D39/D35 -> 0.89014485 | E40: =E39/E35 -> 1.1737412 | F40: =F39/F35 -> 0.93798098 | G40: =G39/G35 -> 0.93075341 | H40: =H39/H35 -> 0.92356617 | I40: =I39/I35 -> 0.91641894 | J40: =J39/J35 -> 0.90931137 | K40: =K39/K35 -> 0.90224313 | ... N40: =N39/N35 -> 0.88127123 | P40: Converges to about 1 - g / ROE as growth reaches g.
B41: Index points / market cap (R$ mn) | C41: 8337.4035 | D41: 112688.35 | E41: =C41/D41 -> 0.073986387 | P41: Members sheet of the main model (Oct-5-2026).
B42: Net income (index pts) | C42: =C35*$E$41 -> 442.58656 | D42: =D35*$E$41 -> 475.39213 | E42: =E35*$E$41 -> 485.44111 | F42: =F35*$E$41 -> 497.09743 | G42: =G35*$E$41 -> 510.46206 | H42: =H35*$E$41 -> 525.65283 | I42: =I35*$E$41 -> 542.80614 | J42: =J35*$E$41 -> 562.07897 | ... N42: =N35*$E$41 -> 664.36914
B43: Dividends (index pts) | D43: =D39*$E$41 -> 423.16785 | E43: =E39*$E$41 -> 569.78222 | F43: =F39*$E$41 -> 466.26794 | G43: =G39*$E$41 -> 475.11431 | H43: =H39*$E$41 -> 485.47518 | I43: =I39*$E$41 -> 497.43783 | J43: =J39*$E$41 -> 511.10479 | K43: =K39*$E$41 -> 526.59532 | ... N43: =N39*$E$41 -> 585.4894
B44: Book value (index pts) | C44: =C38*$E$41 -> 1316.0469 | D44: =D38*$E$41 -> 1368.2711 | E44: =E38*$E$41 -> 1283.93 | F44: =F38*$E$41 -> 1314.7595 | G44: =G38*$E$41 -> 1350.1073 | H44: =H38*$E$41 -> 1390.2849 | I44: =I38*$E$41 -> 1435.6533 | J44: =J38*$E$41 -> 1486.6274 | ... N44: =N38*$E$41 -> 1757.1719
B47: Itausa (ITSA4)
B48: Line | C48: 2026 | D48: 2027 | E48: 2028 | F48: 2029 | G48: 2030 | H48: 2031 | I48: 2032 | J48: 2033 | K48: 2034 | L48: 2035 | M48: 2036 | N48: 2037 | P48: How it is calculated / source
B49: Net income (R$ mn) | C49: 19414 | D49: 20412 | E49: 23060 | F49: =E49*(1+F50) -> 25839.552 | G49: =F49*(1+G50) -> 28716.623 | H49: =G49*(1+H50) -> 31650.077 | I49: =H49*(1+I50) -> 34592.261 | J49: =I49*(1+J50) -> 37489.979 | K49: =J49*(1+K50) -> 40285.827 | L49: =K49*(1+L50) -> 42919.872 | M49: =L49*(1+M50) -> 45331.624 | N49: =M49*(1+N50) -> 47462.21 | P49: 2026-28: consensus (BEST_NET_INCOME); then previous x (1 + growth).
B50: Net income growth | D50: =D49/C49-1 -> 0.051406202 | E50: =E49/D49-1 -> 0.12972761 | F50: =$E$50+(g_-$E$50)*1/9 -> 0.12053565 | G50: =$E$50+(g_-$E$50)*2/9 -> 0.1113437 | H50: =$E$50+(g_-$E$50)*3/9 -> 0.10215174 | I50: =$E$50+(g_-$E$50)*4/9 -> 0.092959784 | J50: =$E$50+(g_-$E$50)*5/9 -> 0.083767827 | K50: =$E$50+(g_-$E$50)*6/9 -> 0.07457587 | L50: =$E$50+(g_-$E$50)*7/9 -> 0.065383914 | M50: =$E$50+(g_-$E$50)*8/9 -> 0.056191957 | N50: =$E$50+(g_-$E$50)*9/9 -> 0.047 | P50: 2027-28: consensus; 2029-37: linear from the 2028 growth to g in 2037.
B51: ROE (no consensus: Itaú's ROE, editable) | C51: 0.24574 | D51: 0.24478 | E51: 0.24343 | F51: =$E$51 -> 0.24343 | G51: =$E$51 -> 0.24343 | H51: =$E$51 -> 0.24343 | I51: =$E$51 -> 0.24343 | J51: =$E$51 -> 0.24343 | K51: =$E$51 -> 0.24343 | L51: =$E$51 -> 0.24343 | M51: =$E$51 -> 0.24343 | N51: =$E$51 -> 0.24343 | P51: No BEST_ROE for the holding: Itaú's consensus ROE as a proxy (assumption).
B52: Book value = net income / ROE (R$ mn) | C52: =C49/C51 -> 79002.197 | D52: =D49/D51 -> 83389.166 | E52: =E49/E51 -> 94729.491 | F52: =F49/F51 -> 106147.77 | G52: =G49/G51 -> 117966.66 | H52: =H49/H51 -> 130017.16 | I52: =I49/I51 -> 142103.52 | J52: =J49/J51 -> 154007.23 | ... N52: =N49/N51 -> 194972.72
B53: Dividends = net income - change in book value (R$ mn) | D53: =D49-(D52-C52) -> 16025.032 | E53: =E49-(E52-D52) -> 11719.675 | F53: =F49-(F52-E52) -> 14421.271 | G53: =G49-(G52-F52) -> 16897.738 | H53: =H49-(H52-G52) -> 19599.577 | I53: =I49-(I52-H52) -> 22505.894 | J53: =J49-(J52-I52) -> 25586.276 | K53: =K49-(K52-J52) -> 28800.604 | ... N53: =N49-(N52-M52) -> 38709.853 | P53: Clean surplus: what is not retained to grow the book value is paid out (dividends, IoC, buybacks).
B54: Payout = dividends / net income | D54: =D53/D49 -> 0.78507896 | E54: =E53/E49 -> 0.50822527 | F54: =F53/F49 -> 0.55810839 | G54: =G53/G49 -> 0.58843053 | H54: =H53/H49 -> 0.61925844 | I54: =I53/I49 -> 0.65060489 | J54: =J53/J49 -> 0.68248306 | K54: =K53/K49 -> 0.71490661 | ... N54: =N53/N49 -> 0.81559314 | P54: Converges to about 1 - g / ROE as growth reaches g.
B55: Index points / market cap (R$ mn) | C55: 7020.6236 | D55: 179573.13 | E55: =C55/D55 -> 0.03909618 | P55: Members sheet of the main model (Oct-5-2026).
B56: Net income (index pts) | C56: =C49*$E$55 -> 759.01324 | D56: =D49*$E$55 -> 798.03122 | E56: =E49*$E$55 -> 901.55791 | F56: =F49*$E$55 -> 1010.2278 | G56: =G49*$E$55 -> 1122.7103 | H56: =H49*$E$55 -> 1237.3971 | I56: =I49*$E$55 -> 1352.4253 | J56: =J49*$E$55 -> 1465.715 | ... N56: =N49*$E$55 -> 1855.5911
B57: Dividends (index pts) | D57: =D53*$E$55 -> 626.51752 | E57: =E53*$E$55 -> 458.19451 | F57: =F53*$E$55 -> 563.81661 | G57: =G53*$E$55 -> 660.63701 | H57: =H53*$E$55 -> 766.26859 | I57: =I53*$E$55 -> 879.89448 | J57: =J53*$E$55 -> 1000.3256 | K57: =K53*$E$55 -> 1125.9936 | ... N57: =N53*$E$55 -> 1513.4074
B58: Book value (index pts) | C58: =C52*$E$55 -> 3088.6841 | D58: =D52*$E$55 -> 3260.1978 | E58: =E52*$E$55 -> 3703.5612 | F58: =F52*$E$55 -> 4149.9724 | G58: =G52*$E$55 -> 4612.0457 | H58: =H52*$E$55 -> 5083.1742 | I58: =I52*$E$55 -> 5555.7049 | J58: =J52*$E$55 -> 6021.0943 | ... N58: =N52*$E$55 -> 7622.6887
B61: BTG Pactual (BPAC11)
B62: Line | C62: 2026 | D62: 2027 | E62: 2028 | F62: 2029 | G62: 2030 | H62: 2031 | I62: 2032 | J62: 2033 | K62: 2034 | L62: 2035 | M62: 2036 | N62: 2037 | P62: How it is calculated / source
B63: Net income (R$ mn) | C63: 20474.182 | D63: 23359.364 | E63: 26673.6 | F63: =E63*(1+F64) -> 30176.861 | G63: =F63*(1+G64) -> 33822.101 | H63: =G63*(1+H64) -> 37551.11 | I63: =H63*(1+I64) -> 41295.381 | J63: =I63*(1+J64) -> 44977.652 | K63: =J63*(1+K64) -> 48514.1 | L63: =K63*(1+L64) -> 51817.16 | M63: =L63*(1+M64) -> 54798.837 | N63: =M63*(1+N64) -> 57374.383 | P63: 2026-28: consensus (BEST_NET_INCOME); then previous x (1 + growth).
B64: Net income growth | D64: =D63/C63-1 -> 0.14091806 | E64: =E63/D63-1 -> 0.1418804 | F64: =$E$64+(g_-$E$64)*1/9 -> 0.13133814 | G64: =$E$64+(g_-$E$64)*2/9 -> 0.12079587 | H64: =$E$64+(g_-$E$64)*3/9 -> 0.1102536 | I64: =$E$64+(g_-$E$64)*4/9 -> 0.099711336 | J64: =$E$64+(g_-$E$64)*5/9 -> 0.089169068 | K64: =$E$64+(g_-$E$64)*6/9 -> 0.078626801 | L64: =$E$64+(g_-$E$64)*7/9 -> 0.068084534 | M64: =$E$64+(g_-$E$64)*8/9 -> 0.057542267 | N64: =$E$64+(g_-$E$64)*9/9 -> 0.047 | P64: 2027-28: consensus; 2029-37: linear from the 2028 growth to g in 2037.
B65: ROE | C65: 0.2655 | D65: 0.2553 | E65: 0.2486 | F65: =$E$65 -> 0.2486 | G65: =$E$65 -> 0.2486 | H65: =$E$65 -> 0.2486 | I65: =$E$65 -> 0.2486 | J65: =$E$65 -> 0.2486 | K65: =$E$65 -> 0.2486 | L65: =$E$65 -> 0.2486 | M65: =$E$65 -> 0.2486 | N65: =$E$65 -> 0.2486 | P65: 2026-28: consensus (BEST_ROE); 2029-37: held at FY28, as the analysts keep ROE about flat.
B66: Book value = net income / ROE (R$ mn) | C66: =C63/C65 -> 77115.563 | D66: =D63/D65 -> 91497.705 | E66: =E63/E65 -> 107295.25 | F66: =F63/F65 -> 121387.21 | G66: =G63/G65 -> 136050.29 | H66: =H63/H65 -> 151050.32 | I66: =I63/I65 -> 166111.75 | J66: =J63/J65 -> 180923.78 | ... N66: =N63/N65 -> 230789.95
B67: Dividends = net income - change in book value (R$ mn) | D67: =D63-(D66-C66) -> 8977.2224 | E67: =E63-(E66-D66) -> 10876.051 | F67: =F63-(F66-E66) -> 16084.902 | G67: =G63-(G66-F66) -> 19159.027 | H67: =H63-(H66-G66) -> 22551.075 | I67: =I63-(I66-H66) -> 26233.952 | J67: =J63-(J66-I66) -> 30165.622 | K67: =K63-(K66-J66) -> 34288.642 | ... N67: =N63-(N66-M66) -> 47014.184 | P67: Clean surplus: what is not retained to grow the book value is paid out (dividends, IoC, buybacks).
B68: Payout = dividends / net income | D68: =D67/D63 -> 0.38430937 | E68: =E67/E63 -> 0.40774591 | F68: =F67/F63 -> 0.53302106 | G68: =G67/G63 -> 0.56646473 | H68: =H67/H63 -> 0.60054352 | I68: =I67/I63 -> 0.63527569 | J68: =J67/J63 -> 0.67068023 | K68: =K67/K63 -> 0.70677684 | ... N68: =N67/N63 -> 0.81942815 | P68: Converges to about 1 - g / ROE as growth reaches g.
B69: Index points / market cap (R$ mn) | C69: 6925.2189 | D69: 305584.14 | E69: =C69/D69 -> 0.022662232 | P69: Members sheet of the main model (Oct-5-2026).
B70: Net income (index pts) | C70: =C63*$E$69 -> 463.99067 | D70: =D63*$E$69 -> 529.37533 | E70: =E63*$E$69 -> 604.48332 | F70: =F63*$E$69 -> 683.87503 | G70: =G63*$E$69 -> 766.48431 | H70: =H63*$E$69 -> 850.99197 | I70: =I63*$E$69 -> 935.84552 | J70: =J63*$E$69 -> 1019.294 | ... N70: =N63*$E$69 -> 1300.2316
B71: Dividends (index pts) | D71: =D67*$E$69 -> 203.4439 | E71: =E67*$E$69 -> 246.4756 | F71: =F67*$E$69 -> 364.51979 | G71: =G67*$E$69 -> 434.18633 | H71: =H67*$E$69 -> 511.05771 | I71: =I67*$E$69 -> 594.51991 | J71: =J67*$E$69 -> 683.62033 | K71: =K67*$E$69 -> 777.05718 | ... N71: =N67*$E$69 -> 1065.4464
B72: Book value (index pts) | C72: =C66*$E$69 -> 1747.6108 | D72: =D66*$E$69 -> 2073.5422 | E72: =E66*$E$69 -> 2431.55 | F72: =F66*$E$69 -> 2750.9052 | G72: =G66*$E$69 -> 3083.2032 | H72: =H66*$E$69 -> 3423.1375 | I72: =I66*$E$69 -> 3764.4631 | J72: =J66*$E$69 -> 4100.1367 | ... N72: =N66*$E$69 -> 5230.2156
B75: Banco do Brasil (BBAS3)
B76: Line | C76: 2026 | D76: 2027 | E76: 2028 | F76: 2029 | G76: 2030 | H76: 2031 | I76: 2032 | J76: 2033 | K76: 2034 | L76: 2035 | M76: 2036 | N76: 2037 | P76: How it is calculated / source
B77: Net income (R$ mn) | C77: 17093.5 | D77: 24478.75 | E77: 29169 | F77: =E77*(1+F78) -> 34289.26 | G77: =F77*(1+G78) -> 39757.387 | H77: =G77*(1+H78) -> 45458.728 | I77: =H77*(1+I78) -> 51247.264 | J77: =I77*(1+J78) -> 56949.49 | K77: =J77*(1+K78) -> 62371.175 | L77: =K77*(1+L78) -> 67306.883 | M77: =L77*(1+M78) -> 71551.741 | N77: =M77*(1+N78) -> 74914.673 | P77: 2026-28: consensus (BEST_NET_INCOME); then previous x (1 + growth).
B78: Net income growth | D78: =D77/C77-1 -> 0.43205019 | E78: =E77/D77-1 -> 0.19160496 | F78: =$E$78+(g_-$E$78)*1/9 -> 0.17553775 | G78: =$E$78+(g_-$E$78)*2/9 -> 0.15947053 | H78: =$E$78+(g_-$E$78)*3/9 -> 0.14340331 | I78: =$E$78+(g_-$E$78)*4/9 -> 0.12733609 | J78: =$E$78+(g_-$E$78)*5/9 -> 0.11126887 | K78: =$E$78+(g_-$E$78)*6/9 -> 0.095201654 | L78: =$E$78+(g_-$E$78)*7/9 -> 0.079134436 | M78: =$E$78+(g_-$E$78)*8/9 -> 0.063067218 | N78: =$E$78+(g_-$E$78)*9/9 -> 0.047 | P78: 2027-28: consensus; 2029-37: linear from the 2028 growth to g in 2037.
B79: ROE | C79: 0.08591 | D79: 0.11989 | E79: 0.13251 | F79: =$E$79 -> 0.13251 | G79: =$E$79 -> 0.13251 | H79: =$E$79 -> 0.13251 | I79: =$E$79 -> 0.13251 | J79: =$E$79 -> 0.13251 | K79: =$E$79 -> 0.13251 | L79: =$E$79 -> 0.13251 | M79: =$E$79 -> 0.13251 | N79: =$E$79 -> 0.13251 | P79: 2026-28: consensus (BEST_ROE); 2029-37: held at FY28, as the analysts keep ROE about flat.
B80: Book value = net income / ROE (R$ mn) | C80: =C77/C79 -> 198969.85 | D80: =D77/D79 -> 204176.75 | E80: =E77/E79 -> 220126.78 | F80: =F77/F79 -> 258767.34 | G80: =G77/G79 -> 300033.11 | H80: =H77/H79 -> 343058.85 | I80: =I77/I79 -> 386742.62 | J80: =J77/J79 -> 429775.03 | ... N80: =N77/N79 -> 565351.09
B81: Dividends = net income - change in book value (R$ mn) | D81: =D77-(D80-C80) -> 19271.857 | E81: =E77-(E80-D80) -> 13218.962 | F81: =F77-(F80-E80) -> -4351.2987 | G81: =G77-(G80-F80) -> -1508.3775 | H81: =H77-(H80-G80) -> 2432.9875 | I81: =I77-(I80-H80) -> 7563.492 | J81: =J77-(J80-I80) -> 13917.075 | K81: =K77-(K80-J80) -> 21455.881 | ... N81: =N77-(N80-M80) -> 49535.971 | P81: Clean surplus: what is not retained to grow the book value is paid out (dividends, IoC, buybacks).
B82: Payout = dividends / net income | D82: =D81/D77 -> 0.78728925 | E82: =E81/E77 -> 0.45318532 | F82: =F81/F77 -> -0.12689975 | G82: =G81/G77 -> -0.037939553 | H82: =H81/H77 -> 0.053520801 | I82: =I81/I77 -> 0.14758821 | J82: =J81/J77 -> 0.24437575 | K82: =K81/K77 -> 0.34400315 | ... N82: =N81/N77 -> 0.66123189 | P82: Converges to about 1 - g / ROE as growth reaches g.
B83: Index points / market cap (R$ mn) | C83: 5397.318 | D83: 138571.57 | E83: =C83/D83 -> 0.038949679 | P83: Members sheet of the main model (Oct-5-2026).
B84: Net income (index pts) | C84: =C77*$E$83 -> 665.78634 | D84: =D77*$E$83 -> 953.43945 | E84: =E77*$E$83 -> 1136.1232 | F84: =F77*$E$83 -> 1335.5557 | G84: =G77*$E$83 -> 1548.5375 | H84: =H77*$E$83 -> 1770.6029 | I84: =I77*$E$83 -> 1996.0645 | J84: =J77*$E$83 -> 2218.1643 | ... N84: =N77*$E$83 -> 2917.9025
B85: Dividends (index pts) | D85: =D81*$E$83 -> 750.63264 | E85: =E81*$E$83 -> 514.87434 | F85: =F81*$E$83 -> -169.48169 | G85: =G81*$E$83 -> -58.75082 | H85: =H81*$E$83 -> 94.764082 | I85: =I81*$E$83 -> 294.59558 | J85: =J81*$E$83 -> 542.06559 | K85: =K81*$E$83 -> 835.69968 | ... N85: =N81*$E$83 -> 1929.4102
B86: Book value (index pts) | C86: =C80*$E$83 -> 7749.8119 | D86: =D80*$E$83 -> 7952.6187 | E86: =E80*$E$83 -> 8573.8675 | F86: =F80*$E$83 -> 10078.905 | G86: =G80*$E$83 -> 11686.193 | H86: =H80*$E$83 -> 13362.032 | I86: =I80*$E$83 -> 15063.501 | J86: =J80*$E$83 -> 16739.6 | ... N86: =N80*$E$83 -> 22020.243
B89: BBSeguridade (BBSE3)
B90: Line | C90: 2026 | D90: 2027 | E90: 2028 | F90: 2029 | G90: 2030 | H90: 2031 | I90: 2032 | J90: 2033 | K90: 2034 | L90: 2035 | M90: 2036 | N90: 2037 | P90: How it is calculated / source
B91: Net income (R$ mn) | C91: 8662.5 | D91: 8582.6 | E91: 8977.125 | F91: =E91*(1+F92) -> 9390.8149 | G91: =F91*(1+G92) -> 9824.6455 | H91: =G91*(1+H92) -> 10279.645 | I91: =H91*(1+I92) -> 10756.894 | J91: =I91*(1+J92) -> 11257.534 | K91: =J91*(1+K92) -> 11782.766 | L91: =K91*(1+L92) -> 12333.854 | M91: =L91*(1+M92) -> 12912.131 | N91: =M91*(1+N92) -> 13519.001 | P91: 2026-28: consensus (BEST_NET_INCOME); then previous x (1 + growth).
B92: Net income growth | D92: =D91/C91-1 -> -0.0092236652 | E92: =E91/D91-1 -> 0.045968005 | F92: =$E$92+(g_-$E$92)*1/9 -> 0.046082671 | G92: =$E$92+(g_-$E$92)*2/9 -> 0.046197337 | H92: =$E$92+(g_-$E$92)*3/9 -> 0.046312003 | I92: =$E$92+(g_-$E$92)*4/9 -> 0.046426669 | J92: =$E$92+(g_-$E$92)*5/9 -> 0.046541336 | K92: =$E$92+(g_-$E$92)*6/9 -> 0.046656002 | L92: =$E$92+(g_-$E$92)*7/9 -> 0.046770668 | M92: =$E$92+(g_-$E$92)*8/9 -> 0.046885334 | N92: =$E$92+(g_-$E$92)*9/9 -> 0.047 | P92: 2027-28: consensus; 2029-37: linear from the 2028 growth to g in 2037.
B93: ROE | C93: 0.91299 | D93: 0.85076 | E93: 0.81663 | F93: =$E$93 -> 0.81663 | G93: =$E$93 -> 0.81663 | H93: =$E$93 -> 0.81663 | I93: =$E$93 -> 0.81663 | J93: =$E$93 -> 0.81663 | K93: =$E$93 -> 0.81663 | L93: =$E$93 -> 0.81663 | M93: =$E$93 -> 0.81663 | N93: =$E$93 -> 0.81663 | P93: 2026-28: consensus (BEST_ROE); 2029-37: held at FY28, as the analysts keep ROE about flat.
B94: Book value = net income / ROE (R$ mn) | C94: =C91/C93 -> 9488.0557 | D94: =D91/D93 -> 10088.156 | E94: =E91/E93 -> 10992.892 | F94: =F91/F93 -> 11499.473 | G94: =G91/G93 -> 12030.718 | H94: =H91/H93 -> 12587.885 | I94: =I91/I93 -> 13172.299 | J94: =J91/J93 -> 13785.355 | ... N94: =N91/N93 -> 16554.622
B95: Dividends = net income - change in book value (R$ mn) | D95: =D91-(D94-C94) -> 7982.4993 | E95: =E91-(E94-D94) -> 8072.39 | F95: =F91-(F94-E94) -> 8884.2331 | G95: =G91-(G94-F94) -> 9293.4005 | H95: =H91-(H94-G94) -> 9722.4779 | I95: =I91-(I94-H94) -> 10172.481 | J95: =J91-(J94-I94) -> 10644.478 | K95: =K91-(K94-J94) -> 11139.596 | ... N95: =N91-(N94-M94) -> 12775.861 | P95: Clean surplus: what is not retained to grow the book value is paid out (dividends, IoC, buybacks).
B96: Payout = dividends / net income | D96: =D95/D91 -> 0.93007938 | E96: =E95/E91 -> 0.89921773 | F96: =F95/F91 -> 0.94605561 | G96: =G95/G91 -> 0.94592731 | H96: =H95/H91 -> 0.94579903 | I96: =I95/I91 -> 0.94567079 | J96: =J95/J91 -> 0.94554257 | K96: =K95/K91 -> 0.94541438 | ... N96: =N95/N91 -> 0.94502999 | P96: Converges to about 1 - g / ROE as growth reaches g.
B97: Index points / market cap (R$ mn) | C97: 1823.5557 | D97: 78199.592 | E97: =C97/D97 -> 0.023319248 | P97: Members sheet of the main model (Oct-5-2026).
B98: Net income (index pts) | C98: =C91*$E$97 -> 202.00299 | D98: =D91*$E$97 -> 200.13978 | E98: =E91*$E$97 -> 209.33981 | F98: =F91*$E$97 -> 218.98675 | G98: =G91*$E$97 -> 229.10335 | H98: =H91*$E$97 -> 239.71359 | I98: =I91*$E$97 -> 250.84269 | J98: =J91*$E$97 -> 262.51724 | ... N98: =N91*$E$97 -> 315.25294
B99: Dividends (index pts) | D99: =D95*$E$97 -> 186.14588 | E99: =E95*$E$97 -> 188.24207 | F99: =F95*$E$97 -> 207.17364 | G99: =G95*$E$97 -> 216.71511 | H99: =H95*$E$97 -> 226.72088 | I99: =I95*$E$97 -> 237.2146 | J99: =J95*$E$97 -> 248.22123 | K99: =K95*$E$97 -> 259.76702 | ... N99: =N95*$E$97 -> 297.92348
B100: Book value (index pts) | C100: =C94*$E$97 -> 221.25433 | D100: =D94*$E$97 -> 235.24823 | E100: =E94*$E$97 -> 256.34597 | F100: =F94*$E$97 -> 268.15907 | G100: =G94*$E$97 -> 280.54731 | H100: =H94*$E$97 -> 293.54002 | I100: =I94*$E$97 -> 307.1681 | J100: =J94*$E$97 -> 321.46412 | ... N100: =N94*$E$97 -> 386.04134
B103: Caixa Seguridade (CXSE3)
B104: Line | C104: 2026 | D104: 2027 | E104: 2028 | F104: 2029 | G104: 2030 | H104: 2031 | I104: 2032 | J104: 2033 | K104: 2034 | L104: 2035 | M104: 2036 | N104: 2037 | P104: How it is calculated / source
B105: Net income (R$ mn) | C105: 4676.444 | D105: 5099.889 | E105: 5562.143 | F105: =E105*(1+F106) -> 6039.3255 | G105: =F105*(1+G106) -> 6528.162 | H105: =G105*(1+H106) -> 7024.9116 | I105: =H105*(1+I106) -> 7525.3976 | J105: =I105*(1+J106) -> 8025.0506 | K105: =J105*(1+K106) -> 8518.9657 | L105: =K105*(1+L106) -> 9001.9722 | M105: =L105*(1+M106) -> 9468.7145 | N105: =M105*(1+N106) -> 9913.744 | P105: 2026-28: consensus (BEST_NET_INCOME); then previous x (1 + growth).
B106: Net income growth | D106: =D105/C105-1 -> 0.090548502 | E106: =E105/D105-1 -> 0.090640012 | F106: =$E$106+(g_-$E$106)*1/9 -> 0.085791122 | G106: =$E$106+(g_-$E$106)*2/9 -> 0.080942232 | H106: =$E$106+(g_-$E$106)*3/9 -> 0.076093341 | I106: =$E$106+(g_-$E$106)*4/9 -> 0.071244451 | J106: =$E$106+(g_-$E$106)*5/9 -> 0.066395561 | K106: =$E$106+(g_-$E$106)*6/9 -> 0.061546671 | L106: =$E$106+(g_-$E$106)*7/9 -> 0.05669778 | M106: =$E$106+(g_-$E$106)*8/9 -> 0.05184889 | N106: =$E$106+(g_-$E$106)*9/9 -> 0.047 | P106: 2027-28: consensus; 2029-37: linear from the 2028 growth to g in 2037.
B107: ROE | C107: 0.3916 | D107: 0.4101 | E107: 0.4234 | F107: =$E$107 -> 0.4234 | G107: =$E$107 -> 0.4234 | H107: =$E$107 -> 0.4234 | I107: =$E$107 -> 0.4234 | J107: =$E$107 -> 0.4234 | K107: =$E$107 -> 0.4234 | L107: =$E$107 -> 0.4234 | M107: =$E$107 -> 0.4234 | N107: =$E$107 -> 0.4234 | P107: 2026-28: consensus (BEST_ROE); 2029-37: held at FY28, as the analysts keep ROE about flat.
B108: Book value = net income / ROE (R$ mn) | C108: =C105/C107 -> 11941.89 | D108: =D105/D107 -> 12435.721 | E108: =E105/E107 -> 13136.852 | F108: =F105/F107 -> 14263.877 | G108: =G105/G107 -> 15418.427 | H108: =H105/H107 -> 16591.667 | I108: =I105/I107 -> 17773.731 | J108: =J105/J107 -> 18953.828 | ... N108: =N105/N107 -> 23414.606
B109: Dividends = net income - change in book value (R$ mn) | D109: =D105-(D108-C108) -> 4606.0581 | E109: =E105-(E108-D108) -> 4861.0119 | F109: =F105-(F108-E108) -> 4912.3002 | G109: =G105-(G108-F108) -> 5373.6119 | H109: =H105-(H108-G108) -> 5851.672 | I109: =I105-(I108-H108) -> 6343.3334 | J109: =J105-(J108-I108) -> 6844.9538 | K109: =K105-(K108-J108) -> 7352.4208 | ... N109: =N105-(N108-M108) -> 8862.6586 | P109: Clean surplus: what is not retained to grow the book value is paid out (dividends, IoC, buybacks).
B110: Payout = dividends / net income | D110: =D109/D105 -> 0.90316831 | E110: =E109/E105 -> 0.87394587 | F110: =F109/F105 -> 0.81338558 | G110: =G109/G105 -> 0.82314317 | H110: =H109/H105 -> 0.8329887 | I110: =I109/I105 -> 0.84292336 | J110: =J109/J105 -> 0.85294836 | K110: =K109/K105 -> 0.86306495 | ... N110: =N109/N105 -> 0.89397694 | P110: Converges to about 1 - g / ROE as growth reaches g.
B111: Index points / market cap (R$ mn) | C111: 895.11912 | D111: 63090 | E111: =C111/D111 -> 0.014187972 | P111: Members sheet of the main model (Oct-5-2026).
B112: Net income (index pts) | C112: =C105*$E$111 -> 66.349254 | D112: =D105*$E$111 -> 72.35708 | E112: =E105*$E$111 -> 78.915526 | F112: =F105*$E$111 -> 85.685778 | G112: =G105*$E$111 -> 92.621376 | H112: =H105*$E$111 -> 99.669246 | I112: =I105*$E$111 -> 106.77013 | J112: =J105*$E$111 -> 113.85919 | ... N112: =N105*$E$111 -> 140.65592
B113: Dividends (index pts) | D113: =D109*$E$111 -> 65.350622 | E113: =E109*$E$111 -> 68.967898 | F113: =F109*$E$111 -> 69.695576 | G113: =G109*$E$111 -> 76.240653 | H113: =H109*$E$111 -> 83.023356 | I113: =I109*$E$111 -> 89.999034 | J113: =J109*$E$111 -> 97.116009 | K113: =K109*$E$111 -> 104.31594 | ... N113: =N109*$E$111 -> 125.74315
B114: Book value (index pts) | C114: =C108*$E$111 -> 169.43119 | D114: =D108*$E$111 -> 176.43765 | E114: =E108*$E$111 -> 186.38528 | F114: =F108*$E$111 -> 202.37548 | G114: =G108*$E$111 -> 218.7562 | H114: =H108*$E$111 -> 235.40209 | I114: =I108*$E$111 -> 252.17319 | J114: =J108*$E$111 -> 268.91637 | ... N114: =N108*$E$111 -> 332.20576
B117: Santander (SANB11)
...

Sheet Analyst Models
B1: Financials - analysts' projections, aggregated (index points)
B2: Net income and dividends of the XP Financials models (R$ mn, files in inputs/analyst_models/Financials/). After a model's last year: net income grows at g and the payout stays at its last value, as the model's own perpetuity. Index points = R$ x the member's index points / market cap (Members sheet of the main model, Oct-5-2026).
B3: Legend: | C3: input | D3: assumption | E3: formula
B5: Itaú Unibanco (ITUB4) | ITUB Model Official 2Q26_vCSStrategy.xlsx
B6: Line | C6: 2026 | D6: 2027 | E6: 2028 | F6: 2029 | G6: 2030 | H6: 2031 | I6: 2032 | J6: 2033 | K6: 2034 | L6: 2035 | M6: 2036 | N6: 2037 | P6: How it is calculated / source
B7: Net income (R$ mn) | C7: 50922 | D7: 56028 | E7: 61318 | F7: 66407 | G7: 71853 | H7: 76890 | I7: 81937 | J7: 87124 | K7: 92891 | L7: 99086 | M7: 105569 | N7: 112362 | P7: Model: Income Statement r61 Recurring Net Income.
B8: Dividends + IoC (R$ mn) | C8: 29433 | D8: 36310 | E8: 42954 | F8: 47031 | G8: 52633 | H8: 58205 | I8: 62018 | J8: 65938 | K8: 72614 | L8: 77433 | M8: 83534 | N8: 90010 | P8: Model: Income Statement r66 Dividends/IoC Provisioned.
B9: Payout | C9: =C8/C7 -> 0.57800165 | D9: =D8/D7 -> 0.64806882 | E9: =E8/E7 -> 0.70051208 | F9: =F8/F7 -> 0.70822353 | G9: =G8/G7 -> 0.73250943 | H9: =H8/H7 -> 0.75699051 | I9: =I8/I7 -> 0.75689859 | J9: =J8/J7 -> 0.75682935 | ... N9: =N8/N7 -> 0.80107154 | P9: Dividends / net income.
B10: Index points / market cap (R$ mn) | C10: 19089.265 | D10: 564225.23 | E10: =C10/D10 -> 0.033832704 | P10: C: index points (Members); D: market cap (Members); E: factor that turns R$ mn into index points.
B11: Net income (index pts) | C11: =C7*$E$10 -> 1722.829 | D11: =D7*$E$10 -> 1895.5787 | E11: =E7*$E$10 -> 2074.5537 | F11: =F7*$E$10 -> 2246.7284 | G11: =G7*$E$10 -> 2430.9813 | H11: =H7*$E$10 -> 2601.3966 | I11: =I7*$E$10 -> 2772.1503 | J11: =J7*$E$10 -> 2947.6405 | ... N11: =N7*$E$10 -> 3801.5103
B12: Dividends (index pts) | C12: =C8*$E$10 -> 995.79798 | D12: =D8*$E$10 -> 1228.4655 | E12: =E8*$E$10 -> 1453.25 | F12: =F8*$E$10 -> 1591.1859 | G12: =G8*$E$10 -> 1780.7167 | H12: =H8*$E$10 -> 1969.2325 | I12: =I8*$E$10 -> 2098.2366 | J12: =J8*$E$10 -> 2230.8608 | ... N12: =N8*$E$10 -> 3045.2817
B15: Bradesco (BBDC4 + BBDC3) | BBDC Model Official 2Q26_vCSStrategy.xlsx
B16: Line | C16: 2026 | D16: 2027 | E16: 2028 | F16: 2029 | G16: 2030 | H16: 2031 | I16: 2032 | J16: 2033 | K16: 2034 | L16: 2035 | M16: 2036 | N16: 2037 | P16: How it is calculated / source
B17: Net income (R$ mn) | C17: 28221 | D17: 31178 | E17: 34548 | F17: 37971 | G17: 41533 | H17: 44699 | I17: 47964 | J17: 51319 | K17: 54749 | L17: 58243 | M17: 61788 | N17: 65372 | P17: Model: Income Statement r73 Recurring Net Income.
B18: Dividends + IoC (R$ mn) | C18: 13727 | D18: 15095 | E18: 16726 | F18: 19903 | G18: 23431 | H18: 26111 | I18: 28978 | J18: 31517 | K18: 34171 | L18: 36934 | M18: 39801 | N18: 42763 | P18: Model: Income Statement r78 Dividends/IoC Provisioned - Net.
B19: Payout | C19: =C18/C17 -> 0.48641083 | D19: =D18/D17 -> 0.48415549 | E19: =E18/E17 -> 0.48413801 | F19: =F18/F17 -> 0.52416318 | G19: =G18/G17 -> 0.56415381 | H19: =H18/H17 -> 0.58415177 | I19: =I18/I17 -> 0.60416145 | J19: =J18/J17 -> 0.61413901 | ... N19: =N18/N17 -> 0.65414857 | P19: Dividends / net income.
B20: Index points / market cap (R$ mn) | C20: 10039.703 | D20: 226447.76 | E20: =C20/D20 -> 0.044335627 | P20: C: index points (Members); D: market cap (Members); E: factor that turns R$ mn into index points.
B21: Net income (index pts) | C21: =C17*$E$20 -> 1251.1957 | D21: =D17*$E$20 -> 1382.2962 | E21: =E17*$E$20 -> 1531.7072 | F21: =F17*$E$20 -> 1683.4681 | G21: =G17*$E$20 -> 1841.3916 | H21: =H17*$E$20 -> 1981.7582 | I21: =I17*$E$20 -> 2126.514 | J21: =J17*$E$20 -> 2275.26 | ... N21: =N17*$E$20 -> 2898.3086
B22: Dividends (index pts) | C22: =C18*$E$20 -> 608.59515 | D22: =D18*$E$20 -> 669.24629 | E22: =E18*$E$20 -> 741.5577 | F22: =F18*$E$20 -> 882.41199 | G22: =G18*$E$20 -> 1038.8281 | H22: =H18*$E$20 -> 1157.6476 | I22: =I18*$E$20 -> 1284.7578 | J22: =J18*$E$20 -> 1397.326 | ... N22: =N18*$E$20 -> 1895.9244
B25: B3 (B3SA3) | B3SA3 Model Official 3Q25_vCSStrategy.xlsx
B26: Line | C26: 2026 | D26: 2027 | E26: 2028 | F26: 2029 | G26: 2030 | H26: 2031 | I26: 2032 | J26: 2033 | K26: 2034 | L26: 2035 | M26: 2036 | N26: 2037 | P26: How it is calculated / source
B27: Net income (R$ mn) | C27: 6537 | D27: 7215 | E27: 7971 | F27: 8876 | G27: 9881 | H27: 10905 | I27: 11848 | J27: 13062 | K27: =J27*(1+gAn) -> 13845.72 | L27: =K27*(1+gAn) -> 14676.463 | M27: =L27*(1+gAn) -> 15557.051 | N27: =M27*(1+gAn) -> 16490.474 | P27: Model: Income Statement r52 Recurring Net Income. After 2033: x (1 + g).
B28: Dividends + IoC (R$ mn) | C28: 6203 | D28: 6859 | E28: 7612 | F28: 8513 | G28: 9413 | H28: 10358 | I28: 11364 | J28: 12526 | K28: =K27*J29 -> 13277.56 | L28: =L27*J29 -> 14074.214 | M28: =M27*J29 -> 14918.666 | N28: =N27*J29 -> 15813.786 | P28: Model: Income Statement r58 Dividends/IoC. After 2033: net income x the 2033 payout.
B29: Payout | C29: =C28/C27 -> 0.94890623 | D29: =D28/D27 -> 0.95065835 | E29: =E28/E27 -> 0.95496174 | F29: =F28/F27 -> 0.9591032 | G29: =G28/G27 -> 0.95263637 | H29: =H28/H27 -> 0.94983952 | I29: =I28/I27 -> 0.95914922 | J29: =J28/J27 -> 0.95896494 | ... N29: =N28/N27 -> 0.95896494 | P29: Dividends / net income.
B30: Index points / market cap (R$ mn) | C30: 8337.4035 | D30: 112688.35 | E30: =C30/D30 -> 0.073986387 | P30: C: index points (Members); D: market cap (Members); E: factor that turns R$ mn into index points.
B31: Net income (index pts) | C31: =C27*$E$30 -> 483.64901 | D31: =D27*$E$30 -> 533.81178 | E31: =E27*$E$30 -> 589.74549 | F31: =F27*$E$30 -> 656.70317 | G31: =G27*$E$30 -> 731.05949 | H31: =H27*$E$30 -> 806.82155 | I31: =I27*$E$30 -> 876.59071 | J31: =J27*$E$30 -> 966.41018 | ... N31: =N27*$E$30 -> 1220.0706
B32: Dividends (index pts) | C32: =C28*$E$30 -> 458.93756 | D32: =D28*$E$30 -> 507.47263 | E32: =E28*$E$30 -> 563.18437 | F32: =F28*$E$30 -> 629.84611 | G32: =G28*$E$30 -> 696.43386 | H32: =H28*$E$30 -> 766.35099 | I32: =I28*$E$30 -> 840.7813 | J32: =J28*$E$30 -> 926.75348 | ... N32: =N28*$E$30 -> 1170.0049
B35: BTG Pactual (BPAC11) | BPAC Model Official 3Q25_vCSStrategy.xlsx
B36: Line | C36: 2026 | D36: 2027 | E36: 2028 | F36: 2029 | G36: 2030 | H36: 2031 | I36: 2032 | J36: 2033 | K36: 2034 | L36: 2035 | M36: 2036 | N36: 2037 | P36: How it is calculated / source
B37: Net income (R$ mn) | C37: 19103 | D37: 21961 | E37: 25043 | F37: 28704 | G37: 32446 | H37: 36374 | I37: 40448 | J37: 44253 | K37: 48504 | L37: 52818 | M37: 57507 | N37: =M37*(1+gAn) -> 60957.42 | P37: Model: Income Statement r50 Net Income. After 2036: x (1 + g).
B38: Dividends + IoC (R$ mn) | C38: 6686 | D38: 9882 | E38: 13774 | F38: 17222 | G38: 21090 | H38: 25462 | I38: 30336 | J38: 35403 | K38: 41228 | L38: 47536 | M38: 54632 | N38: =N37*M39 -> 57909.92 | P38: Model: Income Statement r56 Dividends/IoC. After 2036: net income x the 2036 payout.
B39: Payout | C39: =C38/C37 -> 0.34999738 | D39: =D38/D37 -> 0.44997951 | E39: =E38/E37 -> 0.55001398 | F39: =F38/F37 -> 0.59998606 | G39: =G38/G37 -> 0.65000308 | H39: =H38/H37 -> 0.7000055 | I39: =I38/I37 -> 0.75 | J39: =J38/J37 -> 0.80001356 | ... N39: =N38/N37 -> 0.95000609 | P39: Dividends / net income.
B40: Index points / market cap (R$ mn) | C40: 6925.2189 | D40: 305584.14 | E40: =C40/D40 -> 0.022662232 | P40: C: index points (Members); D: market cap (Members); E: factor that turns R$ mn into index points.
B41: Net income (index pts) | C41: =C37*$E$40 -> 432.91662 | D41: =D37*$E$40 -> 497.68528 | E41: =E37*$E$40 -> 567.53028 | F41: =F37*$E$40 -> 650.49672 | G41: =G37*$E$40 -> 735.29879 | H41: =H37*$E$40 -> 824.31604 | I41: =I37*$E$40 -> 916.64197 | J41: =J37*$E$40 -> 1002.8718 | ... N41: =N37*$E$40 -> 1381.4312
B42: Dividends (index pts) | C42: =C38*$E$40 -> 151.51969 | D42: =D38*$E$40 -> 223.94818 | E42: =E38*$E$40 -> 312.14959 | F42: =F38*$E$40 -> 390.28897 | G42: =G38*$E$40 -> 477.94648 | H42: =H38*$E$40 -> 577.02576 | I42: =I38*$E$40 -> 687.48148 | J42: =J38*$E$40 -> 802.31101 | ... N42: =N38*$E$40 -> 1312.3681
B45: Banco do Brasil (BBAS3) | BBAS Model Official 2Q26_vCSStrategy.xlsx
B46: Line | C46: 2026 | D46: 2027 | E46: 2028 | F46: 2029 | G46: 2030 | H46: 2031 | I46: 2032 | J46: 2033 | K46: 2034 | L46: 2035 | M46: 2036 | N46: 2037 | P46: How it is calculated / source
B47: Net income (R$ mn) | C47: =C48/C49 -> 16916.667 | D47: =D48/D49 -> 23713.333 | E47: =E48/E49 -> 29783.333 | F47: =F48/F49 -> 33300 | G47: =G48/G49 -> 36153.333 | H47: =H48/H49 -> 39662.857 | I47: =I48/I49 -> 42732.5 | J47: =J48/J49 -> 45604.444 | ... N47: =N48/N49 -> 55570.909 | P47: Model: = dividends / payout.
B48: Dividends + IoC (R$ mn) | C48: 4060 | D48: 7114 | E48: 8935 | F48: 9990 | G48: 10846 | H48: 13882 | I48: 17093 | J48: 20522 | K48: 24056 | L48: 27771 | M48: 29140 | N48: 30564 | P48: Model: Valuation r5 Total Return; payout: Model r26.
B49: Payout | C49: 0.24 | D49: 0.3 | E49: 0.3 | F49: 0.3 | G49: 0.3 | H49: 0.35 | I49: 0.4 | J49: 0.45 | K49: 0.5 | L49: 0.55 | M49: 0.55 | N49: 0.55 | P49: Model: Model r26 (input).
B50: Index points / market cap (R$ mn) | C50: 5397.318 | D50: 138571.57 | E50: =C50/D50 -> 0.038949679 | P50: C: index points (Members); D: market cap (Members); E: factor that turns R$ mn into index points.
B51: Net income (index pts) | C51: =C47*$E$50 -> 658.89873 | D51: =D47*$E$50 -> 923.62672 | E51: =E47*$E$50 -> 1160.0513 | F51: =F47*$E$50 -> 1297.0243 | G51: =G47*$E$50 -> 1408.1607 | H51: =H47*$E$50 -> 1544.8556 | I51: =I47*$E$50 -> 1664.4172 | J51: =J47*$E$50 -> 1776.2785 | ... N51: =N47*$E$50 -> 2164.4691
B52: Dividends (index pts) | C52: =C48*$E$50 -> 158.1357 | D52: =D48*$E$50 -> 277.08802 | E52: =E48*$E$50 -> 348.01538 | F52: =F48*$E$50 -> 389.10729 | G52: =G48*$E$50 -> 422.44822 | H52: =H48*$E$50 -> 540.69944 | I52: =I48*$E$50 -> 665.76686 | J52: =J48*$E$50 -> 799.32531 | ... N52: =N48*$E$50 -> 1190.458
B55: Caixa Seguridade (CXSE3) | CXSE3 Model Official 3Q25_vCSStrategy.xlsx
B56: Line | C56: 2026 | D56: 2027 | E56: 2028 | F56: 2029 | G56: 2030 | H56: 2031 | I56: 2032 | J56: 2033 | K56: 2034 | L56: 2035 | M56: 2036 | N56: 2037 | P56: How it is calculated / source
B57: Net income (R$ mn) | C57: 4565.538 | D57: 4903.673 | E57: 5256.803 | F57: 5652.253 | G57: 6018.714 | H57: 6421.658 | I57: 6858 | J57: 7330.546 | K57: 7842.343 | L57: 8396.709 | M57: 8997.253 | N57: =M57*(1+gAn) -> 9537.0882 | P57: Model: Income Statement r54 Managerial Net Income (R$ thousand / 1,000). After 2036: x (1 + g).
B58: Dividends + IoC (R$ mn) | C58: 4208 | D58: 4520 | E58: 4845 | F58: 5210 | G58: 5547 | H58: 5919 | I58: 6321 | J58: 6756 | K58: 7228 | L58: 7739 | M58: 8293 | N58: =N57*M59 -> 8790.58 | P58: Model: Valuation r2 Dividend. After 2036: net income x the 2036 payout.
B59: Payout | C59: =C58/C57 -> 0.92168765 | D59: =D58/D57 -> 0.92175804 | E59: =E58/E57 -> 0.92166284 | F59: =F58/F57 -> 0.92175633 | G59: =G58/G57 -> 0.92162545 | H59: =H58/H57 -> 0.92172458 | I59: =I58/I57 -> 0.92169729 | J59: =J58/J57 -> 0.92162303 | ... N59: =N58/N57 -> 0.92172578 | P59: Dividends / net income.
B60: Index points / market cap (R$ mn) | C60: 895.11912 | D60: 63090 | E60: =C60/D60 -> 0.014187972 | P60: C: index points (Members); D: market cap (Members); E: factor that turns R$ mn into index points.
B61: Net income (index pts) | C61: =C57*$E$60 -> 64.775723 | D61: =D57*$E$60 -> 69.573173 | E61: =E57*$E$60 -> 74.583371 | F61: =F57*$E$60 -> 80.194005 | G61: =G57*$E$60 -> 85.393343 | H61: =H57*$E$60 -> 91.110301 | I61: =I57*$E$60 -> 97.301109 | J61: =J57*$E$60 -> 104.00558 | ... N61: =N57*$E$60 -> 135.31194
B62: Dividends (index pts) | C62: =C58*$E$60 -> 59.702984 | D62: =D58*$E$60 -> 64.129631 | E62: =E58*$E$60 -> 68.740722 | F62: =F58*$E$60 -> 73.919332 | G62: =G58*$E$60 -> 78.700678 | H62: =H58*$E$60 -> 83.978603 | I62: =I58*$E$60 -> 89.682168 | J62: =J58*$E$60 -> 95.853936 | ... N62: =N58*$E$60 -> 124.7205
B65: Santander (SANB11) | SANB Model Official 4Q25_vCSStrategy.xlsx
B66: Line | C66: 2026 | D66: 2027 | E66: 2028 | F66: 2029 | G66: 2030 | H66: 2031 | I66: 2032 | J66: 2033 | K66: 2034 | L66: 2035 | M66: 2036 | N66: 2037 | P66: How it is calculated / source
B67: Net income (R$ mn) | C67: 17399 | D67: 19672 | E67: 20985 | F67: 22473 | G67: 23918 | H67: 25510 | I67: 27201 | J67: 28935 | K67: 30589 | L67: 32224 | M67: 33739 | N67: =M67*(1+gAn) -> 35763.34 | P67: Model: IS r95 Recurring Net Income. After 2036: x (1 + g).
B68: Dividends + IoC (R$ mn) | C68: 11309 | D68: 12787 | E68: 14689 | F68: 15731 | G68: 17939 | H68: 19132 | I68: 20400 | J68: 21702 | K68: 22942 | L68: 24168 | M68: 25304 | N68: =N67*M69 -> 26822.24 | P68: Model: IS r103 Dividends/IoC Provisioned. After 2036: net income x the 2036 payout.
B69: Payout | C69: =C68/C67 -> 0.64997988 | D69: =D68/D67 -> 0.65001017 | E69: =E68/E67 -> 0.69997617 | F69: =F68/F67 -> 0.69999555 | G69: =G68/G67 -> 0.7500209 | H69: =H68/H67 -> 0.7499804 | I69: =I68/I67 -> 0.74997243 | J69: =J68/J67 -> 0.75002592 | ... N69: =N68/N67 -> 0.74999259 | P69: Dividends / net income.
B70: Index points / market cap (R$ mn) | C70: 735.15958 | D70: 109308.45 | E70: =C70/D70 -> 0.0067255513 | P70: C: index points (Members); D: market cap (Members); E: factor that turns R$ mn into index points.
B71: Net income (index pts) | C71: =C67*$E$70 -> 117.01787 | D71: =D67*$E$70 -> 132.30505 | E71: =E67*$E$70 -> 141.13569 | F71: =F67*$E$70 -> 151.14332 | G71: =G67*$E$70 -> 160.86174 | H71: =H67*$E$70 -> 171.56881 | I71: =I67*$E$70 -> 182.94172 | J71: =J67*$E$70 -> 194.60383 | ... N71: =N67*$E$70 -> 240.52818
B72: Dividends (index pts) | C72: =C68*$E$70 -> 76.05926 | D72: =D68*$E$70 -> 85.999625 | E72: =E68*$E$70 -> 98.791624 | F72: =F68*$E$70 -> 105.79965 | G72: =G68*$E$70 -> 120.64967 | H72: =H68*$E$70 -> 128.67325 | I72: =I68*$E$70 -> 137.20125 | J72: =J68*$E$70 -> 145.95792 | ... N72: =N68*$E$70 -> 180.39435
B75: Itaúsa (ITSA4) | no model: Itaú's net income path and payout (holding of Itaú)
B76: Line | C76: 2026 | D76: 2027 | E76: 2028 | F76: 2029 | G76: 2030 | H76: 2031 | I76: 2032 | J76: 2033 | K76: 2034 | L76: 2035 | M76: 2036 | N76: 2037 | P76: How it is calculated / source
B77: Net income (R$ mn) = consensus FY28 x Itaú's net income / Itaú's 2028 | C77: =$C$81*C7/$E$7 -> 19150.353 | D77: =$C$81*D7/$E$7 -> 21070.578 | E77: =$C$81*E7/$E$7 -> 23060 | F77: =$C$81*F7/$E$7 -> 24973.832 | G77: =$C$81*G7/$E$7 -> 27021.921 | H77: =$C$81*H7/$E$7 -> 28916.198 | I77: =$C$81*I7/$E$7 -> 30814.234 | J77: =$C$81*J7/$E$7 -> 32764.921 | ... N77: =$C$81*N7/$E$7 -> 42256.233 | P77: Itaú's path scaled to Itaúsa's FY28 consensus (Members).
B78: Dividends (R$ mn) = net income x Itaú's payout | C78: =C77*C9 -> 11068.935 | D78: =D77*D9 -> 13655.184 | E78: =E77*E9 -> 16153.809 | F78: =F77*F9 -> 17687.055 | G78: =G77*G9 -> 19793.812 | H78: =H77*H9 -> 21889.287 | I78: =I77*I9 -> 23323.251 | J78: =J77*J9 -> 24797.454 | ... N78: =N77*N9 -> 33850.266
B79: Payout | C79: =C78/C77 -> 0.57800165 | D79: =D78/D77 -> 0.64806882 | E79: =E78/E77 -> 0.70051208 | F79: =F78/F77 -> 0.70822353 | G79: =G78/G77 -> 0.73250943 | H79: =H78/H77 -> 0.75699051 | I79: =I78/I77 -> 0.75689859 | J79: =J78/J77 -> 0.75682935 | ... N79: =N78/N77 -> 0.80107154
B80: Index points / market cap (R$ mn) | C80: 7020.6236 | D80: 179573.13 | E80: =C80/D80 -> 0.03909618
B81: Itaúsa net income FY28, Bloomberg consensus (R$ mn) | C81: 23060
B82: Net income (index pts) | C82: =C77*$E$80 -> 748.70563 | D82: =D77*$E$80 -> 823.77909 | E82: =E77*$E$80 -> 901.55791 | F82: =F77*$E$80 -> 976.38142 | G82: =G77*$E$80 -> 1056.4539 | H82: =H77*$E$80 -> 1130.5129 | I82: =I77*$E$80 -> 1204.7188 | J82: =J77*$E$80 -> 1280.9833 | ... N82: =N77*$E$80 -> 1652.0573
B83: Dividends (index pts) | C83: =C78*$E$80 -> 432.75309 | D83: =D78*$E$80 -> 533.86555 | E83: =E78*$E$80 -> 631.55221 | F83: =F78*$E$80 -> 691.4963 | G83: =G78*$E$80 -> 773.86244 | H83: =H78*$E$80 -> 855.7875 | I83: =I78*$E$80 -> 911.85 | J83: =J78*$E$80 -> 969.48572 | ... N83: =N78*$E$80 -> 1323.4161
B86: Aggregate of the modeled members (index points): what the box takes from the analysts
B87: Line | C87: 2026 | D87: 2027 | E87: 2028 | F87: 2029 | G87: 2030 | H87: 2031 | I87: 2032 | J87: 2033 | K87: 2034 | L87: 2035 | M87: 2036 | N87: 2037 | P87: How it is calculated / source
B88: Net income (index pts) | C88: =C11+C21+C31+C41+C51+C61+C71+C82 -> 5479.9883 | D88: =D11+D21+D31+D41+D51+D61+D71+D82 -> 6258.656 | E88: =E11+E21+E31+E41+E51+E61+E71+E82 -> 7040.865 | F88: =F11+F21+F31+F41+F51+F61+F71+F82 -> 7742.1394 | G88: =G11+G21+G31+G41+G51+G61+G71+G82 -> 8449.6009 | H88: =H11+H21+H31+H41+H51+H61+H71+H82 -> 9152.3399 | I88: =I11+I21+I31+I41+I51+I61+I71+I82 -> 9841.2758 | J88: =J11+J21+J31+J41+J51+J61+J71+J82 -> 10548.054 | ... N88: =N11+N21+N31+N41+N51+N61+N71+N82 -> 13493.687
B89: Dividends (index pts) | C89: =C12+C22+C32+C42+C52+C62+C72+C83 -> 2941.5014 | D89: =D12+D22+D32+D42+D52+D62+D72+D83 -> 3590.2154 | E89: =E12+E22+E32+E42+E52+E62+E72+E83 -> 4217.2416 | F89: =F12+F22+F32+F42+F52+F62+F72+F83 -> 4754.0555 | G89: =G12+G22+G32+G42+G52+G62+G72+G83 -> 5389.5861 | H89: =H12+H22+H32+H42+H52+H62+H72+H83 -> 6079.3956 | I89: =I12+I22+I32+I42+I52+I62+I72+I83 -> 6715.7575 | J89: =J12+J22+J32+J42+J52+J62+J72+J83 -> 7367.8742 | ... N89: =N12+N22+N32+N42+N52+N62+N72+N83 -> 10242.568
B90: Net income growth | D90: =D88/C88-1 -> 0.14209296 | E90: =E88/D88-1 -> 0.12498035 | F90: =F88/E88-1 -> 0.099600603 | G90: =G88/F88-1 -> 0.091378032 | H90: =H88/G88-1 -> 0.083168313 | I90: =I88/H88-1 -> 0.075274289 | J90: =J88/I88-1 -> 0.071817703 | K90: =K88/J88-1 -> 0.066585954 | ... N90: =N88/M88-1 -> 0.059515705 | P90: Used for the box from 2029.
B91: Payout = dividends / net income | C91: =C89/C88 -> 0.53677148 | D91: =D89/D88 -> 0.57363999 | E91: =E89/E88 -> 0.5989664 | F91: =F89/F88 -> 0.61404933 | G91: =G89/G88 -> 0.63785097 | H91: =H89/H88 -> 0.66424496 | I91: =I89/I88 -> 0.6824072 | J91: =J89/J88 -> 0.69850557 | ... N91: =N89/N88 -> 0.75906369 | P91: Used for the box in every year.
B92: Coverage: index points of the modeled members / Financials box | C92: =(C10+C20+C30+C40+C50+C60+C70+C80)/'DDM Financials'!$C$7 -> 0.95917278 | P92: BB Seguridade and Porto Seguro have no model: they take the aggregate path.

Sheet Model Parameters
B1: Financials - valuation parameters of the analysts' models
B2: Valuation sheet of each model. Ke = (NTN-B + long-term IPCA) x 0.85 + beta x ERP; g = long-term IPCA + real GDP (Macro sheet).
B3: Legend: | C3: input | D3: assumption | E3: formula
B5: Member | C5: Ke | D5: NTN-B | E5: IPCA LT | F5: Risk free = (NTN-B + IPCA) x 0.85 | G5: ERP | H5: Beta | I5: g | J5: Perpetuity share of value | K5: Last explicit year | L5: Value date | M5: Index points
B6: ITUB4 + ITSA4 | C6: 0.1513 | D6: 0.076 | E6: 0.04 | F6: 0.0986 | G6: 0.055 | H6: 0.958 | I6: 0.06 | J6: 0.4623 | K6: 2037 | L6: End-2027 | M6: 26109.889
B7: BBDC4 + BBDC3 | C7: 0.1619 | D7: 0.076 | E7: 0.04 | F7: 0.0986 | G7: 0.055 | H7: 1.15 | I7: 0.06 | J7: 0.4371 | K7: 2037 | L7: End-2027 | M7: 10039.703
B8: B3SA3 | C8: 0.1583 | D8: 0.0732 | E8: 0.04 | F8: 0.0962 | G8: 0.055 | H8: 1.129 | I8: 0.06 | J8: 0.4358 | K8: 2033 | L8: n/a | M8: 8337.403
B9: BPAC11 | C9: 0.1637 | D9: 0.0741 | E9: 0.04 | F9: 0.097 | G9: 0.055 | H9: 1.213 | I9: 0.06 | J9: 0.5183 | K9: 2036 | L9: End-2026 | M9: 6925.219
B10: BBAS3 | C10: 0.1809 | D10: 0.081 | E10: 0.04 | F10: 0.1029 | G10: 0.06 | H10: 1.3 | I10: 0.06 | J10: 0.4185 | K10: 2037 | L10: End-2027 | M10: 5397.318
B11: CXSE3 | C11: 0.1386 | D11: 0.0751 | E11: 0.04 | F11: 0.0978 | G11: 0.055 | H11: 0.742 | I11: 0.06 | J11: 0.5003 | K11: 2036 | L11: End-2026 | M11: 895.119
B12: SANB11 | C12: 0.149 | D12: 0.0749 | E12: 0.04 | F12: 0.0977 | G12: 0.05 | H12: 1.027 | I12: 0.06 | J12: 0.4541 | K12: 2036 | L12: End-2026 | M12: 735.16
B13: Weighted by index points | C13: =SUMPRODUCT(C6:C12,$M$6:$M$12)/SUM($M$6:$M$12) -> 0.15809943 | D13: =SUMPRODUCT(D6:D12,$M$6:$M$12)/SUM($M$6:$M$12) -> 0.075809542 | F13: =SUMPRODUCT(F6:F12,$M$6:$M$12)/SUM($M$6:$M$12) -> 0.098441557 | G13: =SUMPRODUCT(G6:G12,$M$6:$M$12)/SUM($M$6:$M$12) -> 0.055398885 | H13: =SUMPRODUCT(H6:H12,$M$6:$M$12)/SUM($M$6:$M$12) -> 1.0747443 | I13: =SUMPRODUCT(I6:I12,$M$6:$M$12)/SUM($M$6:$M$12) -> 0.06 | J13: =SUMPRODUCT(J6:J12,$M$6:$M$12)/SUM($M$6:$M$12) -> 0.45725984
B15: Itaúsa takes Itaú's parameters; Bradesco's two share classes are added. Source: Valuation sheet of each file (Ke, NTN-B, risk free, ERP, beta, g, 'Perpetuity' = PV of the terminal value / fair equity value).
