Workbook
Name BetaAn: 'Model Parameters'!$H$13
Name ERPAn: 'Model Parameters'!$G$13
Name g_: 'DDM Financials'!$F$20
Name gAn: 'DDM Financials'!$D$20
Name NExp: 'DDM Financials'!$F$21
Name TVx: 'DDM Financials'!$F$22

Sheet DDM Financials
B1: Financials - FCFE / bank DDM, the analysts' logic on the box consensus (end-2027)
B2: Consensus 2026-28 summed from the members (Box Consensus); the projection is done for the box: ROE held, growth fading to g, cash to shareholders = net income - the increase in book value; Gordon perpetuity on the last explicit year.
B3: Legend: | C3: input | D3: assumption | E3: formula
B5: 1. Inputs
B6: Item | C6: Value | P6: Source / note
B7: Financials, index points today | C7: ='Box Consensus'!C17 -> 0 | P7: Members' weight x Ibovespa close of Oct-5-2026 (Box Consensus; Box Shares!C7 of the main model).
B8: Long-term IPCA | C8: 0.04 | P8: Analysts' Macro sheet and the house (Target!B63).
B9: Long-term real GDP growth | C9: 0.02 | P9: Analysts' Macro sheet.
B10: Share of the risk free kept after tax (analysts' formula) | C10: 0.85 | P10: Analysts: (NTN-B + IPCA) x 0.85.
B11: Earnings beta x normalization (domestic cycle) | C11: 0.732791 | D11: 1.1868588 | P11: Box Earnings!I7 and I16 of the main model: shock of Financials = C x D x the Ibovespa ex-Commodities shock.
B12: Projection: 1 = box consensus with the analysts' logic; 2 = the analysts' own growth and payout (memo) | C12: 1 | P12: 2 applies the analysts' aggregate growth and payout (Analyst Models) to the box consensus of 2026-28.
B13: Box ROE from 2029 (blank = consensus FY28 of the box) | P13: Typed value replaces the FY28 box ROE after 2028.
B15: 2. House vs. analysts, variable by variable (choice: 1 = house, 2 = analysts)
B16: Variable | C16: House | D16: Analysts | E16: Choice | F16: Used | P16: House / analysts
B17: Risk free in Ke (base scenario) | C17: =$D$31 -> 0 | D17: =($D$31+$C$8)*$C$10 -> 0 | E17: 1 | F17: =IF(E17=1,C17,D17) -> 0 | P17: House: 5y NTN-B real rate, discounting nominal flows (Target!B55). Analysts: (NTN-B + long-term IPCA) x 0.85, nominal after tax.
B18: Equity risk premium | C18: 0.06 | D18: =ERPAn -> 0 | E18: 1 | F18: =IF(E18=1,C18,D18) -> 0 | P18: House: 6.0% (Target!B57). Analysts: 5.0-6.0%, 5.5% in most (Model Parameters).
B19: Beta | C19: 1.1490637 | D19: =BetaAn -> 0 | E19: 1 | F19: =IF(E19=1,C19,D19) -> 0 | P19: House: the box beta, weekly 5 years vs. the Ibovespa from the local box index (Box Betas). Analysts: each model's beta, weighted.
B20: Perpetuity growth (g) | C20: 0.047 | D20: =C8+C9 -> 0 | E20: 2 | F20: =IF(E20=1,C20,D20) -> 0 | P20: House: 4.7% (Target!B54). Analysts: long-term IPCA + real GDP.
B21: Explicit years after the value date | C21: 4 | D21: 10 | E21: 1 | F21: =IF(E21=1,C21,D21) -> 0 | P21: House: 2028-31 (4 years after end-2027). Analysts: 10-11 years (to 2036-37). Growth fades to g by the last explicit year.
B22: Extra periods in the discount of the terminal value | C22: 1 | D22: 0 | E22: 2 | F22: =IF(E22=1,C22,D22) -> 0 | P22: House: the TV is discounted one period more than the last flow (Target sheet, NPV layout). Analysts: the last year's factor.
B29: 3. Cost of equity by scenario
B30: Item | C30: Bear | D30: Base | E30: Bull | P30: How it is calculated
B31: 5-year real rate (NTN-B) | C31: 0.085 | D31: 0.0676 | E31: 0.055 | P31: Same scenarios as the other boxes.
B32: Risk free (choice in row 17) | C32: =IF($E$17=1,C31,(C31+$C$8)*$C$10) -> 0 | D32: =IF($E$17=1,D31,(D31+$C$8)*$C$10) -> 0 | E32: =IF($E$17=1,E31,(E31+$C$8)*$C$10) -> 0
B33: Ke = risk free + beta x ERP | C33: =C32+$F$19*$F$18 -> 0 | D33: =D32+$F$19*$F$18 -> 0 | E33: =E32+$F$19*$F$18 -> 0
B34: Ke - g | C34: =(C33-g_)*100 -> 0 | D34: =(D33-g_)*100 -> 0 | E34: =(E33-g_)*100 -> 0
B36: 4. Box projection (index points): consensus 2026-28, box-level projection after 2028
B37: Line | C37: 2026 | D37: 2027 | E37: 2028 | F37: 2029 | G37: 2030 | H37: 2031 | I37: 2032 | J37: 2033 | K37: 2034 | L37: 2035 | M37: 2036 | N37: 2037 | P37: How it is calculated / source
B38: Years after end-2027 (1 = explicit, grey = after the explicit years) | E38: =2028-2027 -> 0 | F38: =2029-2027 -> 0 | G38: =2030-2027 -> 0 | H38: =2031-2027 -> 0 | I38: =2032-2027 -> 0 | J38: =2033-2027 -> 0 | K38: =2034-2027 -> 0 | L38: =2035-2027 -> 0 | M38: =2036-2027 -> 0 | N38: =2037-2027 -> 0 | P38: Flows after the last explicit year are not used.
B39: Net income: 2026-28 consensus (sum of the members); then previous x (1 + growth) | C39: ='Box Consensus'!L17 -> 0 | D39: ='Box Consensus'!M17 -> 0 | E39: ='Box Consensus'!N17 -> 0 | F39: =E39*(1+F40) -> 0 | G39: =F39*(1+G40) -> 0 | H39: =G39*(1+H40) -> 0 | I39: =H39*(1+I40) -> 0 | J39: =I39*(1+J40) -> 0 | K39: =J39*(1+K40) -> 0 | L39: =K39*(1+L40) -> 0 | M39: =L39*(1+M40) -> 0 | N39: =M39*(1+N40) -> 0 | P39: Box Consensus.
B40: Net income growth: 2027-28 consensus; then linear from the 2028 growth to g in the last explicit year | D40: =D39/C39-1 -> 0 | E40: =E39/D39-1 -> 0 | F40: =IF(F38>=NExp,g_,$E$40+(g_-$E$40)*(F38-1)/(NExp-1)) -> 0 | G40: =IF(G38>=NExp,g_,$E$40+(g_-$E$40)*(G38-1)/(NExp-1)) -> 0 | H40: =IF(H38>=NExp,g_,$E$40+(g_-$E$40)*(H38-1)/(NExp-1)) -> 0 | I40: =IF(I38>=NExp,g_,$E$40+(g_-$E$40)*(I38-1)/(NExp-1)) -> 0 | J40: =IF(J38>=NExp,g_,$E$40+(g_-$E$40)*(J38-1)/(NExp-1)) -> 0 | K40: =IF(K38>=NExp,g_,$E$40+(g_-$E$40)*(K38-1)/(NExp-1)) -> 0 | L40: =IF(L38>=NExp,g_,$E$40+(g_-$E$40)*(L38-1)/(NExp-1)) -> 0 | M40: =IF(M38>=NExp,g_,$E$40+(g_-$E$40)*(M38-1)/(NExp-1)) -> 0 | N40: =IF(N38>=NExp,g_,$E$40+(g_-$E$40)*(N38-1)/(NExp-1)) -> 0 | P40: As the analysts: growth slows to about the perpetuity growth by the last explicit year.
B41: ROE: 2026-28 consensus of the box; then held at FY28 | C41: ='Box Consensus'!I17 -> 0 | D41: ='Box Consensus'!J17 -> 0 | E41: ='Box Consensus'!K17 -> 0 | F41: =IF(ISNUMBER($C$13),$C$13,$E$41) -> 0 | G41: =IF(ISNUMBER($C$13),$C$13,$E$41) -> 0 | H41: =IF(ISNUMBER($C$13),$C$13,$E$41) -> 0 | I41: =IF(ISNUMBER($C$13),$C$13,$E$41) -> 0 | J41: =IF(ISNUMBER($C$13),$C$13,$E$41) -> 0 | K41: =IF(ISNUMBER($C$13),$C$13,$E$41) -> 0 | L41: =IF(ISNUMBER($C$13),$C$13,$E$41) -> 0 | M41: =IF(ISNUMBER($C$13),$C$13,$E$41) -> 0 | N41: =IF(ISNUMBER($C$13),$C$13,$E$41) -> 0 | P41: Box ROE = sum of net income / sum of book value. The analysts keep ROE about flat (ITUB 25%, BBDC 17%).
B42: Book value: 2026-28 consensus (net income / ROE, summed); then net income / ROE | C42: ='Box Consensus'!O17 -> 0 | D42: ='Box Consensus'!P17 -> 0 | E42: ='Box Consensus'!Q17 -> 0 | F42: =F39/F41 -> 0 | G42: =G39/G41 -> 0 | H42: =H39/H41 -> 0 | I42: =I39/I41 -> 0 | J42: =J39/J41 -> 0 | K42: =K39/K41 -> 0 | L42: =L39/L41 -> 0 | M42: =M39/M41 -> 0 | N42: =N39/N41 -> 0
B43: Cash to shareholders = net income - increase in book value (dividends + buybacks) | D43: =D39-(D42-C42) -> 0 | E43: =E39-(E42-D42) -> 0 | F43: =F39-(F42-E42) -> 0 | G43: =G39-(G42-F42) -> 0 | H43: =H39-(H42-G42) -> 0 | I43: =I39-(I42-H42) -> 0 | J43: =J39-(J42-I42) -> 0 | K43: =K39-(K42-J42) -> 0 | ... N43: =N39-(N42-M42) -> 0 | P43: FCFE of a bank; as the analysts' equity roll-forward (equity = previous + net income - dividends).
B44: Payout | D44: =D43/D39 -> 0 | E44: =E43/E39 -> 0 | F44: =F43/F39 -> 0 | G44: =G43/G39 -> 0 | H44: =H43/H39 -> 0 | I44: =I43/I39 -> 0 | J44: =J43/J39 -> 0 | K44: =K43/K39 -> 0 | ... N44: =N43/N39 -> 0 | P44: Converges to about 1 - g / ROE as growth reaches g.
B45: Memo: analysts' aggregate net income growth | D45: ='Analyst Models'!D90 -> 0 | E45: ='Analyst Models'!E90 -> 0 | F45: ='Analyst Models'!F90 -> 0 | G45: ='Analyst Models'!G90 -> 0 | H45: ='Analyst Models'!H90 -> 0 | I45: ='Analyst Models'!I90 -> 0 | J45: ='Analyst Models'!J90 -> 0 | K45: ='Analyst Models'!K90 -> 0 | ... N45: ='Analyst Models'!N90 -> 0 | P45: Analyst Models.
B46: Memo: analysts' aggregate payout | C46: ='Analyst Models'!C91 -> 0 | D46: ='Analyst Models'!D91 -> 0 | E46: ='Analyst Models'!E91 -> 0 | F46: ='Analyst Models'!F91 -> 0 | G46: ='Analyst Models'!G91 -> 0 | H46: ='Analyst Models'!H91 -> 0 | I46: ='Analyst Models'!I91 -> 0 | J46: ='Analyst Models'!J91 -> 0 | ... N46: ='Analyst Models'!N91 -> 0 | P46: Analyst Models.
B47: Memo: net income on the analysts' path (consensus 2026-28, then their growth) | C47: =C39 -> 0 | D47: =D39 -> 0 | E47: =E39 -> 0 | F47: =E47*(1+F45) -> 0 | G47: =F47*(1+G45) -> 0 | H47: =G47*(1+H45) -> 0 | I47: =H47*(1+I45) -> 0 | J47: =I47*(1+J45) -> 0 | K47: =J47*(1+K45) -> 0 | L47: =K47*(1+L45) -> 0 | M47: =L47*(1+M45) -> 0 | N47: =M47*(1+N45) -> 0
B48: Memo: dividends on the analysts' path | C48: =C47*C46 -> 0 | D48: =D47*D46 -> 0 | E48: =E47*E46 -> 0 | F48: =F47*F46 -> 0 | G48: =G47*G46 -> 0 | H48: =H47*H46 -> 0 | I48: =I47*I46 -> 0 | J48: =J47*J46 -> 0 | ... N48: =N47*N46 -> 0
B49: Cash to shareholders used (switch in row 12) | D49: =IF($C$12=1,D43,D48) -> 0 | E49: =IF($C$12=1,E43,E48) -> 0 | F49: =IF($C$12=1,F43,F48) -> 0 | G49: =IF($C$12=1,G43,G48) -> 0 | H49: =IF($C$12=1,H43,H48) -> 0 | I49: =IF($C$12=1,I43,I48) -> 0 | J49: =IF($C$12=1,J43,J48) -> 0 | K49: =IF($C$12=1,K43,K48) -> 0 | ... N49: =IF($C$12=1,N43,N48) -> 0
B51: 5. Valuation at the end of 2027
B52: Item | C52: Bear | D52: Base | E52: Bull | P52: How it is calculated
B53: Ke | C53: =C33 -> 0 | D53: =D33 -> 0 | E53: =E33 -> 0
B54: Earnings shock of the Ibovespa ex-Commodities | C54: -0.2 | D54: 0 | E54: 0.2 | P54: Symmetric +/-20%, as the other boxes.
B55: Earnings shock of Financials = beta x normalization x shock | C55: =$C$11*$D$11*C54 -> 0 | D55: =$C$11*$D$11*D54 -> 0 | E55: =$C$11*$D$11*E54 -> 0 | P55: Moves the cash to shareholders of every year.
B56: PV of the explicit flows = (1 + shock) x sum of flow / (1 + Ke) ^ t | C56: =(1+C55)*SUMPRODUCT($E$49:$N$49,--($E$38:$N$38<=NExp),1/(1+C53)^$E$38:$N$38) -> 0 | D56: =(1+D55)*SUMPRODUCT($E$49:$N$49,--($E$38:$N$38<=NExp),1/(1+D53)^$E$38:$N$38) -> 0 | E56: =(1+E55)*SUMPRODUCT($E$49:$N$49,--($E$38:$N$38<=NExp),1/(1+E53)^$E$38:$N$38) -> 0 | P56: t = 1 for 2028 (value at end-2027); only the explicit years.
B57: Terminal value = last explicit flow x (1 + shock) x (1 + g) / (Ke - g) | C57: =INDEX($E$49:$N$49,NExp)*(1+C55)*(1+g_)/(C53-g_) -> 0 | D57: =INDEX($E$49:$N$49,NExp)*(1+D55)*(1+g_)/(D53-g_) -> 0 | E57: =INDEX($E$49:$N$49,NExp)*(1+E55)*(1+g_)/(E53-g_) -> 0 | P57: Gordon on the last explicit flow.
B58: PV of the terminal value = TV / (1 + Ke) ^ (explicit years + extra periods) | C58: =C57/(1+C53)^(NExp+TVx) -> 0 | D58: =D57/(1+D53)^(NExp+TVx) -> 0 | E58: =E57/(1+E53)^(NExp+TVx) -> 0
B59: Fair value of Financials at the end of 2027 (index pts) | C59: =C56+C58 -> 0 | D59: =D56+D58 -> 0 | E59: =E56+E58 -> 0
B60: Upside vs. today | C60: =C59/$C$7-1 -> 0 | D60: =D59/$C$7-1 -> 0 | E60: =E59/$C$7-1 -> 0
B61: Perpetuity share of the value | C61: =C58/C59 -> 0 | D61: =D58/D59 -> 0 | E61: =E58/E59 -> 0 | P61: Analysts' models: 42-52% (Model Parameters).
B62: Memo: upside with the analysts' own growth and payout (row 48), same choices | C62: =((1+C55)*SUMPRODUCT($E$48:$N$48,--($E$38:$N$38<=NExp),1/(1+C53)^$E$38:$N$38)+INDEX($E$48:$N$48,NExp)*(1+C55)*(1+g_)/(C53-g_)/(1+C53)^(NExp+TVx))/$C$7-1 -> 0 | D62: =((1+D55)*SUMPRODUCT($E$48:$N$48,--($E$38:$N$38<=NExp),1/(1+D53)^$E$38:$N$38)+INDEX($E$48:$N$48,NExp)*(1+D55)*(1+g_)/(D53-g_)/(1+D53)^(NExp+TVx))/$C$7-1 -> 0 | E62: =((1+E55)*SUMPRODUCT($E$48:$N$48,--($E$38:$N$38<=NExp),1/(1+E53)^$E$38:$N$38)+INDEX($E$48:$N$48,NExp)*(1+E55)*(1+g_)/(E53-g_)/(1+E53)^(NExp+TVx))/$C$7-1 -> 0
B63: Memo: upside in the unified DCF by box (main model, v7b) | C63: -0.35434755 | D63: -0.061 | E63: 0.28808083 | P63: Ibov_house_2027_by_box_XP.xlsx, DCF by Box row 63 (FCFE, 4 explicit years, house g and rate).
B65: 6. Base upside (no earnings shock): Ke (rows) x perpetuity g (columns); flows as projected
B66: Ke \ g | C66: 0.04 | D66: 0.047 | E66: 0.05 | F66: 0.055 | G66: 0.06
B67: 0.12 | C67: =(SUMPRODUCT($E$49:$N$49,--($E$38:$N$38<=NExp),1/(1+$B67)^$E$38:$N$38)+INDEX($E$49:$N$49,NExp)*(1+C$66)/($B67-C$66)/(1+$B67)^(NExp+TVx))/$C$7-1 -> 0 | D67: =(SUMPRODUCT($E$49:$N$49,--($E$38:$N$38<=NExp),1/(1+$B67)^$E$38:$N$38)+INDEX($E$49:$N$49,NExp)*(1+D$66)/($B67-D$66)/(1+$B67)^(NExp+TVx))/$C$7-1 -> 0 | E67: =(SUMPRODUCT($E$49:$N$49,--($E$38:$N$38<=NExp),1/(1+$B67)^$E$38:$N$38)+INDEX($E$49:$N$49,NExp)*(1+E$66)/($B67-E$66)/(1+$B67)^(NExp+TVx))/$C$7-1 -> 0 | F67: =(SUMPRODUCT($E$49:$N$49,--($E$38:$N$38<=NExp),1/(1+$B67)^$E$38:$N$38)+INDEX($E$49:$N$49,NExp)*(1+F$66)/($B67-F$66)/(1+$B67)^(NExp+TVx))/$C$7-1 -> 0 | G67: =(SUMPRODUCT($E$49:$N$49,--($E$38:$N$38<=NExp),1/(1+$B67)^$E$38:$N$38)+INDEX($E$49:$N$49,NExp)*(1+G$66)/($B67-G$66)/(1+$B67)^(NExp+TVx))/$C$7-1 -> 0
B68: 0.13 | C68: =(SUMPRODUCT($E$49:$N$49,--($E$38:$N$38<=NExp),1/(1+$B68)^$E$38:$N$38)+INDEX($E$49:$N$49,NExp)*(1+C$66)/($B68-C$66)/(1+$B68)^(NExp+TVx))/$C$7-1 -> 0 | D68: =(SUMPRODUCT($E$49:$N$49,--($E$38:$N$38<=NExp),1/(1+$B68)^$E$38:$N$38)+INDEX($E$49:$N$49,NExp)*(1+D$66)/($B68-D$66)/(1+$B68)^(NExp+TVx))/$C$7-1 -> 0 | E68: =(SUMPRODUCT($E$49:$N$49,--($E$38:$N$38<=NExp),1/(1+$B68)^$E$38:$N$38)+INDEX($E$49:$N$49,NExp)*(1+E$66)/($B68-E$66)/(1+$B68)^(NExp+TVx))/$C$7-1 -> 0 | F68: =(SUMPRODUCT($E$49:$N$49,--($E$38:$N$38<=NExp),1/(1+$B68)^$E$38:$N$38)+INDEX($E$49:$N$49,NExp)*(1+F$66)/($B68-F$66)/(1+$B68)^(NExp+TVx))/$C$7-1 -> 0 | G68: =(SUMPRODUCT($E$49:$N$49,--($E$38:$N$38<=NExp),1/(1+$B68)^$E$38:$N$38)+INDEX($E$49:$N$49,NExp)*(1+G$66)/($B68-G$66)/(1+$B68)^(NExp+TVx))/$C$7-1 -> 0
B69: 0.1365 | C69: =(SUMPRODUCT($E$49:$N$49,--($E$38:$N$38<=NExp),1/(1+$B69)^$E$38:$N$38)+INDEX($E$49:$N$49,NExp)*(1+C$66)/($B69-C$66)/(1+$B69)^(NExp+TVx))/$C$7-1 -> 0 | D69: =(SUMPRODUCT($E$49:$N$49,--($E$38:$N$38<=NExp),1/(1+$B69)^$E$38:$N$38)+INDEX($E$49:$N$49,NExp)*(1+D$66)/($B69-D$66)/(1+$B69)^(NExp+TVx))/$C$7-1 -> 0 | E69: =(SUMPRODUCT($E$49:$N$49,--($E$38:$N$38<=NExp),1/(1+$B69)^$E$38:$N$38)+INDEX($E$49:$N$49,NExp)*(1+E$66)/($B69-E$66)/(1+$B69)^(NExp+TVx))/$C$7-1 -> 0 | F69: =(SUMPRODUCT($E$49:$N$49,--($E$38:$N$38<=NExp),1/(1+$B69)^$E$38:$N$38)+INDEX($E$49:$N$49,NExp)*(1+F$66)/($B69-F$66)/(1+$B69)^(NExp+TVx))/$C$7-1 -> 0 | G69: =(SUMPRODUCT($E$49:$N$49,--($E$38:$N$38<=NExp),1/(1+$B69)^$E$38:$N$38)+INDEX($E$49:$N$49,NExp)*(1+G$66)/($B69-G$66)/(1+$B69)^(NExp+TVx))/$C$7-1 -> 0
B70: 0.14 | C70: =(SUMPRODUCT($E$49:$N$49,--($E$38:$N$38<=NExp),1/(1+$B70)^$E$38:$N$38)+INDEX($E$49:$N$49,NExp)*(1+C$66)/($B70-C$66)/(1+$B70)^(NExp+TVx))/$C$7-1 -> 0 | D70: =(SUMPRODUCT($E$49:$N$49,--($E$38:$N$38<=NExp),1/(1+$B70)^$E$38:$N$38)+INDEX($E$49:$N$49,NExp)*(1+D$66)/($B70-D$66)/(1+$B70)^(NExp+TVx))/$C$7-1 -> 0 | E70: =(SUMPRODUCT($E$49:$N$49,--($E$38:$N$38<=NExp),1/(1+$B70)^$E$38:$N$38)+INDEX($E$49:$N$49,NExp)*(1+E$66)/($B70-E$66)/(1+$B70)^(NExp+TVx))/$C$7-1 -> 0 | F70: =(SUMPRODUCT($E$49:$N$49,--($E$38:$N$38<=NExp),1/(1+$B70)^$E$38:$N$38)+INDEX($E$49:$N$49,NExp)*(1+F$66)/($B70-F$66)/(1+$B70)^(NExp+TVx))/$C$7-1 -> 0 | G70: =(SUMPRODUCT($E$49:$N$49,--($E$38:$N$38<=NExp),1/(1+$B70)^$E$38:$N$38)+INDEX($E$49:$N$49,NExp)*(1+G$66)/($B70-G$66)/(1+$B70)^(NExp+TVx))/$C$7-1 -> 0
B71: 0.15 | C71: =(SUMPRODUCT($E$49:$N$49,--($E$38:$N$38<=NExp),1/(1+$B71)^$E$38:$N$38)+INDEX($E$49:$N$49,NExp)*(1+C$66)/($B71-C$66)/(1+$B71)^(NExp+TVx))/$C$7-1 -> 0 | D71: =(SUMPRODUCT($E$49:$N$49,--($E$38:$N$38<=NExp),1/(1+$B71)^$E$38:$N$38)+INDEX($E$49:$N$49,NExp)*(1+D$66)/($B71-D$66)/(1+$B71)^(NExp+TVx))/$C$7-1 -> 0 | E71: =(SUMPRODUCT($E$49:$N$49,--($E$38:$N$38<=NExp),1/(1+$B71)^$E$38:$N$38)+INDEX($E$49:$N$49,NExp)*(1+E$66)/($B71-E$66)/(1+$B71)^(NExp+TVx))/$C$7-1 -> 0 | F71: =(SUMPRODUCT($E$49:$N$49,--($E$38:$N$38<=NExp),1/(1+$B71)^$E$38:$N$38)+INDEX($E$49:$N$49,NExp)*(1+F$66)/($B71-F$66)/(1+$B71)^(NExp+TVx))/$C$7-1 -> 0 | G71: =(SUMPRODUCT($E$49:$N$49,--($E$38:$N$38<=NExp),1/(1+$B71)^$E$38:$N$38)+INDEX($E$49:$N$49,NExp)*(1+G$66)/($B71-G$66)/(1+$B71)^(NExp+TVx))/$C$7-1 -> 0
B72: 0.16 | C72: =(SUMPRODUCT($E$49:$N$49,--($E$38:$N$38<=NExp),1/(1+$B72)^$E$38:$N$38)+INDEX($E$49:$N$49,NExp)*(1+C$66)/($B72-C$66)/(1+$B72)^(NExp+TVx))/$C$7-1 -> 0 | D72: =(SUMPRODUCT($E$49:$N$49,--($E$38:$N$38<=NExp),1/(1+$B72)^$E$38:$N$38)+INDEX($E$49:$N$49,NExp)*(1+D$66)/($B72-D$66)/(1+$B72)^(NExp+TVx))/$C$7-1 -> 0 | E72: =(SUMPRODUCT($E$49:$N$49,--($E$38:$N$38<=NExp),1/(1+$B72)^$E$38:$N$38)+INDEX($E$49:$N$49,NExp)*(1+E$66)/($B72-E$66)/(1+$B72)^(NExp+TVx))/$C$7-1 -> 0 | F72: =(SUMPRODUCT($E$49:$N$49,--($E$38:$N$38<=NExp),1/(1+$B72)^$E$38:$N$38)+INDEX($E$49:$N$49,NExp)*(1+F$66)/($B72-F$66)/(1+$B72)^(NExp+TVx))/$C$7-1 -> 0 | G72: =(SUMPRODUCT($E$49:$N$49,--($E$38:$N$38<=NExp),1/(1+$B72)^$E$38:$N$38)+INDEX($E$49:$N$49,NExp)*(1+G$66)/($B72-G$66)/(1+$B72)^(NExp+TVx))/$C$7-1 -> 0
B74: 13.65% = house Ke in the base; ~15.1% = analysts' Ke in the base. 4.7% = house g; 6.0% = analysts' g.
B78: 7. What is fixed (not switchable) and where it comes from
B79: Content of 2026-28: Bloomberg consensus of the members, summed | P79: Strategy (unified with the other boxes)
B80: Projection for the box only: ROE held at FY28, growth fading to g | P80: Analysts' logic
B81: Cash to shareholders = net income - increase in book value | P81: Analysts' equity roll-forward (= house FCFE)
B82: Gordon perpetuity on the last explicit flow | P82: Both
B83: Scenario real rates 8.5% / today / 5.5% | P83: House (unified with the other boxes)
B84: Earnings shock +/-20% x earnings beta | P84: Strategy (unified with the other boxes)
B85: Value at end-2027, compared with today's points | P85: House

Sheet Box Consensus
B1: Financials - consensus 2026-28 of the members, summed into the box (index points)
B2: Bloomberg BEST consensus (Oct-7-2026): net income (BEST_NET_INCOME, Members sheet of the main model) and ROE (BEST_ROE, dcf_members.parquet). Book value = net income / ROE. Index points = R$ mn x points / market cap. Only the actuals and consensus years are built from the members; the projection is done for the box.
B3: Legend: | C3: input | D3: assumption | E3: formula
B6: Member | C6: Index points | D6: Market cap (R$ mn) | E6: Points / market cap | F6: Net income 2026 (R$ mn) | G6: Net income 2027 (R$ mn) | H6: Net income 2028 (R$ mn) | I6: ROE 2026 | J6: ROE 2027 | K6: ROE 2028 | L6: Net income 2026 (pts) | M6: Net income 2027 (pts) | N6: Net income 2028 (pts) | O6: Book value 2026 (pts) | P6: Book value 2027 (pts) | Q6: Book value 2028 (pts)
B7: Itaú Unibanco (ITUB4) | C7: 19089.265 | D7: 564225.23 | E7: =C7/D7 -> 0 | F7: 50677.333 | G7: 55448.917 | H7: 60687.636 | I7: 0.24574 | J7: 0.24478 | K7: 0.24343 | L7: =F7*$E7 -> 0 | M7: =G7*$E7 -> 0 | N7: =H7*$E7 -> 0 | O7: =L7/I7 -> 0 | P7: =M7/J7 -> 0 | Q7: =N7/K7 -> 0
B8: Bradesco (BBDC4 + BBDC3) | C8: 10039.703 | D8: 226447.76 | E8: =C8/D8 -> 0 | F8: 27739.923 | G8: 30648.077 | H8: 33619.083 | I8: 0.15379 | J8: 0.15855 | K8: 0.1615 | L8: =F8*$E8 -> 0 | M8: =G8*$E8 -> 0 | N8: =H8*$E8 -> 0 | O8: =L8/I8 -> 0 | P8: =M8/J8 -> 0 | Q8: =N8/K8 -> 0
B9: B3 (B3SA3) | C9: 8337.4035 | D9: 112688.35 | E9: =C9/D9 -> 0 | F9: 5982 | G9: 6425.4 | H9: 6561.222 | I9: 0.3363 | J9: 0.34744 | K9: 0.37809 | L9: =F9*$E9 -> 0 | M9: =G9*$E9 -> 0 | N9: =H9*$E9 -> 0 | O9: =L9/I9 -> 0 | P9: =M9/J9 -> 0 | Q9: =N9/K9 -> 0
B10: Itausa (ITSA4) | C10: 7020.6236 | D10: 179573.13 | E10: =C10/D10 -> 0 | F10: 19414 | G10: 20412 | H10: 23060 | I10: 0.24574 | J10: 0.24478 | K10: 0.24343 | L10: =F10*$E10 -> 0 | M10: =G10*$E10 -> 0 | N10: =H10*$E10 -> 0 | O10: =L10/I10 -> 0 | P10: =M10/J10 -> 0 | Q10: =N10/K10 -> 0
B11: BTG Pactual (BPAC11) | C11: 6925.2189 | D11: 305584.14 | E11: =C11/D11 -> 0 | F11: 20474.182 | G11: 23359.364 | H11: 26673.6 | I11: 0.2655 | J11: 0.2553 | K11: 0.2486 | L11: =F11*$E11 -> 0 | M11: =G11*$E11 -> 0 | N11: =H11*$E11 -> 0 | O11: =L11/I11 -> 0 | P11: =M11/J11 -> 0 | Q11: =N11/K11 -> 0
B12: Banco do Brasil (BBAS3) | C12: 5397.318 | D12: 138571.57 | E12: =C12/D12 -> 0 | F12: 17093.5 | G12: 24478.75 | H12: 29169 | I12: 0.08591 | J12: 0.11989 | K12: 0.13251 | L12: =F12*$E12 -> 0 | M12: =G12*$E12 -> 0 | N12: =H12*$E12 -> 0 | O12: =L12/I12 -> 0 | P12: =M12/J12 -> 0 | Q12: =N12/K12 -> 0
B13: BBSeguridade (BBSE3) | C13: 1823.5557 | D13: 78199.592 | E13: =C13/D13 -> 0 | F13: 8662.5 | G13: 8582.6 | H13: 8977.125 | I13: 0.91299 | J13: 0.85076 | K13: 0.81663 | L13: =F13*$E13 -> 0 | M13: =G13*$E13 -> 0 | N13: =H13*$E13 -> 0 | O13: =L13/I13 -> 0 | P13: =M13/J13 -> 0 | Q13: =N13/K13 -> 0
B14: Caixa Seguridade (CXSE3) | C14: 895.11912 | D14: 63090 | E14: =C14/D14 -> 0 | F14: 4676.444 | G14: 5099.889 | H14: 5562.143 | I14: 0.3916 | J14: 0.4101 | K14: 0.4234 | L14: =F14*$E14 -> 0 | M14: =G14*$E14 -> 0 | N14: =H14*$E14 -> 0 | O14: =L14/I14 -> 0 | P14: =M14/J14 -> 0 | Q14: =N14/K14 -> 0
B15: Santander (SANB11) | C15: 735.15958 | D15: 109308.45 | E15: =C15/D15 -> 0 | F15: 13604.778 | G15: 15814.1 | H15: 18082.9 | I15: 0.13896 | J15: 0.15058 | K15: 0.15957 | L15: =F15*$E15 -> 0 | M15: =G15*$E15 -> 0 | N15: =H15*$E15 -> 0 | O15: =L15/I15 -> 0 | P15: =M15/J15 -> 0 | Q15: =N15/K15 -> 0
B16: Porto Seguro (PSSA3) | C16: 663.93681 | D16: 34042.756 | E16: =C16/D16 -> 0 | F16: 3715.9 | G16: 3997.4 | H16: 4403.375 | I16: 0.23357 | J16: 0.22948 | K16: 0.22982 | L16: =F16*$E16 -> 0 | M16: =G16*$E16 -> 0 | N16: =H16*$E16 -> 0 | O16: =L16/I16 -> 0 | P16: =M16/J16 -> 0 | Q16: =N16/K16 -> 0
B17: Financials box | C17: =SUM(C7:C16) -> 0 | I17: =L17/O17 -> 0 | J17: =M17/P17 -> 0 | K17: =N17/Q17 -> 0 | L17: =SUM(L7:L16) -> 0 | M17: =SUM(M7:M16) -> 0 | N17: =SUM(N7:N16) -> 0 | O17: =SUM(O7:O16) -> 0 | P17: =SUM(P7:P16) -> 0 | Q17: =SUM(Q7:Q16) -> 0
B18: Check: net income vs. Box Shares!M7:O7 of the main model | L18: =L17-5708.118100817073 -> 0 | M18: =M17-6447.843510049624 -> 0 | N18: =N17-7167.107435011599 -> 0
B20: Box ROE = sum of net income / sum of book value (row total).
B21: Itaúsa: no BEST_ROE for the holding; Itaú's consensus ROE as a proxy (pink, editable).
B22: Bradesco: BBDC4 and BBDC3 points added (same company figures).

Sheet Analyst Models
B1: Financials - analysts' projections, aggregated (index points)
B2: Net income and dividends of the XP Financials models (R$ mn, files in inputs/analyst_models/Financials/). After a model's last year: net income grows at g and the payout stays at its last value, as the model's own perpetuity. Index points = R$ x the member's index points / market cap (Members sheet of the main model, Oct-5-2026).
B3: Legend: | C3: input | D3: assumption | E3: formula
B5: Itaú Unibanco (ITUB4) | ITUB Model Official 2Q26_vCSStrategy.xlsx
B6: Line | C6: 2026 | D6: 2027 | E6: 2028 | F6: 2029 | G6: 2030 | H6: 2031 | I6: 2032 | J6: 2033 | K6: 2034 | L6: 2035 | M6: 2036 | N6: 2037 | P6: How it is calculated / source
B7: Net income (R$ mn) | C7: 50922 | D7: 56028 | E7: 61318 | F7: 66407 | G7: 71853 | H7: 76890 | I7: 81937 | J7: 87124 | K7: 92891 | L7: 99086 | M7: 105569 | N7: 112362 | P7: Model: Income Statement r61 Recurring Net Income.
B8: Dividends + IoC (R$ mn) | C8: 29433 | D8: 36310 | E8: 42954 | F8: 47031 | G8: 52633 | H8: 58205 | I8: 62018 | J8: 65938 | K8: 72614 | L8: 77433 | M8: 83534 | N8: 90010 | P8: Model: Income Statement r66 Dividends/IoC Provisioned.
B9: Payout | C9: =C8/C7 -> 0 | D9: =D8/D7 -> 0 | E9: =E8/E7 -> 0 | F9: =F8/F7 -> 0 | G9: =G8/G7 -> 0 | H9: =H8/H7 -> 0 | I9: =I8/I7 -> 0 | J9: =J8/J7 -> 0 | ... N9: =N8/N7 -> 0 | P9: Dividends / net income.
B10: Index points / market cap (R$ mn) | C10: 19089.265 | D10: 564225.23 | E10: =C10/D10 -> 0 | P10: C: index points (Members); D: market cap (Members); E: factor that turns R$ mn into index points.
B11: Net income (index pts) | C11: =C7*$E$10 -> 0 | D11: =D7*$E$10 -> 0 | E11: =E7*$E$10 -> 0 | F11: =F7*$E$10 -> 0 | G11: =G7*$E$10 -> 0 | H11: =H7*$E$10 -> 0 | I11: =I7*$E$10 -> 0 | J11: =J7*$E$10 -> 0 | ... N11: =N7*$E$10 -> 0
B12: Dividends (index pts) | C12: =C8*$E$10 -> 0 | D12: =D8*$E$10 -> 0 | E12: =E8*$E$10 -> 0 | F12: =F8*$E$10 -> 0 | G12: =G8*$E$10 -> 0 | H12: =H8*$E$10 -> 0 | I12: =I8*$E$10 -> 0 | J12: =J8*$E$10 -> 0 | ... N12: =N8*$E$10 -> 0
B15: Bradesco (BBDC4 + BBDC3) | BBDC Model Official 2Q26_vCSStrategy.xlsx
B16: Line | C16: 2026 | D16: 2027 | E16: 2028 | F16: 2029 | G16: 2030 | H16: 2031 | I16: 2032 | J16: 2033 | K16: 2034 | L16: 2035 | M16: 2036 | N16: 2037 | P16: How it is calculated / source
B17: Net income (R$ mn) | C17: 28221 | D17: 31178 | E17: 34548 | F17: 37971 | G17: 41533 | H17: 44699 | I17: 47964 | J17: 51319 | K17: 54749 | L17: 58243 | M17: 61788 | N17: 65372 | P17: Model: Income Statement r73 Recurring Net Income.
B18: Dividends + IoC (R$ mn) | C18: 13727 | D18: 15095 | E18: 16726 | F18: 19903 | G18: 23431 | H18: 26111 | I18: 28978 | J18: 31517 | K18: 34171 | L18: 36934 | M18: 39801 | N18: 42763 | P18: Model: Income Statement r78 Dividends/IoC Provisioned - Net.
B19: Payout | C19: =C18/C17 -> 0 | D19: =D18/D17 -> 0 | E19: =E18/E17 -> 0 | F19: =F18/F17 -> 0 | G19: =G18/G17 -> 0 | H19: =H18/H17 -> 0 | I19: =I18/I17 -> 0 | J19: =J18/J17 -> 0 | ... N19: =N18/N17 -> 0 | P19: Dividends / net income.
B20: Index points / market cap (R$ mn) | C20: 10039.703 | D20: 226447.76 | E20: =C20/D20 -> 0 | P20: C: index points (Members); D: market cap (Members); E: factor that turns R$ mn into index points.
B21: Net income (index pts) | C21: =C17*$E$20 -> 0 | D21: =D17*$E$20 -> 0 | E21: =E17*$E$20 -> 0 | F21: =F17*$E$20 -> 0 | G21: =G17*$E$20 -> 0 | H21: =H17*$E$20 -> 0 | I21: =I17*$E$20 -> 0 | J21: =J17*$E$20 -> 0 | ... N21: =N17*$E$20 -> 0
B22: Dividends (index pts) | C22: =C18*$E$20 -> 0 | D22: =D18*$E$20 -> 0 | E22: =E18*$E$20 -> 0 | F22: =F18*$E$20 -> 0 | G22: =G18*$E$20 -> 0 | H22: =H18*$E$20 -> 0 | I22: =I18*$E$20 -> 0 | J22: =J18*$E$20 -> 0 | ... N22: =N18*$E$20 -> 0
B25: B3 (B3SA3) | B3SA3 Model Official 3Q25_vCSStrategy.xlsx
B26: Line | C26: 2026 | D26: 2027 | E26: 2028 | F26: 2029 | G26: 2030 | H26: 2031 | I26: 2032 | J26: 2033 | K26: 2034 | L26: 2035 | M26: 2036 | N26: 2037 | P26: How it is calculated / source
B27: Net income (R$ mn) | C27: 6537 | D27: 7215 | E27: 7971 | F27: 8876 | G27: 9881 | H27: 10905 | I27: 11848 | J27: 13062 | K27: =J27*(1+gAn) -> 0 | L27: =K27*(1+gAn) -> 0 | M27: =L27*(1+gAn) -> 0 | N27: =M27*(1+gAn) -> 0 | P27: Model: Income Statement r52 Recurring Net Income. After 2033: x (1 + g).
B28: Dividends + IoC (R$ mn) | C28: 6203 | D28: 6859 | E28: 7612 | F28: 8513 | G28: 9413 | H28: 10358 | I28: 11364 | J28: 12526 | K28: =K27*J29 -> 0 | L28: =L27*J29 -> 0 | M28: =M27*J29 -> 0 | N28: =N27*J29 -> 0 | P28: Model: Income Statement r58 Dividends/IoC. After 2033: net income x the 2033 payout.
B29: Payout | C29: =C28/C27 -> 0 | D29: =D28/D27 -> 0 | E29: =E28/E27 -> 0 | F29: =F28/F27 -> 0 | G29: =G28/G27 -> 0 | H29: =H28/H27 -> 0 | I29: =I28/I27 -> 0 | J29: =J28/J27 -> 0 | ... N29: =N28/N27 -> 0 | P29: Dividends / net income.
B30: Index points / market cap (R$ mn) | C30: 8337.4035 | D30: 112688.35 | E30: =C30/D30 -> 0 | P30: C: index points (Members); D: market cap (Members); E: factor that turns R$ mn into index points.
B31: Net income (index pts) | C31: =C27*$E$30 -> 0 | D31: =D27*$E$30 -> 0 | E31: =E27*$E$30 -> 0 | F31: =F27*$E$30 -> 0 | G31: =G27*$E$30 -> 0 | H31: =H27*$E$30 -> 0 | I31: =I27*$E$30 -> 0 | J31: =J27*$E$30 -> 0 | ... N31: =N27*$E$30 -> 0
B32: Dividends (index pts) | C32: =C28*$E$30 -> 0 | D32: =D28*$E$30 -> 0 | E32: =E28*$E$30 -> 0 | F32: =F28*$E$30 -> 0 | G32: =G28*$E$30 -> 0 | H32: =H28*$E$30 -> 0 | I32: =I28*$E$30 -> 0 | J32: =J28*$E$30 -> 0 | ... N32: =N28*$E$30 -> 0
B35: BTG Pactual (BPAC11) | BPAC Model Official 3Q25_vCSStrategy.xlsx
B36: Line | C36: 2026 | D36: 2027 | E36: 2028 | F36: 2029 | G36: 2030 | H36: 2031 | I36: 2032 | J36: 2033 | K36: 2034 | L36: 2035 | M36: 2036 | N36: 2037 | P36: How it is calculated / source
B37: Net income (R$ mn) | C37: 19103 | D37: 21961 | E37: 25043 | F37: 28704 | G37: 32446 | H37: 36374 | I37: 40448 | J37: 44253 | K37: 48504 | L37: 52818 | M37: 57507 | N37: =M37*(1+gAn) -> 0 | P37: Model: Income Statement r50 Net Income. After 2036: x (1 + g).
B38: Dividends + IoC (R$ mn) | C38: 6686 | D38: 9882 | E38: 13774 | F38: 17222 | G38: 21090 | H38: 25462 | I38: 30336 | J38: 35403 | K38: 41228 | L38: 47536 | M38: 54632 | N38: =N37*M39 -> 0 | P38: Model: Income Statement r56 Dividends/IoC. After 2036: net income x the 2036 payout.
B39: Payout | C39: =C38/C37 -> 0 | D39: =D38/D37 -> 0 | E39: =E38/E37 -> 0 | F39: =F38/F37 -> 0 | G39: =G38/G37 -> 0 | H39: =H38/H37 -> 0 | I39: =I38/I37 -> 0 | J39: =J38/J37 -> 0 | ... N39: =N38/N37 -> 0 | P39: Dividends / net income.
B40: Index points / market cap (R$ mn) | C40: 6925.2189 | D40: 305584.14 | E40: =C40/D40 -> 0 | P40: C: index points (Members); D: market cap (Members); E: factor that turns R$ mn into index points.
B41: Net income (index pts) | C41: =C37*$E$40 -> 0 | D41: =D37*$E$40 -> 0 | E41: =E37*$E$40 -> 0 | F41: =F37*$E$40 -> 0 | G41: =G37*$E$40 -> 0 | H41: =H37*$E$40 -> 0 | I41: =I37*$E$40 -> 0 | J41: =J37*$E$40 -> 0 | ... N41: =N37*$E$40 -> 0
B42: Dividends (index pts) | C42: =C38*$E$40 -> 0 | D42: =D38*$E$40 -> 0 | E42: =E38*$E$40 -> 0 | F42: =F38*$E$40 -> 0 | G42: =G38*$E$40 -> 0 | H42: =H38*$E$40 -> 0 | I42: =I38*$E$40 -> 0 | J42: =J38*$E$40 -> 0 | ... N42: =N38*$E$40 -> 0
B45: Banco do Brasil (BBAS3) | BBAS Model Official 2Q26_vCSStrategy.xlsx
B46: Line | C46: 2026 | D46: 2027 | E46: 2028 | F46: 2029 | G46: 2030 | H46: 2031 | I46: 2032 | J46: 2033 | K46: 2034 | L46: 2035 | M46: 2036 | N46: 2037 | P46: How it is calculated / source
B47: Net income (R$ mn) | C47: =C48/C49 -> 0 | D47: =D48/D49 -> 0 | E47: =E48/E49 -> 0 | F47: =F48/F49 -> 0 | G47: =G48/G49 -> 0 | H47: =H48/H49 -> 0 | I47: =I48/I49 -> 0 | J47: =J48/J49 -> 0 | ... N47: =N48/N49 -> 0 | P47: Model: = dividends / payout.
B48: Dividends + IoC (R$ mn) | C48: 4060 | D48: 7114 | E48: 8935 | F48: 9990 | G48: 10846 | H48: 13882 | I48: 17093 | J48: 20522 | K48: 24056 | L48: 27771 | M48: 29140 | N48: 30564 | P48: Model: Valuation r5 Total Return; payout: Model r26.
B49: Payout | C49: 0.24 | D49: 0.3 | E49: 0.3 | F49: 0.3 | G49: 0.3 | H49: 0.35 | I49: 0.4 | J49: 0.45 | K49: 0.5 | L49: 0.55 | M49: 0.55 | N49: 0.55 | P49: Model: Model r26 (input).
B50: Index points / market cap (R$ mn) | C50: 5397.318 | D50: 138571.57 | E50: =C50/D50 -> 0 | P50: C: index points (Members); D: market cap (Members); E: factor that turns R$ mn into index points.
B51: Net income (index pts) | C51: =C47*$E$50 -> 0 | D51: =D47*$E$50 -> 0 | E51: =E47*$E$50 -> 0 | F51: =F47*$E$50 -> 0 | G51: =G47*$E$50 -> 0 | H51: =H47*$E$50 -> 0 | I51: =I47*$E$50 -> 0 | J51: =J47*$E$50 -> 0 | ... N51: =N47*$E$50 -> 0
B52: Dividends (index pts) | C52: =C48*$E$50 -> 0 | D52: =D48*$E$50 -> 0 | E52: =E48*$E$50 -> 0 | F52: =F48*$E$50 -> 0 | G52: =G48*$E$50 -> 0 | H52: =H48*$E$50 -> 0 | I52: =I48*$E$50 -> 0 | J52: =J48*$E$50 -> 0 | ... N52: =N48*$E$50 -> 0
B55: Caixa Seguridade (CXSE3) | CXSE3 Model Official 3Q25_vCSStrategy.xlsx
B56: Line | C56: 2026 | D56: 2027 | E56: 2028 | F56: 2029 | G56: 2030 | H56: 2031 | I56: 2032 | J56: 2033 | K56: 2034 | L56: 2035 | M56: 2036 | N56: 2037 | P56: How it is calculated / source
B57: Net income (R$ mn) | C57: 4565.538 | D57: 4903.673 | E57: 5256.803 | F57: 5652.253 | G57: 6018.714 | H57: 6421.658 | I57: 6858 | J57: 7330.546 | K57: 7842.343 | L57: 8396.709 | M57: 8997.253 | N57: =M57*(1+gAn) -> 0 | P57: Model: Income Statement r54 Managerial Net Income (R$ thousand / 1,000). After 2036: x (1 + g).
B58: Dividends + IoC (R$ mn) | C58: 4208 | D58: 4520 | E58: 4845 | F58: 5210 | G58: 5547 | H58: 5919 | I58: 6321 | J58: 6756 | K58: 7228 | L58: 7739 | M58: 8293 | N58: =N57*M59 -> 0 | P58: Model: Valuation r2 Dividend. After 2036: net income x the 2036 payout.
B59: Payout | C59: =C58/C57 -> 0 | D59: =D58/D57 -> 0 | E59: =E58/E57 -> 0 | F59: =F58/F57 -> 0 | G59: =G58/G57 -> 0 | H59: =H58/H57 -> 0 | I59: =I58/I57 -> 0 | J59: =J58/J57 -> 0 | ... N59: =N58/N57 -> 0 | P59: Dividends / net income.
B60: Index points / market cap (R$ mn) | C60: 895.11912 | D60: 63090 | E60: =C60/D60 -> 0 | P60: C: index points (Members); D: market cap (Members); E: factor that turns R$ mn into index points.
B61: Net income (index pts) | C61: =C57*$E$60 -> 0 | D61: =D57*$E$60 -> 0 | E61: =E57*$E$60 -> 0 | F61: =F57*$E$60 -> 0 | G61: =G57*$E$60 -> 0 | H61: =H57*$E$60 -> 0 | I61: =I57*$E$60 -> 0 | J61: =J57*$E$60 -> 0 | ... N61: =N57*$E$60 -> 0
B62: Dividends (index pts) | C62: =C58*$E$60 -> 0 | D62: =D58*$E$60 -> 0 | E62: =E58*$E$60 -> 0 | F62: =F58*$E$60 -> 0 | G62: =G58*$E$60 -> 0 | H62: =H58*$E$60 -> 0 | I62: =I58*$E$60 -> 0 | J62: =J58*$E$60 -> 0 | ... N62: =N58*$E$60 -> 0
B65: Santander (SANB11) | SANB Model Official 4Q25_vCSStrategy.xlsx
B66: Line | C66: 2026 | D66: 2027 | E66: 2028 | F66: 2029 | G66: 2030 | H66: 2031 | I66: 2032 | J66: 2033 | K66: 2034 | L66: 2035 | M66: 2036 | N66: 2037 | P66: How it is calculated / source
B67: Net income (R$ mn) | C67: 17399 | D67: 19672 | E67: 20985 | F67: 22473 | G67: 23918 | H67: 25510 | I67: 27201 | J67: 28935 | K67: 30589 | L67: 32224 | M67: 33739 | N67: =M67*(1+gAn) -> 0 | P67: Model: IS r95 Recurring Net Income. After 2036: x (1 + g).
B68: Dividends + IoC (R$ mn) | C68: 11309 | D68: 12787 | E68: 14689 | F68: 15731 | G68: 17939 | H68: 19132 | I68: 20400 | J68: 21702 | K68: 22942 | L68: 24168 | M68: 25304 | N68: =N67*M69 -> 0 | P68: Model: IS r103 Dividends/IoC Provisioned. After 2036: net income x the 2036 payout.
B69: Payout | C69: =C68/C67 -> 0 | D69: =D68/D67 -> 0 | E69: =E68/E67 -> 0 | F69: =F68/F67 -> 0 | G69: =G68/G67 -> 0 | H69: =H68/H67 -> 0 | I69: =I68/I67 -> 0 | J69: =J68/J67 -> 0 | ... N69: =N68/N67 -> 0 | P69: Dividends / net income.
B70: Index points / market cap (R$ mn) | C70: 735.15958 | D70: 109308.45 | E70: =C70/D70 -> 0 | P70: C: index points (Members); D: market cap (Members); E: factor that turns R$ mn into index points.
B71: Net income (index pts) | C71: =C67*$E$70 -> 0 | D71: =D67*$E$70 -> 0 | E71: =E67*$E$70 -> 0 | F71: =F67*$E$70 -> 0 | G71: =G67*$E$70 -> 0 | H71: =H67*$E$70 -> 0 | I71: =I67*$E$70 -> 0 | J71: =J67*$E$70 -> 0 | ... N71: =N67*$E$70 -> 0
B72: Dividends (index pts) | C72: =C68*$E$70 -> 0 | D72: =D68*$E$70 -> 0 | E72: =E68*$E$70 -> 0 | F72: =F68*$E$70 -> 0 | G72: =G68*$E$70 -> 0 | H72: =H68*$E$70 -> 0 | I72: =I68*$E$70 -> 0 | J72: =J68*$E$70 -> 0 | ... N72: =N68*$E$70 -> 0
B75: Itaúsa (ITSA4) | no model: Itaú's net income path and payout (holding of Itaú)
B76: Line | C76: 2026 | D76: 2027 | E76: 2028 | F76: 2029 | G76: 2030 | H76: 2031 | I76: 2032 | J76: 2033 | K76: 2034 | L76: 2035 | M76: 2036 | N76: 2037 | P76: How it is calculated / source
B77: Net income (R$ mn) = consensus FY28 x Itaú's net income / Itaú's 2028 | C77: =$C$81*C7/$E$7 -> 0 | D77: =$C$81*D7/$E$7 -> 0 | E77: =$C$81*E7/$E$7 -> 0 | F77: =$C$81*F7/$E$7 -> 0 | G77: =$C$81*G7/$E$7 -> 0 | H77: =$C$81*H7/$E$7 -> 0 | I77: =$C$81*I7/$E$7 -> 0 | J77: =$C$81*J7/$E$7 -> 0 | ... N77: =$C$81*N7/$E$7 -> 0 | P77: Itaú's path scaled to Itaúsa's FY28 consensus (Members).
B78: Dividends (R$ mn) = net income x Itaú's payout | C78: =C77*C9 -> 0 | D78: =D77*D9 -> 0 | E78: =E77*E9 -> 0 | F78: =F77*F9 -> 0 | G78: =G77*G9 -> 0 | H78: =H77*H9 -> 0 | I78: =I77*I9 -> 0 | J78: =J77*J9 -> 0 | ... N78: =N77*N9 -> 0
B79: Payout | C79: =C78/C77 -> 0 | D79: =D78/D77 -> 0 | E79: =E78/E77 -> 0 | F79: =F78/F77 -> 0 | G79: =G78/G77 -> 0 | H79: =H78/H77 -> 0 | I79: =I78/I77 -> 0 | J79: =J78/J77 -> 0 | ... N79: =N78/N77 -> 0
B80: Index points / market cap (R$ mn) | C80: 7020.6236 | D80: 179573.13 | E80: =C80/D80 -> 0
B81: Itaúsa net income FY28, Bloomberg consensus (R$ mn) | C81: 23060
B82: Net income (index pts) | C82: =C77*$E$80 -> 0 | D82: =D77*$E$80 -> 0 | E82: =E77*$E$80 -> 0 | F82: =F77*$E$80 -> 0 | G82: =G77*$E$80 -> 0 | H82: =H77*$E$80 -> 0 | I82: =I77*$E$80 -> 0 | J82: =J77*$E$80 -> 0 | ... N82: =N77*$E$80 -> 0
B83: Dividends (index pts) | C83: =C78*$E$80 -> 0 | D83: =D78*$E$80 -> 0 | E83: =E78*$E$80 -> 0 | F83: =F78*$E$80 -> 0 | G83: =G78*$E$80 -> 0 | H83: =H78*$E$80 -> 0 | I83: =I78*$E$80 -> 0 | J83: =J78*$E$80 -> 0 | ... N83: =N78*$E$80 -> 0
B86: Aggregate of the modeled members (index points): what the box takes from the analysts
B87: Line | C87: 2026 | D87: 2027 | E87: 2028 | F87: 2029 | G87: 2030 | H87: 2031 | I87: 2032 | J87: 2033 | K87: 2034 | L87: 2035 | M87: 2036 | N87: 2037 | P87: How it is calculated / source
B88: Net income (index pts) | C88: =C11+C21+C31+C41+C51+C61+C71+C82 -> 0 | D88: =D11+D21+D31+D41+D51+D61+D71+D82 -> 0 | E88: =E11+E21+E31+E41+E51+E61+E71+E82 -> 0 | F88: =F11+F21+F31+F41+F51+F61+F71+F82 -> 0 | G88: =G11+G21+G31+G41+G51+G61+G71+G82 -> 0 | H88: =H11+H21+H31+H41+H51+H61+H71+H82 -> 0 | I88: =I11+I21+I31+I41+I51+I61+I71+I82 -> 0 | J88: =J11+J21+J31+J41+J51+J61+J71+J82 -> 0 | ... N88: =N11+N21+N31+N41+N51+N61+N71+N82 -> 0
B89: Dividends (index pts) | C89: =C12+C22+C32+C42+C52+C62+C72+C83 -> 0 | D89: =D12+D22+D32+D42+D52+D62+D72+D83 -> 0 | E89: =E12+E22+E32+E42+E52+E62+E72+E83 -> 0 | F89: =F12+F22+F32+F42+F52+F62+F72+F83 -> 0 | G89: =G12+G22+G32+G42+G52+G62+G72+G83 -> 0 | H89: =H12+H22+H32+H42+H52+H62+H72+H83 -> 0 | I89: =I12+I22+I32+I42+I52+I62+I72+I83 -> 0 | J89: =J12+J22+J32+J42+J52+J62+J72+J83 -> 0 | ... N89: =N12+N22+N32+N42+N52+N62+N72+N83 -> 0
B90: Net income growth | D90: =D88/C88-1 -> 0 | E90: =E88/D88-1 -> 0 | F90: =F88/E88-1 -> 0 | G90: =G88/F88-1 -> 0 | H90: =H88/G88-1 -> 0 | I90: =I88/H88-1 -> 0 | J90: =J88/I88-1 -> 0 | K90: =K88/J88-1 -> 0 | ... N90: =N88/M88-1 -> 0 | P90: Used for the box from 2029.
B91: Payout = dividends / net income | C91: =C89/C88 -> 0 | D91: =D89/D88 -> 0 | E91: =E89/E88 -> 0 | F91: =F89/F88 -> 0 | G91: =G89/G88 -> 0 | H91: =H89/H88 -> 0 | I91: =I89/I88 -> 0 | J91: =J89/J88 -> 0 | ... N91: =N89/N88 -> 0 | P91: Used for the box in every year.
B92: Coverage: index points of the modeled members / Financials box | C92: =(C10+C20+C30+C40+C50+C60+C70+C80)/'DDM Financials'!$C$7 -> 0 | P92: BB Seguridade and Porto Seguro have no model: they take the aggregate path.

Sheet Model Parameters
B1: Financials - valuation parameters of the analysts' models
B2: Valuation sheet of each model. Ke = (NTN-B + long-term IPCA) x 0.85 + beta x ERP; g = long-term IPCA + real GDP (Macro sheet).
B3: Legend: | C3: input | D3: assumption | E3: formula
B5: Member | C5: Ke | D5: NTN-B | E5: IPCA LT | F5: Risk free = (NTN-B + IPCA) x 0.85 | G5: ERP | H5: Beta | I5: g | J5: Perpetuity share of value | K5: Last explicit year | L5: Value date | M5: Index points
B6: ITUB4 + ITSA4 | C6: 0.1513 | D6: 0.076 | E6: 0.04 | F6: 0.0986 | G6: 0.055 | H6: 0.958 | I6: 0.06 | J6: 0.4623 | K6: 2037 | L6: End-2027 | M6: 26109.889
B7: BBDC4 + BBDC3 | C7: 0.1619 | D7: 0.076 | E7: 0.04 | F7: 0.0986 | G7: 0.055 | H7: 1.15 | I7: 0.06 | J7: 0.4371 | K7: 2037 | L7: End-2027 | M7: 10039.703
B8: B3SA3 | C8: 0.1583 | D8: 0.0732 | E8: 0.04 | F8: 0.0962 | G8: 0.055 | H8: 1.129 | I8: 0.06 | J8: 0.4358 | K8: 2033 | L8: n/a | M8: 8337.403
B9: BPAC11 | C9: 0.1637 | D9: 0.0741 | E9: 0.04 | F9: 0.097 | G9: 0.055 | H9: 1.213 | I9: 0.06 | J9: 0.5183 | K9: 2036 | L9: End-2026 | M9: 6925.219
B10: BBAS3 | C10: 0.1809 | D10: 0.081 | E10: 0.04 | F10: 0.1029 | G10: 0.06 | H10: 1.3 | I10: 0.06 | J10: 0.4185 | K10: 2037 | L10: End-2027 | M10: 5397.318
B11: CXSE3 | C11: 0.1386 | D11: 0.0751 | E11: 0.04 | F11: 0.0978 | G11: 0.055 | H11: 0.742 | I11: 0.06 | J11: 0.5003 | K11: 2036 | L11: End-2026 | M11: 895.119
B12: SANB11 | C12: 0.149 | D12: 0.0749 | E12: 0.04 | F12: 0.0977 | G12: 0.05 | H12: 1.027 | I12: 0.06 | J12: 0.4541 | K12: 2036 | L12: End-2026 | M12: 735.16
B13: Weighted by index points | C13: =SUMPRODUCT(C6:C12,$M$6:$M$12)/SUM($M$6:$M$12) -> 0 | D13: =SUMPRODUCT(D6:D12,$M$6:$M$12)/SUM($M$6:$M$12) -> 0 | F13: =SUMPRODUCT(F6:F12,$M$6:$M$12)/SUM($M$6:$M$12) -> 0 | G13: =SUMPRODUCT(G6:G12,$M$6:$M$12)/SUM($M$6:$M$12) -> 0 | H13: =SUMPRODUCT(H6:H12,$M$6:$M$12)/SUM($M$6:$M$12) -> 0 | I13: =SUMPRODUCT(I6:I12,$M$6:$M$12)/SUM($M$6:$M$12) -> 0 | J13: =SUMPRODUCT(J6:J12,$M$6:$M$12)/SUM($M$6:$M$12) -> 0
B15: Itaúsa takes Itaú's parameters; Bradesco's two share classes are added. Source: Valuation sheet of each file (Ke, NTN-B, risk free, ERP, beta, g, 'Perpetuity' = PV of the terminal value / fair equity value).
