Workbook
Name BetaAdj: Assumptions!$C$45
Name BetaYears: Assumptions!$C$44
Name BoxRate: Assumptions!$C$42
Name ERPfloor: Assumptions!$C$43
Name FinROE: 'Box Shares'!$C$39
Name FinROEovr: Assumptions!$C$40
Name FixInfl: Assumptions!$C$29
Name FixND: Assumptions!$C$27
Name FixNWC: Assumptions!$C$26
Name FixTV: Assumptions!$C$28
Name FV27Base: DCF!$D$57
Name FV27Bear: DCF!$C$57
Name FV27Bull: DCF!$E$57
Name gLT: Assumptions!$C$13
Name IbovUsed: Assumptions!$E$7
Name InflLT: Assumptions!$C$14
Name NDmult: Assumptions!$C$16
Name NWCpct: Assumptions!$C$15
Name RRUsed: Assumptions!$E$8
Name ScaleBox: Assumptions!$C$39
Name Vintage: Assumptions!$C$9

Sheet Cover
C3: Ibovespa | DCF by box (house model), end-2027
C4: VALUATION MODEL · EQUITY STRATEGY
C7: Main tabs >>
C8: Summary | E8: Assumptions | G8: DCF by Box | I8: DCF (Ibovespa) | K8: Ibovespa used | M8: =IbovUsed -> 208431.92
K9: Fair value end-2027, base | M9: =Summary!E11 -> 235695.44
K10: Upside, base | M10: =Summary!I11 -> 0.13080299
C11: Auxiliary tabs >> | K11: Fair value end-2027, bear | M11: =Summary!D11 -> 191722.24
C12: Sensitivity | E12: Box Shares | G12: Members (76 stocks) | I12: Checks | K12: Fair value end-2027, bull | M12: =Summary!F11 -> 261607.54
K13: Model checks | M13: =Checks!C5 -> All checks OK
K15: How this model works >>
K16: Equity Strategy | XP Research
C18: Base case by box >>
C19: Box | F19: Index points | G19: Fair value | H19: Upside
C20: Financials | F20: =Summary!C7 -> 60927.304 | G20: =Summary!E7 -> 64254.945 | H20: =Summary!I7 -> 0.054616589
C21: Defensives | F21: =Summary!C8 -> 55822.367 | G21: =Summary!E8 -> 65034.096 | H21: =Summary!I8 -> 0.1650186
C22: Cyclicals | F22: =Summary!C9 -> 26271.075 | G22: =Summary!E9 -> 42289.695 | H22: =Summary!I9 -> 0.60974361
C23: Commodities | F23: =Summary!C10 -> 65411.174 | G23: =Summary!E10 -> 64116.702 | H23: =Summary!I10 -> -0.01978978
C24: Ibovespa | F24: =Summary!C11 -> 208431.92 | G24: =Summary!E11 -> 235695.44 | H24: =Summary!I11 -> 0.13080299
C26: House DCF rolled to end-2027 and split by box: FCFF for Defensives, Cyclicals and Commodities, FCFE for Financials; boxes scaled to the house total.

Sheet Summary
B1: Ibovespa - DCF by box (house model): fair value at the end of 2027
B2: House DCF rolled to end-2027 and split by box; box rates keep each box's historical relative valuation. Construction: DCF by Box, Box Rates, DCF.
B3: Ibovespa used | C3: =IbovUsed -> 208431.92 | D3: Market data | E3: =CHOOSE(Vintage,"house file","Oct-5-2026") -> Oct-5-2026 | F3: Checks | G3: =Checks!C5 -> All checks OK | H3: Boxes scaled | I3: =IF(ScaleBox=1,"yes","no") -> yes
B4: Box discount rates | C4: =CHOOSE(BoxRate+1,"the house rate for every box","relative to each box's history (Box Rates)","CAPM: real rate + box beta x ERP (Box Betas)") -> relative to each box's history (Box Rates)
B5: 1. Fair value at the end of 2027 by box (index pts)
B6: Group | C6: Index points | D6: Bear | E6: Base | F6: Bull | H6: Upside: Bear | I6: Base | J6: Bull
B7: Financials | C7: ='Box Shares'!C7 -> 60927.304 | D7: ='DCF by Box'!C57 -> 54797.695 | E7: ='DCF by Box'!D57 -> 64254.945 | F7: ='DCF by Box'!E57 -> 71234.793 | H7: =D7/$C7-1 -> -0.10060529 | I7: =E7/$C7-1 -> 0.054616589 | J7: =F7/$C7-1 -> 0.16917685
B8: Defensives | C8: ='Box Shares'!C8 -> 55822.367 | D8: ='DCF by Box'!C98 -> 55244.064 | E8: ='DCF by Box'!D98 -> 65034.096 | F8: ='DCF by Box'!E98 -> 72213.386 | H8: =D8/$C8-1 -> -0.010359706 | I8: =E8/$C8-1 -> 0.1650186 | J8: =F8/$C8-1 -> 0.29362816
B9: Cyclicals | C9: ='Box Shares'!C9 -> 26271.075 | D9: ='DCF by Box'!C139 -> 27251.182 | E9: ='DCF by Box'!D139 -> 42289.695 | F9: ='DCF by Box'!E139 -> 46906.281 | H9: =D9/$C9-1 -> 0.037307468 | I9: =E9/$C9-1 -> 0.60974361 | J9: =F9/$C9-1 -> 0.78547248
B10: Commodities | C10: ='Box Shares'!C10 -> 65411.174 | D10: ='DCF by Box'!C180 -> 54429.3 | E10: ='DCF by Box'!D180 -> 64116.702 | F10: ='DCF by Box'!E180 -> 71253.079 | H10: =D10/$C10-1 -> -0.16788988 | I10: =E10/$C10-1 -> -0.01978978 | J10: =F10/$C10-1 -> 0.089310501
B11: Ibovespa | C11: =SUM(C7:C10) -> 208431.92 | D11: =SUM(D7:D10) -> 191722.24 | E11: =SUM(E7:E10) -> 235695.44 | F11: =SUM(F7:F10) -> 261607.54 | H11: =D11/$C11-1 -> -0.080168523 | I11: =E11/$C11-1 -> 0.13080299 | J11: =F11/$C11-1 -> 0.25512225
B12: Memo (inside Cyclicals; own rates, not additive)
B13: Cyclicals ex-WEG & Embraer | C13: ='Box Shares'!C14 -> 16066.52 | D13: ='DCF by Box'!C221 -> 20090.494 | E13: ='DCF by Box'!D221 -> 28924.182 | F13: ='DCF by Box'!E221 -> 32105.636 | H13: =D13/$C13-1 -> 0.25045715 | I13: =E13/$C13-1 -> 0.80027678 | J13: =F13/$C13-1 -> 0.9982944
B14: WEG & Embraer | C14: ='Box Shares'!C15 -> 10204.555 | D14: ='DCF by Box'!C262 -> 7160.6877 | E14: ='DCF by Box'!D262 -> 12859.72 | F14: ='DCF by Box'!E262 -> 15715.205 | H14: =D14/$C14-1 -> -0.29828517 | I14: =E14/$C14-1 -> 0.2601941 | J14: =F14/$C14-1 -> 0.54001865
B16: 2. Upside by box: this DCF vs. the multiples model (Oct-6 table) and vs. the DCF at the house rate
B17: Group | D17: DCF: Bear | E17: Multiples: Bear | F17: DCF: Base | G17: Multiples: Base | H17: DCF: Bull | I17: Multiples: Bull | J17: Base, DCF at the house rate
B18: Financials | D18: =H7 -> -0.10060529 | E18: =$D$68/$C$7-1 -> -0.26279942 | F18: =I7 -> 0.054616589 | G18: =$D$69/$C$7-1 -> -0.075462708 | H18: =J7 -> 0.16917685 | I18: =$D$70/$C$7-1 -> 0.1764631 | J18: ='DCF by Box'!$D$61*IF(ScaleBox=1,'DCF by Box'!$D$14,1)/$C$7-1 -> 0.081885096
B19: Defensives | D19: =H8 -> -0.010359706 | E19: =$E$68/$C$8-1 -> -0.13463029 | F19: =I8 -> 0.1650186 | G19: =$E$69/$C$8-1 -> 0.070674259 | H19: =J8 -> 0.29362816 | I19: =$E$70/$C$8-1 -> 0.31471271 | J19: ='DCF by Box'!$D$102*IF(ScaleBox=1,'DCF by Box'!$D$14,1)/$C$8-1 -> -0.19702917
B20: Cyclicals | D20: =H9 -> 0.037307468 | E20: =$F$68/$C$9-1 -> 0.015544907 | F20: =I9 -> 0.60974361 | G20: =$F$69/$C$9-1 -> 0.39651752 | H20: =J9 -> 0.78547248 | I20: =$F$70/$C$9-1 -> 0.846917 | J20: ='DCF by Box'!$D$143*IF(ScaleBox=1,'DCF by Box'!$D$14,1)/$C$9-1 -> -0.50629096
B21: Commodities | D21: =H10 -> -0.16788988 | E21: =$G$68/$C$10-1 -> -0.16662894 | F21: =I10 -> -0.01978978 | G21: =$G$69/$C$10-1 -> 0.16870547 | H21: =J10 -> 0.089310501 | I21: =$G$70/$C$10-1 -> 0.54777705 | J21: ='DCF by Box'!$D$184*IF(ScaleBox=1,'DCF by Box'!$D$14,1)/$C$10-1 -> 0.71201782
B22: Ibovespa | D22: =H11 -> -0.080168523 | E22: =$H$68/$C$11-1 -> -0.16320943 | F22: =I11 -> 0.13080299 | G22: =$H$69/$C$11-1 -> 0.099791 | H22: =J11 -> 0.25512225 | I22: =$H$70/$C$11-1 -> 0.41452187 | J22: ='DCF by Box'!$D$13*IF(ScaleBox=1,'DCF by Box'!$D$14,1)/$C$11-1 -> 0.13080299
B23: Memo (inside Cyclicals)
B24: Cyclicals ex-WEG & Embraer | D24: =H13 -> 0.25045715 | E24: =$I$68/$C$13-1 -> 0.13423127 | F24: =I13 -> 0.80027678 | G24: =$I$69/$C$13-1 -> 0.62781467 | H24: =J13 -> 0.9982944 | I24: =$I$70/$C$13-1 -> 1.2146051 | J24: ='DCF by Box'!$D$225*IF(ScaleBox=1,'DCF by Box'!$D$14,1)/$C$13-1 -> -0.41012576
B25: WEG & Embraer | D25: =H14 -> -0.29828517 | E25: =$J$68/$C$14-1 -> -0.25637845 | F25: =I14 -> 0.2601941 | G25: =$J$69/$C$14-1 -> 0.25783362 | H25: =J14 -> 0.54001865 | I25: =$J$70/$C$14-1 -> 0.82151303 | J25: ='DCF by Box'!$D$266*IF(ScaleBox=1,'DCF by Box'!$D$14,1)/$C$14-1 -> -0.65769786
B26: Average absolute gap to the multiples, four boxes | D26: =AVERAGE(ABS(D18-E18),ABS(D19-E19),ABS(D20-E20),ABS(D21-E21)) -> 0.077372054 | F26: =AVERAGE(ABS(F18-G18),ABS(F19-G19),ABS(F20-G20),ABS(F21-G21)) -> 0.15653625 | H26: =AVERAGE(ABS(H18-I18),ABS(H19-I19),ABS(H20-I20),ABS(H21-I21)) -> 0.13707046 | J26: =AVERAGE(ABS(J18-G18),ABS(J19-G19),ABS(J20-G20),ABS(J21-G21)) -> 0.46779302
B27: Gap in points of upside. Last column: the house mechanics with one rate (BoxRate = 0), against the multiples' base.
B29: 3. Discount rate by box (Box Rates)
B30: Group | C30: Relative cash yield | D30: Rate: Bear | E30: Base | F30: Bull | G30: CAPM beta | H30: Risk premium: Bear | I30: Base | J30: Bull
B31: Financials | C31: ='Box Rates'!G7 -> 0.9245176 | D31: ='Box Rates'!C21 -> 0.13760273 | E31: ='Box Rates'!D21 -> 0.12151612 | F31: ='Box Rates'!E21 -> 0.11448979 | G31: ='Box Betas'!I7 -> 1.1490637 | H31: ='Box Rates'!G21 -> 0.052602725 | I31: ='Box Rates'!H21 -> 0.053916119 | J31: ='Box Rates'!I21 -> 0.054489785
B32: Defensives | C32: ='Box Rates'!G8 -> 0.63524349 | D32: ='Box Rates'!C22 -> 0.10925386 | E32: ='Box Rates'!D22 -> 0.098200625 | F32: ='Box Rates'!E22 -> 0.093372774 | G32: ='Box Betas'!I8 -> 0.92867396 | H32: ='Box Rates'!G22 -> 0.024253862 | I32: ='Box Rates'!H22 -> 0.030600625 | J32: ='Box Rates'!I22 -> 0.033372774
B33: Cyclicals | C33: ='Box Rates'!G9 -> 0.29730445 | D33: ='Box Rates'!C23 -> 0.085 | E33: ='Box Rates'!D23 -> 0.070962739 | F33: ='Box Rates'!E23 -> 0.068703225 | G33: ='Box Betas'!I9 -> 1.1504511 | H33: ='Box Rates'!G23 -> 0 | I33: ='Box Rates'!H23 -> 0.003362739 | J33: ='Box Rates'!I23 -> 0.0087032252
B34: Commodities | C34: ='Box Rates'!G10 -> 1.53528 | D34: ='Box Rates'!C24 -> 0.19745744 | E34: ='Box Rates'!D24 -> 0.17074357 | F34: ='Box Rates'!E24 -> 0.15907544 | G34: ='Box Betas'!I10 -> 0.87168584 | H34: ='Box Rates'!G24 -> 0.11245744 | I34: ='Box Rates'!H24 -> 0.10314357 | J34: ='Box Rates'!I24 -> 0.099075438
B35: Ibovespa (house rate) | C35: ='Box Rates'!G11 -> 1 | D35: ='Box Rates'!C19 -> 0.145 | E35: ='Box Rates'!D19 -> 0.1276 | F35: ='Box Rates'!E19 -> 0.12 | G35: ='Box Betas'!I11 -> 1 | H35: ='Box Rates'!G19 -> 0.06 | I35: ='Box Rates'!H19 -> 0.06 | J35: ='Box Rates'!I19 -> 0.06
B36: Memo (inside Cyclicals)
B37: Cyclicals ex-WEG & Embraer | C37: ='Box Rates'!G13 -> 0.32038362 | D37: ='Box Rates'!C26 -> 0.085 | E37: ='Box Rates'!D26 -> 0.072822919 | F37: ='Box Rates'!E26 -> 0.070388004 | G37: ='Box Betas'!I13 -> 1.3187146 | H37: ='Box Rates'!G26 -> 0 | I37: ='Box Rates'!H26 -> 0.0052229195 | J37: ='Box Rates'!I26 -> 0.010388004
B38: WEG & Embraer | C38: ='Box Rates'!G14 -> 0.23199022 | D38: ='Box Rates'!C27 -> 0.085 | E38: ='Box Rates'!D27 -> 0.0676 | F38: ='Box Rates'!E27 -> 0.063935286 | G38: ='Box Betas'!I14 -> 0.71783452 | H38: ='Box Rates'!G27 -> 0 | I38: ='Box Rates'!H27 -> 0 | J38: ='Box Rates'!I27 -> 0.0039352858
B39: Rates in use (BoxRate). Relative cash yield = (10y average earnings yield x cash conversion) of the box / the Ibovespa's; CAPM beta: Box Betas.
B41: 4. Each box with its own value, before scaling (box rates; Financials by FCFE)
D42: Bear | E42: Base | F42: Bull | H42: Upside: Bear | I42: Base | J42: Bull
B43: Financials | D43: ='DCF by Box'!C54 -> 56491.129 | E43: ='DCF by Box'!D54 -> 69096.294 | F43: ='DCF by Box'!E54 -> 76515.629 | H43: ='DCF by Box'!C56 -> -0.072810939 | I43: ='DCF by Box'!D56 -> 0.13407767 | J43: ='DCF by Box'!E56 -> 0.25585122
B44: Defensives | D44: ='DCF by Box'!C95 -> 56951.293 | E44: ='DCF by Box'!D95 -> 69934.152 | F44: ='DCF by Box'!E95 -> 77566.768 | H44: ='DCF by Box'!C97 -> 0.020223535 | I44: ='DCF by Box'!D97 -> 0.25279803 | J44: ='DCF by Box'!E97 -> 0.38952845
B45: Cyclicals | D45: ='DCF by Box'!C136 -> 28093.336 | E45: ='DCF by Box'!D136 -> 45476.051 | F45: ='DCF by Box'!E136 -> 50383.575 | H45: ='DCF by Box'!C138 -> 0.069363786 | I45: ='DCF by Box'!D138 -> 0.73103126 | J45: ='DCF by Box'!E138 -> 0.91783458
B46: Commodities | D46: ='DCF by Box'!C177 -> 56111.35 | E46: ='DCF by Box'!D177 -> 68947.635 | F46: ='DCF by Box'!E177 -> 76535.27 | H46: ='DCF by Box'!C179 -> -0.14217486 | I46: ='DCF by Box'!D179 -> 0.054065081 | J46: ='DCF by Box'!E179 -> 0.17006415
B47: Sum of the boxes | D47: ='DCF by Box'!C7 -> 197647.11 | E47: ='DCF by Box'!D7 -> 253454.13 | F47: ='DCF by Box'!E7 -> 281001.24
B48: House DCF fair value, Ibovespa (DCF sheet) | D48: ='DCF by Box'!C8 -> 191722.24 | E48: ='DCF by Box'!D8 -> 235695.44 | F48: ='DCF by Box'!E8 -> 261607.54
B49: Scale factor = house / sum of the boxes | D49: ='DCF by Box'!C9 -> 0.970023 | E49: ='DCF by Box'!D9 -> 0.9299333 | F49: ='DCF by Box'!E9 -> 0.93098357
B51: 5. Scenario parameters and settings (Assumptions)
D52: Bear | E52: Base | F52: Bull
B53: 5-year real rate (NTN-B) | D53: =DCF!C46 -> 0.085 | E53: =DCF!D46 -> 0.0676 | F53: =DCF!E46 -> 0.06
B54: ERP (house) | D54: =DCF!C47 -> 0.06 | E54: =DCF!D47 -> 0.06 | F54: =DCF!E47 -> 0.06
B55: House discount rate | D55: =DCF!C48 -> 0.145 | E55: =DCF!D48 -> 0.1276 | F55: =DCF!E48 -> 0.12
B56: Corrections in use (Assumptions section 4) | D56: =IF(FixNWC+FixND+FixTV+FixInfl=0,"none: as the house","on: "&IF(FixNWC=1,"NWC change ","")&IF(FixND=1,"net debt ","")&IF(FixTV=1,"TV timing ","")&IF(FixInfl=1,"inflation","")) -> none: as the house
B58: 6. Box shares of the house lines (Box Shares; last consensus year)
B59: Line | D59: Financials | E59: Defensives | F59: Cyclicals | G59: Commodities
B60: Sales 2027 | D60: ='Box Shares'!E19 -> 0.1642579 | E60: ='Box Shares'!E20 -> 0.26048992 | F60: ='Box Shares'!E21 -> 0.11218492 | G60: ='Box Shares'!E22 -> 0.46306726
B61: EBIT 2028 | D61: ='Box Shares'!I19 -> 0.22985575 | E61: ='Box Shares'!I20 -> 0.24415677 | F61: ='Box Shares'!I21 -> 0.105999 | G61: ='Box Shares'!I22 -> 0.41998848
B62: EBITDA 2028 | D62: ='Box Shares'!L19 -> 0.2555345 | E62: ='Box Shares'!L20 -> 0.22223939 | F62: ='Box Shares'!L21 -> 0.097444816 | G62: ='Box Shares'!L22 -> 0.42478129
B63: Net income 2028 | D63: ='Box Shares'!O19 -> 0.3064974 | E63: ='Box Shares'!O20 -> 0.19377661 | F63: ='Box Shares'!O21 -> 0.098542148 | G63: ='Box Shares'!O22 -> 0.40118384
B64: Capex 2027 | D64: ='Box Shares'!Q19 -> 0.24938824 | E64: ='Box Shares'!Q20 -> 0.24129138 | F64: ='Box Shares'!Q21 -> 0.14132059 | G64: ='Box Shares'!Q22 -> 0.36799979
B66: 7. Reference (not linked): multiples model and our DCF by box (index pts)
B67: Model | D67: Financials | E67: Defensives | F67: Cyclicals | G67: Commodities | H67: Ibovespa | I67: Cyc. ex-WEG & EMB | J67: WEG & Embraer
B68: Multiples model, average of methods (Oct-6 table): Bear | D68: 44915.644 | E68: 48306.986 | F68: 26679.456 | G68: 54511.78 | H68: 174413.87 | I68: 18223.149 | J68: 7588.3271
B69: Multiples model, average of methods (Oct-6 table): Base | D69: 56329.564 | E69: 59767.572 | F69: 36688.016 | G69: 76446.398 | H69: 229231.55 | I69: 26153.316 | J69: 12835.632
B70: Multiples model, average of methods (Oct-6 table): Bull | D70: 71678.724 | E70: 73390.376 | F70: 48520.494 | G70: 101241.91 | H70: 294831.51 | I70: 35580.997 | J70: 18587.73
B71: DCF by box (Ibov_DCF_by_box_XP.xlsx, 12 months): Base | D71: 70757 | E71: 42152 | F71: 24906 | G71: 85903 | H71: 223718 | I71: 17780 | J71: 7140
B72: Multiples model: Ibov_valuation_by_box_model_XP.xlsx (prices of Oct-5; each box at its own 10y average multiples, plus bottom-up).

Sheet Assumptions
B1: Ibovespa - DCF assumptions (house model by box, end-2027)
B2: Change the pink cells; the DCF sheet recalculates. Projection rules for 2028-2031 are pink cells in the DCF sheet.
B3: Legend: | C3: input | D3: assumption | E3: formula
B5: 1. Market data
B6: Item | C6: House file | D6: Oct-5-2026 | E6: Used | G6: Source
B7: Ibovespa (index pts) | C7: 182419.73 | D7: 208431.92 | E7: =CHOOSE(Vintage,C7,D7) -> 208431.92 | G7: House file: Target!B61 (BDP IBOV Index, as saved). Oct-5: Bloomberg IBOV Index PX_LAST.
B8: 5-year real rate (NTN-B) | C8: 0.0742 | D8: 0.0676 | E8: =CHOOSE(Vintage,C8,D8) -> 0.0676 | G8: House file: Target!C56 (BZRFB5PY Index, 7.42%). Oct-5: ANBIMA 5-year NTN-B (Bloomberg was down; check BZRFB5PY before publishing).
B9: Market data used: 1 = house file, 2 = Oct-5-2026 | C9: 2 | G9: Consensus and history are the house file's in both cases (not refreshed: the consensus moved little).
B11: 2. Valuation parameters (house Target sheet)
B12: Parameter | C12: Value | G12: Source
B13: Long-term growth of the FCFF (g) | C13: 0.047 | G13: Target!B54 (4.7%).
B14: Long-term inflation (Fisher switch and the implied-return block) | C14: 0.04 | G14: Target!B63 (4.0%).
B15: Working capital, % of sales | C15: 0.04 | G15: Target row 43: NWC = -4% of sales.
B16: Net debt / EBITDA of two years before (net debt switch) | C16: 1.6 | G16: Target rows 70-71 (EV/EBITDA method): net debt = 1.6x the EBITDA of two years before the value date.
B18: 3. Scenarios (fair value at the end of 2027)
B19: Lever | C19: Bear | D19: Base | E19: Bull | G19: Source
B20: 5-year real rate (NTN-B) | C20: 0.085 | D20: =RRUsed -> 0.0676 | E20: 0.06 | G20: As the house (Target rows 131-151): bear 8.5%, base = the market rate, bull 6.0%.
B21: ERP | C21: 0.06 | D21: 0.06 | E21: 0.06 | G21: Target!B57 (6.0%), the same in every scenario.
B22: Discount rate (house: real rate + ERP) | C22: =IF(FixInfl=1,(1+C20+C21)*(1+InflLT)-1,C20+C21) -> 0.145 | D22: =IF(FixInfl=1,(1+D20+D21)*(1+InflLT)-1,D20+D21) -> 0.1276 | E22: =IF(FixInfl=1,(1+E20+E21)*(1+InflLT)-1,E20+E21) -> 0.12 | G22: Target!B55 = BZRFB5PY + ERP. With the inflation switch on: (1 + real rate + ERP) x (1 + inflation) - 1.
B24: 4. Corrections to the house mechanics (0 = as the house, 1 = corrected)
B25: Switch | C25: Value | G25: What it changes
B26: Working capital: 0 = level (house), 1 = change | C26: 0 | G26: House row 44 adds the whole NWC level (-4% of sales) every year; the cash flow is the change in NWC.
B27: Net debt: 0 = not subtracted (house), 1 = subtracted | C27: 0 | G27: FCFF values the firm; equity = firm value - net debt (1.6x EBITDA two years before, as the house's EV/EBITDA method).
B28: Terminal value: 0 = one period after the last flow (house), 1 = with the last flow | C28: 0 | G28: NPV(rate, flows, TV) puts the TV one year after the last explicit year; it is a value at the end of that year.
B29: Inflation in the rate: 0 = real rate + ERP (house), 1 = Fisher | C29: 0 | G29: The flows are nominal (sales grow with nominal GDP); real rate + ERP is a real rate.
B31: 5. Projection rules (pink cells in the DCF sheet, 2028-2031 columns)
B32: Real GDP and inflation 2028-2031: 2.0% and 4.0% (house); sales grow with nominal GDP x ratio (1.0).
B33: EBITDA margin 2029-2031: 30% (house). EBIT margin, interest and gross margin: held at the 2028 level (house: same % as the year before).
B34: Capex % of sales: 11% in 2028-2029, 9% from 2030 (house); 2031, the year added here, keeps 2030's 9%.
B35: Consensus: sales and capex to 2027, EBIT, EBITDA and EPS to 2028 (IBOV Index, as in the house file).
B37: 6. By box
B38: Setting | C38: Value | G38: What it does
B39: Scale the boxes to the house's Ibovespa value: 1 = yes, 0 = no | C39: 1 | G39: 1: each box x (house Ibovespa value / sum of the boxes), so the boxes add up to the house number. 0: each box with its own value.
B40: Financials ROE for the FCFE (blank = consensus FY28, Box Shares) | G40: FCFE = net income x (1 - g / ROE): the earnings left after keeping the bank's equity growing at g.
B41: Index points of the members: Ibovespa on Oct-5-2026 (Assumptions D7) x price-drifted Sep-30 weights.
B42: Box discount rates: 0 = house rate, 1 = relative to history, 2 = CAPM (box beta) | C42: 1 | G42: 0: every box at the house rate. 1: box rate - g = (house rate - g) x the box's 10y cash yield relative to the Ibovespa (Box Rates), as the multiples. 2: CAPM, real rate + box beta x ERP (Box Betas).
B43: Lowest risk premium of a box (box rate >= real rate + this) | C43: 0 | G43: Keeps a box's risk premium from going below this; at 0% it binds only for Cyclicals in the bear.
B44: CAPM beta window (years of weekly returns: 2, 5 or 10) | C44: 5 | G44: Weekly total returns of the box indices up to Sep-25-2026 (Box Betas).
B45: CAPM beta: 1 = raw, 2 = Blume adjusted (0.67 x raw + 0.33) | C45: 1 | G45: The adjustment pulls the betas toward 1 (Bloomberg's default adjusted beta).

Sheet DCF by Box
B1: Ibovespa - DCF by box (house mechanics, end-2027)
B2: Each box gets its share of every house line (Box Shares). FCFF as the house for Defensives, Cyclicals and Commodities; FCFE for Financials. Rates and switches: Assumptions.
B3: Legend: | C3: input | D3: assumption | E3: formula
B5: Ibovespa = sum of the four boxes (end-2027)
C6: Bear | D6: Base | E6: Bull
B7: Sum of the box values, own mechanics and box rates (Financials by FCFE) | C7: =C54+C95+C136+C177 -> 197647.11 | D7: =D54+D95+D136+D177 -> 253454.13 | E7: =E54+E95+E136+E177 -> 281001.24 | J7: Defensives + Cyclicals + Commodities (FCFF) + Financials (FCFE), each at its box rate (Box Rates).
B8: House DCF fair value for the Ibovespa (DCF sheet) | C8: =DCF!C57 -> 191722.24 | D8: =DCF!D57 -> 235695.44 | E8: =DCF!E57 -> 261607.54
B9: Scale factor = house value / sum of the boxes | C9: =C8/C7 -> 0.970023 | D9: =D8/D7 -> 0.9299333 | E9: =E8/E7 -> 0.93098357 | J9: Close to 1: the boxes' own values add up to about the house number.
B10: Factor applied (ScaleBox in Assumptions) | C10: =IF(ScaleBox=1,C9,1) -> 0.970023 | D10: =IF(ScaleBox=1,D9,1) -> 0.9299333 | E10: =IF(ScaleBox=1,E9,1) -> 0.93098357
B11: Sum of the box fair values | C11: =C57+C98+C139+C180 -> 191722.24 | D11: =D57+D98+D139+D180 -> 235695.44 | E11: =E57+E98+E139+E180 -> 261607.54
B12: Memo: sum of the FCFF pieces at the house rate (house mechanics) = house value | C12: =C60+C101+C142+C183 -> 191722.24 | D12: =D60+D101+D142+D183 -> 235695.44 | E12: =E60+E101+E142+E183 -> 261607.54 | J12: The split itself is exact: with every box on the house mechanics and the house rate, the boxes add up to the house value.
B13: Memo: sum of the box values at the house rate (Financials by FCFE) | C13: =C61+C102+C143+C184 -> 185570.93 | D13: =D61+D102+D143+D184 -> 227874.08 | E13: =E61+E102+E143+E184 -> 252798.07 | J13: The boxes as in the house (one rate), for comparison.
B14: Memo: scale factor at the house rate | C14: =C8/C13 -> 1.033148 | D14: =D8/D13 -> 1.0343232 | E14: =E8/E13 -> 1.0348478
B16: Financials (FCFE)
C17: 2026 | D17: 2027 | E17: 2028 | F17: 2029 | G17: 2030 | H17: 2031 | J17: How it is calculated
B18: Share of sales | C18: ='Box Shares'!D19 -> 0.16009415 | D18: ='Box Shares'!E19 -> 0.1642579 | E18: =D18 -> 0.1642579 | F18: =E18 -> 0.1642579 | G18: =F18 -> 0.1642579 | H18: =G18 -> 0.1642579 | J18: Box Shares: 2026-27 consensus; 2028+ as 2027 (the house projects sales from 2027).
B19: Sales | C19: =DCF!N13*C18 -> 25442.323 | D19: =DCF!O13*D18 -> 26900.352 | E19: =DCF!P13*E18 -> 28535.894 | F19: =DCF!Q13*F18 -> 30270.876 | G19: =DCF!R13*G18 -> 32111.345 | H19: =DCF!S13*H18 -> 34063.715 | J19: House sales (DCF sheet) x share.
B20: Share of EBIT | C20: ='Box Shares'!G19 -> 0.20683299 | D20: ='Box Shares'!H19 -> 0.22119544 | E20: ='Box Shares'!I19 -> 0.22985575 | F20: =E20 -> 0.22985575 | G20: =F20 -> 0.22985575 | H20: =G20 -> 0.22985575 | J20: Box Shares: 2026-28 consensus; 2029+ as 2028.
B21: EBIT | C21: =DCF!N19*C20 -> 6842.0354 | D21: =DCF!O19*D20 -> 7715.9607 | E21: =DCF!P19*E20 -> 8578.6786 | F21: =DCF!Q19*F20 -> 9100.2623 | G21: =DCF!R19*G20 -> 9653.5582 | H21: =DCF!S19*H20 -> 10240.495
B22: Share of EBITDA | C22: ='Box Shares'!J19 -> 0.25196485 | D22: ='Box Shares'!K19 -> 0.25096616 | E22: ='Box Shares'!L19 -> 0.2555345 | F22: =E22 -> 0.2555345 | G22: =F22 -> 0.2555345 | H22: =G22 -> 0.2555345 | J22: Box Shares: 2026-28; 2029+ as 2028. Financials includes the EBITDA the index imputes to banks.
B23: EBITDA | C23: =DCF!N21*C22 -> 12427.914 | D23: =DCF!O21*D22 -> 12728.251 | E23: =DCF!P21*E22 -> 13287.025 | F23: =DCF!Q21*F22 -> 14127.636 | G23: =DCF!R21*G22 -> 14986.597 | H23: =DCF!S21*H22 -> 15897.782
B24: Share of capex | C24: ='Box Shares'!P19 -> 0.24802703 | D24: ='Box Shares'!Q19 -> 0.24938824 | E24: =D24 -> 0.24938824 | F24: =E24 -> 0.24938824 | G24: =F24 -> 0.24938824 | H24: =G24 -> 0.24938824 | J24: Box Shares: 2026-27; 2028+ as 2027.
B25: Capex | C25: =DCF!N33*C24 -> -4751.9498 | D25: =DCF!O33*D24 -> -4821.4228 | E25: =DCF!P33*E24 -> -4765.7786 | F25: =DCF!Q33*F24 -> -5055.5379 | G25: =DCF!R33*G24 -> -4387.8392 | H25: =DCF!S33*H24 -> -4654.6199
B26: Share of net income | C26: ='Box Shares'!M19 -> 0.27229092 | D26: ='Box Shares'!N19 -> 0.29478935 | E26: ='Box Shares'!O19 -> 0.3064974 | F26: =E26 -> 0.3064974 | G26: =F26 -> 0.3064974 | H26: =G26 -> 0.3064974 | J26: Box Shares: 2026-28; 2029+ as 2028.
B27: Net income | C27: =DCF!N29*C26 -> 5706.6731 | D27: =DCF!O29*D26 -> 6386.9061 | E27: =DCF!P29*E26 -> 7103.6903 | F27: =DCF!Q29*F26 -> 7535.5947 | G27: =DCF!R29*G26 -> 7993.7588 | H27: =DCF!S29*H26 -> 8479.7794
B28: D&A = EBITDA - EBIT | C28: =C23-C21 -> 5585.8788 | D28: =D23-D21 -> 5012.2903 | E28: =E23-E21 -> 4708.346 | F28: =F23-F21 -> 5027.3741 | G28: =G23-G21 -> 5333.0385 | H28: =H23-H21 -> 5657.2872
B29: Tax rate (house) | C29: =DCF!N25 -> -0.24 | D29: =DCF!O25 -> -0.24 | E29: =DCF!P25 -> -0.24 | F29: =DCF!Q25 -> -0.24 | G29: =DCF!R25 -> -0.24 | H29: =DCF!S25 -> -0.24 | J29: DCF sheet (house, -24%).
B30: NOPAT = EBIT x (1 + tax rate) | C30: =C21*(1+C29) -> 5199.9469 | D30: =D21*(1+D29) -> 5864.1301 | E30: =E21*(1+E29) -> 6519.7958 | F30: =F21*(1+F29) -> 6916.1993 | G30: =G21*(1+G29) -> 7336.7043 | H30: =H21*(1+H29) -> 7782.7759
B31: Working capital (NWC) = -NWC % x sales | C31: =-NWCpct*C19 -> -1017.6929 | D31: =-NWCpct*D19 -> -1076.0141 | E31: =-NWCpct*E19 -> -1141.4357 | F31: =-NWCpct*F19 -> -1210.835 | G31: =-NWCpct*G19 -> -1284.4538 | H31: =-NWCpct*H19 -> -1362.5486
B32: Change in NWC | D32: =D31-C31 -> -58.321171 | E32: =E31-D31 -> -65.421657 | F32: =F31-E31 -> -69.399293 | G32: =G31-F31 -> -73.61877 | H32: =H31-G31 -> -78.094792
B33: FCFF, house = D&A + NOPAT + capex + NWC (level) | C33: =C28+C30+C25+C31 -> 5016.1829 | D33: =D28+D30+D25+D31 -> 4978.9835 | E33: =E28+E30+E25+E31 -> 5320.9274 | F33: =F28+F30+F25+F31 -> 5677.2005 | G33: =G28+G30+G25+G31 -> 6997.4497 | H33: =H28+H30+H25+H31 -> 7422.8946
B34: FCFF with the change in NWC | D34: =D28+D30+D25+D32 -> 5996.6764 | E34: =E28+E30+E25+E32 -> 6396.9415 | F34: =F28+F30+F25+F32 -> 6818.6362 | G34: =G28+G30+G25+G32 -> 8208.2847 | H34: =H28+H30+H25+H32 -> 8707.3484
B35: FCFF used (switch FixNWC) | C35: =C33 -> 5016.1829 | D35: =IF(FixNWC=1,D34,D33) -> 4978.9835 | E35: =IF(FixNWC=1,E34,E33) -> 5320.9274 | F35: =IF(FixNWC=1,F34,F33) -> 5677.2005 | G35: =IF(FixNWC=1,G34,G33) -> 6997.4497 | H35: =IF(FixNWC=1,H34,H33) -> 7422.8946 | J35: FixNWC = 0: house row; 1: corrected row. Sum of the boxes = house FCFF (Checks).
B36: ROE (Financials, Box Shares section 4) | C36: =FinROE -> 0.19870618 | D36: =FinROE -> 0.19870618 | E36: =FinROE -> 0.19870618 | F36: =FinROE -> 0.19870618 | G36: =FinROE -> 0.19870618 | H36: =FinROE -> 0.19870618
B37: FCFE = net income x (1 - g / ROE) | C37: =C27*(1-gLT/C36) -> 4356.8729 | D37: =D27*(1-gLT/D36) -> 4876.2103 | E37: =E27*(1-gLT/E36) -> 5423.4535 | F37: =F27*(1-gLT/F36) -> 5753.1994 | G37: =G27*(1-gLT/G36) -> 6102.994 | H37: =H27*(1-gLT/H36) -> 6474.056 | J37: Financials only: the value used for the box (same rate and g as the house).
B39: Valuation at the end of 2027 | C39: Bear | D39: Base | E39: Bull
B40: Discount rate of the box (Box Rates) | C40: ='Box Rates'!C21 -> 0.13760273 | D40: ='Box Rates'!D21 -> 0.12151612 | E40: ='Box Rates'!E21 -> 0.11448979 | J40: BoxRate 0: the house rate; 1: g + (house rate - g) x the box's relative cash yield, at least real rate + floor; 2: CAPM, real rate + beta x ERP.
B41: FCFF 2031 | C41: =$H$35 -> 7422.8946 | D41: =$H$35 -> 7422.8946 | E41: =$H$35 -> 7422.8946
B42: Terminal value = FCFF 2031 x (1 + g) / (rate - g) | C42: =C41*(1+gLT)/(C40-gLT) -> 85778.553 | D42: =D41*(1+gLT)/(D40-gLT) -> 104296.5 | E42: =E41*(1+gLT)/(E40-gLT) -> 115154.77
B43: Periods the TV is discounted | C43: =5-FixTV -> 5 | D43: =5-FixTV -> 5 | E43: =5-FixTV -> 5
B44: Present value of FCFF 2028-2031 | C44: =NPV(C40,$E$35:$H$35) -> 18249.282 | D44: =NPV(D40,$E$35:$H$35) -> 18910.408 | E44: =NPV(E40,$E$35:$H$35) -> 19211.269
B45: Present value of the terminal value | C45: =C42/(1+C40)^C43 -> 45022.084 | D45: =D42/(1+D40)^D43 -> 58781.701 | E45: =E42/(1+E40)^E43 -> 66973.265
B46: Value of the FCFF | C46: =C44+C45 -> 63271.366 | D46: =D44+D45 -> 77692.109 | E46: =E44+E45 -> 86184.534
B47: Net debt subtracted (switch FixND) | C47: =IF(FixND=1,NDmult*DCF!$M$21*$C$22,0) -> 0 | D47: =IF(FixND=1,NDmult*DCF!$M$21*$C$22,0) -> 0 | E47: =IF(FixND=1,NDmult*DCF!$M$21*$C$22,0) -> 0 | J47: 1.6x the house EBITDA of 2025 x the box's 2026 EBITDA share, only with FixND = 1.
B48: Value by the house mechanics (FCFF) | C48: =C46-C47 -> 63271.366 | D48: =D46-D47 -> 77692.109 | E48: =E46-E47 -> 86184.534 | J48: Financials: shown for the reconciliation with the house value; not used.
B49: FCFE 2031 | C49: =$H$37 -> 6474.056 | D49: =$H$37 -> 6474.056 | E49: =$H$37 -> 6474.056
B50: Terminal value = FCFE 2031 x (1 + g) / (rate - g) | C50: =C49*(1+gLT)/(C40-gLT) -> 74813.827 | D50: =D49*(1+gLT)/(D40-gLT) -> 90964.703 | E50: =E49*(1+gLT)/(E40-gLT) -> 100435
B51: Present value of FCFE 2028-2031 | C51: =NPV(C40,$E$37:$H$37) -> 17224.036 | D51: =NPV(D40,$E$37:$H$37) -> 17828.42 | E51: =NPV(E40,$E$37:$H$37) -> 18103.286
B52: Present value of the FCFE terminal value | C52: =C50/(1+C40)^C43 -> 39267.093 | D52: =D50/(1+D40)^D43 -> 51267.874 | E52: =E50/(1+E40)^E43 -> 58412.343
B53: Value by FCFE | C53: =C51+C52 -> 56491.129 | D53: =D51+D52 -> 69096.294 | E53: =E51+E52 -> 76515.629
B54: Box value, own mechanics | C54: =C53 -> 56491.129 | D54: =D53 -> 69096.294 | E54: =E53 -> 76515.629 | J54: FCFF value (Financials: FCFE value).
B55: Index points today | C55: ='Box Shares'!$C$7 -> 60927.304 | D55: ='Box Shares'!$C$7 -> 60927.304 | E55: ='Box Shares'!$C$7 -> 60927.304
B56: Upside, own value | C56: =C54/C55-1 -> -0.072810939 | D56: =D54/D55-1 -> 0.13407767 | E56: =E54/E55-1 -> 0.25585122
B57: Fair value at the end of 2027 (scaled) | C57: =C54*C$10 -> 54797.695 | D57: =D54*D$10 -> 64254.945 | E57: =E54*E$10 -> 71234.793 | J57: Own value x factor applied (top of the sheet).
B58: Upside | C58: =C57/C55-1 -> -0.10060529 | D58: =D57/D55-1 -> 0.054616589 | E58: =E57/E55-1 -> 0.16917685
B59: Memo: house discount rate (DCF sheet) | C59: =DCF!C48 -> 0.145 | D59: =DCF!D48 -> 0.1276 | E59: =DCF!E48 -> 0.12
B60: Memo: value of the FCFF at the house rate (house mechanics) | C60: =NPV(C59,$E$35:$H$35)+$H$35*(1+gLT)/(C59-gLT)/(1+C59)^C43-C47 -> 58254.029 | D60: =NPV(D59,$E$35:$H$35)+$H$35*(1+gLT)/(D59-gLT)/(1+D59)^D43-D47 -> 71550.322 | E60: =NPV(E59,$E$35:$H$35)+$H$35*(1+gLT)/(E59-gLT)/(1+E59)^E43-E47 -> 79384.433 | J60: Same FCFF at the house rate: the four boxes add up to the house value exactly (Checks).
B61: Memo: box value at the house rate (Financials by FCFE) | C61: =NPV(C59,$E$37:$H$37)+$H$37*(1+gLT)/(C59-gLT)/(1+C59)^C43 -> 52102.715 | D61: =NPV(D59,$E$37:$H$37)+$H$37*(1+gLT)/(D59-gLT)/(1+D59)^D43 -> 63728.962 | E61: =NPV(E59,$E$37:$H$37)+$H$37*(1+gLT)/(E59-gLT)/(1+E59)^E43 -> 70574.966 | J61: The box as in the house (one rate); Summary compares it with the box-rate value.
B64: Defensives (house FCFF)
C65: 2026 | D65: 2027 | E65: 2028 | F65: 2029 | G65: 2030 | H65: 2031 | J65: How it is calculated
B66: Share of sales | C66: ='Box Shares'!D20 -> 0.25320998 | D66: ='Box Shares'!E20 -> 0.26048992 | E66: =D66 -> 0.26048992 | F66: =E66 -> 0.26048992 | G66: =F66 -> 0.26048992 | H66: =G66 -> 0.26048992 | J66: Box Shares: 2026-27 consensus; 2028+ as 2027 (the house projects sales from 2027).
B67: Sales | C67: =DCF!N13*C66 -> 40240.383 | D67: =DCF!O13*D66 -> 42660.173 | E67: =DCF!P13*E66 -> 45253.912 | F67: =DCF!Q13*F66 -> 48005.35 | G67: =DCF!R13*G66 -> 50924.075 | H67: =DCF!S13*H66 -> 54020.259 | J67: House sales (DCF sheet) x share.
B68: Share of EBIT | C68: ='Box Shares'!G20 -> 0.20945024 | D68: ='Box Shares'!H20 -> 0.23407448 | E68: ='Box Shares'!I20 -> 0.24415677 | F68: =E68 -> 0.24415677 | G68: =F68 -> 0.24415677 | H68: =G68 -> 0.24415677 | J68: Box Shares: 2026-28 consensus; 2029+ as 2028.
B69: EBIT | C69: =DCF!N19*C68 -> 6928.614 | D69: =DCF!O19*D68 -> 8165.2202 | E69: =DCF!P19*E68 -> 9112.4215 | F69: =DCF!Q19*F68 -> 9666.4567 | G69: =DCF!R19*G68 -> 10254.177 | H69: =DCF!S19*H68 -> 10877.631
B70: Share of EBITDA | C70: ='Box Shares'!J20 -> 0.19172465 | D70: ='Box Shares'!K20 -> 0.21119668 | E70: ='Box Shares'!L20 -> 0.22223939 | F70: =E70 -> 0.22223939 | G70: =F70 -> 0.22223939 | H70: =G70 -> 0.22223939 | J70: Box Shares: 2026-28; 2029+ as 2028. Financials includes the EBITDA the index imputes to banks.
B71: EBITDA | C71: =DCF!N21*C70 -> 9456.6268 | D71: =DCF!O21*D70 -> 10711.262 | E71: =DCF!P21*E70 -> 11555.78 | F71: =DCF!Q21*F70 -> 12286.863 | G71: =DCF!R21*G70 -> 13033.904 | H71: =DCF!S21*H70 -> 13826.366
B72: Share of capex | C72: ='Box Shares'!P20 -> 0.2478664 | D72: ='Box Shares'!Q20 -> 0.24129138 | E72: =D72 -> 0.24129138 | F72: =E72 -> 0.24129138 | G72: =F72 -> 0.24129138 | H72: =G72 -> 0.24129138 | J72: Box Shares: 2026-27; 2028+ as 2027.
B73: Capex | C73: =DCF!N33*C72 -> -4748.8724 | D73: =DCF!O33*D72 -> -4664.8863 | E73: =DCF!P33*E72 -> -4611.0486 | F73: =DCF!Q33*F72 -> -4891.4004 | G73: =DCF!R33*G72 -> -4245.3798 | H73: =DCF!S33*H72 -> -4503.4989
B74: Share of net income | C74: ='Box Shares'!M20 -> 0.14197048 | D74: ='Box Shares'!N20 -> 0.17585707 | E74: ='Box Shares'!O20 -> 0.19377661 | F74: =E74 -> 0.19377661 | G74: =F74 -> 0.19377661 | H74: =G74 -> 0.19377661 | J74: Box Shares: 2026-28; 2029+ as 2028.
B75: Net income | C75: =DCF!N29*C74 -> 2975.4173 | D75: =DCF!O29*D74 -> 3810.1192 | E75: =DCF!P29*E74 -> 4491.1605 | F75: =DCF!Q29*F74 -> 4764.2231 | G75: =DCF!R29*G74 -> 5053.8878 | H75: =DCF!S29*H74 -> 5361.1642
B76: D&A = EBITDA - EBIT | C76: =C71-C69 -> 2528.0128 | D76: =D71-D69 -> 2546.0418 | E76: =E71-E69 -> 2443.3581 | F76: =F71-F69 -> 2620.4064 | G76: =G71-G69 -> 2779.7271 | H76: =H71-H69 -> 2948.7345
B77: Tax rate (house) | C77: =DCF!N25 -> -0.24 | D77: =DCF!O25 -> -0.24 | E77: =DCF!P25 -> -0.24 | F77: =DCF!Q25 -> -0.24 | G77: =DCF!R25 -> -0.24 | H77: =DCF!S25 -> -0.24 | J77: DCF sheet (house, -24%).
B78: NOPAT = EBIT x (1 + tax rate) | C78: =C69*(1+C77) -> 5265.7466 | D78: =D69*(1+D77) -> 6205.5673 | E78: =E69*(1+E77) -> 6925.4403 | F78: =F69*(1+F77) -> 7346.5071 | G78: =G69*(1+G77) -> 7793.1747 | H78: =H69*(1+H77) -> 8266.9998
B79: Working capital (NWC) = -NWC % x sales | C79: =-NWCpct*C67 -> -1609.6153 | D79: =-NWCpct*D67 -> -1706.4069 | E79: =-NWCpct*E67 -> -1810.1565 | F79: =-NWCpct*F67 -> -1920.214 | G79: =-NWCpct*G67 -> -2036.963 | H79: =-NWCpct*H67 -> -2160.8103
B80: Change in NWC | D80: =D79-C79 -> -96.791621 | E80: =E79-D79 -> -103.74954 | F80: =F79-E79 -> -110.05751 | G80: =G79-F79 -> -116.74901 | H80: =H79-G79 -> -123.84735
B81: FCFF, house = D&A + NOPAT + capex + NWC (level) | C81: =C76+C78+C73+C79 -> 1435.2717 | D81: =D76+D78+D73+D79 -> 2380.3159 | E81: =E76+E78+E73+E79 -> 2947.5933 | F81: =F76+F78+F73+F79 -> 3155.2991 | G81: =G76+G78+G73+G79 -> 4290.559 | H81: =H76+H78+H73+H79 -> 4551.425
B82: FCFF with the change in NWC | D82: =D76+D78+D73+D80 -> 3989.9312 | E82: =E76+E78+E73+E80 -> 4654.0003 | F82: =F76+F78+F73+F80 -> 4965.4556 | G82: =G76+G78+G73+G80 -> 6210.773 | H82: =H76+H78+H73+H80 -> 6588.388
B83: FCFF used (switch FixNWC) | C83: =C81 -> 1435.2717 | D83: =IF(FixNWC=1,D82,D81) -> 2380.3159 | E83: =IF(FixNWC=1,E82,E81) -> 2947.5933 | F83: =IF(FixNWC=1,F82,F81) -> 3155.2991 | G83: =IF(FixNWC=1,G82,G81) -> 4290.559 | H83: =IF(FixNWC=1,H82,H81) -> 4551.425 | J83: FixNWC = 0: house row; 1: corrected row. Sum of the boxes = house FCFF (Checks).
B85: Valuation at the end of 2027 | C85: Bear | D85: Base | E85: Bull
B86: Discount rate of the box (Box Rates) | C86: ='Box Rates'!C22 -> 0.10925386 | D86: ='Box Rates'!D22 -> 0.098200625 | E86: ='Box Rates'!E22 -> 0.093372774 | J86: BoxRate 0: the house rate; 1: g + (house rate - g) x the box's relative cash yield, at least real rate + floor; 2: CAPM, real rate + beta x ERP.
B87: FCFF 2031 | C87: =$H$83 -> 4551.425 | D87: =$H$83 -> 4551.425 | E87: =$H$83 -> 4551.425
B88: Terminal value = FCFF 2031 x (1 + g) / (rate - g) | C88: =C87*(1+gLT)/(C86-gLT) -> 76546.93 | D88: =D87*(1+gLT)/(D86-gLT) -> 93071.95 | E88: =E87*(1+gLT)/(E86-gLT) -> 102761.63
B89: Periods the TV is discounted | C89: =5-FixTV -> 5 | D89: =5-FixTV -> 5 | E89: =5-FixTV -> 5
B90: Present value of FCFF 2028-2031 | C90: =NPV(C86,$E$83:$H$83) -> 11371.428 | D90: =NPV(D86,$E$83:$H$83) -> 11668.799 | E90: =NPV(E86,$E$83:$H$83) -> 11802.541
B91: Present value of the terminal value | C91: =C88/(1+C86)^C89 -> 45579.865 | D91: =D88/(1+D86)^D89 -> 58265.353 | E91: =E88/(1+E86)^E89 -> 65764.227
B92: Value of the FCFF | C92: =C90+C91 -> 56951.293 | D92: =D90+D91 -> 69934.152 | E92: =E90+E91 -> 77566.768
B93: Net debt subtracted (switch FixND) | C93: =IF(FixND=1,NDmult*DCF!$M$21*$C$70,0) -> 0 | D93: =IF(FixND=1,NDmult*DCF!$M$21*$C$70,0) -> 0 | E93: =IF(FixND=1,NDmult*DCF!$M$21*$C$70,0) -> 0 | J93: 1.6x the house EBITDA of 2025 x the box's 2026 EBITDA share, only with FixND = 1.
B94: Value by the house mechanics (FCFF) | C94: =C92-C93 -> 56951.293 | D94: =D92-D93 -> 69934.152 | E94: =E92-E93 -> 77566.768 | J94: Financials: shown for the reconciliation with the house value; not used.
B95: Box value, own mechanics | C95: =C94 -> 56951.293 | D95: =D94 -> 69934.152 | E95: =E94 -> 77566.768 | J95: FCFF value (Financials: FCFE value).
B96: Index points today | C96: ='Box Shares'!$C$8 -> 55822.367 | D96: ='Box Shares'!$C$8 -> 55822.367 | E96: ='Box Shares'!$C$8 -> 55822.367
B97: Upside, own value | C97: =C95/C96-1 -> 0.020223535 | D97: =D95/D96-1 -> 0.25279803 | E97: =E95/E96-1 -> 0.38952845
B98: Fair value at the end of 2027 (scaled) | C98: =C95*C$10 -> 55244.064 | D98: =D95*D$10 -> 65034.096 | E98: =E95*E$10 -> 72213.386 | J98: Own value x factor applied (top of the sheet).
B99: Upside | C99: =C98/C96-1 -> -0.010359706 | D99: =D98/D96-1 -> 0.1650186 | E99: =E98/E96-1 -> 0.29362816
B100: Memo: house discount rate (DCF sheet) | C100: =DCF!C48 -> 0.145 | D100: =DCF!D48 -> 0.1276 | E100: =DCF!E48 -> 0.12
B101: Memo: value of the FCFF at the house rate (house mechanics) | C101: =NPV(C100,$E$83:$H$83)+$H$83*(1+gLT)/(C100-gLT)/(1+C100)^C89-C93 -> 35195.506 | D101: =NPV(D100,$E$83:$H$83)+$H$83*(1+gLT)/(D100-gLT)/(1+D100)^D89-D93 -> 43336.294 | E101: =NPV(E100,$E$83:$H$83)+$H$83*(1+gLT)/(E100-gLT)/(1+E100)^E89-E93 -> 48134.476 | J101: Same FCFF at the house rate: the four boxes add up to the house value exactly (Checks).
B102: Memo: box value at the house rate (Financials by FCFE) | C102: =C101 -> 35195.506 | D102: =D101 -> 43336.294 | E102: =E101 -> 48134.476 | J102: The box as in the house (one rate); Summary compares it with the box-rate value.
B105: Cyclicals (house FCFF)
C106: 2026 | D106: 2027 | E106: 2028 | F106: 2029 | G106: 2030 | H106: 2031 | J106: How it is calculated
B107: Share of sales | C107: ='Box Shares'!D21 -> 0.10558339 | D107: ='Box Shares'!E21 -> 0.11218492 | E107: =D107 -> 0.11218492 | F107: =E107 -> 0.11218492 | G107: =F107 -> 0.11218492 | H107: =G107 -> 0.11218492 | J107: Box Shares: 2026-27 consensus; 2028+ as 2027 (the house projects sales from 2027).
B108: Sales | C108: =DCF!N13*C107 -> 16779.418 | D108: =DCF!O13*D107 -> 18372.413 | E108: =DCF!P13*E107 -> 19489.455 | F108: =DCF!Q13*F107 -> 20674.414 | G108: =DCF!R13*G107 -> 21931.419 | H108: =DCF!S13*H107 -> 23264.849 | J108: House sales (DCF sheet) x share.
...

Sheet DCF
B1: Ibovespa - DCF (house model rolled to end-2027)
B2: Replica of Target rows 17-65 of DCF Ibov 2026_Out.xlsx, in Ibovespa points, extended to 2031. Blue = house file input; pink = projection rule.
B3: Legend: | C3: input | D3: assumption | E3: formula
B5: Projections (index points)
C6: 2015 | D6: 2016 | E6: 2017 | F6: 2018 | G6: 2019 | H6: 2020 | I6: 2021 | J6: 2022 | K6: 2023 | L6: 2024 | M6: 2025 | N6: 2026 | O6: 2027 | P6: 2028 | Q6: 2029 | R6: 2030 | S6: 2031 | U6: How it is calculated (house Target row)
C7: Actual | D7: Actual | E7: Actual | F7: Actual | G7: Actual | H7: Actual | I7: Actual | J7: Actual | K7: Actual | L7: Actual | M7: Actual | N7: Consensus | O7: Consensus | P7: Consensus | Q7: Projection | R7: Projection | S7: Projection
B8: Real GDP | J8: 0.029 | K8: 0.029 | L8: 0.031 | M8: 0.021 | N8: 0.018 | O8: 0.01 | P8: 0.02 | Q8: 0.02 | R8: 0.02 | S8: 0.02
B9: Inflation | C9: 0.1067 | D9: 0.0629 | E9: 0.0295 | F9: 0.0375 | G9: 0.0431 | H9: 0.045 | I9: 0.101 | J9: 0.058 | K9: 0.046 | L9: 0.046 | M9: 0.045 | N9: 0.038 | O9: 0.04 | P9: 0.04 | Q9: 0.04 | R9: 0.04 | S9: 0.04
B10: Nominal GDP | C10: =(1+C8)*(1+C9)-1 -> 0.1067 | D10: =(1+D8)*(1+D9)-1 -> 0.0629 | E10: =(1+E8)*(1+E9)-1 -> 0.0295 | F10: =(1+F8)*(1+F9)-1 -> 0.0375 | G10: =(1+G8)*(1+G9)-1 -> 0.0431 | H10: =(1+H8)*(1+H9)-1 -> 0.045 | I10: =(1+I8)*(1+I9)-1 -> 0.101 | J10: =(1+J8)*(1+J9)-1 -> 0.088682 | ... S10: =(1+S8)*(1+S9)-1 -> 0.0608 | U10: (1 + real GDP) x (1 + inflation) - 1 (row 20).
B11: Sales growth | D11: =D13/C13-1 -> 0.031809353 | E11: =E13/D13-1 -> 0.014830489 | F11: =F13/E13-1 -> 0.16663413 | G11: =G13/F13-1 -> 0.12933978 | H11: =H13/G13-1 -> 0.081369435 | I11: =I13/H13-1 -> 0.33636272 | J11: =J13/I13-1 -> 0.20564508 | K11: =K13/J13-1 -> 0.058209825 | ... O11: =O13/N13-1 -> 0.030505723 | P11: =P10*P12 -> 0.0608 | Q11: =Q10*Q12 -> 0.0608 | R11: =R10*R12 -> 0.0608 | S11: =S10*S12 -> 0.0608 | U11: Actual/consensus: sales / previous - 1. Projection: nominal GDP x ratio (row 21).
B12: Ratio (sales growth / nominal GDP) | D12: =D11/D10 -> 0.50571309 | E12: =E11/E10 -> 0.50272844 | F12: =F11/F10 -> 4.4435767 | G12: =G11/G10 -> 3.0009229 | H12: =H11/H10 -> 1.8082097 | I12: =I11/I10 -> 3.3303239 | J12: =J11/J10 -> 2.3189044 | K12: =K11/K10 -> 0.76256746 | ... O12: =O11/O10 -> 0.60527228 | P12: 1 | Q12: 1 | R12: 1 | S12: 1
B13: Sales | C13: 51357.85 | D13: 52991.51 | E13: 53777.4 | F13: 62738.55 | G13: 70853.14 | H13: 76618.42 | I13: 102390 | J13: 123446 | K13: 130631.77 | L13: 138166 | M13: 150140 | N13: 158921 | O13: 163769 | P13: =O13*(1+P11) -> 173726.16 | Q13: =P13*(1+Q11) -> 184288.71 | R13: =Q13*(1+R11) -> 195493.46 | S13: =R13*(1+S11) -> 207379.46 | U13: To 2027: house file (consensus 2026-27). 2028+: previous x (1 + growth) (row 25).
B14: COGS | C14: =C13*(C15-1) -> -38374.586 | D14: =D13*(D15-1) -> -39865.513 | E14: =E13*(E15-1) -> -38940.215 | F14: =F13*(F15-1) -> -44801.599 | G14: =G13*(G15-1) -> -50192.364 | H14: =H13*(H15-1) -> -53939.368 | I14: =I13*(I15-1) -> -65529.6 | J14: =J13*(J15-1) -> -82708.82 | ... S14: =S13*(S15-1) -> -133199.83 | U14: Sales x (gross margin - 1) (row 26).
B15: Gross margin % | C15: 0.2528 | D15: 0.2477 | E15: 0.2759 | F15: 0.2859 | G15: 0.2916 | H15: 0.296 | I15: 0.36 | J15: 0.33 | K15: 0.2757 | L15: 0.2514 | M15: 0.2737 | N15: 0.388 | O15: 0.3827 | P15: 0.3577 | Q15: =P15 -> 0.3577 | R15: =Q15 -> 0.3577 | S15: =R15 -> 0.3577 | U15: To 2028: house file. 2029+: previous year (row 27).
B16: Gross profit | C16: =C13+C14 -> 12983.264 | D16: =D13+D14 -> 13125.997 | E16: =E13+E14 -> 14837.185 | F16: =F13+F14 -> 17936.951 | G16: =G13+G14 -> 20660.776 | H16: =H13+H14 -> 22679.052 | I16: =I13+I14 -> 36860.4 | J16: =J13+J14 -> 40737.18 | ... S16: =S13+S14 -> 74179.633
B17: SG&A | C17: =C19-C16 -> -11461.954 | D17: =D19-D16 -> -6806.437 | E17: =E19-E16 -> -7556.5447 | F17: =F19-F16 -> -8126.6114 | G17: =G19-G16 -> -11860.076 | H17: =H19-H16 -> -11988.992 | I17: =I19-I16 -> -13266.4 | J17: =J19-J16 -> -14963.67 | ... P17: =P19-P16 -> -24819.836 | Q17: =Q13*Q18 -> -26328.882 | R17: =R13*R18 -> -27929.678 | S17: =S13*S18 -> -29627.802 | U17: To 2028: EBIT - gross profit. 2029+: sales x SG&A % (row 29).
B18: SG&A % of sales | C18: =C17/C13 -> -0.22317824 | D18: =D17/D13 -> -0.12844392 | E18: =E17/E13 -> -0.14051525 | F18: =F17/F13 -> -0.12953139 | G18: =G17/G13 -> -0.16738956 | H18: =H17/H13 -> -0.15647663 | I18: =I17/I13 -> -0.12956734 | J18: =J17/J13 -> -0.12121632 | ... P18: =P17/P13 -> -0.14286758 | Q18: =P18 -> -0.14286758 | R18: =Q18 -> -0.14286758 | S18: =R18 -> -0.14286758 | U18: 2029+: previous year's % (row 30).
B19: EBIT | C19: 1521.31 | D19: 6319.56 | E19: 7280.64 | F19: 9810.34 | G19: 8800.7 | H19: 10690.06 | I19: 23594 | J19: 25773.51 | K19: 21324.34 | L19: 25291.3 | M19: 20846 | N19: 33080 | O19: 34883 | P19: 37322.01 | Q19: =Q16+Q17 -> 39591.188 | R19: =R16+R17 -> 41998.332 | S19: =S16+S17 -> 44551.831 | U19: To 2028: house file (consensus). 2029+: gross profit + SG&A (row 31).
B20: EBIT margin % | C20: =C19/C13 -> 0.029621762 | D20: =D19/D13 -> 0.11925608 | E20: =E19/E13 -> 0.13538475 | F20: =F19/F13 -> 0.15636861 | G20: =G19/G13 -> 0.12421044 | H20: =H19/H13 -> 0.13952337 | I20: =I19/I13 -> 0.23043266 | J20: =J19/J13 -> 0.20878368 | ... S20: =S19/S13 -> 0.21483242
B21: EBITDA | C21: 11322.26 | D21: 11803.92 | E21: 13642.8 | F21: 17850.25 | G21: 18979.35 | H21: 19022.66 | I21: 31545 | J21: 36387.17 | K21: 32032.37 | L21: 37339 | M21: 33801 | N21: 49324 | O21: 50717 | P21: 51996.99 | Q21: =Q13*Q22 -> 55286.612 | R21: =R13*R22 -> 58648.038 | S21: =S13*S22 -> 62213.838 | U21: To 2028: house file (consensus). 2029+: sales x EBITDA margin (row 33).
B22: EBITDA margin % | C22: =C21/C13 -> 0.22045822 | D22: =D21/D13 -> 0.22275115 | E22: =E21/E13 -> 0.25369021 | F22: =F21/F13 -> 0.28451805 | G22: =G21/G13 -> 0.26786886 | H22: =H21/H13 -> 0.24827789 | I22: =I21/I13 -> 0.30808673 | J22: =J21/J13 -> 0.29476184 | ... P22: =P21/P13 -> 0.29930433 | Q22: 0.3 | R22: 0.3 | S22: 0.3 | U22: 2029+: 30% (house, row 34).
B23: D&A | C23: =C21-C19 -> 9800.95 | D23: =D21-D19 -> 5484.36 | E23: =E21-E19 -> 6362.16 | F23: =F21-F19 -> 8039.91 | G23: =G21-G19 -> 10178.65 | H23: =H21-H19 -> 8332.6 | I23: =I21-I19 -> 7951 | J23: =J21-J19 -> 10613.66 | ... S23: =S21-S19 -> 17662.007 | U23: EBITDA - EBIT (row 35).
B24: D&A % of sales | C24: =C23/C13 -> 0.19083645 | D24: =D23/D13 -> 0.10349507 | E24: =E23/E13 -> 0.11830546 | F24: =F23/F13 -> 0.12814944 | G24: =G23/G13 -> 0.14365842 | H24: =H23/H13 -> 0.10875453 | I24: =I23/I13 -> 0.077654068 | J24: =J23/J13 -> 0.08597816 | ... S24: =S23/S13 -> 0.085167582
B25: Tax rate | C25: -0.25 | D25: =C25 -> -0.25 | E25: =D25 -> -0.25 | F25: =E25 -> -0.25 | G25: =F25 -> -0.25 | H25: =G25 -> -0.25 | I25: =H25 -> -0.25 | J25: =I25 -> -0.25 | K25: =J25 -> -0.25 | L25: -0.24 | M25: =L25 -> -0.24 | N25: =M25 -> -0.24 | O25: =N25 -> -0.24 | P25: =O25 -> -0.24 | Q25: =P25 -> -0.24 | R25: =Q25 -> -0.24 | S25: =R25 -> -0.24 | U25: -25% to 2023, -24% from 2024 (row 37).
B26: NOPAT | C26: =C19*(1+C25) -> 1140.9825 | D26: =D19*(1+D25) -> 4739.67 | E26: =E19*(1+E25) -> 5460.48 | F26: =F19*(1+F25) -> 7357.755 | G26: =G19*(1+G25) -> 6600.525 | H26: =H19*(1+H25) -> 8017.545 | I26: =I19*(1+I25) -> 17695.5 | J26: =J19*(1+J25) -> 19330.132 | ... S26: =S19*(1+S25) -> 33859.392 | U26: EBIT x (1 + tax rate) (row 38).
B27: Net interest expense | C27: =C29-C26 -> -1992.7125 | D27: =D29-D26 -> -1693.5 | E27: =E29-E26 -> -1553.31 | F27: =F29-F26 -> -1433.345 | G27: =G29-G26 -> -1239.105 | H27: =H29-H26 -> -4140.545 | I27: =I29-I26 -> -2007.5 | J27: =J29-J26 -> -561.0525 | ... P27: =P29-P26 -> -5187.7276 | Q27: =Q13*Q28 -> -5503.1414 | R27: =R13*R28 -> -5837.7324 | S27: =S13*S28 -> -6192.6666 | U27: To 2028: net income - NOPAT. 2029+: sales x interest % (row 39).
B28: Interest % of sales | C28: =C27/C13 -> -0.038800544 | D28: =D27/D13 -> -0.031957949 | E28: =E27/E13 -> -0.028884067 | F28: =F27/F13 -> -0.02284632 | G28: =G27/G13 -> -0.017488357 | H28: =H27/H13 -> -0.054041117 | I28: =I27/I13 -> -0.019606407 | J28: =J27/J13 -> -0.0045449225 | ... P28: =P27/P13 -> -0.029861523 | Q28: =P28 -> -0.029861523 | R28: =Q28 -> -0.029861523 | S28: =R28 -> -0.029861523 | U28: 2029+: previous year's % (row 40).
B29: Net income (EPS, index pts) | C29: -851.73 | D29: 3046.17 | E29: 3907.17 | F29: 5924.41 | G29: 5361.42 | H29: 3877 | I29: 15688 | J29: 18769.08 | K29: 13729.57 | L29: 14944 | M29: 13889 | N29: 20958 | O29: 21666 | P29: 23177 | Q29: =Q26+Q27 -> 24586.162 | R29: =R26+R27 -> 26081 | S29: =S26+S27 -> 27666.725 | U29: To 2028: house file (consensus EPS). 2029+: NOPAT + net interest (row 41).
B30: Net margin % | C30: =C29/C13 -> -0.016584222 | D30: =D29/D13 -> 0.057484114 | E30: =E29/E13 -> 0.072654498 | F30: =F29/F13 -> 0.094430139 | G30: =G29/G13 -> 0.075669476 | H30: =H29/H13 -> 0.050601409 | I30: =I29/I13 -> 0.15321809 | J30: =J29/J13 -> 0.15204284 | ... S30: =S29/S13 -> 0.13341111
B31: Working capital (NWC) | C31: =-NWCpct*C13 -> -2054.314 | D31: =-NWCpct*D13 -> -2119.6604 | E31: =-NWCpct*E13 -> -2151.096 | F31: =-NWCpct*F13 -> -2509.542 | G31: =-NWCpct*G13 -> -2834.1256 | H31: =-NWCpct*H13 -> -3064.7368 | I31: =-NWCpct*I13 -> -4095.6 | J31: =-NWCpct*J13 -> -4937.84 | ... S31: =-NWCpct*S13 -> -8295.1784 | U31: -NWC % x sales (Assumptions; row 43).
B32: Change in NWC | D32: =D31-C31 -> -65.3464 | E32: =E31-D31 -> -31.4356 | F32: =F31-E31 -> -358.446 | G32: =G31-F31 -> -324.5836 | H32: =H31-G31 -> -230.6112 | I32: =I31-H31 -> -1030.8632 | J32: =J31-I31 -> -842.24 | K32: =K31-J31 -> -287.4308 | ... S32: =S31-R31 -> -475.44009
B33: Capex | C33: -5294.22 | D33: -3805.46 | E33: -3278.37 | F33: -3699.48 | G33: -3779.44 | H33: -3672 | I33: -4618.18 | J33: -6641.75 | K33: -8753.81 | L33: -10938 | M33: -18822 | N33: -19159 | O33: -19333 | P33: =P13*P34 -> -19109.877 | Q33: =Q13*Q34 -> -20271.758 | R33: =R13*R34 -> -17594.411 | S33: =S13*S34 -> -18664.151 | U33: To 2027: house file. 2028+: sales x capex % (row 46).
B34: Capex % of sales | C34: =C33/C13 -> -0.10308492 | D34: =D33/D13 -> -0.071812636 | E34: =E33/E13 -> -0.060961854 | F34: =F33/F13 -> -0.058966616 | G34: =G33/G13 -> -0.053341884 | H34: =H33/H13 -> -0.047925812 | I34: =I33/I13 -> -0.045103819 | J34: =J33/J13 -> -0.053802877 | ... O34: =O33/O13 -> -0.11805042 | P34: -0.11 | Q34: =P34 -> -0.11 | R34: -0.09 | S34: =R34 -> -0.09 | U34: 2028-29: -11%; 2030: -9% (house); 2031: as 2030 (row 47).
B35: FCFF, house = D&A + NOPAT + capex + NWC (level) | C35: =C23+C26+C33+C31 -> 3593.3985 | D35: =D23+D26+D33+D31 -> 4298.9096 | E35: =E23+E26+E33+E31 -> 6393.174 | F35: =F23+F26+F33+F31 -> 9188.643 | G35: =G23+G26+G33+G31 -> 10165.609 | H35: =H23+H26+H33+H31 -> 9613.4082 | I35: =I23+I26+I33+I31 -> 16932.72 | J35: =J23+J26+J33+J31 -> 18364.202 | ... S35: =S23+S26+S33+S31 -> 24562.069 | U35: D&A + NOPAT + capex + NWC level (row 44): what the house discounts.
B36: FCFF with the change in NWC | D36: =D23+D26+D33+D32 -> 6353.2236 | E36: =E23+E26+E33+E32 -> 8512.8344 | F36: =F23+F26+F33+F32 -> 11339.739 | G36: =G23+G26+G33+G32 -> 12675.151 | H36: =H23+H26+H33+H32 -> 12447.534 | I36: =I23+I26+I33+I32 -> 19997.457 | J36: =J23+J26+J33+J32 -> 22459.802 | K36: =K23+K26+K33+K32 -> 17660.044 | ... S36: =S23+S26+S33+S32 -> 32381.807 | U36: D&A + NOPAT + capex + change in NWC.
B37: FCFF used in the valuation (switch FixNWC) | C37: =C35 -> 3593.3985 | D37: =IF(FixNWC=1,D36,D35) -> 4298.9096 | E37: =IF(FixNWC=1,E36,E35) -> 6393.174 | F37: =IF(FixNWC=1,F36,F35) -> 9188.643 | G37: =IF(FixNWC=1,G36,G35) -> 10165.609 | H37: =IF(FixNWC=1,H36,H35) -> 9613.4082 | I37: =IF(FixNWC=1,I36,I35) -> 16932.72 | J37: =IF(FixNWC=1,J36,J35) -> 18364.202 | K37: =IF(FixNWC=1,K36,K35) -> 12722.204 | ... S37: =IF(FixNWC=1,S36,S35) -> 24562.069 | U37: FixNWC = 0: the house row; 1: the corrected row.
B38: memo: FCFF = EBITDA x (1 - tax) + capex | C38: 3875.1 | D38: 3414.98 | E38: 3131.8 | F38: 5798.58 | G38: 7840.38 | H38: 10543 | I38: 15220 | J38: 21728 | K38: 10626.16 | L38: 12342 | M38: 13051 | N38: =N21*(1+N25)+N33 -> 18327.24 | O38: =O21*(1+O25)+O33 -> 19211.92 | P38: =P21*(1+P25)+P33 -> 20407.835 | Q38: =Q21*(1+Q25)+Q33 -> 21746.067 | R38: =R21*(1+R25)+R33 -> 26978.097 | S38: =S21*(1+S25)+S33 -> 28618.366 | U38: To 2025: house file. 2026+: EBITDA x (1 + tax) + capex (row 49).
B39: memo: Ibovespa (average to 2020, then the price used) | C39: 49828 | D39: 53350 | E39: 67784 | F39: 81677 | G39: 101000 | H39: 99143 | I39: =IbovUsed -> 208431.92 | J39: =IbovUsed -> 208431.92 | K39: =IbovUsed -> 208431.92 | L39: =IbovUsed -> 208431.92 | M39: =IbovUsed -> 208431.92 | N39: =IbovUsed -> 208431.92 | O39: =IbovUsed -> 208431.92 | P39: =IbovUsed -> 208431.92 | ... S39: =IbovUsed -> 208431.92 | U39: Row 50: average to 2020 (house file), then the Ibovespa price used.
B40: memo: FCF yield | C40: =C38/C39 -> 0.077769527 | D40: =D38/D39 -> 0.064010872 | E40: =E38/E39 -> 0.046202644 | F40: =F38/F39 -> 0.070994037 | G40: =G38/G39 -> 0.077627525 | H40: =H38/H39 -> 0.10634135 | I40: =I38/I39 -> 0.073021445 | J40: =J38/J39 -> 0.10424507 | ... S40: =S38/S39 -> 0.13730318 | U40: Simple FCFF / Ibovespa (row 51).
B42: Valuation: fair value at the end of the year (house Target rows 53-59)
C43: Bear | D43: Base | E43: Bull | G43: Base 2026 | H43: How it is calculated
B44: Value date (end of year) | C44: 2027 | D44: 2027 | E44: 2027 | G44: 2026
B45: Explicit FCFF years | C45: 2028-2031 | D45: 2028-2031 | E45: 2028-2031 | G45: 2027-2030
B46: 5-year real rate (NTN-B) | C46: =Assumptions!C20 -> 0.085 | D46: =Assumptions!D20 -> 0.0676 | E46: =Assumptions!E20 -> 0.06 | G46: =Assumptions!D20 -> 0.0676
B47: ERP | C47: =Assumptions!C21 -> 0.06 | D47: =Assumptions!D21 -> 0.06 | E47: =Assumptions!E21 -> 0.06 | G47: =Assumptions!D21 -> 0.06
B48: Discount rate (house 'WACC') | C48: =IF(FixInfl=1,(1+C46+C47)*(1+InflLT)-1,C46+C47) -> 0.145 | D48: =IF(FixInfl=1,(1+D46+D47)*(1+InflLT)-1,D46+D47) -> 0.1276 | E48: =IF(FixInfl=1,(1+E46+E47)*(1+InflLT)-1,E46+E47) -> 0.12 | G48: =IF(FixInfl=1,(1+G46+G47)*(1+InflLT)-1,G46+G47) -> 0.1276 | H48: Real rate + ERP (Target!B55); Fisher with FixInfl = 1.
B49: Long-term growth (g) | C49: =gLT -> 0.047 | D49: =gLT -> 0.047 | E49: =gLT -> 0.047 | G49: =gLT -> 0.047
B50: FCFF of the last explicit year | C50: =S37 -> 24562.069 | D50: =S37 -> 24562.069 | E50: =S37 -> 24562.069 | G50: =R37 -> 23154.288
B51: Terminal value = last FCFF x (1 + g) / (rate - g) | C51: =C50*(1+C49)/(C48-C49) -> 262413.12 | D51: =D50*(1+D49)/(D48-D49) -> 319063.1 | E51: =E50*(1+E49)/(E48-E49) -> 352280.63 | G51: =G50*(1+G49)/(G48-G49) -> 300775.93 | H51: Target!R44.
B52: Periods the terminal value is discounted | C52: =5-FixTV -> 5 | D52: =5-FixTV -> 5 | E52: =5-FixTV -> 5 | G52: =5-FixTV -> 5 | H52: 4 explicit years + 1 (house NPV puts the TV one period later); 4 with FixTV = 1.
B53: Present value of the explicit FCFF | C53: =NPV(C48,P37:S37) -> 58382.957 | D53: =NPV(D48,P37:S37) -> 60669.969 | E53: =NPV(E48,P37:S37) -> 61714.048 | G53: =NPV(G48,O37:R37) -> 54929.274 | H53: Excel NPV of the explicit FCFF (Target row 59).
B54: Present value of the terminal value | C54: =C51/(1+C48)^C52 -> 133339.28 | D54: =D51/(1+D48)^D52 -> 175025.47 | E54: =E51/(1+E48)^E52 -> 199893.49 | G54: =G51/(1+G48)^G52 -> 164993.84
B55: Value of the cash flows | C55: =C53+C54 -> 191722.24 | D55: =D53+D54 -> 235695.44 | E55: =E53+E54 -> 261607.54 | G55: =G53+G54 -> 219923.12
B56: Net debt subtracted (switch FixND) | C56: =IF(FixND=1,NDmult*M21,0) -> 0 | D56: =IF(FixND=1,NDmult*M21,0) -> 0 | E56: =IF(FixND=1,NDmult*M21,0) -> 0 | G56: =IF(FixND=1,NDmult*L21,0) -> 0 | H56: 1.6x the EBITDA two years before the value date (Target rows 70-71), only with FixND = 1.
B57: Fair value (index pts) | C57: =C55-C56 -> 191722.24 | D57: =D55-D56 -> 235695.44 | E57: =E55-E56 -> 261607.54 | G57: =G55-G56 -> 219923.12 | H57: Value of the cash flows - net debt subtracted.
B58: Ibovespa used | C58: =IbovUsed -> 208431.92 | D58: =IbovUsed -> 208431.92 | E58: =IbovUsed -> 208431.92 | G58: =IbovUsed -> 208431.92
B59: Upside | C59: =C57/C58-1 -> -0.080168523 | D59: =D57/D58-1 -> 0.13080299 | E59: =E57/E58-1 -> 0.25512225 | G59: =G57/G58-1 -> 0.055131656
B60: Terminal value / value of the cash flows | C60: =C54/C55 -> 0.69548156 | D60: =D54/D55 -> 0.74259167 | E60: =E54/E55 -> 0.76409683 | G60: =G54/G55 -> 0.7502342
B61: Implied P/E on next year's EPS | C61: =C57/P29 -> 8.2720905 | D61: =D57/P29 -> 10.169368 | E61: =E57/P29 -> 11.287377 | G61: =G57/O29 -> 10.15061 | H61: Fair value / net income of the year after the value date.
B63: Implied return at the Ibovespa price used (house Target rows 61-65, rolled one year)
C64: Today | D64: 2027 | E64: 2028 | F64: 2029 | G64: Terminal
B65: Cash flows | C65: =-IbovUsed -> -208431.92 | D65: =O37 -> 16461.32 | E65: =P37 -> 16980.784 | F65: =Q37 -> 18141.421 | G65: =D51 -> 319063.1 | H65: As the house: price today, three yearly FCFF and the base terminal value as the fourth flow. An indicator, not a full DCF return.
B66: IRR | C66: =IRR(C65:G65) -> 0.16943777
B67: Inflation | C67: =InflLT -> 0.04
B68: Real IRR = IRR - inflation | C68: =C66-C67 -> 0.12943777
B69: Implied ERP = real IRR - 5-year real rate (base) | C69: =C68-D46 -> 0.061837772

Sheet Sensitivity
B1: Ibovespa - Sensitivity: real rate and ERP
B2: The house's real-rate table (tie-out) and a real rate x ERP grid for the end-2027 fair value with the current settings.
B3: Legend: | C3: input | D3: assumption | E3: formula
B5: House table: 5-year real rate vs DCF value (Target rows 120-129)
B6: 5-year real rate | C6: House file, end-2026 | D6: Replica, end-2026 (house settings) | E6: Difference | G6: End-2027, current settings
B7: 0.055 | C7: 263358.81 | D7: =NPV(($B7+0.06),DCF!$O$35:$R$35)+DCF!$R$35*(1+0.047)/(($B7+0.06)-0.047)/(1+($B7+0.06))^5-0 -> 263358.81 | E7: =D7-C7 -> 0 | G7: =NPV(IF(FixInfl=1,(1+$B7+Assumptions!$D$21)*(1+InflLT)-1,$B7+Assumptions!$D$21),DCF!$P$37:$S$37)+DCF!$S$37*(1+gLT)/(IF(FixInfl=1,(1+$B7+Assumptions!$D$21)*(1+InflLT)-1,$B7+Assumptions!$D$21)-gLT)/(1+IF(FixInfl=1,(1+$B7+Assumptions!$D$21)*(1+InflLT)-1,$B7+Assumptions!$D$21))^(4+1-FixTV)-IF(FixND=1,NDmult*DCF!$M$21,0) -> 281862.98
B8: 0.06 | C8: 244298.81 | D8: =NPV(($B8+0.06),DCF!$O$35:$R$35)+DCF!$R$35*(1+0.047)/(($B8+0.06)-0.047)/(1+($B8+0.06))^5-0 -> 244298.81 | E8: =D8-C8 -> 0 | G8: =NPV(IF(FixInfl=1,(1+$B8+Assumptions!$D$21)*(1+InflLT)-1,$B8+Assumptions!$D$21),DCF!$P$37:$S$37)+DCF!$S$37*(1+gLT)/(IF(FixInfl=1,(1+$B8+Assumptions!$D$21)*(1+InflLT)-1,$B8+Assumptions!$D$21)-gLT)/(1+IF(FixInfl=1,(1+$B8+Assumptions!$D$21)*(1+InflLT)-1,$B8+Assumptions!$D$21))^(4+1-FixTV)-IF(FixND=1,NDmult*DCF!$M$21,0) -> 261607.54
B9: 0.07 | C9: 213168.52 | D9: =NPV(($B9+0.06),DCF!$O$35:$R$35)+DCF!$R$35*(1+0.047)/(($B9+0.06)-0.047)/(1+($B9+0.06))^5-0 -> 213168.52 | E9: =D9-C9 -> 0 | G9: =NPV(IF(FixInfl=1,(1+$B9+Assumptions!$D$21)*(1+InflLT)-1,$B9+Assumptions!$D$21),DCF!$P$37:$S$37)+DCF!$S$37*(1+gLT)/(IF(FixInfl=1,(1+$B9+Assumptions!$D$21)*(1+InflLT)-1,$B9+Assumptions!$D$21)-gLT)/(1+IF(FixInfl=1,(1+$B9+Assumptions!$D$21)*(1+InflLT)-1,$B9+Assumptions!$D$21))^(4+1-FixTV)-IF(FixND=1,NDmult*DCF!$M$21,0) -> 228513.31
B10: 0.0742 | C10: 202259.17 | D10: =NPV(($B10+0.06),DCF!$O$35:$R$35)+DCF!$R$35*(1+0.047)/(($B10+0.06)-0.047)/(1+($B10+0.06))^5-0 -> 202259.17 | E10: =D10-C10 -> 0 | G10: =NPV(IF(FixInfl=1,(1+$B10+Assumptions!$D$21)*(1+InflLT)-1,$B10+Assumptions!$D$21),DCF!$P$37:$S$37)+DCF!$S$37*(1+gLT)/(IF(FixInfl=1,(1+$B10+Assumptions!$D$21)*(1+InflLT)-1,$B10+Assumptions!$D$21)-gLT)/(1+IF(FixInfl=1,(1+$B10+Assumptions!$D$21)*(1+InflLT)-1,$B10+Assumptions!$D$21))^(4+1-FixTV)-IF(FixND=1,NDmult*DCF!$M$21,0) -> 216911.5
B11: 0.075 | C11: 200301.58 | D11: =NPV(($B11+0.06),DCF!$O$35:$R$35)+DCF!$R$35*(1+0.047)/(($B11+0.06)-0.047)/(1+($B11+0.06))^5-0 -> 200301.58 | E11: =D11-C11 -> 0 | G11: =NPV(IF(FixInfl=1,(1+$B11+Assumptions!$D$21)*(1+InflLT)-1,$B11+Assumptions!$D$21),DCF!$P$37:$S$37)+DCF!$S$37*(1+gLT)/(IF(FixInfl=1,(1+$B11+Assumptions!$D$21)*(1+InflLT)-1,$B11+Assumptions!$D$21)-gLT)/(1+IF(FixInfl=1,(1+$B11+Assumptions!$D$21)*(1+InflLT)-1,$B11+Assumptions!$D$21))^(4+1-FixTV)-IF(FixND=1,NDmult*DCF!$M$21,0) -> 214829.39
B12: 0.08 | C12: 188845.17 | D12: =NPV(($B12+0.06),DCF!$O$35:$R$35)+DCF!$R$35*(1+0.047)/(($B12+0.06)-0.047)/(1+($B12+0.06))^5-0 -> 188845.17 | E12: =D12-C12 -> 0 | G12: =NPV(IF(FixInfl=1,(1+$B12+Assumptions!$D$21)*(1+InflLT)-1,$B12+Assumptions!$D$21),DCF!$P$37:$S$37)+DCF!$S$37*(1+gLT)/(IF(FixInfl=1,(1+$B12+Assumptions!$D$21)*(1+InflLT)-1,$B12+Assumptions!$D$21)-gLT)/(1+IF(FixInfl=1,(1+$B12+Assumptions!$D$21)*(1+InflLT)-1,$B12+Assumptions!$D$21))^(4+1-FixTV)-IF(FixND=1,NDmult*DCF!$M$21,0) -> 202642.39
B13: 0.085 | C13: 178582.43 | D13: =NPV(($B13+0.06),DCF!$O$35:$R$35)+DCF!$R$35*(1+0.047)/(($B13+0.06)-0.047)/(1+($B13+0.06))^5-0 -> 178582.43 | E13: =D13-C13 -> 0 | G13: =NPV(IF(FixInfl=1,(1+$B13+Assumptions!$D$21)*(1+InflLT)-1,$B13+Assumptions!$D$21),DCF!$P$37:$S$37)+DCF!$S$37*(1+gLT)/(IF(FixInfl=1,(1+$B13+Assumptions!$D$21)*(1+InflLT)-1,$B13+Assumptions!$D$21)-gLT)/(1+IF(FixInfl=1,(1+$B13+Assumptions!$D$21)*(1+InflLT)-1,$B13+Assumptions!$D$21))^(4+1-FixTV)-IF(FixND=1,NDmult*DCF!$M$21,0) -> 191722.24
B14: 0.09 | C14: 169338.66 | D14: =NPV(($B14+0.06),DCF!$O$35:$R$35)+DCF!$R$35*(1+0.047)/(($B14+0.06)-0.047)/(1+($B14+0.06))^5-0 -> 169338.66 | E14: =D14-C14 -> 0 | G14: =NPV(IF(FixInfl=1,(1+$B14+Assumptions!$D$21)*(1+InflLT)-1,$B14+Assumptions!$D$21),DCF!$P$37:$S$37)+DCF!$S$37*(1+gLT)/(IF(FixInfl=1,(1+$B14+Assumptions!$D$21)*(1+InflLT)-1,$B14+Assumptions!$D$21)-gLT)/(1+IF(FixInfl=1,(1+$B14+Assumptions!$D$21)*(1+InflLT)-1,$B14+Assumptions!$D$21))^(4+1-FixTV)-IF(FixND=1,NDmult*DCF!$M$21,0) -> 181883.6
B15: House settings: ERP 6.0%, g 4.7%, no corrections, house FCFF. The house table is an Excel data table on Target!C56.
B18: End-2027 fair value (index pts), current settings
B19: Real rate \ ERP | C19: 0.04 | D19: 0.05 | E19: 0.06 | F19: 0.07 | G19: 0.08
B20: 0.05 | C20: =NPV(IF(FixInfl=1,(1+$B20+C$19)*(1+InflLT)-1,$B20+C$19),DCF!$P$37:$S$37)+DCF!$S$37*(1+gLT)/(IF(FixInfl=1,(1+$B20+C$19)*(1+InflLT)-1,$B20+C$19)-gLT)/(1+IF(FixInfl=1,(1+$B20+C$19)*(1+InflLT)-1,$B20+C$19))^(4+1-FixTV)-IF(FixND=1,NDmult*DCF!$M$21,0) -> 454824.27 | D20: =NPV(IF(FixInfl=1,(1+$B20+D$19)*(1+InflLT)-1,$B20+D$19),DCF!$P$37:$S$37)+DCF!$S$37*(1+gLT)/(IF(FixInfl=1,(1+$B20+D$19)*(1+InflLT)-1,$B20+D$19)-gLT)/(1+IF(FixInfl=1,(1+$B20+D$19)*(1+InflLT)-1,$B20+D$19))^(4+1-FixTV)-IF(FixND=1,NDmult*DCF!$M$21,0) -> 365883.78 | E20: =NPV(IF(FixInfl=1,(1+$B20+E$19)*(1+InflLT)-1,$B20+E$19),DCF!$P$37:$S$37)+DCF!$S$37*(1+gLT)/(IF(FixInfl=1,(1+$B20+E$19)*(1+InflLT)-1,$B20+E$19)-gLT)/(1+IF(FixInfl=1,(1+$B20+E$19)*(1+InflLT)-1,$B20+E$19))^(4+1-FixTV)-IF(FixND=1,NDmult*DCF!$M$21,0) -> 305377.76 | F20: =NPV(IF(FixInfl=1,(1+$B20+F$19)*(1+InflLT)-1,$B20+F$19),DCF!$P$37:$S$37)+DCF!$S$37*(1+gLT)/(IF(FixInfl=1,(1+$B20+F$19)*(1+InflLT)-1,$B20+F$19)-gLT)/(1+IF(FixInfl=1,(1+$B20+F$19)*(1+InflLT)-1,$B20+F$19))^(4+1-FixTV)-IF(FixND=1,NDmult*DCF!$M$21,0) -> 261607.54 | G20: =NPV(IF(FixInfl=1,(1+$B20+G$19)*(1+InflLT)-1,$B20+G$19),DCF!$P$37:$S$37)+DCF!$S$37*(1+gLT)/(IF(FixInfl=1,(1+$B20+G$19)*(1+InflLT)-1,$B20+G$19)-gLT)/(1+IF(FixInfl=1,(1+$B20+G$19)*(1+InflLT)-1,$B20+G$19))^(4+1-FixTV)-IF(FixND=1,NDmult*DCF!$M$21,0) -> 228513.31
B21: 0.055 | C21: =NPV(IF(FixInfl=1,(1+$B21+C$19)*(1+InflLT)-1,$B21+C$19),DCF!$P$37:$S$37)+DCF!$S$37*(1+gLT)/(IF(FixInfl=1,(1+$B21+C$19)*(1+InflLT)-1,$B21+C$19)-gLT)/(1+IF(FixInfl=1,(1+$B21+C$19)*(1+InflLT)-1,$B21+C$19))^(4+1-FixTV)-IF(FixND=1,NDmult*DCF!$M$21,0) -> 405687.66 | D21: =NPV(IF(FixInfl=1,(1+$B21+D$19)*(1+InflLT)-1,$B21+D$19),DCF!$P$37:$S$37)+DCF!$S$37*(1+gLT)/(IF(FixInfl=1,(1+$B21+D$19)*(1+InflLT)-1,$B21+D$19)-gLT)/(1+IF(FixInfl=1,(1+$B21+D$19)*(1+InflLT)-1,$B21+D$19))^(4+1-FixTV)-IF(FixND=1,NDmult*DCF!$M$21,0) -> 332996.75 | E21: =NPV(IF(FixInfl=1,(1+$B21+E$19)*(1+InflLT)-1,$B21+E$19),DCF!$P$37:$S$37)+DCF!$S$37*(1+gLT)/(IF(FixInfl=1,(1+$B21+E$19)*(1+InflLT)-1,$B21+E$19)-gLT)/(1+IF(FixInfl=1,(1+$B21+E$19)*(1+InflLT)-1,$B21+E$19))^(4+1-FixTV)-IF(FixND=1,NDmult*DCF!$M$21,0) -> 281862.98 | F21: =NPV(IF(FixInfl=1,(1+$B21+F$19)*(1+InflLT)-1,$B21+F$19),DCF!$P$37:$S$37)+DCF!$S$37*(1+gLT)/(IF(FixInfl=1,(1+$B21+F$19)*(1+InflLT)-1,$B21+F$19)-gLT)/(1+IF(FixInfl=1,(1+$B21+F$19)*(1+InflLT)-1,$B21+F$19))^(4+1-FixTV)-IF(FixND=1,NDmult*DCF!$M$21,0) -> 243983.24 | G21: =NPV(IF(FixInfl=1,(1+$B21+G$19)*(1+InflLT)-1,$B21+G$19),DCF!$P$37:$S$37)+DCF!$S$37*(1+gLT)/(IF(FixInfl=1,(1+$B21+G$19)*(1+InflLT)-1,$B21+G$19)-gLT)/(1+IF(FixInfl=1,(1+$B21+G$19)*(1+InflLT)-1,$B21+G$19))^(4+1-FixTV)-IF(FixND=1,NDmult*DCF!$M$21,0) -> 214829.39
B22: 0.06 | C22: =NPV(IF(FixInfl=1,(1+$B22+C$19)*(1+InflLT)-1,$B22+C$19),DCF!$P$37:$S$37)+DCF!$S$37*(1+gLT)/(IF(FixInfl=1,(1+$B22+C$19)*(1+InflLT)-1,$B22+C$19)-gLT)/(1+IF(FixInfl=1,(1+$B22+C$19)*(1+InflLT)-1,$B22+C$19))^(4+1-FixTV)-IF(FixND=1,NDmult*DCF!$M$21,0) -> 365883.78 | D22: =NPV(IF(FixInfl=1,(1+$B22+D$19)*(1+InflLT)-1,$B22+D$19),DCF!$P$37:$S$37)+DCF!$S$37*(1+gLT)/(IF(FixInfl=1,(1+$B22+D$19)*(1+InflLT)-1,$B22+D$19)-gLT)/(1+IF(FixInfl=1,(1+$B22+D$19)*(1+InflLT)-1,$B22+D$19))^(4+1-FixTV)-IF(FixND=1,NDmult*DCF!$M$21,0) -> 305377.76 | E22: =NPV(IF(FixInfl=1,(1+$B22+E$19)*(1+InflLT)-1,$B22+E$19),DCF!$P$37:$S$37)+DCF!$S$37*(1+gLT)/(IF(FixInfl=1,(1+$B22+E$19)*(1+InflLT)-1,$B22+E$19)-gLT)/(1+IF(FixInfl=1,(1+$B22+E$19)*(1+InflLT)-1,$B22+E$19))^(4+1-FixTV)-IF(FixND=1,NDmult*DCF!$M$21,0) -> 261607.54 | F22: =NPV(IF(FixInfl=1,(1+$B22+F$19)*(1+InflLT)-1,$B22+F$19),DCF!$P$37:$S$37)+DCF!$S$37*(1+gLT)/(IF(FixInfl=1,(1+$B22+F$19)*(1+InflLT)-1,$B22+F$19)-gLT)/(1+IF(FixInfl=1,(1+$B22+F$19)*(1+InflLT)-1,$B22+F$19))^(4+1-FixTV)-IF(FixND=1,NDmult*DCF!$M$21,0) -> 228513.31 | G22: =NPV(IF(FixInfl=1,(1+$B22+G$19)*(1+InflLT)-1,$B22+G$19),DCF!$P$37:$S$37)+DCF!$S$37*(1+gLT)/(IF(FixInfl=1,(1+$B22+G$19)*(1+InflLT)-1,$B22+G$19)-gLT)/(1+IF(FixInfl=1,(1+$B22+G$19)*(1+InflLT)-1,$B22+G$19))^(4+1-FixTV)-IF(FixND=1,NDmult*DCF!$M$21,0) -> 202642.39
B23: 0.065 | C23: =NPV(IF(FixInfl=1,(1+$B23+C$19)*(1+InflLT)-1,$B23+C$19),DCF!$P$37:$S$37)+DCF!$S$37*(1+gLT)/(IF(FixInfl=1,(1+$B23+C$19)*(1+InflLT)-1,$B23+C$19)-gLT)/(1+IF(FixInfl=1,(1+$B23+C$19)*(1+InflLT)-1,$B23+C$19))^(4+1-FixTV)-IF(FixND=1,NDmult*DCF!$M$21,0) -> 332996.75 | D23: =NPV(IF(FixInfl=1,(1+$B23+D$19)*(1+InflLT)-1,$B23+D$19),DCF!$P$37:$S$37)+DCF!$S$37*(1+gLT)/(IF(FixInfl=1,(1+$B23+D$19)*(1+InflLT)-1,$B23+D$19)-gLT)/(1+IF(FixInfl=1,(1+$B23+D$19)*(1+InflLT)-1,$B23+D$19))^(4+1-FixTV)-IF(FixND=1,NDmult*DCF!$M$21,0) -> 281862.98 | E23: =NPV(IF(FixInfl=1,(1+$B23+E$19)*(1+InflLT)-1,$B23+E$19),DCF!$P$37:$S$37)+DCF!$S$37*(1+gLT)/(IF(FixInfl=1,(1+$B23+E$19)*(1+InflLT)-1,$B23+E$19)-gLT)/(1+IF(FixInfl=1,(1+$B23+E$19)*(1+InflLT)-1,$B23+E$19))^(4+1-FixTV)-IF(FixND=1,NDmult*DCF!$M$21,0) -> 243983.24 | F23: =NPV(IF(FixInfl=1,(1+$B23+F$19)*(1+InflLT)-1,$B23+F$19),DCF!$P$37:$S$37)+DCF!$S$37*(1+gLT)/(IF(FixInfl=1,(1+$B23+F$19)*(1+InflLT)-1,$B23+F$19)-gLT)/(1+IF(FixInfl=1,(1+$B23+F$19)*(1+InflLT)-1,$B23+F$19))^(4+1-FixTV)-IF(FixND=1,NDmult*DCF!$M$21,0) -> 214829.39 | G23: =NPV(IF(FixInfl=1,(1+$B23+G$19)*(1+InflLT)-1,$B23+G$19),DCF!$P$37:$S$37)+DCF!$S$37*(1+gLT)/(IF(FixInfl=1,(1+$B23+G$19)*(1+InflLT)-1,$B23+G$19)-gLT)/(1+IF(FixInfl=1,(1+$B23+G$19)*(1+InflLT)-1,$B23+G$19))^(4+1-FixTV)-IF(FixND=1,NDmult*DCF!$M$21,0) -> 191722.24
B24: 0.0676 | C24: =NPV(IF(FixInfl=1,(1+$B24+C$19)*(1+InflLT)-1,$B24+C$19),DCF!$P$37:$S$37)+DCF!$S$37*(1+gLT)/(IF(FixInfl=1,(1+$B24+C$19)*(1+InflLT)-1,$B24+C$19)-gLT)/(1+IF(FixInfl=1,(1+$B24+C$19)*(1+InflLT)-1,$B24+C$19))^(4+1-FixTV)-IF(FixND=1,NDmult*DCF!$M$21,0) -> 318060.01 | D24: =NPV(IF(FixInfl=1,(1+$B24+D$19)*(1+InflLT)-1,$B24+D$19),DCF!$P$37:$S$37)+DCF!$S$37*(1+gLT)/(IF(FixInfl=1,(1+$B24+D$19)*(1+InflLT)-1,$B24+D$19)-gLT)/(1+IF(FixInfl=1,(1+$B24+D$19)*(1+InflLT)-1,$B24+D$19))^(4+1-FixTV)-IF(FixND=1,NDmult*DCF!$M$21,0) -> 270967.27 | E24: =NPV(IF(FixInfl=1,(1+$B24+E$19)*(1+InflLT)-1,$B24+E$19),DCF!$P$37:$S$37)+DCF!$S$37*(1+gLT)/(IF(FixInfl=1,(1+$B24+E$19)*(1+InflLT)-1,$B24+E$19)-gLT)/(1+IF(FixInfl=1,(1+$B24+E$19)*(1+InflLT)-1,$B24+E$19))^(4+1-FixTV)-IF(FixND=1,NDmult*DCF!$M$21,0) -> 235695.44 | F24: =NPV(IF(FixInfl=1,(1+$B24+F$19)*(1+InflLT)-1,$B24+F$19),DCF!$P$37:$S$37)+DCF!$S$37*(1+gLT)/(IF(FixInfl=1,(1+$B24+F$19)*(1+InflLT)-1,$B24+F$19)-gLT)/(1+IF(FixInfl=1,(1+$B24+F$19)*(1+InflLT)-1,$B24+F$19))^(4+1-FixTV)-IF(FixND=1,NDmult*DCF!$M$21,0) -> 208321.07 | G24: =NPV(IF(FixInfl=1,(1+$B24+G$19)*(1+InflLT)-1,$B24+G$19),DCF!$P$37:$S$37)+DCF!$S$37*(1+gLT)/(IF(FixInfl=1,(1+$B24+G$19)*(1+InflLT)-1,$B24+G$19)-gLT)/(1+IF(FixInfl=1,(1+$B24+G$19)*(1+InflLT)-1,$B24+G$19))^(4+1-FixTV)-IF(FixND=1,NDmult*DCF!$M$21,0) -> 186481.43
B25: 0.07 | C25: =NPV(IF(FixInfl=1,(1+$B25+C$19)*(1+InflLT)-1,$B25+C$19),DCF!$P$37:$S$37)+DCF!$S$37*(1+gLT)/(IF(FixInfl=1,(1+$B25+C$19)*(1+InflLT)-1,$B25+C$19)-gLT)/(1+IF(FixInfl=1,(1+$B25+C$19)*(1+InflLT)-1,$B25+C$19))^(4+1-FixTV)-IF(FixND=1,NDmult*DCF!$M$21,0) -> 305377.76 | D25: =NPV(IF(FixInfl=1,(1+$B25+D$19)*(1+InflLT)-1,$B25+D$19),DCF!$P$37:$S$37)+DCF!$S$37*(1+gLT)/(IF(FixInfl=1,(1+$B25+D$19)*(1+InflLT)-1,$B25+D$19)-gLT)/(1+IF(FixInfl=1,(1+$B25+D$19)*(1+InflLT)-1,$B25+D$19))^(4+1-FixTV)-IF(FixND=1,NDmult*DCF!$M$21,0) -> 261607.54 | E25: =NPV(IF(FixInfl=1,(1+$B25+E$19)*(1+InflLT)-1,$B25+E$19),DCF!$P$37:$S$37)+DCF!$S$37*(1+gLT)/(IF(FixInfl=1,(1+$B25+E$19)*(1+InflLT)-1,$B25+E$19)-gLT)/(1+IF(FixInfl=1,(1+$B25+E$19)*(1+InflLT)-1,$B25+E$19))^(4+1-FixTV)-IF(FixND=1,NDmult*DCF!$M$21,0) -> 228513.31 | F25: =NPV(IF(FixInfl=1,(1+$B25+F$19)*(1+InflLT)-1,$B25+F$19),DCF!$P$37:$S$37)+DCF!$S$37*(1+gLT)/(IF(FixInfl=1,(1+$B25+F$19)*(1+InflLT)-1,$B25+F$19)-gLT)/(1+IF(FixInfl=1,(1+$B25+F$19)*(1+InflLT)-1,$B25+F$19))^(4+1-FixTV)-IF(FixND=1,NDmult*DCF!$M$21,0) -> 202642.39 | G25: =NPV(IF(FixInfl=1,(1+$B25+G$19)*(1+InflLT)-1,$B25+G$19),DCF!$P$37:$S$37)+DCF!$S$37*(1+gLT)/(IF(FixInfl=1,(1+$B25+G$19)*(1+InflLT)-1,$B25+G$19)-gLT)/(1+IF(FixInfl=1,(1+$B25+G$19)*(1+InflLT)-1,$B25+G$19))^(4+1-FixTV)-IF(FixND=1,NDmult*DCF!$M$21,0) -> 181883.6
B26: 0.075 | C26: =NPV(IF(FixInfl=1,(1+$B26+C$19)*(1+InflLT)-1,$B26+C$19),DCF!$P$37:$S$37)+DCF!$S$37*(1+gLT)/(IF(FixInfl=1,(1+$B26+C$19)*(1+InflLT)-1,$B26+C$19)-gLT)/(1+IF(FixInfl=1,(1+$B26+C$19)*(1+InflLT)-1,$B26+C$19))^(4+1-FixTV)-IF(FixND=1,NDmult*DCF!$M$21,0) -> 281862.98 | D26: =NPV(IF(FixInfl=1,(1+$B26+D$19)*(1+InflLT)-1,$B26+D$19),DCF!$P$37:$S$37)+DCF!$S$37*(1+gLT)/(IF(FixInfl=1,(1+$B26+D$19)*(1+InflLT)-1,$B26+D$19)-gLT)/(1+IF(FixInfl=1,(1+$B26+D$19)*(1+InflLT)-1,$B26+D$19))^(4+1-FixTV)-IF(FixND=1,NDmult*DCF!$M$21,0) -> 243983.24 | E26: =NPV(IF(FixInfl=1,(1+$B26+E$19)*(1+InflLT)-1,$B26+E$19),DCF!$P$37:$S$37)+DCF!$S$37*(1+gLT)/(IF(FixInfl=1,(1+$B26+E$19)*(1+InflLT)-1,$B26+E$19)-gLT)/(1+IF(FixInfl=1,(1+$B26+E$19)*(1+InflLT)-1,$B26+E$19))^(4+1-FixTV)-IF(FixND=1,NDmult*DCF!$M$21,0) -> 214829.39 | F26: =NPV(IF(FixInfl=1,(1+$B26+F$19)*(1+InflLT)-1,$B26+F$19),DCF!$P$37:$S$37)+DCF!$S$37*(1+gLT)/(IF(FixInfl=1,(1+$B26+F$19)*(1+InflLT)-1,$B26+F$19)-gLT)/(1+IF(FixInfl=1,(1+$B26+F$19)*(1+InflLT)-1,$B26+F$19))^(4+1-FixTV)-IF(FixND=1,NDmult*DCF!$M$21,0) -> 191722.24 | G26: =NPV(IF(FixInfl=1,(1+$B26+G$19)*(1+InflLT)-1,$B26+G$19),DCF!$P$37:$S$37)+DCF!$S$37*(1+gLT)/(IF(FixInfl=1,(1+$B26+G$19)*(1+InflLT)-1,$B26+G$19)-gLT)/(1+IF(FixInfl=1,(1+$B26+G$19)*(1+InflLT)-1,$B26+G$19))^(4+1-FixTV)-IF(FixND=1,NDmult*DCF!$M$21,0) -> 172975.46
B27: 0.08 | C27: =NPV(IF(FixInfl=1,(1+$B27+C$19)*(1+InflLT)-1,$B27+C$19),DCF!$P$37:$S$37)+DCF!$S$37*(1+gLT)/(IF(FixInfl=1,(1+$B27+C$19)*(1+InflLT)-1,$B27+C$19)-gLT)/(1+IF(FixInfl=1,(1+$B27+C$19)*(1+InflLT)-1,$B27+C$19))^(4+1-FixTV)-IF(FixND=1,NDmult*DCF!$M$21,0) -> 261607.54 | D27: =NPV(IF(FixInfl=1,(1+$B27+D$19)*(1+InflLT)-1,$B27+D$19),DCF!$P$37:$S$37)+DCF!$S$37*(1+gLT)/(IF(FixInfl=1,(1+$B27+D$19)*(1+InflLT)-1,$B27+D$19)-gLT)/(1+IF(FixInfl=1,(1+$B27+D$19)*(1+InflLT)-1,$B27+D$19))^(4+1-FixTV)-IF(FixND=1,NDmult*DCF!$M$21,0) -> 228513.31 | E27: =NPV(IF(FixInfl=1,(1+$B27+E$19)*(1+InflLT)-1,$B27+E$19),DCF!$P$37:$S$37)+DCF!$S$37*(1+gLT)/(IF(FixInfl=1,(1+$B27+E$19)*(1+InflLT)-1,$B27+E$19)-gLT)/(1+IF(FixInfl=1,(1+$B27+E$19)*(1+InflLT)-1,$B27+E$19))^(4+1-FixTV)-IF(FixND=1,NDmult*DCF!$M$21,0) -> 202642.39 | F27: =NPV(IF(FixInfl=1,(1+$B27+F$19)*(1+InflLT)-1,$B27+F$19),DCF!$P$37:$S$37)+DCF!$S$37*(1+gLT)/(IF(FixInfl=1,(1+$B27+F$19)*(1+InflLT)-1,$B27+F$19)-gLT)/(1+IF(FixInfl=1,(1+$B27+F$19)*(1+InflLT)-1,$B27+F$19))^(4+1-FixTV)-IF(FixND=1,NDmult*DCF!$M$21,0) -> 181883.6 | G27: =NPV(IF(FixInfl=1,(1+$B27+G$19)*(1+InflLT)-1,$B27+G$19),DCF!$P$37:$S$37)+DCF!$S$37*(1+gLT)/(IF(FixInfl=1,(1+$B27+G$19)*(1+InflLT)-1,$B27+G$19)-gLT)/(1+IF(FixInfl=1,(1+$B27+G$19)*(1+InflLT)-1,$B27+G$19))^(4+1-FixTV)-IF(FixND=1,NDmult*DCF!$M$21,0) -> 164873.6
B28: 0.085 | C28: =NPV(IF(FixInfl=1,(1+$B28+C$19)*(1+InflLT)-1,$B28+C$19),DCF!$P$37:$S$37)+DCF!$S$37*(1+gLT)/(IF(FixInfl=1,(1+$B28+C$19)*(1+InflLT)-1,$B28+C$19)-gLT)/(1+IF(FixInfl=1,(1+$B28+C$19)*(1+InflLT)-1,$B28+C$19))^(4+1-FixTV)-IF(FixND=1,NDmult*DCF!$M$21,0) -> 243983.24 | D28: =NPV(IF(FixInfl=1,(1+$B28+D$19)*(1+InflLT)-1,$B28+D$19),DCF!$P$37:$S$37)+DCF!$S$37*(1+gLT)/(IF(FixInfl=1,(1+$B28+D$19)*(1+InflLT)-1,$B28+D$19)-gLT)/(1+IF(FixInfl=1,(1+$B28+D$19)*(1+InflLT)-1,$B28+D$19))^(4+1-FixTV)-IF(FixND=1,NDmult*DCF!$M$21,0) -> 214829.39 | E28: =NPV(IF(FixInfl=1,(1+$B28+E$19)*(1+InflLT)-1,$B28+E$19),DCF!$P$37:$S$37)+DCF!$S$37*(1+gLT)/(IF(FixInfl=1,(1+$B28+E$19)*(1+InflLT)-1,$B28+E$19)-gLT)/(1+IF(FixInfl=1,(1+$B28+E$19)*(1+InflLT)-1,$B28+E$19))^(4+1-FixTV)-IF(FixND=1,NDmult*DCF!$M$21,0) -> 191722.24 | F28: =NPV(IF(FixInfl=1,(1+$B28+F$19)*(1+InflLT)-1,$B28+F$19),DCF!$P$37:$S$37)+DCF!$S$37*(1+gLT)/(IF(FixInfl=1,(1+$B28+F$19)*(1+InflLT)-1,$B28+F$19)-gLT)/(1+IF(FixInfl=1,(1+$B28+F$19)*(1+InflLT)-1,$B28+F$19))^(4+1-FixTV)-IF(FixND=1,NDmult*DCF!$M$21,0) -> 172975.46 | G28: =NPV(IF(FixInfl=1,(1+$B28+G$19)*(1+InflLT)-1,$B28+G$19),DCF!$P$37:$S$37)+DCF!$S$37*(1+gLT)/(IF(FixInfl=1,(1+$B28+G$19)*(1+InflLT)-1,$B28+G$19)-gLT)/(1+IF(FixInfl=1,(1+$B28+G$19)*(1+InflLT)-1,$B28+G$19))^(4+1-FixTV)-IF(FixND=1,NDmult*DCF!$M$21,0) -> 157474.85
B29: 0.09 | C29: =NPV(IF(FixInfl=1,(1+$B29+C$19)*(1+InflLT)-1,$B29+C$19),DCF!$P$37:$S$37)+DCF!$S$37*(1+gLT)/(IF(FixInfl=1,(1+$B29+C$19)*(1+InflLT)-1,$B29+C$19)-gLT)/(1+IF(FixInfl=1,(1+$B29+C$19)*(1+InflLT)-1,$B29+C$19))^(4+1-FixTV)-IF(FixND=1,NDmult*DCF!$M$21,0) -> 228513.31 | D29: =NPV(IF(FixInfl=1,(1+$B29+D$19)*(1+InflLT)-1,$B29+D$19),DCF!$P$37:$S$37)+DCF!$S$37*(1+gLT)/(IF(FixInfl=1,(1+$B29+D$19)*(1+InflLT)-1,$B29+D$19)-gLT)/(1+IF(FixInfl=1,(1+$B29+D$19)*(1+InflLT)-1,$B29+D$19))^(4+1-FixTV)-IF(FixND=1,NDmult*DCF!$M$21,0) -> 202642.39 | E29: =NPV(IF(FixInfl=1,(1+$B29+E$19)*(1+InflLT)-1,$B29+E$19),DCF!$P$37:$S$37)+DCF!$S$37*(1+gLT)/(IF(FixInfl=1,(1+$B29+E$19)*(1+InflLT)-1,$B29+E$19)-gLT)/(1+IF(FixInfl=1,(1+$B29+E$19)*(1+InflLT)-1,$B29+E$19))^(4+1-FixTV)-IF(FixND=1,NDmult*DCF!$M$21,0) -> 181883.6 | F29: =NPV(IF(FixInfl=1,(1+$B29+F$19)*(1+InflLT)-1,$B29+F$19),DCF!$P$37:$S$37)+DCF!$S$37*(1+gLT)/(IF(FixInfl=1,(1+$B29+F$19)*(1+InflLT)-1,$B29+F$19)-gLT)/(1+IF(FixInfl=1,(1+$B29+F$19)*(1+InflLT)-1,$B29+F$19))^(4+1-FixTV)-IF(FixND=1,NDmult*DCF!$M$21,0) -> 164873.6 | G29: =NPV(IF(FixInfl=1,(1+$B29+G$19)*(1+InflLT)-1,$B29+G$19),DCF!$P$37:$S$37)+DCF!$S$37*(1+gLT)/(IF(FixInfl=1,(1+$B29+G$19)*(1+InflLT)-1,$B29+G$19)-gLT)/(1+IF(FixInfl=1,(1+$B29+G$19)*(1+InflLT)-1,$B29+G$19))^(4+1-FixTV)-IF(FixND=1,NDmult*DCF!$M$21,0) -> 150692.86
B30: 0.095 | C30: =NPV(IF(FixInfl=1,(1+$B30+C$19)*(1+InflLT)-1,$B30+C$19),DCF!$P$37:$S$37)+DCF!$S$37*(1+gLT)/(IF(FixInfl=1,(1+$B30+C$19)*(1+InflLT)-1,$B30+C$19)-gLT)/(1+IF(FixInfl=1,(1+$B30+C$19)*(1+InflLT)-1,$B30+C$19))^(4+1-FixTV)-IF(FixND=1,NDmult*DCF!$M$21,0) -> 214829.39 | D30: =NPV(IF(FixInfl=1,(1+$B30+D$19)*(1+InflLT)-1,$B30+D$19),DCF!$P$37:$S$37)+DCF!$S$37*(1+gLT)/(IF(FixInfl=1,(1+$B30+D$19)*(1+InflLT)-1,$B30+D$19)-gLT)/(1+IF(FixInfl=1,(1+$B30+D$19)*(1+InflLT)-1,$B30+D$19))^(4+1-FixTV)-IF(FixND=1,NDmult*DCF!$M$21,0) -> 191722.24 | E30: =NPV(IF(FixInfl=1,(1+$B30+E$19)*(1+InflLT)-1,$B30+E$19),DCF!$P$37:$S$37)+DCF!$S$37*(1+gLT)/(IF(FixInfl=1,(1+$B30+E$19)*(1+InflLT)-1,$B30+E$19)-gLT)/(1+IF(FixInfl=1,(1+$B30+E$19)*(1+InflLT)-1,$B30+E$19))^(4+1-FixTV)-IF(FixND=1,NDmult*DCF!$M$21,0) -> 172975.46 | F30: =NPV(IF(FixInfl=1,(1+$B30+F$19)*(1+InflLT)-1,$B30+F$19),DCF!$P$37:$S$37)+DCF!$S$37*(1+gLT)/(IF(FixInfl=1,(1+$B30+F$19)*(1+InflLT)-1,$B30+F$19)-gLT)/(1+IF(FixInfl=1,(1+$B30+F$19)*(1+InflLT)-1,$B30+F$19))^(4+1-FixTV)-IF(FixND=1,NDmult*DCF!$M$21,0) -> 157474.85 | G30: =NPV(IF(FixInfl=1,(1+$B30+G$19)*(1+InflLT)-1,$B30+G$19),DCF!$P$37:$S$37)+DCF!$S$37*(1+gLT)/(IF(FixInfl=1,(1+$B30+G$19)*(1+InflLT)-1,$B30+G$19)-gLT)/(1+IF(FixInfl=1,(1+$B30+G$19)*(1+InflLT)-1,$B30+G$19))^(4+1-FixTV)-IF(FixND=1,NDmult*DCF!$M$21,0) -> 144454.79
B34: Upside vs the Ibovespa used
B35: Real rate \ ERP | C35: =C$19 -> 0.04 | D35: =D$19 -> 0.05 | E35: =E$19 -> 0.06 | F35: =F$19 -> 0.07 | G35: =G$19 -> 0.08
B36: =$B$20 -> 0.05 | C36: =C20/IbovUsed-1 -> 1.1821239 | D36: =D20/IbovUsed-1 -> 0.75541144 | E36: =E20/IbovUsed-1 -> 0.46511993 | F36: =F20/IbovUsed-1 -> 0.25512225 | G36: =G20/IbovUsed-1 -> 0.096345059
B37: =$B$21 -> 0.055 | C37: =C21/IbovUsed-1 -> 0.94637972 | D37: =D21/IbovUsed-1 -> 0.5976284 | E37: =E21/IbovUsed-1 -> 0.35230239 | F37: =F21/IbovUsed-1 -> 0.1705656 | G37: =G21/IbovUsed-1 -> 0.030693331
B38: =$B$22 -> 0.06 | C38: =C22/IbovUsed-1 -> 0.75541144 | D38: =D22/IbovUsed-1 -> 0.46511993 | E38: =E22/IbovUsed-1 -> 0.25512225 | F38: =F22/IbovUsed-1 -> 0.096345059 | G38: =G22/IbovUsed-1 -> -0.027776609
B39: =$B$23 -> 0.065 | C39: =C23/IbovUsed-1 -> 0.5976284 | D39: =D23/IbovUsed-1 -> 0.35230239 | E39: =E23/IbovUsed-1 -> 0.1705656 | F39: =F23/IbovUsed-1 -> 0.030693331 | G39: =G23/IbovUsed-1 -> -0.080168523
B40: =$B$24 -> 0.0676 | C40: =C24/IbovUsed-1 -> 0.52596591 | D40: =D24/IbovUsed-1 -> 0.30002773 | E40: =E24/IbovUsed-1 -> 0.13080299 | F40: =F24/IbovUsed-1 -> -0.00053182661 | G40: =G24/IbovUsed-1 -> -0.10531254
B41: =$B$25 -> 0.07 | C41: =C25/IbovUsed-1 -> 0.46511993 | D41: =D25/IbovUsed-1 -> 0.25512225 | E41: =E25/IbovUsed-1 -> 0.096345059 | F41: =F25/IbovUsed-1 -> -0.027776609 | G41: =G25/IbovUsed-1 -> -0.12737168
B42: =$B$26 -> 0.075 | C42: =C26/IbovUsed-1 -> 0.35230239 | D42: =D26/IbovUsed-1 -> 0.1705656 | E42: =E26/IbovUsed-1 -> 0.030693331 | F42: =F26/IbovUsed-1 -> -0.080168523 | G42: =G26/IbovUsed-1 -> -0.1701105
B43: =$B$27 -> 0.08 | C43: =C27/IbovUsed-1 -> 0.25512225 | D43: =D27/IbovUsed-1 -> 0.096345059 | E43: =E27/IbovUsed-1 -> -0.027776609 | F43: =F27/IbovUsed-1 -> -0.12737168 | G43: =G27/IbovUsed-1 -> -0.20898106
B44: =$B$28 -> 0.085 | C44: =C28/IbovUsed-1 -> 0.1705656 | D44: =D28/IbovUsed-1 -> 0.030693331 | E44: =E28/IbovUsed-1 -> -0.080168523 | F44: =F28/IbovUsed-1 -> -0.1701105 | G44: =G28/IbovUsed-1 -> -0.24447826
B45: =$B$29 -> 0.09 | C45: =C29/IbovUsed-1 -> 0.096345059 | D45: =D29/IbovUsed-1 -> -0.027776609 | E45: =E29/IbovUsed-1 -> -0.12737168 | F45: =F29/IbovUsed-1 -> -0.20898106 | G45: =G29/IbovUsed-1 -> -0.27701641
B46: =$B$30 -> 0.095 | C46: =C30/IbovUsed-1 -> 0.030693331 | D46: =D30/IbovUsed-1 -> -0.080168523 | E46: =E30/IbovUsed-1 -> -0.1701105 | F46: =F30/IbovUsed-1 -> -0.24447826 | G46: =G30/IbovUsed-1 -> -0.30694497
B51: Framed cell = base real rate and base ERP. The grid uses the switches in Assumptions section 4.

Sheet Support >

Sheet Box Rates
B1: Ibovespa - Box discount rates: house, relative to history or CAPM
B2: Box rate - g = (house rate - g) x relative cash yield; relative cash yield = (10y average earnings yield x cash conversion) / the same for the Ibovespa.
B3: Legend: | C3: input | D3: assumption | E3: formula
B5: 1. Historical cash yield relative to the Ibovespa (12m fwd, Oct-16..Sep-26)
B6: Group | C6: Cash conversion 2031 (FCFF or FCFE / net income) | D6: Average earnings yield (section 3) | E6: Average P/E = 1 / yield | F6: Cash yield = conversion x earnings yield | G6: Relative to the Ibovespa | H6: CAPM beta used (Box Betas)
B7: Financials | C7: ='DCF by Box'!$H$37/'DCF by Box'!$H$27 -> 0.76346986 | D7: =AVERAGE(C$32:C$151) -> 0.12075605 | E7: =1/D7 -> 8.2811588 | F7: =C7*D7 -> 0.092193602 | G7: =F7/$F$11 -> 0.9245176 | H7: ='Box Betas'!I7 -> 1.1490637
B8: Defensives | C8: ='DCF by Box'!$H$83/'DCF by Box'!$H$75 -> 0.84896206 | D8: =AVERAGE(D$32:D$151) -> 0.074616957 | E8: =1/D8 -> 13.401779 | F8: =C8*D8 -> 0.063346966 | G8: =F8/$F$11 -> 0.63524349 | H8: ='Box Betas'!I8 -> 0.92867396
B9: Cyclicals | C9: ='DCF by Box'!$H$124/'DCF by Box'!$H$116 -> 0.49913291 | D9: =AVERAGE(E$32:E$151) -> 0.059397862 | E9: =1/D9 -> 16.835623 | F9: =C9*D9 -> 0.029647427 | G9: =F9/$F$11 -> 0.29730445 | H9: ='Box Betas'!I9 -> 1.1504511
B10: Commodities | C10: ='DCF by Box'!$H$165/'DCF by Box'!$H$157 -> 1.0114872 | D10: =AVERAGE(F$32:F$151) -> 0.15136059 | E10: =1/D10 -> 6.6067396 | F10: =C10*D10 -> 0.15309929 | G10: =F10/$F$11 -> 1.53528 | H10: ='Box Betas'!I10 -> 0.87168584
B11: Ibovespa | C11: =DCF!$S$37/DCF!$S$29 -> 0.88778375 | D11: =AVERAGE(G$32:G$151) -> 0.11232551 | E11: =1/D11 -> 8.902697 | F11: =C11*D11 -> 0.099720765 | G11: =F11/$F$11 -> 1 | H11: ='Box Betas'!I11 -> 1
B12: Memo (inside Cyclicals)
B13: Cyclicals ex-WEG & Embraer | C13: ='DCF by Box'!$H$206/'DCF by Box'!$H$198 -> 0.48381774 | D13: =AVERAGE(H$32:H$151) -> 0.06603499 | E13: =1/D13 -> 15.143487 | F13: =C13*D13 -> 0.031948899 | G13: =F13/$F$11 -> 0.32038362 | H13: ='Box Betas'!I13 -> 1.3187146
B14: WEG & Embraer | C14: ='DCF by Box'!$H$247/'DCF by Box'!$H$239 -> 0.54944199 | D14: =AVERAGE(I$32:I$151) -> 0.042104976 | E14: =1/D14 -> 23.750162 | F14: =C14*D14 -> 0.023134242 | G14: =F14/$F$11 -> 0.23199022 | H14: ='Box Betas'!I14 -> 0.71783452
B15: Cash conversion: the box's FCFF (Financials: FCFE) / net income in 2031, the year the terminal value grows from (DCF by Box; Ibovespa: DCF sheet).
B17: 2. Discount rate by box (fair value at the end of 2027)
C18: Bear | D18: Base | E18: Bull | G18: Risk premium: Bear | H18: Base | I18: Bull
B19: House discount rate (DCF sheet) | C19: =DCF!C48 -> 0.145 | D19: =DCF!D48 -> 0.1276 | E19: =DCF!E48 -> 0.12 | G19: =C19-C20 -> 0.06 | H19: =D19-D20 -> 0.06 | I19: =E19-E20 -> 0.06
B20: 5-year real rate (DCF sheet) | C20: =DCF!C46 -> 0.085 | D20: =DCF!D46 -> 0.0676 | E20: =DCF!E46 -> 0.06
B21: Financials | C21: =CHOOSE(BoxRate+1,C$19,MAX(gLT+(C$19-gLT)*$G$7,C$20+ERPfloor),IF(FixInfl=1,(1+C$20+$H$7*DCF!C$47)*(1+InflLT)-1,C$20+$H$7*DCF!C$47)) -> 0.13760273 | D21: =CHOOSE(BoxRate+1,D$19,MAX(gLT+(D$19-gLT)*$G$7,D$20+ERPfloor),IF(FixInfl=1,(1+D$20+$H$7*DCF!D$47)*(1+InflLT)-1,D$20+$H$7*DCF!D$47)) -> 0.12151612 | E21: =CHOOSE(BoxRate+1,E$19,MAX(gLT+(E$19-gLT)*$G$7,E$20+ERPfloor),IF(FixInfl=1,(1+E$20+$H$7*DCF!E$47)*(1+InflLT)-1,E$20+$H$7*DCF!E$47)) -> 0.11448979 | G21: =C21-C$20 -> 0.052602725 | H21: =D21-D$20 -> 0.053916119 | I21: =E21-E$20 -> 0.054489785
B22: Defensives | C22: =CHOOSE(BoxRate+1,C$19,MAX(gLT+(C$19-gLT)*$G$8,C$20+ERPfloor),IF(FixInfl=1,(1+C$20+$H$8*DCF!C$47)*(1+InflLT)-1,C$20+$H$8*DCF!C$47)) -> 0.10925386 | D22: =CHOOSE(BoxRate+1,D$19,MAX(gLT+(D$19-gLT)*$G$8,D$20+ERPfloor),IF(FixInfl=1,(1+D$20+$H$8*DCF!D$47)*(1+InflLT)-1,D$20+$H$8*DCF!D$47)) -> 0.098200625 | E22: =CHOOSE(BoxRate+1,E$19,MAX(gLT+(E$19-gLT)*$G$8,E$20+ERPfloor),IF(FixInfl=1,(1+E$20+$H$8*DCF!E$47)*(1+InflLT)-1,E$20+$H$8*DCF!E$47)) -> 0.093372774 | G22: =C22-C$20 -> 0.024253862 | H22: =D22-D$20 -> 0.030600625 | I22: =E22-E$20 -> 0.033372774
B23: Cyclicals | C23: =CHOOSE(BoxRate+1,C$19,MAX(gLT+(C$19-gLT)*$G$9,C$20+ERPfloor),IF(FixInfl=1,(1+C$20+$H$9*DCF!C$47)*(1+InflLT)-1,C$20+$H$9*DCF!C$47)) -> 0.085 | D23: =CHOOSE(BoxRate+1,D$19,MAX(gLT+(D$19-gLT)*$G$9,D$20+ERPfloor),IF(FixInfl=1,(1+D$20+$H$9*DCF!D$47)*(1+InflLT)-1,D$20+$H$9*DCF!D$47)) -> 0.070962739 | E23: =CHOOSE(BoxRate+1,E$19,MAX(gLT+(E$19-gLT)*$G$9,E$20+ERPfloor),IF(FixInfl=1,(1+E$20+$H$9*DCF!E$47)*(1+InflLT)-1,E$20+$H$9*DCF!E$47)) -> 0.068703225 | G23: =C23-C$20 -> 0 | H23: =D23-D$20 -> 0.003362739 | I23: =E23-E$20 -> 0.0087032252
B24: Commodities | C24: =CHOOSE(BoxRate+1,C$19,MAX(gLT+(C$19-gLT)*$G$10,C$20+ERPfloor),IF(FixInfl=1,(1+C$20+$H$10*DCF!C$47)*(1+InflLT)-1,C$20+$H$10*DCF!C$47)) -> 0.19745744 | D24: =CHOOSE(BoxRate+1,D$19,MAX(gLT+(D$19-gLT)*$G$10,D$20+ERPfloor),IF(FixInfl=1,(1+D$20+$H$10*DCF!D$47)*(1+InflLT)-1,D$20+$H$10*DCF!D$47)) -> 0.17074357 | E24: =CHOOSE(BoxRate+1,E$19,MAX(gLT+(E$19-gLT)*$G$10,E$20+ERPfloor),IF(FixInfl=1,(1+E$20+$H$10*DCF!E$47)*(1+InflLT)-1,E$20+$H$10*DCF!E$47)) -> 0.15907544 | G24: =C24-C$20 -> 0.11245744 | H24: =D24-D$20 -> 0.10314357 | I24: =E24-E$20 -> 0.099075438
B25: Memo (inside Cyclicals)
B26: Cyclicals ex-WEG & Embraer | C26: =CHOOSE(BoxRate+1,C$19,MAX(gLT+(C$19-gLT)*$G$13,C$20+ERPfloor),IF(FixInfl=1,(1+C$20+$H$13*DCF!C$47)*(1+InflLT)-1,C$20+$H$13*DCF!C$47)) -> 0.085 | D26: =CHOOSE(BoxRate+1,D$19,MAX(gLT+(D$19-gLT)*$G$13,D$20+ERPfloor),IF(FixInfl=1,(1+D$20+$H$13*DCF!D$47)*(1+InflLT)-1,D$20+$H$13*DCF!D$47)) -> 0.072822919 | E26: =CHOOSE(BoxRate+1,E$19,MAX(gLT+(E$19-gLT)*$G$13,E$20+ERPfloor),IF(FixInfl=1,(1+E$20+$H$13*DCF!E$47)*(1+InflLT)-1,E$20+$H$13*DCF!E$47)) -> 0.070388004 | G26: =C26-C$20 -> 0 | H26: =D26-D$20 -> 0.0052229195 | I26: =E26-E$20 -> 0.010388004
B27: WEG & Embraer | C27: =CHOOSE(BoxRate+1,C$19,MAX(gLT+(C$19-gLT)*$G$14,C$20+ERPfloor),IF(FixInfl=1,(1+C$20+$H$14*DCF!C$47)*(1+InflLT)-1,C$20+$H$14*DCF!C$47)) -> 0.085 | D27: =CHOOSE(BoxRate+1,D$19,MAX(gLT+(D$19-gLT)*$G$14,D$20+ERPfloor),IF(FixInfl=1,(1+D$20+$H$14*DCF!D$47)*(1+InflLT)-1,D$20+$H$14*DCF!D$47)) -> 0.0676 | E27: =CHOOSE(BoxRate+1,E$19,MAX(gLT+(E$19-gLT)*$G$14,E$20+ERPfloor),IF(FixInfl=1,(1+E$20+$H$14*DCF!E$47)*(1+InflLT)-1,E$20+$H$14*DCF!E$47)) -> 0.063935286 | G27: =C27-C$20 -> 0 | H27: =D27-D$20 -> 0 | I27: =E27-E$20 -> 0.0039352858
B28: BoxRate 0: the house rate. 1: g + (house rate - g) x relative cash yield, at least real rate + floor. 2: CAPM, real rate + beta x house ERP (Fisher if FixInfl = 1). Risk premium = rate - real rate.
B30: 3. Monthly 12m fwd earnings yield by box (1 / harmonic P/E of the month's members; Bloomberg panel of the multiples model)
B31: Month-end | C31: Financials | D31: Defensives | E31: Cyclicals | F31: Commodities | G31: Ibovespa | H31: Cyclicals ex-WEG & Embraer | I31: WEG & Embraer
B32: 42674 | C32: 0.097129301 | D32: 0.054043084 | E32: 0.061020751 | F32: 0.059499887 | G32: 0.071929311 | H32: 0.059724662 | I32: 0.068374833
B33: 42704 | C33: 0.10999658 | D33: 0.059068695 | E33: 0.068871355 | F33: 0.056921621 | G33: 0.07740352 | H33: 0.067637157 | I33: 0.075473874
B34: 42735 | C34: 0.11380828 | D34: 0.060950372 | E34: 0.069286831 | F34: 0.074568531 | G34: 0.084370771 | H34: 0.067704258 | I34: 0.078184002
B35: 42766 | C35: 0.10434124 | D35: 0.058688993 | E35: 0.067259516 | F35: 0.077537889 | G35: 0.081485863 | H35: 0.06644891 | I35: 0.071561336
B36: 42794 | C36: 0.10058139 | D36: 0.058304742 | E36: 0.064388348 | F36: 0.08627569 | G36: 0.08216617 | H36: 0.063605189 | I36: 0.06879095
B37: 42825 | C37: 0.10649035 | D37: 0.059366601 | E37: 0.064297621 | F37: 0.10213707 | G37: 0.088318039 | H37: 0.063701459 | I37: 0.067878586
B38: 42855 | C38: 0.1047335 | D38: 0.058662053 | E38: 0.062554795 | F38: 0.10251536 | G38: 0.086871579 | H38: 0.061623108 | I38: 0.068857016
B39: 42886 | C39: 0.11417637 | D39: 0.055875353 | E39: 0.067520158 | F39: 0.11641556 | G39: 0.093376516 | H39: 0.068145011 | I39: 0.064018648
B40: 42916 | C40: 0.11269323 | D40: 0.063002736 | E40: 0.067664863 | F40: 0.11070484 | G40: 0.093550509 | H40: 0.067580456 | I40: 0.068182556
B41: 42947 | C41: 0.1092513 | D41: 0.060343248 | E41: 0.063730894 | F41: 0.10091957 | G41: 0.088525712 | H41: 0.063542383 | I41: 0.064919083
B42: 42978 | C42: 0.10121318 | D42: 0.057276405 | E42: 0.05891732 | F42: 0.087965053 | G42: 0.081052692 | H42: 0.059428875 | I42: 0.055744274
B43: 43008 | C43: 0.094121653 | D43: 0.056487977 | E43: 0.054739012 | F43: 0.090717724 | G43: 0.078083076 | H43: 0.054853251 | I43: 0.05398122
... B151: 46295 | C151: 0.11841947 | D151: 0.076205395 | E151: 0.087337675 | F151: 0.15896093 | G151: 0.11635217 | H151: 0.1088258 | I151: 0.058419893

Sheet Box Betas
B1: Ibovespa - Box betas vs the Ibovespa (CAPM)
B2: Beta = covariance of the box's weekly total return with the Ibovespa's / variance of the Ibovespa's, over the window in Assumptions.
B3: Legend: | C3: input | D3: assumption | E3: formula
B5: 1. Beta of each box vs the Ibovespa (weekly total returns, window in Assumptions)
B6: Group | C6: Weeks in the window | D6: Average weekly return | E6: Covariance with the Ibovespa | F6: Variance of the Ibovespa | G6: Beta (raw) | H6: Beta (Blume adjusted) | I6: Beta used
B7: Financials | C7: =SUM($C$23:$C$544) -> 261 | D7: =SUMPRODUCT($C$23:$C$544,K$23:K$544)/C7 -> 0.0030820715 | E7: =(SUMPRODUCT($C$23:$C$544,K$23:K$544,O$23:O$544)-C7*D7*$D$11)/(C7-1) -> 0.00063674946 | F7: =(SUMPRODUCT($C$23:$C$544,O$23:O$544,O$23:O$544)-C7*$D$11^2)/(C7-1) -> 0.00055414638 | G7: =E7/F7 -> 1.1490637 | H7: =0.67*G7+0.33 -> 1.0998727 | I7: =IF(BetaAdj=2,H7,G7) -> 1.1490637
B8: Defensives | C8: =SUM($C$23:$C$544) -> 261 | D8: =SUMPRODUCT($C$23:$C$544,L$23:L$544)/C8 -> 0.0012762594 | E8: =(SUMPRODUCT($C$23:$C$544,L$23:L$544,O$23:O$544)-C8*D8*$D$11)/(C8-1) -> 0.00051462131 | F8: =(SUMPRODUCT($C$23:$C$544,O$23:O$544,O$23:O$544)-C8*$D$11^2)/(C8-1) -> 0.00055414638 | G8: =E8/F8 -> 0.92867396 | H8: =0.67*G8+0.33 -> 0.95221156 | I8: =IF(BetaAdj=2,H8,G8) -> 0.92867396
B9: Cyclicals | C9: =SUM($C$23:$C$544) -> 261 | D9: =SUMPRODUCT($C$23:$C$544,M$23:M$544)/C9 -> -1.0469226e-05 | E9: =(SUMPRODUCT($C$23:$C$544,M$23:M$544,O$23:O$544)-C9*D9*$D$11)/(C9-1) -> 0.00063751831 | F9: =(SUMPRODUCT($C$23:$C$544,O$23:O$544,O$23:O$544)-C9*$D$11^2)/(C9-1) -> 0.00055414638 | G9: =E9/F9 -> 1.1504511 | H9: =0.67*G9+0.33 -> 1.1008022 | I9: =IF(BetaAdj=2,H9,G9) -> 1.1504511
B10: Commodities | C10: =SUM($C$23:$C$544) -> 261 | D10: =SUMPRODUCT($C$23:$C$544,N$23:N$544)/C10 -> 0.0035658949 | E10: =(SUMPRODUCT($C$23:$C$544,N$23:N$544,O$23:O$544)-C10*D10*$D$11)/(C10-1) -> 0.00048304155 | F10: =(SUMPRODUCT($C$23:$C$544,O$23:O$544,O$23:O$544)-C10*$D$11^2)/(C10-1) -> 0.00055414638 | G10: =E10/F10 -> 0.87168584 | H10: =0.67*G10+0.33 -> 0.91402951 | I10: =IF(BetaAdj=2,H10,G10) -> 0.87168584
B11: Ibovespa | C11: =SUM($C$23:$C$544) -> 261 | D11: =SUMPRODUCT($C$23:$C$544,O$23:O$544)/C11 -> 0.0022357788 | E11: =(SUMPRODUCT($C$23:$C$544,O$23:O$544,O$23:O$544)-C11*D11*$D$11)/(C11-1) -> 0.00055414638 | F11: =(SUMPRODUCT($C$23:$C$544,O$23:O$544,O$23:O$544)-C11*$D$11^2)/(C11-1) -> 0.00055414638 | G11: =E11/F11 -> 1 | H11: =0.67*G11+0.33 -> 1 | I11: =IF(BetaAdj=2,H11,G11) -> 1
B12: Memo (inside Cyclicals)
B13: Cyclicals ex-WEG & Embraer | C13: =SUM($C$23:$C$544) -> 261 | D13: =SUMPRODUCT($C$23:$C$544,P$23:P$544)/C13 -> -0.0014397436 | E13: =(SUMPRODUCT($C$23:$C$544,P$23:P$544,O$23:O$544)-C13*D13*$D$11)/(C13-1) -> 0.0007307609 | F13: =(SUMPRODUCT($C$23:$C$544,O$23:O$544,O$23:O$544)-C13*$D$11^2)/(C13-1) -> 0.00055414638 | G13: =E13/F13 -> 1.3187146 | H13: =0.67*G13+0.33 -> 1.2135388 | I13: =IF(BetaAdj=2,H13,G13) -> 1.3187146
B14: WEG & Embraer | C14: =SUM($C$23:$C$544) -> 261 | D14: =SUMPRODUCT($C$23:$C$544,Q$23:Q$544)/C14 -> 0.0035937116 | E14: =(SUMPRODUCT($C$23:$C$544,Q$23:Q$544,O$23:O$544)-C14*D14*$D$11)/(C14-1) -> 0.0003977854 | F14: =(SUMPRODUCT($C$23:$C$544,O$23:O$544,O$23:O$544)-C14*$D$11^2)/(C14-1) -> 0.00055414638 | G14: =E14/F14 -> 0.71783452 | H14: =0.67*G14+0.33 -> 0.81094913 | I14: =IF(BetaAdj=2,H14,G14) -> 0.71783452
B16: Weighted average of the four box betas (~1) | C16: =SUMPRODUCT(I7:I10,'Box Shares'!C7:C10)/SUM('Box Shares'!C7:C10) -> 1.0031655
B17: Window: weeks after | C17: =EDATE($B$544,-12*BetaYears) -> 44464
B18: Source: box total-return indices (Economatica adjusted close, members at the previous month-end index weights; Oct-5 performance study, box_daily.parquet). The Ibovespa here is the sum of the four boxes.
B20: 2. Weekly data (Friday closes): index levels (inputs) and returns (formulas)
B21: Week | C21: In window (1/0) | D21: Financials, level | E21: Defensives, level | F21: Cyclicals, level | G21: Commodities, level | H21: Ibovespa, level | I21: Cyclicals ex-WEG & Embraer, level | J21: WEG & Embraer, level | K21: Financials, return | L21: Defensives, return | M21: Cyclicals, return | N21: Commodities, return | O21: Ibovespa, return | P21: Cyclicals ex-WEG & Embraer, return | Q21: WEG & Embraer, return
B22: 42636 | D22: 2.8362212 | E22: 2.4029919 | F22: 0.90378628 | G22: 0.84339519 | H22: 1.5783635 | I22: 0.95267186 | J22: 1.1819149
B23: 42643 | C23: =IF(B23>$C$17,1,0) -> 0 | D23: 2.8001254 | E23: 2.3817054 | F23: 0.89890386 | G23: 0.84952528 | H23: 1.5690736 | I23: 0.95185448 | J23: 1.1423026 | K23: =D23/D22-1 -> -0.012726725 | L23: =E23/E22-1 -> -0.0088583086 | M23: =F23/F22-1 -> -0.0054021796 | N23: =G23/G22-1 -> 0.007268344 | O23: =H23/H22-1 -> -0.0058857491 | P23: =I23/I22-1 -> -0.00085798315 | Q23: =J23/J22-1 -> -0.033515325
B24: 42650 | C24: =IF(B24>$C$17,1,0) -> 0 | D24: 2.9766966 | E24: 2.4208488 | F24: 0.92884678 | G24: 0.90979039 | H24: 1.6437996 | I24: 0.98455911 | J24: 1.1727671 | K24: =D24/D23-1 -> 0.063058329 | L24: =E24/E23-1 -> 0.016435028 | M24: =F24/F23-1 -> 0.033310483 | N24: =G24/G23-1 -> 0.070939752 | O24: =H24/H23-1 -> 0.047624242 | P24: =I24/I23-1 -> 0.034358849 | Q24: =J24/J23-1 -> 0.026669316
B25: 42657 | C25: =IF(B25>$C$17,1,0) -> 0 | D25: 3.0309802 | E25: 2.4025779 | F25: 0.92309053 | G25: 0.93843968 | H25: 1.6617599 | I25: 0.9783263 | J25: 1.1664974 | K25: =D25/D24-1 -> 0.018236173 | L25: =E25/E24-1 -> -0.0075473366 | M25: =F25/F24-1 -> -0.0061972024 | N25: =G25/G24-1 -> 0.031489991 | O25: =H25/H24-1 -> 0.010926088 | P25: =I25/I24-1 -> -0.0063305612 | Q25: =J25/J24-1 -> -0.0053460766
B26: 42664 | C26: =IF(B26>$C$17,1,0) -> 0 | D26: 3.1368775 | E26: 2.4129921 | F26: 0.95430764 | G26: 1.0139571 | H26: 1.7249901 | I26: 1.0097588 | J26: 1.2185095 | K26: =D26/D25-1 -> 0.034938297 | L26: =E26/E25-1 -> 0.0043345804 | M26: =F26/F25-1 -> 0.033818038 | N26: =G26/G25-1 -> 0.080471297 | O26: =H26/H25-1 -> 0.038050185 | P26: =I26/I25-1 -> 0.032128832 | Q26: =J26/J25-1 -> 0.044588256
B27: 42671 | C27: =IF(B27>$C$17,1,0) -> 0 | D27: 3.1533524 | E27: 2.370798 | F27: 0.93318344 | G27: 1.0493576 | H27: 1.7303738 | I27: 0.98437897 | J27: 1.2145578 | K27: =D27/D26-1 -> 0.0052520316 | L27: =E27/E26-1 -> -0.017486206 | M27: =F27/F26-1 -> -0.022135637 | N27: =G27/G26-1 -> 0.034913135 | O27: =H27/H26-1 -> 0.0031209749 | P27: =I27/I26-1 -> -0.025134529 | Q27: =J27/J26-1 -> -0.0032430408
B28: 42678 | C28: =IF(B28>$C$17,1,0) -> 0 | D28: 3.0921265 | E28: 2.2585034 | F28: 0.89988788 | G28: 0.97700476 | H28: 1.6580507 | I28: 0.93744822 | J28: 1.2587786 | K28: =D28/D27-1 -> -0.019416132 | L28: =E28/E27-1 -> -0.047365717 | M28: =F28/F27-1 -> -0.035679545 | N28: =G28/G27-1 -> -0.068949616 | O28: =H28/H27-1 -> -0.041796192 | P28: =I28/I27-1 -> -0.047675482 | Q28: =J28/J27-1 -> 0.036409028
B29: 42685 | C29: =IF(B29>$C$17,1,0) -> 0 | D29: 2.888352 | E29: 2.150716 | F29: 0.83820132 | G29: 1.0017697 | H29: 1.5945633 | I29: 0.86316304 | J29: 1.2453824 | K29: =D29/D28-1 -> -0.065901082 | L29: =E29/E28-1 -> -0.04772514 | M29: =F29/F28-1 -> -0.068549152 | N29: =G29/G28-1 -> 0.025347828 | O29: =H29/H28-1 -> -0.03829043 | P29: =I29/I28-1 -> -0.07924191 | Q29: =J29/J28-1 -> -0.010642291
B30: 42692 | C30: =IF(B30>$C$17,1,0) -> 0 | D30: 2.9567279 | E30: 2.2120121 | F30: 0.83408751 | G30: 0.9960464 | H30: 1.6149506 | I30: 0.85752472 | J30: 1.2494651 | K30: =D30/D29-1 -> 0.023672966 | L30: =E30/E29-1 -> 0.028500294 | M30: =F30/F29-1 -> -0.0049079116 | N30: =G30/G29-1 -> -0.0057131992 | O30: =H30/H29-1 -> 0.012785535 | P30: =I30/I29-1 -> -0.0065321595 | Q30: =J30/J29-1 -> 0.0032783344
B31: 42699 | C31: =IF(B31>$C$17,1,0) -> 0 | D31: 2.9596254 | E31: 2.2131989 | F31: 0.83893724 | G31: 1.0907753 | H31: 1.6583623 | I31: 0.87130813 | J31: 1.192757 | K31: =D31/D30-1 -> 0.0009799777 | L31: =E31/E30-1 -> 0.00053655115 | M31: =F31/F30-1 -> 0.005814415 | N31: =G31/G30-1 -> 0.095104864 | O31: =H31/H30-1 -> 0.026881138 | P31: =I31/I30-1 -> 0.016073482 | Q31: =J31/J30-1 -> -0.04538591
B32: 42706 | C32: =IF(B32>$C$17,1,0) -> 0 | D32: 2.8701871 | E32: 2.1193881 | F32: 0.81019204 | G32: 1.110478 | H32: 1.6259416 | I32: 0.8381695 | J32: 1.1755638 | K32: =D32/D31-1 -> -0.030219484 | L32: =E32/E31-1 -> -0.042387004 | M32: =F32/F31-1 -> -0.034263826 | N32: =G32/G31-1 -> 0.018063094 | O32: =H32/H31-1 -> -0.019549822 | P32: =I32/I31-1 -> -0.038033186 | Q32: =J32/J31-1 -> -0.0144147
B33: 42713 | C33: =IF(B33>$C$17,1,0) -> 0 | D33: 2.8782633 | E33: 2.1529599 | F33: 0.81053728 | G33: 1.1034389 | H33: 1.6304638 | I33: 0.84246307 | J33: 1.1476038 | K33: =D33/D32-1 -> 0.0028138319 | L33: =E33/E32-1 -> 0.015840343 | M33: =F33/F32-1 -> 0.00042612385 | N33: =G33/G32-1 -> -0.0063388709 | O33: =H33/H32-1 -> 0.0027812863 | P33: =I33/I32-1 -> 0.0051225561 | Q33: =J33/J32-1 -> -0.023784312
B34: 42720 | C34: =IF(B34>$C$17,1,0) -> 0 | D34: 2.7625784 | E34: 2.1299047 | F34: 0.78496025 | G34: 1.0481401 | H34: 1.5733805 | I34: 0.8160108 | J34: 1.1104346 | K34: =D34/D33-1 -> -0.040192591 | L34: =E34/E33-1 -> -0.010708592 | M34: =F34/F33-1 -> -0.031555649 | N34: =G34/G33-1 -> -0.050114968 | O34: =H34/H33-1 -> -0.035010507 | P34: =I34/I33-1 -> -0.031398736 | Q34: =J34/J33-1 -> -0.032388499
... B544: 46290 | C544: =IF(B544>$C$17,1,0) -> 1 | D544: 9.5756116 | E544: 4.4061862 | F544: 1.2196401 | G544: 6.3449697 | H544: 5.2095645 | I544: 0.71292613 | J544: 9.8330559 | K544: =D544/D543-1 -> -0.0047055902 | L544: =E544/E543-1 -> -0.0057913546 | M544: =F544/F543-1 -> 0.024536683 | N544: =G544/G543-1 -> -0.028530005 | O544: =H544/H543-1 -> -0.0092774246 | P544: =I544/I543-1 -> 0.031134181 | Q544: =J544/J543-1 -> 0.016586627

Sheet Box Shares
B1: Ibovespa - Box shares of the house lines
B2: Members' consensus by box (index pts) as a share of the IBOV Index line (Bloomberg, Oct-7-2026); Financials = the rest. Net income: share of the members' total.
B3: Legend: | C3: input | D3: assumption | E3: formula
B5: 1. Members' consensus by box (index pts, Members sheet)
B6: Group | C6: Index points | D6: Sales 2026 | E6: Sales 2027 | F6: Sales 2028 | G6: EBIT 2026 | H6: EBIT 2027 | I6: EBIT 2028 | J6: EBITDA 2026 | K6: EBITDA 2027 | L6: EBITDA 2028 | M6: Net income 2026 | N6: Net income 2027 | O6: Net income 2028 | P6: Capex 2026 | Q6: Capex 2027 | R6: Capex 2028
B7: Financials | C7: =SUMIFS(Members!$J$6:$J$81,Members!$C$6:$C$81,"Financials") -> 60927.304 | D7: =SUMIFS(Members!$AA$6:$AA$81,Members!$C$6:$C$81,"Financials") -> 23202.292 | E7: =SUMIFS(Members!$AB$6:$AB$81,Members!$C$6:$C$81,"Financials") -> 24843.532 | F7: =SUMIFS(Members!$AC$6:$AC$81,Members!$C$6:$C$81,"Financials") -> 26614.283 | G7: =SUMIFS(Members!$AD$6:$AD$81,Members!$C$6:$C$81,"Financials") -> 5850.9178 | H7: =SUMIFS(Members!$AE$6:$AE$81,Members!$C$6:$C$81,"Financials") -> 6776.2881 | I7: =SUMIFS(Members!$AF$6:$AF$81,Members!$C$6:$C$81,"Financials") -> 7553.6721 | J7: =SUMIFS(Members!$AG$6:$AG$81,Members!$C$6:$C$81,"Financials") -> 1489.4529 | K7: =SUMIFS(Members!$AH$6:$AH$81,Members!$C$6:$C$81,"Financials") -> 4304.3334 | L7: =SUMIFS(Members!$AI$6:$AI$81,Members!$C$6:$C$81,"Financials") -> 4975.2097 | M7: =SUMIFS(Members!$AJ$6:$AJ$81,Members!$C$6:$C$81,"Financials") -> 5708.1181 | N7: =SUMIFS(Members!$AK$6:$AK$81,Members!$C$6:$C$81,"Financials") -> 6447.8435 | O7: =SUMIFS(Members!$AL$6:$AL$81,Members!$C$6:$C$81,"Financials") -> 7167.1074 | P7: =SUMIFS(Members!$AM$6:$AM$81,Members!$C$6:$C$81,"Financials") -> -38.325056 | Q7: =SUMIFS(Members!$AN$6:$AN$81,Members!$C$6:$C$81,"Financials") -> -40.957339 | R7: =SUMIFS(Members!$AO$6:$AO$81,Members!$C$6:$C$81,"Financials") -> -42.548672
B8: Defensives | C8: =SUMIFS(Members!$J$6:$J$81,Members!$C$6:$C$81,"Defensives") -> 55822.367 | D8: =SUMIFS(Members!$AA$6:$AA$81,Members!$C$6:$C$81,"Defensives") -> 40617.343 | E8: =SUMIFS(Members!$AB$6:$AB$81,Members!$C$6:$C$81,"Defensives") -> 43046.203 | F8: =SUMIFS(Members!$AC$6:$AC$81,Members!$C$6:$C$81,"Defensives") -> 45622.953 | G8: =SUMIFS(Members!$AD$6:$AD$81,Members!$C$6:$C$81,"Defensives") -> 6963.6385 | H8: =SUMIFS(Members!$AE$6:$AE$81,Members!$C$6:$C$81,"Defensives") -> 8214.8511 | I8: =SUMIFS(Members!$AF$6:$AF$81,Members!$C$6:$C$81,"Defensives") -> 9038.7163 | J8: =SUMIFS(Members!$AG$6:$AG$81,Members!$C$6:$C$81,"Defensives") -> 9723.997 | K8: =SUMIFS(Members!$AH$6:$AH$81,Members!$C$6:$C$81,"Defensives") -> 11076.936 | L8: =SUMIFS(Members!$AI$6:$AI$81,Members!$C$6:$C$81,"Defensives") -> 12045.129 | M8: =SUMIFS(Members!$AJ$6:$AJ$81,Members!$C$6:$C$81,"Defensives") -> 2976.1707 | N8: =SUMIFS(Members!$AK$6:$AK$81,Members!$C$6:$C$81,"Defensives") -> 3846.4715 | O8: =SUMIFS(Members!$AL$6:$AL$81,Members!$C$6:$C$81,"Defensives") -> 4531.2547 | P8: =SUMIFS(Members!$AM$6:$AM$81,Members!$C$6:$C$81,"Defensives") -> -5321.2517 | Q8: =SUMIFS(Members!$AN$6:$AN$81,Members!$C$6:$C$81,"Defensives") -> -5151.0639 | R8: =SUMIFS(Members!$AO$6:$AO$81,Members!$C$6:$C$81,"Defensives") -> -5194.9343
B9: Cyclicals | C9: =SUMIFS(Members!$J$6:$J$81,Members!$C$6:$C$81,"Cyclicals") -> 26271.075 | D9: =SUMIFS(Members!$AA$6:$AA$81,Members!$C$6:$C$81,"Cyclicals") -> 16936.602 | E9: =SUMIFS(Members!$AB$6:$AB$81,Members!$C$6:$C$81,"Cyclicals") -> 18538.664 | F9: =SUMIFS(Members!$AC$6:$AC$81,Members!$C$6:$C$81,"Cyclicals") -> 20107.22 | G9: =SUMIFS(Members!$AD$6:$AD$81,Members!$C$6:$C$81,"Cyclicals") -> 3109.1241 | H9: =SUMIFS(Members!$AE$6:$AE$81,Members!$C$6:$C$81,"Cyclicals") -> 3528.414 | I9: =SUMIFS(Members!$AF$6:$AF$81,Members!$C$6:$C$81,"Cyclicals") -> 3924.0972 | J9: =SUMIFS(Members!$AG$6:$AG$81,Members!$C$6:$C$81,"Cyclicals") -> 4335.4894 | K9: =SUMIFS(Members!$AH$6:$AH$81,Members!$C$6:$C$81,"Cyclicals") -> 4818.2195 | L9: =SUMIFS(Members!$AI$6:$AI$81,Members!$C$6:$C$81,"Cyclicals") -> 5281.4012 | M9: =SUMIFS(Members!$AJ$6:$AJ$81,Members!$C$6:$C$81,"Cyclicals") -> 1607.0455 | N9: =SUMIFS(Members!$AK$6:$AK$81,Members!$C$6:$C$81,"Cyclicals") -> 1944.9107 | O9: =SUMIFS(Members!$AL$6:$AL$81,Members!$C$6:$C$81,"Cyclicals") -> 2304.3006 | P9: =SUMIFS(Members!$AM$6:$AM$81,Members!$C$6:$C$81,"Cyclicals") -> -2939.1741 | Q9: =SUMIFS(Members!$AN$6:$AN$81,Members!$C$6:$C$81,"Cyclicals") -> -3016.8976 | R9: =SUMIFS(Members!$AO$6:$AO$81,Members!$C$6:$C$81,"Cyclicals") -> -3046.1844
B10: Commodities | C10: =SUMIFS(Members!$J$6:$J$81,Members!$C$6:$C$81,"Commodities") -> 65411.174 | D10: =SUMIFS(Members!$AA$6:$AA$81,Members!$C$6:$C$81,"Commodities") -> 77175.121 | E10: =SUMIFS(Members!$AB$6:$AB$81,Members!$C$6:$C$81,"Commodities") -> 76522.299 | F10: =SUMIFS(Members!$AC$6:$AC$81,Members!$C$6:$C$81,"Commodities") -> 76672.759 | G10: =SUMIFS(Members!$AD$6:$AD$81,Members!$C$6:$C$81,"Commodities") -> 16297.837 | H10: =SUMIFS(Members!$AE$6:$AE$81,Members!$C$6:$C$81,"Commodities") -> 15588.904 | I10: =SUMIFS(Members!$AF$6:$AF$81,Members!$C$6:$C$81,"Commodities") -> 15548.029 | J10: =SUMIFS(Members!$AG$6:$AG$81,Members!$C$6:$C$81,"Commodities") -> 23879.774 | K10: =SUMIFS(Members!$AH$6:$AH$81,Members!$C$6:$C$81,"Commodities") -> 23390.5 | L10: =SUMIFS(Members!$AI$6:$AI$81,Members!$C$6:$C$81,"Commodities") -> 23022.676 | M10: =SUMIFS(Members!$AJ$6:$AJ$81,Members!$C$6:$C$81,"Commodities") -> 10671.973 | N10: =SUMIFS(Members!$AK$6:$AK$81,Members!$C$6:$C$81,"Commodities") -> 9633.4894 | O10: =SUMIFS(Members!$AL$6:$AL$81,Members!$C$6:$C$81,"Commodities") -> 9381.2464 | P10: =SUMIFS(Members!$AM$6:$AM$81,Members!$C$6:$C$81,"Commodities") -> -7883.0992 | Q10: =SUMIFS(Members!$AN$6:$AN$81,Members!$C$6:$C$81,"Commodities") -> -7856.0222 | R10: =SUMIFS(Members!$AO$6:$AO$81,Members!$C$6:$C$81,"Commodities") -> -8084.3149
B11: Sum of the members | C11: =SUM(C7:C10) -> 208431.92 | D11: =SUM(D7:D10) -> 157931.36 | E11: =SUM(E7:E10) -> 162950.7 | F11: =SUM(F7:F10) -> 169017.22 | G11: =SUM(G7:G10) -> 32221.517 | H11: =SUM(H7:H10) -> 34108.458 | I11: =SUM(I7:I10) -> 36064.515 | J11: =SUM(J7:J10) -> 39428.713 | ... R11: =SUM(R7:R10) -> -16367.982
B12: IBOV Index line (Bloomberg BEST, Oct-7) | C12: =Assumptions!$D$7 -> 208431.92 | D12: 160409.73 | E12: 165250.94 | F12: 171865.57 | G12: 33247.221 | H12: 35095.03 | I12: 37020.133 | J12: 50718.553 | K12: 52448.44 | L12: 54198.893 | M12: n/a | N12: n/a | O12: n/a | P12: -21468.225 | Q12: -21347.899 | R12: -21866.048
B13: Memo (inside Cyclicals)
B14: Cyclicals ex-WEG & Embraer | C14: =SUMIFS(Members!$J$6:$J$81,Members!$D$6:$D$81,"Cyclicals ex-WEG & Embraer") -> 16066.52 | D14: =SUMIFS(Members!$AA$6:$AA$81,Members!$D$6:$D$81,"Cyclicals ex-WEG & Embraer") -> 12657.227 | E14: =SUMIFS(Members!$AB$6:$AB$81,Members!$D$6:$D$81,"Cyclicals ex-WEG & Embraer") -> 13704.692 | F14: =SUMIFS(Members!$AC$6:$AC$81,Members!$D$6:$D$81,"Cyclicals ex-WEG & Embraer") -> 14680.718 | G14: =SUMIFS(Members!$AD$6:$AD$81,Members!$D$6:$D$81,"Cyclicals ex-WEG & Embraer") -> 2576.2819 | H14: =SUMIFS(Members!$AE$6:$AE$81,Members!$D$6:$D$81,"Cyclicals ex-WEG & Embraer") -> 2902.4362 | I14: =SUMIFS(Members!$AF$6:$AF$81,Members!$D$6:$D$81,"Cyclicals ex-WEG & Embraer") -> 3198.314 | J14: =SUMIFS(Members!$AG$6:$AG$81,Members!$D$6:$D$81,"Cyclicals ex-WEG & Embraer") -> 3683.3443 | K14: =SUMIFS(Members!$AH$6:$AH$81,Members!$D$6:$D$81,"Cyclicals ex-WEG & Embraer") -> 4066.1867 | L14: =SUMIFS(Members!$AI$6:$AI$81,Members!$D$6:$D$81,"Cyclicals ex-WEG & Embraer") -> 4413.0871 | M14: =SUMIFS(Members!$AJ$6:$AJ$81,Members!$D$6:$D$81,"Cyclicals ex-WEG & Embraer") -> 1231.4676 | N14: =SUMIFS(Members!$AK$6:$AK$81,Members!$D$6:$D$81,"Cyclicals ex-WEG & Embraer") -> 1493.1316 | O14: =SUMIFS(Members!$AL$6:$AL$81,Members!$D$6:$D$81,"Cyclicals ex-WEG & Embraer") -> 1766.5305 | P14: =SUMIFS(Members!$AM$6:$AM$81,Members!$D$6:$D$81,"Cyclicals ex-WEG & Embraer") -> -2719.5338 | Q14: =SUMIFS(Members!$AN$6:$AN$81,Members!$D$6:$D$81,"Cyclicals ex-WEG & Embraer") -> -2794.0287 | R14: =SUMIFS(Members!$AO$6:$AO$81,Members!$D$6:$D$81,"Cyclicals ex-WEG & Embraer") -> -2813.5173
B15: WEG & Embraer | C15: =SUMIFS(Members!$J$6:$J$81,Members!$D$6:$D$81,"WEG & Embraer") -> 10204.555 | D15: =SUMIFS(Members!$AA$6:$AA$81,Members!$D$6:$D$81,"WEG & Embraer") -> 4279.3755 | E15: =SUMIFS(Members!$AB$6:$AB$81,Members!$D$6:$D$81,"WEG & Embraer") -> 4833.9715 | F15: =SUMIFS(Members!$AC$6:$AC$81,Members!$D$6:$D$81,"WEG & Embraer") -> 5426.5028 | G15: =SUMIFS(Members!$AD$6:$AD$81,Members!$D$6:$D$81,"WEG & Embraer") -> 532.84218 | H15: =SUMIFS(Members!$AE$6:$AE$81,Members!$D$6:$D$81,"WEG & Embraer") -> 625.9778 | I15: =SUMIFS(Members!$AF$6:$AF$81,Members!$D$6:$D$81,"WEG & Embraer") -> 725.78323 | J15: =SUMIFS(Members!$AG$6:$AG$81,Members!$D$6:$D$81,"WEG & Embraer") -> 652.14517 | K15: =SUMIFS(Members!$AH$6:$AH$81,Members!$D$6:$D$81,"WEG & Embraer") -> 752.03278 | L15: =SUMIFS(Members!$AI$6:$AI$81,Members!$D$6:$D$81,"WEG & Embraer") -> 868.31407 | M15: =SUMIFS(Members!$AJ$6:$AJ$81,Members!$D$6:$D$81,"WEG & Embraer") -> 375.5779 | N15: =SUMIFS(Members!$AK$6:$AK$81,Members!$D$6:$D$81,"WEG & Embraer") -> 451.77901 | O15: =SUMIFS(Members!$AL$6:$AL$81,Members!$D$6:$D$81,"WEG & Embraer") -> 537.77011 | P15: =SUMIFS(Members!$AM$6:$AM$81,Members!$D$6:$D$81,"WEG & Embraer") -> -219.64027 | Q15: =SUMIFS(Members!$AN$6:$AN$81,Members!$D$6:$D$81,"WEG & Embraer") -> -222.86895 | R15: =SUMIFS(Members!$AO$6:$AO$81,Members!$D$6:$D$81,"WEG & Embraer") -> -232.66716
B17: 2. Shares used to split the house lines (DCF by Box)
B18: Group | C18: Index points | D18: Sales 2026 | E18: Sales 2027 | F18: Sales 2028 | G18: EBIT 2026 | H18: EBIT 2027 | I18: EBIT 2028 | J18: EBITDA 2026 | K18: EBITDA 2027 | L18: EBITDA 2028 | M18: Net income 2026 | N18: Net income 2027 | O18: Net income 2028 | P18: Capex 2026 | Q18: Capex 2027 | R18: Capex 2028
B19: Financials | C19: =C7/$C$11 -> 0.29231273 | D19: =1-SUM(D20:D22) -> 0.16009415 | E19: =1-SUM(E20:E22) -> 0.1642579 | F19: =1-SUM(F20:F22) -> 0.17142837 | G19: =1-SUM(G20:G22) -> 0.20683299 | H19: =1-SUM(H20:H22) -> 0.22119544 | I19: =1-SUM(I20:I22) -> 0.22985575 | J19: =1-SUM(J20:J22) -> 0.25196485 | K19: =1-SUM(K20:K22) -> 0.25096616 | L19: =1-SUM(L20:L22) -> 0.2555345 | M19: =M7/M$11 -> 0.27229092 | N19: =N7/N$11 -> 0.29478935 | O19: =O7/O$11 -> 0.3064974 | P19: =1-SUM(P20:P22) -> 0.24802703 | Q19: =1-SUM(Q20:Q22) -> 0.24938824 | R19: =1-SUM(R20:R22) -> 0.25338892
B20: Defensives | C20: =C8/$C$11 -> 0.26782063 | D20: =D8/D$12 -> 0.25320998 | E20: =E8/E$12 -> 0.26048992 | F20: =F8/F$12 -> 0.26545721 | G20: =G8/G$12 -> 0.20945024 | H20: =H8/H$12 -> 0.23407448 | I20: =I8/I$12 -> 0.24415677 | J20: =J8/J$12 -> 0.19172465 | K20: =K8/K$12 -> 0.21119668 | L20: =L8/L$12 -> 0.22223939 | M20: =M8/M$11 -> 0.14197048 | N20: =N8/N$11 -> 0.17585707 | O20: =O8/O$11 -> 0.19377661 | P20: =P8/P$12 -> 0.2478664 | Q20: =Q8/Q$12 -> 0.24129138 | R20: =R8/R$12 -> 0.23757994
B21: Cyclicals | C21: =C9/$C$11 -> 0.12604151 | D21: =D9/D$12 -> 0.10558339 | E21: =E9/E$12 -> 0.11218492 | F21: =F9/F$12 -> 0.11699389 | G21: =G9/G$12 -> 0.093515305 | H21: =H9/H$12 -> 0.10053885 | I21: =I9/I$12 -> 0.105999 | J21: =J9/J$12 -> 0.085481331 | K21: =K9/K$12 -> 0.09186583 | L21: =L9/L$12 -> 0.097444816 | M21: =M9/M$11 -> 0.076659923 | N21: =N9/N$11 -> 0.08891949 | O21: =O9/O$11 -> 0.098542148 | P21: =P9/P$12 -> 0.13690811 | Q21: =Q9/Q$12 -> 0.14132059 | R21: =R9/R$12 -> 0.13931116
B22: Commodities | C22: =C10/$C$11 -> 0.31382513 | D22: =D10/D$12 -> 0.48111248 | E22: =E10/E$12 -> 0.46306726 | F22: =F10/F$12 -> 0.44612054 | G22: =G10/G$12 -> 0.49020146 | H22: =H10/H$12 -> 0.44419122 | I22: =I10/I$12 -> 0.41998848 | J22: =J10/J$12 -> 0.47082917 | K22: =K10/K$12 -> 0.44597133 | L22: =L10/L$12 -> 0.42478129 | M22: =M10/M$11 -> 0.50907868 | N22: =N10/N$11 -> 0.44043409 | O22: =O10/O$11 -> 0.40118384 | P22: =P10/P$12 -> 0.36719846 | Q22: =Q10/Q$12 -> 0.36799979 | R22: =R10/R$12 -> 0.36971999
B23: Total | D23: =SUM(D19:D22) -> 1 | E23: =SUM(E19:E22) -> 1 | F23: =SUM(F19:F22) -> 1 | G23: =SUM(G19:G22) -> 1 | H23: =SUM(H19:H22) -> 1 | I23: =SUM(I19:I22) -> 1 | J23: =SUM(J19:J22) -> 1 | K23: =SUM(K19:K22) -> 1 | ... R23: =SUM(R19:R22) -> 1
B24: Memo (inside Cyclicals)
B25: Cyclicals ex-WEG & Embraer | C25: =C14/$C$11 -> 0.077082817 | D25: =D14/D$12 -> 0.078905608 | E25: =E14/E$12 -> 0.082932614 | F25: =F14/F$12 -> 0.085419773 | G25: =G14/G$12 -> 0.077488637 | H25: =H14/H$12 -> 0.082702201 | I25: =I14/I$12 -> 0.086393907 | J25: =J14/J$12 -> 0.072623213 | K25: =K14/K$12 -> 0.077527314 | L25: =L14/L$12 -> 0.081423934 | M25: =M14/M$11 -> 0.058743957 | N25: =N14/N$11 -> 0.068264577 | O25: =O14/O$11 -> 0.075544706 | P25: =P14/P$12 -> 0.12667716 | Q25: =Q14/Q$12 -> 0.13088074 | R25: =R14/R$12 -> 0.12867059
B26: WEG & Embraer | C26: =C15/$C$11 -> 0.048958696 | D26: =D15/D$12 -> 0.026677781 | E26: =E15/E$12 -> 0.029252309 | F26: =F15/F$12 -> 0.031574113 | G26: =G15/G$12 -> 0.016026668 | H26: =H15/H$12 -> 0.017836651 | I26: =I15/I$12 -> 0.019605095 | J26: =J15/J$12 -> 0.012858119 | K26: =K15/K$12 -> 0.014338516 | L26: =L15/L$12 -> 0.016020882 | M26: =M15/M$11 -> 0.017915966 | N26: =N15/N$11 -> 0.020654912 | O26: =O15/O$11 -> 0.022997443 | P26: =P15/P$12 -> 0.010230947 | Q26: =Q15/Q$12 -> 0.010439854 | R26: =R15/R$12 -> 0.010640568
B27: Non-financial boxes: members' line / IBOV Index line. Financials: 1 - the other three (net income: members' share of the members' total).
B29: 3. Financials: reported by the members vs. taken by Financials from the index line (index pts)
B30: Group | C30: Index points | D30: Sales 2026 | E30: Sales 2027 | F30: Sales 2028 | G30: EBIT 2026 | H30: EBIT 2027 | I30: EBIT 2028 | J30: EBITDA 2026 | K30: EBITDA 2027 | L30: EBITDA 2028 | M30: Net income 2026 | N30: Net income 2027 | O30: Net income 2028 | P30: Capex 2026 | Q30: Capex 2027 | R30: Capex 2028
B31: Financials, members' reported consensus | D31: =D7 -> 23202.292 | E31: =E7 -> 24843.532 | F31: =F7 -> 26614.283 | G31: =G7 -> 5850.9178 | H31: =H7 -> 6776.2881 | I31: =I7 -> 7553.6721 | J31: =J7 -> 1489.4529 | K31: =K7 -> 4304.3334 | L31: =L7 -> 4975.2097 | M31: n/a | N31: n/a | O31: n/a | P31: =P7 -> -38.325056 | Q31: =Q7 -> -40.957339 | R31: =R7 -> -42.548672
B32: Financials share x IBOV Index line | D32: =D19*D12 -> 25680.659 | E32: =E19*E12 -> 27143.772 | F32: =F19*F12 -> 29462.634 | G32: =G19*G12 -> 6876.6223 | H32: =H19*H12 -> 7762.8608 | I32: =I19*I12 -> 8509.2906 | J32: =J19*J12 -> 12779.293 | K32: =K19*K12 -> 13162.784 | L32: =L19*L12 -> 13849.687 | M32: n/a | N32: n/a | O32: n/a | P32: =P19*P12 -> -5324.7 | Q32: =Q19*Q12 -> -5323.9148 | R32: =R19*R12 -> -5540.6142
B33: Imputed by the index (banks' EBITDA and capex) + index gap | D33: =D32-D31 -> 2478.367 | E33: =E32-E31 -> 2300.2404 | F33: =F32-F31 -> 2848.3516 | G33: =G32-G31 -> 1025.7045 | H33: =H32-H31 -> 986.57268 | I33: =I32-I31 -> 955.61842 | J33: =J32-J31 -> 11289.84 | K33: =K32-K31 -> 8858.4503 | L33: =L32-L31 -> 8874.4772 | M33: n/a | N33: n/a | O33: n/a | P33: =P32-P31 -> -5286.375 | Q33: =Q32-Q31 -> -5282.9575 | R33: =R32-R31 -> -5498.0655
B35: 4. Financials ROE for the FCFE (FY28 consensus)
B36: Net income FY28 of the Financials with an ROE (index pts) | C36: =SUMIFS(Members!$AQ$6:$AQ$81,Members!$C$6:$C$81,"Financials") -> 6265.5495
B37: Book value FY28 = net income / ROE (index pts) | C37: =SUMIFS(Members!$AR$6:$AR$81,Members!$C$6:$C$81,"Financials") -> 31531.729
B38: ROE FY28, consensus = net income / book value | C38: =C36/C37 -> 0.19870618
B39: ROE used (Assumptions override if typed) | C39: =IF(ISNUMBER(FinROEovr),FinROEovr,C38) -> 0.19870618

Sheet Members
B1: Ibovespa - Members: consensus lines by stock
B2: Bloomberg BEST consensus, company totals in BRL mn (Oct-7-2026), and market cap; in index points = points x line / market cap.
B3: Legend: | C3: input | D3: assumption | E3: formula
A4: Identification | E4: Weight, index points, market cap | L4: Consensus, BRL mn (Bloomberg BEST, EQY_FUND_CRNCY = BRL) | AA4: In index points = points x line / market cap | AP4: Financials ROE
A5: Ticker | B5: Company | C5: Box | D5: Sub-box | E5: Ibovespa weight Sep-30 | F5: Price Sep-30 (R$) | G5: Price Oct-5 (R$) | H5: Price-drifted weight (unscaled) | I5: Weight Oct-5 | J5: Index points | K5: Market cap (BRL mn) | L5: Sales FY26 (BRL mn) | M5: Sales FY27 (BRL mn) | N5: Sales FY28 (BRL mn) | O5: EBIT FY26 (BRL mn) | P5: EBIT FY27 (BRL mn) | Q5: EBIT FY28 (BRL mn) | R5: EBITDA FY26 (BRL mn) | S5: EBITDA FY27 (BRL mn) | T5: EBITDA FY28 (BRL mn) | U5: Net income FY26 (BRL mn) | V5: Net income FY27 (BRL mn) | W5: Net income FY28 (BRL mn) | X5: Capex FY26 (BRL mn) | Y5: Capex FY27 (BRL mn) | Z5: Capex FY28 (BRL mn) | AA5: Sales FY26 (index pts) | AB5: Sales FY27 (index pts) | AC5: Sales FY28 (index pts) | AD5: EBIT FY26 (index pts) | AE5: EBIT FY27 (index pts) | AF5: EBIT FY28 (index pts) | AG5: EBITDA FY26 (index pts) | AH5: EBITDA FY27 (index pts) | AI5: EBITDA FY28 (index pts) | AJ5: Net income FY26 (index pts) | AK5: Net income FY27 (index pts) | AL5: Net income FY28 (index pts) | AM5: Capex FY26 (index pts) | AN5: Capex FY27 (index pts) | AO5: Capex FY28 (index pts) | AP5: ROE FY28 | AQ5: Net income FY28 with ROE (pts) | AR5: Book value FY28 (pts) | AS5: Missing lines
A6: ITUB4 | B6: Itaú Unibanco | C6: Financials | D6: Financials | E6: 0.0905 | F6: 44.28 | G6: 49.82 | H6: =E6*G6/F6 -> 0.10182272 | I6: =H6/SUM($H$6:$H$81) -> 0.091585133 | J6: =I6*Assumptions!$D$7 -> 19089.265 | K6: 564225.23 | L6: 192256.7 | M6: 206472.4 | N6: 221026.11 | O6: 55944 | P6: 69756 | Q6: 75870 | S6: 78354 | T6: 87509 | U6: 50677.333 | V6: 55448.917 | W6: 60687.636 | AA6: =IF(ISNUMBER(L6),$J6*L6/$K6,0) -> 6504.564 | AB6: =IF(ISNUMBER(M6),$J6*M6/$K6,0) -> 6985.5196 | AC6: =IF(ISNUMBER(N6),$J6*N6/$K6,0) -> 7477.911 | AD6: =IF(ISNUMBER(O6),$J6*O6/$K6,0) -> 1892.7368 | AE6: =IF(ISNUMBER(P6),$J6*P6/$K6,0) -> 2360.0341 | AF6: =IF(ISNUMBER(Q6),$J6*Q6/$K6,0) -> 2566.8872 | AG6: =IF(ISNUMBER(R6),$J6*R6/$K6,0) -> 0 | AH6: =IF(ISNUMBER(S6),$J6*S6/$K6,0) -> 2650.9277 | ... AO6: =IF(ISNUMBER(Z6),$J6*Z6/$K6,0) -> 0 | AP6: 0.24343 | AQ6: =IF(AND(ISNUMBER(AP6),N(AP6)>0),AL6,0) -> 2053.2268 | AR6: =IF(AQ6<>0,AQ6/AP6,0) -> 8434.5677 | AS6: ebitda26, capex26, capex27, capex28
A7: BBDC4 | B7: Bradesco | C7: Financials | D7: Financials | E7: 0.03616 | F7: 18.51 | G7: 21.85 | H7: =E7*G7/F7 -> 0.042684819 | I7: =H7/SUM($H$6:$H$81) -> 0.038393149 | J7: =I7*Assumptions!$D$7 -> 8002.3578 | K7: 226447.76 | L7: 150490.36 | M7: 162160.18 | N7: 174205.3 | O7: 35753.2 | P7: 41429.2 | Q7: 47109.6 | U7: 27739.923 | V7: 30648.077 | W7: 33619.083 | AA7: =IF(ISNUMBER(L7),$J7*L7/$K7,0) -> 5318.1261 | AB7: =IF(ISNUMBER(M7),$J7*M7/$K7,0) -> 5730.5218 | AC7: =IF(ISNUMBER(N7),$J7*N7/$K7,0) -> 6156.18 | AD7: =IF(ISNUMBER(O7),$J7*O7/$K7,0) -> 1263.4698 | AE7: =IF(ISNUMBER(P7),$J7*P7/$K7,0) -> 1464.052 | AF7: =IF(ISNUMBER(Q7),$J7*Q7/$K7,0) -> 1664.7896 | AG7: =IF(ISNUMBER(R7),$J7*R7/$K7,0) -> 0 | AH7: =IF(ISNUMBER(S7),$J7*S7/$K7,0) -> 0 | ... AO7: =IF(ISNUMBER(Z7),$J7*Z7/$K7,0) -> 0 | AP7: 0.1615 | AQ7: =IF(AND(ISNUMBER(AP7),N(AP7)>0),AL7,0) -> 1188.053 | AR7: =IF(AQ7<>0,AQ7/AP7,0) -> 7356.3652 | AS7: ebitda26, ebitda27, ebitda28, capex26, capex27, capex28
A8: B3SA3 | B8: B3 | C8: Financials | D8: Financials | E8: 0.03502 | F8: 18.34 | G8: 23.29 | H8: =E8*G8/F8 -> 0.044471963 | I8: =H8/SUM($H$6:$H$81) -> 0.040000608 | J8: =I8*Assumptions!$D$7 -> 8337.4035 | K8: 112688.35 | L8: 11412.692 | M8: 12420.308 | N8: 13564.583 | O8: 7483.4545 | P8: 8323.0909 | Q8: 9206.8182 | R8: 7884.7778 | S8: 8662.1111 | T8: 9591.25 | U8: 5982 | V8: 6425.4 | W8: 6561.222 | X8: -314.5 | Y8: -319.5 | Z8: -336 | AA8: =IF(ISNUMBER(L8),$J8*L8/$K8,0) -> 844.38386 | AB8: =IF(ISNUMBER(M8),$J8*M8/$K8,0) -> 918.93369 | AC8: =IF(ISNUMBER(N8),$J8*N8/$K8,0) -> 1003.5945 | AD8: =IF(ISNUMBER(O8),$J8*O8/$K8,0) -> 553.67376 | AE8: =IF(ISNUMBER(P8),$J8*P8/$K8,0) -> 615.79542 | AF8: =IF(ISNUMBER(Q8),$J8*Q8/$K8,0) -> 681.17921 | AG8: =IF(ISNUMBER(R8),$J8*R8/$K8,0) -> 583.36622 | AH8: =IF(ISNUMBER(S8),$J8*S8/$K8,0) -> 640.8783 | ... AO8: =IF(ISNUMBER(Z8),$J8*Z8/$K8,0) -> -24.859426 | AP8: 0.37809 | AQ8: =IF(AND(ISNUMBER(AP8),N(AP8)>0),AL8,0) -> 485.44111 | AR8: =IF(AQ8<>0,AQ8/AP8,0) -> 1283.93
A9: ITSA4 | B9: Itausa | C9: Financials | D9: Financials | E9: 0.03344 | F9: 14.6 | G9: 16.35 | H9: =E9*G9/F9 -> 0.037448219 | I9: =H9/SUM($H$6:$H$81) -> 0.033683054 | J9: =I9*Assumptions!$D$7 -> 7020.6236 | K9: 179573.13 | L9: 19414 | M9: 20412 | N9: 23060 | O9: 19414 | P9: 20412 | Q9: 23060 | U9: 19414 | V9: 20412 | W9: 23060 | AA9: =IF(ISNUMBER(L9),$J9*L9/$K9,0) -> 759.01324 | AB9: =IF(ISNUMBER(M9),$J9*M9/$K9,0) -> 798.03122 | AC9: =IF(ISNUMBER(N9),$J9*N9/$K9,0) -> 901.55791 | AD9: =IF(ISNUMBER(O9),$J9*O9/$K9,0) -> 759.01324 | AE9: =IF(ISNUMBER(P9),$J9*P9/$K9,0) -> 798.03122 | AF9: =IF(ISNUMBER(Q9),$J9*Q9/$K9,0) -> 901.55791 | AG9: =IF(ISNUMBER(R9),$J9*R9/$K9,0) -> 0 | AH9: =IF(ISNUMBER(S9),$J9*S9/$K9,0) -> 0 | ... AO9: =IF(ISNUMBER(Z9),$J9*Z9/$K9,0) -> 0 | AQ9: =IF(AND(ISNUMBER(AP9),N(AP9)>0),AL9,0) -> 0 | AR9: =IF(AQ9<>0,AQ9/AP9,0) -> 0 | AS9: ebitda26, ebitda27, ebitda28, capex26, capex27, capex28
A10: BPAC11 | B10: BTG Pactual | C10: Financials | D10: Financials | E10: 0.02933 | F10: 64.1 | G10: 80.73 | H10: =E10*G10/F10 -> 0.036939328 | I10: =H10/SUM($H$6:$H$81) -> 0.033225328 | J10: =I10*Assumptions!$D$7 -> 6925.2189 | K10: 305584.14 | L10: 42383 | M10: 48877.2 | N10: 55529.889 | O10: 25071.667 | P10: 28280.333 | Q10: 32011 | R10: 25522 | S10: 30252.5 | T10: 34882 | U10: 20474.182 | V10: 23359.364 | W10: 26673.6 | AA10: =IF(ISNUMBER(L10),$J10*L10/$K10,0) -> 960.49339 | AB10: =IF(ISNUMBER(M10),$J10*M10/$K10,0) -> 1107.6665 | AC10: =IF(ISNUMBER(N10),$J10*N10/$K10,0) -> 1258.4312 | AD10: =IF(ISNUMBER(O10),$J10*O10/$K10,0) -> 568.17994 | AE10: =IF(ISNUMBER(P10),$J10*P10/$K10,0) -> 640.89549 | AF10: =IF(ISNUMBER(Q10),$J10*Q10/$K10,0) -> 725.44072 | AG10: =IF(ISNUMBER(R10),$J10*R10/$K10,0) -> 578.38549 | AH10: =IF(ISNUMBER(S10),$J10*S10/$K10,0) -> 685.58918 | ... AO10: =IF(ISNUMBER(Z10),$J10*Z10/$K10,0) -> 0 | AP10: 0.2486 | AQ10: =IF(AND(ISNUMBER(AP10),N(AP10)>0),AL10,0) -> 604.48332 | AR10: =IF(AQ10<>0,AQ10/AP10,0) -> 2431.55 | AS10: capex26, capex27, capex28
A11: BBAS3 | B11: Banco do Brasil | C11: Financials | D11: Financials | E11: 0.02512 | F11: 23.07 | G11: 26.44 | H11: =E11*G11/F11 -> 0.028789458 | I11: =H11/SUM($H$6:$H$81) -> 0.025894873 | J11: =I11*Assumptions!$D$7 -> 5397.318 | K11: 138571.57 | L11: 149736.62 | M11: 156547.5 | N11: 163578.88 | U11: 17093.5 | V11: 24478.75 | W11: 29169 | AA11: =IF(ISNUMBER(L11),$J11*L11/$K11,0) -> 5832.1935 | AB11: =IF(ISNUMBER(M11),$J11*M11/$K11,0) -> 6097.4749 | AC11: =IF(ISNUMBER(N11),$J11*N11/$K11,0) -> 6371.3447 | AD11: =IF(ISNUMBER(O11),$J11*O11/$K11,0) -> 0 | AE11: =IF(ISNUMBER(P11),$J11*P11/$K11,0) -> 0 | AF11: =IF(ISNUMBER(Q11),$J11*Q11/$K11,0) -> 0 | AG11: =IF(ISNUMBER(R11),$J11*R11/$K11,0) -> 0 | AH11: =IF(ISNUMBER(S11),$J11*S11/$K11,0) -> 0 | ... AO11: =IF(ISNUMBER(Z11),$J11*Z11/$K11,0) -> 0 | AP11: 0.13251 | AQ11: =IF(AND(ISNUMBER(AP11),N(AP11)>0),AL11,0) -> 1136.1232 | AR11: =IF(AQ11<>0,AQ11/AP11,0) -> 8573.8675 | AS11: ebit26, ebit27, ebit28, ebitda26, ebitda27, ebitda28, capex26, capex27, capex28
A12: BBSE3 | B12: BBSeguridade | C12: Financials | D12: Financials | E12: 0.00925 | F12: 39.18 | G12: 41.2 | H12: =E12*G12/F12 -> 0.0097269015 | I12: =H12/SUM($H$6:$H$81) -> 0.0087489273 | J12: =I12*Assumptions!$D$7 -> 1823.5557 | K12: 78199.592 | L12: 9682.5714 | M12: 9166.875 | N12: 9647.1429 | O12: 9490 | P12: 9306.25 | Q12: 9782.5 | R12: 10880.5 | S12: 10610.5 | T12: 10965 | U12: 8662.5 | V12: 8582.6 | W12: 8977.125 | AA12: =IF(ISNUMBER(L12),$J12*L12/$K12,0) -> 225.79029 | AB12: =IF(ISNUMBER(M12),$J12*M12/$K12,0) -> 213.76464 | AC12: =IF(ISNUMBER(N12),$J12*N12/$K12,0) -> 224.96412 | AD12: =IF(ISNUMBER(O12),$J12*O12/$K12,0) -> 221.29967 | AE12: =IF(ISNUMBER(P12),$J12*P12/$K12,0) -> 217.01476 | AF12: =IF(ISNUMBER(Q12),$J12*Q12/$K12,0) -> 228.12055 | AG12: =IF(ISNUMBER(R12),$J12*R12/$K12,0) -> 253.72508 | AH12: =IF(ISNUMBER(S12),$J12*S12/$K12,0) -> 247.42889 | ... AO12: =IF(ISNUMBER(Z12),$J12*Z12/$K12,0) -> 0 | AP12: 0.81663 | AQ12: =IF(AND(ISNUMBER(AP12),N(AP12)>0),AL12,0) -> 209.33981 | AR12: =IF(AQ12<>0,AQ12/AP12,0) -> 256.34597 | AS12: capex26, capex27, capex28
A13: BBDC3 | B13: Bradesco | C13: Financials | D13: Financials | E13: 0.0091 | F13: 16.22 | G13: 19.37 | H13: =E13*G13/F13 -> 0.010867263 | I13: =H13/SUM($H$6:$H$81) -> 0.0097746328 | J13: =I13*Assumptions!$D$7 -> 2037.3455 | K13: 226447.76 | L13: 150490.36 | M13: 162160.18 | N13: 174205.3 | O13: 35753.2 | P13: 41429.2 | Q13: 47109.6 | U13: 27739.923 | V13: 30648.077 | W13: 33619.083 | AA13: =IF(ISNUMBER(L13),$J13*L13/$K13,0) -> 1353.9585 | AB13: =IF(ISNUMBER(M13),$J13*M13/$K13,0) -> 1458.9516 | AC13: =IF(ISNUMBER(N13),$J13*N13/$K13,0) -> 1567.3213 | AD13: =IF(ISNUMBER(O13),$J13*O13/$K13,0) -> 321.67076 | AE13: =IF(ISNUMBER(P13),$J13*P13/$K13,0) -> 372.7376 | AF13: =IF(ISNUMBER(Q13),$J13*Q13/$K13,0) -> 423.84404 | AG13: =IF(ISNUMBER(R13),$J13*R13/$K13,0) -> 0 | AH13: =IF(ISNUMBER(S13),$J13*S13/$K13,0) -> 0 | ... AO13: =IF(ISNUMBER(Z13),$J13*Z13/$K13,0) -> 0 | AP13: 0.1615 | AQ13: =IF(AND(ISNUMBER(AP13),N(AP13)>0),AL13,0) -> 302.47015 | AR13: =IF(AQ13<>0,AQ13/AP13,0) -> 1872.8802 | AS13: ebitda26, ebitda27, ebitda28, capex26, capex27, capex28
A14: CXSE3 | B14: Caixa Seguridade | C14: Financials | D14: Financials | E14: 0.00457 | F14: 19.88 | G14: 20.77 | H14: =E14*G14/F14 -> 0.0047745926 | I14: =H14/SUM($H$6:$H$81) -> 0.0042945395 | J14: =I14*Assumptions!$D$7 -> 895.11912 | K14: 63090 | L14: 6236.6667 | M14: 6932.5 | N14: 7628.2 | O14: 5141 | P14: 5629.4 | Q14: 6133 | R14: 5214 | S14: 5604 | T14: 6111 | U14: 4676.444 | V14: 5099.889 | W14: 5562.143 | AA14: =IF(ISNUMBER(L14),$J14*L14/$K14,0) -> 88.485649 | AB14: =IF(ISNUMBER(M14),$J14*M14/$K14,0) -> 98.358113 | AC14: =IF(ISNUMBER(N14),$J14*N14/$K14,0) -> 108.22868 | AD14: =IF(ISNUMBER(O14),$J14*O14/$K14,0) -> 72.940362 | AE14: =IF(ISNUMBER(P14),$J14*P14/$K14,0) -> 79.869767 | AF14: =IF(ISNUMBER(Q14),$J14*Q14/$K14,0) -> 87.014829 | AG14: =IF(ISNUMBER(R14),$J14*R14/$K14,0) -> 73.976083 | AH14: =IF(ISNUMBER(S14),$J14*S14/$K14,0) -> 79.509392 | ... AO14: =IF(ISNUMBER(Z14),$J14*Z14/$K14,0) -> 0 | AP14: 0.4234 | AQ14: =IF(AND(ISNUMBER(AP14),N(AP14)>0),AL14,0) -> 78.915526 | AR14: =IF(AQ14<>0,AQ14/AP14,0) -> 186.38528 | AS14: capex26, capex27, capex28
A15: SANB11 | B15: Santander | C15: Financials | D15: Financials | E15: 0.00392 | F15: 28.75 | G15: 28.76 | H15: =E15*G15/F15 -> 0.0039213635 | I15: =H15/SUM($H$6:$H$81) -> 0.0035270969 | J15: =I15*Assumptions!$D$7 -> 735.15958 | K15: 109308.45 | L15: 83362.111 | M15: 91025.333 | N15: 97332.556 | O15: 15347 | P15: 17953.5 | Q15: 22791.5 | T15: 25577 | U15: 13604.778 | V15: 15814.1 | W15: 18082.9 | AA15: =IF(ISNUMBER(L15),$J15*L15/$K15,0) -> 560.65616 | AB15: =IF(ISNUMBER(M15),$J15*M15/$K15,0) -> 612.19555 | AC15: =IF(ISNUMBER(N15),$J15*N15/$K15,0) -> 654.6151 | AD15: =IF(ISNUMBER(O15),$J15*O15/$K15,0) -> 103.21704 | AE15: =IF(ISNUMBER(P15),$J15*P15/$K15,0) -> 120.74719 | AF15: =IF(ISNUMBER(Q15),$J15*Q15/$K15,0) -> 153.2854 | AG15: =IF(ISNUMBER(R15),$J15*R15/$K15,0) -> 0 | AH15: =IF(ISNUMBER(S15),$J15*S15/$K15,0) -> 0 | ... AO15: =IF(ISNUMBER(Z15),$J15*Z15/$K15,0) -> 0 | AP15: 0.15957 | AQ15: =IF(AND(ISNUMBER(AP15),N(AP15)>0),AL15,0) -> 121.61747 | AR15: =IF(AQ15<>0,AQ15/AP15,0) -> 762.1575 | AS15: ebitda26, ebitda27, capex26, capex27, capex28
A16: PSSA3 | B16: Porto Seguro | C16: Financials | D16: Financials | E16: 0.00324 | F16: 47.29 | G16: 51.69 | H16: =E16*G16/F16 -> 0.0035414591 | I16: =H16/SUM($H$6:$H$81) -> 0.0031853893 | J16: =I16*Assumptions!$D$7 -> 663.93681 | K16: 34042.756 | L16: 38692.833 | M16: 42153.167 | N16: 45640.833 | O16: 4856.5 | P16: 5492 | Q16: 6232.5 | U16: 3715.9 | V16: 3997.4 | W16: 4403.375 | X16: -772 | Y16: -888 | Z16: -907 | AA16: =IF(ISNUMBER(L16),$J16*L16/$K16,0) -> 754.62739 | AB16: =IF(ISNUMBER(M16),$J16*M16/$K16,0) -> 822.11437 | AC16: =IF(ISNUMBER(N16),$J16*N16/$K16,0) -> 890.13443 | AD16: =IF(ISNUMBER(O16),$J16*O16/$K16,0) -> 94.716453 | AE16: =IF(ISNUMBER(P16),$J16*P16/$K16,0) -> 107.11063 | AF16: =IF(ISNUMBER(Q16),$J16*Q16/$K16,0) -> 121.55262 | AG16: =IF(ISNUMBER(R16),$J16*R16/$K16,0) -> 0 | AH16: =IF(ISNUMBER(S16),$J16*S16/$K16,0) -> 0 | ... AO16: =IF(ISNUMBER(Z16),$J16*Z16/$K16,0) -> -17.689246 | AP16: 0.22982 | AQ16: =IF(AND(ISNUMBER(AP16),N(AP16)>0),AL16,0) -> 85.879144 | AR16: =IF(AQ16<>0,AQ16/AP16,0) -> 373.68003 | AS16: ebitda26, ebitda27, ebitda28
A17: AXIA3 | B17: Axia Energia | C17: Defensives | D17: Defensives | E17: 0.0483 | F17: 55.35 | G17: 61.49 | H17: =E17*G17/F17 -> 0.05365794 | I17: =H17/SUM($H$6:$H$81) -> 0.048262997 | J17: =I17*Assumptions!$D$7 -> 10059.549 | K17: 169405.1 | L17: 44513.545 | M17: 51510.727 | N17: 50594.3 | O17: 21767.2 | P17: 29362 | Q17: 28773.8 | R17: 28674.444 | S17: 35952.667 | T17: 35675 | U17: 9732.909 | V17: 15666.636 | W17: 15374.8 | X17: -10141.25 | Y17: -11373.5 | Z17: -10673 | AA17: =IF(ISNUMBER(L17),$J17*L17/$K17,0) -> 2643.2864 | AB17: =IF(ISNUMBER(M17),$J17*M17/$K17,0) -> 3058.7904 | AC17: =IF(ISNUMBER(N17),$J17*N17/$K17,0) -> 3004.3715 | AD17: =IF(ISNUMBER(O17),$J17*O17/$K17,0) -> 1292.5716 | AE17: =IF(ISNUMBER(P17),$J17*P17/$K17,0) -> 1743.5631 | AF17: =IF(ISNUMBER(Q17),$J17*Q17/$K17,0) -> 1708.6348 | AG17: =IF(ISNUMBER(R17),$J17*R17/$K17,0) -> 1702.7349 | AH17: =IF(ISNUMBER(S17),$J17*S17/$K17,0) -> 2134.9276 | ... AO17: =IF(ISNUMBER(Z17),$J17*Z17/$K17,0) -> -633.78003 | AP17: 0.12197 | AQ17: =IF(AND(ISNUMBER(AP17),N(AP17)>0),AL17,0) -> 912.98052 | AR17: =IF(AQ17<>0,AQ17/AP17,0) -> 7485.2876
A18: SBSP3 | B18: Sabesp | C18: Defensives | D18: Defensives | E18: 0.03702 | F18: 27.43 | G18: 31.5 | H18: =E18*G18/F18 -> 0.042512942 | I18: =H18/SUM($H$6:$H$81) -> 0.038238553 | J18: =I18*Assumptions!$D$7 -> 7970.135 | K18: 113143.16 | L18: 31193.917 | M18: 35866 | N18: 40763.222 | O18: 12232.7 | P18: 16728.1 | Q18: 19678.111 | R18: 15095.75 | S18: 20130.364 | T18: 23678.111 | U18: 5579.182 | V18: 7501.7 | W18: 9525.222 | X18: -18050 | Y18: -16230 | Z18: -17124 | AA18: =IF(ISNUMBER(L18),$J18*L18/$K18,0) -> 2197.3907 | AB18: =IF(ISNUMBER(M18),$J18*M18/$K18,0) -> 2526.5059 | AC18: =IF(ISNUMBER(N18),$J18*N18/$K18,0) -> 2871.4806 | AD18: =IF(ISNUMBER(O18),$J18*O18/$K18,0) -> 861.70715 | AE18: =IF(ISNUMBER(P18),$J18*P18/$K18,0) -> 1178.3763 | AF18: =IF(ISNUMBER(Q18),$J18*Q18/$K18,0) -> 1386.1837 | AG18: =IF(ISNUMBER(R18),$J18*R18/$K18,0) -> 1063.3888 | AH18: =IF(ISNUMBER(S18),$J18*S18/$K18,0) -> 1418.0417 | ... AO18: =IF(ISNUMBER(Z18),$J18*Z18/$K18,0) -> -1206.2646 | AP18: 0.18357 | AQ18: =IF(AND(ISNUMBER(AP18),N(AP18)>0),AL18,0) -> 670.98449 | AR18: =IF(AQ18<>0,AQ18/AP18,0) -> 3655.1969
A19: ABEV3 | B19: Ambev | C19: Defensives | D19: Defensives | E19: 0.02379 | F19: 15.36 | G19: 16.52 | H19: =E19*G19/F19 -> 0.025586641 | I19: =H19/SUM($H$6:$H$81) -> 0.023014077 | J19: =I19*Assumptions!$D$7 -> 4796.8682 | K19: 247290.1 | L19: 90144.765 | M19: 94600.438 | N19: 100036.93 | O19: 23899.714 | P19: 24745.4 | Q19: 26343.933 | R19: 30427.438 | S19: 31638 | T19: 33437.429 | U19: 16365.5 | V19: 17242.167 | W19: 18564.5 | X19: -4425.1 | Y19: -5124.1 | Z19: -5499.4 | AA19: =IF(ISNUMBER(L19),$J19*L19/$K19,0) -> 1748.6044 | AB19: =IF(ISNUMBER(M19),$J19*M19/$K19,0) -> 1835.0344 | AC19: =IF(ISNUMBER(N19),$J19*N19/$K19,0) -> 1940.4901 | AD19: =IF(ISNUMBER(O19),$J19*O19/$K19,0) -> 463.60037 | AE19: =IF(ISNUMBER(P19),$J19*P19/$K19,0) -> 480.00475 | AF19: =IF(ISNUMBER(Q19),$J19*Q19/$K19,0) -> 511.01268 | AG19: =IF(ISNUMBER(R19),$J19*R19/$K19,0) -> 590.22342 | AH19: =IF(ISNUMBER(S19),$J19*S19/$K19,0) -> 613.7056 | ... AO19: =IF(ISNUMBER(Z19),$J19*Z19/$K19,0) -> -106.67591 | AP19: 0.20658 | AQ19: =IF(AND(ISNUMBER(AP19),N(AP19)>0),AL19,0) -> 360.10928 | AR19: =IF(AQ19<>0,AQ19/AP19,0) -> 1743.1953
A20: ENEV3 | B20: Eneva | C20: Defensives | D20: Defensives | E20: 0.02046 | F20: 27.87 | G20: 30.29 | H20: =E20*G20/F20 -> 0.022236577 | I20: =H20/SUM($H$6:$H$81) -> 0.020000839 | J20: =I20*Assumptions!$D$7 -> 4168.8134 | K20: 59109.494 | L20: 14114.625 | M20: 14654.778 | N20: 16601.111 | O20: 3244.6 | P20: 4234.6 | Q20: 5458.7778 | R20: 5643 | S20: 6975 | T20: 8367.5556 | U20: 763.889 | V20: 1493 | W20: 2556.556 | X20: -5965.6667 | Y20: -3718 | Z20: -5316.25 | AA20: =IF(ISNUMBER(L20),$J20*L20/$K20,0) -> 995.46169 | AB20: =IF(ISNUMBER(M20),$J20*M20/$K20,0) -> 1033.557 | AC20: =IF(ISNUMBER(N20),$J20*N20/$K20,0) -> 1170.826 | AD20: =IF(ISNUMBER(O20),$J20*O20/$K20,0) -> 228.8318 | AE20: =IF(ISNUMBER(P20),$J20*P20/$K20,0) -> 298.65349 | AF20: =IF(ISNUMBER(Q20),$J20*Q20/$K20,0) -> 384.99104 | AG20: =IF(ISNUMBER(R20),$J20*R20/$K20,0) -> 397.98368 | AH20: =IF(ISNUMBER(S20),$J20*S20/$K20,0) -> 491.9256 | ... AO20: =IF(ISNUMBER(Z20),$J20*Z20/$K20,0) -> -374.93899 | AP20: 0.08007 | AQ20: =IF(AND(ISNUMBER(AP20),N(AP20)>0),AL20,0) -> 180.30614 | AR20: =IF(AQ20<>0,AQ20/AP20,0) -> 2251.8564
A21: EQTL3 | B21: Equatorial Energia | C21: Defensives | D21: Defensives | E21: 0.0194 | F21: 40.65 | G21: 47.91 | H21: =E21*G21/F21 -> 0.022864797 | I21: =H21/SUM($H$6:$H$81) -> 0.020565896 | J21: =I21*Assumptions!$D$7 -> 4286.5892 | K21: 61712.489 | L21: 43275.636 | M21: 44801.2 | N21: 47535.111 | O21: 8571 | P21: 9456.1818 | Q21: 10666.889 | R21: 11958.667 | S21: 12902.182 | T21: 14327.778 | U21: 2174.083 | V21: 3031.636 | W21: 4594.222 | X21: -11704 | Y21: -9861.6667 | Z21: -9002.75 | AA21: =IF(ISNUMBER(L21),$J21*L21/$K21,0) -> 3005.9536 | AB21: =IF(ISNUMBER(M21),$J21*M21/$K21,0) -> 3111.9202 | AC21: =IF(ISNUMBER(N21),$J21*N21/$K21,0) -> 3301.8195 | AD21: =IF(ISNUMBER(O21),$J21*O21/$K21,0) -> 595.34718 | AE21: =IF(ISNUMBER(P21),$J21*P21/$K21,0) -> 656.83248 | AF21: =IF(ISNUMBER(Q21),$J21*Q21/$K21,0) -> 740.92898 | AG21: =IF(ISNUMBER(R21),$J21*R21/$K21,0) -> 830.65669 | AH21: =IF(ISNUMBER(S21),$J21*S21/$K21,0) -> 896.19386 | ... AO21: =IF(ISNUMBER(Z21),$J21*Z21/$K21,0) -> -625.33682 | AP21: 0.1533 | AQ21: =IF(AND(ISNUMBER(AP21),N(AP21)>0),AL21,0) -> 319.11762 | AR21: =IF(AQ21<>0,AQ21/AP21,0) -> 2081.6544
A22: CPLE3 | B22: Copel | C22: Defensives | D22: Defensives | E22: 0.0182 | F22: 16 | G22: 17.39 | H22: =E22*G22/F22 -> 0.019781125 | I22: =H22/SUM($H$6:$H$81) -> 0.017792267 | J22: =I22*Assumptions!$D$7 -> 3708.4763 | K22: 52079.873 | L22: 25592.778 | M22: 26138.556 | N22: 28340.429 | O22: 5774.1667 | P22: 6455.8333 | Q22: 7047.6667 | R22: 7300.125 | S22: 8171.75 | T22: 8811.75 | U22: 2881.5 | V22: 3125.375 | W22: 3391.429 | X22: -3424.8 | Y22: -4747.2 | Z22: -4984.6 | AA22: =IF(ISNUMBER(L22),$J22*L22/$K22,0) -> 1822.3971 | AB22: =IF(ISNUMBER(M22),$J22*M22/$K22,0) -> 1861.2606 | AC22: =IF(ISNUMBER(N22),$J22*N22/$K22,0) -> 2018.0504 | AD22: =IF(ISNUMBER(O22),$J22*O22/$K22,0) -> 411.16383 | AE22: =IF(ISNUMBER(P22),$J22*P22/$K22,0) -> 459.7036 | AF22: =IF(ISNUMBER(Q22),$J22*Q22/$K22,0) -> 501.84655 | AG22: =IF(ISNUMBER(R22),$J22*R22/$K22,0) -> 519.82347 | AH22: =IF(ISNUMBER(S22),$J22*S22/$K22,0) -> 581.88969 | ... AO22: =IF(ISNUMBER(Z22),$J22*Z22/$K22,0) -> -354.94078 | AP22: 0.13287 | AQ22: =IF(AND(ISNUMBER(AP22),N(AP22)>0),AL22,0) -> 241.4951 | AR22: =IF(AQ22<>0,AQ22/AP22,0) -> 1817.5292
A23: RDOR3 | B23: Rede D'Or | C23: Defensives | D23: Defensives | E23: 0.01511 | F23: 38.29 | G23: 43.87 | H23: =E23*G23/F23 -> 0.01731198 | I23: =H23/SUM($H$6:$H$81) -> 0.015571377 | J23: =I23*Assumptions!$D$7 -> 3245.572 | K23: 101621.7 | L23: 62171.083 | M23: 69044.538 | N23: 75743.273 | O23: 9701.9 | P23: 10997.3 | Q23: 12588.7 | R23: 12344.923 | S23: 13828.462 | T23: 15456.182 | U23: 4997.833 | V23: 6056.667 | W23: 7141.545 | X23: -2663 | Y23: -2544 | Z23: -2175.6667 | AA23: =IF(ISNUMBER(L23),$J23*L23/$K23,0) -> 1985.6067 | AB23: =IF(ISNUMBER(M23),$J23*M23/$K23,0) -> 2205.1297 | AC23: =IF(ISNUMBER(N23),$J23*N23/$K23,0) -> 2419.0724 | AD23: =IF(ISNUMBER(O23),$J23*O23/$K23,0) -> 309.8572 | AE23: =IF(ISNUMBER(P23),$J23*P23/$K23,0) -> 351.22941 | AF23: =IF(ISNUMBER(Q23),$J23*Q23/$K23,0) -> 402.0552 | AG23: =IF(ISNUMBER(R23),$J23*R23/$K23,0) -> 394.26951 | AH23: =IF(ISNUMBER(S23),$J23*S23/$K23,0) -> 441.65044 | ... AO23: =IF(ISNUMBER(Z23),$J23*Z23/$K23,0) -> -69.485976 | AP23: 0.25745 | AQ23: =IF(AND(ISNUMBER(AP23),N(AP23)>0),AL23,0) -> 228.08513 | AR23: =IF(AQ23<>0,AQ23/AP23,0) -> 885.93954
A24: RADL3 | B24: Raia Drogasil | C24: Defensives | D24: Defensives | E24: 0.00924 | F24: 18.37 | G24: 21.05 | H24: =E24*G24/F24 -> 0.010588024 | I24: =H24/SUM($H$6:$H$81) -> 0.0095234697 | J24: =I24*Assumptions!$D$7 -> 1984.9951 | K24: 36957.427 | L24: 46876.308 | M24: 53062 | N24: 59054.917 | O24: 2695.6667 | P24: 3325.3333 | Q24: 3869.7778 | R24: 3923.6667 | S24: 4569.2222 | T24: 5097.875 | U24: 1595 | V24: 2026.417 | W24: 2484.636 | X24: -1487.5556 | Y24: -1644.6667 | Z24: -1767.3333 | AA24: =IF(ISNUMBER(L24),$J24*L24/$K24,0) -> 2517.7413 | AB24: =IF(ISNUMBER(M24),$J24*M24/$K24,0) -> 2849.9768 | AC24: =IF(ISNUMBER(N24),$J24*N24/$K24,0) -> 3171.8582 | AD24: =IF(ISNUMBER(O24),$J24*O24/$K24,0) -> 144.78511 | AE24: =IF(ISNUMBER(P24),$J24*P24/$K24,0) -> 178.6047 | AF24: =IF(ISNUMBER(Q24),$J24*Q24/$K24,0) -> 207.84699 | AG24: =IF(ISNUMBER(R24),$J24*R24/$K24,0) -> 210.74137 | AH24: =IF(ISNUMBER(S24),$J24*S24/$K24,0) -> 245.41437 | ... AO24: =IF(ISNUMBER(Z24),$J24*Z24/$K24,0) -> -94.924031 | AP24: 0.25264 | AQ24: =IF(AND(ISNUMBER(AP24),N(AP24)>0),AL24,0) -> 133.45058 | AR24: =IF(AQ24<>0,AQ24/AP24,0) -> 528.22428
A25: CSMG3 | B25: Copasa | C25: Defensives | D25: Defensives | E25: 0.00818 | F25: 56.31 | G25: 61.56 | H25: =E25*G25/F25 -> 0.0089426532 | I25: =H25/SUM($H$6:$H$81) -> 0.0080435298 | J25: =I25*Assumptions!$D$7 -> 1676.5284 | K25: 23902.708 | L25: 8582.8333 | M25: 9979.4 | N25: 10840.2 | O25: 2148.25 | P25: 2613.25 | Q25: 3629.1429 | R25: 3224.125 | S25: 3866 | T25: 5225.5714 | U25: 1108.25 | V25: 1148.571 | W25: 1718 | X25: -3633 | Y25: -4410 | Z25: -5241.75 | AA25: =IF(ISNUMBER(L25),$J25*L25/$K25,0) -> 601.99721 | AB25: =IF(ISNUMBER(M25),$J25*M25/$K25,0) -> 699.95196 | AC25: =IF(ISNUMBER(N25),$J25*N25/$K25,0) -> 760.3282 | AD25: =IF(ISNUMBER(O25),$J25*O25/$K25,0) -> 150.67758 | AE25: =IF(ISNUMBER(P25),$J25*P25/$K25,0) -> 183.29253 | AF25: =IF(ISNUMBER(Q25),$J25*Q25/$K25,0) -> 254.54693 | AG25: =IF(ISNUMBER(R25),$J25*R25/$K25,0) -> 226.13911 | AH25: =IF(ISNUMBER(S25),$J25*S25/$K25,0) -> 271.16002 | ... AO25: =IF(ISNUMBER(Z25),$J25*Z25/$K25,0) -> -367.65469 | AP25: 0.17802 | AQ25: =IF(AND(ISNUMBER(AP25),N(AP25)>0),AL25,0) -> 120.49998 | AR25: =IF(AQ25<>0,AQ25/AP25,0) -> 676.8901
A26: VIVT3 | B26: Telefônica Brasil | C26: Defensives | D26: Defensives | E26: 0.00807 | F26: 29.81 | G26: 31.69 | H26: =E26*G26/F26 -> 0.0085789433 | I26: =H26/SUM($H$6:$H$81) -> 0.0077163885 | J26: =I26*Assumptions!$D$7 -> 1608.3417 | K26: 101875.93 | L26: 63659.867 | M26: 67188.2 | N26: 70950.167 | O26: 12017.833 | P26: 14286.75 | Q26: 15152.182 | R26: 27121.8 | S26: 29157.4 | T26: 30271.167 | U26: 7265.091 | V26: 9591.357 | W26: 10439.167 | X26: -9612.8889 | Y26: -10092.556 | Z26: -10413.111 | AA26: =IF(ISNUMBER(L26),$J26*L26/$K26,0) -> 1005.0148 | AB26: =IF(ISNUMBER(M26),$J26*M26/$K26,0) -> 1060.7175 | AC26: =IF(ISNUMBER(N26),$J26*N26/$K26,0) -> 1120.1086 | AD26: =IF(ISNUMBER(O26),$J26*O26/$K26,0) -> 189.72864 | AE26: =IF(ISNUMBER(P26),$J26*P26/$K26,0) -> 225.54862 | AF26: =IF(ISNUMBER(Q26),$J26*Q26/$K26,0) -> 239.21142 | AG26: =IF(ISNUMBER(R26),$J26*R26/$K26,0) -> 428.17888 | AH26: =IF(ISNUMBER(S26),$J26*S26/$K26,0) -> 460.31542 | ... AO26: =IF(ISNUMBER(Z26),$J26*Z26/$K26,0) -> -164.39448 | AP26: 0.15648 | AQ26: =IF(AND(ISNUMBER(AP26),N(AP26)>0),AL26,0) -> 164.80583 | AR26: =IF(AQ26<>0,AQ26/AP26,0) -> 1053.207
A27: CMIG4 | B27: Cemig | C27: Defensives | D27: Defensives | E27: 0.00779 | F27: 11.16 | G27: 12.08 | H27: =E27*G27/F27 -> 0.0084321864 | I27: =H27/SUM($H$6:$H$81) -> 0.007584387 | J27: =I27*Assumptions!$D$7 -> 1580.8284 | K27: 39737.661 | L27: 39365.286 | M27: 35664 | N27: 37164.143 | O27: 5924.2857 | P27: 6179.1429 | Q27: 7732.2857 | R27: 7518.125 | S27: 7949.375 | T27: 9589.1429 | U27: 3611.375 | V27: 3740.625 | W27: 4638.857 | X27: -5508 | Y27: -5924.75 | Z27: -5536.5 | AA27: =IF(ISNUMBER(L27),$J27*L27/$K27,0) -> 1566.0147 | AB27: =IF(ISNUMBER(M27),$J27*M27/$K27,0) -> 1418.7715 | AC27: =IF(ISNUMBER(N27),$J27*N27/$K27,0) -> 1478.4497 | AD27: =IF(ISNUMBER(O27),$J27*O27/$K27,0) -> 235.67766 | AE27: =IF(ISNUMBER(P27),$J27*P27/$K27,0) -> 245.81629 | AF27: =IF(ISNUMBER(Q27),$J27*Q27/$K27,0) -> 307.60282 | AG27: =IF(ISNUMBER(R27),$J27*R27/$K27,0) -> 299.08316 | AH27: =IF(ISNUMBER(S27),$J27*S27/$K27,0) -> 316.23898 | ... AO27: =IF(ISNUMBER(Z27),$J27*Z27/$K27,0) -> -220.25092 | AP27: 0.14308 | AQ27: =IF(AND(ISNUMBER(AP27),N(AP27)>0),AL27,0) -> 184.54123 | AR27: =IF(AQ27<>0,AQ27/AP27,0) -> 1289.7765
A28: ENGI11 | B28: Energisa | C28: Defensives | D28: Defensives | E28: 0.00726 | F28: 52.97 | G28: 63.21 | H28: =E28*G28/F28 -> 0.0086634812 | I28: =H28/SUM($H$6:$H$81) -> 0.0077924267 | J28: =I28*Assumptions!$D$7 -> 1624.1905 | K28: 32974.913 | L28: 31721.286 | M28: 32853.833 | N28: 35095 | O28: 6636.8571 | P28: 7111.875 | Q28: 7853.1667 | R28: 9002.875 | S28: 9485.8571 | T28: 10440 | U28: 1552.125 | V28: 1897.714 | W28: 2613.5 | X28: -6128.5 | Y28: -6467.5 | Z28: -6184 | AA28: =IF(ISNUMBER(L28),$J28*L28/$K28,0) -> 1562.4426 | AB28: =IF(ISNUMBER(M28),$J28*M28/$K28,0) -> 1618.2266 | AC28: =IF(ISNUMBER(N28),$J28*N28/$K28,0) -> 1728.6161 | AD28: =IF(ISNUMBER(O28),$J28*O28/$K28,0) -> 326.90064 | AE28: =IF(ISNUMBER(P28),$J28*P28/$K28,0) -> 350.2978 | AF28: =IF(ISNUMBER(Q28),$J28*Q28/$K28,0) -> 386.81037 | AG28: =IF(ISNUMBER(R28),$J28*R28/$K28,0) -> 443.43964 | AH28: =IF(ISNUMBER(S28),$J28*S28/$K28,0) -> 467.22909 | ... AO28: =IF(ISNUMBER(Z28),$J28*Z28/$K28,0) -> -304.59501 | AP28: 0.1233 | AQ28: =IF(AND(ISNUMBER(AP28),N(AP28)>0),AL28,0) -> 128.72882 | AR28: =IF(AQ28<>0,AQ28/AP28,0) -> 1044.0294
... A74: KLBN11 | B74: Klabin | C74: Commodities | D74: Commodities | E74: 0.00545 | F74: 18.11 | G74: 18.47 | H74: =E74*G74/F74 -> 0.0055583379 | I74: =H74/SUM($H$6:$H$81) -> 0.0049994846 | J74: =I74*Assumptions!$D$7 -> 1042.0522 | K74: 23199.922 | L74: 21123.929 | M74: 22132.786 | N74: 22840.75 | O74: 3463.6364 | P74: 4265.6364 | Q74: 4616.4545 | R74: 7594.3571 | S74: 8069.0714 | T74: 8357 | U74: 1009.727 | V74: 1680.583 | W74: 1980.545 | X74: -3249.5 | Y74: -2873 | Z74: -2698.4286 | AA74: =IF(ISNUMBER(L74),$J74*L74/$K74,0) -> 948.80645 | AB74: =IF(ISNUMBER(M74),$J74*M74/$K74,0) -> 994.12047 | AC74: =IF(ISNUMBER(N74),$J74*N74/$K74,0) -> 1025.9195 | AD74: =IF(ISNUMBER(O74),$J74*O74/$K74,0) -> 155.57336 | AE74: =IF(ISNUMBER(P74),$J74*P74/$K74,0) -> 191.59615 | AF74: =IF(ISNUMBER(Q74),$J74*Q74/$K74,0) -> 207.35356 | AG74: =IF(ISNUMBER(R74),$J74*R74/$K74,0) -> 341.10961 | AH74: =IF(ISNUMBER(S74),$J74*S74/$K74,0) -> 362.43197 | ... AO74: =IF(ISNUMBER(Z74),$J74*Z74/$K74,0) -> -121.20314 | AP74: 0.30387 | AQ74: =IF(AND(ISNUMBER(AP74),N(AP74)>0),AL74,0) -> 88.958541 | AR74: =IF(AQ74<>0,AQ74/AP74,0) -> 292.75197
A75: GOAU4 | B75: Met. Gerdau | C75: Commodities | D75: Commodities | E75: 0.00347 | F75: 10.94 | G75: 11.77 | H75: =E75*G75/F75 -> 0.0037332633 | I75: =H75/SUM($H$6:$H$81) -> 0.0033579089 | J75: =I75*Assumptions!$D$7 -> 699.89539 | K75: 14527.916 | L75: 1924 | M75: 1671 | O75: 1701 | P75: 1945 | Q75: 1725 | R75: 1925 | S75: 1672 | U75: 1932 | V75: 1686 | AA75: =IF(ISNUMBER(L75),$J75*L75/$K75,0) -> 92.690428 | AB75: =IF(ISNUMBER(M75),$J75*M75/$K75,0) -> 80.501926 | AC75: =IF(ISNUMBER(N75),$J75*N75/$K75,0) -> 0 | AD75: =IF(ISNUMBER(O75),$J75*O75/$K75,0) -> 81.947203 | AE75: =IF(ISNUMBER(P75),$J75*P75/$K75,0) -> 93.702122 | AF75: =IF(ISNUMBER(Q75),$J75*Q75/$K75,0) -> 83.103424 | AG75: =IF(ISNUMBER(R75),$J75*R75/$K75,0) -> 92.738604 | AH75: =IF(ISNUMBER(S75),$J75*S75/$K75,0) -> 80.550102 | ... AO75: =IF(ISNUMBER(Z75),$J75*Z75/$K75,0) -> 0 | AQ75: =IF(AND(ISNUMBER(AP75),N(AP75)>0),AL75,0) -> 0 | AR75: =IF(AQ75<>0,AQ75/AP75,0) -> 0 | AS75: sales28, ebitda28, ni28, capex26, capex27, capex28
A76: CSAN3 | B76: Cosan | C76: Commodities | D76: Commodities | E76: 0.00346 | F76: 3.96 | G76: 5.12 | H76: =E76*G76/F76 -> 0.0044735354 | I76: =H76/SUM($H$6:$H$81) -> 0.0040237516 | J76: =I76*Assumptions!$D$7 -> 838.67827 | K76: 20031.183 | L76: 39894.2 | M76: 46724 | N76: 52061.25 | O76: 12235.4 | P76: 13142.6 | Q76: 14606 | R76: 17435.857 | S76: 17310.556 | T76: 20075.667 | U76: -856.55 | V76: 2196.857 | W76: 3607.167 | X76: -11294.667 | Y76: -10044 | Z76: -11243.333 | AA76: =IF(ISNUMBER(L76),$J76*L76/$K76,0) -> 1670.3156 | AB76: =IF(ISNUMBER(M76),$J76*M76/$K76,0) -> 1956.27 | AC76: =IF(ISNUMBER(N76),$J76*N76/$K76,0) -> 2179.7334 | AD76: =IF(ISNUMBER(O76),$J76*O76/$K76,0) -> 512.27948 | AE76: =IF(ISNUMBER(P76),$J76*P76/$K76,0) -> 550.26271 | AF76: =IF(ISNUMBER(Q76),$J76*Q76/$K76,0) -> 611.53326 | AG76: =IF(ISNUMBER(R76),$J76*R76/$K76,0) -> 730.01552 | AH76: =IF(ISNUMBER(S76),$J76*S76/$K76,0) -> 724.76931 | ... AO76: =IF(ISNUMBER(Z76),$J76*Z76/$K76,0) -> -470.74301 | AP76: 0.21347 | AQ76: =IF(AND(ISNUMBER(AP76),N(AP76)>0),AL76,0) -> 151.02715 | AR76: =IF(AQ76<>0,AQ76/AP76,0) -> 707.48655
A77: CMIN3 | B77: CSN Mineração | C77: Commodities | D77: Commodities | E77: 0.00302 | F77: 5.01 | G77: 5.04 | H77: =E77*G77/F77 -> 0.0030380838 | I77: =H77/SUM($H$6:$H$81) -> 0.002732625 | J77: =I77*Assumptions!$D$7 -> 569.56628 | K77: 26997.261 | L77: 14636.2 | M77: 14279.4 | N77: 16155.25 | O77: 3309 | P77: 3156.2 | Q77: 4810.7778 | R77: 4729.8182 | S77: 4618.2727 | T77: 5805.1111 | U77: 1535.091 | V77: 1364.7 | W77: 1844 | X77: -2891.2857 | Y77: -3586.1429 | Z77: -4009.5 | AA77: =IF(ISNUMBER(L77),$J77*L77/$K77,0) -> 308.78265 | AB77: =IF(ISNUMBER(M77),$J77*M77/$K77,0) -> 301.25518 | AC77: =IF(ISNUMBER(N77),$J77*N77/$K77,0) -> 340.83034 | AD77: =IF(ISNUMBER(O77),$J77*O77/$K77,0) -> 69.810593 | AE77: =IF(ISNUMBER(P77),$J77*P77/$K77,0) -> 66.586943 | AF77: =IF(ISNUMBER(Q77),$J77*Q77/$K77,0) -> 101.49388 | AG77: =IF(ISNUMBER(R77),$J77*R77/$K77,0) -> 99.785861 | AH77: =IF(ISNUMBER(S77),$J77*S77/$K77,0) -> 97.432565 | ... AO77: =IF(ISNUMBER(Z77),$J77*Z77/$K77,0) -> -84.589173 | AP77: 0.3377 | AQ77: =IF(AND(ISNUMBER(AP77),N(AP77)>0),AL77,0) -> 38.903214 | AR77: =IF(AQ77<>0,AQ77/AP77,0) -> 115.20051
A78: BRAP4 | B78: Bradespar | C78: Commodities | D78: Commodities | E78: 0.00194 | F78: 20.23 | G78: 21.15 | H78: =E78*G78/F78 -> 0.0020282254 | I78: =H78/SUM($H$6:$H$81) -> 0.0018243011 | J78: =I78*Assumptions!$D$7 -> 380.24257 | K78: 7940.7481 | L78: 1719.5 | M78: 5737 | N78: 1656 | O78: 1082 | P78: 5669.5 | Q78: 9389 | R78: 1082 | S78: 5669.5 | T78: 1548 | U78: 1660 | V78: 1663.5 | W78: 1533 | AA78: =IF(ISNUMBER(L78),$J78*L78/$K78,0) -> 82.338225 | AB78: =IF(ISNUMBER(M78),$J78*M78/$K78,0) -> 274.71614 | AC78: =IF(ISNUMBER(N78),$J78*N78/$K78,0) -> 79.297528 | AD78: =IF(ISNUMBER(O78),$J78*O78/$K78,0) -> 51.811549 | AE78: =IF(ISNUMBER(P78),$J78*P78/$K78,0) -> 271.4839 | AF78: =IF(ISNUMBER(Q78),$J78*Q78/$K78,0) -> 449.59209 | AG78: =IF(ISNUMBER(R78),$J78*R78/$K78,0) -> 51.811549 | AH78: =IF(ISNUMBER(S78),$J78*S78/$K78,0) -> 271.4839 | ... AO78: =IF(ISNUMBER(Z78),$J78*Z78/$K78,0) -> 0 | AP78: 0.158 | AQ78: =IF(AND(ISNUMBER(AP78),N(AP78)>0),AL78,0) -> 73.407676 | AR78: =IF(AQ78<>0,AQ78/AP78,0) -> 464.60554 | AS78: capex26, capex27, capex28
A79: BRAV3 | B79: Brava Energia | C79: Commodities | D79: Commodities | E79: 0.00193 | F79: 18.12 | G79: 19.1 | H79: =E79*G79/F79 -> 0.0020343819 | I79: =H79/SUM($H$6:$H$81) -> 0.0018298385 | J79: =I79*Assumptions!$D$7 -> 381.39676 | K79: 9240.0441 | L79: 13491.1 | M79: 13712.182 | N79: 13075.333 | O79: 4110.3 | P79: 4262.2727 | Q79: 3471.8 | R79: 6799.4 | S79: 7196.7273 | T79: 6561.8889 | U79: 911 | V79: 1804.545 | W79: 1734.778 | X79: -3101.1667 | Y79: -2098 | Z79: -2040.6667 | AA79: =IF(ISNUMBER(L79),$J79*L79/$K79,0) -> 556.86551 | AB79: =IF(ISNUMBER(M79),$J79*M79/$K79,0) -> 565.991 | AC79: =IF(ISNUMBER(N79),$J79*N79/$K79,0) -> 539.70411 | AD79: =IF(ISNUMBER(O79),$J79*O79/$K79,0) -> 169.65884 | AE79: =IF(ISNUMBER(P79),$J79*P79/$K79,0) -> 175.93174 | AF79: =IF(ISNUMBER(Q79),$J79*Q79/$K79,0) -> 143.30378 | AG79: =IF(ISNUMBER(R79),$J79*R79/$K79,0) -> 280.6555 | AH79: =IF(ISNUMBER(S79),$J79*S79/$K79,0) -> 297.05578 | ... AO79: =IF(ISNUMBER(Z79),$J79*Z79/$K79,0) -> -84.231596 | AP79: 0.10748 | AQ79: =IF(AND(ISNUMBER(AP79),N(AP79)>0),AL79,0) -> 71.60558 | AR79: =IF(AQ79<>0,AQ79/AP79,0) -> 666.22236
A80: CSNA3 | B80: CSN | C80: Commodities | D80: Commodities | E80: 0.00161 | F80: 5.77 | G80: 6.42 | H80: =E80*G80/F80 -> 0.0017913692 | I80: =H80/SUM($H$6:$H$81) -> 0.0016112591 | J80: =I80*Assumptions!$D$7 -> 335.83783 | K80: 8420.6966 | L80: 45041.333 | M80: 43164.8 | N80: 45946.5 | O80: 5127.1111 | P80: 5876.8889 | Q80: 7499.25 | R80: 10237.6 | S80: 11015.2 | T80: 12622.625 | U80: -504.444 | V80: 310.1 | W80: 803.463 | X80: -5019 | Y80: -5630 | Z80: -6095.75 | AA80: =IF(ISNUMBER(L80),$J80*L80/$K80,0) -> 1796.3577 | AB80: =IF(ISNUMBER(M80),$J80*M80/$K80,0) -> 1721.517 | AC80: =IF(ISNUMBER(N80),$J80*N80/$K80,0) -> 1832.458 | AD80: =IF(ISNUMBER(O80),$J80*O80/$K80,0) -> 204.48164 | AE80: =IF(ISNUMBER(P80),$J80*P80/$K80,0) -> 234.3846 | AF80: =IF(ISNUMBER(Q80),$J80*Q80/$K80,0) -> 299.0883 | AG80: =IF(ISNUMBER(R80),$J80*R80/$K80,0) -> 408.30035 | AH80: =IF(ISNUMBER(S80),$J80*S80/$K80,0) -> 439.31292 | ... AO80: =IF(ISNUMBER(Z80),$J80*Z80/$K80,0) -> -243.11331 | AP80: 0.07778 | AQ80: =IF(AND(ISNUMBER(AP80),N(AP80)>0),AL80,0) -> 32.044055 | AR80: =IF(AQ80<>0,AQ80/AP80,0) -> 411.98323
A81: USIM5 | B81: Usiminas | C81: Commodities | D81: Commodities | E81: 0.00139 | F81: 7.01 | G81: 7.46 | H81: =E81*G81/F81 -> 0.0014792297 | I81: =H81/SUM($H$6:$H$81) -> 0.0013305031 | J81: =I81*Assumptions!$D$7 -> 277.31932 | K81: 8789.3845 | L81: 24954.182 | M81: 26001 | N81: 26984.778 | O81: 1569.75 | P81: 1984 | Q81: 2097 | R81: 2644 | S81: 3020.4 | T81: 3319.5556 | U81: 1592.909 | V81: 1416.182 | W81: 1598.667 | X81: -1308.1667 | Y81: -1658 | Z81: -2254.6667 | AA81: =IF(ISNUMBER(L81),$J81*L81/$K81,0) -> 787.34486 | AB81: =IF(ISNUMBER(M81),$J81*M81/$K81,0) -> 820.37367 | AC81: =IF(ISNUMBER(N81),$J81*N81/$K81,0) -> 851.41346 | AD81: =IF(ISNUMBER(O81),$J81*O81/$K81,0) -> 49.528156 | AE81: =IF(ISNUMBER(P81),$J81*P81/$K81,0) -> 62.598414 | AF81: =IF(ISNUMBER(Q81),$J81*Q81/$K81,0) -> 66.163747 | AG81: =IF(ISNUMBER(R81),$J81*R81/$K81,0) -> 83.422484 | AH81: =IF(ISNUMBER(S81),$J81*S81/$K81,0) -> 95.298513 | ... AO81: =IF(ISNUMBER(Z81),$J81*Z81/$K81,0) -> -71.138386 | AP81: 0.06654 | AQ81: =IF(AND(ISNUMBER(AP81),N(AP81)>0),AL81,0) -> 50.440534 | AR81: =IF(AQ81<>0,AQ81/AP81,0) -> 758.0483
A83: Total | E83: =SUM(E6:E81) -> 1 | I83: =SUM(I6:I81) -> 1 | J83: =SUM(J6:J81) -> 208431.92 | AA83: =SUM(AA6:AA81) -> 157931.36 | AB83: =SUM(AB6:AB81) -> 162950.7 | AC83: =SUM(AC6:AC81) -> 169017.22 | AD83: =SUM(AD6:AD81) -> 32221.517 | AE83: =SUM(AE6:AE81) -> 34108.458 | AF83: =SUM(AF6:AF81) -> 36064.515 | AG83: =SUM(AG6:AG81) -> 39428.713 | AH83: =SUM(AH6:AH81) -> 43589.989 | ... AO83: =SUM(AO6:AO81) -> -16367.982 | AQ83: =SUM(AQ6:AQ81) -> 22482.351 | AR83: =SUM(AR6:AR81) -> 130587.43
A85: Index points of a line = index points x line / market cap: the stock's share of the line, in points. Company totals and market cap in BRL, so the currency of reporting does not matter; both share classes of a company use the company's market cap.
A86: Banks have no EBITDA and no capex in Bloomberg; the IBOV Index line scales the members with data up to the whole index, so part of the index EBITDA and capex is imputed to the banks (Box Shares section 3).

Sheet Checks
B1: Ibovespa - Checks
B2: 'OK' / 'CHECK' drive the status in C5; 'Info' does not. House tie-outs hold while the projection rules are the house's.
B5: Overall status | C5: =IF(COUNTIF(F8:F43,"CHECK")=0,"All checks OK","Some checks need attention") -> All checks OK
B7: Check | C7: Value | D7: Target | E7: Difference | F7: Status | G7: Note
B8: House replica
B9: FCFF 2025, house row = Target row 44 | C9: =DCF!M35 -> 3970.36 | D9: =3970.35999999999 -> 3970.36 | E9: =IFERROR(C9-D9,"") -> 8.6401997e-12 | F9: =IF(ABS(C9-D9)<=0.01,"OK","CHECK") -> OK | G9: House file value.
B10: FCFF 2026, house row = Target row 44 | C10: =DCF!N35 -> 15868.96 | D10: =15868.96 -> 15868.96 | E10: =IFERROR(C10-D10,"") -> 3.6379788e-12 | F10: =IF(ABS(C10-D10)<=0.01,"OK","CHECK") -> OK | G10: House file value.
B11: FCFF 2027, house row = Target row 44 | C11: =DCF!O35 -> 16461.32 | D11: =16461.32 -> 16461.32 | E11: =IFERROR(C11-D11,"") -> 0 | F11: =IF(ABS(C11-D11)<=0.01,"OK","CHECK") -> OK | G11: House file value.
B12: FCFF 2028, house row = Target row 44 | C12: =DCF!P35 -> 16980.784 | D12: =16980.7843199999 -> 16980.784 | E12: =IFERROR(C12-D12,"") -> 9.4587449e-11 | F12: =IF(ABS(C12-D12)<=0.01,"OK","CHECK") -> OK | G12: House file value.
B13: FCFF 2029, house row = Target row 44 | C13: =DCF!Q35 -> 18141.421 | D13: =18141.4206455039 -> 18141.421 | E13: =IFERROR(C13-D13,"") -> 9.4587449e-11 | F13: =IF(ABS(C13-D13)<=0.01,"OK","CHECK") -> OK | G13: House file value.
B14: FCFF 2030, house row = Target row 44 | C14: =DCF!R35 -> 23154.288 | D14: =23154.2881952842 -> 23154.288 | E14: =IFERROR(C14-D14,"") -> 1.4551915e-11 | F14: =IF(ABS(C14-D14)<=0.01,"OK","CHECK") -> OK | G14: House file value.
B15: Terminal value on 2030, house rate (Target!R44) | C15: =DCF!R35*(1+Checks!$C$54)/(Checks!$C$52+Checks!$C$53-Checks!$C$54) -> 278010.78 | D15: =278010.776840167 -> 278010.78 | E15: =IFERROR(C15-D15,"") -> 1.1641532e-10 | F15: =IF(ABS(C15-D15)<=0.01,"OK","CHECK") -> OK
B16: Fair value end-2025, house settings (Target!D59) | C16: =NPV((Checks!$C$52+Checks!$C$53),DCF!$M$35:$R$35)+DCF!$R$35*(1+Checks!$C$54)/((Checks!$C$52+Checks!$C$53)-Checks!$C$54)/(1+(Checks!$C$52+Checks!$C$53))^7-0 -> 173064.09 | D16: =173064.087825606 -> 173064.09 | E16: =IFERROR(C16-D16,"") -> 8.7311491e-11 | F16: =IF(ABS(C16-D16)<=0.01,"OK","CHECK") -> OK
B17: Fair value end-2026, house settings (Target!F59) | C17: =NPV((Checks!$C$52+Checks!$C$53),DCF!$O$35:$R$35)+DCF!$R$35*(1+Checks!$C$54)/((Checks!$C$52+Checks!$C$53)-Checks!$C$54)/(1+(Checks!$C$52+Checks!$C$53))^5-0 -> 202259.17 | D17: =202259.168604666 -> 202259.17 | E17: =IFERROR(C17-D17,"") -> 2.6193447e-10 | F17: =IF(ABS(C17-D17)<=0.01,"OK","CHECK") -> OK
B18: Fair value end-2027, house file column (Target!G59) | C18: =NPV((Checks!$C$52+Checks!$C$53),DCF!$P$35:$R$35)+DCF!$R$35*(1+Checks!$C$54)/((Checks!$C$52+Checks!$C$53)-Checks!$C$54)/(1+(Checks!$C$52+Checks!$C$53))^4-0 -> 212941.03 | D18: =212941.029031412 -> 212941.03 | E18: =IFERROR(C18-D18,"") -> 4.3655746e-10 | F18: =IF(ABS(C18-D18)<=0.01,"OK","CHECK") -> OK
B19: Real-rate table, largest gap to the house (Sensitivity) | C19: =MAX(MAX(Sensitivity!E7:E14),-MIN(Sensitivity!E7:E14)) -> 0 | D19: =0 -> 0 | E19: =IFERROR(C19-D19,"") -> 0 | F19: =IF(ABS(C19-D19)<=0.01,"OK","CHECK") -> OK
B20: House implied return at the house price (Target!B62) | C20: =IRR(Checks!C56:G56) -> 0.17379161 | D20: =0.173791607034303 -> 0.17379161 | E20: =IFERROR(C20-D20,"") -> 3.0531133e-16 | F20: =IF(ABS(C20-D20)<=0.000001,"OK","CHECK") -> OK | G20: Helper row 56.
B21: Split by box
B22: Member weights on Oct-5 add up to 100% | C22: =Members!I83 -> 1 | D22: =1 -> 1 | E22: =IFERROR(C22-D22,"") -> 2.220446e-16 | F22: =IF(ABS(C22-D22)<=0.000000001,"OK","CHECK") -> OK
B23: Members' index points = Ibovespa on Oct-5 | C23: =Members!J83 -> 208431.92 | D23: =Assumptions!$D$7 -> 208431.92 | E23: =IFERROR(C23-D23,"") -> 5.8207661e-11 | F23: =IF(ABS(C23-D23)<=0.01,"OK","CHECK") -> OK
B24: Box shares add up to 100% (all lines and years; sum of absolute gaps) | C24: =SUMPRODUCT(ABS('Box Shares'!D23:R23-1)) -> 1.110223e-16 | D24: =0 -> 0 | E24: =IFERROR(C24-D24,"") -> 1.110223e-16 | F24: =IF(ABS(C24-D24)<=0.000000001,"OK","CHECK") -> OK
B25: Memo sub-boxes = Cyclicals (index points) | C25: ='Box Shares'!C14+'Box Shares'!C15 -> 26271.075 | D25: ='Box Shares'!C9 -> 26271.075 | E25: =IFERROR(C25-D25,"") -> 0 | F25: =IF(ABS(C25-D25)<=0.01,"OK","CHECK") -> OK
B26: FCFF used: sum of the boxes = house, 2028-2031 (sum of absolute gaps) | C26: =SUMPRODUCT(ABS('DCF by Box'!E35:H35+'DCF by Box'!E83:H83+'DCF by Box'!E124:H124+'DCF by Box'!E165:H165-DCF!P37:S37)) -> 2.910383e-11 | D26: =0 -> 0 | E26: =IFERROR(C26-D26,"") -> 2.910383e-11 | F26: =IF(ABS(C26-D26)<=0.01,"OK","CHECK") -> OK
B27: Bear: sum of the FCFF pieces = house value (exact split) | C27: ='DCF by Box'!C12 -> 191722.24 | D27: ='DCF by Box'!C8 -> 191722.24 | E27: =IFERROR(C27-D27,"") -> 2.910383e-11 | F27: =IF(ABS(C27-D27)<=0.01,"OK","CHECK") -> OK
B28: Base: sum of the FCFF pieces = house value (exact split) | C28: ='DCF by Box'!D12 -> 235695.44 | D28: ='DCF by Box'!D8 -> 235695.44 | E28: =IFERROR(C28-D28,"") -> 8.7311491e-11 | F28: =IF(ABS(C28-D28)<=0.01,"OK","CHECK") -> OK
B29: Bull: sum of the FCFF pieces = house value (exact split) | C29: ='DCF by Box'!E12 -> 261607.54 | D29: ='DCF by Box'!E8 -> 261607.54 | E29: =IFERROR(C29-D29,"") -> 1.1641532e-10 | F29: =IF(ABS(C29-D29)<=0.01,"OK","CHECK") -> OK
B30: Base: memo sub-boxes = Cyclicals at the house rate | C30: ='DCF by Box'!D225+'DCF by Box'!D266 -> 12539.859 | D30: ='DCF by Box'!D143 -> 12539.859 | E30: =IFERROR(C30-D30,"") -> -5.4569682e-12 | F30: =IF(ABS(C30-D30)<=0.01,"OK","CHECK") -> OK | G30: At the box rates the memo rows have their own rates and are not additive.
B31: Base: sum of the box fair values = house value (or the own sum if not scaled) | C31: ='DCF by Box'!D11 -> 235695.44 | D31: =IF(ScaleBox=1,'DCF by Box'!D8,'DCF by Box'!D7) -> 235695.44 | E31: =IFERROR(C31-D31,"") -> 0 | F31: =IF(ABS(C31-D31)<=0.01,"OK","CHECK") -> OK
B32: Base: scale factor (house / sum of own values) | C32: ='DCF by Box'!D9 -> 0.9299333 | D32: =1 -> 1 | E32: =IFERROR(C32-D32,"") -> -0.0700667 | F32: ="Info" -> Info | G32: Info: Financials by FCFE vs. its FCFF piece explains the gap.
B33: Base: Financials FCFE value / its FCFF piece - 1 | C33: ='DCF by Box'!D53/'DCF by Box'!D48-1 -> -0.11063948 | D33: =0 -> 0 | E33: =IFERROR(C33-D33,"") -> -0.11063948 | F33: ="Info" -> Info | G33: Info.
B34: Box rates: months of earnings-yield history (Box Rates) | C34: =COUNT('Box Rates'!C32:C151) -> 120 | D34: =120 -> 120 | E34: =IFERROR(C34-D34,"") -> 0 | F34: =IF(ABS(C34-D34)<=0,"OK","CHECK") -> OK
B35: Box rates in use (0 = house rate, 1 = relative to history, 2 = CAPM) | C35: =BoxRate -> 1 | D35: =1 -> 1 | E35: =IFERROR(C35-D35,"") -> 0 | F35: ="Info" -> Info | G35: Info.
B36: CAPM betas: weighted average of the four boxes (index points) | C36: ='Box Betas'!C16 -> 1.0031655 | D36: =1 -> 1 | E36: =IFERROR(C36-D36,"") -> 0.0031654975 | F36: ="Info" -> Info | G36: Info: close to 1, the Ibovespa's beta.
B37: Base: average gap to the multiples model, four boxes (upside, pp) | C37: =Summary!F26*100 -> 15.653625 | D37: =0 -> 0 | E37: =IFERROR(C37-D37,"") -> 15.653625 | F37: ="Info" -> Info | G37: Info: Summary section 2.
B38: Members with a missing consensus line | C38: =COUNTIF(Members!AS6:AS81,"?*") -> 12 | D38: =0 -> 0 | E38: =IFERROR(C38-D38,"") -> 12 | F38: ="Info" -> Info | G38: Info: missing lines count as 0 (banks: EBITDA, capex).
B39: Settings
B40: Corrections switched on (Assumptions section 4) | C40: =FixNWC+FixND+FixTV+FixInfl -> 0 | D40: =0 -> 0 | E40: =IFERROR(C40-D40,"") -> 0 | F40: ="Info" -> Info | G40: Info: 0 = the house mechanics.
B41: Market data used (1 = house file, 2 = Oct-5) | C41: =Vintage -> 2 | D41: =2 -> 2 | E41: =IFERROR(C41-D41,"") -> 0 | F41: ="Info" -> Info | G41: Info.
B42: Formula errors (DCF, DCF by Box, Summary, Sensitivity, Box Shares, Box Rates, Box Betas, Members) | C42: =SUMPRODUCT(--ISERROR(DCF!C8:S90))+SUMPRODUCT(--ISERROR('DCF by Box'!C5:H269))+SUMPRODUCT(--ISERROR(Summary!C4:J75))+SUMPRODUCT(--ISERROR(Sensitivity!C7:G60))+SUMPRODUCT(--ISERROR('Box Shares'!C7:R40))+SUMPRODUCT(--ISERROR('Box Rates'!C7:I151))+SUMPRODUCT(--ISERROR('Box Betas'!C7:Q600))+SUMPRODUCT(--ISERROR(Members!E6:AR83)) -> 0 | D42: =0 -> 0 | E42: =IFERROR(C42-D42,"") -> 0 | F42: =IF(ABS(C42-D42)<=0,"OK","CHECK") -> OK
B51: House file settings used by the tie-outs (Target sheet)
B52: 5-year real rate (Target!C56) | C52: 0.0742
B53: ERP (Target!B57) | C53: 0.06
B54: g (Target!B54) | C54: 0.047
B55: Ibovespa (Target!B61) | C55: 182419.73
B56: Helper: house implied-return flows (Target row 61) | C56: =-C55 -> -182419.73 | D56: =DCF!N35 -> 15868.96 | E56: =DCF!O35 -> 16461.32 | F56: =DCF!P35 -> 16980.784 | G56: =DCF!R35*(1+C54)/(C52+C53-C54) -> 278010.78

Sheet Read Me
B1: Ibovespa DCF by box, house model rolled to end-2027
B2: XP Research · Equity Strategy · built Oct-7-2026 · house file inputs (Sep-26); members' consensus Oct-7-2026; market data Oct-5-2026
B4: What it is
B5: Aggregate | C5: The DCF block of the house Ibovespa model (DCF Ibov 2026_Out.xlsx, Target sheet), same inputs, rules and mechanics, rolled forward to a fair value at the end of 2027 (FCFF 2028-2031 + terminal value). Checks tie it to the house file.
B6: By box | C6: Every house line (sales, EBIT, EBITDA, net income, capex) is split among Financials, Defensives, Cyclicals and Commodities by their share of the IBOV Index line, measured with the members' Bloomberg consensus. Same years, rules, rate and switches as the house.
B8: How the split works
B9: Index points | C9: A member's line in index points = its index points x company line / company market cap (Members).
B10: Shares | C10: Non-financial boxes: their members' sum / the IBOV Index line. Financials: the rest. Net income: share of the members' total (Box Shares).
B11: Banks | C11: Banks have no EBITDA or capex. The IBOV Index line scales the members with data up to the whole index, so the house's EBITDA and capex include an amount imputed to the banks; it goes to Financials (Box Shares section 3).
B12: Years | C12: Shares from consensus for 2026-2027 (sales, capex) and 2026-2028 (EBIT, EBITDA, net income); later years keep the last share, as the house keeps margins and ratios.
B14: Valuation
B15: Non-financials | C15: House FCFF = D&A + NOPAT + capex + NWC (level), discounted at 5y real rate + 6.0% ERP, g 4.7%, TV one period after the last flow.
B16: Financials | C16: FCFE = net income x (1 - g / ROE), ROE = FY28 consensus of the Financials (Box Shares section 4); same g and TV convention.
B17: Box rates | C17: BoxRate = 1 (default): box rate - g = (house rate - g) x the box's relative cash yield = (its 10y average 12m fwd earnings yield x its cash conversion in 2031) / the same for the Ibovespa (Box Rates). A box that always traded at a higher multiple for its cash flow gets a lower rate, so the DCF keeps each box's historical relative valuation, as the multiples do. BoxRate = 0: one rate, as the house.
B18: CAPM | C18: BoxRate = 2: box rate = real rate + box beta x the house ERP (6.0%). Beta = covariance of the box's weekly total return with the Ibovespa's / variance of the Ibovespa's (Box Betas; window and Blume adjustment in Assumptions). Betas are close to 1, so the CAPM rates differ little from the house rate.
B19: Sum | C19: With every box on the house mechanics the boxes add up to the house value exactly. With Financials on FCFE they add up to about it; ScaleBox = 1 (default) scales the four boxes pro rata to the house value.
B21: How to use it
B22: 1. Change | C22: Assumptions: market data, g, NWC %, scenarios (real rate, ERP), correction switches, ScaleBox, BoxRate, ERP floor, Financials ROE. DCF sheet: pink projection rules.
B23: 2. Read | C23: Summary: boxes and Ibovespa, bear / base / bull; own values before scaling; shares.
B24: 3. Trace | C24: Summary -> DCF by Box (one block per box) -> Box Rates / Box Shares -> Members; DCF (house aggregate).
B26: Sources
B27: House file | C27: History 2015-2025 and IBOV Index consensus 2026-2028 as saved in DCF Ibov 2026_Out.xlsx (Sep-26); not refreshed.
B28: Members | C28: Bloomberg BEST_SALES, BEST_EBIT, BEST_EBITDA, BEST_NET_INCOME, BEST_CAPEX (FY26-FY28, BRL), CUR_MKT_CAP, BEST_ROE; Oct-7-2026. Weights: Economatica Sep-30, drifted by price to Oct-5.
B29: Market | C29: Ibovespa 208,431.92 (Oct-5 close); 5-year NTN-B 6.76% (ANBIMA, Oct-5).
B30: Code | C30: Brazil Bull Case/scripts: box_lines_data.py (Bloomberg) and build_house2027_box.py (this workbook).
