Workbook
Name ConsDate: Assumptions!$C$12
Name ERPBasis: Assumptions!$C$38
Name ErpHistIbov: History!$V$8
Name ErpSdIbov: History!$V$9
Name FYleft: Assumptions!$C$18
Name GicsMap: Assumptions!$B$89:$C$99
Name GlobalList: Assumptions!$B$102:$B$105
Name GrowthYear: Assumptions!$C$44
Name HistG: Assumptions!$C$41
Name HistGn: History!$C$14
Name Horizon: Assumptions!$C$39
Name IbovMem: Assumptions!$C$11
Name IbovNow: Assumptions!$C$7
Name IPCA1: Assumptions!$C$15
Name IPCA2: Assumptions!$C$16
Name IPCALT: Assumptions!$C$17
Name MemDate: Assumptions!$C$10
Name PEmax: Assumptions!$C$48
Name PEmin: Assumptions!$C$47
Name PxDate: Assumptions!$C$6
Name RateConv: Assumptions!$C$37
Name RoeLT: Assumptions!$C$40
Name ROEmax: Assumptions!$C$50
Name ROEmin: Assumptions!$C$49
Name RoeYear: Assumptions!$C$45
Name RR5Now: Assumptions!$C$9
Name SelicNow: Assumptions!$C$8
Name UseEPS: Assumptions!$C$46
Name WinEnd: Assumptions!$C$43
Name WinStart: Assumptions!$C$42

Sheet Cover
C3: Ibovespa | DCF by box
C4: VALUATION MODEL · EQUITY STRATEGY
C7: Main tabs >>
C8: Summary | E8: Assumptions | G8: DCF Base | I8: Implied ERP | K8: Ibovespa close | M8: =IbovNow -> 208431.92
K9: Pricing date | M9: =PxDate -> 46300
K10: Fair value, base case | M10: =Summary!E21 -> 223718.33
C11: Auxiliary tabs >> | K11: Upside, base case | M11: =Summary!J21 -> 0.073340058
C12: DCF Bear | E12: DCF Bull | G12: DCF Custom | I12: Sensitivity (real rate x ERP) | K12: Model checks | M12: =Checks!C5 -> All checks OK
K14: Equity Strategy | XP Research
C15: Boxes Now (consensus by box) | E15: History (ROE, P/E, ERP) | G15: Members (76 stocks) | I15: Checks (tests) | K15: How this model works >>
K16: Prices Oct-5; consensus Oct-7-2026.
C19: DCF summary >>
C20: Ibovespa | F20: Bear | G20: Base | H20: Bull | I20: Custom
C21: 5-year real rate | F21: =Summary!D9 -> 0.085 | G21: =Summary!E9 -> 0.0676 | H21: =Summary!F9 -> 0.06 | I21: =Summary!G9 -> 0.0676
C22: ERP used | F22: =Summary!D10 -> 0.06 | G22: =Summary!E10 -> 0.06 | H22: =Summary!F10 -> 0.06 | I22: =Summary!G10 -> 0.06
C23: Fair value (index pts) | F23: =Summary!D21 -> 169580.37 | G23: =Summary!E21 -> 223718.33 | H23: =Summary!F21 -> 276936.37 | I23: =Summary!G21 -> 223718.33
C24: Upside | F24: =Summary!I21 -> -0.18639922 | G24: =Summary!J21 -> 0.073340058 | H24: =Summary!K21 -> 0.32866581 | I24: =Summary!L21 -> 0.073340058
C25: Implied 12m fwd P/E | F25: =Summary!D32 -> 7.3508359 | G25: =Summary!E32 -> 9.187307 | H25: =Summary!F32 -> 10.728055 | I25: =Summary!G32 -> 9.187307
C26: Implied ERP at today's price | F26: =Summary!D40 -> 0.036072978 | G26: =Summary!E40 -> 0.059938855 | H26: =Summary!F40 -> 0.073981108 | I26: =Summary!G40 -> 0.059938855
C28: DCF = sum of four boxes, each valued by free cash flow to equity (consensus earnings, ROE converging to its 10-year average). House premises: 5y real rate + ERP 6.0%, g 4.7%.

Sheet Summary
B1: Ibovespa - DCF by box: bear / base / bull
B2: Separate from the multiples model. Construction: DCF Bear / Base / Bull / Custom sheets.
B3: Pricing date | C3: =PxDate -> 46300 | D3: Ibovespa | E3: =IbovNow -> 208431.92 | F3: Checks | G3: =Checks!C5 -> All checks OK | H3: Horizon | I3: =IF(Horizon=1,"12 months (fair value in 12m)","today") -> 12 months (fair value in 12m)
B5: Scenario levers in use (Assumptions)
C6: Today | D6: Bear | E6: Base | F6: Bull | G6: Custom
B7: Narrative | D7: =Assumptions!D22 -> Moderate populist | E7: =Assumptions!E22 -> Base | F7: =Assumptions!F22 -> Reformist | G7: =Assumptions!G22 -> User-defined
B8: Selic at the end of the horizon | C8: =SelicNow -> 0.1375 | D8: =Assumptions!D23 -> 0.132 | E8: =Assumptions!E23 -> 0.115 | F8: =Assumptions!F23 -> 0.095 | G8: =Assumptions!G23 -> 0.115
B9: 5-year real rate (NTN-B) | C9: =RR5Now -> 0.0676 | D9: =Assumptions!D25 -> 0.085 | E9: =Assumptions!E25 -> 0.0676 | F9: =Assumptions!F25 -> 0.06 | G9: =Assumptions!G25 -> 0.0676
B10: ERP used, Ibovespa level | D10: =Assumptions!D29 -> 0.06 | E10: =Assumptions!E29 -> 0.06 | F10: =Assumptions!F29 -> 0.06 | G10: =Assumptions!G29 -> 0.06
B11: Cost of equity = real rate + ERP, Ibovespa level | D11: =Assumptions!D30 -> 0.145 | E11: =Assumptions!E30 -> 0.1276 | F11: =Assumptions!F30 -> 0.12 | G11: =Assumptions!G30 -> 0.1276
B12: Earnings growth vs consensus path, years 2-5 (pp/yr) | D12: =Assumptions!D31 -> -2 | E12: =Assumptions!E31 -> 0 | F12: =Assumptions!F31 -> 2 | G12: =Assumptions!G31 -> 0
B13: Long-term nominal growth (g) | D13: =Assumptions!D32 -> 0.042 | E13: =Assumptions!E32 -> 0.047 | F13: =Assumptions!F32 -> 0.052 | G13: =Assumptions!G32 -> 0.047
B14: Settings (Assumptions section 4) | C14: ="ERP basis "&CHOOSE(ERPBasis,"1: typed","2: Ibovespa 10y average","3: each box's 10y average")&" · rate convention "&CHOOSE(RateConv,"1: house","2: Fisher")&" · long-term ROE "&CHOOSE(RoeLT,"1: 10y average","2: consensus") -> ERP basis 1: typed · rate convention 1: house · long-term ROE 2: consensus
B15: DCF fair value by box (index pts, at the horizon in H3) and upside
B16: Group | C16: Index points | D16: Bear | E16: Base | F16: Bull | G16: Custom | I16: Upside: Bear | J16: Base | K16: Bull | L16: Custom
B17: Financials | C17: ='DCF Base'!C49 -> 60927.304 | D17: ='DCF Bear'!C68 -> 52444.51 | E17: ='DCF Base'!C68 -> 70757.467 | F17: ='DCF Bull'!C68 -> 89467 | G17: ='DCF Custom'!C68 -> 70757.467 | I17: ='DCF Bear'!C69 -> -0.13922811 | J17: ='DCF Base'!C69 -> 0.16134251 | K17: ='DCF Bull'!C69 -> 0.46842212 | L17: ='DCF Custom'!C69 -> 0.16134251
B18: Defensives | C18: ='DCF Base'!C78 -> 55822.367 | D18: ='DCF Bear'!C97 -> 32005.698 | E18: ='DCF Base'!C97 -> 42151.986 | F18: ='DCF Bull'!C97 -> 51639.749 | G18: ='DCF Custom'!C97 -> 42151.986 | I18: ='DCF Bear'!C98 -> -0.42665102 | J18: ='DCF Base'!C98 -> -0.24489075 | K18: ='DCF Bull'!C98 -> -0.074927277 | L18: ='DCF Custom'!C98 -> -0.24489075
B19: Cyclicals | C19: ='DCF Base'!C107 -> 26271.075 | D19: ='DCF Bear'!C126 -> 18307.282 | E19: ='DCF Base'!C126 -> 24905.989 | F19: ='DCF Bull'!C126 -> 31645.333 | G19: ='DCF Custom'!C126 -> 24905.989 | I19: ='DCF Bear'!C127 -> -0.30313921 | J19: ='DCF Base'!C127 -> -0.051961535 | K19: ='DCF Bull'!C127 -> 0.20456941 | L19: ='DCF Custom'!C127 -> -0.051961535
B20: Commodities | C20: ='DCF Base'!C136 -> 65411.174 | D20: ='DCF Bear'!C155 -> 66822.884 | E20: ='DCF Base'!C155 -> 85902.887 | F20: ='DCF Bull'!C155 -> 104184.28 | G20: ='DCF Custom'!C155 -> 85902.887 | I20: ='DCF Bear'!C156 -> 0.021582082 | J20: ='DCF Base'!C156 -> 0.3132754 | K20: ='DCF Bull'!C156 -> 0.59275971 | L20: ='DCF Custom'!C156 -> 0.3132754
B21: Ibovespa | C21: ='DCF Base'!C27 -> 208431.92 | D21: ='DCF Bear'!C34 -> 169580.37 | E21: ='DCF Base'!C34 -> 223718.33 | F21: ='DCF Bull'!C34 -> 276936.37 | G21: ='DCF Custom'!C34 -> 223718.33 | I21: ='DCF Bear'!C35 -> -0.18639922 | J21: ='DCF Base'!C35 -> 0.073340058 | K21: ='DCF Bull'!C35 -> 0.32866581 | L21: ='DCF Custom'!C35 -> 0.073340058
B22: Memo
B23: Cyclicals ex-WEG & Embraer | C23: ='DCF Base'!C165 -> 16066.52 | D23: ='DCF Bear'!C184 -> 13017.737 | E23: ='DCF Base'!C184 -> 17779.836 | F23: ='DCF Bull'!C184 -> 22714.745 | G23: ='DCF Custom'!C184 -> 17779.836 | I23: ='DCF Bear'!C185 -> -0.18976001 | J23: ='DCF Base'!C185 -> 0.10663891 | K23: ='DCF Bull'!C185 -> 0.41379373 | L23: ='DCF Custom'!C185 -> 0.10663891
B24: WEG & Embraer | C24: ='DCF Base'!C194 -> 10204.555 | D24: ='DCF Bear'!C213 -> 5365.8281 | E24: ='DCF Base'!C213 -> 7139.5859 | F24: ='DCF Bull'!C213 -> 8819.4219 | G24: ='DCF Custom'!C213 -> 7139.5859 | I24: ='DCF Bear'!C214 -> -0.47417325 | J24: ='DCF Base'!C214 -> -0.30035305 | K24: ='DCF Bull'!C214 -> -0.13573676 | L24: ='DCF Custom'!C214 -> -0.30035305
B26: Implied 12m fwd P/E at the horizon (fair value / next 12m earnings) vs today
B27: Group | C27: Today | D27: Bear | E27: Base | F27: Bull | G27: Custom
B28: Financials | C28: ='DCF Base'!C71 -> 9.9676747 | D28: ='DCF Bear'!C70 -> 7.7051116 | E28: ='DCF Base'!C70 -> 9.7581887 | F28: ='DCF Bull'!C70 -> 11.522169 | G28: ='DCF Custom'!C70 -> 9.7581887
B29: Defensives | C29: ='DCF Base'!C100 -> 14.663346 | D29: ='DCF Bear'!C99 -> 6.9711384 | E29: ='DCF Base'!C99 -> 8.7170961 | F29: ='DCF Bull'!C99 -> 10.094805 | G29: ='DCF Custom'!C99 -> 8.7170961
B30: Cyclicals | C30: ='DCF Base'!C129 -> 12.926128 | D30: ='DCF Bear'!C128 -> 7.5749765 | E30: ='DCF Base'!C128 -> 9.6025738 | F30: ='DCF Bull'!C128 -> 11.304248 | G30: ='DCF Custom'!C128 -> 9.6025738
B31: Commodities | C31: ='DCF Base'!C158 -> 6.7361561 | D31: ='DCF Bear'!C157 -> 7.2201177 | E31: ='DCF Base'!C157 -> 8.8829944 | F31: ='DCF Bull'!C157 -> 10.280107 | G31: ='DCF Custom'!C157 -> 8.8829944
B32: Ibovespa | C32: ='DCF Base'!C38 -> 9.6218817 | D32: ='DCF Bear'!C37 -> 7.3508359 | E32: ='DCF Base'!C37 -> 9.187307 | F32: ='DCF Bull'!C37 -> 10.728055 | G32: ='DCF Custom'!C37 -> 9.187307
B34: Implied ERP at today's prices (cost of equity - 5y real rate that makes the DCF = index points)
B35: Group | C35: ERP used (Base) | D35: Bear | E35: Base | F35: Bull | G35: Custom
B36: Financials | C36: ='DCF Base'!C51 -> 0.06 | D36: ='Implied ERP'!$C$7 -> 0.040959388 | E36: ='Implied ERP'!$D$7 -> 0.066374616 | F36: ='Implied ERP'!$E$7 -> 0.082091167 | G36: ='Implied ERP'!$F$7 -> 0.066374616
B37: Defensives | C37: ='DCF Base'!C80 -> 0.06 | D37: ='Implied ERP'!$C$8 -> 0.015094707 | E37: ='Implied ERP'!$D$8 -> 0.037952038 | F37: ='Implied ERP'!$E$8 -> 0.050920125 | G37: ='Implied ERP'!$F$8 -> 0.037952038
B38: Cyclicals | C38: ='DCF Base'!C109 -> 0.06 | D38: ='Implied ERP'!$C$9 -> 0.026174653 | E38: ='Implied ERP'!$D$9 -> 0.051297126 | F38: ='Implied ERP'!$E$9 -> 0.066691219 | G38: ='Implied ERP'!$F$9 -> 0.051297126
B39: Commodities | C39: ='DCF Base'!C138 -> 0.06 | D39: ='Implied ERP'!$C$10 -> 0.056091266 | E39: ='Implied ERP'!$D$10 -> 0.078554438 | F39: ='Implied ERP'!$E$10 -> 0.09112991 | G39: ='Implied ERP'!$F$10 -> 0.078554438
B40: Ibovespa | C40: =Assumptions!E29 -> 0.06 | D40: ='Implied ERP'!$C$11 -> 0.036072978 | E40: ='Implied ERP'!$D$11 -> 0.059938855 | F40: ='Implied ERP'!$E$11 -> 0.073981108 | G40: ='Implied ERP'!$F$11 -> 0.059938855
B42: Implied ERP history in DCF terms (History; 5y real rate, steady state)
B43: Group | C43: 10y average | D43: Std. dev. | E43: Now | F43: Now vs average (sd)
B44: Financials | C44: =History!R8 -> 0.083556934 | D44: =History!R9 -> 0.013433563 | E44: =History!R11 -> 0.055359543 | F44: =History!R12 -> -2.0990255
B45: Defensives | C45: =History!S8 -> 0.040024755 | D45: =History!S9 -> 0.013640071 | E45: =History!S11 -> 0.023114046 | F45: =History!S12 -> -1.2397816
B46: Cyclicals | C46: =History!T8 -> 0.031540174 | D46: =History!T9 -> 0.010180294 | E46: =History!T11 -> 0.034242752 | F46: =History!T12 -> 0.26547148
B47: Commodities | C47: =History!U8 -> 0.10567744 | D47: =History!U9 -> 0.045409909 | E47: =History!U11 -> 0.093813654 | F47: =History!U12 -> -0.26125979
B48: Ibovespa | C48: =History!V8 -> 0.074470831 | D48: =History!V9 -> 0.019220255 | E48: =History!V11 -> 0.056129808 | F48: =History!V12 -> -0.95425498
B50: Terminal value share and contribution to the Ibovespa upside
D51: Bear | E51: Base | F51: Bull | G51: Custom
B52: Terminal value / equity value (Ibovespa) | D52: ='DCF Bear'!C39 -> 0.62906592 | E52: ='DCF Base'!C39 -> 0.72670153 | F52: ='DCF Bull'!C39 -> 0.79535856 | G52: ='DCF Custom'!C39 -> 0.72670153
B53: Contribution: Financials (pp) | D53: ='DCF Bear'!C41 -> -4.0698148 | E53: ='DCF Base'!C41 -> 4.7162468 | F53: ='DCF Bull'!C41 -> 13.692575 | G53: ='DCF Custom'!C41 -> 4.7162468
B54: Contribution: Defensives (pp) | D54: ='DCF Bear'!C42 -> -11.426594 | E54: ='DCF Base'!C42 -> -6.5586793 | F54: ='DCF Bull'!C42 -> -2.006707 | G54: ='DCF Custom'!C42 -> -6.5586793
B55: Contribution: Cyclicals (pp) | D55: ='DCF Bear'!C43 -> -3.8208125 | E55: ='DCF Base'!C43 -> -0.65493106 | F55: ='DCF Bull'!C43 -> 2.5784239 | G55: ='DCF Custom'!C43 -> -0.65493106
B56: Contribution: Commodities (pp) | D56: ='DCF Bear'!C44 -> 0.67729997 | E56: ='DCF Base'!C44 -> 9.8313694 | F56: ='DCF Bull'!C44 -> 18.602289 | G56: ='DCF Custom'!C44 -> 9.8313694
B58: Reference (not linked): multiples model and the house DCF
B59: Ibovespa fair value (index pts) | D59: Bear | E59: Base | F59: Bull
B60: Multiples model, average of methods (Oct-6 table) | D60: 174413.87 | E60: 229231.55 | F60: 294831.51
B61: Multiples model, P/E method | D61: 164103.57 | E61: 228098.91 | F61: 297779.23
B62: House DCF (DCF Ibov 2026_Out.xlsx), fair value 2026 | E62: 202259.2
B63: House DCF: FCFF of the whole index at 13.4% (5y real rate 7.42% on its date + ERP 6%), g 4.7%, value at end-2026; working capital by level, no net debt, terminal value discounted 5 years. Same premises, different cash flows.

Sheet Assumptions
B1: Ibovespa - DCF assumptions
B2: The only sheet to edit: change the pink cells (dotted border); the DCF sheets recalculate.
B3: Legend: | C3: input | D3: assumption | E3: formula
B5: 1. Market snapshot
B6: Pricing date (prices and index weights) | C6: 46300 | H6: Close of Oct-5-2026, the same snapshot as the multiples model.
B7: Ibovespa close (index pts) | C7: 208431.92 | H7: Bloomberg IBOV Index PX_LAST.
B8: Selic target today | C8: 0.1375 | H8: BCB (BZSTSETA Index).
B9: 5-year real rate today (NTN-B) | C9: 0.0676 | H9: ANBIMA, Oct-5 (as in the multiples model). The house model uses the 5y (BZRFB5PY Index, Target!B56). For reference, the 10y (IPCA+ 2035/2037) was 6.86%.
B10: Ibovespa membership date | C10: 46295 | H10: Members and weights: Economatica Ibovespa composition, drifted by price to the pricing date.
B11: Ibovespa close on the membership date (index pts) | C11: 186340.46 | H11: Used only in Checks.
B12: Consensus snapshot date (Bloomberg) | C12: 46302 | H12: BEST_PE_RATIO and BEST_ROE, FY26/FY27/FY28; earnings = price on this date / P/E.
B14: 2. Macro
B15: IPCA, forward year 1 | C15: 0.04 | H15: House Ibovespa model (DCF Ibov 2026_Out.xlsx, Target sheet): 2027 4.0%. Used only with the Fisher convention (RateConv = 2).
B16: IPCA, forward year 2 | C16: 0.04 | H16: House model: 2028 4.0%.
B17: IPCA, long term (year 3 onwards, terminal and history) | C17: 0.04 | H17: House model long-term inflation 4.0% (Target!B63).
B18: Share of FY2026 still ahead on the pricing date | C18: =(DATE(2026,12,31)-PxDate)/365 -> 0.23835616 | H18: Forward year 1 = this share of FY26 + the rest of FY27; year 2 = the same split of FY27 and FY28 (12m-forward convention).
B20: 3. Scenario levers
B21: Lever | C21: Today | D21: Bear | E21: Base | F21: Bull | G21: Custom | H21: How it is used
B22: Narrative | D22: Moderate populist | E22: Base | F22: Reformist | G22: User-defined | H22: Labels only.
B23: Selic at the end of the horizon | C23: =SelicNow -> 0.1375 | D23: 0.132 | E23: 0.115 | F23: 0.095 | G23: 0.115 | H23: Same scenarios as the multiples model; drives the rate-driven change in earnings (section 5).
B24: Selic cut vs today (pp; positive = cut) | D24: =(SelicNow-D23)*100 -> 0.55 | E24: =(SelicNow-E23)*100 -> 2.25 | F24: =(SelicNow-F23)*100 -> 4.25 | G24: =(SelicNow-G23)*100 -> 2.25 | H24: Formula: (Selic today - Selic in the scenario) x 100.
B25: 5-year real rate (NTN-B) | C25: =RR5Now -> 0.0676 | D25: 0.085 | E25: =RR5Now -> 0.0676 | F25: 0.06 | G25: =RR5Now -> 0.0676 | H25: As the house model (Target sheet): bear 8.5%, base = today's 5y real rate, bull 6.0%.
B26: ERP, typed (used when the ERP basis = 1) | D26: 0.06 | E26: 0.06 | F26: 0.06 | G26: 0.06 | H26: House ERP 6.0% (Target!B57), the same in every scenario.
B27: ERP shift (pp, added to the ERP of any basis) | D27: 0 | E27: 0 | F27: 0 | G27: 0 | H27: Added to the ERP of the basis in use (typed, Ibovespa or box 10-year average).
B28: ERP move in std. dev. of its history (k; +1 = ERP 1 sd lower) | D28: 0 | E28: 0 | F28: 0 | G28: 0 | H28: Mirrors the multiples model (target multiple = 10y average + k x sd): ERP moves by -k x the sd of the 10-year implied ERP (Ibovespa; each box with basis 3).
B29: ERP used, Ibovespa level | D29: =CHOOSE(ERPBasis,D26,ErpHistIbov,ErpHistIbov)+D27/100-D28*ErpSdIbov -> 0.06 | E29: =CHOOSE(ERPBasis,E26,ErpHistIbov,ErpHistIbov)+E27/100-E28*ErpSdIbov -> 0.06 | F29: =CHOOSE(ERPBasis,F26,ErpHistIbov,ErpHistIbov)+F27/100-F28*ErpSdIbov -> 0.06 | G29: =CHOOSE(ERPBasis,G26,ErpHistIbov,ErpHistIbov)+G27/100-G28*ErpSdIbov -> 0.06 | H29: Basis ERP (typed, or the Ibovespa's 10-year average) + shift - k x sd. With basis 3 each box uses its own average and sd (DCF sheets).
B30: Cost of equity, Ibovespa level = real rate + ERP | D30: =D25+D29 -> 0.145 | E30: =E25+E29 -> 0.1276 | F30: =F25+F29 -> 0.12 | G30: =G25+G29 -> 0.1276 | H30: RateConv 1 (house): the discount rate of the nominal cash flows, as Target!B55. RateConv 2 (Fisher): turned nominal year by year with the IPCA.
B31: Earnings growth vs consensus path, years 2-5 (pp per year) | D31: -2 | E31: 0 | F31: 2 | G31: 0 | H31: Added to the earnings growth of every box in years 2-5 (consensus in year 2, then the path to the long term); bear -2 / bull +2 pp (proposal). The terminal grows at g.
B32: Long-term nominal growth (g) | D32: 0.042 | E32: 0.047 | F32: 0.052 | G32: 0.047 | H32: Base = house perpetuity growth 4.7% (Target!B54), nominal. Bear / bull -/+ 0.5 pp (proposal). Earnings growth reaches it by GrowthYear.
B33: Long-term ROE vs the box's 10-year average (pp) | D33: 0 | E33: 0 | F33: 0 | G33: 0 | H33: Shifts every box's long-term ROE (10-year average of its 12m fwd ROE, History).
B35: 4. Settings
B36: Setting | C36: Value | H36: Notes
B37: Discount-rate convention: 1 = house (real rate + ERP), 2 = Fisher (with IPCA) | C37: 1 | H37: 1: real rate + ERP discounts the nominal cash flows, as the house model (Target!B55 = BZRFB5PY + ERP). 2: (1 + real rate + ERP) x (1 + IPCA) - 1. Same ERP, about 4 pp more discount rate.
B38: ERP basis: 1 = typed, 2 = Ibovespa 10y average, 3 = each box's 10y average | C38: 1 | H38: 1 = the house's 6.0%. 2 and 3: implied ERP measured each month in the same convention (History): Ke = g + (1 - g / ROE) / P/E, minus the 5y real rate.
B39: Valuation horizon: 0 = today, 1 = 12 months (end of forward year 1) | C39: 1 | H39: 1: fair value in 12 months = value today x (1 + year-1 discount rate) - year-1 FCFE (paid out during the year), as a 12-month target price. 0: value today.
B40: Long-term ROE: 1 = box's 10-year average, 2 = consensus year 2 (no mean reversion) | C40: 2 | H40: 1: ROE converges to the box's 10-year average 12m fwd ROE (History). 2: ROE stays at the consensus year-2 level, as the house model keeps consensus profitability.
B41: Long-term nominal growth behind the historical implied ERP | C41: 0.047 | H41: g used to read the ERP out of each month's P/E and ROE (History); house 4.7%.
B42: ROE and ERP history window: first month | C42: 42674 | H42: Averages over the window (any day counts the whole month).
B43: ROE and ERP history window: last month | C43: 46295
B44: Year by which growth reaches the long term | C44: 5 | H44: Growth converges linearly from the consensus year-2 growth (years 3 to GrowthYear). 3-5.
B45: Year by which ROE reaches the long term | C45: 5 | H45: ROE converges linearly from the consensus year-2 ROE (years 3 to RoeYear). 3-5.
B46: Apply the rate-driven change in earnings (1 = yes, 0 = no) | C46: 1 | H46: 1: years 1-2 earnings move with the Selic as in the multiples model (section 5). 0: consensus as is.
B47: P/E: lowest valid value | C47: 1 | H47: Members with any FY26-FY28 P/E or ROE outside the ranges are left out and the box is scaled to 100% of its points.
B48: P/E: highest valid value | C48: 100
B49: ROE: lowest valid value | C49: 0.01
B50: ROE: highest valid value | C50: 1
B51: Explicit forecast years | C51: 5 | H51: Fixed by the layout of the DCF sheets (years 1-5 + terminal), like the house model (4 years after its value date + terminal). NY in build_dcf.py.
B53: 5. Inputs from the multiples model (Ibov_valuation_by_box_model_XP.xlsx)
B54: Box | C54: EPS change per -100bp of Selic | H54: Source
B55: Financials | C55: 0.027617753 | H55: Rates & EPS sheet of the multiples model: Ibovespa +2.07% per -100bp, split by box return beta to the 2y pre (Oct-6).
B56: Defensives | C56: 0.021334944
B57: Cyclicals | C57: 0.033008845
B58: Commodities | C58: 0.013778845
B59: Cyclicals ex-WEG & Embraer | C59: 0.039614274
B60: WEG & Embraer | C60: 0.010232818
B62: 6. Optional overrides (leave blank to use the model rule)
B63: A number typed here replaces the model value for that box and scenario. Checks counts the overrides in use.
B64: Box | D64: Bear | E64: Base | F64: Bull | G64: Custom
B65: Long-term ROE (%)
B66: Financials
B67: Defensives
B68: Cyclicals
B69: Commodities
B70: Cyclicals ex-WEG & Embraer
B71: WEG & Embraer
B72: Long-term nominal growth (%)
B73: Financials
B74: Defensives
B75: Cyclicals
B76: Commodities
... B87: 7. Classification
B88: XP-adjusted GICS sector | C88: Box
B89: Financials | C89: Financials
B90: Consumer Staples | C90: Defensives
B91: Health Care | C91: Defensives
B92: Utilities | C92: Defensives
B93: Communication Services | C93: Defensives
B94: Consumer Discretionary | C94: Cyclicals
B95: Industrials | C95: Cyclicals
B96: Information Technology | C96: Cyclicals
B97: Real Estate | C97: Cyclicals
B98: Energy | C98: Commodities
B99: Materials | C99: Commodities
B101: Global industrials (shown apart as a memo)
B102: WEGE3
B103: EMBJ3

Sheet DCF Base
B1: Ibovespa - DCF, Base case
B2: FCFE by box in Ibovespa points. Scenario levers: Assumptions column E. Years 1-5 + terminal; Ibovespa = sum of the four boxes.
B3: Legend: | C3: input | D3: assumption | E3: formula
B5: Scenario parameters (Base; Assumptions column E)
B6: 5-year real rate (NTN-B) | C6: =Assumptions!E25 -> 0.0676
B7: ERP, typed (ERP basis 1) | C7: =Assumptions!E26 -> 0.06
B8: ERP shift (pp) | C8: =Assumptions!E27 -> 0
B9: ERP move in std. dev. of its history (k) | C9: =Assumptions!E28 -> 0
B10: ERP basis (1 typed, 2 Ibovespa 10y average, 3 each box's 10y average) | C10: =ERPBasis -> 1
B11: Earnings growth vs consensus path, years 2-5 (pp per year) | C11: =Assumptions!E31 -> 0
B12: Long-term nominal growth (default) | C12: =Assumptions!E32 -> 0.047
B13: Long-term ROE vs 10y average (pp) | C13: =Assumptions!E33 -> 0
B14: Selic cut vs today (pp) | C14: =Assumptions!E24 -> 2.25
B15: Discount-rate convention (1 house: real rate + ERP; 2 Fisher: with IPCA) | C15: =RateConv -> 1
B17: Timeline (shared by every box)
C18: Today | D18: Year 1 | E18: Year 2 | F18: Year 3 | G18: Year 4 | H18: Year 5 | I18: Terminal | J18: How it is calculated
B19: Year (t) | C19: 0 | D19: 1 | E19: 2 | F19: 3 | G19: 4 | H19: 5
B20: End of the forward year | C20: =PxDate -> 46300 | D20: =EDATE(PxDate,12*D19) -> 46665 | E20: =EDATE(PxDate,12*E19) -> 47031 | F20: =EDATE(PxDate,12*F19) -> 47396 | G20: =EDATE(PxDate,12*G19) -> 47761 | H20: =EDATE(PxDate,12*H19) -> 48126
B21: Inflation (IPCA) | D21: =IPCA1 -> 0.04 | E21: =IPCA2 -> 0.04 | F21: =IPCALT -> 0.04 | G21: =IPCALT -> 0.04 | H21: =IPCALT -> 0.04 | I21: =IPCALT -> 0.04
B22: Price index (today = 1) | C22: 1 | D22: =C22*(1+D21) -> 1.04 | E22: =D22*(1+E21) -> 1.0816 | F22: =E22*(1+F21) -> 1.124864 | G22: =F22*(1+G21) -> 1.1698586 | H22: =G22*(1+H21) -> 1.2166529 | J22: Cash flows are nominal (consensus). House convention: discounted at real rate + ERP. Fisher: at (1 + real rate + ERP) x (1 + IPCA) - 1.
B23: Deflator for discounting (1 under the house convention) | C23: 1 | D23: =IF(RateConv=1,1,D22) -> 1 | E23: =IF(RateConv=1,1,E22) -> 1 | F23: =IF(RateConv=1,1,F22) -> 1 | G23: =IF(RateConv=1,1,G22) -> 1 | H23: =IF(RateConv=1,1,H22) -> 1 | J23: Used by the closed-form checks: FCFE / deflator discounted at (1 + real rate + ERP) gives the same value under either convention.
B25: Ibovespa = sum of the four boxes (Base)
C26: Today | D26: Year 1 | E26: Year 2 | F26: Year 3 | G26: Year 4 | H26: Year 5 | I26: Terminal | J26: How it is calculated
B27: Index points | C27: =C49+C78+C107+C136 -> 208431.92
B28: Earnings (index pts) | D28: =D58+D87+D116+D145 -> 22676.853 | E28: =E58+E87+E116+E145 -> 24350.806 | F28: =F58+F87+F116+F145 -> 26086.104 | G28: =G58+G87+G116+G145 -> 27684.137 | H28: =H58+H87+H116+H145 -> 28985.291
B29: Book value at the start of the year | D29: =D60+D89+D118+D147 -> 126386.42 | E29: =E60+E89+E118+E147 -> 137942.6 | F29: =F60+F89+F118+F147 -> 148132.24 | G29: =G60+G89+G118+G147 -> 157415.3 | H29: =H60+H89+H118+H147 -> 164813.82 | I29: =I60+I89+I118+I147 -> 172560.07
B30: Free cash flow to equity (FCFE) | D30: =D62+D91+D120+D149 -> 11120.667 | E30: =E62+E91+E120+E149 -> 14161.17 | F30: =F62+F91+F120+F149 -> 16803.038 | G30: =G62+G91+G120+G149 -> 20285.618 | H30: =H62+H91+H120+H149 -> 21239.042
B31: Present value of FCFE | C31: =C64+C93+C122+C151 -> 56918.357 | D31: =D64+D93+D122+D151 -> 9862.245 | E31: =E64+E93+E122+E151 -> 11137.533 | F31: =F64+F93+F122+F151 -> 11719.865 | G31: =G64+G93+G122+G151 -> 12547.811 | H31: =H64+H93+H122+H151 -> 11650.903
B32: Present value of the terminal value | C32: =C66+C95+C124+C153 -> 151346.1
B33: Equity value today (index pts) | C33: =C67+C96+C125+C154 -> 208264.45
B34: Fair value at the horizon (index pts) | C34: =C68+C97+C126+C155 -> 223718.33
B35: Upside (fair value / index points today - 1) | C35: =C34/C27-1 -> 0.073340058
B36: ROE (sum of earnings / sum of book value) | D36: =D28/D29 -> 0.17942476 | E36: =E28/E29 -> 0.17652854 | F36: =F28/F29 -> 0.17610011 | G36: =G28/G29 -> 0.17586687 | H36: =H28/H29 -> 0.17586687
B37: Implied 12m fwd P/E at the horizon (fair value / next 12m earnings) | C37: =C34/IF(Horizon=1,E28,D28) -> 9.187307
B38: 12m fwd P/E today (consensus year-1 earnings) | C38: ='Boxes Now'!Y10 -> 9.6218817
B39: Terminal value / equity value | C39: =C32/C33 -> 0.72670153
B40: Contribution to the Ibovespa upside (pp)
B41: Financials | C41: =(C68-C49)/C27*100 -> 4.7162468
B42: Defensives | C42: =(C97-C78)/C27*100 -> -6.5586793
B43: Cyclicals | C43: =(C126-C107)/C27*100 -> -0.65493106
B44: Commodities | C44: =(C155-C136)/C27*100 -> 9.8313694
B47: Financials
C48: Today | D48: Year 1 | E48: Year 2 | F48: Year 3 | G48: Year 4 | H48: Year 5 | I48: Terminal | J48: How it is calculated
B49: Index points | C49: ='Boxes Now'!F6 -> 60927.304 | J49: Boxes Now (members' weight x Ibovespa close).
B50: Earnings change from the Selic scenario (years 1-2) | C50: =IF(UseEPS=1,Assumptions!$C$55*$C$14,0) -> 0.062139945 | J50: Box EPS sensitivity to the Selic (Assumptions section 5) x Selic cut; applied to years 1 and 2 (0 if UseEPS = 0).
B51: Equity risk premium (ERP) | C51: =IF(ISNUMBER(Assumptions!E80),Assumptions!E80,CHOOSE($C$10,$C$7,ErpHistIbov,History!$R$8)+$C$8/100-$C$9*CHOOSE($C$10,ErpSdIbov,ErpSdIbov,History!$R$9)) -> 0.06 | J51: Override if typed; else the basis ERP (1 typed, 2 Ibovespa 10y average, 3 this box's 10y average) + shift - k x sd of its history (History).
B52: Cost of equity = real rate + ERP | C52: =$C$6+C51 -> 0.1276 | J52: 5y real rate (scenario) + ERP. House convention: this is the discount rate (Target!B55).
B53: Discount rate of the nominal cash flows | D53: =IF(RateConv=1,$C52,(1+$C52)*(1+D$21)-1) -> 0.1276 | E53: =IF(RateConv=1,$C52,(1+$C52)*(1+E$21)-1) -> 0.1276 | F53: =IF(RateConv=1,$C52,(1+$C52)*(1+F$21)-1) -> 0.1276 | G53: =IF(RateConv=1,$C52,(1+$C52)*(1+G$21)-1) -> 0.1276 | H53: =IF(RateConv=1,$C52,(1+$C52)*(1+H$21)-1) -> 0.1276 | I53: =IF(RateConv=1,$C52,(1+$C52)*(1+IPCALT)-1) -> 0.1276 | J53: House convention: = cost of equity. Fisher: (1 + cost of equity) x (1 + IPCA of the year) - 1; terminal uses the long-term IPCA.
B54: Discount factor | C54: 1 | D54: =C54/(1+D53) -> 0.8868393 | E54: =D54/(1+E53) -> 0.78648395 | F54: =E54/(1+F53) -> 0.69748488 | G54: =F54/(1+G53) -> 0.61855701 | H54: =G54/(1+H53) -> 0.54856067 | J54: Product of 1 / (1 + nominal cost of equity) up to the year.
B55: Long-term ROE | C55: =IF(ISNUMBER(Assumptions!E66),Assumptions!E66,CHOOSE(RoeLT,'Boxes Now'!Z6,'Boxes Now'!W6)+$C$13/100) -> 0.19949374 | J55: RoeLT 1: 10-year average of the box's 12m fwd ROE (History); 2: consensus year-2 ROE. Plus the shift in Assumptions, or the override.
B56: Long-term nominal growth | C56: =IF(ISNUMBER(Assumptions!E73),Assumptions!E73,$C$12) -> 0.047 | J56: Long-term nominal growth of the scenario (house 4.7%), or the override.
B57: Earnings growth | E57: ='Boxes Now'!$X$6+$C$11/100 -> 0.11687154 | F57: ='Boxes Now'!$X$6+($C56-'Boxes Now'!$X$6)*MIN(1,(F$19-2)/(GrowthYear-2))+$C$11/100 -> 0.093581024 | G57: ='Boxes Now'!$X$6+($C56-'Boxes Now'!$X$6)*MIN(1,(G$19-2)/(GrowthYear-2))+$C$11/100 -> 0.070290512 | H57: ='Boxes Now'!$X$6+($C56-'Boxes Now'!$X$6)*MIN(1,(H$19-2)/(GrowthYear-2))+$C$11/100 -> 0.047 | I57: =$C56 -> 0.047 | J57: Year 2 = consensus; converges linearly to the long-term growth by GrowthYear; + the scenario's growth add-on in years 2-5; terminal = long term.
B58: Earnings (index pts) | D58: ='Boxes Now'!R6*(1+$C50) -> 6492.3189 | E58: =D58*(1+E57) -> 7251.0862 | F58: =E58*(1+F57) -> 7929.6503 | G58: =F58*(1+G57) -> 8487.0295 | H58: =G58*(1+H57) -> 8885.9199 | I58: =H58*(1+I57) -> 9303.5581 | J58: Year 1 = consensus blended to the forward year (Boxes Now) x (1 + change from rates); then grows at the row above.
B59: ROE | D59: ='Boxes Now'!V6 -> 0.19352714 | E59: ='Boxes Now'!W6 -> 0.19949374 | F59: =$E59+($C55-$E59)*MIN(1,(F$19-2)/(RoeYear-2)) -> 0.19949374 | G59: =$E59+($C55-$E59)*MIN(1,(G$19-2)/(RoeYear-2)) -> 0.19949374 | H59: =$E59+($C55-$E59)*MIN(1,(H$19-2)/(RoeYear-2)) -> 0.19949374 | I59: =$C55 -> 0.19949374 | J59: Years 1-2 = consensus; converges linearly to the long-term ROE by RoeYear (Assumptions).
B60: Book value at the start of the year (index pts) | D60: =D58/D59 -> 33547.33 | E60: =E58/E59 -> 36347.437 | F60: =F58/F59 -> 39748.868 | G60: =G58/G59 -> 42542.836 | H60: =H58/H59 -> 44542.349 | I60: =I58/I59 -> 46635.84 | J60: Equity at the start of the year needed to earn the year's earnings at the year's ROE = earnings / ROE.
B61: Increase in book value during the year | D61: =E60-D60 -> 2800.1069 | E61: =F60-E60 -> 3401.4304 | F61: =G60-F60 -> 2793.9683 | G61: =H60-G60 -> 1999.5133 | H61: =I60-H60 -> 2093.4904 | J61: Book value at the start of next year - at the start of this year = earnings retained to fund growth.
B62: Free cash flow to equity (FCFE) | D62: =D58-D61 -> 3692.212 | E62: =E58-E61 -> 3849.6558 | F62: =F58-F61 -> 5135.682 | G62: =G58-G61 -> 6487.5162 | H62: =H58-H61 -> 6792.4294 | J62: Earnings - increase in book value (what can be paid out). In the long term = earnings x (1 - g / ROE).
B63: FCFE / earnings | D63: =D62/D58 -> 0.56870466 | E63: =E62/E58 -> 0.53090747 | F63: =F62/F58 -> 0.64765555 | G63: =G62/G58 -> 0.76440364 | H63: =H62/H58 -> 0.76440364
B64: Present value of FCFE | C64: =SUM(D64:H64) -> 17623.11 | D64: =D62*D54 -> 3274.3988 | E64: =E62*E54 -> 3027.6925 | F64: =F62*F54 -> 3582.0606 | G64: =G62*G54 -> 4012.8986 | H64: =H62*H54 -> 3726.0596 | J64: FCFE x discount factor. 'Today' = sum of years 1-5.
B65: Terminal value at the end of year 5 | I65: =I58*(1-I57/I59)/(I53-I57) -> 88234.164 | J65: Year-11 earnings x (1 - g / ROE) / (Ke - g), nominal long-term values (Gordon growth).
B66: Present value of the terminal value | C66: =I66 -> 48401.792 | I66: =I65*H54 -> 48401.792
B67: Equity value today (index pts) | C67: =C64+C66 -> 66024.902 | J67: Present value of FCFE (years 1-5) + present value of the terminal value.
B68: Fair value at the horizon (index pts) | C68: =IF(Horizon=1,C67*(1+D53)-D62,C67) -> 70757.467 | J68: Horizon 1: value today x (1 + year-1 discount rate) - year-1 FCFE (paid out during the year) = value in 12 months. Horizon 0: value today.
B69: Upside (fair value / index points today - 1) | C69: =C68/C49-1 -> 0.16134251
B70: Implied 12m fwd P/E at the horizon (fair value / next 12m earnings) | C70: =C68/IF(Horizon=1,E58,D58) -> 9.7581887
B71: 12m fwd P/E today (consensus year-1 earnings) | C71: ='Boxes Now'!Y6 -> 9.9676747 | J71: Index points / consensus year-1 earnings (without the change from rates).
B72: Terminal value / equity value | C72: =C66/C67 -> 0.73308389
B73: FCFE / deflator (for Implied ERP) | D73: =D62/D$23 -> 3692.212 | E73: =E62/E$23 -> 3849.6558 | F73: =F62/F$23 -> 5135.682 | G73: =G62/G$23 -> 6487.5162 | H73: =H62/H$23 -> 6792.4294 | J73: FCFE / deflator (timeline): used by Implied ERP and Sensitivity to re-discount the same cash flows at other rates.
B76: Defensives
C77: Today | D77: Year 1 | E77: Year 2 | F77: Year 3 | G77: Year 4 | H77: Year 5 | I77: Terminal | J77: How it is calculated
B78: Index points | C78: ='Boxes Now'!F7 -> 55822.367 | J78: Boxes Now (members' weight x Ibovespa close).
B79: Earnings change from the Selic scenario (years 1-2) | C79: =IF(UseEPS=1,Assumptions!$C$56*$C$14,0) -> 0.048003624 | J79: Box EPS sensitivity to the Selic (Assumptions section 5) x Selic cut; applied to years 1 and 2 (0 if UseEPS = 0).
B80: Equity risk premium (ERP) | C80: =IF(ISNUMBER(Assumptions!E81),Assumptions!E81,CHOOSE($C$10,$C$7,ErpHistIbov,History!$S$8)+$C$8/100-$C$9*CHOOSE($C$10,ErpSdIbov,ErpSdIbov,History!$S$9)) -> 0.06 | J80: Override if typed; else the basis ERP (1 typed, 2 Ibovespa 10y average, 3 this box's 10y average) + shift - k x sd of its history (History).
B81: Cost of equity = real rate + ERP | C81: =$C$6+C80 -> 0.1276 | J81: 5y real rate (scenario) + ERP. House convention: this is the discount rate (Target!B55).
B82: Discount rate of the nominal cash flows | D82: =IF(RateConv=1,$C81,(1+$C81)*(1+D$21)-1) -> 0.1276 | E82: =IF(RateConv=1,$C81,(1+$C81)*(1+E$21)-1) -> 0.1276 | F82: =IF(RateConv=1,$C81,(1+$C81)*(1+F$21)-1) -> 0.1276 | G82: =IF(RateConv=1,$C81,(1+$C81)*(1+G$21)-1) -> 0.1276 | H82: =IF(RateConv=1,$C81,(1+$C81)*(1+H$21)-1) -> 0.1276 | I82: =IF(RateConv=1,$C81,(1+$C81)*(1+IPCALT)-1) -> 0.1276 | J82: House convention: = cost of equity. Fisher: (1 + cost of equity) x (1 + IPCA of the year) - 1; terminal uses the long-term IPCA.
B83: Discount factor | C83: 1 | D83: =C83/(1+D82) -> 0.8868393 | E83: =D83/(1+E82) -> 0.78648395 | F83: =E83/(1+F82) -> 0.69748488 | G83: =F83/(1+G82) -> 0.61855701 | H83: =G83/(1+H82) -> 0.54856067 | J83: Product of 1 / (1 + nominal cost of equity) up to the year.
B84: Long-term ROE | C84: =IF(ISNUMBER(Assumptions!E67),Assumptions!E67,CHOOSE(RoeLT,'Boxes Now'!Z7,'Boxes Now'!W7)+$C$13/100) -> 0.14793968 | J84: RoeLT 1: 10-year average of the box's 12m fwd ROE (History); 2: consensus year-2 ROE. Plus the shift in Assumptions, or the override.
B85: Long-term nominal growth | C85: =IF(ISNUMBER(Assumptions!E74),Assumptions!E74,$C$12) -> 0.047 | J85: Long-term nominal growth of the scenario (house 4.7%), or the override.
B86: Earnings growth | E86: ='Boxes Now'!$X$7+$C$11/100 -> 0.21201573 | F86: ='Boxes Now'!$X$7+($C85-'Boxes Now'!$X$7)*MIN(1,(F$19-2)/(GrowthYear-2))+$C$11/100 -> 0.15701049 | G86: ='Boxes Now'!$X$7+($C85-'Boxes Now'!$X$7)*MIN(1,(G$19-2)/(GrowthYear-2))+$C$11/100 -> 0.10200524 | H86: ='Boxes Now'!$X$7+($C85-'Boxes Now'!$X$7)*MIN(1,(H$19-2)/(GrowthYear-2))+$C$11/100 -> 0.047 | I86: =$C85 -> 0.047 | J86: Year 2 = consensus; converges linearly to the long-term growth by GrowthYear; + the scenario's growth add-on in years 2-5; terminal = long term.
B87: Earnings (index pts) | D87: ='Boxes Now'!R7*(1+$C79) -> 3989.679 | E87: =D87*(1+E86) -> 4835.5537 | F87: =E87*(1+F86) -> 5594.7863 | G87: =F87*(1+G86) -> 6165.4838 | H87: =G87*(1+H86) -> 6455.2616 | I87: =H87*(1+I86) -> 6758.6589 | J87: Year 1 = consensus blended to the forward year (Boxes Now) x (1 + change from rates); then grows at the row above.
B88: ROE | D88: ='Boxes Now'!V7 -> 0.1309171 | E88: ='Boxes Now'!W7 -> 0.14793968 | F88: =$E88+($C84-$E88)*MIN(1,(F$19-2)/(RoeYear-2)) -> 0.14793968 | G88: =$E88+($C84-$E88)*MIN(1,(G$19-2)/(RoeYear-2)) -> 0.14793968 | H88: =$E88+($C84-$E88)*MIN(1,(H$19-2)/(RoeYear-2)) -> 0.14793968 | I88: =$C84 -> 0.14793968 | J88: Years 1-2 = consensus; converges linearly to the long-term ROE by RoeYear (Assumptions).
B89: Book value at the start of the year (index pts) | D89: =D87/D88 -> 30474.85 | E89: =E87/E88 -> 32685.982 | F89: =F87/F88 -> 37818.024 | G89: =G87/G88 -> 41675.661 | H89: =H87/H88 -> 43634.417 | I89: =I87/I88 -> 45685.235 | J89: Equity at the start of the year needed to earn the year's earnings at the year's ROE = earnings / ROE.
B90: Increase in book value during the year | D90: =E89-D89 -> 2211.1321 | E90: =F89-E89 -> 5132.042 | F90: =G89-F89 -> 3857.6368 | G90: =H89-G89 -> 1958.7561 | H90: =I89-H89 -> 2050.8176 | J90: Book value at the start of next year - at the start of this year = earnings retained to fund growth.
B91: Free cash flow to equity (FCFE) | D91: =D87-D90 -> 1778.5469 | E91: =E87-E90 -> -296.48831 | F91: =F87-F90 -> 1737.1495 | G91: =G87-G90 -> 4206.7278 | H91: =H87-H90 -> 4404.444 | J91: Earnings - increase in book value (what can be paid out). In the long term = earnings x (1 - g / ROE).
B92: FCFE / earnings | D92: =D91/D87 -> 0.44578696 | E92: =E91/E87 -> -0.061314243 | F92: =F91/F87 -> 0.31049435 | G92: =G91/G87 -> 0.68230294 | H92: =H91/H87 -> 0.68230294
B93: Present value of FCFE | C93: =SUM(D93:H93) -> 7573.9432 | D93: =D91*D83 -> 1577.2853 | E93: =E91*E83 -> -233.1833 | F93: =F91*F83 -> 1211.6355 | G93: =G91*G83 -> 2602.1009 | H93: =H91*H83 -> 2416.1047 | J93: FCFE x discount factor. 'Today' = sum of years 1-5.
B94: Terminal value at the end of year 5 | I94: =I87*(1-I86/I88)/(I82-I86) -> 57214.055 | J94: Year-11 earnings x (1 - g / ROE) / (Ke - g), nominal long-term values (Gordon growth).
B95: Present value of the terminal value | C95: =I95 -> 31385.38 | I95: =I94*H83 -> 31385.38
B96: Equity value today (index pts) | C96: =C93+C95 -> 38959.323 | J96: Present value of FCFE (years 1-5) + present value of the terminal value.
B97: Fair value at the horizon (index pts) | C97: =IF(Horizon=1,C96*(1+D82)-D91,C96) -> 42151.986 | J97: Horizon 1: value today x (1 + year-1 discount rate) - year-1 FCFE (paid out during the year) = value in 12 months. Horizon 0: value today.
B98: Upside (fair value / index points today - 1) | C98: =C97/C78-1 -> -0.24489075
B99: Implied 12m fwd P/E at the horizon (fair value / next 12m earnings) | C99: =C97/IF(Horizon=1,E87,D87) -> 8.7170961
B100: 12m fwd P/E today (consensus year-1 earnings) | C100: ='Boxes Now'!Y7 -> 14.663346 | J100: Index points / consensus year-1 earnings (without the change from rates).
B101: Terminal value / equity value | C101: =C95/C96 -> 0.80559356
B102: FCFE / deflator (for Implied ERP) | D102: =D91/D$23 -> 1778.5469 | E102: =E91/E$23 -> -296.48831 | F102: =F91/F$23 -> 1737.1495 | G102: =G91/G$23 -> 4206.7278 | H102: =H91/H$23 -> 4404.444 | J102: FCFE / deflator (timeline): used by Implied ERP and Sensitivity to re-discount the same cash flows at other rates.
B105: Cyclicals
C106: Today | D106: Year 1 | E106: Year 2 | F106: Year 3 | G106: Year 4 | H106: Year 5 | I106: Terminal | J106: How it is calculated
B107: Index points | C107: ='Boxes Now'!F8 -> 26271.075 | J107: Boxes Now (members' weight x Ibovespa close).
B108: Earnings change from the Selic scenario (years 1-2) | C108: =IF(UseEPS=1,Assumptions!$C$57*$C$14,0) -> 0.074269902 | J108: Box EPS sensitivity to the Selic (Assumptions section 5) x Selic cut; applied to years 1 and 2 (0 if UseEPS = 0).
B109: Equity risk premium (ERP) | C109: =IF(ISNUMBER(Assumptions!E82),Assumptions!E82,CHOOSE($C$10,$C$7,ErpHistIbov,History!$T$8)+$C$8/100-$C$9*CHOOSE($C$10,ErpSdIbov,ErpSdIbov,History!$T$9)) -> 0.06 | J109: Override if typed; else the basis ERP (1 typed, 2 Ibovespa 10y average, 3 this box's 10y average) + shift - k x sd of its history (History).
...

Sheet DCF Bear
B1: Ibovespa - DCF, Bear case
B2: FCFE by box in Ibovespa points. Scenario levers: Assumptions column D. Years 1-5 + terminal; Ibovespa = sum of the four boxes.
B3: Legend: | C3: input | D3: assumption | E3: formula
B5: Scenario parameters (Bear; Assumptions column D)
B6: 5-year real rate (NTN-B) | C6: =Assumptions!D25 -> 0.085
B7: ERP, typed (ERP basis 1) | C7: =Assumptions!D26 -> 0.06
B8: ERP shift (pp) | C8: =Assumptions!D27 -> 0
B9: ERP move in std. dev. of its history (k) | C9: =Assumptions!D28 -> 0
B10: ERP basis (1 typed, 2 Ibovespa 10y average, 3 each box's 10y average) | C10: =ERPBasis -> 1
B11: Earnings growth vs consensus path, years 2-5 (pp per year) | C11: =Assumptions!D31 -> -2
B12: Long-term nominal growth (default) | C12: =Assumptions!D32 -> 0.042
B13: Long-term ROE vs 10y average (pp) | C13: =Assumptions!D33 -> 0
B14: Selic cut vs today (pp) | C14: =Assumptions!D24 -> 0.55
B15: Discount-rate convention (1 house: real rate + ERP; 2 Fisher: with IPCA) | C15: =RateConv -> 1
B17: Timeline (shared by every box)
C18: Today | D18: Year 1 | E18: Year 2 | F18: Year 3 | G18: Year 4 | H18: Year 5 | I18: Terminal | J18: How it is calculated
B19: Year (t) | C19: 0 | D19: 1 | E19: 2 | F19: 3 | G19: 4 | H19: 5
B20: End of the forward year | C20: =PxDate -> 46300 | D20: =EDATE(PxDate,12*D19) -> 46665 | E20: =EDATE(PxDate,12*E19) -> 47031 | F20: =EDATE(PxDate,12*F19) -> 47396 | G20: =EDATE(PxDate,12*G19) -> 47761 | H20: =EDATE(PxDate,12*H19) -> 48126
B21: Inflation (IPCA) | D21: =IPCA1 -> 0.04 | E21: =IPCA2 -> 0.04 | F21: =IPCALT -> 0.04 | G21: =IPCALT -> 0.04 | H21: =IPCALT -> 0.04 | I21: =IPCALT -> 0.04
B22: Price index (today = 1) | C22: 1 | D22: =C22*(1+D21) -> 1.04 | E22: =D22*(1+E21) -> 1.0816 | F22: =E22*(1+F21) -> 1.124864 | G22: =F22*(1+G21) -> 1.1698586 | H22: =G22*(1+H21) -> 1.2166529 | J22: Cash flows are nominal (consensus). House convention: discounted at real rate + ERP. Fisher: at (1 + real rate + ERP) x (1 + IPCA) - 1.
B23: Deflator for discounting (1 under the house convention) | C23: 1 | D23: =IF(RateConv=1,1,D22) -> 1 | E23: =IF(RateConv=1,1,E22) -> 1 | F23: =IF(RateConv=1,1,F22) -> 1 | G23: =IF(RateConv=1,1,G22) -> 1 | H23: =IF(RateConv=1,1,H22) -> 1 | J23: Used by the closed-form checks: FCFE / deflator discounted at (1 + real rate + ERP) gives the same value under either convention.
B25: Ibovespa = sum of the four boxes (Bear)
C26: Today | D26: Year 1 | E26: Year 2 | F26: Year 3 | G26: Year 4 | H26: Year 5 | I26: Terminal | J26: How it is calculated
B27: Index points | C27: =C49+C78+C107+C136 -> 208431.92
B28: Earnings (index pts) | D28: =D58+D87+D116+D145 -> 21910.289 | E28: =E58+E87+E116+E145 -> 23069.536 | F28: =F58+F87+F116+F145 -> 24203.009 | G28: =G58+G87+G116+G145 -> 25116.639 | H28: =H58+H87+H116+H145 -> 25669.205
B29: Book value at the start of the year | D29: =D60+D89+D118+D147 -> 122032.81 | E29: =E60+E89+E118+E147 -> 130736.79 | F29: =F60+F89+F118+F147 -> 137503.25 | G29: =G60+G89+G118+G147 -> 142888.88 | H29: =H60+H89+H118+H147 -> 146032.43 | I29: =I60+I89+I118+I147 -> 152165.79
B30: Free cash flow to equity (FCFE) | D30: =D62+D91+D120+D149 -> 13206.306 | E30: =E62+E91+E120+E149 -> 16303.08 | F30: =F62+F91+F120+F149 -> 18817.379 | G30: =G62+G91+G120+G149 -> 21973.084 | H30: =H62+H91+H120+H149 -> 19535.843
B31: Present value of FCFE | C31: =C64+C93+C122+C151 -> 59215.553 | D31: =D64+D93+D122+D151 -> 11533.891 | E31: =E64+E93+E122+E151 -> 12435.369 | F31: =F64+F93+F122+F151 -> 12535.529 | G31: =G64+G93+G122+G151 -> 12784.068 | H31: =H64+H93+H122+H151 -> 9926.6959
B32: Present value of the terminal value | C32: =C66+C95+C124+C153 -> 100423.47
B33: Equity value today (index pts) | C33: =C67+C96+C125+C154 -> 159639.02
B34: Fair value at the horizon (index pts) | C34: =C68+C97+C126+C155 -> 169580.37
B35: Upside (fair value / index points today - 1) | C35: =C34/C27-1 -> -0.18639922
B36: ROE (sum of earnings / sum of book value) | D36: =D28/D29 -> 0.17954425 | E36: =E28/E29 -> 0.17645787 | F36: =F28/F29 -> 0.17601773 | G36: =G28/G29 -> 0.17577743 | H36: =H28/H29 -> 0.17577743
B37: Implied 12m fwd P/E at the horizon (fair value / next 12m earnings) | C37: =C34/IF(Horizon=1,E28,D28) -> 7.3508359
B38: 12m fwd P/E today (consensus year-1 earnings) | C38: ='Boxes Now'!Y10 -> 9.6218817
B39: Terminal value / equity value | C39: =C32/C33 -> 0.62906592
B40: Contribution to the Ibovespa upside (pp)
B41: Financials | C41: =(C68-C49)/C27*100 -> -4.0698148
B42: Defensives | C42: =(C97-C78)/C27*100 -> -11.426594
B43: Cyclicals | C43: =(C126-C107)/C27*100 -> -3.8208125
B44: Commodities | C44: =(C155-C136)/C27*100 -> 0.67729997
B47: Financials
C48: Today | D48: Year 1 | E48: Year 2 | F48: Year 3 | G48: Year 4 | H48: Year 5 | I48: Terminal | J48: How it is calculated
B49: Index points | C49: ='Boxes Now'!F6 -> 60927.304 | J49: Boxes Now (members' weight x Ibovespa close).
B50: Earnings change from the Selic scenario (years 1-2) | C50: =IF(UseEPS=1,Assumptions!$C$55*$C$14,0) -> 0.015189764 | J50: Box EPS sensitivity to the Selic (Assumptions section 5) x Selic cut; applied to years 1 and 2 (0 if UseEPS = 0).
B51: Equity risk premium (ERP) | C51: =IF(ISNUMBER(Assumptions!D80),Assumptions!D80,CHOOSE($C$10,$C$7,ErpHistIbov,History!$R$8)+$C$8/100-$C$9*CHOOSE($C$10,ErpSdIbov,ErpSdIbov,History!$R$9)) -> 0.06 | J51: Override if typed; else the basis ERP (1 typed, 2 Ibovespa 10y average, 3 this box's 10y average) + shift - k x sd of its history (History).
B52: Cost of equity = real rate + ERP | C52: =$C$6+C51 -> 0.145 | J52: 5y real rate (scenario) + ERP. House convention: this is the discount rate (Target!B55).
B53: Discount rate of the nominal cash flows | D53: =IF(RateConv=1,$C52,(1+$C52)*(1+D$21)-1) -> 0.145 | E53: =IF(RateConv=1,$C52,(1+$C52)*(1+E$21)-1) -> 0.145 | F53: =IF(RateConv=1,$C52,(1+$C52)*(1+F$21)-1) -> 0.145 | G53: =IF(RateConv=1,$C52,(1+$C52)*(1+G$21)-1) -> 0.145 | H53: =IF(RateConv=1,$C52,(1+$C52)*(1+H$21)-1) -> 0.145 | I53: =IF(RateConv=1,$C52,(1+$C52)*(1+IPCALT)-1) -> 0.145 | J53: House convention: = cost of equity. Fisher: (1 + cost of equity) x (1 + IPCA of the year) - 1; terminal uses the long-term IPCA.
B54: Discount factor | C54: 1 | D54: =C54/(1+D53) -> 0.87336245 | E54: =D54/(1+E53) -> 0.76276196 | F54: =E54/(1+F53) -> 0.66616765 | G54: =F54/(1+G53) -> 0.58180581 | H54: =G54/(1+H53) -> 0.50812734 | J54: Product of 1 / (1 + nominal cost of equity) up to the year.
B55: Long-term ROE | C55: =IF(ISNUMBER(Assumptions!D66),Assumptions!D66,CHOOSE(RoeLT,'Boxes Now'!Z6,'Boxes Now'!W6)+$C$13/100) -> 0.19949374 | J55: RoeLT 1: 10-year average of the box's 12m fwd ROE (History); 2: consensus year-2 ROE. Plus the shift in Assumptions, or the override.
B56: Long-term nominal growth | C56: =IF(ISNUMBER(Assumptions!D73),Assumptions!D73,$C$12) -> 0.042 | J56: Long-term nominal growth of the scenario (house 4.7%), or the override.
B57: Earnings growth | E57: ='Boxes Now'!$X$6+$C$11/100 -> 0.096871536 | F57: ='Boxes Now'!$X$6+($C56-'Boxes Now'!$X$6)*MIN(1,(F$19-2)/(GrowthYear-2))+$C$11/100 -> 0.071914358 | G57: ='Boxes Now'!$X$6+($C56-'Boxes Now'!$X$6)*MIN(1,(G$19-2)/(GrowthYear-2))+$C$11/100 -> 0.046957179 | H57: ='Boxes Now'!$X$6+($C56-'Boxes Now'!$X$6)*MIN(1,(H$19-2)/(GrowthYear-2))+$C$11/100 -> 0.022 | I57: =$C56 -> 0.042 | J57: Year 2 = consensus; converges linearly to the long-term growth by GrowthYear; + the scenario's growth add-on in years 2-5; terminal = long term.
B58: Earnings (index pts) | D58: ='Boxes Now'!R6*(1+$C50) -> 6205.3365 | E58: =D58*(1+E57) -> 6806.4569 | F58: =E58*(1+F57) -> 7295.9389 | G58: =F58*(1+G57) -> 7638.5356 | H58: =G58*(1+H57) -> 7806.5834 | I58: =H58*(1+I57) -> 8134.4599 | J58: Year 1 = consensus blended to the forward year (Boxes Now) x (1 + change from rates); then grows at the row above.
B59: ROE | D59: ='Boxes Now'!V6 -> 0.19352714 | E59: ='Boxes Now'!W6 -> 0.19949374 | F59: =$E59+($C55-$E59)*MIN(1,(F$19-2)/(RoeYear-2)) -> 0.19949374 | G59: =$E59+($C55-$E59)*MIN(1,(G$19-2)/(RoeYear-2)) -> 0.19949374 | H59: =$E59+($C55-$E59)*MIN(1,(H$19-2)/(RoeYear-2)) -> 0.19949374 | I59: =$C55 -> 0.19949374 | J59: Years 1-2 = consensus; converges linearly to the long-term ROE by RoeYear (Assumptions).
B60: Book value at the start of the year (index pts) | D60: =D58/D59 -> 32064.425 | E60: =E58/E59 -> 34118.649 | F60: =F58/F59 -> 36572.27 | G60: =G58/G59 -> 38289.601 | H60: =H58/H59 -> 39131.972 | I60: =I58/I59 -> 40775.515 | J60: Equity at the start of the year needed to earn the year's earnings at the year's ROE = earnings / ROE.
B61: Increase in book value during the year | D61: =E60-D60 -> 2054.2243 | E61: =F60-E60 -> 2453.6207 | F61: =G60-F60 -> 1717.3306 | G61: =H60-G60 -> 842.37121 | H61: =I60-H60 -> 1643.5428 | J61: Book value at the start of next year - at the start of this year = earnings retained to fund growth.
B62: Free cash flow to equity (FCFE) | D62: =D58-D61 -> 4151.1122 | E62: =E58-E61 -> 4352.8362 | F62: =F58-F61 -> 5578.6083 | G62: =G58-G61 -> 6796.1644 | H62: =H58-H61 -> 6163.0406 | J62: Earnings - increase in book value (what can be paid out). In the long term = earnings x (1 - g / ROE).
B63: FCFE / earnings | D63: =D62/D58 -> 0.66895843 | E63: =E62/E58 -> 0.63951572 | F63: =F62/F58 -> 0.76461828 | G63: =G62/G58 -> 0.88972085 | H63: =H62/H58 -> 0.78946708
B64: Present value of FCFE | C64: =SUM(D64:H64) -> 17747.549 | D64: =D62*D54 -> 3625.4255 | E64: =E62*E54 -> 3320.1779 | F64: =F62*F54 -> 3716.2884 | G64: =G62*G54 -> 3954.0479 | H64: =H62*H54 -> 3131.6094 | J64: FCFE x discount factor. 'Today' = sum of years 1-5.
B65: Terminal value at the end of year 5 | I65: =I58*(1-I57/I59)/(I53-I57) -> 62348.43 | J65: Year-11 earnings x (1 - g / ROE) / (Ke - g), nominal long-term values (Gordon growth).
B66: Present value of the terminal value | C66: =I66 -> 31680.942 | I66: =I65*H54 -> 31680.942
B67: Equity value today (index pts) | C67: =C64+C66 -> 49428.491 | J67: Present value of FCFE (years 1-5) + present value of the terminal value.
B68: Fair value at the horizon (index pts) | C68: =IF(Horizon=1,C67*(1+D53)-D62,C67) -> 52444.51 | J68: Horizon 1: value today x (1 + year-1 discount rate) - year-1 FCFE (paid out during the year) = value in 12 months. Horizon 0: value today.
B69: Upside (fair value / index points today - 1) | C69: =C68/C49-1 -> -0.13922811
B70: Implied 12m fwd P/E at the horizon (fair value / next 12m earnings) | C70: =C68/IF(Horizon=1,E58,D58) -> 7.7051116
B71: 12m fwd P/E today (consensus year-1 earnings) | C71: ='Boxes Now'!Y6 -> 9.9676747 | J71: Index points / consensus year-1 earnings (without the change from rates).
B72: Terminal value / equity value | C72: =C66/C67 -> 0.64094496
B73: FCFE / deflator (for Implied ERP) | D73: =D62/D$23 -> 4151.1122 | E73: =E62/E$23 -> 4352.8362 | F73: =F62/F$23 -> 5578.6083 | G73: =G62/G$23 -> 6796.1644 | H73: =H62/H$23 -> 6163.0406 | J73: FCFE / deflator (timeline): used by Implied ERP and Sensitivity to re-discount the same cash flows at other rates.
B76: Defensives
C77: Today | D77: Year 1 | E77: Year 2 | F77: Year 3 | G77: Year 4 | H77: Year 5 | I77: Terminal | J77: How it is calculated
B78: Index points | C78: ='Boxes Now'!F7 -> 55822.367 | J78: Boxes Now (members' weight x Ibovespa close).
B79: Earnings change from the Selic scenario (years 1-2) | C79: =IF(UseEPS=1,Assumptions!$C$56*$C$14,0) -> 0.011734219 | J79: Box EPS sensitivity to the Selic (Assumptions section 5) x Selic cut; applied to years 1 and 2 (0 if UseEPS = 0).
B80: Equity risk premium (ERP) | C80: =IF(ISNUMBER(Assumptions!D81),Assumptions!D81,CHOOSE($C$10,$C$7,ErpHistIbov,History!$S$8)+$C$8/100-$C$9*CHOOSE($C$10,ErpSdIbov,ErpSdIbov,History!$S$9)) -> 0.06 | J80: Override if typed; else the basis ERP (1 typed, 2 Ibovespa 10y average, 3 this box's 10y average) + shift - k x sd of its history (History).
B81: Cost of equity = real rate + ERP | C81: =$C$6+C80 -> 0.145 | J81: 5y real rate (scenario) + ERP. House convention: this is the discount rate (Target!B55).
B82: Discount rate of the nominal cash flows | D82: =IF(RateConv=1,$C81,(1+$C81)*(1+D$21)-1) -> 0.145 | E82: =IF(RateConv=1,$C81,(1+$C81)*(1+E$21)-1) -> 0.145 | F82: =IF(RateConv=1,$C81,(1+$C81)*(1+F$21)-1) -> 0.145 | G82: =IF(RateConv=1,$C81,(1+$C81)*(1+G$21)-1) -> 0.145 | H82: =IF(RateConv=1,$C81,(1+$C81)*(1+H$21)-1) -> 0.145 | I82: =IF(RateConv=1,$C81,(1+$C81)*(1+IPCALT)-1) -> 0.145 | J82: House convention: = cost of equity. Fisher: (1 + cost of equity) x (1 + IPCA of the year) - 1; terminal uses the long-term IPCA.
B83: Discount factor | C83: 1 | D83: =C83/(1+D82) -> 0.87336245 | E83: =D83/(1+E82) -> 0.76276196 | F83: =E83/(1+F82) -> 0.66616765 | G83: =F83/(1+G82) -> 0.58180581 | H83: =G83/(1+H82) -> 0.50812734 | J83: Product of 1 / (1 + nominal cost of equity) up to the year.
B84: Long-term ROE | C84: =IF(ISNUMBER(Assumptions!D67),Assumptions!D67,CHOOSE(RoeLT,'Boxes Now'!Z7,'Boxes Now'!W7)+$C$13/100) -> 0.14793968 | J84: RoeLT 1: 10-year average of the box's 12m fwd ROE (History); 2: consensus year-2 ROE. Plus the shift in Assumptions, or the override.
B85: Long-term nominal growth | C85: =IF(ISNUMBER(Assumptions!D74),Assumptions!D74,$C$12) -> 0.042 | J85: Long-term nominal growth of the scenario (house 4.7%), or the override.
B86: Earnings growth | E86: ='Boxes Now'!$X$7+$C$11/100 -> 0.19201573 | F86: ='Boxes Now'!$X$7+($C85-'Boxes Now'!$X$7)*MIN(1,(F$19-2)/(GrowthYear-2))+$C$11/100 -> 0.13534382 | G86: ='Boxes Now'!$X$7+($C85-'Boxes Now'!$X$7)*MIN(1,(G$19-2)/(GrowthYear-2))+$C$11/100 -> 0.07867191 | H86: ='Boxes Now'!$X$7+($C85-'Boxes Now'!$X$7)*MIN(1,(H$19-2)/(GrowthYear-2))+$C$11/100 -> 0.022 | I86: =$C85 -> 0.042 | J86: Year 2 = consensus; converges linearly to the long-term growth by GrowthYear; + the scenario's growth add-on in years 2-5; terminal = long term.
B87: Earnings (index pts) | D87: ='Boxes Now'!R7*(1+$C79) -> 3851.6038 | E87: =D87*(1+E86) -> 4591.1723 | F87: =E87*(1+F86) -> 5212.5591 | G87: =F87*(1+G86) -> 5622.6411 | H87: =G87*(1+H86) -> 5746.3392 | I87: =H87*(1+I86) -> 5987.6854 | J87: Year 1 = consensus blended to the forward year (Boxes Now) x (1 + change from rates); then grows at the row above.
B88: ROE | D88: ='Boxes Now'!V7 -> 0.1309171 | E88: ='Boxes Now'!W7 -> 0.14793968 | F88: =$E88+($C84-$E88)*MIN(1,(F$19-2)/(RoeYear-2)) -> 0.14793968 | G88: =$E88+($C84-$E88)*MIN(1,(G$19-2)/(RoeYear-2)) -> 0.14793968 | H88: =$E88+($C84-$E88)*MIN(1,(H$19-2)/(RoeYear-2)) -> 0.14793968 | I88: =$C84 -> 0.14793968 | J88: Years 1-2 = consensus; converges linearly to the long-term ROE by RoeYear (Assumptions).
B89: Book value at the start of the year (index pts) | D89: =D87/D88 -> 29420.174 | E89: =E87/E88 -> 31034.084 | F89: =F87/F88 -> 35234.355 | G89: =G87/G88 -> 38006.309 | H89: =H87/H88 -> 38842.448 | I89: =I87/I88 -> 40473.831 | J89: Equity at the start of the year needed to earn the year's earnings at the year's ROE = earnings / ROE.
B90: Increase in book value during the year | D90: =E89-D89 -> 1613.9098 | E90: =F89-E89 -> 4200.2714 | F90: =G89-F89 -> 2771.954 | G90: =H89-G89 -> 836.1388 | H90: =I89-H89 -> 1631.3828 | J90: Book value at the start of next year - at the start of this year = earnings retained to fund growth.
B91: Free cash flow to equity (FCFE) | D91: =D87-D90 -> 2237.694 | E91: =E87-E90 -> 390.90089 | F91: =F87-F90 -> 2440.6051 | G91: =G87-G90 -> 4786.5023 | H91: =H87-H90 -> 4114.9564 | J91: Earnings - increase in book value (what can be paid out). In the long term = earnings x (1 - g / ROE).
B92: FCFE / earnings | D92: =D91/D87 -> 0.5809772 | E92: =E91/E87 -> 0.085141847 | F92: =F91/F87 -> 0.46821629 | G92: =G91/G87 -> 0.85129074 | H92: =H91/H87 -> 0.7161005
B93: Present value of FCFE | C93: =SUM(D93:H93) -> 8754.0711 | D93: =D91*D83 -> 1954.3179 | E93: =E91*E83 -> 298.16433 | F93: =F91*F83 -> 1625.8522 | G93: =G91*G83 -> 2784.8148 | H93: =H91*H83 -> 2090.9219 | J93: FCFE x discount factor. 'Today' = sum of years 1-5.
B94: Terminal value at the end of year 5 | I94: =I87*(1-I86/I88)/(I82-I86) -> 41628.976 | J94: Year-11 earnings x (1 - g / ROE) / (Ke - g), nominal long-term values (Gordon growth).
B95: Present value of the terminal value | C95: =I95 -> 21152.821 | I95: =I94*H83 -> 21152.821
B96: Equity value today (index pts) | C96: =C93+C95 -> 29906.892 | J96: Present value of FCFE (years 1-5) + present value of the terminal value.
B97: Fair value at the horizon (index pts) | C97: =IF(Horizon=1,C96*(1+D82)-D91,C96) -> 32005.698 | J97: Horizon 1: value today x (1 + year-1 discount rate) - year-1 FCFE (paid out during the year) = value in 12 months. Horizon 0: value today.
B98: Upside (fair value / index points today - 1) | C98: =C97/C78-1 -> -0.42665102
B99: Implied 12m fwd P/E at the horizon (fair value / next 12m earnings) | C99: =C97/IF(Horizon=1,E87,D87) -> 6.9711384
B100: 12m fwd P/E today (consensus year-1 earnings) | C100: ='Boxes Now'!Y7 -> 14.663346 | J100: Index points / consensus year-1 earnings (without the change from rates).
B101: Terminal value / equity value | C101: =C95/C96 -> 0.70728918
B102: FCFE / deflator (for Implied ERP) | D102: =D91/D$23 -> 2237.694 | E102: =E91/E$23 -> 390.90089 | F102: =F91/F$23 -> 2440.6051 | G102: =G91/G$23 -> 4786.5023 | H102: =H91/H$23 -> 4114.9564 | J102: FCFE / deflator (timeline): used by Implied ERP and Sensitivity to re-discount the same cash flows at other rates.
B105: Cyclicals
C106: Today | D106: Year 1 | E106: Year 2 | F106: Year 3 | G106: Year 4 | H106: Year 5 | I106: Terminal | J106: How it is calculated
B107: Index points | C107: ='Boxes Now'!F8 -> 26271.075 | J107: Boxes Now (members' weight x Ibovespa close).
B108: Earnings change from the Selic scenario (years 1-2) | C108: =IF(UseEPS=1,Assumptions!$C$57*$C$14,0) -> 0.018154865 | J108: Box EPS sensitivity to the Selic (Assumptions section 5) x Selic cut; applied to years 1 and 2 (0 if UseEPS = 0).
B109: Equity risk premium (ERP) | C109: =IF(ISNUMBER(Assumptions!D82),Assumptions!D82,CHOOSE($C$10,$C$7,ErpHistIbov,History!$T$8)+$C$8/100-$C$9*CHOOSE($C$10,ErpSdIbov,ErpSdIbov,History!$T$9)) -> 0.06 | J109: Override if typed; else the basis ERP (1 typed, 2 Ibovespa 10y average, 3 this box's 10y average) + shift - k x sd of its history (History).
...

Sheet DCF Bull
B1: Ibovespa - DCF, Bull case
B2: FCFE by box in Ibovespa points. Scenario levers: Assumptions column F. Years 1-5 + terminal; Ibovespa = sum of the four boxes.
B3: Legend: | C3: input | D3: assumption | E3: formula
B5: Scenario parameters (Bull; Assumptions column F)
B6: 5-year real rate (NTN-B) | C6: =Assumptions!F25 -> 0.06
B7: ERP, typed (ERP basis 1) | C7: =Assumptions!F26 -> 0.06
B8: ERP shift (pp) | C8: =Assumptions!F27 -> 0
B9: ERP move in std. dev. of its history (k) | C9: =Assumptions!F28 -> 0
B10: ERP basis (1 typed, 2 Ibovespa 10y average, 3 each box's 10y average) | C10: =ERPBasis -> 1
B11: Earnings growth vs consensus path, years 2-5 (pp per year) | C11: =Assumptions!F31 -> 2
B12: Long-term nominal growth (default) | C12: =Assumptions!F32 -> 0.052
B13: Long-term ROE vs 10y average (pp) | C13: =Assumptions!F33 -> 0
B14: Selic cut vs today (pp) | C14: =Assumptions!F24 -> 4.25
B15: Discount-rate convention (1 house: real rate + ERP; 2 Fisher: with IPCA) | C15: =RateConv -> 1
B17: Timeline (shared by every box)
C18: Today | D18: Year 1 | E18: Year 2 | F18: Year 3 | G18: Year 4 | H18: Year 5 | I18: Terminal | J18: How it is calculated
B19: Year (t) | C19: 0 | D19: 1 | E19: 2 | F19: 3 | G19: 4 | H19: 5
B20: End of the forward year | C20: =PxDate -> 46300 | D20: =EDATE(PxDate,12*D19) -> 46665 | E20: =EDATE(PxDate,12*E19) -> 47031 | F20: =EDATE(PxDate,12*F19) -> 47396 | G20: =EDATE(PxDate,12*G19) -> 47761 | H20: =EDATE(PxDate,12*H19) -> 48126
B21: Inflation (IPCA) | D21: =IPCA1 -> 0.04 | E21: =IPCA2 -> 0.04 | F21: =IPCALT -> 0.04 | G21: =IPCALT -> 0.04 | H21: =IPCALT -> 0.04 | I21: =IPCALT -> 0.04
B22: Price index (today = 1) | C22: 1 | D22: =C22*(1+D21) -> 1.04 | E22: =D22*(1+E21) -> 1.0816 | F22: =E22*(1+F21) -> 1.124864 | G22: =F22*(1+G21) -> 1.1698586 | H22: =G22*(1+H21) -> 1.2166529 | J22: Cash flows are nominal (consensus). House convention: discounted at real rate + ERP. Fisher: at (1 + real rate + ERP) x (1 + IPCA) - 1.
B23: Deflator for discounting (1 under the house convention) | C23: 1 | D23: =IF(RateConv=1,1,D22) -> 1 | E23: =IF(RateConv=1,1,E22) -> 1 | F23: =IF(RateConv=1,1,F22) -> 1 | G23: =IF(RateConv=1,1,G22) -> 1 | H23: =IF(RateConv=1,1,H22) -> 1 | J23: Used by the closed-form checks: FCFE / deflator discounted at (1 + real rate + ERP) gives the same value under either convention.
B25: Ibovespa = sum of the four boxes (Bull)
C26: Today | D26: Year 1 | E26: Year 2 | F26: Year 3 | G26: Year 4 | H26: Year 5 | I26: Terminal | J26: How it is calculated
B27: Index points | C27: =C49+C78+C107+C136 -> 208431.92
B28: Earnings (index pts) | D28: =D58+D87+D116+D145 -> 23578.693 | E28: =E58+E87+E116+E145 -> 25814.22 | F28: =F58+F87+F116+F145 -> 28226.581 | G28: =G58+G87+G116+G145 -> 30620.243 | H28: =H58+H87+H116+H145 -> 32824.901
B29: Book value at the start of the year | D29: =D60+D89+D118+D147 -> 131508.31 | E29: =E60+E89+E118+E147 -> 146169.89 | F29: =F60+F89+F118+F147 -> 160207.98 | G29: =G60+G89+G118+G147 -> 174017.57 | H29: =H60+H89+H118+H147 -> 186546.83 | I29: =I60+I89+I118+I147 -> 196247.27
B30: Free cash flow to equity (FCFE) | D30: =D62+D91+D120+D149 -> 8917.1089 | E30: =E62+E91+E120+E149 -> 11776.13 | F30: =F62+F91+F120+F149 -> 14416.994 | G30: =G62+G91+G120+G149 -> 18090.978 | H30: =H62+H91+H120+H149 -> 23124.465
B31: Present value of FCFE | C31: =C64+C93+C122+C151 -> 52229.881 | D31: =D64+D93+D122+D151 -> 7961.7043 | E31: =E64+E93+E122+E151 -> 9387.8589 | F31: =F64+F93+F122+F151 -> 10261.732 | G31: =G64+G93+G122+G151 -> 11497.144 | H31: =H64+H93+H122+H151 -> 13121.443
B32: Present value of the terminal value | C32: =C66+C95+C124+C153 -> 202996.44
B33: Equity value today (index pts) | C33: =C67+C96+C125+C154 -> 255226.32
B34: Fair value at the horizon (index pts) | C34: =C68+C97+C126+C155 -> 276936.37
B35: Upside (fair value / index points today - 1) | C35: =C34/C27-1 -> 0.32866581
B36: ROE (sum of earnings / sum of book value) | D36: =D28/D29 -> 0.17929432 | E36: =E28/E29 -> 0.17660422 | F36: =F28/F29 -> 0.17618711 | G36: =G28/G29 -> 0.17596064 | H36: =H28/H29 -> 0.17596064
B37: Implied 12m fwd P/E at the horizon (fair value / next 12m earnings) | C37: =C34/IF(Horizon=1,E28,D28) -> 10.728055
B38: 12m fwd P/E today (consensus year-1 earnings) | C38: ='Boxes Now'!Y10 -> 9.6218817
B39: Terminal value / equity value | C39: =C32/C33 -> 0.79535856
B40: Contribution to the Ibovespa upside (pp)
B41: Financials | C41: =(C68-C49)/C27*100 -> 13.692575
B42: Defensives | C42: =(C97-C78)/C27*100 -> -2.006707
B43: Cyclicals | C43: =(C126-C107)/C27*100 -> 2.5784239
B44: Commodities | C44: =(C155-C136)/C27*100 -> 18.602289
B47: Financials
C48: Today | D48: Year 1 | E48: Year 2 | F48: Year 3 | G48: Year 4 | H48: Year 5 | I48: Terminal | J48: How it is calculated
B49: Index points | C49: ='Boxes Now'!F6 -> 60927.304 | J49: Boxes Now (members' weight x Ibovespa close).
B50: Earnings change from the Selic scenario (years 1-2) | C50: =IF(UseEPS=1,Assumptions!$C$55*$C$14,0) -> 0.11737545 | J50: Box EPS sensitivity to the Selic (Assumptions section 5) x Selic cut; applied to years 1 and 2 (0 if UseEPS = 0).
B51: Equity risk premium (ERP) | C51: =IF(ISNUMBER(Assumptions!F80),Assumptions!F80,CHOOSE($C$10,$C$7,ErpHistIbov,History!$R$8)+$C$8/100-$C$9*CHOOSE($C$10,ErpSdIbov,ErpSdIbov,History!$R$9)) -> 0.06 | J51: Override if typed; else the basis ERP (1 typed, 2 Ibovespa 10y average, 3 this box's 10y average) + shift - k x sd of its history (History).
B52: Cost of equity = real rate + ERP | C52: =$C$6+C51 -> 0.12 | J52: 5y real rate (scenario) + ERP. House convention: this is the discount rate (Target!B55).
B53: Discount rate of the nominal cash flows | D53: =IF(RateConv=1,$C52,(1+$C52)*(1+D$21)-1) -> 0.12 | E53: =IF(RateConv=1,$C52,(1+$C52)*(1+E$21)-1) -> 0.12 | F53: =IF(RateConv=1,$C52,(1+$C52)*(1+F$21)-1) -> 0.12 | G53: =IF(RateConv=1,$C52,(1+$C52)*(1+G$21)-1) -> 0.12 | H53: =IF(RateConv=1,$C52,(1+$C52)*(1+H$21)-1) -> 0.12 | I53: =IF(RateConv=1,$C52,(1+$C52)*(1+IPCALT)-1) -> 0.12 | J53: House convention: = cost of equity. Fisher: (1 + cost of equity) x (1 + IPCA of the year) - 1; terminal uses the long-term IPCA.
B54: Discount factor | C54: 1 | D54: =C54/(1+D53) -> 0.89285714 | E54: =D54/(1+E53) -> 0.79719388 | F54: =E54/(1+F53) -> 0.71178025 | G54: =F54/(1+G53) -> 0.63551808 | H54: =G54/(1+H53) -> 0.56742686 | J54: Product of 1 / (1 + nominal cost of equity) up to the year.
B55: Long-term ROE | C55: =IF(ISNUMBER(Assumptions!F66),Assumptions!F66,CHOOSE(RoeLT,'Boxes Now'!Z6,'Boxes Now'!W6)+$C$13/100) -> 0.19949374 | J55: RoeLT 1: 10-year average of the box's 12m fwd ROE (History); 2: consensus year-2 ROE. Plus the shift in Assumptions, or the override.
B56: Long-term nominal growth | C56: =IF(ISNUMBER(Assumptions!F73),Assumptions!F73,$C$12) -> 0.052 | J56: Long-term nominal growth of the scenario (house 4.7%), or the override.
B57: Earnings growth | E57: ='Boxes Now'!$X$6+$C$11/100 -> 0.13687154 | F57: ='Boxes Now'!$X$6+($C56-'Boxes Now'!$X$6)*MIN(1,(F$19-2)/(GrowthYear-2))+$C$11/100 -> 0.11524769 | G57: ='Boxes Now'!$X$6+($C56-'Boxes Now'!$X$6)*MIN(1,(G$19-2)/(GrowthYear-2))+$C$11/100 -> 0.093623845 | H57: ='Boxes Now'!$X$6+($C56-'Boxes Now'!$X$6)*MIN(1,(H$19-2)/(GrowthYear-2))+$C$11/100 -> 0.072 | I57: =$C56 -> 0.052 | J57: Year 2 = consensus; converges linearly to the long-term growth by GrowthYear; + the scenario's growth add-on in years 2-5; terminal = long term.
B58: Earnings (index pts) | D58: ='Boxes Now'!R6*(1+$C50) -> 6829.9454 | E58: =D58*(1+E57) -> 7764.7705 | F58: =E58*(1+F57) -> 8659.6423 | G58: =F58*(1+G57) -> 9470.3914 | H58: =G58*(1+H57) -> 10152.26 | I58: =H58*(1+I57) -> 10680.177 | J58: Year 1 = consensus blended to the forward year (Boxes Now) x (1 + change from rates); then grows at the row above.
B59: ROE | D59: ='Boxes Now'!V6 -> 0.19352714 | E59: ='Boxes Now'!W6 -> 0.19949374 | F59: =$E59+($C55-$E59)*MIN(1,(F$19-2)/(RoeYear-2)) -> 0.19949374 | G59: =$E59+($C55-$E59)*MIN(1,(G$19-2)/(RoeYear-2)) -> 0.19949374 | H59: =$E59+($C55-$E59)*MIN(1,(H$19-2)/(RoeYear-2)) -> 0.19949374 | I59: =$C55 -> 0.19949374 | J59: Years 1-2 = consensus; converges linearly to the long-term ROE by RoeYear (Assumptions).
B60: Book value at the start of the year (index pts) | D60: =D58/D59 -> 35291.925 | E60: =E58/E59 -> 38922.377 | F60: =F58/F59 -> 43408.091 | G60: =G58/G59 -> 47472.123 | H60: =H58/H59 -> 50890.116 | I60: =I58/I59 -> 53536.402 | J60: Equity at the start of the year needed to earn the year's earnings at the year's ROE = earnings / ROE.
B61: Increase in book value during the year | D61: =E60-D60 -> 3630.4514 | E61: =F60-E60 -> 4485.714 | F61: =G60-F60 -> 4064.0324 | G61: =H60-G60 -> 3417.9929 | H61: =I60-H60 -> 2646.286 | J61: Book value at the start of next year - at the start of this year = earnings retained to fund growth.
B62: Free cash flow to equity (FCFE) | D62: =D58-D61 -> 3199.494 | E62: =E58-E61 -> 3279.0565 | F62: =F58-F61 -> 4595.61 | G62: =G58-G61 -> 6052.3985 | H62: =H58-H61 -> 7505.9735 | J62: Earnings - increase in book value (what can be paid out). In the long term = earnings x (1 - g / ROE).
B63: FCFE / earnings | D63: =D62/D58 -> 0.46845089 | E63: =E62/E58 -> 0.42229921 | F63: =F62/F58 -> 0.53069282 | G63: =G62/G58 -> 0.63908642 | H63: =H62/H58 -> 0.73934019
B64: Present value of FCFE | C64: =SUM(D64:H64) -> 16847.299 | D64: =D62*D54 -> 2856.691 | E64: =E62*E54 -> 2614.0437 | F64: =F62*F54 -> 3271.0644 | G64: =G62*G54 -> 3846.4087 | H64: =H62*H54 -> 4259.091 | J64: FCFE x discount factor. 'Today' = sum of years 1-5.
B65: Terminal value at the end of year 5 | I65: =I58*(1-I57/I59)/(I53-I57) -> 116121.83 | J65: Year-11 earnings x (1 - g / ROE) / (Ke - g), nominal long-term values (Gordon growth).
B66: Present value of the terminal value | C66: =I66 -> 65890.642 | I66: =I65*H54 -> 65890.642
B67: Equity value today (index pts) | C67: =C64+C66 -> 82737.941 | J67: Present value of FCFE (years 1-5) + present value of the terminal value.
B68: Fair value at the horizon (index pts) | C68: =IF(Horizon=1,C67*(1+D53)-D62,C67) -> 89467 | J68: Horizon 1: value today x (1 + year-1 discount rate) - year-1 FCFE (paid out during the year) = value in 12 months. Horizon 0: value today.
B69: Upside (fair value / index points today - 1) | C69: =C68/C49-1 -> 0.46842212
B70: Implied 12m fwd P/E at the horizon (fair value / next 12m earnings) | C70: =C68/IF(Horizon=1,E58,D58) -> 11.522169
B71: 12m fwd P/E today (consensus year-1 earnings) | C71: ='Boxes Now'!Y6 -> 9.9676747 | J71: Index points / consensus year-1 earnings (without the change from rates).
B72: Terminal value / equity value | C72: =C66/C67 -> 0.79637759
B73: FCFE / deflator (for Implied ERP) | D73: =D62/D$23 -> 3199.494 | E73: =E62/E$23 -> 3279.0565 | F73: =F62/F$23 -> 4595.61 | G73: =G62/G$23 -> 6052.3985 | H73: =H62/H$23 -> 7505.9735 | J73: FCFE / deflator (timeline): used by Implied ERP and Sensitivity to re-discount the same cash flows at other rates.
B76: Defensives
C77: Today | D77: Year 1 | E77: Year 2 | F77: Year 3 | G77: Year 4 | H77: Year 5 | I77: Terminal | J77: How it is calculated
B78: Index points | C78: ='Boxes Now'!F7 -> 55822.367 | J78: Boxes Now (members' weight x Ibovespa close).
B79: Earnings change from the Selic scenario (years 1-2) | C79: =IF(UseEPS=1,Assumptions!$C$56*$C$14,0) -> 0.090673512 | J79: Box EPS sensitivity to the Selic (Assumptions section 5) x Selic cut; applied to years 1 and 2 (0 if UseEPS = 0).
B80: Equity risk premium (ERP) | C80: =IF(ISNUMBER(Assumptions!F81),Assumptions!F81,CHOOSE($C$10,$C$7,ErpHistIbov,History!$S$8)+$C$8/100-$C$9*CHOOSE($C$10,ErpSdIbov,ErpSdIbov,History!$S$9)) -> 0.06 | J80: Override if typed; else the basis ERP (1 typed, 2 Ibovespa 10y average, 3 this box's 10y average) + shift - k x sd of its history (History).
B81: Cost of equity = real rate + ERP | C81: =$C$6+C80 -> 0.12 | J81: 5y real rate (scenario) + ERP. House convention: this is the discount rate (Target!B55).
B82: Discount rate of the nominal cash flows | D82: =IF(RateConv=1,$C81,(1+$C81)*(1+D$21)-1) -> 0.12 | E82: =IF(RateConv=1,$C81,(1+$C81)*(1+E$21)-1) -> 0.12 | F82: =IF(RateConv=1,$C81,(1+$C81)*(1+F$21)-1) -> 0.12 | G82: =IF(RateConv=1,$C81,(1+$C81)*(1+G$21)-1) -> 0.12 | H82: =IF(RateConv=1,$C81,(1+$C81)*(1+H$21)-1) -> 0.12 | I82: =IF(RateConv=1,$C81,(1+$C81)*(1+IPCALT)-1) -> 0.12 | J82: House convention: = cost of equity. Fisher: (1 + cost of equity) x (1 + IPCA of the year) - 1; terminal uses the long-term IPCA.
B83: Discount factor | C83: 1 | D83: =C83/(1+D82) -> 0.89285714 | E83: =D83/(1+E82) -> 0.79719388 | F83: =E83/(1+F82) -> 0.71178025 | G83: =F83/(1+G82) -> 0.63551808 | H83: =G83/(1+H82) -> 0.56742686 | J83: Product of 1 / (1 + nominal cost of equity) up to the year.
B84: Long-term ROE | C84: =IF(ISNUMBER(Assumptions!F67),Assumptions!F67,CHOOSE(RoeLT,'Boxes Now'!Z7,'Boxes Now'!W7)+$C$13/100) -> 0.14793968 | J84: RoeLT 1: 10-year average of the box's 12m fwd ROE (History); 2: consensus year-2 ROE. Plus the shift in Assumptions, or the override.
B85: Long-term nominal growth | C85: =IF(ISNUMBER(Assumptions!F74),Assumptions!F74,$C$12) -> 0.052 | J85: Long-term nominal growth of the scenario (house 4.7%), or the override.
B86: Earnings growth | E86: ='Boxes Now'!$X$7+$C$11/100 -> 0.23201573 | F86: ='Boxes Now'!$X$7+($C85-'Boxes Now'!$X$7)*MIN(1,(F$19-2)/(GrowthYear-2))+$C$11/100 -> 0.17867715 | G86: ='Boxes Now'!$X$7+($C85-'Boxes Now'!$X$7)*MIN(1,(G$19-2)/(GrowthYear-2))+$C$11/100 -> 0.12533858 | H86: ='Boxes Now'!$X$7+($C85-'Boxes Now'!$X$7)*MIN(1,(H$19-2)/(GrowthYear-2))+$C$11/100 -> 0.072 | I86: =$C85 -> 0.052 | J86: Year 2 = consensus; converges linearly to the long-term growth by GrowthYear; + the scenario's growth add-on in years 2-5; terminal = long term.
B87: Earnings (index pts) | D87: ='Boxes Now'!R7*(1+$C79) -> 4152.1203 | E87: =D87*(1+E86) -> 5115.4776 | F87: =E87*(1+F86) -> 6029.4965 | G87: =F87*(1+G86) -> 6785.2251 | H87: =G87*(1+H86) -> 7273.7613 | I87: =H87*(1+I86) -> 7651.9969 | J87: Year 1 = consensus blended to the forward year (Boxes Now) x (1 + change from rates); then grows at the row above.
B88: ROE | D88: ='Boxes Now'!V7 -> 0.1309171 | E88: ='Boxes Now'!W7 -> 0.14793968 | F88: =$E88+($C84-$E88)*MIN(1,(F$19-2)/(RoeYear-2)) -> 0.14793968 | G88: =$E88+($C84-$E88)*MIN(1,(G$19-2)/(RoeYear-2)) -> 0.14793968 | H88: =$E88+($C84-$E88)*MIN(1,(H$19-2)/(RoeYear-2)) -> 0.14793968 | I88: =$C84 -> 0.14793968 | J88: Years 1-2 = consensus; converges linearly to the long-term ROE by RoeYear (Assumptions).
B89: Book value at the start of the year (index pts) | D89: =D87/D88 -> 31715.646 | E89: =E87/E88 -> 34578.131 | F89: =F87/F88 -> 40756.453 | G89: =G87/G88 -> 45864.809 | H89: =H87/H88 -> 49167.076 | I89: =I87/I88 -> 51723.763 | J89: Equity at the start of the year needed to earn the year's earnings at the year's ROE = earnings / ROE.
B90: Increase in book value during the year | D90: =E89-D89 -> 2862.4854 | E90: =F89-E89 -> 6178.3221 | F90: =G89-F89 -> 5108.3559 | G90: =H89-G89 -> 3302.2663 | H90: =I89-H89 -> 2556.6879 | J90: Book value at the start of next year - at the start of this year = earnings retained to fund growth.
B91: Free cash flow to equity (FCFE) | D91: =D87-D90 -> 1289.635 | E91: =E87-E90 -> -1062.8445 | F91: =F87-F90 -> 921.1407 | G91: =G87-G90 -> 3482.9588 | H91: =H87-H90 -> 4717.0733 | J91: Earnings - increase in book value (what can be paid out). In the long term = earnings x (1 - g / ROE).
B92: FCFE / earnings | D92: =D91/D87 -> 0.31059672 | E92: =E91/E87 -> -0.20777033 | F92: =F91/F87 -> 0.15277241 | G92: =G91/G87 -> 0.51331515 | H92: =H91/H87 -> 0.64850538
B93: Present value of FCFE | C93: =SUM(D93:H93) -> 5849.8938 | D93: =D91*D83 -> 1151.4598 | E93: =E91*E83 -> -847.29311 | F93: =F91*F83 -> 655.64975 | G93: =G91*G83 -> 2213.4833 | H93: =H91*H83 -> 2676.5941 | J93: FCFE x discount factor. 'Today' = sum of years 1-5.
B94: Terminal value at the end of year 5 | I94: =I87*(1-I86/I88)/(I82-I86) -> 72975.899 | J94: Year-11 earnings x (1 - g / ROE) / (Ke - g), nominal long-term values (Gordon growth).
B95: Present value of the terminal value | C95: =I95 -> 41408.485 | I95: =I94*H83 -> 41408.485
B96: Equity value today (index pts) | C96: =C93+C95 -> 47258.379 | J96: Present value of FCFE (years 1-5) + present value of the terminal value.
B97: Fair value at the horizon (index pts) | C97: =IF(Horizon=1,C96*(1+D82)-D91,C96) -> 51639.749 | J97: Horizon 1: value today x (1 + year-1 discount rate) - year-1 FCFE (paid out during the year) = value in 12 months. Horizon 0: value today.
B98: Upside (fair value / index points today - 1) | C98: =C97/C78-1 -> -0.074927277
B99: Implied 12m fwd P/E at the horizon (fair value / next 12m earnings) | C99: =C97/IF(Horizon=1,E87,D87) -> 10.094805
B100: 12m fwd P/E today (consensus year-1 earnings) | C100: ='Boxes Now'!Y7 -> 14.663346 | J100: Index points / consensus year-1 earnings (without the change from rates).
B101: Terminal value / equity value | C101: =C95/C96 -> 0.87621467
B102: FCFE / deflator (for Implied ERP) | D102: =D91/D$23 -> 1289.635 | E102: =E91/E$23 -> -1062.8445 | F102: =F91/F$23 -> 921.1407 | G102: =G91/G$23 -> 3482.9588 | H102: =H91/H$23 -> 4717.0733 | J102: FCFE / deflator (timeline): used by Implied ERP and Sensitivity to re-discount the same cash flows at other rates.
B105: Cyclicals
C106: Today | D106: Year 1 | E106: Year 2 | F106: Year 3 | G106: Year 4 | H106: Year 5 | I106: Terminal | J106: How it is calculated
B107: Index points | C107: ='Boxes Now'!F8 -> 26271.075 | J107: Boxes Now (members' weight x Ibovespa close).
B108: Earnings change from the Selic scenario (years 1-2) | C108: =IF(UseEPS=1,Assumptions!$C$57*$C$14,0) -> 0.14028759 | J108: Box EPS sensitivity to the Selic (Assumptions section 5) x Selic cut; applied to years 1 and 2 (0 if UseEPS = 0).
B109: Equity risk premium (ERP) | C109: =IF(ISNUMBER(Assumptions!F82),Assumptions!F82,CHOOSE($C$10,$C$7,ErpHistIbov,History!$T$8)+$C$8/100-$C$9*CHOOSE($C$10,ErpSdIbov,ErpSdIbov,History!$T$9)) -> 0.06 | J109: Override if typed; else the basis ERP (1 typed, 2 Ibovespa 10y average, 3 this box's 10y average) + shift - k x sd of its history (History).
...

Sheet DCF Custom
B1: Ibovespa - DCF, Custom case
B2: FCFE by box in Ibovespa points. Scenario levers: Assumptions column G. Years 1-5 + terminal; Ibovespa = sum of the four boxes.
B3: Legend: | C3: input | D3: assumption | E3: formula
B5: Scenario parameters (Custom; Assumptions column G)
B6: 5-year real rate (NTN-B) | C6: =Assumptions!G25 -> 0.0676
B7: ERP, typed (ERP basis 1) | C7: =Assumptions!G26 -> 0.06
B8: ERP shift (pp) | C8: =Assumptions!G27 -> 0
B9: ERP move in std. dev. of its history (k) | C9: =Assumptions!G28 -> 0
B10: ERP basis (1 typed, 2 Ibovespa 10y average, 3 each box's 10y average) | C10: =ERPBasis -> 1
B11: Earnings growth vs consensus path, years 2-5 (pp per year) | C11: =Assumptions!G31 -> 0
B12: Long-term nominal growth (default) | C12: =Assumptions!G32 -> 0.047
B13: Long-term ROE vs 10y average (pp) | C13: =Assumptions!G33 -> 0
B14: Selic cut vs today (pp) | C14: =Assumptions!G24 -> 2.25
B15: Discount-rate convention (1 house: real rate + ERP; 2 Fisher: with IPCA) | C15: =RateConv -> 1
B17: Timeline (shared by every box)
C18: Today | D18: Year 1 | E18: Year 2 | F18: Year 3 | G18: Year 4 | H18: Year 5 | I18: Terminal | J18: How it is calculated
B19: Year (t) | C19: 0 | D19: 1 | E19: 2 | F19: 3 | G19: 4 | H19: 5
B20: End of the forward year | C20: =PxDate -> 46300 | D20: =EDATE(PxDate,12*D19) -> 46665 | E20: =EDATE(PxDate,12*E19) -> 47031 | F20: =EDATE(PxDate,12*F19) -> 47396 | G20: =EDATE(PxDate,12*G19) -> 47761 | H20: =EDATE(PxDate,12*H19) -> 48126
B21: Inflation (IPCA) | D21: =IPCA1 -> 0.04 | E21: =IPCA2 -> 0.04 | F21: =IPCALT -> 0.04 | G21: =IPCALT -> 0.04 | H21: =IPCALT -> 0.04 | I21: =IPCALT -> 0.04
B22: Price index (today = 1) | C22: 1 | D22: =C22*(1+D21) -> 1.04 | E22: =D22*(1+E21) -> 1.0816 | F22: =E22*(1+F21) -> 1.124864 | G22: =F22*(1+G21) -> 1.1698586 | H22: =G22*(1+H21) -> 1.2166529 | J22: Cash flows are nominal (consensus). House convention: discounted at real rate + ERP. Fisher: at (1 + real rate + ERP) x (1 + IPCA) - 1.
B23: Deflator for discounting (1 under the house convention) | C23: 1 | D23: =IF(RateConv=1,1,D22) -> 1 | E23: =IF(RateConv=1,1,E22) -> 1 | F23: =IF(RateConv=1,1,F22) -> 1 | G23: =IF(RateConv=1,1,G22) -> 1 | H23: =IF(RateConv=1,1,H22) -> 1 | J23: Used by the closed-form checks: FCFE / deflator discounted at (1 + real rate + ERP) gives the same value under either convention.
B25: Ibovespa = sum of the four boxes (Custom)
C26: Today | D26: Year 1 | E26: Year 2 | F26: Year 3 | G26: Year 4 | H26: Year 5 | I26: Terminal | J26: How it is calculated
B27: Index points | C27: =C49+C78+C107+C136 -> 208431.92
B28: Earnings (index pts) | D28: =D58+D87+D116+D145 -> 22676.853 | E28: =E58+E87+E116+E145 -> 24350.806 | F28: =F58+F87+F116+F145 -> 26086.104 | G28: =G58+G87+G116+G145 -> 27684.137 | H28: =H58+H87+H116+H145 -> 28985.291
B29: Book value at the start of the year | D29: =D60+D89+D118+D147 -> 126386.42 | E29: =E60+E89+E118+E147 -> 137942.6 | F29: =F60+F89+F118+F147 -> 148132.24 | G29: =G60+G89+G118+G147 -> 157415.3 | H29: =H60+H89+H118+H147 -> 164813.82 | I29: =I60+I89+I118+I147 -> 172560.07
B30: Free cash flow to equity (FCFE) | D30: =D62+D91+D120+D149 -> 11120.667 | E30: =E62+E91+E120+E149 -> 14161.17 | F30: =F62+F91+F120+F149 -> 16803.038 | G30: =G62+G91+G120+G149 -> 20285.618 | H30: =H62+H91+H120+H149 -> 21239.042
B31: Present value of FCFE | C31: =C64+C93+C122+C151 -> 56918.357 | D31: =D64+D93+D122+D151 -> 9862.245 | E31: =E64+E93+E122+E151 -> 11137.533 | F31: =F64+F93+F122+F151 -> 11719.865 | G31: =G64+G93+G122+G151 -> 12547.811 | H31: =H64+H93+H122+H151 -> 11650.903
B32: Present value of the terminal value | C32: =C66+C95+C124+C153 -> 151346.1
B33: Equity value today (index pts) | C33: =C67+C96+C125+C154 -> 208264.45
B34: Fair value at the horizon (index pts) | C34: =C68+C97+C126+C155 -> 223718.33
B35: Upside (fair value / index points today - 1) | C35: =C34/C27-1 -> 0.073340058
B36: ROE (sum of earnings / sum of book value) | D36: =D28/D29 -> 0.17942476 | E36: =E28/E29 -> 0.17652854 | F36: =F28/F29 -> 0.17610011 | G36: =G28/G29 -> 0.17586687 | H36: =H28/H29 -> 0.17586687
B37: Implied 12m fwd P/E at the horizon (fair value / next 12m earnings) | C37: =C34/IF(Horizon=1,E28,D28) -> 9.187307
B38: 12m fwd P/E today (consensus year-1 earnings) | C38: ='Boxes Now'!Y10 -> 9.6218817
B39: Terminal value / equity value | C39: =C32/C33 -> 0.72670153
B40: Contribution to the Ibovespa upside (pp)
B41: Financials | C41: =(C68-C49)/C27*100 -> 4.7162468
B42: Defensives | C42: =(C97-C78)/C27*100 -> -6.5586793
B43: Cyclicals | C43: =(C126-C107)/C27*100 -> -0.65493106
B44: Commodities | C44: =(C155-C136)/C27*100 -> 9.8313694
B47: Financials
C48: Today | D48: Year 1 | E48: Year 2 | F48: Year 3 | G48: Year 4 | H48: Year 5 | I48: Terminal | J48: How it is calculated
B49: Index points | C49: ='Boxes Now'!F6 -> 60927.304 | J49: Boxes Now (members' weight x Ibovespa close).
B50: Earnings change from the Selic scenario (years 1-2) | C50: =IF(UseEPS=1,Assumptions!$C$55*$C$14,0) -> 0.062139945 | J50: Box EPS sensitivity to the Selic (Assumptions section 5) x Selic cut; applied to years 1 and 2 (0 if UseEPS = 0).
B51: Equity risk premium (ERP) | C51: =IF(ISNUMBER(Assumptions!G80),Assumptions!G80,CHOOSE($C$10,$C$7,ErpHistIbov,History!$R$8)+$C$8/100-$C$9*CHOOSE($C$10,ErpSdIbov,ErpSdIbov,History!$R$9)) -> 0.06 | J51: Override if typed; else the basis ERP (1 typed, 2 Ibovespa 10y average, 3 this box's 10y average) + shift - k x sd of its history (History).
B52: Cost of equity = real rate + ERP | C52: =$C$6+C51 -> 0.1276 | J52: 5y real rate (scenario) + ERP. House convention: this is the discount rate (Target!B55).
B53: Discount rate of the nominal cash flows | D53: =IF(RateConv=1,$C52,(1+$C52)*(1+D$21)-1) -> 0.1276 | E53: =IF(RateConv=1,$C52,(1+$C52)*(1+E$21)-1) -> 0.1276 | F53: =IF(RateConv=1,$C52,(1+$C52)*(1+F$21)-1) -> 0.1276 | G53: =IF(RateConv=1,$C52,(1+$C52)*(1+G$21)-1) -> 0.1276 | H53: =IF(RateConv=1,$C52,(1+$C52)*(1+H$21)-1) -> 0.1276 | I53: =IF(RateConv=1,$C52,(1+$C52)*(1+IPCALT)-1) -> 0.1276 | J53: House convention: = cost of equity. Fisher: (1 + cost of equity) x (1 + IPCA of the year) - 1; terminal uses the long-term IPCA.
B54: Discount factor | C54: 1 | D54: =C54/(1+D53) -> 0.8868393 | E54: =D54/(1+E53) -> 0.78648395 | F54: =E54/(1+F53) -> 0.69748488 | G54: =F54/(1+G53) -> 0.61855701 | H54: =G54/(1+H53) -> 0.54856067 | J54: Product of 1 / (1 + nominal cost of equity) up to the year.
B55: Long-term ROE | C55: =IF(ISNUMBER(Assumptions!G66),Assumptions!G66,CHOOSE(RoeLT,'Boxes Now'!Z6,'Boxes Now'!W6)+$C$13/100) -> 0.19949374 | J55: RoeLT 1: 10-year average of the box's 12m fwd ROE (History); 2: consensus year-2 ROE. Plus the shift in Assumptions, or the override.
B56: Long-term nominal growth | C56: =IF(ISNUMBER(Assumptions!G73),Assumptions!G73,$C$12) -> 0.047 | J56: Long-term nominal growth of the scenario (house 4.7%), or the override.
B57: Earnings growth | E57: ='Boxes Now'!$X$6+$C$11/100 -> 0.11687154 | F57: ='Boxes Now'!$X$6+($C56-'Boxes Now'!$X$6)*MIN(1,(F$19-2)/(GrowthYear-2))+$C$11/100 -> 0.093581024 | G57: ='Boxes Now'!$X$6+($C56-'Boxes Now'!$X$6)*MIN(1,(G$19-2)/(GrowthYear-2))+$C$11/100 -> 0.070290512 | H57: ='Boxes Now'!$X$6+($C56-'Boxes Now'!$X$6)*MIN(1,(H$19-2)/(GrowthYear-2))+$C$11/100 -> 0.047 | I57: =$C56 -> 0.047 | J57: Year 2 = consensus; converges linearly to the long-term growth by GrowthYear; + the scenario's growth add-on in years 2-5; terminal = long term.
B58: Earnings (index pts) | D58: ='Boxes Now'!R6*(1+$C50) -> 6492.3189 | E58: =D58*(1+E57) -> 7251.0862 | F58: =E58*(1+F57) -> 7929.6503 | G58: =F58*(1+G57) -> 8487.0295 | H58: =G58*(1+H57) -> 8885.9199 | I58: =H58*(1+I57) -> 9303.5581 | J58: Year 1 = consensus blended to the forward year (Boxes Now) x (1 + change from rates); then grows at the row above.
B59: ROE | D59: ='Boxes Now'!V6 -> 0.19352714 | E59: ='Boxes Now'!W6 -> 0.19949374 | F59: =$E59+($C55-$E59)*MIN(1,(F$19-2)/(RoeYear-2)) -> 0.19949374 | G59: =$E59+($C55-$E59)*MIN(1,(G$19-2)/(RoeYear-2)) -> 0.19949374 | H59: =$E59+($C55-$E59)*MIN(1,(H$19-2)/(RoeYear-2)) -> 0.19949374 | I59: =$C55 -> 0.19949374 | J59: Years 1-2 = consensus; converges linearly to the long-term ROE by RoeYear (Assumptions).
B60: Book value at the start of the year (index pts) | D60: =D58/D59 -> 33547.33 | E60: =E58/E59 -> 36347.437 | F60: =F58/F59 -> 39748.868 | G60: =G58/G59 -> 42542.836 | H60: =H58/H59 -> 44542.349 | I60: =I58/I59 -> 46635.84 | J60: Equity at the start of the year needed to earn the year's earnings at the year's ROE = earnings / ROE.
B61: Increase in book value during the year | D61: =E60-D60 -> 2800.1069 | E61: =F60-E60 -> 3401.4304 | F61: =G60-F60 -> 2793.9683 | G61: =H60-G60 -> 1999.5133 | H61: =I60-H60 -> 2093.4904 | J61: Book value at the start of next year - at the start of this year = earnings retained to fund growth.
B62: Free cash flow to equity (FCFE) | D62: =D58-D61 -> 3692.212 | E62: =E58-E61 -> 3849.6558 | F62: =F58-F61 -> 5135.682 | G62: =G58-G61 -> 6487.5162 | H62: =H58-H61 -> 6792.4294 | J62: Earnings - increase in book value (what can be paid out). In the long term = earnings x (1 - g / ROE).
B63: FCFE / earnings | D63: =D62/D58 -> 0.56870466 | E63: =E62/E58 -> 0.53090747 | F63: =F62/F58 -> 0.64765555 | G63: =G62/G58 -> 0.76440364 | H63: =H62/H58 -> 0.76440364
B64: Present value of FCFE | C64: =SUM(D64:H64) -> 17623.11 | D64: =D62*D54 -> 3274.3988 | E64: =E62*E54 -> 3027.6925 | F64: =F62*F54 -> 3582.0606 | G64: =G62*G54 -> 4012.8986 | H64: =H62*H54 -> 3726.0596 | J64: FCFE x discount factor. 'Today' = sum of years 1-5.
B65: Terminal value at the end of year 5 | I65: =I58*(1-I57/I59)/(I53-I57) -> 88234.164 | J65: Year-11 earnings x (1 - g / ROE) / (Ke - g), nominal long-term values (Gordon growth).
B66: Present value of the terminal value | C66: =I66 -> 48401.792 | I66: =I65*H54 -> 48401.792
B67: Equity value today (index pts) | C67: =C64+C66 -> 66024.902 | J67: Present value of FCFE (years 1-5) + present value of the terminal value.
B68: Fair value at the horizon (index pts) | C68: =IF(Horizon=1,C67*(1+D53)-D62,C67) -> 70757.467 | J68: Horizon 1: value today x (1 + year-1 discount rate) - year-1 FCFE (paid out during the year) = value in 12 months. Horizon 0: value today.
B69: Upside (fair value / index points today - 1) | C69: =C68/C49-1 -> 0.16134251
B70: Implied 12m fwd P/E at the horizon (fair value / next 12m earnings) | C70: =C68/IF(Horizon=1,E58,D58) -> 9.7581887
B71: 12m fwd P/E today (consensus year-1 earnings) | C71: ='Boxes Now'!Y6 -> 9.9676747 | J71: Index points / consensus year-1 earnings (without the change from rates).
B72: Terminal value / equity value | C72: =C66/C67 -> 0.73308389
B73: FCFE / deflator (for Implied ERP) | D73: =D62/D$23 -> 3692.212 | E73: =E62/E$23 -> 3849.6558 | F73: =F62/F$23 -> 5135.682 | G73: =G62/G$23 -> 6487.5162 | H73: =H62/H$23 -> 6792.4294 | J73: FCFE / deflator (timeline): used by Implied ERP and Sensitivity to re-discount the same cash flows at other rates.
B76: Defensives
C77: Today | D77: Year 1 | E77: Year 2 | F77: Year 3 | G77: Year 4 | H77: Year 5 | I77: Terminal | J77: How it is calculated
B78: Index points | C78: ='Boxes Now'!F7 -> 55822.367 | J78: Boxes Now (members' weight x Ibovespa close).
B79: Earnings change from the Selic scenario (years 1-2) | C79: =IF(UseEPS=1,Assumptions!$C$56*$C$14,0) -> 0.048003624 | J79: Box EPS sensitivity to the Selic (Assumptions section 5) x Selic cut; applied to years 1 and 2 (0 if UseEPS = 0).
B80: Equity risk premium (ERP) | C80: =IF(ISNUMBER(Assumptions!G81),Assumptions!G81,CHOOSE($C$10,$C$7,ErpHistIbov,History!$S$8)+$C$8/100-$C$9*CHOOSE($C$10,ErpSdIbov,ErpSdIbov,History!$S$9)) -> 0.06 | J80: Override if typed; else the basis ERP (1 typed, 2 Ibovespa 10y average, 3 this box's 10y average) + shift - k x sd of its history (History).
B81: Cost of equity = real rate + ERP | C81: =$C$6+C80 -> 0.1276 | J81: 5y real rate (scenario) + ERP. House convention: this is the discount rate (Target!B55).
B82: Discount rate of the nominal cash flows | D82: =IF(RateConv=1,$C81,(1+$C81)*(1+D$21)-1) -> 0.1276 | E82: =IF(RateConv=1,$C81,(1+$C81)*(1+E$21)-1) -> 0.1276 | F82: =IF(RateConv=1,$C81,(1+$C81)*(1+F$21)-1) -> 0.1276 | G82: =IF(RateConv=1,$C81,(1+$C81)*(1+G$21)-1) -> 0.1276 | H82: =IF(RateConv=1,$C81,(1+$C81)*(1+H$21)-1) -> 0.1276 | I82: =IF(RateConv=1,$C81,(1+$C81)*(1+IPCALT)-1) -> 0.1276 | J82: House convention: = cost of equity. Fisher: (1 + cost of equity) x (1 + IPCA of the year) - 1; terminal uses the long-term IPCA.
B83: Discount factor | C83: 1 | D83: =C83/(1+D82) -> 0.8868393 | E83: =D83/(1+E82) -> 0.78648395 | F83: =E83/(1+F82) -> 0.69748488 | G83: =F83/(1+G82) -> 0.61855701 | H83: =G83/(1+H82) -> 0.54856067 | J83: Product of 1 / (1 + nominal cost of equity) up to the year.
B84: Long-term ROE | C84: =IF(ISNUMBER(Assumptions!G67),Assumptions!G67,CHOOSE(RoeLT,'Boxes Now'!Z7,'Boxes Now'!W7)+$C$13/100) -> 0.14793968 | J84: RoeLT 1: 10-year average of the box's 12m fwd ROE (History); 2: consensus year-2 ROE. Plus the shift in Assumptions, or the override.
B85: Long-term nominal growth | C85: =IF(ISNUMBER(Assumptions!G74),Assumptions!G74,$C$12) -> 0.047 | J85: Long-term nominal growth of the scenario (house 4.7%), or the override.
B86: Earnings growth | E86: ='Boxes Now'!$X$7+$C$11/100 -> 0.21201573 | F86: ='Boxes Now'!$X$7+($C85-'Boxes Now'!$X$7)*MIN(1,(F$19-2)/(GrowthYear-2))+$C$11/100 -> 0.15701049 | G86: ='Boxes Now'!$X$7+($C85-'Boxes Now'!$X$7)*MIN(1,(G$19-2)/(GrowthYear-2))+$C$11/100 -> 0.10200524 | H86: ='Boxes Now'!$X$7+($C85-'Boxes Now'!$X$7)*MIN(1,(H$19-2)/(GrowthYear-2))+$C$11/100 -> 0.047 | I86: =$C85 -> 0.047 | J86: Year 2 = consensus; converges linearly to the long-term growth by GrowthYear; + the scenario's growth add-on in years 2-5; terminal = long term.
B87: Earnings (index pts) | D87: ='Boxes Now'!R7*(1+$C79) -> 3989.679 | E87: =D87*(1+E86) -> 4835.5537 | F87: =E87*(1+F86) -> 5594.7863 | G87: =F87*(1+G86) -> 6165.4838 | H87: =G87*(1+H86) -> 6455.2616 | I87: =H87*(1+I86) -> 6758.6589 | J87: Year 1 = consensus blended to the forward year (Boxes Now) x (1 + change from rates); then grows at the row above.
B88: ROE | D88: ='Boxes Now'!V7 -> 0.1309171 | E88: ='Boxes Now'!W7 -> 0.14793968 | F88: =$E88+($C84-$E88)*MIN(1,(F$19-2)/(RoeYear-2)) -> 0.14793968 | G88: =$E88+($C84-$E88)*MIN(1,(G$19-2)/(RoeYear-2)) -> 0.14793968 | H88: =$E88+($C84-$E88)*MIN(1,(H$19-2)/(RoeYear-2)) -> 0.14793968 | I88: =$C84 -> 0.14793968 | J88: Years 1-2 = consensus; converges linearly to the long-term ROE by RoeYear (Assumptions).
B89: Book value at the start of the year (index pts) | D89: =D87/D88 -> 30474.85 | E89: =E87/E88 -> 32685.982 | F89: =F87/F88 -> 37818.024 | G89: =G87/G88 -> 41675.661 | H89: =H87/H88 -> 43634.417 | I89: =I87/I88 -> 45685.235 | J89: Equity at the start of the year needed to earn the year's earnings at the year's ROE = earnings / ROE.
B90: Increase in book value during the year | D90: =E89-D89 -> 2211.1321 | E90: =F89-E89 -> 5132.042 | F90: =G89-F89 -> 3857.6368 | G90: =H89-G89 -> 1958.7561 | H90: =I89-H89 -> 2050.8176 | J90: Book value at the start of next year - at the start of this year = earnings retained to fund growth.
B91: Free cash flow to equity (FCFE) | D91: =D87-D90 -> 1778.5469 | E91: =E87-E90 -> -296.48831 | F91: =F87-F90 -> 1737.1495 | G91: =G87-G90 -> 4206.7278 | H91: =H87-H90 -> 4404.444 | J91: Earnings - increase in book value (what can be paid out). In the long term = earnings x (1 - g / ROE).
B92: FCFE / earnings | D92: =D91/D87 -> 0.44578696 | E92: =E91/E87 -> -0.061314243 | F92: =F91/F87 -> 0.31049435 | G92: =G91/G87 -> 0.68230294 | H92: =H91/H87 -> 0.68230294
B93: Present value of FCFE | C93: =SUM(D93:H93) -> 7573.9432 | D93: =D91*D83 -> 1577.2853 | E93: =E91*E83 -> -233.1833 | F93: =F91*F83 -> 1211.6355 | G93: =G91*G83 -> 2602.1009 | H93: =H91*H83 -> 2416.1047 | J93: FCFE x discount factor. 'Today' = sum of years 1-5.
B94: Terminal value at the end of year 5 | I94: =I87*(1-I86/I88)/(I82-I86) -> 57214.055 | J94: Year-11 earnings x (1 - g / ROE) / (Ke - g), nominal long-term values (Gordon growth).
B95: Present value of the terminal value | C95: =I95 -> 31385.38 | I95: =I94*H83 -> 31385.38
B96: Equity value today (index pts) | C96: =C93+C95 -> 38959.323 | J96: Present value of FCFE (years 1-5) + present value of the terminal value.
B97: Fair value at the horizon (index pts) | C97: =IF(Horizon=1,C96*(1+D82)-D91,C96) -> 42151.986 | J97: Horizon 1: value today x (1 + year-1 discount rate) - year-1 FCFE (paid out during the year) = value in 12 months. Horizon 0: value today.
B98: Upside (fair value / index points today - 1) | C98: =C97/C78-1 -> -0.24489075
B99: Implied 12m fwd P/E at the horizon (fair value / next 12m earnings) | C99: =C97/IF(Horizon=1,E87,D87) -> 8.7170961
B100: 12m fwd P/E today (consensus year-1 earnings) | C100: ='Boxes Now'!Y7 -> 14.663346 | J100: Index points / consensus year-1 earnings (without the change from rates).
B101: Terminal value / equity value | C101: =C95/C96 -> 0.80559356
B102: FCFE / deflator (for Implied ERP) | D102: =D91/D$23 -> 1778.5469 | E102: =E91/E$23 -> -296.48831 | F102: =F91/F$23 -> 1737.1495 | G102: =G91/G$23 -> 4206.7278 | H102: =H91/H$23 -> 4404.444 | J102: FCFE / deflator (timeline): used by Implied ERP and Sensitivity to re-discount the same cash flows at other rates.
B105: Cyclicals
C106: Today | D106: Year 1 | E106: Year 2 | F106: Year 3 | G106: Year 4 | H106: Year 5 | I106: Terminal | J106: How it is calculated
B107: Index points | C107: ='Boxes Now'!F8 -> 26271.075 | J107: Boxes Now (members' weight x Ibovespa close).
B108: Earnings change from the Selic scenario (years 1-2) | C108: =IF(UseEPS=1,Assumptions!$C$57*$C$14,0) -> 0.074269902 | J108: Box EPS sensitivity to the Selic (Assumptions section 5) x Selic cut; applied to years 1 and 2 (0 if UseEPS = 0).
B109: Equity risk premium (ERP) | C109: =IF(ISNUMBER(Assumptions!G82),Assumptions!G82,CHOOSE($C$10,$C$7,ErpHistIbov,History!$T$8)+$C$8/100-$C$9*CHOOSE($C$10,ErpSdIbov,ErpSdIbov,History!$T$9)) -> 0.06 | J109: Override if typed; else the basis ERP (1 typed, 2 Ibovespa 10y average, 3 this box's 10y average) + shift - k x sd of its history (History).
...

Sheet Implied ERP
B1: Ibovespa - Implied ERP: the risk premium that makes the DCF equal today's price
B2: Each column re-discounts the scenario's cash flows at real rate + ERP (convention in use) for ERP = 0.0% to 15.0%; the implied ERP is interpolated where the value crosses the index points.
B3: Legend: | C3: input | D3: assumption | E3: formula
B5: Implied ERP at today's prices, by box and scenario (each scenario's real rate and cash flows)
B6: Group | C6: Bear | D6: Base | E6: Bull | F6: Custom | G6: 10y average (History)
B7: Financials | C7: =IFERROR(IF(C$18>C$21,"< 0%",INDEX($B$21:$B$171,MATCH(C$18,C$21:C$171,-1))+(INDEX(C$21:C$171,MATCH(C$18,C$21:C$171,-1))-C$18)/(INDEX(C$21:C$171,MATCH(C$18,C$21:C$171,-1))-INDEX(C$21:C$171,MATCH(C$18,C$21:C$171,-1)+1))*0.001),"> 15%") -> 0.040959388 | D7: =IFERROR(IF(H$18>H$21,"< 0%",INDEX($B$21:$B$171,MATCH(H$18,H$21:H$171,-1))+(INDEX(H$21:H$171,MATCH(H$18,H$21:H$171,-1))-H$18)/(INDEX(H$21:H$171,MATCH(H$18,H$21:H$171,-1))-INDEX(H$21:H$171,MATCH(H$18,H$21:H$171,-1)+1))*0.001),"> 15%") -> 0.066374616 | E7: =IFERROR(IF(M$18>M$21,"< 0%",INDEX($B$21:$B$171,MATCH(M$18,M$21:M$171,-1))+(INDEX(M$21:M$171,MATCH(M$18,M$21:M$171,-1))-M$18)/(INDEX(M$21:M$171,MATCH(M$18,M$21:M$171,-1))-INDEX(M$21:M$171,MATCH(M$18,M$21:M$171,-1)+1))*0.001),"> 15%") -> 0.082091167 | F7: =IFERROR(IF(R$18>R$21,"< 0%",INDEX($B$21:$B$171,MATCH(R$18,R$21:R$171,-1))+(INDEX(R$21:R$171,MATCH(R$18,R$21:R$171,-1))-R$18)/(INDEX(R$21:R$171,MATCH(R$18,R$21:R$171,-1))-INDEX(R$21:R$171,MATCH(R$18,R$21:R$171,-1)+1))*0.001),"> 15%") -> 0.066374616 | G7: =History!R8 -> 0.083556934
B8: Defensives | C8: =IFERROR(IF(D$18>D$21,"< 0%",INDEX($B$21:$B$171,MATCH(D$18,D$21:D$171,-1))+(INDEX(D$21:D$171,MATCH(D$18,D$21:D$171,-1))-D$18)/(INDEX(D$21:D$171,MATCH(D$18,D$21:D$171,-1))-INDEX(D$21:D$171,MATCH(D$18,D$21:D$171,-1)+1))*0.001),"> 15%") -> 0.015094707 | D8: =IFERROR(IF(I$18>I$21,"< 0%",INDEX($B$21:$B$171,MATCH(I$18,I$21:I$171,-1))+(INDEX(I$21:I$171,MATCH(I$18,I$21:I$171,-1))-I$18)/(INDEX(I$21:I$171,MATCH(I$18,I$21:I$171,-1))-INDEX(I$21:I$171,MATCH(I$18,I$21:I$171,-1)+1))*0.001),"> 15%") -> 0.037952038 | E8: =IFERROR(IF(N$18>N$21,"< 0%",INDEX($B$21:$B$171,MATCH(N$18,N$21:N$171,-1))+(INDEX(N$21:N$171,MATCH(N$18,N$21:N$171,-1))-N$18)/(INDEX(N$21:N$171,MATCH(N$18,N$21:N$171,-1))-INDEX(N$21:N$171,MATCH(N$18,N$21:N$171,-1)+1))*0.001),"> 15%") -> 0.050920125 | F8: =IFERROR(IF(S$18>S$21,"< 0%",INDEX($B$21:$B$171,MATCH(S$18,S$21:S$171,-1))+(INDEX(S$21:S$171,MATCH(S$18,S$21:S$171,-1))-S$18)/(INDEX(S$21:S$171,MATCH(S$18,S$21:S$171,-1))-INDEX(S$21:S$171,MATCH(S$18,S$21:S$171,-1)+1))*0.001),"> 15%") -> 0.037952038 | G8: =History!S8 -> 0.040024755
B9: Cyclicals | C9: =IFERROR(IF(E$18>E$21,"< 0%",INDEX($B$21:$B$171,MATCH(E$18,E$21:E$171,-1))+(INDEX(E$21:E$171,MATCH(E$18,E$21:E$171,-1))-E$18)/(INDEX(E$21:E$171,MATCH(E$18,E$21:E$171,-1))-INDEX(E$21:E$171,MATCH(E$18,E$21:E$171,-1)+1))*0.001),"> 15%") -> 0.026174653 | D9: =IFERROR(IF(J$18>J$21,"< 0%",INDEX($B$21:$B$171,MATCH(J$18,J$21:J$171,-1))+(INDEX(J$21:J$171,MATCH(J$18,J$21:J$171,-1))-J$18)/(INDEX(J$21:J$171,MATCH(J$18,J$21:J$171,-1))-INDEX(J$21:J$171,MATCH(J$18,J$21:J$171,-1)+1))*0.001),"> 15%") -> 0.051297126 | E9: =IFERROR(IF(O$18>O$21,"< 0%",INDEX($B$21:$B$171,MATCH(O$18,O$21:O$171,-1))+(INDEX(O$21:O$171,MATCH(O$18,O$21:O$171,-1))-O$18)/(INDEX(O$21:O$171,MATCH(O$18,O$21:O$171,-1))-INDEX(O$21:O$171,MATCH(O$18,O$21:O$171,-1)+1))*0.001),"> 15%") -> 0.066691219 | F9: =IFERROR(IF(T$18>T$21,"< 0%",INDEX($B$21:$B$171,MATCH(T$18,T$21:T$171,-1))+(INDEX(T$21:T$171,MATCH(T$18,T$21:T$171,-1))-T$18)/(INDEX(T$21:T$171,MATCH(T$18,T$21:T$171,-1))-INDEX(T$21:T$171,MATCH(T$18,T$21:T$171,-1)+1))*0.001),"> 15%") -> 0.051297126 | G9: =History!T8 -> 0.031540174
B10: Commodities | C10: =IFERROR(IF(F$18>F$21,"< 0%",INDEX($B$21:$B$171,MATCH(F$18,F$21:F$171,-1))+(INDEX(F$21:F$171,MATCH(F$18,F$21:F$171,-1))-F$18)/(INDEX(F$21:F$171,MATCH(F$18,F$21:F$171,-1))-INDEX(F$21:F$171,MATCH(F$18,F$21:F$171,-1)+1))*0.001),"> 15%") -> 0.056091266 | D10: =IFERROR(IF(K$18>K$21,"< 0%",INDEX($B$21:$B$171,MATCH(K$18,K$21:K$171,-1))+(INDEX(K$21:K$171,MATCH(K$18,K$21:K$171,-1))-K$18)/(INDEX(K$21:K$171,MATCH(K$18,K$21:K$171,-1))-INDEX(K$21:K$171,MATCH(K$18,K$21:K$171,-1)+1))*0.001),"> 15%") -> 0.078554438 | E10: =IFERROR(IF(P$18>P$21,"< 0%",INDEX($B$21:$B$171,MATCH(P$18,P$21:P$171,-1))+(INDEX(P$21:P$171,MATCH(P$18,P$21:P$171,-1))-P$18)/(INDEX(P$21:P$171,MATCH(P$18,P$21:P$171,-1))-INDEX(P$21:P$171,MATCH(P$18,P$21:P$171,-1)+1))*0.001),"> 15%") -> 0.09112991 | F10: =IFERROR(IF(U$18>U$21,"< 0%",INDEX($B$21:$B$171,MATCH(U$18,U$21:U$171,-1))+(INDEX(U$21:U$171,MATCH(U$18,U$21:U$171,-1))-U$18)/(INDEX(U$21:U$171,MATCH(U$18,U$21:U$171,-1))-INDEX(U$21:U$171,MATCH(U$18,U$21:U$171,-1)+1))*0.001),"> 15%") -> 0.078554438 | G10: =History!U8 -> 0.10567744
B11: Ibovespa | C11: =IFERROR(IF(G$18>G$21,"< 0%",INDEX($B$21:$B$171,MATCH(G$18,G$21:G$171,-1))+(INDEX(G$21:G$171,MATCH(G$18,G$21:G$171,-1))-G$18)/(INDEX(G$21:G$171,MATCH(G$18,G$21:G$171,-1))-INDEX(G$21:G$171,MATCH(G$18,G$21:G$171,-1)+1))*0.001),"> 15%") -> 0.036072978 | D11: =IFERROR(IF(L$18>L$21,"< 0%",INDEX($B$21:$B$171,MATCH(L$18,L$21:L$171,-1))+(INDEX(L$21:L$171,MATCH(L$18,L$21:L$171,-1))-L$18)/(INDEX(L$21:L$171,MATCH(L$18,L$21:L$171,-1))-INDEX(L$21:L$171,MATCH(L$18,L$21:L$171,-1)+1))*0.001),"> 15%") -> 0.059938855 | E11: =IFERROR(IF(Q$18>Q$21,"< 0%",INDEX($B$21:$B$171,MATCH(Q$18,Q$21:Q$171,-1))+(INDEX(Q$21:Q$171,MATCH(Q$18,Q$21:Q$171,-1))-Q$18)/(INDEX(Q$21:Q$171,MATCH(Q$18,Q$21:Q$171,-1))-INDEX(Q$21:Q$171,MATCH(Q$18,Q$21:Q$171,-1)+1))*0.001),"> 15%") -> 0.073981108 | F11: =IFERROR(IF(V$18>V$21,"< 0%",INDEX($B$21:$B$171,MATCH(V$18,V$21:V$171,-1))+(INDEX(V$21:V$171,MATCH(V$18,V$21:V$171,-1))-V$18)/(INDEX(V$21:V$171,MATCH(V$18,V$21:V$171,-1))-INDEX(V$21:V$171,MATCH(V$18,V$21:V$171,-1)+1))*0.001),"> 15%") -> 0.059938855 | G11: =History!V8 -> 0.074470831
B13: ERP = cost of equity - 5y real rate, read with each scenario's cash flows and the discount-rate convention in use (RateConv). The History column uses steady-state cash flows.
B15: Grid: equity value (index pts) at each ERP
C16: Bear (real rate: DCF Bear!C6) | H16: Base (real rate: DCF Base!C6) | M16: Bull (real rate: DCF Bull!C6) | R16: Custom (real rate: DCF Custom!C6)
B17: ERP | C17: Financials | D17: Defensives | E17: Cyclicals | F17: Commodities | G17: Ibovespa | H17: Financials | I17: Defensives | J17: Cyclicals | K17: Commodities | L17: Ibovespa | M17: Financials | N17: Defensives | O17: Cyclicals | P17: Commodities | Q17: Ibovespa | R17: Financials | S17: Defensives | T17: Cyclicals | U17: Commodities | V17: Ibovespa
B18: Index points today | C18: ='DCF Bear'!$C$49 -> 60927.304 | D18: ='DCF Bear'!$C$78 -> 55822.367 | E18: ='DCF Bear'!$C$107 -> 26271.075 | F18: ='DCF Bear'!$C$136 -> 65411.174 | G18: ='DCF Bear'!$C$27 -> 208431.92 | H18: ='DCF Base'!$C$49 -> 60927.304 | I18: ='DCF Base'!$C$78 -> 55822.367 | J18: ='DCF Base'!$C$107 -> 26271.075 | K18: ='DCF Base'!$C$136 -> 65411.174 | L18: ='DCF Base'!$C$27 -> 208431.92 | M18: ='DCF Bull'!$C$49 -> 60927.304 | N18: ='DCF Bull'!$C$78 -> 55822.367 | O18: ='DCF Bull'!$C$107 -> 26271.075 | P18: ='DCF Bull'!$C$136 -> 65411.174 | Q18: ='DCF Bull'!$C$27 -> 208431.92 | R18: ='DCF Custom'!$C$49 -> 60927.304 | S18: ='DCF Custom'!$C$78 -> 55822.367 | T18: ='DCF Custom'!$C$107 -> 26271.075 | U18: ='DCF Custom'!$C$136 -> 65411.174 | V18: ='DCF Custom'!$C$27 -> 208431.92
B19: DCF value today (DCF sheet) | C19: ='DCF Bear'!$C$67 -> 49428.491 | D19: ='DCF Bear'!$C$96 -> 29906.892 | E19: ='DCF Bear'!$C$125 -> 17214.384 | F19: ='DCF Bear'!$C$154 -> 63089.254 | G19: ='DCF Bear'!$C$33 -> 159639.02 | H19: ='DCF Base'!$C$67 -> 66024.902 | I19: ='DCF Base'!$C$96 -> 38959.323 | J19: ='DCF Base'!$C$125 -> 23184.563 | K19: ='DCF Base'!$C$154 -> 80095.664 | L19: ='DCF Base'!$C$33 -> 208264.45 | M19: ='DCF Bull'!$C$67 -> 82737.941 | N19: ='DCF Bull'!$C$96 -> 47258.379 | O19: ='DCF Bull'!$C$125 -> 29196.162 | P19: ='DCF Bull'!$C$154 -> 96033.835 | Q19: ='DCF Bull'!$C$33 -> 255226.32 | R19: ='DCF Custom'!$C$67 -> 66024.902 | S19: ='DCF Custom'!$C$96 -> 38959.323 | T19: ='DCF Custom'!$C$125 -> 23184.563 | U19: ='DCF Custom'!$C$154 -> 80095.664 | V19: ='DCF Custom'!$C$33 -> 208264.45
B20: Check: closed form at the ERP used | C20: =SUMPRODUCT('DCF Bear'!$D$73:$H$73,(1+'DCF Bear'!$C$52)^(-'DCF Bear'!$D$19:$H$19))+'DCF Bear'!$I$58*(1-'DCF Bear'!$I$57/'DCF Bear'!$I$59)/((1+'DCF Bear'!$C$52)*IF(RateConv=1,1,1+IPCALT)-1-'DCF Bear'!$I$57)/'DCF Bear'!$H$23*(1+'DCF Bear'!$C$52)^(-5) -> 49428.491 | D20: =SUMPRODUCT('DCF Bear'!$D$102:$H$102,(1+'DCF Bear'!$C$81)^(-'DCF Bear'!$D$19:$H$19))+'DCF Bear'!$I$87*(1-'DCF Bear'!$I$86/'DCF Bear'!$I$88)/((1+'DCF Bear'!$C$81)*IF(RateConv=1,1,1+IPCALT)-1-'DCF Bear'!$I$86)/'DCF Bear'!$H$23*(1+'DCF Bear'!$C$81)^(-5) -> 29906.892 | E20: =SUMPRODUCT('DCF Bear'!$D$131:$H$131,(1+'DCF Bear'!$C$110)^(-'DCF Bear'!$D$19:$H$19))+'DCF Bear'!$I$116*(1-'DCF Bear'!$I$115/'DCF Bear'!$I$117)/((1+'DCF Bear'!$C$110)*IF(RateConv=1,1,1+IPCALT)-1-'DCF Bear'!$I$115)/'DCF Bear'!$H$23*(1+'DCF Bear'!$C$110)^(-5) -> 17214.384 | F20: =SUMPRODUCT('DCF Bear'!$D$160:$H$160,(1+'DCF Bear'!$C$139)^(-'DCF Bear'!$D$19:$H$19))+'DCF Bear'!$I$145*(1-'DCF Bear'!$I$144/'DCF Bear'!$I$146)/((1+'DCF Bear'!$C$139)*IF(RateConv=1,1,1+IPCALT)-1-'DCF Bear'!$I$144)/'DCF Bear'!$H$23*(1+'DCF Bear'!$C$139)^(-5) -> 63089.254 | G20: =C20+D20+E20+F20 -> 159639.02 | H20: =SUMPRODUCT('DCF Base'!$D$73:$H$73,(1+'DCF Base'!$C$52)^(-'DCF Base'!$D$19:$H$19))+'DCF Base'!$I$58*(1-'DCF Base'!$I$57/'DCF Base'!$I$59)/((1+'DCF Base'!$C$52)*IF(RateConv=1,1,1+IPCALT)-1-'DCF Base'!$I$57)/'DCF Base'!$H$23*(1+'DCF Base'!$C$52)^(-5) -> 66024.902 | I20: =SUMPRODUCT('DCF Base'!$D$102:$H$102,(1+'DCF Base'!$C$81)^(-'DCF Base'!$D$19:$H$19))+'DCF Base'!$I$87*(1-'DCF Base'!$I$86/'DCF Base'!$I$88)/((1+'DCF Base'!$C$81)*IF(RateConv=1,1,1+IPCALT)-1-'DCF Base'!$I$86)/'DCF Base'!$H$23*(1+'DCF Base'!$C$81)^(-5) -> 38959.323 | J20: =SUMPRODUCT('DCF Base'!$D$131:$H$131,(1+'DCF Base'!$C$110)^(-'DCF Base'!$D$19:$H$19))+'DCF Base'!$I$116*(1-'DCF Base'!$I$115/'DCF Base'!$I$117)/((1+'DCF Base'!$C$110)*IF(RateConv=1,1,1+IPCALT)-1-'DCF Base'!$I$115)/'DCF Base'!$H$23*(1+'DCF Base'!$C$110)^(-5) -> 23184.563 | K20: =SUMPRODUCT('DCF Base'!$D$160:$H$160,(1+'DCF Base'!$C$139)^(-'DCF Base'!$D$19:$H$19))+'DCF Base'!$I$145*(1-'DCF Base'!$I$144/'DCF Base'!$I$146)/((1+'DCF Base'!$C$139)*IF(RateConv=1,1,1+IPCALT)-1-'DCF Base'!$I$144)/'DCF Base'!$H$23*(1+'DCF Base'!$C$139)^(-5) -> 80095.664 | L20: =H20+I20+J20+K20 -> 208264.45 | M20: =SUMPRODUCT('DCF Bull'!$D$73:$H$73,(1+'DCF Bull'!$C$52)^(-'DCF Bull'!$D$19:$H$19))+'DCF Bull'!$I$58*(1-'DCF Bull'!$I$57/'DCF Bull'!$I$59)/((1+'DCF Bull'!$C$52)*IF(RateConv=1,1,1+IPCALT)-1-'DCF Bull'!$I$57)/'DCF Bull'!$H$23*(1+'DCF Bull'!$C$52)^(-5) -> 82737.941 | N20: =SUMPRODUCT('DCF Bull'!$D$102:$H$102,(1+'DCF Bull'!$C$81)^(-'DCF Bull'!$D$19:$H$19))+'DCF Bull'!$I$87*(1-'DCF Bull'!$I$86/'DCF Bull'!$I$88)/((1+'DCF Bull'!$C$81)*IF(RateConv=1,1,1+IPCALT)-1-'DCF Bull'!$I$86)/'DCF Bull'!$H$23*(1+'DCF Bull'!$C$81)^(-5) -> 47258.379 | O20: =SUMPRODUCT('DCF Bull'!$D$131:$H$131,(1+'DCF Bull'!$C$110)^(-'DCF Bull'!$D$19:$H$19))+'DCF Bull'!$I$116*(1-'DCF Bull'!$I$115/'DCF Bull'!$I$117)/((1+'DCF Bull'!$C$110)*IF(RateConv=1,1,1+IPCALT)-1-'DCF Bull'!$I$115)/'DCF Bull'!$H$23*(1+'DCF Bull'!$C$110)^(-5) -> 29196.162 | P20: =SUMPRODUCT('DCF Bull'!$D$160:$H$160,(1+'DCF Bull'!$C$139)^(-'DCF Bull'!$D$19:$H$19))+'DCF Bull'!$I$145*(1-'DCF Bull'!$I$144/'DCF Bull'!$I$146)/((1+'DCF Bull'!$C$139)*IF(RateConv=1,1,1+IPCALT)-1-'DCF Bull'!$I$144)/'DCF Bull'!$H$23*(1+'DCF Bull'!$C$139)^(-5) -> 96033.835 | Q20: =M20+N20+O20+P20 -> 255226.32 | R20: =SUMPRODUCT('DCF Custom'!$D$73:$H$73,(1+'DCF Custom'!$C$52)^(-'DCF Custom'!$D$19:$H$19))+'DCF Custom'!$I$58*(1-'DCF Custom'!$I$57/'DCF Custom'!$I$59)/((1+'DCF Custom'!$C$52)*IF(RateConv=1,1,1+IPCALT)-1-'DCF Custom'!$I$57)/'DCF Custom'!$H$23*(1+'DCF Custom'!$C$52)^(-5) -> 66024.902 | S20: =SUMPRODUCT('DCF Custom'!$D$102:$H$102,(1+'DCF Custom'!$C$81)^(-'DCF Custom'!$D$19:$H$19))+'DCF Custom'!$I$87*(1-'DCF Custom'!$I$86/'DCF Custom'!$I$88)/((1+'DCF Custom'!$C$81)*IF(RateConv=1,1,1+IPCALT)-1-'DCF Custom'!$I$86)/'DCF Custom'!$H$23*(1+'DCF Custom'!$C$81)^(-5) -> 38959.323 | T20: =SUMPRODUCT('DCF Custom'!$D$131:$H$131,(1+'DCF Custom'!$C$110)^(-'DCF Custom'!$D$19:$H$19))+'DCF Custom'!$I$116*(1-'DCF Custom'!$I$115/'DCF Custom'!$I$117)/((1+'DCF Custom'!$C$110)*IF(RateConv=1,1,1+IPCALT)-1-'DCF Custom'!$I$115)/'DCF Custom'!$H$23*(1+'DCF Custom'!$C$110)^(-5) -> 23184.563 | U20: =SUMPRODUCT('DCF Custom'!$D$160:$H$160,(1+'DCF Custom'!$C$139)^(-'DCF Custom'!$D$19:$H$19))+'DCF Custom'!$I$145*(1-'DCF Custom'!$I$144/'DCF Custom'!$I$146)/((1+'DCF Custom'!$C$139)*IF(RateConv=1,1,1+IPCALT)-1-'DCF Custom'!$I$144)/'DCF Custom'!$H$23*(1+'DCF Custom'!$C$139)^(-5) -> 80095.664 | V20: =R20+S20+T20+U20 -> 208264.45
B21: 0 | C21: =SUMPRODUCT('DCF Bear'!$D$73:$H$73,(1+'DCF Bear'!$C$6+$B21)^(-'DCF Bear'!$D$19:$H$19))+'DCF Bear'!$I$58*(1-'DCF Bear'!$I$57/'DCF Bear'!$I$59)/((1+'DCF Bear'!$C$6+$B21)*IF(RateConv=1,1,1+IPCALT)-1-'DCF Bear'!$I$57)/'DCF Bear'!$H$23*(1+'DCF Bear'!$C$6+$B21)^(-5) -> 120215.66 | D21: =SUMPRODUCT('DCF Bear'!$D$102:$H$102,(1+'DCF Bear'!$C$6+$B21)^(-'DCF Bear'!$D$19:$H$19))+'DCF Bear'!$I$87*(1-'DCF Bear'!$I$86/'DCF Bear'!$I$88)/((1+'DCF Bear'!$C$6+$B21)*IF(RateConv=1,1,1+IPCALT)-1-'DCF Bear'!$I$86)/'DCF Bear'!$H$23*(1+'DCF Bear'!$C$6+$B21)^(-5) -> 76811.279 | E21: =SUMPRODUCT('DCF Bear'!$D$131:$H$131,(1+'DCF Bear'!$C$6+$B21)^(-'DCF Bear'!$D$19:$H$19))+'DCF Bear'!$I$116*(1-'DCF Bear'!$I$115/'DCF Bear'!$I$117)/((1+'DCF Bear'!$C$6+$B21)*IF(RateConv=1,1,1+IPCALT)-1-'DCF Bear'!$I$115)/'DCF Bear'!$H$23*(1+'DCF Bear'!$C$6+$B21)^(-5) -> 43128.962 | F21: =SUMPRODUCT('DCF Bear'!$D$160:$H$160,(1+'DCF Bear'!$C$6+$B21)^(-'DCF Bear'!$D$19:$H$19))+'DCF Bear'!$I$145*(1-'DCF Bear'!$I$144/'DCF Bear'!$I$146)/((1+'DCF Bear'!$C$6+$B21)*IF(RateConv=1,1,1+IPCALT)-1-'DCF Bear'!$I$144)/'DCF Bear'!$H$23*(1+'DCF Bear'!$C$6+$B21)^(-5) -> 144279.06 | G21: =C21+D21+E21+F21 -> 384434.96 | H21: =SUMPRODUCT('DCF Base'!$D$73:$H$73,(1+'DCF Base'!$C$6+$B21)^(-'DCF Base'!$D$19:$H$19))+'DCF Base'!$I$58*(1-'DCF Base'!$I$57/'DCF Base'!$I$59)/((1+'DCF Base'!$C$6+$B21)*IF(RateConv=1,1,1+IPCALT)-1-'DCF Base'!$I$57)/'DCF Base'!$H$23*(1+'DCF Base'!$C$6+$B21)^(-5) -> 269869.25 | I21: =SUMPRODUCT('DCF Base'!$D$102:$H$102,(1+'DCF Base'!$C$6+$B21)^(-'DCF Base'!$D$19:$H$19))+'DCF Base'!$I$87*(1-'DCF Base'!$I$86/'DCF Base'!$I$88)/((1+'DCF Base'!$C$6+$B21)*IF(RateConv=1,1,1+IPCALT)-1-'DCF Base'!$I$86)/'DCF Base'!$H$23*(1+'DCF Base'!$C$6+$B21)^(-5) -> 170656.42 | J21: =SUMPRODUCT('DCF Base'!$D$131:$H$131,(1+'DCF Base'!$C$6+$B21)^(-'DCF Base'!$D$19:$H$19))+'DCF Base'!$I$116*(1-'DCF Base'!$I$115/'DCF Base'!$I$117)/((1+'DCF Base'!$C$6+$B21)*IF(RateConv=1,1,1+IPCALT)-1-'DCF Base'!$I$115)/'DCF Base'!$H$23*(1+'DCF Base'!$C$6+$B21)^(-5) -> 98091.15 | K21: =SUMPRODUCT('DCF Base'!$D$160:$H$160,(1+'DCF Base'!$C$6+$B21)^(-'DCF Base'!$D$19:$H$19))+'DCF Base'!$I$145*(1-'DCF Base'!$I$144/'DCF Base'!$I$146)/((1+'DCF Base'!$C$6+$B21)*IF(RateConv=1,1,1+IPCALT)-1-'DCF Base'!$I$144)/'DCF Base'!$H$23*(1+'DCF Base'!$C$6+$B21)^(-5) -> 307306.78 | L21: =H21+I21+J21+K21 -> 845923.6 | M21: =SUMPRODUCT('DCF Bull'!$D$73:$H$73,(1+'DCF Bull'!$C$6+$B21)^(-'DCF Bull'!$D$19:$H$19))+'DCF Bull'!$I$58*(1-'DCF Bull'!$I$57/'DCF Bull'!$I$59)/((1+'DCF Bull'!$C$6+$B21)*IF(RateConv=1,1,1+IPCALT)-1-'DCF Bull'!$I$57)/'DCF Bull'!$H$23*(1+'DCF Bull'!$C$6+$B21)^(-5) -> 757768.63 | N21: =SUMPRODUCT('DCF Bull'!$D$102:$H$102,(1+'DCF Bull'!$C$6+$B21)^(-'DCF Bull'!$D$19:$H$19))+'DCF Bull'!$I$87*(1-'DCF Bull'!$I$86/'DCF Bull'!$I$88)/((1+'DCF Bull'!$C$6+$B21)*IF(RateConv=1,1,1+IPCALT)-1-'DCF Bull'!$I$86)/'DCF Bull'!$H$23*(1+'DCF Bull'!$C$6+$B21)^(-5) -> 470848.43 | O21: =SUMPRODUCT('DCF Bull'!$D$131:$H$131,(1+'DCF Bull'!$C$6+$B21)^(-'DCF Bull'!$D$19:$H$19))+'DCF Bull'!$I$116*(1-'DCF Bull'!$I$115/'DCF Bull'!$I$117)/((1+'DCF Bull'!$C$6+$B21)*IF(RateConv=1,1,1+IPCALT)-1-'DCF Bull'!$I$115)/'DCF Bull'!$H$23*(1+'DCF Bull'!$C$6+$B21)^(-5) -> 277905.39 | P21: =SUMPRODUCT('DCF Bull'!$D$160:$H$160,(1+'DCF Bull'!$C$6+$B21)^(-'DCF Bull'!$D$19:$H$19))+'DCF Bull'!$I$145*(1-'DCF Bull'!$I$144/'DCF Bull'!$I$146)/((1+'DCF Bull'!$C$6+$B21)*IF(RateConv=1,1,1+IPCALT)-1-'DCF Bull'!$I$144)/'DCF Bull'!$H$23*(1+'DCF Bull'!$C$6+$B21)^(-5) -> 828397.96 | Q21: =M21+N21+O21+P21 -> 2334920.4 | R21: =SUMPRODUCT('DCF Custom'!$D$73:$H$73,(1+'DCF Custom'!$C$6+$B21)^(-'DCF Custom'!$D$19:$H$19))+'DCF Custom'!$I$58*(1-'DCF Custom'!$I$57/'DCF Custom'!$I$59)/((1+'DCF Custom'!$C$6+$B21)*IF(RateConv=1,1,1+IPCALT)-1-'DCF Custom'!$I$57)/'DCF Custom'!$H$23*(1+'DCF Custom'!$C$6+$B21)^(-5) -> 269869.25 | S21: =SUMPRODUCT('DCF Custom'!$D$102:$H$102,(1+'DCF Custom'!$C$6+$B21)^(-'DCF Custom'!$D$19:$H$19))+'DCF Custom'!$I$87*(1-'DCF Custom'!$I$86/'DCF Custom'!$I$88)/((1+'DCF Custom'!$C$6+$B21)*IF(RateConv=1,1,1+IPCALT)-1-'DCF Custom'!$I$86)/'DCF Custom'!$H$23*(1+'DCF Custom'!$C$6+$B21)^(-5) -> 170656.42 | T21: =SUMPRODUCT('DCF Custom'!$D$131:$H$131,(1+'DCF Custom'!$C$6+$B21)^(-'DCF Custom'!$D$19:$H$19))+'DCF Custom'!$I$116*(1-'DCF Custom'!$I$115/'DCF Custom'!$I$117)/((1+'DCF Custom'!$C$6+$B21)*IF(RateConv=1,1,1+IPCALT)-1-'DCF Custom'!$I$115)/'DCF Custom'!$H$23*(1+'DCF Custom'!$C$6+$B21)^(-5) -> 98091.15 | U21: =SUMPRODUCT('DCF Custom'!$D$160:$H$160,(1+'DCF Custom'!$C$6+$B21)^(-'DCF Custom'!$D$19:$H$19))+'DCF Custom'!$I$145*(1-'DCF Custom'!$I$144/'DCF Custom'!$I$146)/((1+'DCF Custom'!$C$6+$B21)*IF(RateConv=1,1,1+IPCALT)-1-'DCF Custom'!$I$144)/'DCF Custom'!$H$23*(1+'DCF Custom'!$C$6+$B21)^(-5) -> 307306.78 | V21: =R21+S21+T21+U21 -> 845923.6
B22: 0.001 | C22: =SUMPRODUCT('DCF Bear'!$D$73:$H$73,(1+'DCF Bear'!$C$6+$B22)^(-'DCF Bear'!$D$19:$H$19))+'DCF Bear'!$I$58*(1-'DCF Bear'!$I$57/'DCF Bear'!$I$59)/((1+'DCF Bear'!$C$6+$B22)*IF(RateConv=1,1,1+IPCALT)-1-'DCF Bear'!$I$57)/'DCF Bear'!$H$23*(1+'DCF Bear'!$C$6+$B22)^(-5) -> 117453.02 | D22: =SUMPRODUCT('DCF Bear'!$D$102:$H$102,(1+'DCF Bear'!$C$6+$B22)^(-'DCF Bear'!$D$19:$H$19))+'DCF Bear'!$I$87*(1-'DCF Bear'!$I$86/'DCF Bear'!$I$88)/((1+'DCF Bear'!$C$6+$B22)*IF(RateConv=1,1,1+IPCALT)-1-'DCF Bear'!$I$86)/'DCF Bear'!$H$23*(1+'DCF Bear'!$C$6+$B22)^(-5) -> 74973.21 | E22: =SUMPRODUCT('DCF Bear'!$D$131:$H$131,(1+'DCF Bear'!$C$6+$B22)^(-'DCF Bear'!$D$19:$H$19))+'DCF Bear'!$I$116*(1-'DCF Bear'!$I$115/'DCF Bear'!$I$117)/((1+'DCF Bear'!$C$6+$B22)*IF(RateConv=1,1,1+IPCALT)-1-'DCF Bear'!$I$115)/'DCF Bear'!$H$23*(1+'DCF Bear'!$C$6+$B22)^(-5) -> 42115.141 | F22: =SUMPRODUCT('DCF Bear'!$D$160:$H$160,(1+'DCF Bear'!$C$6+$B22)^(-'DCF Bear'!$D$19:$H$19))+'DCF Bear'!$I$145*(1-'DCF Bear'!$I$144/'DCF Bear'!$I$146)/((1+'DCF Bear'!$C$6+$B22)*IF(RateConv=1,1,1+IPCALT)-1-'DCF Bear'!$I$144)/'DCF Bear'!$H$23*(1+'DCF Bear'!$C$6+$B22)^(-5) -> 141128.91 | G22: =C22+D22+E22+F22 -> 375670.27 | H22: =SUMPRODUCT('DCF Base'!$D$73:$H$73,(1+'DCF Base'!$C$6+$B22)^(-'DCF Base'!$D$19:$H$19))+'DCF Base'!$I$58*(1-'DCF Base'!$I$57/'DCF Base'!$I$59)/((1+'DCF Base'!$C$6+$B22)*IF(RateConv=1,1,1+IPCALT)-1-'DCF Base'!$I$57)/'DCF Base'!$H$23*(1+'DCF Base'!$C$6+$B22)^(-5) -> 257173.48 | I22: =SUMPRODUCT('DCF Base'!$D$102:$H$102,(1+'DCF Base'!$C$6+$B22)^(-'DCF Base'!$D$19:$H$19))+'DCF Base'!$I$87*(1-'DCF Base'!$I$86/'DCF Base'!$I$88)/((1+'DCF Base'!$C$6+$B22)*IF(RateConv=1,1,1+IPCALT)-1-'DCF Base'!$I$86)/'DCF Base'!$H$23*(1+'DCF Base'!$C$6+$B22)^(-5) -> 162432.85 | J22: =SUMPRODUCT('DCF Base'!$D$131:$H$131,(1+'DCF Base'!$C$6+$B22)^(-'DCF Base'!$D$19:$H$19))+'DCF Base'!$I$116*(1-'DCF Base'!$I$115/'DCF Base'!$I$117)/((1+'DCF Base'!$C$6+$B22)*IF(RateConv=1,1,1+IPCALT)-1-'DCF Base'!$I$115)/'DCF Base'!$H$23*(1+'DCF Base'!$C$6+$B22)^(-5) -> 93419.473 | K22: =SUMPRODUCT('DCF Base'!$D$160:$H$160,(1+'DCF Base'!$C$6+$B22)^(-'DCF Base'!$D$19:$H$19))+'DCF Base'!$I$145*(1-'DCF Base'!$I$144/'DCF Base'!$I$146)/((1+'DCF Base'!$C$6+$B22)*IF(RateConv=1,1,1+IPCALT)-1-'DCF Base'!$I$144)/'DCF Base'!$H$23*(1+'DCF Base'!$C$6+$B22)^(-5) -> 293194.96 | L22: =H22+I22+J22+K22 -> 806220.76 | M22: =SUMPRODUCT('DCF Bull'!$D$73:$H$73,(1+'DCF Bull'!$C$6+$B22)^(-'DCF Bull'!$D$19:$H$19))+'DCF Bull'!$I$58*(1-'DCF Bull'!$I$57/'DCF Bull'!$I$59)/((1+'DCF Bull'!$C$6+$B22)*IF(RateConv=1,1,1+IPCALT)-1-'DCF Bull'!$I$57)/'DCF Bull'!$H$23*(1+'DCF Bull'!$C$6+$B22)^(-5) -> 672668.89 | N22: =SUMPRODUCT('DCF Bull'!$D$102:$H$102,(1+'DCF Bull'!$C$6+$B22)^(-'DCF Bull'!$D$19:$H$19))+'DCF Bull'!$I$87*(1-'DCF Bull'!$I$86/'DCF Bull'!$I$88)/((1+'DCF Bull'!$C$6+$B22)*IF(RateConv=1,1,1+IPCALT)-1-'DCF Bull'!$I$86)/'DCF Bull'!$H$23*(1+'DCF Bull'!$C$6+$B22)^(-5) -> 417379.63 | O22: =SUMPRODUCT('DCF Bull'!$D$131:$H$131,(1+'DCF Bull'!$C$6+$B22)^(-'DCF Bull'!$D$19:$H$19))+'DCF Bull'!$I$116*(1-'DCF Bull'!$I$115/'DCF Bull'!$I$117)/((1+'DCF Bull'!$C$6+$B22)*IF(RateConv=1,1,1+IPCALT)-1-'DCF Bull'!$I$115)/'DCF Bull'!$H$23*(1+'DCF Bull'!$C$6+$B22)^(-5) -> 246532.16 | P22: =SUMPRODUCT('DCF Bull'!$D$160:$H$160,(1+'DCF Bull'!$C$6+$B22)^(-'DCF Bull'!$D$19:$H$19))+'DCF Bull'!$I$145*(1-'DCF Bull'!$I$144/'DCF Bull'!$I$146)/((1+'DCF Bull'!$C$6+$B22)*IF(RateConv=1,1,1+IPCALT)-1-'DCF Bull'!$I$144)/'DCF Bull'!$H$23*(1+'DCF Bull'!$C$6+$B22)^(-5) -> 736162.82 | Q22: =M22+N22+O22+P22 -> 2072743.5 | R22: =SUMPRODUCT('DCF Custom'!$D$73:$H$73,(1+'DCF Custom'!$C$6+$B22)^(-'DCF Custom'!$D$19:$H$19))+'DCF Custom'!$I$58*(1-'DCF Custom'!$I$57/'DCF Custom'!$I$59)/((1+'DCF Custom'!$C$6+$B22)*IF(RateConv=1,1,1+IPCALT)-1-'DCF Custom'!$I$57)/'DCF Custom'!$H$23*(1+'DCF Custom'!$C$6+$B22)^(-5) -> 257173.48 | S22: =SUMPRODUCT('DCF Custom'!$D$102:$H$102,(1+'DCF Custom'!$C$6+$B22)^(-'DCF Custom'!$D$19:$H$19))+'DCF Custom'!$I$87*(1-'DCF Custom'!$I$86/'DCF Custom'!$I$88)/((1+'DCF Custom'!$C$6+$B22)*IF(RateConv=1,1,1+IPCALT)-1-'DCF Custom'!$I$86)/'DCF Custom'!$H$23*(1+'DCF Custom'!$C$6+$B22)^(-5) -> 162432.85 | T22: =SUMPRODUCT('DCF Custom'!$D$131:$H$131,(1+'DCF Custom'!$C$6+$B22)^(-'DCF Custom'!$D$19:$H$19))+'DCF Custom'!$I$116*(1-'DCF Custom'!$I$115/'DCF Custom'!$I$117)/((1+'DCF Custom'!$C$6+$B22)*IF(RateConv=1,1,1+IPCALT)-1-'DCF Custom'!$I$115)/'DCF Custom'!$H$23*(1+'DCF Custom'!$C$6+$B22)^(-5) -> 93419.473 | U22: =SUMPRODUCT('DCF Custom'!$D$160:$H$160,(1+'DCF Custom'!$C$6+$B22)^(-'DCF Custom'!$D$19:$H$19))+'DCF Custom'!$I$145*(1-'DCF Custom'!$I$144/'DCF Custom'!$I$146)/((1+'DCF Custom'!$C$6+$B22)*IF(RateConv=1,1,1+IPCALT)-1-'DCF Custom'!$I$144)/'DCF Custom'!$H$23*(1+'DCF Custom'!$C$6+$B22)^(-5) -> 293194.96 | V22: =R22+S22+T22+U22 -> 806220.76
B23: 0.002 | C23: =SUMPRODUCT('DCF Bear'!$D$73:$H$73,(1+'DCF Bear'!$C$6+$B23)^(-'DCF Bear'!$D$19:$H$19))+'DCF Bear'!$I$58*(1-'DCF Bear'!$I$57/'DCF Bear'!$I$59)/((1+'DCF Bear'!$C$6+$B23)*IF(RateConv=1,1,1+IPCALT)-1-'DCF Bear'!$I$57)/'DCF Bear'!$H$23*(1+'DCF Bear'!$C$6+$B23)^(-5) -> 114813.18 | D23: =SUMPRODUCT('DCF Bear'!$D$102:$H$102,(1+'DCF Bear'!$C$6+$B23)^(-'DCF Bear'!$D$19:$H$19))+'DCF Bear'!$I$87*(1-'DCF Bear'!$I$86/'DCF Bear'!$I$88)/((1+'DCF Bear'!$C$6+$B23)*IF(RateConv=1,1,1+IPCALT)-1-'DCF Bear'!$I$86)/'DCF Bear'!$H$23*(1+'DCF Bear'!$C$6+$B23)^(-5) -> 73217.119 | E23: =SUMPRODUCT('DCF Bear'!$D$131:$H$131,(1+'DCF Bear'!$C$6+$B23)^(-'DCF Bear'!$D$19:$H$19))+'DCF Bear'!$I$116*(1-'DCF Bear'!$I$115/'DCF Bear'!$I$117)/((1+'DCF Bear'!$C$6+$B23)*IF(RateConv=1,1,1+IPCALT)-1-'DCF Bear'!$I$115)/'DCF Bear'!$H$23*(1+'DCF Bear'!$C$6+$B23)^(-5) -> 41146.475 | F23: =SUMPRODUCT('DCF Bear'!$D$160:$H$160,(1+'DCF Bear'!$C$6+$B23)^(-'DCF Bear'!$D$19:$H$19))+'DCF Bear'!$I$145*(1-'DCF Bear'!$I$144/'DCF Bear'!$I$146)/((1+'DCF Bear'!$C$6+$B23)*IF(RateConv=1,1,1+IPCALT)-1-'DCF Bear'!$I$144)/'DCF Bear'!$H$23*(1+'DCF Bear'!$C$6+$B23)^(-5) -> 138118.12 | G23: =C23+D23+E23+F23 -> 367294.9 | H23: =SUMPRODUCT('DCF Base'!$D$73:$H$73,(1+'DCF Base'!$C$6+$B23)^(-'DCF Base'!$D$19:$H$19))+'DCF Base'!$I$58*(1-'DCF Base'!$I$57/'DCF Base'!$I$59)/((1+'DCF Base'!$C$6+$B23)*IF(RateConv=1,1,1+IPCALT)-1-'DCF Base'!$I$57)/'DCF Base'!$H$23*(1+'DCF Base'!$C$6+$B23)^(-5) -> 245601.88 | I23: =SUMPRODUCT('DCF Base'!$D$102:$H$102,(1+'DCF Base'!$C$6+$B23)^(-'DCF Base'!$D$19:$H$19))+'DCF Base'!$I$87*(1-'DCF Base'!$I$86/'DCF Base'!$I$88)/((1+'DCF Base'!$C$6+$B23)*IF(RateConv=1,1,1+IPCALT)-1-'DCF Base'!$I$86)/'DCF Base'!$H$23*(1+'DCF Base'!$C$6+$B23)^(-5) -> 154938.19 | J23: =SUMPRODUCT('DCF Base'!$D$131:$H$131,(1+'DCF Base'!$C$6+$B23)^(-'DCF Base'!$D$19:$H$19))+'DCF Base'!$I$116*(1-'DCF Base'!$I$115/'DCF Base'!$I$117)/((1+'DCF Base'!$C$6+$B23)*IF(RateConv=1,1,1+IPCALT)-1-'DCF Base'!$I$115)/'DCF Base'!$H$23*(1+'DCF Base'!$C$6+$B23)^(-5) -> 89161.682 | K23: =SUMPRODUCT('DCF Base'!$D$160:$H$160,(1+'DCF Base'!$C$6+$B23)^(-'DCF Base'!$D$19:$H$19))+'DCF Base'!$I$145*(1-'DCF Base'!$I$144/'DCF Base'!$I$146)/((1+'DCF Base'!$C$6+$B23)*IF(RateConv=1,1,1+IPCALT)-1-'DCF Base'!$I$144)/'DCF Base'!$H$23*(1+'DCF Base'!$C$6+$B23)^(-5) -> 280331.3 | L23: =H23+I23+J23+K23 -> 770033.05 | M23: =SUMPRODUCT('DCF Bull'!$D$73:$H$73,(1+'DCF Bull'!$C$6+$B23)^(-'DCF Bull'!$D$19:$H$19))+'DCF Bull'!$I$58*(1-'DCF Bull'!$I$57/'DCF Bull'!$I$59)/((1+'DCF Bull'!$C$6+$B23)*IF(RateConv=1,1,1+IPCALT)-1-'DCF Bull'!$I$57)/'DCF Bull'!$H$23*(1+'DCF Bull'!$C$6+$B23)^(-5) -> 604592.3 | N23: =SUMPRODUCT('DCF Bull'!$D$102:$H$102,(1+'DCF Bull'!$C$6+$B23)^(-'DCF Bull'!$D$19:$H$19))+'DCF Bull'!$I$87*(1-'DCF Bull'!$I$86/'DCF Bull'!$I$88)/((1+'DCF Bull'!$C$6+$B23)*IF(RateConv=1,1,1+IPCALT)-1-'DCF Bull'!$I$86)/'DCF Bull'!$H$23*(1+'DCF Bull'!$C$6+$B23)^(-5) -> 374608.87 | O23: =SUMPRODUCT('DCF Bull'!$D$131:$H$131,(1+'DCF Bull'!$C$6+$B23)^(-'DCF Bull'!$D$19:$H$19))+'DCF Bull'!$I$116*(1-'DCF Bull'!$I$115/'DCF Bull'!$I$117)/((1+'DCF Bull'!$C$6+$B23)*IF(RateConv=1,1,1+IPCALT)-1-'DCF Bull'!$I$115)/'DCF Bull'!$H$23*(1+'DCF Bull'!$C$6+$B23)^(-5) -> 221435.4 | P23: =SUMPRODUCT('DCF Bull'!$D$160:$H$160,(1+'DCF Bull'!$C$6+$B23)^(-'DCF Bull'!$D$19:$H$19))+'DCF Bull'!$I$145*(1-'DCF Bull'!$I$144/'DCF Bull'!$I$146)/((1+'DCF Bull'!$C$6+$B23)*IF(RateConv=1,1,1+IPCALT)-1-'DCF Bull'!$I$144)/'DCF Bull'!$H$23*(1+'DCF Bull'!$C$6+$B23)^(-5) -> 662375.1 | Q23: =M23+N23+O23+P23 -> 1863011.7 | R23: =SUMPRODUCT('DCF Custom'!$D$73:$H$73,(1+'DCF Custom'!$C$6+$B23)^(-'DCF Custom'!$D$19:$H$19))+'DCF Custom'!$I$58*(1-'DCF Custom'!$I$57/'DCF Custom'!$I$59)/((1+'DCF Custom'!$C$6+$B23)*IF(RateConv=1,1,1+IPCALT)-1-'DCF Custom'!$I$57)/'DCF Custom'!$H$23*(1+'DCF Custom'!$C$6+$B23)^(-5) -> 245601.88 | S23: =SUMPRODUCT('DCF Custom'!$D$102:$H$102,(1+'DCF Custom'!$C$6+$B23)^(-'DCF Custom'!$D$19:$H$19))+'DCF Custom'!$I$87*(1-'DCF Custom'!$I$86/'DCF Custom'!$I$88)/((1+'DCF Custom'!$C$6+$B23)*IF(RateConv=1,1,1+IPCALT)-1-'DCF Custom'!$I$86)/'DCF Custom'!$H$23*(1+'DCF Custom'!$C$6+$B23)^(-5) -> 154938.19 | T23: =SUMPRODUCT('DCF Custom'!$D$131:$H$131,(1+'DCF Custom'!$C$6+$B23)^(-'DCF Custom'!$D$19:$H$19))+'DCF Custom'!$I$116*(1-'DCF Custom'!$I$115/'DCF Custom'!$I$117)/((1+'DCF Custom'!$C$6+$B23)*IF(RateConv=1,1,1+IPCALT)-1-'DCF Custom'!$I$115)/'DCF Custom'!$H$23*(1+'DCF Custom'!$C$6+$B23)^(-5) -> 89161.682 | U23: =SUMPRODUCT('DCF Custom'!$D$160:$H$160,(1+'DCF Custom'!$C$6+$B23)^(-'DCF Custom'!$D$19:$H$19))+'DCF Custom'!$I$145*(1-'DCF Custom'!$I$144/'DCF Custom'!$I$146)/((1+'DCF Custom'!$C$6+$B23)*IF(RateConv=1,1,1+IPCALT)-1-'DCF Custom'!$I$144)/'DCF Custom'!$H$23*(1+'DCF Custom'!$C$6+$B23)^(-5) -> 280331.3 | V23: =R23+S23+T23+U23 -> 770033.05
B24: 0.003 | C24: =SUMPRODUCT('DCF Bear'!$D$73:$H$73,(1+'DCF Bear'!$C$6+$B24)^(-'DCF Bear'!$D$19:$H$19))+'DCF Bear'!$I$58*(1-'DCF Bear'!$I$57/'DCF Bear'!$I$59)/((1+'DCF Bear'!$C$6+$B24)*IF(RateConv=1,1,1+IPCALT)-1-'DCF Bear'!$I$57)/'DCF Bear'!$H$23*(1+'DCF Bear'!$C$6+$B24)^(-5) -> 112288.15 | D24: =SUMPRODUCT('DCF Bear'!$D$102:$H$102,(1+'DCF Bear'!$C$6+$B24)^(-'DCF Bear'!$D$19:$H$19))+'DCF Bear'!$I$87*(1-'DCF Bear'!$I$86/'DCF Bear'!$I$88)/((1+'DCF Bear'!$C$6+$B24)*IF(RateConv=1,1,1+IPCALT)-1-'DCF Bear'!$I$86)/'DCF Bear'!$H$23*(1+'DCF Bear'!$C$6+$B24)^(-5) -> 71537.661 | E24: =SUMPRODUCT('DCF Bear'!$D$131:$H$131,(1+'DCF Bear'!$C$6+$B24)^(-'DCF Bear'!$D$19:$H$19))+'DCF Bear'!$I$116*(1-'DCF Bear'!$I$115/'DCF Bear'!$I$117)/((1+'DCF Bear'!$C$6+$B24)*IF(RateConv=1,1,1+IPCALT)-1-'DCF Bear'!$I$115)/'DCF Bear'!$H$23*(1+'DCF Bear'!$C$6+$B24)^(-5) -> 40220.021 | F24: =SUMPRODUCT('DCF Bear'!$D$160:$H$160,(1+'DCF Bear'!$C$6+$B24)^(-'DCF Bear'!$D$19:$H$19))+'DCF Bear'!$I$145*(1-'DCF Bear'!$I$144/'DCF Bear'!$I$146)/((1+'DCF Bear'!$C$6+$B24)*IF(RateConv=1,1,1+IPCALT)-1-'DCF Bear'!$I$144)/'DCF Bear'!$H$23*(1+'DCF Bear'!$C$6+$B24)^(-5) -> 135237.62 | G24: =C24+D24+E24+F24 -> 359283.45 | H24: =SUMPRODUCT('DCF Base'!$D$73:$H$73,(1+'DCF Base'!$C$6+$B24)^(-'DCF Base'!$D$19:$H$19))+'DCF Base'!$I$58*(1-'DCF Base'!$I$57/'DCF Base'!$I$59)/((1+'DCF Base'!$C$6+$B24)*IF(RateConv=1,1,1+IPCALT)-1-'DCF Base'!$I$57)/'DCF Base'!$H$23*(1+'DCF Base'!$C$6+$B24)^(-5) -> 235011.54 | I24: =SUMPRODUCT('DCF Base'!$D$102:$H$102,(1+'DCF Base'!$C$6+$B24)^(-'DCF Base'!$D$19:$H$19))+'DCF Base'!$I$87*(1-'DCF Base'!$I$86/'DCF Base'!$I$88)/((1+'DCF Base'!$C$6+$B24)*IF(RateConv=1,1,1+IPCALT)-1-'DCF Base'!$I$86)/'DCF Base'!$H$23*(1+'DCF Base'!$C$6+$B24)^(-5) -> 148079.79 | J24: =SUMPRODUCT('DCF Base'!$D$131:$H$131,(1+'DCF Base'!$C$6+$B24)^(-'DCF Base'!$D$19:$H$19))+'DCF Base'!$I$116*(1-'DCF Base'!$I$115/'DCF Base'!$I$117)/((1+'DCF Base'!$C$6+$B24)*IF(RateConv=1,1,1+IPCALT)-1-'DCF Base'!$I$115)/'DCF Base'!$H$23*(1+'DCF Base'!$C$6+$B24)^(-5) -> 85265.163 | K24: =SUMPRODUCT('DCF Base'!$D$160:$H$160,(1+'DCF Base'!$C$6+$B24)^(-'DCF Base'!$D$19:$H$19))+'DCF Base'!$I$145*(1-'DCF Base'!$I$144/'DCF Base'!$I$146)/((1+'DCF Base'!$C$6+$B24)*IF(RateConv=1,1,1+IPCALT)-1-'DCF Base'!$I$144)/'DCF Base'!$H$23*(1+'DCF Base'!$C$6+$B24)^(-5) -> 268557.14 | L24: =H24+I24+J24+K24 -> 736913.64 | M24: =SUMPRODUCT('DCF Bull'!$D$73:$H$73,(1+'DCF Bull'!$C$6+$B24)^(-'DCF Bull'!$D$19:$H$19))+'DCF Bull'!$I$58*(1-'DCF Bull'!$I$57/'DCF Bull'!$I$59)/((1+'DCF Bull'!$C$6+$B24)*IF(RateConv=1,1,1+IPCALT)-1-'DCF Bull'!$I$57)/'DCF Bull'!$H$23*(1+'DCF Bull'!$C$6+$B24)^(-5) -> 548896.19 | N24: =SUMPRODUCT('DCF Bull'!$D$102:$H$102,(1+'DCF Bull'!$C$6+$B24)^(-'DCF Bull'!$D$19:$H$19))+'DCF Bull'!$I$87*(1-'DCF Bull'!$I$86/'DCF Bull'!$I$88)/((1+'DCF Bull'!$C$6+$B24)*IF(RateConv=1,1,1+IPCALT)-1-'DCF Bull'!$I$86)/'DCF Bull'!$H$23*(1+'DCF Bull'!$C$6+$B24)^(-5) -> 339618.49 | O24: =SUMPRODUCT('DCF Bull'!$D$131:$H$131,(1+'DCF Bull'!$C$6+$B24)^(-'DCF Bull'!$D$19:$H$19))+'DCF Bull'!$I$116*(1-'DCF Bull'!$I$115/'DCF Bull'!$I$117)/((1+'DCF Bull'!$C$6+$B24)*IF(RateConv=1,1,1+IPCALT)-1-'DCF Bull'!$I$115)/'DCF Bull'!$H$23*(1+'DCF Bull'!$C$6+$B24)^(-5) -> 200903.33 | P24: =SUMPRODUCT('DCF Bull'!$D$160:$H$160,(1+'DCF Bull'!$C$6+$B24)^(-'DCF Bull'!$D$19:$H$19))+'DCF Bull'!$I$145*(1-'DCF Bull'!$I$144/'DCF Bull'!$I$146)/((1+'DCF Bull'!$C$6+$B24)*IF(RateConv=1,1,1+IPCALT)-1-'DCF Bull'!$I$144)/'DCF Bull'!$H$23*(1+'DCF Bull'!$C$6+$B24)^(-5) -> 602003.7 | Q24: =M24+N24+O24+P24 -> 1691421.7 | R24: =SUMPRODUCT('DCF Custom'!$D$73:$H$73,(1+'DCF Custom'!$C$6+$B24)^(-'DCF Custom'!$D$19:$H$19))+'DCF Custom'!$I$58*(1-'DCF Custom'!$I$57/'DCF Custom'!$I$59)/((1+'DCF Custom'!$C$6+$B24)*IF(RateConv=1,1,1+IPCALT)-1-'DCF Custom'!$I$57)/'DCF Custom'!$H$23*(1+'DCF Custom'!$C$6+$B24)^(-5) -> 235011.54 | S24: =SUMPRODUCT('DCF Custom'!$D$102:$H$102,(1+'DCF Custom'!$C$6+$B24)^(-'DCF Custom'!$D$19:$H$19))+'DCF Custom'!$I$87*(1-'DCF Custom'!$I$86/'DCF Custom'!$I$88)/((1+'DCF Custom'!$C$6+$B24)*IF(RateConv=1,1,1+IPCALT)-1-'DCF Custom'!$I$86)/'DCF Custom'!$H$23*(1+'DCF Custom'!$C$6+$B24)^(-5) -> 148079.79 | T24: =SUMPRODUCT('DCF Custom'!$D$131:$H$131,(1+'DCF Custom'!$C$6+$B24)^(-'DCF Custom'!$D$19:$H$19))+'DCF Custom'!$I$116*(1-'DCF Custom'!$I$115/'DCF Custom'!$I$117)/((1+'DCF Custom'!$C$6+$B24)*IF(RateConv=1,1,1+IPCALT)-1-'DCF Custom'!$I$115)/'DCF Custom'!$H$23*(1+'DCF Custom'!$C$6+$B24)^(-5) -> 85265.163 | U24: =SUMPRODUCT('DCF Custom'!$D$160:$H$160,(1+'DCF Custom'!$C$6+$B24)^(-'DCF Custom'!$D$19:$H$19))+'DCF Custom'!$I$145*(1-'DCF Custom'!$I$144/'DCF Custom'!$I$146)/((1+'DCF Custom'!$C$6+$B24)*IF(RateConv=1,1,1+IPCALT)-1-'DCF Custom'!$I$144)/'DCF Custom'!$H$23*(1+'DCF Custom'!$C$6+$B24)^(-5) -> 268557.14 | V24: =R24+S24+T24+U24 -> 736913.64
B25: 0.004 | C25: =SUMPRODUCT('DCF Bear'!$D$73:$H$73,(1+'DCF Bear'!$C$6+$B25)^(-'DCF Bear'!$D$19:$H$19))+'DCF Bear'!$I$58*(1-'DCF Bear'!$I$57/'DCF Bear'!$I$59)/((1+'DCF Bear'!$C$6+$B25)*IF(RateConv=1,1,1+IPCALT)-1-'DCF Bear'!$I$57)/'DCF Bear'!$H$23*(1+'DCF Bear'!$C$6+$B25)^(-5) -> 109870.59 | D25: =SUMPRODUCT('DCF Bear'!$D$102:$H$102,(1+'DCF Bear'!$C$6+$B25)^(-'DCF Bear'!$D$19:$H$19))+'DCF Bear'!$I$87*(1-'DCF Bear'!$I$86/'DCF Bear'!$I$88)/((1+'DCF Bear'!$C$6+$B25)*IF(RateConv=1,1,1+IPCALT)-1-'DCF Bear'!$I$86)/'DCF Bear'!$H$23*(1+'DCF Bear'!$C$6+$B25)^(-5) -> 69929.941 | E25: =SUMPRODUCT('DCF Bear'!$D$131:$H$131,(1+'DCF Bear'!$C$6+$B25)^(-'DCF Bear'!$D$19:$H$19))+'DCF Bear'!$I$116*(1-'DCF Bear'!$I$115/'DCF Bear'!$I$117)/((1+'DCF Bear'!$C$6+$B25)*IF(RateConv=1,1,1+IPCALT)-1-'DCF Bear'!$I$115)/'DCF Bear'!$H$23*(1+'DCF Bear'!$C$6+$B25)^(-5) -> 39333.082 | F25: =SUMPRODUCT('DCF Bear'!$D$160:$H$160,(1+'DCF Bear'!$C$6+$B25)^(-'DCF Bear'!$D$19:$H$19))+'DCF Bear'!$I$145*(1-'DCF Bear'!$I$144/'DCF Bear'!$I$146)/((1+'DCF Bear'!$C$6+$B25)*IF(RateConv=1,1,1+IPCALT)-1-'DCF Bear'!$I$144)/'DCF Bear'!$H$23*(1+'DCF Bear'!$C$6+$B25)^(-5) -> 132479.09 | G25: =C25+D25+E25+F25 -> 351612.7 | H25: =SUMPRODUCT('DCF Base'!$D$73:$H$73,(1+'DCF Base'!$C$6+$B25)^(-'DCF Base'!$D$19:$H$19))+'DCF Base'!$I$58*(1-'DCF Base'!$I$57/'DCF Base'!$I$59)/((1+'DCF Base'!$C$6+$B25)*IF(RateConv=1,1,1+IPCALT)-1-'DCF Base'!$I$57)/'DCF Base'!$H$23*(1+'DCF Base'!$C$6+$B25)^(-5) -> 225282.79 | I25: =SUMPRODUCT('DCF Base'!$D$102:$H$102,(1+'DCF Base'!$C$6+$B25)^(-'DCF Base'!$D$19:$H$19))+'DCF Base'!$I$87*(1-'DCF Base'!$I$86/'DCF Base'!$I$88)/((1+'DCF Base'!$C$6+$B25)*IF(RateConv=1,1,1+IPCALT)-1-'DCF Base'!$I$86)/'DCF Base'!$H$23*(1+'DCF Base'!$C$6+$B25)^(-5) -> 141780.05 | J25: =SUMPRODUCT('DCF Base'!$D$131:$H$131,(1+'DCF Base'!$C$6+$B25)^(-'DCF Base'!$D$19:$H$19))+'DCF Base'!$I$116*(1-'DCF Base'!$I$115/'DCF Base'!$I$117)/((1+'DCF Base'!$C$6+$B25)*IF(RateConv=1,1,1+IPCALT)-1-'DCF Base'!$I$115)/'DCF Base'!$H$23*(1+'DCF Base'!$C$6+$B25)^(-5) -> 81685.855 | K25: =SUMPRODUCT('DCF Base'!$D$160:$H$160,(1+'DCF Base'!$C$6+$B25)^(-'DCF Base'!$D$19:$H$19))+'DCF Base'!$I$145*(1-'DCF Base'!$I$144/'DCF Base'!$I$146)/((1+'DCF Base'!$C$6+$B25)*IF(RateConv=1,1,1+IPCALT)-1-'DCF Base'!$I$144)/'DCF Base'!$H$23*(1+'DCF Base'!$C$6+$B25)^(-5) -> 257739.63 | L25: =H25+I25+J25+K25 -> 706488.33 | M25: =SUMPRODUCT('DCF Bull'!$D$73:$H$73,(1+'DCF Bull'!$C$6+$B25)^(-'DCF Bull'!$D$19:$H$19))+'DCF Bull'!$I$58*(1-'DCF Bull'!$I$57/'DCF Bull'!$I$59)/((1+'DCF Bull'!$C$6+$B25)*IF(RateConv=1,1,1+IPCALT)-1-'DCF Bull'!$I$57)/'DCF Bull'!$H$23*(1+'DCF Bull'!$C$6+$B25)^(-5) -> 502485.41 | N25: =SUMPRODUCT('DCF Bull'!$D$102:$H$102,(1+'DCF Bull'!$C$6+$B25)^(-'DCF Bull'!$D$19:$H$19))+'DCF Bull'!$I$87*(1-'DCF Bull'!$I$86/'DCF Bull'!$I$88)/((1+'DCF Bull'!$C$6+$B25)*IF(RateConv=1,1,1+IPCALT)-1-'DCF Bull'!$I$86)/'DCF Bull'!$H$23*(1+'DCF Bull'!$C$6+$B25)^(-5) -> 310463.36 | O25: =SUMPRODUCT('DCF Bull'!$D$131:$H$131,(1+'DCF Bull'!$C$6+$B25)^(-'DCF Bull'!$D$19:$H$19))+'DCF Bull'!$I$116*(1-'DCF Bull'!$I$115/'DCF Bull'!$I$117)/((1+'DCF Bull'!$C$6+$B25)*IF(RateConv=1,1,1+IPCALT)-1-'DCF Bull'!$I$115)/'DCF Bull'!$H$23*(1+'DCF Bull'!$C$6+$B25)^(-5) -> 183794.76 | P25: =SUMPRODUCT('DCF Bull'!$D$160:$H$160,(1+'DCF Bull'!$C$6+$B25)^(-'DCF Bull'!$D$19:$H$19))+'DCF Bull'!$I$145*(1-'DCF Bull'!$I$144/'DCF Bull'!$I$146)/((1+'DCF Bull'!$C$6+$B25)*IF(RateConv=1,1,1+IPCALT)-1-'DCF Bull'!$I$144)/'DCF Bull'!$H$23*(1+'DCF Bull'!$C$6+$B25)^(-5) -> 551694.52 | Q25: =M25+N25+O25+P25 -> 1548438.1 | R25: =SUMPRODUCT('DCF Custom'!$D$73:$H$73,(1+'DCF Custom'!$C$6+$B25)^(-'DCF Custom'!$D$19:$H$19))+'DCF Custom'!$I$58*(1-'DCF Custom'!$I$57/'DCF Custom'!$I$59)/((1+'DCF Custom'!$C$6+$B25)*IF(RateConv=1,1,1+IPCALT)-1-'DCF Custom'!$I$57)/'DCF Custom'!$H$23*(1+'DCF Custom'!$C$6+$B25)^(-5) -> 225282.79 | S25: =SUMPRODUCT('DCF Custom'!$D$102:$H$102,(1+'DCF Custom'!$C$6+$B25)^(-'DCF Custom'!$D$19:$H$19))+'DCF Custom'!$I$87*(1-'DCF Custom'!$I$86/'DCF Custom'!$I$88)/((1+'DCF Custom'!$C$6+$B25)*IF(RateConv=1,1,1+IPCALT)-1-'DCF Custom'!$I$86)/'DCF Custom'!$H$23*(1+'DCF Custom'!$C$6+$B25)^(-5) -> 141780.05 | T25: =SUMPRODUCT('DCF Custom'!$D$131:$H$131,(1+'DCF Custom'!$C$6+$B25)^(-'DCF Custom'!$D$19:$H$19))+'DCF Custom'!$I$116*(1-'DCF Custom'!$I$115/'DCF Custom'!$I$117)/((1+'DCF Custom'!$C$6+$B25)*IF(RateConv=1,1,1+IPCALT)-1-'DCF Custom'!$I$115)/'DCF Custom'!$H$23*(1+'DCF Custom'!$C$6+$B25)^(-5) -> 81685.855 | U25: =SUMPRODUCT('DCF Custom'!$D$160:$H$160,(1+'DCF Custom'!$C$6+$B25)^(-'DCF Custom'!$D$19:$H$19))+'DCF Custom'!$I$145*(1-'DCF Custom'!$I$144/'DCF Custom'!$I$146)/((1+'DCF Custom'!$C$6+$B25)*IF(RateConv=1,1,1+IPCALT)-1-'DCF Custom'!$I$144)/'DCF Custom'!$H$23*(1+'DCF Custom'!$C$6+$B25)^(-5) -> 257739.63 | V25: =R25+S25+T25+U25 -> 706488.33
B26: 0.005 | C26: =SUMPRODUCT('DCF Bear'!$D$73:$H$73,(1+'DCF Bear'!$C$6+$B26)^(-'DCF Bear'!$D$19:$H$19))+'DCF Bear'!$I$58*(1-'DCF Bear'!$I$57/'DCF Bear'!$I$59)/((1+'DCF Bear'!$C$6+$B26)*IF(RateConv=1,1,1+IPCALT)-1-'DCF Bear'!$I$57)/'DCF Bear'!$H$23*(1+'DCF Bear'!$C$6+$B26)^(-5) -> 107553.78 | D26: =SUMPRODUCT('DCF Bear'!$D$102:$H$102,(1+'DCF Bear'!$C$6+$B26)^(-'DCF Bear'!$D$19:$H$19))+'DCF Bear'!$I$87*(1-'DCF Bear'!$I$86/'DCF Bear'!$I$88)/((1+'DCF Bear'!$C$6+$B26)*IF(RateConv=1,1,1+IPCALT)-1-'DCF Bear'!$I$86)/'DCF Bear'!$H$23*(1+'DCF Bear'!$C$6+$B26)^(-5) -> 68389.477 | E26: =SUMPRODUCT('DCF Bear'!$D$131:$H$131,(1+'DCF Bear'!$C$6+$B26)^(-'DCF Bear'!$D$19:$H$19))+'DCF Bear'!$I$116*(1-'DCF Bear'!$I$115/'DCF Bear'!$I$117)/((1+'DCF Bear'!$C$6+$B26)*IF(RateConv=1,1,1+IPCALT)-1-'DCF Bear'!$I$115)/'DCF Bear'!$H$23*(1+'DCF Bear'!$C$6+$B26)^(-5) -> 38483.19 | F26: =SUMPRODUCT('DCF Bear'!$D$160:$H$160,(1+'DCF Bear'!$C$6+$B26)^(-'DCF Bear'!$D$19:$H$19))+'DCF Bear'!$I$145*(1-'DCF Bear'!$I$144/'DCF Bear'!$I$146)/((1+'DCF Bear'!$C$6+$B26)*IF(RateConv=1,1,1+IPCALT)-1-'DCF Bear'!$I$144)/'DCF Bear'!$H$23*(1+'DCF Bear'!$C$6+$B26)^(-5) -> 129834.9 | G26: =C26+D26+E26+F26 -> 344261.35 | H26: =SUMPRODUCT('DCF Base'!$D$73:$H$73,(1+'DCF Base'!$C$6+$B26)^(-'DCF Base'!$D$19:$H$19))+'DCF Base'!$I$58*(1-'DCF Base'!$I$57/'DCF Base'!$I$59)/((1+'DCF Base'!$C$6+$B26)*IF(RateConv=1,1,1+IPCALT)-1-'DCF Base'!$I$57)/'DCF Base'!$H$23*(1+'DCF Base'!$C$6+$B26)^(-5) -> 216314.67 | I26: =SUMPRODUCT('DCF Base'!$D$102:$H$102,(1+'DCF Base'!$C$6+$B26)^(-'DCF Base'!$D$19:$H$19))+'DCF Base'!$I$87*(1-'DCF Base'!$I$86/'DCF Base'!$I$88)/((1+'DCF Base'!$C$6+$B26)*IF(RateConv=1,1,1+IPCALT)-1-'DCF Base'!$I$86)/'DCF Base'!$H$23*(1+'DCF Base'!$C$6+$B26)^(-5) -> 135973.5 | J26: =SUMPRODUCT('DCF Base'!$D$131:$H$131,(1+'DCF Base'!$C$6+$B26)^(-'DCF Base'!$D$19:$H$19))+'DCF Base'!$I$116*(1-'DCF Base'!$I$115/'DCF Base'!$I$117)/((1+'DCF Base'!$C$6+$B26)*IF(RateConv=1,1,1+IPCALT)-1-'DCF Base'!$I$115)/'DCF Base'!$H$23*(1+'DCF Base'!$C$6+$B26)^(-5) -> 78386.584 | K26: =SUMPRODUCT('DCF Base'!$D$160:$H$160,(1+'DCF Base'!$C$6+$B26)^(-'DCF Base'!$D$19:$H$19))+'DCF Base'!$I$145*(1-'DCF Base'!$I$144/'DCF Base'!$I$146)/((1+'DCF Base'!$C$6+$B26)*IF(RateConv=1,1,1+IPCALT)-1-'DCF Base'!$I$144)/'DCF Base'!$H$23*(1+'DCF Base'!$C$6+$B26)^(-5) -> 247766.65 | L26: =H26+I26+J26+K26 -> 678441.4 | M26: =SUMPRODUCT('DCF Bull'!$D$73:$H$73,(1+'DCF Bull'!$C$6+$B26)^(-'DCF Bull'!$D$19:$H$19))+'DCF Bull'!$I$58*(1-'DCF Bull'!$I$57/'DCF Bull'!$I$59)/((1+'DCF Bull'!$C$6+$B26)*IF(RateConv=1,1,1+IPCALT)-1-'DCF Bull'!$I$57)/'DCF Bull'!$H$23*(1+'DCF Bull'!$C$6+$B26)^(-5) -> 463217.18 | N26: =SUMPRODUCT('DCF Bull'!$D$102:$H$102,(1+'DCF Bull'!$C$6+$B26)^(-'DCF Bull'!$D$19:$H$19))+'DCF Bull'!$I$87*(1-'DCF Bull'!$I$86/'DCF Bull'!$I$88)/((1+'DCF Bull'!$C$6+$B26)*IF(RateConv=1,1,1+IPCALT)-1-'DCF Bull'!$I$86)/'DCF Bull'!$H$23*(1+'DCF Bull'!$C$6+$B26)^(-5) -> 285796.89 | O26: =SUMPRODUCT('DCF Bull'!$D$131:$H$131,(1+'DCF Bull'!$C$6+$B26)^(-'DCF Bull'!$D$19:$H$19))+'DCF Bull'!$I$116*(1-'DCF Bull'!$I$115/'DCF Bull'!$I$117)/((1+'DCF Bull'!$C$6+$B26)*IF(RateConv=1,1,1+IPCALT)-1-'DCF Bull'!$I$115)/'DCF Bull'!$H$23*(1+'DCF Bull'!$C$6+$B26)^(-5) -> 169319.67 | P26: =SUMPRODUCT('DCF Bull'!$D$160:$H$160,(1+'DCF Bull'!$C$6+$B26)^(-'DCF Bull'!$D$19:$H$19))+'DCF Bull'!$I$145*(1-'DCF Bull'!$I$144/'DCF Bull'!$I$146)/((1+'DCF Bull'!$C$6+$B26)*IF(RateConv=1,1,1+IPCALT)-1-'DCF Bull'!$I$144)/'DCF Bull'!$H$23*(1+'DCF Bull'!$C$6+$B26)^(-5) -> 509125.52 | Q26: =M26+N26+O26+P26 -> 1427459.3 | R26: =SUMPRODUCT('DCF Custom'!$D$73:$H$73,(1+'DCF Custom'!$C$6+$B26)^(-'DCF Custom'!$D$19:$H$19))+'DCF Custom'!$I$58*(1-'DCF Custom'!$I$57/'DCF Custom'!$I$59)/((1+'DCF Custom'!$C$6+$B26)*IF(RateConv=1,1,1+IPCALT)-1-'DCF Custom'!$I$57)/'DCF Custom'!$H$23*(1+'DCF Custom'!$C$6+$B26)^(-5) -> 216314.67 | S26: =SUMPRODUCT('DCF Custom'!$D$102:$H$102,(1+'DCF Custom'!$C$6+$B26)^(-'DCF Custom'!$D$19:$H$19))+'DCF Custom'!$I$87*(1-'DCF Custom'!$I$86/'DCF Custom'!$I$88)/((1+'DCF Custom'!$C$6+$B26)*IF(RateConv=1,1,1+IPCALT)-1-'DCF Custom'!$I$86)/'DCF Custom'!$H$23*(1+'DCF Custom'!$C$6+$B26)^(-5) -> 135973.5 | T26: =SUMPRODUCT('DCF Custom'!$D$131:$H$131,(1+'DCF Custom'!$C$6+$B26)^(-'DCF Custom'!$D$19:$H$19))+'DCF Custom'!$I$116*(1-'DCF Custom'!$I$115/'DCF Custom'!$I$117)/((1+'DCF Custom'!$C$6+$B26)*IF(RateConv=1,1,1+IPCALT)-1-'DCF Custom'!$I$115)/'DCF Custom'!$H$23*(1+'DCF Custom'!$C$6+$B26)^(-5) -> 78386.584 | U26: =SUMPRODUCT('DCF Custom'!$D$160:$H$160,(1+'DCF Custom'!$C$6+$B26)^(-'DCF Custom'!$D$19:$H$19))+'DCF Custom'!$I$145*(1-'DCF Custom'!$I$144/'DCF Custom'!$I$146)/((1+'DCF Custom'!$C$6+$B26)*IF(RateConv=1,1,1+IPCALT)-1-'DCF Custom'!$I$144)/'DCF Custom'!$H$23*(1+'DCF Custom'!$C$6+$B26)^(-5) -> 247766.65 | V26: =R26+S26+T26+U26 -> 678441.4
B27: 0.006 | C27: =SUMPRODUCT('DCF Bear'!$D$73:$H$73,(1+'DCF Bear'!$C$6+$B27)^(-'DCF Bear'!$D$19:$H$19))+'DCF Bear'!$I$58*(1-'DCF Bear'!$I$57/'DCF Bear'!$I$59)/((1+'DCF Bear'!$C$6+$B27)*IF(RateConv=1,1,1+IPCALT)-1-'DCF Bear'!$I$57)/'DCF Bear'!$H$23*(1+'DCF Bear'!$C$6+$B27)^(-5) -> 105331.57 | D27: =SUMPRODUCT('DCF Bear'!$D$102:$H$102,(1+'DCF Bear'!$C$6+$B27)^(-'DCF Bear'!$D$19:$H$19))+'DCF Bear'!$I$87*(1-'DCF Bear'!$I$86/'DCF Bear'!$I$88)/((1+'DCF Bear'!$C$6+$B27)*IF(RateConv=1,1,1+IPCALT)-1-'DCF Bear'!$I$86)/'DCF Bear'!$H$23*(1+'DCF Bear'!$C$6+$B27)^(-5) -> 66912.148 | E27: =SUMPRODUCT('DCF Bear'!$D$131:$H$131,(1+'DCF Bear'!$C$6+$B27)^(-'DCF Bear'!$D$19:$H$19))+'DCF Bear'!$I$116*(1-'DCF Bear'!$I$115/'DCF Bear'!$I$117)/((1+'DCF Bear'!$C$6+$B27)*IF(RateConv=1,1,1+IPCALT)-1-'DCF Bear'!$I$115)/'DCF Bear'!$H$23*(1+'DCF Bear'!$C$6+$B27)^(-5) -> 37668.076 | F27: =SUMPRODUCT('DCF Bear'!$D$160:$H$160,(1+'DCF Bear'!$C$6+$B27)^(-'DCF Bear'!$D$19:$H$19))+'DCF Bear'!$I$145*(1-'DCF Bear'!$I$144/'DCF Bear'!$I$146)/((1+'DCF Bear'!$C$6+$B27)*IF(RateConv=1,1,1+IPCALT)-1-'DCF Bear'!$I$144)/'DCF Bear'!$H$23*(1+'DCF Bear'!$C$6+$B27)^(-5) -> 127298.07 | G27: =C27+D27+E27+F27 -> 337209.86 | H27: =SUMPRODUCT('DCF Base'!$D$73:$H$73,(1+'DCF Base'!$C$6+$B27)^(-'DCF Base'!$D$19:$H$19))+'DCF Base'!$I$58*(1-'DCF Base'!$I$57/'DCF Base'!$I$59)/((1+'DCF Base'!$C$6+$B27)*IF(RateConv=1,1,1+IPCALT)-1-'DCF Base'!$I$57)/'DCF Base'!$H$23*(1+'DCF Base'!$C$6+$B27)^(-5) -> 208021.38 | I27: =SUMPRODUCT('DCF Base'!$D$102:$H$102,(1+'DCF Base'!$C$6+$B27)^(-'DCF Base'!$D$19:$H$19))+'DCF Base'!$I$87*(1-'DCF Base'!$I$86/'DCF Base'!$I$88)/((1+'DCF Base'!$C$6+$B27)*IF(RateConv=1,1,1+IPCALT)-1-'DCF Base'!$I$86)/'DCF Base'!$H$23*(1+'DCF Base'!$C$6+$B27)^(-5) -> 130604.5 | J27: =SUMPRODUCT('DCF Base'!$D$131:$H$131,(1+'DCF Base'!$C$6+$B27)^(-'DCF Base'!$D$19:$H$19))+'DCF Base'!$I$116*(1-'DCF Base'!$I$115/'DCF Base'!$I$117)/((1+'DCF Base'!$C$6+$B27)*IF(RateConv=1,1,1+IPCALT)-1-'DCF Base'!$I$115)/'DCF Base'!$H$23*(1+'DCF Base'!$C$6+$B27)^(-5) -> 75335.766 | K27: =SUMPRODUCT('DCF Base'!$D$160:$H$160,(1+'DCF Base'!$C$6+$B27)^(-'DCF Base'!$D$19:$H$19))+'DCF Base'!$I$145*(1-'DCF Base'!$I$144/'DCF Base'!$I$146)/((1+'DCF Base'!$C$6+$B27)*IF(RateConv=1,1,1+IPCALT)-1-'DCF Base'!$I$144)/'DCF Base'!$H$23*(1+'DCF Base'!$C$6+$B27)^(-5) -> 238542.96 | L27: =H27+I27+J27+K27 -> 652504.61 | M27: =SUMPRODUCT('DCF Bull'!$D$73:$H$73,(1+'DCF Bull'!$C$6+$B27)^(-'DCF Bull'!$D$19:$H$19))+'DCF Bull'!$I$58*(1-'DCF Bull'!$I$57/'DCF Bull'!$I$59)/((1+'DCF Bull'!$C$6+$B27)*IF(RateConv=1,1,1+IPCALT)-1-'DCF Bull'!$I$57)/'DCF Bull'!$H$23*(1+'DCF Bull'!$C$6+$B27)^(-5) -> 429560.95 | N27: =SUMPRODUCT('DCF Bull'!$D$102:$H$102,(1+'DCF Bull'!$C$6+$B27)^(-'DCF Bull'!$D$19:$H$19))+'DCF Bull'!$I$87*(1-'DCF Bull'!$I$86/'DCF Bull'!$I$88)/((1+'DCF Bull'!$C$6+$B27)*IF(RateConv=1,1,1+IPCALT)-1-'DCF Bull'!$I$86)/'DCF Bull'!$H$23*(1+'DCF Bull'!$C$6+$B27)^(-5) -> 264657.19 | O27: =SUMPRODUCT('DCF Bull'!$D$131:$H$131,(1+'DCF Bull'!$C$6+$B27)^(-'DCF Bull'!$D$19:$H$19))+'DCF Bull'!$I$116*(1-'DCF Bull'!$I$115/'DCF Bull'!$I$117)/((1+'DCF Bull'!$C$6+$B27)*IF(RateConv=1,1,1+IPCALT)-1-'DCF Bull'!$I$115)/'DCF Bull'!$H$23*(1+'DCF Bull'!$C$6+$B27)^(-5) -> 156913.71 | P27: =SUMPRODUCT('DCF Bull'!$D$160:$H$160,(1+'DCF Bull'!$C$6+$B27)^(-'DCF Bull'!$D$19:$H$19))+'DCF Bull'!$I$145*(1-'DCF Bull'!$I$144/'DCF Bull'!$I$146)/((1+'DCF Bull'!$C$6+$B27)*IF(RateConv=1,1,1+IPCALT)-1-'DCF Bull'!$I$144)/'DCF Bull'!$H$23*(1+'DCF Bull'!$C$6+$B27)^(-5) -> 472638.08 | Q27: =M27+N27+O27+P27 -> 1323769.9 | R27: =SUMPRODUCT('DCF Custom'!$D$73:$H$73,(1+'DCF Custom'!$C$6+$B27)^(-'DCF Custom'!$D$19:$H$19))+'DCF Custom'!$I$58*(1-'DCF Custom'!$I$57/'DCF Custom'!$I$59)/((1+'DCF Custom'!$C$6+$B27)*IF(RateConv=1,1,1+IPCALT)-1-'DCF Custom'!$I$57)/'DCF Custom'!$H$23*(1+'DCF Custom'!$C$6+$B27)^(-5) -> 208021.38 | S27: =SUMPRODUCT('DCF Custom'!$D$102:$H$102,(1+'DCF Custom'!$C$6+$B27)^(-'DCF Custom'!$D$19:$H$19))+'DCF Custom'!$I$87*(1-'DCF Custom'!$I$86/'DCF Custom'!$I$88)/((1+'DCF Custom'!$C$6+$B27)*IF(RateConv=1,1,1+IPCALT)-1-'DCF Custom'!$I$86)/'DCF Custom'!$H$23*(1+'DCF Custom'!$C$6+$B27)^(-5) -> 130604.5 | T27: =SUMPRODUCT('DCF Custom'!$D$131:$H$131,(1+'DCF Custom'!$C$6+$B27)^(-'DCF Custom'!$D$19:$H$19))+'DCF Custom'!$I$116*(1-'DCF Custom'!$I$115/'DCF Custom'!$I$117)/((1+'DCF Custom'!$C$6+$B27)*IF(RateConv=1,1,1+IPCALT)-1-'DCF Custom'!$I$115)/'DCF Custom'!$H$23*(1+'DCF Custom'!$C$6+$B27)^(-5) -> 75335.766 | U27: =SUMPRODUCT('DCF Custom'!$D$160:$H$160,(1+'DCF Custom'!$C$6+$B27)^(-'DCF Custom'!$D$19:$H$19))+'DCF Custom'!$I$145*(1-'DCF Custom'!$I$144/'DCF Custom'!$I$146)/((1+'DCF Custom'!$C$6+$B27)*IF(RateConv=1,1,1+IPCALT)-1-'DCF Custom'!$I$144)/'DCF Custom'!$H$23*(1+'DCF Custom'!$C$6+$B27)^(-5) -> 238542.96 | V27: =R27+S27+T27+U27 -> 652504.61
B28: 0.007 | C28: =SUMPRODUCT('DCF Bear'!$D$73:$H$73,(1+'DCF Bear'!$C$6+$B28)^(-'DCF Bear'!$D$19:$H$19))+'DCF Bear'!$I$58*(1-'DCF Bear'!$I$57/'DCF Bear'!$I$59)/((1+'DCF Bear'!$C$6+$B28)*IF(RateConv=1,1,1+IPCALT)-1-'DCF Bear'!$I$57)/'DCF Bear'!$H$23*(1+'DCF Bear'!$C$6+$B28)^(-5) -> 103198.26 | D28: =SUMPRODUCT('DCF Bear'!$D$102:$H$102,(1+'DCF Bear'!$C$6+$B28)^(-'DCF Bear'!$D$19:$H$19))+'DCF Bear'!$I$87*(1-'DCF Bear'!$I$86/'DCF Bear'!$I$88)/((1+'DCF Bear'!$C$6+$B28)*IF(RateConv=1,1,1+IPCALT)-1-'DCF Bear'!$I$86)/'DCF Bear'!$H$23*(1+'DCF Bear'!$C$6+$B28)^(-5) -> 65494.166 | E28: =SUMPRODUCT('DCF Bear'!$D$131:$H$131,(1+'DCF Bear'!$C$6+$B28)^(-'DCF Bear'!$D$19:$H$19))+'DCF Bear'!$I$116*(1-'DCF Bear'!$I$115/'DCF Bear'!$I$117)/((1+'DCF Bear'!$C$6+$B28)*IF(RateConv=1,1,1+IPCALT)-1-'DCF Bear'!$I$115)/'DCF Bear'!$H$23*(1+'DCF Bear'!$C$6+$B28)^(-5) -> 36885.653 | F28: =SUMPRODUCT('DCF Bear'!$D$160:$H$160,(1+'DCF Bear'!$C$6+$B28)^(-'DCF Bear'!$D$19:$H$19))+'DCF Bear'!$I$145*(1-'DCF Bear'!$I$144/'DCF Bear'!$I$146)/((1+'DCF Bear'!$C$6+$B28)*IF(RateConv=1,1,1+IPCALT)-1-'DCF Bear'!$I$144)/'DCF Bear'!$H$23*(1+'DCF Bear'!$C$6+$B28)^(-5) -> 124862.15 | G28: =C28+D28+E28+F28 -> 330440.23 | H28: =SUMPRODUCT('DCF Base'!$D$73:$H$73,(1+'DCF Base'!$C$6+$B28)^(-'DCF Base'!$D$19:$H$19))+'DCF Base'!$I$58*(1-'DCF Base'!$I$57/'DCF Base'!$I$59)/((1+'DCF Base'!$C$6+$B28)*IF(RateConv=1,1,1+IPCALT)-1-'DCF Base'!$I$57)/'DCF Base'!$H$23*(1+'DCF Base'!$C$6+$B28)^(-5) -> 200329.57 | I28: =SUMPRODUCT('DCF Base'!$D$102:$H$102,(1+'DCF Base'!$C$6+$B28)^(-'DCF Base'!$D$19:$H$19))+'DCF Base'!$I$87*(1-'DCF Base'!$I$86/'DCF Base'!$I$88)/((1+'DCF Base'!$C$6+$B28)*IF(RateConv=1,1,1+IPCALT)-1-'DCF Base'!$I$86)/'DCF Base'!$H$23*(1+'DCF Base'!$C$6+$B28)^(-5) -> 125625.5 | J28: =SUMPRODUCT('DCF Base'!$D$131:$H$131,(1+'DCF Base'!$C$6+$B28)^(-'DCF Base'!$D$19:$H$19))+'DCF Base'!$I$116*(1-'DCF Base'!$I$115/'DCF Base'!$I$117)/((1+'DCF Base'!$C$6+$B28)*IF(RateConv=1,1,1+IPCALT)-1-'DCF Base'!$I$115)/'DCF Base'!$H$23*(1+'DCF Base'!$C$6+$B28)^(-5) -> 72506.392 | K28: =SUMPRODUCT('DCF Base'!$D$160:$H$160,(1+'DCF Base'!$C$6+$B28)^(-'DCF Base'!$D$19:$H$19))+'DCF Base'!$I$145*(1-'DCF Base'!$I$144/'DCF Base'!$I$146)/((1+'DCF Base'!$C$6+$B28)*IF(RateConv=1,1,1+IPCALT)-1-'DCF Base'!$I$144)/'DCF Base'!$H$23*(1+'DCF Base'!$C$6+$B28)^(-5) -> 229987.13 | L28: =H28+I28+J28+K28 -> 628448.59 | M28: =SUMPRODUCT('DCF Bull'!$D$73:$H$73,(1+'DCF Bull'!$C$6+$B28)^(-'DCF Bull'!$D$19:$H$19))+'DCF Bull'!$I$58*(1-'DCF Bull'!$I$57/'DCF Bull'!$I$59)/((1+'DCF Bull'!$C$6+$B28)*IF(RateConv=1,1,1+IPCALT)-1-'DCF Bull'!$I$57)/'DCF Bull'!$H$23*(1+'DCF Bull'!$C$6+$B28)^(-5) -> 400394.3 | N28: =SUMPRODUCT('DCF Bull'!$D$102:$H$102,(1+'DCF Bull'!$C$6+$B28)^(-'DCF Bull'!$D$19:$H$19))+'DCF Bull'!$I$87*(1-'DCF Bull'!$I$86/'DCF Bull'!$I$88)/((1+'DCF Bull'!$C$6+$B28)*IF(RateConv=1,1,1+IPCALT)-1-'DCF Bull'!$I$86)/'DCF Bull'!$H$23*(1+'DCF Bull'!$C$6+$B28)^(-5) -> 246338.9 | O28: =SUMPRODUCT('DCF Bull'!$D$131:$H$131,(1+'DCF Bull'!$C$6+$B28)^(-'DCF Bull'!$D$19:$H$19))+'DCF Bull'!$I$116*(1-'DCF Bull'!$I$115/'DCF Bull'!$I$117)/((1+'DCF Bull'!$C$6+$B28)*IF(RateConv=1,1,1+IPCALT)-1-'DCF Bull'!$I$115)/'DCF Bull'!$H$23*(1+'DCF Bull'!$C$6+$B28)^(-5) -> 146163.07 | P28: =SUMPRODUCT('DCF Bull'!$D$160:$H$160,(1+'DCF Bull'!$C$6+$B28)^(-'DCF Bull'!$D$19:$H$19))+'DCF Bull'!$I$145*(1-'DCF Bull'!$I$144/'DCF Bull'!$I$146)/((1+'DCF Bull'!$C$6+$B28)*IF(RateConv=1,1,1+IPCALT)-1-'DCF Bull'!$I$144)/'DCF Bull'!$H$23*(1+'DCF Bull'!$C$6+$B28)^(-5) -> 441015.89 | Q28: =M28+N28+O28+P28 -> 1233912.2 | R28: =SUMPRODUCT('DCF Custom'!$D$73:$H$73,(1+'DCF Custom'!$C$6+$B28)^(-'DCF Custom'!$D$19:$H$19))+'DCF Custom'!$I$58*(1-'DCF Custom'!$I$57/'DCF Custom'!$I$59)/((1+'DCF Custom'!$C$6+$B28)*IF(RateConv=1,1,1+IPCALT)-1-'DCF Custom'!$I$57)/'DCF Custom'!$H$23*(1+'DCF Custom'!$C$6+$B28)^(-5) -> 200329.57 | S28: =SUMPRODUCT('DCF Custom'!$D$102:$H$102,(1+'DCF Custom'!$C$6+$B28)^(-'DCF Custom'!$D$19:$H$19))+'DCF Custom'!$I$87*(1-'DCF Custom'!$I$86/'DCF Custom'!$I$88)/((1+'DCF Custom'!$C$6+$B28)*IF(RateConv=1,1,1+IPCALT)-1-'DCF Custom'!$I$86)/'DCF Custom'!$H$23*(1+'DCF Custom'!$C$6+$B28)^(-5) -> 125625.5 | T28: =SUMPRODUCT('DCF Custom'!$D$131:$H$131,(1+'DCF Custom'!$C$6+$B28)^(-'DCF Custom'!$D$19:$H$19))+'DCF Custom'!$I$116*(1-'DCF Custom'!$I$115/'DCF Custom'!$I$117)/((1+'DCF Custom'!$C$6+$B28)*IF(RateConv=1,1,1+IPCALT)-1-'DCF Custom'!$I$115)/'DCF Custom'!$H$23*(1+'DCF Custom'!$C$6+$B28)^(-5) -> 72506.392 | U28: =SUMPRODUCT('DCF Custom'!$D$160:$H$160,(1+'DCF Custom'!$C$6+$B28)^(-'DCF Custom'!$D$19:$H$19))+'DCF Custom'!$I$145*(1-'DCF Custom'!$I$144/'DCF Custom'!$I$146)/((1+'DCF Custom'!$C$6+$B28)*IF(RateConv=1,1,1+IPCALT)-1-'DCF Custom'!$I$144)/'DCF Custom'!$H$23*(1+'DCF Custom'!$C$6+$B28)^(-5) -> 229987.13 | V28: =R28+S28+T28+U28 -> 628448.59
B29: 0.008 | C29: =SUMPRODUCT('DCF Bear'!$D$73:$H$73,(1+'DCF Bear'!$C$6+$B29)^(-'DCF Bear'!$D$19:$H$19))+'DCF Bear'!$I$58*(1-'DCF Bear'!$I$57/'DCF Bear'!$I$59)/((1+'DCF Bear'!$C$6+$B29)*IF(RateConv=1,1,1+IPCALT)-1-'DCF Bear'!$I$57)/'DCF Bear'!$H$23*(1+'DCF Bear'!$C$6+$B29)^(-5) -> 101148.64 | D29: =SUMPRODUCT('DCF Bear'!$D$102:$H$102,(1+'DCF Bear'!$C$6+$B29)^(-'DCF Bear'!$D$19:$H$19))+'DCF Bear'!$I$87*(1-'DCF Bear'!$I$86/'DCF Bear'!$I$88)/((1+'DCF Bear'!$C$6+$B29)*IF(RateConv=1,1,1+IPCALT)-1-'DCF Bear'!$I$86)/'DCF Bear'!$H$23*(1+'DCF Bear'!$C$6+$B29)^(-5) -> 64132.04 | E29: =SUMPRODUCT('DCF Bear'!$D$131:$H$131,(1+'DCF Bear'!$C$6+$B29)^(-'DCF Bear'!$D$19:$H$19))+'DCF Bear'!$I$116*(1-'DCF Bear'!$I$115/'DCF Bear'!$I$117)/((1+'DCF Bear'!$C$6+$B29)*IF(RateConv=1,1,1+IPCALT)-1-'DCF Bear'!$I$115)/'DCF Bear'!$H$23*(1+'DCF Bear'!$C$6+$B29)^(-5) -> 36133.997 | F29: =SUMPRODUCT('DCF Bear'!$D$160:$H$160,(1+'DCF Bear'!$C$6+$B29)^(-'DCF Bear'!$D$19:$H$19))+'DCF Bear'!$I$145*(1-'DCF Bear'!$I$144/'DCF Bear'!$I$146)/((1+'DCF Bear'!$C$6+$B29)*IF(RateConv=1,1,1+IPCALT)-1-'DCF Bear'!$I$144)/'DCF Bear'!$H$23*(1+'DCF Bear'!$C$6+$B29)^(-5) -> 122521.2 | G29: =C29+D29+E29+F29 -> 323935.88 | H29: =SUMPRODUCT('DCF Base'!$D$73:$H$73,(1+'DCF Base'!$C$6+$B29)^(-'DCF Base'!$D$19:$H$19))+'DCF Base'!$I$58*(1-'DCF Base'!$I$57/'DCF Base'!$I$59)/((1+'DCF Base'!$C$6+$B29)*IF(RateConv=1,1,1+IPCALT)-1-'DCF Base'!$I$57)/'DCF Base'!$H$23*(1+'DCF Base'!$C$6+$B29)^(-5) -> 193176.15 | I29: =SUMPRODUCT('DCF Base'!$D$102:$H$102,(1+'DCF Base'!$C$6+$B29)^(-'DCF Base'!$D$19:$H$19))+'DCF Base'!$I$87*(1-'DCF Base'!$I$86/'DCF Base'!$I$88)/((1+'DCF Base'!$C$6+$B29)*IF(RateConv=1,1,1+IPCALT)-1-'DCF Base'!$I$86)/'DCF Base'!$H$23*(1+'DCF Base'!$C$6+$B29)^(-5) -> 120995.58 | J29: =SUMPRODUCT('DCF Base'!$D$131:$H$131,(1+'DCF Base'!$C$6+$B29)^(-'DCF Base'!$D$19:$H$19))+'DCF Base'!$I$116*(1-'DCF Base'!$I$115/'DCF Base'!$I$117)/((1+'DCF Base'!$C$6+$B29)*IF(RateConv=1,1,1+IPCALT)-1-'DCF Base'!$I$115)/'DCF Base'!$H$23*(1+'DCF Base'!$C$6+$B29)^(-5) -> 69875.232 | K29: =SUMPRODUCT('DCF Base'!$D$160:$H$160,(1+'DCF Base'!$C$6+$B29)^(-'DCF Base'!$D$19:$H$19))+'DCF Base'!$I$145*(1-'DCF Base'!$I$144/'DCF Base'!$I$146)/((1+'DCF Base'!$C$6+$B29)*IF(RateConv=1,1,1+IPCALT)-1-'DCF Base'!$I$144)/'DCF Base'!$H$23*(1+'DCF Base'!$C$6+$B29)^(-5) -> 222029.09 | L29: =H29+I29+J29+K29 -> 606076.05 | M29: =SUMPRODUCT('DCF Bull'!$D$73:$H$73,(1+'DCF Bull'!$C$6+$B29)^(-'DCF Bull'!$D$19:$H$19))+'DCF Bull'!$I$58*(1-'DCF Bull'!$I$57/'DCF Bull'!$I$59)/((1+'DCF Bull'!$C$6+$B29)*IF(RateConv=1,1,1+IPCALT)-1-'DCF Bull'!$I$57)/'DCF Bull'!$H$23*(1+'DCF Bull'!$C$6+$B29)^(-5) -> 374875.44 | N29: =SUMPRODUCT('DCF Bull'!$D$102:$H$102,(1+'DCF Bull'!$C$6+$B29)^(-'DCF Bull'!$D$19:$H$19))+'DCF Bull'!$I$87*(1-'DCF Bull'!$I$86/'DCF Bull'!$I$88)/((1+'DCF Bull'!$C$6+$B29)*IF(RateConv=1,1,1+IPCALT)-1-'DCF Bull'!$I$86)/'DCF Bull'!$H$23*(1+'DCF Bull'!$C$6+$B29)^(-5) -> 230313 | O29: =SUMPRODUCT('DCF Bull'!$D$131:$H$131,(1+'DCF Bull'!$C$6+$B29)^(-'DCF Bull'!$D$19:$H$19))+'DCF Bull'!$I$116*(1-'DCF Bull'!$I$115/'DCF Bull'!$I$117)/((1+'DCF Bull'!$C$6+$B29)*IF(RateConv=1,1,1+IPCALT)-1-'DCF Bull'!$I$115)/'DCF Bull'!$H$23*(1+'DCF Bull'!$C$6+$B29)^(-5) -> 136757.36 | P29: =SUMPRODUCT('DCF Bull'!$D$160:$H$160,(1+'DCF Bull'!$C$6+$B29)^(-'DCF Bull'!$D$19:$H$19))+'DCF Bull'!$I$145*(1-'DCF Bull'!$I$144/'DCF Bull'!$I$146)/((1+'DCF Bull'!$C$6+$B29)*IF(RateConv=1,1,1+IPCALT)-1-'DCF Bull'!$I$144)/'DCF Bull'!$H$23*(1+'DCF Bull'!$C$6+$B29)^(-5) -> 413346.71 | Q29: =M29+N29+O29+P29 -> 1155292.5 | R29: =SUMPRODUCT('DCF Custom'!$D$73:$H$73,(1+'DCF Custom'!$C$6+$B29)^(-'DCF Custom'!$D$19:$H$19))+'DCF Custom'!$I$58*(1-'DCF Custom'!$I$57/'DCF Custom'!$I$59)/((1+'DCF Custom'!$C$6+$B29)*IF(RateConv=1,1,1+IPCALT)-1-'DCF Custom'!$I$57)/'DCF Custom'!$H$23*(1+'DCF Custom'!$C$6+$B29)^(-5) -> 193176.15 | S29: =SUMPRODUCT('DCF Custom'!$D$102:$H$102,(1+'DCF Custom'!$C$6+$B29)^(-'DCF Custom'!$D$19:$H$19))+'DCF Custom'!$I$87*(1-'DCF Custom'!$I$86/'DCF Custom'!$I$88)/((1+'DCF Custom'!$C$6+$B29)*IF(RateConv=1,1,1+IPCALT)-1-'DCF Custom'!$I$86)/'DCF Custom'!$H$23*(1+'DCF Custom'!$C$6+$B29)^(-5) -> 120995.58 | T29: =SUMPRODUCT('DCF Custom'!$D$131:$H$131,(1+'DCF Custom'!$C$6+$B29)^(-'DCF Custom'!$D$19:$H$19))+'DCF Custom'!$I$116*(1-'DCF Custom'!$I$115/'DCF Custom'!$I$117)/((1+'DCF Custom'!$C$6+$B29)*IF(RateConv=1,1,1+IPCALT)-1-'DCF Custom'!$I$115)/'DCF Custom'!$H$23*(1+'DCF Custom'!$C$6+$B29)^(-5) -> 69875.232 | U29: =SUMPRODUCT('DCF Custom'!$D$160:$H$160,(1+'DCF Custom'!$C$6+$B29)^(-'DCF Custom'!$D$19:$H$19))+'DCF Custom'!$I$145*(1-'DCF Custom'!$I$144/'DCF Custom'!$I$146)/((1+'DCF Custom'!$C$6+$B29)*IF(RateConv=1,1,1+IPCALT)-1-'DCF Custom'!$I$144)/'DCF Custom'!$H$23*(1+'DCF Custom'!$C$6+$B29)^(-5) -> 222029.09 | V29: =R29+S29+T29+U29 -> 606076.05
B30: 0.009 | C30: =SUMPRODUCT('DCF Bear'!$D$73:$H$73,(1+'DCF Bear'!$C$6+$B30)^(-'DCF Bear'!$D$19:$H$19))+'DCF Bear'!$I$58*(1-'DCF Bear'!$I$57/'DCF Bear'!$I$59)/((1+'DCF Bear'!$C$6+$B30)*IF(RateConv=1,1,1+IPCALT)-1-'DCF Bear'!$I$57)/'DCF Bear'!$H$23*(1+'DCF Bear'!$C$6+$B30)^(-5) -> 99177.875 | D30: =SUMPRODUCT('DCF Bear'!$D$102:$H$102,(1+'DCF Bear'!$C$6+$B30)^(-'DCF Bear'!$D$19:$H$19))+'DCF Bear'!$I$87*(1-'DCF Bear'!$I$86/'DCF Bear'!$I$88)/((1+'DCF Bear'!$C$6+$B30)*IF(RateConv=1,1,1+IPCALT)-1-'DCF Bear'!$I$86)/'DCF Bear'!$H$23*(1+'DCF Bear'!$C$6+$B30)^(-5) -> 62822.545 | E30: =SUMPRODUCT('DCF Bear'!$D$131:$H$131,(1+'DCF Bear'!$C$6+$B30)^(-'DCF Bear'!$D$19:$H$19))+'DCF Bear'!$I$116*(1-'DCF Bear'!$I$115/'DCF Bear'!$I$117)/((1+'DCF Bear'!$C$6+$B30)*IF(RateConv=1,1,1+IPCALT)-1-'DCF Bear'!$I$115)/'DCF Bear'!$H$23*(1+'DCF Bear'!$C$6+$B30)^(-5) -> 35411.333 | F30: =SUMPRODUCT('DCF Bear'!$D$160:$H$160,(1+'DCF Bear'!$C$6+$B30)^(-'DCF Bear'!$D$19:$H$19))+'DCF Bear'!$I$145*(1-'DCF Bear'!$I$144/'DCF Bear'!$I$146)/((1+'DCF Bear'!$C$6+$B30)*IF(RateConv=1,1,1+IPCALT)-1-'DCF Bear'!$I$144)/'DCF Bear'!$H$23*(1+'DCF Bear'!$C$6+$B30)^(-5) -> 120269.77 | G30: =C30+D30+E30+F30 -> 317681.52 | H30: =SUMPRODUCT('DCF Base'!$D$73:$H$73,(1+'DCF Base'!$C$6+$B30)^(-'DCF Base'!$D$19:$H$19))+'DCF Base'!$I$58*(1-'DCF Base'!$I$57/'DCF Base'!$I$59)/((1+'DCF Base'!$C$6+$B30)*IF(RateConv=1,1,1+IPCALT)-1-'DCF Base'!$I$57)/'DCF Base'!$H$23*(1+'DCF Base'!$C$6+$B30)^(-5) -> 186506.54 | I30: =SUMPRODUCT('DCF Base'!$D$102:$H$102,(1+'DCF Base'!$C$6+$B30)^(-'DCF Base'!$D$19:$H$19))+'DCF Base'!$I$87*(1-'DCF Base'!$I$86/'DCF Base'!$I$88)/((1+'DCF Base'!$C$6+$B30)*IF(RateConv=1,1,1+IPCALT)-1-'DCF Base'!$I$86)/'DCF Base'!$H$23*(1+'DCF Base'!$C$6+$B30)^(-5) -> 116679.36 | J30: =SUMPRODUCT('DCF Base'!$D$131:$H$131,(1+'DCF Base'!$C$6+$B30)^(-'DCF Base'!$D$19:$H$19))+'DCF Base'!$I$116*(1-'DCF Base'!$I$115/'DCF Base'!$I$117)/((1+'DCF Base'!$C$6+$B30)*IF(RateConv=1,1,1+IPCALT)-1-'DCF Base'!$I$115)/'DCF Base'!$H$23*(1+'DCF Base'!$C$6+$B30)^(-5) -> 67422.196 | K30: =SUMPRODUCT('DCF Base'!$D$160:$H$160,(1+'DCF Base'!$C$6+$B30)^(-'DCF Base'!$D$19:$H$19))+'DCF Base'!$I$145*(1-'DCF Base'!$I$144/'DCF Base'!$I$146)/((1+'DCF Base'!$C$6+$B30)*IF(RateConv=1,1,1+IPCALT)-1-'DCF Base'!$I$144)/'DCF Base'!$H$23*(1+'DCF Base'!$C$6+$B30)^(-5) -> 214608.26 | L30: =H30+I30+J30+K30 -> 585216.36 | M30: =SUMPRODUCT('DCF Bull'!$D$73:$H$73,(1+'DCF Bull'!$C$6+$B30)^(-'DCF Bull'!$D$19:$H$19))+'DCF Bull'!$I$58*(1-'DCF Bull'!$I$57/'DCF Bull'!$I$59)/((1+'DCF Bull'!$C$6+$B30)*IF(RateConv=1,1,1+IPCALT)-1-'DCF Bull'!$I$57)/'DCF Bull'!$H$23*(1+'DCF Bull'!$C$6+$B30)^(-5) -> 352360.61 | N30: =SUMPRODUCT('DCF Bull'!$D$102:$H$102,(1+'DCF Bull'!$C$6+$B30)^(-'DCF Bull'!$D$19:$H$19))+'DCF Bull'!$I$87*(1-'DCF Bull'!$I$86/'DCF Bull'!$I$88)/((1+'DCF Bull'!$C$6+$B30)*IF(RateConv=1,1,1+IPCALT)-1-'DCF Bull'!$I$86)/'DCF Bull'!$H$23*(1+'DCF Bull'!$C$6+$B30)^(-5) -> 216174.92 | O30: =SUMPRODUCT('DCF Bull'!$D$131:$H$131,(1+'DCF Bull'!$C$6+$B30)^(-'DCF Bull'!$D$19:$H$19))+'DCF Bull'!$I$116*(1-'DCF Bull'!$I$115/'DCF Bull'!$I$117)/((1+'DCF Bull'!$C$6+$B30)*IF(RateConv=1,1,1+IPCALT)-1-'DCF Bull'!$I$115)/'DCF Bull'!$H$23*(1+'DCF Bull'!$C$6+$B30)^(-5) -> 128459.23 | P30: =SUMPRODUCT('DCF Bull'!$D$160:$H$160,(1+'DCF Bull'!$C$6+$B30)^(-'DCF Bull'!$D$19:$H$19))+'DCF Bull'!$I$145*(1-'DCF Bull'!$I$144/'DCF Bull'!$I$146)/((1+'DCF Bull'!$C$6+$B30)*IF(RateConv=1,1,1+IPCALT)-1-'DCF Bull'!$I$144)/'DCF Bull'!$H$23*(1+'DCF Bull'!$C$6+$B30)^(-5) -> 388932.96 | Q30: =M30+N30+O30+P30 -> 1085927.7 | R30: =SUMPRODUCT('DCF Custom'!$D$73:$H$73,(1+'DCF Custom'!$C$6+$B30)^(-'DCF Custom'!$D$19:$H$19))+'DCF Custom'!$I$58*(1-'DCF Custom'!$I$57/'DCF Custom'!$I$59)/((1+'DCF Custom'!$C$6+$B30)*IF(RateConv=1,1,1+IPCALT)-1-'DCF Custom'!$I$57)/'DCF Custom'!$H$23*(1+'DCF Custom'!$C$6+$B30)^(-5) -> 186506.54 | S30: =SUMPRODUCT('DCF Custom'!$D$102:$H$102,(1+'DCF Custom'!$C$6+$B30)^(-'DCF Custom'!$D$19:$H$19))+'DCF Custom'!$I$87*(1-'DCF Custom'!$I$86/'DCF Custom'!$I$88)/((1+'DCF Custom'!$C$6+$B30)*IF(RateConv=1,1,1+IPCALT)-1-'DCF Custom'!$I$86)/'DCF Custom'!$H$23*(1+'DCF Custom'!$C$6+$B30)^(-5) -> 116679.36 | T30: =SUMPRODUCT('DCF Custom'!$D$131:$H$131,(1+'DCF Custom'!$C$6+$B30)^(-'DCF Custom'!$D$19:$H$19))+'DCF Custom'!$I$116*(1-'DCF Custom'!$I$115/'DCF Custom'!$I$117)/((1+'DCF Custom'!$C$6+$B30)*IF(RateConv=1,1,1+IPCALT)-1-'DCF Custom'!$I$115)/'DCF Custom'!$H$23*(1+'DCF Custom'!$C$6+$B30)^(-5) -> 67422.196 | U30: =SUMPRODUCT('DCF Custom'!$D$160:$H$160,(1+'DCF Custom'!$C$6+$B30)^(-'DCF Custom'!$D$19:$H$19))+'DCF Custom'!$I$145*(1-'DCF Custom'!$I$144/'DCF Custom'!$I$146)/((1+'DCF Custom'!$C$6+$B30)*IF(RateConv=1,1,1+IPCALT)-1-'DCF Custom'!$I$144)/'DCF Custom'!$H$23*(1+'DCF Custom'!$C$6+$B30)^(-5) -> 214608.26 | V30: =R30+S30+T30+U30 -> 585216.36
B31: 0.01 | C31: =SUMPRODUCT('DCF Bear'!$D$73:$H$73,(1+'DCF Bear'!$C$6+$B31)^(-'DCF Bear'!$D$19:$H$19))+'DCF Bear'!$I$58*(1-'DCF Bear'!$I$57/'DCF Bear'!$I$59)/((1+'DCF Bear'!$C$6+$B31)*IF(RateConv=1,1,1+IPCALT)-1-'DCF Bear'!$I$57)/'DCF Bear'!$H$23*(1+'DCF Bear'!$C$6+$B31)^(-5) -> 97281.5 | D31: =SUMPRODUCT('DCF Bear'!$D$102:$H$102,(1+'DCF Bear'!$C$6+$B31)^(-'DCF Bear'!$D$19:$H$19))+'DCF Bear'!$I$87*(1-'DCF Bear'!$I$86/'DCF Bear'!$I$88)/((1+'DCF Bear'!$C$6+$B31)*IF(RateConv=1,1,1+IPCALT)-1-'DCF Bear'!$I$86)/'DCF Bear'!$H$23*(1+'DCF Bear'!$C$6+$B31)^(-5) -> 61562.702 | E31: =SUMPRODUCT('DCF Bear'!$D$131:$H$131,(1+'DCF Bear'!$C$6+$B31)^(-'DCF Bear'!$D$19:$H$19))+'DCF Bear'!$I$116*(1-'DCF Bear'!$I$115/'DCF Bear'!$I$117)/((1+'DCF Bear'!$C$6+$B31)*IF(RateConv=1,1,1+IPCALT)-1-'DCF Bear'!$I$115)/'DCF Bear'!$H$23*(1+'DCF Bear'!$C$6+$B31)^(-5) -> 34716.02 | F31: =SUMPRODUCT('DCF Bear'!$D$160:$H$160,(1+'DCF Bear'!$C$6+$B31)^(-'DCF Bear'!$D$19:$H$19))+'DCF Bear'!$I$145*(1-'DCF Bear'!$I$144/'DCF Bear'!$I$146)/((1+'DCF Bear'!$C$6+$B31)*IF(RateConv=1,1,1+IPCALT)-1-'DCF Bear'!$I$144)/'DCF Bear'!$H$23*(1+'DCF Bear'!$C$6+$B31)^(-5) -> 118102.77 | G31: =C31+D31+E31+F31 -> 311662.99 | H31: =SUMPRODUCT('DCF Base'!$D$73:$H$73,(1+'DCF Base'!$C$6+$B31)^(-'DCF Base'!$D$19:$H$19))+'DCF Base'!$I$58*(1-'DCF Base'!$I$57/'DCF Base'!$I$59)/((1+'DCF Base'!$C$6+$B31)*IF(RateConv=1,1,1+IPCALT)-1-'DCF Base'!$I$57)/'DCF Base'!$H$23*(1+'DCF Base'!$C$6+$B31)^(-5) -> 180273.32 | I31: =SUMPRODUCT('DCF Base'!$D$102:$H$102,(1+'DCF Base'!$C$6+$B31)^(-'DCF Base'!$D$19:$H$19))+'DCF Base'!$I$87*(1-'DCF Base'!$I$86/'DCF Base'!$I$88)/((1+'DCF Base'!$C$6+$B31)*IF(RateConv=1,1,1+IPCALT)-1-'DCF Base'!$I$86)/'DCF Base'!$H$23*(1+'DCF Base'!$C$6+$B31)^(-5) -> 112646.08 | J31: =SUMPRODUCT('DCF Base'!$D$131:$H$131,(1+'DCF Base'!$C$6+$B31)^(-'DCF Base'!$D$19:$H$19))+'DCF Base'!$I$116*(1-'DCF Base'!$I$115/'DCF Base'!$I$117)/((1+'DCF Base'!$C$6+$B31)*IF(RateConv=1,1,1+IPCALT)-1-'DCF Base'!$I$115)/'DCF Base'!$H$23*(1+'DCF Base'!$C$6+$B31)^(-5) -> 65129.819 | K31: =SUMPRODUCT('DCF Base'!$D$160:$H$160,(1+'DCF Base'!$C$6+$B31)^(-'DCF Base'!$D$19:$H$19))+'DCF Base'!$I$145*(1-'DCF Base'!$I$144/'DCF Base'!$I$146)/((1+'DCF Base'!$C$6+$B31)*IF(RateConv=1,1,1+IPCALT)-1-'DCF Base'!$I$144)/'DCF Base'!$H$23*(1+'DCF Base'!$C$6+$B31)^(-5) -> 207671.98 | L31: =H31+I31+J31+K31 -> 565721.2 | M31: =SUMPRODUCT('DCF Bull'!$D$73:$H$73,(1+'DCF Bull'!$C$6+$B31)^(-'DCF Bull'!$D$19:$H$19))+'DCF Bull'!$I$58*(1-'DCF Bull'!$I$57/'DCF Bull'!$I$59)/((1+'DCF Bull'!$C$6+$B31)*IF(RateConv=1,1,1+IPCALT)-1-'DCF Bull'!$I$57)/'DCF Bull'!$H$23*(1+'DCF Bull'!$C$6+$B31)^(-5) -> 332349.15 | N31: =SUMPRODUCT('DCF Bull'!$D$102:$H$102,(1+'DCF Bull'!$C$6+$B31)^(-'DCF Bull'!$D$19:$H$19))+'DCF Bull'!$I$87*(1-'DCF Bull'!$I$86/'DCF Bull'!$I$88)/((1+'DCF Bull'!$C$6+$B31)*IF(RateConv=1,1,1+IPCALT)-1-'DCF Bull'!$I$86)/'DCF Bull'!$H$23*(1+'DCF Bull'!$C$6+$B31)^(-5) -> 203610.03 | O31: =SUMPRODUCT('DCF Bull'!$D$131:$H$131,(1+'DCF Bull'!$C$6+$B31)^(-'DCF Bull'!$D$19:$H$19))+'DCF Bull'!$I$116*(1-'DCF Bull'!$I$115/'DCF Bull'!$I$117)/((1+'DCF Bull'!$C$6+$B31)*IF(RateConv=1,1,1+IPCALT)-1-'DCF Bull'!$I$115)/'DCF Bull'!$H$23*(1+'DCF Bull'!$C$6+$B31)^(-5) -> 121084.09 | P31: =SUMPRODUCT('DCF Bull'!$D$160:$H$160,(1+'DCF Bull'!$C$6+$B31)^(-'DCF Bull'!$D$19:$H$19))+'DCF Bull'!$I$145*(1-'DCF Bull'!$I$144/'DCF Bull'!$I$146)/((1+'DCF Bull'!$C$6+$B31)*IF(RateConv=1,1,1+IPCALT)-1-'DCF Bull'!$I$144)/'DCF Bull'!$H$23*(1+'DCF Bull'!$C$6+$B31)^(-5) -> 367232.05 | Q31: =M31+N31+O31+P31 -> 1024275.3 | R31: =SUMPRODUCT('DCF Custom'!$D$73:$H$73,(1+'DCF Custom'!$C$6+$B31)^(-'DCF Custom'!$D$19:$H$19))+'DCF Custom'!$I$58*(1-'DCF Custom'!$I$57/'DCF Custom'!$I$59)/((1+'DCF Custom'!$C$6+$B31)*IF(RateConv=1,1,1+IPCALT)-1-'DCF Custom'!$I$57)/'DCF Custom'!$H$23*(1+'DCF Custom'!$C$6+$B31)^(-5) -> 180273.32 | S31: =SUMPRODUCT('DCF Custom'!$D$102:$H$102,(1+'DCF Custom'!$C$6+$B31)^(-'DCF Custom'!$D$19:$H$19))+'DCF Custom'!$I$87*(1-'DCF Custom'!$I$86/'DCF Custom'!$I$88)/((1+'DCF Custom'!$C$6+$B31)*IF(RateConv=1,1,1+IPCALT)-1-'DCF Custom'!$I$86)/'DCF Custom'!$H$23*(1+'DCF Custom'!$C$6+$B31)^(-5) -> 112646.08 | T31: =SUMPRODUCT('DCF Custom'!$D$131:$H$131,(1+'DCF Custom'!$C$6+$B31)^(-'DCF Custom'!$D$19:$H$19))+'DCF Custom'!$I$116*(1-'DCF Custom'!$I$115/'DCF Custom'!$I$117)/((1+'DCF Custom'!$C$6+$B31)*IF(RateConv=1,1,1+IPCALT)-1-'DCF Custom'!$I$115)/'DCF Custom'!$H$23*(1+'DCF Custom'!$C$6+$B31)^(-5) -> 65129.819 | U31: =SUMPRODUCT('DCF Custom'!$D$160:$H$160,(1+'DCF Custom'!$C$6+$B31)^(-'DCF Custom'!$D$19:$H$19))+'DCF Custom'!$I$145*(1-'DCF Custom'!$I$144/'DCF Custom'!$I$146)/((1+'DCF Custom'!$C$6+$B31)*IF(RateConv=1,1,1+IPCALT)-1-'DCF Custom'!$I$144)/'DCF Custom'!$H$23*(1+'DCF Custom'!$C$6+$B31)^(-5) -> 207671.98 | V31: =R31+S31+T31+U31 -> 565721.2
B32: 0.011 | C32: =SUMPRODUCT('DCF Bear'!$D$73:$H$73,(1+'DCF Bear'!$C$6+$B32)^(-'DCF Bear'!$D$19:$H$19))+'DCF Bear'!$I$58*(1-'DCF Bear'!$I$57/'DCF Bear'!$I$59)/((1+'DCF Bear'!$C$6+$B32)*IF(RateConv=1,1,1+IPCALT)-1-'DCF Bear'!$I$57)/'DCF Bear'!$H$23*(1+'DCF Bear'!$C$6+$B32)^(-5) -> 95455.385 | D32: =SUMPRODUCT('DCF Bear'!$D$102:$H$102,(1+'DCF Bear'!$C$6+$B32)^(-'DCF Bear'!$D$19:$H$19))+'DCF Bear'!$I$87*(1-'DCF Bear'!$I$86/'DCF Bear'!$I$88)/((1+'DCF Bear'!$C$6+$B32)*IF(RateConv=1,1,1+IPCALT)-1-'DCF Bear'!$I$86)/'DCF Bear'!$H$23*(1+'DCF Bear'!$C$6+$B32)^(-5) -> 60349.751 | E32: =SUMPRODUCT('DCF Bear'!$D$131:$H$131,(1+'DCF Bear'!$C$6+$B32)^(-'DCF Bear'!$D$19:$H$19))+'DCF Bear'!$I$116*(1-'DCF Bear'!$I$115/'DCF Bear'!$I$117)/((1+'DCF Bear'!$C$6+$B32)*IF(RateConv=1,1,1+IPCALT)-1-'DCF Bear'!$I$115)/'DCF Bear'!$H$23*(1+'DCF Bear'!$C$6+$B32)^(-5) -> 34046.539 | F32: =SUMPRODUCT('DCF Bear'!$D$160:$H$160,(1+'DCF Bear'!$C$6+$B32)^(-'DCF Bear'!$D$19:$H$19))+'DCF Bear'!$I$145*(1-'DCF Bear'!$I$144/'DCF Bear'!$I$146)/((1+'DCF Bear'!$C$6+$B32)*IF(RateConv=1,1,1+IPCALT)-1-'DCF Bear'!$I$144)/'DCF Bear'!$H$23*(1+'DCF Bear'!$C$6+$B32)^(-5) -> 116015.52 | G32: =C32+D32+E32+F32 -> 305867.19 | H32: =SUMPRODUCT('DCF Base'!$D$73:$H$73,(1+'DCF Base'!$C$6+$B32)^(-'DCF Base'!$D$19:$H$19))+'DCF Base'!$I$58*(1-'DCF Base'!$I$57/'DCF Base'!$I$59)/((1+'DCF Base'!$C$6+$B32)*IF(RateConv=1,1,1+IPCALT)-1-'DCF Base'!$I$57)/'DCF Base'!$H$23*(1+'DCF Base'!$C$6+$B32)^(-5) -> 174435.06 | I32: =SUMPRODUCT('DCF Base'!$D$102:$H$102,(1+'DCF Base'!$C$6+$B32)^(-'DCF Base'!$D$19:$H$19))+'DCF Base'!$I$87*(1-'DCF Base'!$I$86/'DCF Base'!$I$88)/((1+'DCF Base'!$C$6+$B32)*IF(RateConv=1,1,1+IPCALT)-1-'DCF Base'!$I$86)/'DCF Base'!$H$23*(1+'DCF Base'!$C$6+$B32)^(-5) -> 108868.87 | J32: =SUMPRODUCT('DCF Base'!$D$131:$H$131,(1+'DCF Base'!$C$6+$B32)^(-'DCF Base'!$D$19:$H$19))+'DCF Base'!$I$116*(1-'DCF Base'!$I$115/'DCF Base'!$I$117)/((1+'DCF Base'!$C$6+$B32)*IF(RateConv=1,1,1+IPCALT)-1-'DCF Base'!$I$115)/'DCF Base'!$H$23*(1+'DCF Base'!$C$6+$B32)^(-5) -> 62982.848 | K32: =SUMPRODUCT('DCF Base'!$D$160:$H$160,(1+'DCF Base'!$C$6+$B32)^(-'DCF Base'!$D$19:$H$19))+'DCF Base'!$I$145*(1-'DCF Base'!$I$144/'DCF Base'!$I$146)/((1+'DCF Base'!$C$6+$B32)*IF(RateConv=1,1,1+IPCALT)-1-'DCF Base'!$I$144)/'DCF Base'!$H$23*(1+'DCF Base'!$C$6+$B32)^(-5) -> 201174.25 | L32: =H32+I32+J32+K32 -> 547461.02 | M32: =SUMPRODUCT('DCF Bull'!$D$73:$H$73,(1+'DCF Bull'!$C$6+$B32)^(-'DCF Bull'!$D$19:$H$19))+'DCF Bull'!$I$58*(1-'DCF Bull'!$I$57/'DCF Bull'!$I$59)/((1+'DCF Bull'!$C$6+$B32)*IF(RateConv=1,1,1+IPCALT)-1-'DCF Bull'!$I$57)/'DCF Bull'!$H$23*(1+'DCF Bull'!$C$6+$B32)^(-5) -> 314445.77 | N32: =SUMPRODUCT('DCF Bull'!$D$102:$H$102,(1+'DCF Bull'!$C$6+$B32)^(-'DCF Bull'!$D$19:$H$19))+'DCF Bull'!$I$87*(1-'DCF Bull'!$I$86/'DCF Bull'!$I$88)/((1+'DCF Bull'!$C$6+$B32)*IF(RateConv=1,1,1+IPCALT)-1-'DCF Bull'!$I$86)/'DCF Bull'!$H$23*(1+'DCF Bull'!$C$6+$B32)^(-5) -> 192369.91 | O32: =SUMPRODUCT('DCF Bull'!$D$131:$H$131,(1+'DCF Bull'!$C$6+$B32)^(-'DCF Bull'!$D$19:$H$19))+'DCF Bull'!$I$116*(1-'DCF Bull'!$I$115/'DCF Bull'!$I$117)/((1+'DCF Bull'!$C$6+$B32)*IF(RateConv=1,1,1+IPCALT)-1-'DCF Bull'!$I$115)/'DCF Bull'!$H$23*(1+'DCF Bull'!$C$6+$B32)^(-5) -> 114486.2 | P32: =SUMPRODUCT('DCF Bull'!$D$160:$H$160,(1+'DCF Bull'!$C$6+$B32)^(-'DCF Bull'!$D$19:$H$19))+'DCF Bull'!$I$145*(1-'DCF Bull'!$I$144/'DCF Bull'!$I$146)/((1+'DCF Bull'!$C$6+$B32)*IF(RateConv=1,1,1+IPCALT)-1-'DCF Bull'!$I$144)/'DCF Bull'!$H$23*(1+'DCF Bull'!$C$6+$B32)^(-5) -> 347815.65 | Q32: =M32+N32+O32+P32 -> 969117.53 | R32: =SUMPRODUCT('DCF Custom'!$D$73:$H$73,(1+'DCF Custom'!$C$6+$B32)^(-'DCF Custom'!$D$19:$H$19))+'DCF Custom'!$I$58*(1-'DCF Custom'!$I$57/'DCF Custom'!$I$59)/((1+'DCF Custom'!$C$6+$B32)*IF(RateConv=1,1,1+IPCALT)-1-'DCF Custom'!$I$57)/'DCF Custom'!$H$23*(1+'DCF Custom'!$C$6+$B32)^(-5) -> 174435.06 | S32: =SUMPRODUCT('DCF Custom'!$D$102:$H$102,(1+'DCF Custom'!$C$6+$B32)^(-'DCF Custom'!$D$19:$H$19))+'DCF Custom'!$I$87*(1-'DCF Custom'!$I$86/'DCF Custom'!$I$88)/((1+'DCF Custom'!$C$6+$B32)*IF(RateConv=1,1,1+IPCALT)-1-'DCF Custom'!$I$86)/'DCF Custom'!$H$23*(1+'DCF Custom'!$C$6+$B32)^(-5) -> 108868.87 | T32: =SUMPRODUCT('DCF Custom'!$D$131:$H$131,(1+'DCF Custom'!$C$6+$B32)^(-'DCF Custom'!$D$19:$H$19))+'DCF Custom'!$I$116*(1-'DCF Custom'!$I$115/'DCF Custom'!$I$117)/((1+'DCF Custom'!$C$6+$B32)*IF(RateConv=1,1,1+IPCALT)-1-'DCF Custom'!$I$115)/'DCF Custom'!$H$23*(1+'DCF Custom'!$C$6+$B32)^(-5) -> 62982.848 | U32: =SUMPRODUCT('DCF Custom'!$D$160:$H$160,(1+'DCF Custom'!$C$6+$B32)^(-'DCF Custom'!$D$19:$H$19))+'DCF Custom'!$I$145*(1-'DCF Custom'!$I$144/'DCF Custom'!$I$146)/((1+'DCF Custom'!$C$6+$B32)*IF(RateConv=1,1,1+IPCALT)-1-'DCF Custom'!$I$144)/'DCF Custom'!$H$23*(1+'DCF Custom'!$C$6+$B32)^(-5) -> 201174.25 | V32: =R32+S32+T32+U32 -> 547461.02
... B171: 0.15 | C171: =SUMPRODUCT('DCF Bear'!$D$73:$H$73,(1+'DCF Bear'!$C$6+$B171)^(-'DCF Bear'!$D$19:$H$19))+'DCF Bear'!$I$58*(1-'DCF Bear'!$I$57/'DCF Bear'!$I$59)/((1+'DCF Bear'!$C$6+$B171)*IF(RateConv=1,1,1+IPCALT)-1-'DCF Bear'!$I$57)/'DCF Bear'!$H$23*(1+'DCF Bear'!$C$6+$B171)^(-5) -> 25824.965 | D171: =SUMPRODUCT('DCF Bear'!$D$102:$H$102,(1+'DCF Bear'!$C$6+$B171)^(-'DCF Bear'!$D$19:$H$19))+'DCF Bear'!$I$87*(1-'DCF Bear'!$I$86/'DCF Bear'!$I$88)/((1+'DCF Bear'!$C$6+$B171)*IF(RateConv=1,1,1+IPCALT)-1-'DCF Bear'!$I$86)/'DCF Bear'!$H$23*(1+'DCF Bear'!$C$6+$B171)^(-5) -> 14586.576 | E171: =SUMPRODUCT('DCF Bear'!$D$131:$H$131,(1+'DCF Bear'!$C$6+$B171)^(-'DCF Bear'!$D$19:$H$19))+'DCF Bear'!$I$116*(1-'DCF Bear'!$I$115/'DCF Bear'!$I$117)/((1+'DCF Bear'!$C$6+$B171)*IF(RateConv=1,1,1+IPCALT)-1-'DCF Bear'!$I$115)/'DCF Bear'!$H$23*(1+'DCF Bear'!$C$6+$B171)^(-5) -> 8676.5352 | F171: =SUMPRODUCT('DCF Bear'!$D$160:$H$160,(1+'DCF Bear'!$C$6+$B171)^(-'DCF Bear'!$D$19:$H$19))+'DCF Bear'!$I$145*(1-'DCF Bear'!$I$144/'DCF Bear'!$I$146)/((1+'DCF Bear'!$C$6+$B171)*IF(RateConv=1,1,1+IPCALT)-1-'DCF Bear'!$I$144)/'DCF Bear'!$H$23*(1+'DCF Bear'!$C$6+$B171)^(-5) -> 35241.347 | G171: =C171+D171+E171+F171 -> 84329.424 | H171: =SUMPRODUCT('DCF Base'!$D$73:$H$73,(1+'DCF Base'!$C$6+$B171)^(-'DCF Base'!$D$19:$H$19))+'DCF Base'!$I$58*(1-'DCF Base'!$I$57/'DCF Base'!$I$59)/((1+'DCF Base'!$C$6+$B171)*IF(RateConv=1,1,1+IPCALT)-1-'DCF Base'!$I$57)/'DCF Base'!$H$23*(1+'DCF Base'!$C$6+$B171)^(-5) -> 29540.193 | I171: =SUMPRODUCT('DCF Base'!$D$102:$H$102,(1+'DCF Base'!$C$6+$B171)^(-'DCF Base'!$D$19:$H$19))+'DCF Base'!$I$87*(1-'DCF Base'!$I$86/'DCF Base'!$I$88)/((1+'DCF Base'!$C$6+$B171)*IF(RateConv=1,1,1+IPCALT)-1-'DCF Base'!$I$86)/'DCF Base'!$H$23*(1+'DCF Base'!$C$6+$B171)^(-5) -> 15883.066 | J171: =SUMPRODUCT('DCF Base'!$D$131:$H$131,(1+'DCF Base'!$C$6+$B171)^(-'DCF Base'!$D$19:$H$19))+'DCF Base'!$I$116*(1-'DCF Base'!$I$115/'DCF Base'!$I$117)/((1+'DCF Base'!$C$6+$B171)*IF(RateConv=1,1,1+IPCALT)-1-'DCF Base'!$I$115)/'DCF Base'!$H$23*(1+'DCF Base'!$C$6+$B171)^(-5) -> 9925.6648 | K171: =SUMPRODUCT('DCF Base'!$D$160:$H$160,(1+'DCF Base'!$C$6+$B171)^(-'DCF Base'!$D$19:$H$19))+'DCF Base'!$I$145*(1-'DCF Base'!$I$144/'DCF Base'!$I$146)/((1+'DCF Base'!$C$6+$B171)*IF(RateConv=1,1,1+IPCALT)-1-'DCF Base'!$I$144)/'DCF Base'!$H$23*(1+'DCF Base'!$C$6+$B171)^(-5) -> 38515.779 | L171: =H171+I171+J171+K171 -> 93864.703 | M171: =SUMPRODUCT('DCF Bull'!$D$73:$H$73,(1+'DCF Bull'!$C$6+$B171)^(-'DCF Bull'!$D$19:$H$19))+'DCF Bull'!$I$58*(1-'DCF Bull'!$I$57/'DCF Bull'!$I$59)/((1+'DCF Bull'!$C$6+$B171)*IF(RateConv=1,1,1+IPCALT)-1-'DCF Bull'!$I$57)/'DCF Bull'!$H$23*(1+'DCF Bull'!$C$6+$B171)^(-5) -> 32463.415 | N171: =SUMPRODUCT('DCF Bull'!$D$102:$H$102,(1+'DCF Bull'!$C$6+$B171)^(-'DCF Bull'!$D$19:$H$19))+'DCF Bull'!$I$87*(1-'DCF Bull'!$I$86/'DCF Bull'!$I$88)/((1+'DCF Bull'!$C$6+$B171)*IF(RateConv=1,1,1+IPCALT)-1-'DCF Bull'!$I$86)/'DCF Bull'!$H$23*(1+'DCF Bull'!$C$6+$B171)^(-5) -> 16412.191 | O171: =SUMPRODUCT('DCF Bull'!$D$131:$H$131,(1+'DCF Bull'!$C$6+$B171)^(-'DCF Bull'!$D$19:$H$19))+'DCF Bull'!$I$116*(1-'DCF Bull'!$I$115/'DCF Bull'!$I$117)/((1+'DCF Bull'!$C$6+$B171)*IF(RateConv=1,1,1+IPCALT)-1-'DCF Bull'!$I$115)/'DCF Bull'!$H$23*(1+'DCF Bull'!$C$6+$B171)^(-5) -> 10869.877 | P171: =SUMPRODUCT('DCF Bull'!$D$160:$H$160,(1+'DCF Bull'!$C$6+$B171)^(-'DCF Bull'!$D$19:$H$19))+'DCF Bull'!$I$145*(1-'DCF Bull'!$I$144/'DCF Bull'!$I$146)/((1+'DCF Bull'!$C$6+$B171)*IF(RateConv=1,1,1+IPCALT)-1-'DCF Bull'!$I$144)/'DCF Bull'!$H$23*(1+'DCF Bull'!$C$6+$B171)^(-5) -> 40521.671 | Q171: =M171+N171+O171+P171 -> 100267.15 | R171: =SUMPRODUCT('DCF Custom'!$D$73:$H$73,(1+'DCF Custom'!$C$6+$B171)^(-'DCF Custom'!$D$19:$H$19))+'DCF Custom'!$I$58*(1-'DCF Custom'!$I$57/'DCF Custom'!$I$59)/((1+'DCF Custom'!$C$6+$B171)*IF(RateConv=1,1,1+IPCALT)-1-'DCF Custom'!$I$57)/'DCF Custom'!$H$23*(1+'DCF Custom'!$C$6+$B171)^(-5) -> 29540.193 | S171: =SUMPRODUCT('DCF Custom'!$D$102:$H$102,(1+'DCF Custom'!$C$6+$B171)^(-'DCF Custom'!$D$19:$H$19))+'DCF Custom'!$I$87*(1-'DCF Custom'!$I$86/'DCF Custom'!$I$88)/((1+'DCF Custom'!$C$6+$B171)*IF(RateConv=1,1,1+IPCALT)-1-'DCF Custom'!$I$86)/'DCF Custom'!$H$23*(1+'DCF Custom'!$C$6+$B171)^(-5) -> 15883.066 | T171: =SUMPRODUCT('DCF Custom'!$D$131:$H$131,(1+'DCF Custom'!$C$6+$B171)^(-'DCF Custom'!$D$19:$H$19))+'DCF Custom'!$I$116*(1-'DCF Custom'!$I$115/'DCF Custom'!$I$117)/((1+'DCF Custom'!$C$6+$B171)*IF(RateConv=1,1,1+IPCALT)-1-'DCF Custom'!$I$115)/'DCF Custom'!$H$23*(1+'DCF Custom'!$C$6+$B171)^(-5) -> 9925.6648 | U171: =SUMPRODUCT('DCF Custom'!$D$160:$H$160,(1+'DCF Custom'!$C$6+$B171)^(-'DCF Custom'!$D$19:$H$19))+'DCF Custom'!$I$145*(1-'DCF Custom'!$I$144/'DCF Custom'!$I$146)/((1+'DCF Custom'!$C$6+$B171)*IF(RateConv=1,1,1+IPCALT)-1-'DCF Custom'!$I$144)/'DCF Custom'!$H$23*(1+'DCF Custom'!$C$6+$B171)^(-5) -> 38515.779 | V171: =R171+S171+T171+U171 -> 93864.703

Sheet Sensitivity
B1: Ibovespa - Sensitivity: Ibovespa DCF value vs real rate and ERP (Base cash flows)
B2: One ERP for every box; value depends on real rate + ERP. Cash flows of DCF Base. Edit the pink headers to change the grid points.
B3: Legend: | C3: input | D3: assumption | E3: formula
B5: Ibovespa fair value at the horizon (index pts)
B6: 5-year real rate (rows) | ERP (columns)
B7: Real rate \ ERP | C7: 0.035 | D7: 0.04 | E7: 0.045 | F7: 0.05 | G7: 0.055 | H7: 0.06 | I7: 0.065 | J7: 0.07 | K7: 0.075 | L7: 0.08 | M7: 0.085
B8: 0.05 | C8: =IF(Horizon=1,(SUMPRODUCT('DCF Base'!$D$73:$H$73,(1+$B8+C$7)^(-'DCF Base'!$D$19:$H$19))+'DCF Base'!$I$58*(1-'DCF Base'!$I$57/'DCF Base'!$I$59)/((1+$B8+C$7)*IF(RateConv=1,1,1+IPCALT)-1-'DCF Base'!$I$57)/'DCF Base'!$H$23*(1+$B8+C$7)^(-5))*IF(RateConv=1,(1+$B8+C$7),(1+$B8+C$7)*(1+IPCA1))-'DCF Base'!$D$62,SUMPRODUCT('DCF Base'!$D$73:$H$73,(1+$B8+C$7)^(-'DCF Base'!$D$19:$H$19))+'DCF Base'!$I$58*(1-'DCF Base'!$I$57/'DCF Base'!$I$59)/((1+$B8+C$7)*IF(RateConv=1,1,1+IPCALT)-1-'DCF Base'!$I$57)/'DCF Base'!$H$23*(1+$B8+C$7)^(-5))+IF(Horizon=1,(SUMPRODUCT('DCF Base'!$D$102:$H$102,(1+$B8+C$7)^(-'DCF Base'!$D$19:$H$19))+'DCF Base'!$I$87*(1-'DCF Base'!$I$86/'DCF Base'!$I$88)/((1+$B8+C$7)*IF(RateConv=1,1,1+IPCALT)-1-'DCF Base'!$I$86)/'DCF Base'!$H$23*(1+$B8+C$7)^(-5))*IF(RateConv=1,(1+$B8+C$7),(1+$B8+C$7)*(1+IPCA1))-'DCF Base'!$D$91,SUMPRODUCT('DCF Base'!$D$102:$H$102,(1+$B8+C$7)^(-'DCF Base'!$D$19:$H$19))+'DCF Base'!$I$87*(1-'DCF Base'!$I$86/'DCF Base'!$I$88)/((1+$B8+C$7)*IF(RateConv=1,1,1+IPCALT)-1-'DCF Base'!$I$86)/'DCF Base'!$H$23*(1+$B8+C$7)^(-5))+IF(Horizon=1,(SUMPRODUCT('DCF Base'!$D$131:$H$131,(1+$B8+C$7)^(-'DCF Base'!$D$19:$H$19))+'DCF Base'!$I$116*(1-'DCF Base'!$I$115/'DCF Base'!$I$117)/((1+$B8+C$7)*IF(RateConv=1,1,1+IPCALT)-1-'DCF Base'!$I$115)/'DCF Base'!$H$23*(1+$B8+C$7)^(-5))*IF(RateConv=1,(1+$B8+C$7),(1+$B8+C$7)*(1+IPCA1))-'DCF Base'!$D$120,SUMPRODUCT('DCF Base'!$D$131:$H$131,(1+$B8+C$7)^(-'DCF Base'!$D$19:$H$19))+'DCF Base'!$I$116*(1-'DCF Base'!$I$115/'DCF Base'!$I$117)/((1+$B8+C$7)*IF(RateConv=1,1,1+IPCALT)-1-'DCF Base'!$I$115)/'DCF Base'!$H$23*(1+$B8+C$7)^(-5))+IF(Horizon=1,(SUMPRODUCT('DCF Base'!$D$160:$H$160,(1+$B8+C$7)^(-'DCF Base'!$D$19:$H$19))+'DCF Base'!$I$145*(1-'DCF Base'!$I$144/'DCF Base'!$I$146)/((1+$B8+C$7)*IF(RateConv=1,1,1+IPCALT)-1-'DCF Base'!$I$144)/'DCF Base'!$H$23*(1+$B8+C$7)^(-5))*IF(RateConv=1,(1+$B8+C$7),(1+$B8+C$7)*(1+IPCA1))-'DCF Base'!$D$149,SUMPRODUCT('DCF Base'!$D$160:$H$160,(1+$B8+C$7)^(-'DCF Base'!$D$19:$H$19))+'DCF Base'!$I$145*(1-'DCF Base'!$I$144/'DCF Base'!$I$146)/((1+$B8+C$7)*IF(RateConv=1,1,1+IPCALT)-1-'DCF Base'!$I$144)/'DCF Base'!$H$23*(1+$B8+C$7)^(-5)) -> 480791.65 | D8: =IF(Horizon=1,(SUMPRODUCT('DCF Base'!$D$73:$H$73,(1+$B8+D$7)^(-'DCF Base'!$D$19:$H$19))+'DCF Base'!$I$58*(1-'DCF Base'!$I$57/'DCF Base'!$I$59)/((1+$B8+D$7)*IF(RateConv=1,1,1+IPCALT)-1-'DCF Base'!$I$57)/'DCF Base'!$H$23*(1+$B8+D$7)^(-5))*IF(RateConv=1,(1+$B8+D$7),(1+$B8+D$7)*(1+IPCA1))-'DCF Base'!$D$62,SUMPRODUCT('DCF Base'!$D$73:$H$73,(1+$B8+D$7)^(-'DCF Base'!$D$19:$H$19))+'DCF Base'!$I$58*(1-'DCF Base'!$I$57/'DCF Base'!$I$59)/((1+$B8+D$7)*IF(RateConv=1,1,1+IPCALT)-1-'DCF Base'!$I$57)/'DCF Base'!$H$23*(1+$B8+D$7)^(-5))+IF(Horizon=1,(SUMPRODUCT('DCF Base'!$D$102:$H$102,(1+$B8+D$7)^(-'DCF Base'!$D$19:$H$19))+'DCF Base'!$I$87*(1-'DCF Base'!$I$86/'DCF Base'!$I$88)/((1+$B8+D$7)*IF(RateConv=1,1,1+IPCALT)-1-'DCF Base'!$I$86)/'DCF Base'!$H$23*(1+$B8+D$7)^(-5))*IF(RateConv=1,(1+$B8+D$7),(1+$B8+D$7)*(1+IPCA1))-'DCF Base'!$D$91,SUMPRODUCT('DCF Base'!$D$102:$H$102,(1+$B8+D$7)^(-'DCF Base'!$D$19:$H$19))+'DCF Base'!$I$87*(1-'DCF Base'!$I$86/'DCF Base'!$I$88)/((1+$B8+D$7)*IF(RateConv=1,1,1+IPCALT)-1-'DCF Base'!$I$86)/'DCF Base'!$H$23*(1+$B8+D$7)^(-5))+IF(Horizon=1,(SUMPRODUCT('DCF Base'!$D$131:$H$131,(1+$B8+D$7)^(-'DCF Base'!$D$19:$H$19))+'DCF Base'!$I$116*(1-'DCF Base'!$I$115/'DCF Base'!$I$117)/((1+$B8+D$7)*IF(RateConv=1,1,1+IPCALT)-1-'DCF Base'!$I$115)/'DCF Base'!$H$23*(1+$B8+D$7)^(-5))*IF(RateConv=1,(1+$B8+D$7),(1+$B8+D$7)*(1+IPCA1))-'DCF Base'!$D$120,SUMPRODUCT('DCF Base'!$D$131:$H$131,(1+$B8+D$7)^(-'DCF Base'!$D$19:$H$19))+'DCF Base'!$I$116*(1-'DCF Base'!$I$115/'DCF Base'!$I$117)/((1+$B8+D$7)*IF(RateConv=1,1,1+IPCALT)-1-'DCF Base'!$I$115)/'DCF Base'!$H$23*(1+$B8+D$7)^(-5))+IF(Horizon=1,(SUMPRODUCT('DCF Base'!$D$160:$H$160,(1+$B8+D$7)^(-'DCF Base'!$D$19:$H$19))+'DCF Base'!$I$145*(1-'DCF Base'!$I$144/'DCF Base'!$I$146)/((1+$B8+D$7)*IF(RateConv=1,1,1+IPCALT)-1-'DCF Base'!$I$144)/'DCF Base'!$H$23*(1+$B8+D$7)^(-5))*IF(RateConv=1,(1+$B8+D$7),(1+$B8+D$7)*(1+IPCA1))-'DCF Base'!$D$149,SUMPRODUCT('DCF Base'!$D$160:$H$160,(1+$B8+D$7)^(-'DCF Base'!$D$19:$H$19))+'DCF Base'!$I$145*(1-'DCF Base'!$I$144/'DCF Base'!$I$146)/((1+$B8+D$7)*IF(RateConv=1,1,1+IPCALT)-1-'DCF Base'!$I$144)/'DCF Base'!$H$23*(1+$B8+D$7)^(-5)) -> 424204.41 | E8: =IF(Horizon=1,(SUMPRODUCT('DCF Base'!$D$73:$H$73,(1+$B8+E$7)^(-'DCF Base'!$D$19:$H$19))+'DCF Base'!$I$58*(1-'DCF Base'!$I$57/'DCF Base'!$I$59)/((1+$B8+E$7)*IF(RateConv=1,1,1+IPCALT)-1-'DCF Base'!$I$57)/'DCF Base'!$H$23*(1+$B8+E$7)^(-5))*IF(RateConv=1,(1+$B8+E$7),(1+$B8+E$7)*(1+IPCA1))-'DCF Base'!$D$62,SUMPRODUCT('DCF Base'!$D$73:$H$73,(1+$B8+E$7)^(-'DCF Base'!$D$19:$H$19))+'DCF Base'!$I$58*(1-'DCF Base'!$I$57/'DCF Base'!$I$59)/((1+$B8+E$7)*IF(RateConv=1,1,1+IPCALT)-1-'DCF Base'!$I$57)/'DCF Base'!$H$23*(1+$B8+E$7)^(-5))+IF(Horizon=1,(SUMPRODUCT('DCF Base'!$D$102:$H$102,(1+$B8+E$7)^(-'DCF Base'!$D$19:$H$19))+'DCF Base'!$I$87*(1-'DCF Base'!$I$86/'DCF Base'!$I$88)/((1+$B8+E$7)*IF(RateConv=1,1,1+IPCALT)-1-'DCF Base'!$I$86)/'DCF Base'!$H$23*(1+$B8+E$7)^(-5))*IF(RateConv=1,(1+$B8+E$7),(1+$B8+E$7)*(1+IPCA1))-'DCF Base'!$D$91,SUMPRODUCT('DCF Base'!$D$102:$H$102,(1+$B8+E$7)^(-'DCF Base'!$D$19:$H$19))+'DCF Base'!$I$87*(1-'DCF Base'!$I$86/'DCF Base'!$I$88)/((1+$B8+E$7)*IF(RateConv=1,1,1+IPCALT)-1-'DCF Base'!$I$86)/'DCF Base'!$H$23*(1+$B8+E$7)^(-5))+IF(Horizon=1,(SUMPRODUCT('DCF Base'!$D$131:$H$131,(1+$B8+E$7)^(-'DCF Base'!$D$19:$H$19))+'DCF Base'!$I$116*(1-'DCF Base'!$I$115/'DCF Base'!$I$117)/((1+$B8+E$7)*IF(RateConv=1,1,1+IPCALT)-1-'DCF Base'!$I$115)/'DCF Base'!$H$23*(1+$B8+E$7)^(-5))*IF(RateConv=1,(1+$B8+E$7),(1+$B8+E$7)*(1+IPCA1))-'DCF Base'!$D$120,SUMPRODUCT('DCF Base'!$D$131:$H$131,(1+$B8+E$7)^(-'DCF Base'!$D$19:$H$19))+'DCF Base'!$I$116*(1-'DCF Base'!$I$115/'DCF Base'!$I$117)/((1+$B8+E$7)*IF(RateConv=1,1,1+IPCALT)-1-'DCF Base'!$I$115)/'DCF Base'!$H$23*(1+$B8+E$7)^(-5))+IF(Horizon=1,(SUMPRODUCT('DCF Base'!$D$160:$H$160,(1+$B8+E$7)^(-'DCF Base'!$D$19:$H$19))+'DCF Base'!$I$145*(1-'DCF Base'!$I$144/'DCF Base'!$I$146)/((1+$B8+E$7)*IF(RateConv=1,1,1+IPCALT)-1-'DCF Base'!$I$144)/'DCF Base'!$H$23*(1+$B8+E$7)^(-5))*IF(RateConv=1,(1+$B8+E$7),(1+$B8+E$7)*(1+IPCA1))-'DCF Base'!$D$149,SUMPRODUCT('DCF Base'!$D$160:$H$160,(1+$B8+E$7)^(-'DCF Base'!$D$19:$H$19))+'DCF Base'!$I$145*(1-'DCF Base'!$I$144/'DCF Base'!$I$146)/((1+$B8+E$7)*IF(RateConv=1,1,1+IPCALT)-1-'DCF Base'!$I$144)/'DCF Base'!$H$23*(1+$B8+E$7)^(-5)) -> 379413.74 | F8: =IF(Horizon=1,(SUMPRODUCT('DCF Base'!$D$73:$H$73,(1+$B8+F$7)^(-'DCF Base'!$D$19:$H$19))+'DCF Base'!$I$58*(1-'DCF Base'!$I$57/'DCF Base'!$I$59)/((1+$B8+F$7)*IF(RateConv=1,1,1+IPCALT)-1-'DCF Base'!$I$57)/'DCF Base'!$H$23*(1+$B8+F$7)^(-5))*IF(RateConv=1,(1+$B8+F$7),(1+$B8+F$7)*(1+IPCA1))-'DCF Base'!$D$62,SUMPRODUCT('DCF Base'!$D$73:$H$73,(1+$B8+F$7)^(-'DCF Base'!$D$19:$H$19))+'DCF Base'!$I$58*(1-'DCF Base'!$I$57/'DCF Base'!$I$59)/((1+$B8+F$7)*IF(RateConv=1,1,1+IPCALT)-1-'DCF Base'!$I$57)/'DCF Base'!$H$23*(1+$B8+F$7)^(-5))+IF(Horizon=1,(SUMPRODUCT('DCF Base'!$D$102:$H$102,(1+$B8+F$7)^(-'DCF Base'!$D$19:$H$19))+'DCF Base'!$I$87*(1-'DCF Base'!$I$86/'DCF Base'!$I$88)/((1+$B8+F$7)*IF(RateConv=1,1,1+IPCALT)-1-'DCF Base'!$I$86)/'DCF Base'!$H$23*(1+$B8+F$7)^(-5))*IF(RateConv=1,(1+$B8+F$7),(1+$B8+F$7)*(1+IPCA1))-'DCF Base'!$D$91,SUMPRODUCT('DCF Base'!$D$102:$H$102,(1+$B8+F$7)^(-'DCF Base'!$D$19:$H$19))+'DCF Base'!$I$87*(1-'DCF Base'!$I$86/'DCF Base'!$I$88)/((1+$B8+F$7)*IF(RateConv=1,1,1+IPCALT)-1-'DCF Base'!$I$86)/'DCF Base'!$H$23*(1+$B8+F$7)^(-5))+IF(Horizon=1,(SUMPRODUCT('DCF Base'!$D$131:$H$131,(1+$B8+F$7)^(-'DCF Base'!$D$19:$H$19))+'DCF Base'!$I$116*(1-'DCF Base'!$I$115/'DCF Base'!$I$117)/((1+$B8+F$7)*IF(RateConv=1,1,1+IPCALT)-1-'DCF Base'!$I$115)/'DCF Base'!$H$23*(1+$B8+F$7)^(-5))*IF(RateConv=1,(1+$B8+F$7),(1+$B8+F$7)*(1+IPCA1))-'DCF Base'!$D$120,SUMPRODUCT('DCF Base'!$D$131:$H$131,(1+$B8+F$7)^(-'DCF Base'!$D$19:$H$19))+'DCF Base'!$I$116*(1-'DCF Base'!$I$115/'DCF Base'!$I$117)/((1+$B8+F$7)*IF(RateConv=1,1,1+IPCALT)-1-'DCF Base'!$I$115)/'DCF Base'!$H$23*(1+$B8+F$7)^(-5))+IF(Horizon=1,(SUMPRODUCT('DCF Base'!$D$160:$H$160,(1+$B8+F$7)^(-'DCF Base'!$D$19:$H$19))+'DCF Base'!$I$145*(1-'DCF Base'!$I$144/'DCF Base'!$I$146)/((1+$B8+F$7)*IF(RateConv=1,1,1+IPCALT)-1-'DCF Base'!$I$144)/'DCF Base'!$H$23*(1+$B8+F$7)^(-5))*IF(RateConv=1,(1+$B8+F$7),(1+$B8+F$7)*(1+IPCA1))-'DCF Base'!$D$149,SUMPRODUCT('DCF Base'!$D$160:$H$160,(1+$B8+F$7)^(-'DCF Base'!$D$19:$H$19))+'DCF Base'!$I$145*(1-'DCF Base'!$I$144/'DCF Base'!$I$146)/((1+$B8+F$7)*IF(RateConv=1,1,1+IPCALT)-1-'DCF Base'!$I$144)/'DCF Base'!$H$23*(1+$B8+F$7)^(-5)) -> 343080.85 | G8: =IF(Horizon=1,(SUMPRODUCT('DCF Base'!$D$73:$H$73,(1+$B8+G$7)^(-'DCF Base'!$D$19:$H$19))+'DCF Base'!$I$58*(1-'DCF Base'!$I$57/'DCF Base'!$I$59)/((1+$B8+G$7)*IF(RateConv=1,1,1+IPCALT)-1-'DCF Base'!$I$57)/'DCF Base'!$H$23*(1+$B8+G$7)^(-5))*IF(RateConv=1,(1+$B8+G$7),(1+$B8+G$7)*(1+IPCA1))-'DCF Base'!$D$62,SUMPRODUCT('DCF Base'!$D$73:$H$73,(1+$B8+G$7)^(-'DCF Base'!$D$19:$H$19))+'DCF Base'!$I$58*(1-'DCF Base'!$I$57/'DCF Base'!$I$59)/((1+$B8+G$7)*IF(RateConv=1,1,1+IPCALT)-1-'DCF Base'!$I$57)/'DCF Base'!$H$23*(1+$B8+G$7)^(-5))+IF(Horizon=1,(SUMPRODUCT('DCF Base'!$D$102:$H$102,(1+$B8+G$7)^(-'DCF Base'!$D$19:$H$19))+'DCF Base'!$I$87*(1-'DCF Base'!$I$86/'DCF Base'!$I$88)/((1+$B8+G$7)*IF(RateConv=1,1,1+IPCALT)-1-'DCF Base'!$I$86)/'DCF Base'!$H$23*(1+$B8+G$7)^(-5))*IF(RateConv=1,(1+$B8+G$7),(1+$B8+G$7)*(1+IPCA1))-'DCF Base'!$D$91,SUMPRODUCT('DCF Base'!$D$102:$H$102,(1+$B8+G$7)^(-'DCF Base'!$D$19:$H$19))+'DCF Base'!$I$87*(1-'DCF Base'!$I$86/'DCF Base'!$I$88)/((1+$B8+G$7)*IF(RateConv=1,1,1+IPCALT)-1-'DCF Base'!$I$86)/'DCF Base'!$H$23*(1+$B8+G$7)^(-5))+IF(Horizon=1,(SUMPRODUCT('DCF Base'!$D$131:$H$131,(1+$B8+G$7)^(-'DCF Base'!$D$19:$H$19))+'DCF Base'!$I$116*(1-'DCF Base'!$I$115/'DCF Base'!$I$117)/((1+$B8+G$7)*IF(RateConv=1,1,1+IPCALT)-1-'DCF Base'!$I$115)/'DCF Base'!$H$23*(1+$B8+G$7)^(-5))*IF(RateConv=1,(1+$B8+G$7),(1+$B8+G$7)*(1+IPCA1))-'DCF Base'!$D$120,SUMPRODUCT('DCF Base'!$D$131:$H$131,(1+$B8+G$7)^(-'DCF Base'!$D$19:$H$19))+'DCF Base'!$I$116*(1-'DCF Base'!$I$115/'DCF Base'!$I$117)/((1+$B8+G$7)*IF(RateConv=1,1,1+IPCALT)-1-'DCF Base'!$I$115)/'DCF Base'!$H$23*(1+$B8+G$7)^(-5))+IF(Horizon=1,(SUMPRODUCT('DCF Base'!$D$160:$H$160,(1+$B8+G$7)^(-'DCF Base'!$D$19:$H$19))+'DCF Base'!$I$145*(1-'DCF Base'!$I$144/'DCF Base'!$I$146)/((1+$B8+G$7)*IF(RateConv=1,1,1+IPCALT)-1-'DCF Base'!$I$144)/'DCF Base'!$H$23*(1+$B8+G$7)^(-5))*IF(RateConv=1,(1+$B8+G$7),(1+$B8+G$7)*(1+IPCA1))-'DCF Base'!$D$149,SUMPRODUCT('DCF Base'!$D$160:$H$160,(1+$B8+G$7)^(-'DCF Base'!$D$19:$H$19))+'DCF Base'!$I$145*(1-'DCF Base'!$I$144/'DCF Base'!$I$146)/((1+$B8+G$7)*IF(RateConv=1,1,1+IPCALT)-1-'DCF Base'!$I$144)/'DCF Base'!$H$23*(1+$B8+G$7)^(-5)) -> 313018.29 | H8: =IF(Horizon=1,(SUMPRODUCT('DCF Base'!$D$73:$H$73,(1+$B8+H$7)^(-'DCF Base'!$D$19:$H$19))+'DCF Base'!$I$58*(1-'DCF Base'!$I$57/'DCF Base'!$I$59)/((1+$B8+H$7)*IF(RateConv=1,1,1+IPCALT)-1-'DCF Base'!$I$57)/'DCF Base'!$H$23*(1+$B8+H$7)^(-5))*IF(RateConv=1,(1+$B8+H$7),(1+$B8+H$7)*(1+IPCA1))-'DCF Base'!$D$62,SUMPRODUCT('DCF Base'!$D$73:$H$73,(1+$B8+H$7)^(-'DCF Base'!$D$19:$H$19))+'DCF Base'!$I$58*(1-'DCF Base'!$I$57/'DCF Base'!$I$59)/((1+$B8+H$7)*IF(RateConv=1,1,1+IPCALT)-1-'DCF Base'!$I$57)/'DCF Base'!$H$23*(1+$B8+H$7)^(-5))+IF(Horizon=1,(SUMPRODUCT('DCF Base'!$D$102:$H$102,(1+$B8+H$7)^(-'DCF Base'!$D$19:$H$19))+'DCF Base'!$I$87*(1-'DCF Base'!$I$86/'DCF Base'!$I$88)/((1+$B8+H$7)*IF(RateConv=1,1,1+IPCALT)-1-'DCF Base'!$I$86)/'DCF Base'!$H$23*(1+$B8+H$7)^(-5))*IF(RateConv=1,(1+$B8+H$7),(1+$B8+H$7)*(1+IPCA1))-'DCF Base'!$D$91,SUMPRODUCT('DCF Base'!$D$102:$H$102,(1+$B8+H$7)^(-'DCF Base'!$D$19:$H$19))+'DCF Base'!$I$87*(1-'DCF Base'!$I$86/'DCF Base'!$I$88)/((1+$B8+H$7)*IF(RateConv=1,1,1+IPCALT)-1-'DCF Base'!$I$86)/'DCF Base'!$H$23*(1+$B8+H$7)^(-5))+IF(Horizon=1,(SUMPRODUCT('DCF Base'!$D$131:$H$131,(1+$B8+H$7)^(-'DCF Base'!$D$19:$H$19))+'DCF Base'!$I$116*(1-'DCF Base'!$I$115/'DCF Base'!$I$117)/((1+$B8+H$7)*IF(RateConv=1,1,1+IPCALT)-1-'DCF Base'!$I$115)/'DCF Base'!$H$23*(1+$B8+H$7)^(-5))*IF(RateConv=1,(1+$B8+H$7),(1+$B8+H$7)*(1+IPCA1))-'DCF Base'!$D$120,SUMPRODUCT('DCF Base'!$D$131:$H$131,(1+$B8+H$7)^(-'DCF Base'!$D$19:$H$19))+'DCF Base'!$I$116*(1-'DCF Base'!$I$115/'DCF Base'!$I$117)/((1+$B8+H$7)*IF(RateConv=1,1,1+IPCALT)-1-'DCF Base'!$I$115)/'DCF Base'!$H$23*(1+$B8+H$7)^(-5))+IF(Horizon=1,(SUMPRODUCT('DCF Base'!$D$160:$H$160,(1+$B8+H$7)^(-'DCF Base'!$D$19:$H$19))+'DCF Base'!$I$145*(1-'DCF Base'!$I$144/'DCF Base'!$I$146)/((1+$B8+H$7)*IF(RateConv=1,1,1+IPCALT)-1-'DCF Base'!$I$144)/'DCF Base'!$H$23*(1+$B8+H$7)^(-5))*IF(RateConv=1,(1+$B8+H$7),(1+$B8+H$7)*(1+IPCA1))-'DCF Base'!$D$149,SUMPRODUCT('DCF Base'!$D$160:$H$160,(1+$B8+H$7)^(-'DCF Base'!$D$19:$H$19))+'DCF Base'!$I$145*(1-'DCF Base'!$I$144/'DCF Base'!$I$146)/((1+$B8+H$7)*IF(RateConv=1,1,1+IPCALT)-1-'DCF Base'!$I$144)/'DCF Base'!$H$23*(1+$B8+H$7)^(-5)) -> 287733.03 | I8: =IF(Horizon=1,(SUMPRODUCT('DCF Base'!$D$73:$H$73,(1+$B8+I$7)^(-'DCF Base'!$D$19:$H$19))+'DCF Base'!$I$58*(1-'DCF Base'!$I$57/'DCF Base'!$I$59)/((1+$B8+I$7)*IF(RateConv=1,1,1+IPCALT)-1-'DCF Base'!$I$57)/'DCF Base'!$H$23*(1+$B8+I$7)^(-5))*IF(RateConv=1,(1+$B8+I$7),(1+$B8+I$7)*(1+IPCA1))-'DCF Base'!$D$62,SUMPRODUCT('DCF Base'!$D$73:$H$73,(1+$B8+I$7)^(-'DCF Base'!$D$19:$H$19))+'DCF Base'!$I$58*(1-'DCF Base'!$I$57/'DCF Base'!$I$59)/((1+$B8+I$7)*IF(RateConv=1,1,1+IPCALT)-1-'DCF Base'!$I$57)/'DCF Base'!$H$23*(1+$B8+I$7)^(-5))+IF(Horizon=1,(SUMPRODUCT('DCF Base'!$D$102:$H$102,(1+$B8+I$7)^(-'DCF Base'!$D$19:$H$19))+'DCF Base'!$I$87*(1-'DCF Base'!$I$86/'DCF Base'!$I$88)/((1+$B8+I$7)*IF(RateConv=1,1,1+IPCALT)-1-'DCF Base'!$I$86)/'DCF Base'!$H$23*(1+$B8+I$7)^(-5))*IF(RateConv=1,(1+$B8+I$7),(1+$B8+I$7)*(1+IPCA1))-'DCF Base'!$D$91,SUMPRODUCT('DCF Base'!$D$102:$H$102,(1+$B8+I$7)^(-'DCF Base'!$D$19:$H$19))+'DCF Base'!$I$87*(1-'DCF Base'!$I$86/'DCF Base'!$I$88)/((1+$B8+I$7)*IF(RateConv=1,1,1+IPCALT)-1-'DCF Base'!$I$86)/'DCF Base'!$H$23*(1+$B8+I$7)^(-5))+IF(Horizon=1,(SUMPRODUCT('DCF Base'!$D$131:$H$131,(1+$B8+I$7)^(-'DCF Base'!$D$19:$H$19))+'DCF Base'!$I$116*(1-'DCF Base'!$I$115/'DCF Base'!$I$117)/((1+$B8+I$7)*IF(RateConv=1,1,1+IPCALT)-1-'DCF Base'!$I$115)/'DCF Base'!$H$23*(1+$B8+I$7)^(-5))*IF(RateConv=1,(1+$B8+I$7),(1+$B8+I$7)*(1+IPCA1))-'DCF Base'!$D$120,SUMPRODUCT('DCF Base'!$D$131:$H$131,(1+$B8+I$7)^(-'DCF Base'!$D$19:$H$19))+'DCF Base'!$I$116*(1-'DCF Base'!$I$115/'DCF Base'!$I$117)/((1+$B8+I$7)*IF(RateConv=1,1,1+IPCALT)-1-'DCF Base'!$I$115)/'DCF Base'!$H$23*(1+$B8+I$7)^(-5))+IF(Horizon=1,(SUMPRODUCT('DCF Base'!$D$160:$H$160,(1+$B8+I$7)^(-'DCF Base'!$D$19:$H$19))+'DCF Base'!$I$145*(1-'DCF Base'!$I$144/'DCF Base'!$I$146)/((1+$B8+I$7)*IF(RateConv=1,1,1+IPCALT)-1-'DCF Base'!$I$144)/'DCF Base'!$H$23*(1+$B8+I$7)^(-5))*IF(RateConv=1,(1+$B8+I$7),(1+$B8+I$7)*(1+IPCA1))-'DCF Base'!$D$149,SUMPRODUCT('DCF Base'!$D$160:$H$160,(1+$B8+I$7)^(-'DCF Base'!$D$19:$H$19))+'DCF Base'!$I$145*(1-'DCF Base'!$I$144/'DCF Base'!$I$146)/((1+$B8+I$7)*IF(RateConv=1,1,1+IPCALT)-1-'DCF Base'!$I$144)/'DCF Base'!$H$23*(1+$B8+I$7)^(-5)) -> 266171.17 | J8: =IF(Horizon=1,(SUMPRODUCT('DCF Base'!$D$73:$H$73,(1+$B8+J$7)^(-'DCF Base'!$D$19:$H$19))+'DCF Base'!$I$58*(1-'DCF Base'!$I$57/'DCF Base'!$I$59)/((1+$B8+J$7)*IF(RateConv=1,1,1+IPCALT)-1-'DCF Base'!$I$57)/'DCF Base'!$H$23*(1+$B8+J$7)^(-5))*IF(RateConv=1,(1+$B8+J$7),(1+$B8+J$7)*(1+IPCA1))-'DCF Base'!$D$62,SUMPRODUCT('DCF Base'!$D$73:$H$73,(1+$B8+J$7)^(-'DCF Base'!$D$19:$H$19))+'DCF Base'!$I$58*(1-'DCF Base'!$I$57/'DCF Base'!$I$59)/((1+$B8+J$7)*IF(RateConv=1,1,1+IPCALT)-1-'DCF Base'!$I$57)/'DCF Base'!$H$23*(1+$B8+J$7)^(-5))+IF(Horizon=1,(SUMPRODUCT('DCF Base'!$D$102:$H$102,(1+$B8+J$7)^(-'DCF Base'!$D$19:$H$19))+'DCF Base'!$I$87*(1-'DCF Base'!$I$86/'DCF Base'!$I$88)/((1+$B8+J$7)*IF(RateConv=1,1,1+IPCALT)-1-'DCF Base'!$I$86)/'DCF Base'!$H$23*(1+$B8+J$7)^(-5))*IF(RateConv=1,(1+$B8+J$7),(1+$B8+J$7)*(1+IPCA1))-'DCF Base'!$D$91,SUMPRODUCT('DCF Base'!$D$102:$H$102,(1+$B8+J$7)^(-'DCF Base'!$D$19:$H$19))+'DCF Base'!$I$87*(1-'DCF Base'!$I$86/'DCF Base'!$I$88)/((1+$B8+J$7)*IF(RateConv=1,1,1+IPCALT)-1-'DCF Base'!$I$86)/'DCF Base'!$H$23*(1+$B8+J$7)^(-5))+IF(Horizon=1,(SUMPRODUCT('DCF Base'!$D$131:$H$131,(1+$B8+J$7)^(-'DCF Base'!$D$19:$H$19))+'DCF Base'!$I$116*(1-'DCF Base'!$I$115/'DCF Base'!$I$117)/((1+$B8+J$7)*IF(RateConv=1,1,1+IPCALT)-1-'DCF Base'!$I$115)/'DCF Base'!$H$23*(1+$B8+J$7)^(-5))*IF(RateConv=1,(1+$B8+J$7),(1+$B8+J$7)*(1+IPCA1))-'DCF Base'!$D$120,SUMPRODUCT('DCF Base'!$D$131:$H$131,(1+$B8+J$7)^(-'DCF Base'!$D$19:$H$19))+'DCF Base'!$I$116*(1-'DCF Base'!$I$115/'DCF Base'!$I$117)/((1+$B8+J$7)*IF(RateConv=1,1,1+IPCALT)-1-'DCF Base'!$I$115)/'DCF Base'!$H$23*(1+$B8+J$7)^(-5))+IF(Horizon=1,(SUMPRODUCT('DCF Base'!$D$160:$H$160,(1+$B8+J$7)^(-'DCF Base'!$D$19:$H$19))+'DCF Base'!$I$145*(1-'DCF Base'!$I$144/'DCF Base'!$I$146)/((1+$B8+J$7)*IF(RateConv=1,1,1+IPCALT)-1-'DCF Base'!$I$144)/'DCF Base'!$H$23*(1+$B8+J$7)^(-5))*IF(RateConv=1,(1+$B8+J$7),(1+$B8+J$7)*(1+IPCA1))-'DCF Base'!$D$149,SUMPRODUCT('DCF Base'!$D$160:$H$160,(1+$B8+J$7)^(-'DCF Base'!$D$19:$H$19))+'DCF Base'!$I$145*(1-'DCF Base'!$I$144/'DCF Base'!$I$146)/((1+$B8+J$7)*IF(RateConv=1,1,1+IPCALT)-1-'DCF Base'!$I$144)/'DCF Base'!$H$23*(1+$B8+J$7)^(-5)) -> 247567.54 | ... M8: =IF(Horizon=1,(SUMPRODUCT('DCF Base'!$D$73:$H$73,(1+$B8+M$7)^(-'DCF Base'!$D$19:$H$19))+'DCF Base'!$I$58*(1-'DCF Base'!$I$57/'DCF Base'!$I$59)/((1+$B8+M$7)*IF(RateConv=1,1,1+IPCALT)-1-'DCF Base'!$I$57)/'DCF Base'!$H$23*(1+$B8+M$7)^(-5))*IF(RateConv=1,(1+$B8+M$7),(1+$B8+M$7)*(1+IPCA1))-'DCF Base'!$D$62,SUMPRODUCT('DCF Base'!$D$73:$H$73,(1+$B8+M$7)^(-'DCF Base'!$D$19:$H$19))+'DCF Base'!$I$58*(1-'DCF Base'!$I$57/'DCF Base'!$I$59)/((1+$B8+M$7)*IF(RateConv=1,1,1+IPCALT)-1-'DCF Base'!$I$57)/'DCF Base'!$H$23*(1+$B8+M$7)^(-5))+IF(Horizon=1,(SUMPRODUCT('DCF Base'!$D$102:$H$102,(1+$B8+M$7)^(-'DCF Base'!$D$19:$H$19))+'DCF Base'!$I$87*(1-'DCF Base'!$I$86/'DCF Base'!$I$88)/((1+$B8+M$7)*IF(RateConv=1,1,1+IPCALT)-1-'DCF Base'!$I$86)/'DCF Base'!$H$23*(1+$B8+M$7)^(-5))*IF(RateConv=1,(1+$B8+M$7),(1+$B8+M$7)*(1+IPCA1))-'DCF Base'!$D$91,SUMPRODUCT('DCF Base'!$D$102:$H$102,(1+$B8+M$7)^(-'DCF Base'!$D$19:$H$19))+'DCF Base'!$I$87*(1-'DCF Base'!$I$86/'DCF Base'!$I$88)/((1+$B8+M$7)*IF(RateConv=1,1,1+IPCALT)-1-'DCF Base'!$I$86)/'DCF Base'!$H$23*(1+$B8+M$7)^(-5))+IF(Horizon=1,(SUMPRODUCT('DCF Base'!$D$131:$H$131,(1+$B8+M$7)^(-'DCF Base'!$D$19:$H$19))+'DCF Base'!$I$116*(1-'DCF Base'!$I$115/'DCF Base'!$I$117)/((1+$B8+M$7)*IF(RateConv=1,1,1+IPCALT)-1-'DCF Base'!$I$115)/'DCF Base'!$H$23*(1+$B8+M$7)^(-5))*IF(RateConv=1,(1+$B8+M$7),(1+$B8+M$7)*(1+IPCA1))-'DCF Base'!$D$120,SUMPRODUCT('DCF Base'!$D$131:$H$131,(1+$B8+M$7)^(-'DCF Base'!$D$19:$H$19))+'DCF Base'!$I$116*(1-'DCF Base'!$I$115/'DCF Base'!$I$117)/((1+$B8+M$7)*IF(RateConv=1,1,1+IPCALT)-1-'DCF Base'!$I$115)/'DCF Base'!$H$23*(1+$B8+M$7)^(-5))+IF(Horizon=1,(SUMPRODUCT('DCF Base'!$D$160:$H$160,(1+$B8+M$7)^(-'DCF Base'!$D$19:$H$19))+'DCF Base'!$I$145*(1-'DCF Base'!$I$144/'DCF Base'!$I$146)/((1+$B8+M$7)*IF(RateConv=1,1,1+IPCALT)-1-'DCF Base'!$I$144)/'DCF Base'!$H$23*(1+$B8+M$7)^(-5))*IF(RateConv=1,(1+$B8+M$7),(1+$B8+M$7)*(1+IPCA1))-'DCF Base'!$D$149,SUMPRODUCT('DCF Base'!$D$160:$H$160,(1+$B8+M$7)^(-'DCF Base'!$D$19:$H$19))+'DCF Base'!$I$145*(1-'DCF Base'!$I$144/'DCF Base'!$I$146)/((1+$B8+M$7)*IF(RateConv=1,1,1+IPCALT)-1-'DCF Base'!$I$144)/'DCF Base'!$H$23*(1+$B8+M$7)^(-5)) -> 204463
