Workbook
Name BetaAdj: Assumptions!$C$45
Name BetaYears: Assumptions!$C$44
Name BoxCF: Assumptions!$C$46
Name BoxGrowth: Assumptions!$C$47
Name BoxRate: Assumptions!$C$42
Name EBNorm: Assumptions!$C$65
Name EBStart: Assumptions!$C$68
Name ERPfloor: Assumptions!$C$43
Name FadeMode: Assumptions!$C$67
Name FadeYears: Assumptions!$C$48
Name FinROE: 'Box Shares'!$C$39
Name FinROEovr: Assumptions!$C$40
Name FixInfl: Assumptions!$C$29
Name FixND: Assumptions!$C$27
Name FixNWC: Assumptions!$C$26
Name FixTV: Assumptions!$C$28
Name FV27Base: DCF!$D$57
Name FV27Bear: DCF!$C$57
Name FV27Bull: DCF!$E$57
Name gLT: Assumptions!$C$13
Name GrowthCap: Assumptions!$C$49
Name IbovUsed: Assumptions!$E$7
Name InflLT: Assumptions!$C$14
Name NDmult: Assumptions!$C$16
Name NWCpct: Assumptions!$C$15
Name RateShock: Assumptions!$C$64
Name RelMult: Assumptions!$C$56
Name RRUsed: Assumptions!$E$8
Name ScaleBox: Assumptions!$C$39
Name ScaleScen: Assumptions!$C$66
Name Vintage: Assumptions!$C$9
Name WBU: Assumptions!$F$57
Name WDCF: Assumptions!$C$57
Name WEV: Assumptions!$E$57
Name WPE: Assumptions!$D$57

Sheet Cover
C3: Ibovespa | target by box (house model), end-2027
C4: VALUATION MODEL · EQUITY STRATEGY
C7: Main tabs >>
C8: Summary | E8: Assumptions | G8: DCF by Box | I8: Multiples by Box | K8: Ibovespa used | M8: =IbovUsed -> 208431.92
K9: Target end-2027, base (average) | M9: =Summary!E11 -> 222319.31
K10: Upside, base | M10: =Summary!I11 -> 0.066627924
C11: Auxiliary tabs >> | K11: Target end-2027, bear | M11: =Summary!D11 -> 164452.23
C12: DCF (Ibovespa) | E12: Sensitivity | G12: Box Rates | I12: Box Betas | K12: Target end-2027, bull | M12: =Summary!F11 -> 276518.12
K13: Model checks | M13: =Checks!C5 -> All checks OK
C15: Box Earnings | E15: Box Fade | G15: Box Shares | I15: Members (76 stocks) | K15: How this model works >>
K16: Equity Strategy | XP Research
C18: Checks
C21: Target by box, base (average of the methods) >>
C22: Box | F22: Index points | G22: Target | H22: Upside
C23: Financials | F23: =Summary!C7 -> 60927.304 | G23: =Summary!E7 -> 56485.165 | H23: =Summary!I7 -> -0.072908827
C24: Defensives | F24: =Summary!C8 -> 55822.367 | G24: =Summary!E8 -> 58266.156 | H24: =Summary!I8 -> 0.043777943
C25: Cyclicals | F25: =Summary!C9 -> 26271.075 | G25: =Summary!E9 -> 31594.945 | H25: =Summary!I9 -> 0.20265141
C26: Commodities | F26: =Summary!C10 -> 65411.174 | G26: =Summary!E10 -> 75973.04 | H26: =Summary!I10 -> 0.16146883
C27: Ibovespa | F27: =Summary!C11 -> 208431.92 | G27: =Summary!E11 -> 222319.31 | H27: =Summary!I11 -> 0.066627924
C29: House target methods rolled to end-2027 and split by box: DCF (CAPM), P/E, EV/EBITDA and bottom-up, and their average.

Sheet Summary
B1: Ibovespa - Target by box at the end of 2027 (house model)
B2: House Target methods rolled to end-2027 and split by box: DCF (CAPM), P/E, EV/EBITDA, bottom-up, and their average. Construction: Multiples by Box, DCF by Box.
B3: Ibovespa used | C3: =IbovUsed -> 208431.92 | D3: Market data | E3: =CHOOSE(Vintage,"house file","Oct-5-2026") -> Oct-5-2026 | F3: Checks | G3: =Checks!C5 -> All checks OK | H3: Boxes scaled | I3: =IF(ScaleBox=1,"yes","no") -> no
B4: DCF box settings | C4: =CHOOSE(BoxRate+1,"house rate","rate relative to history","CAPM rates")&IF(BoxCF=1,", capex funding growth and NWC by change","")&IF(BoxGrowth=1,", consensus growth fading after 2031","")&CHOOSE(FadeMode+1," (H-model)"," (year by year)"," (year by year, growth paid)")&IF(RateShock=1,"; scenario rate shock x beta","")&IF(ScaleScen=1,"; earnings shocks open the bear / bull","")&IF(RelMult=1,"; multiples relative to history","") -> CAPM rates, capex funding growth and NWC by change (H-model); earnings shocks open the bear / bull; multiples relative to history
B5: 1. Target at the end of 2027 by box: average of the methods (index pts)
B6: Group | C6: Index points | D6: Bear | E6: Base | F6: Bull | H6: Upside: Bear | I6: Base | J6: Bull
B7: Financials | C7: ='Box Shares'!C7 -> 60927.304 | D7: ='Multiples by Box'!C57 -> 42178.948 | E7: ='Multiples by Box'!D57 -> 56485.165 | F7: ='Multiples by Box'!E57 -> 70248.12 | H7: =D7/$C7-1 -> -0.30771681 | I7: =E7/$C7-1 -> -0.072908827 | J7: =F7/$C7-1 -> 0.15298259
B8: Defensives | C8: ='Box Shares'!C8 -> 55822.367 | D8: ='Multiples by Box'!C58 -> 44488.458 | E8: ='Multiples by Box'!D58 -> 58266.156 | F8: ='Multiples by Box'!E58 -> 70165.63 | H8: =D8/$C8-1 -> -0.20303528 | I8: =E8/$C8-1 -> 0.043777943 | J8: =F8/$C8-1 -> 0.25694471
B9: Cyclicals | C9: ='Box Shares'!C9 -> 26271.075 | D9: ='Multiples by Box'!C59 -> 23520.141 | E9: ='Multiples by Box'!D59 -> 31594.945 | F9: ='Multiples by Box'!E59 -> 38674.578 | H9: =D9/$C9-1 -> -0.10471341 | I9: =E9/$C9-1 -> 0.20265141 | J9: =F9/$C9-1 -> 0.47213538
B10: Commodities | C10: ='Box Shares'!C10 -> 65411.174 | D10: ='Multiples by Box'!C60 -> 54264.684 | E10: ='Multiples by Box'!D60 -> 75973.04 | F10: ='Multiples by Box'!E60 -> 97429.794 | H10: =D10/$C10-1 -> -0.17040651 | I10: =E10/$C10-1 -> 0.16146883 | J10: =F10/$C10-1 -> 0.48949769
B11: Ibovespa | C11: =SUM(C7:C10) -> 208431.92 | D11: =SUM(D7:D10) -> 164452.23 | E11: =SUM(E7:E10) -> 222319.31 | F11: =SUM(F7:F10) -> 276518.12 | H11: =D11/$C11-1 -> -0.21100266 | I11: =E11/$C11-1 -> 0.066627924 | J11: =F11/$C11-1 -> 0.32665919
B12: Memo (inside Cyclicals; not additive)
B13: Cyclicals ex-WEG & Embraer | C13: ='Box Shares'!C14 -> 16066.52 | D13: ='Multiples by Box'!C63 -> 16435.648 | E13: ='Multiples by Box'!D63 -> 22098.909 | F13: ='Multiples by Box'!E63 -> 26950.299 | H13: =D13/$C13-1 -> 0.022975024 | I13: =E13/$C13-1 -> 0.37546338 | J13: =F13/$C13-1 -> 0.67741988
B14: WEG & Embraer | C14: ='Box Shares'!C15 -> 10204.555 | D14: ='Multiples by Box'!C64 -> 7941.7118 | E14: ='Multiples by Box'!D64 -> 10167.611 | F14: ='Multiples by Box'!E64 -> 12000.448 | H14: =D14/$C14-1 -> -0.22174836 | I14: =E14/$C14-1 -> -0.0036203445 | J14: =F14/$C14-1 -> 0.17598931
B16: 2. Base case by method (upside vs. index points) and the multiples model
B17: Group | D17: DCF (CAPM) | E17: P/E | F17: EV/EBITDA | G17: Bottom-up | H17: Average of the methods | I17: Multiples model (Oct-6)
B18: Financials | D18: ='DCF by Box'!$D$63 -> -0.061509922 | E18: ='Multiples by Box'!$D$23/$C$7-1 -> -0.075806071 | F18: ='Multiples by Box'!$D$35/$C$7-1 -> -0.075806071 | G18: ='Multiples by Box'!$D$46/$C$7-1 -> -0.078513243 | H18: ='Multiples by Box'!$D$57/$C$7-1 -> -0.072908827 | I18: =$D$80/$C$7-1 -> -0.075462708
B19: Defensives | D19: ='DCF by Box'!$D$110 -> -0.13690961 | E19: ='Multiples by Box'!$D$24/$C$8-1 -> -0.027834485 | F19: ='Multiples by Box'!$D$36/$C$8-1 -> 0.21201325 | G19: ='Multiples by Box'!$D$47/$C$8-1 -> 0.12784261 | H19: ='Multiples by Box'!$D$58/$C$8-1 -> 0.043777943 | I19: =$E$80/$C$8-1 -> 0.070674259
B20: Cyclicals | D20: ='DCF by Box'!$D$157 -> -0.2217573 | E20: ='Multiples by Box'!$D$25/$C$9-1 -> 0.37727396 | F20: ='Multiples by Box'!$D$37/$C$9-1 -> 0.46218697 | G20: ='Multiples by Box'!$D$48/$C$9-1 -> 0.19290201 | H20: ='Multiples by Box'!$D$59/$C$9-1 -> 0.20265141 | I20: =$F$80/$C$9-1 -> 0.39651752
B21: Commodities | D21: ='DCF by Box'!$D$204 -> 0.49842633 | E21: ='Multiples by Box'!$D$26/$C$10-1 -> 0.068629466 | F21: ='Multiples by Box'!$D$38/$C$10-1 -> -0.044772022 | G21: ='Multiples by Box'!$D$49/$C$10-1 -> 0.12359153 | H21: ='Multiples by Box'!$D$60/$C$10-1 -> 0.16146883 | I21: =$G$80/$C$10-1 -> 0.16870547
B22: Ibovespa | D22: ='DCF by Box'!$D$11/$C$11-1 -> 0.073820729 | E22: ='Multiples by Box'!$D$27/$C$11-1 -> 0.039476103 | F22: ='Multiples by Box'!$D$39/$C$11-1 -> 0.078826602 | G22: ='Multiples by Box'!$D$50/$C$11-1 -> 0.074388259 | H22: ='Multiples by Box'!$D$61/$C$11-1 -> 0.066627924 | I22: =$H$80/$C$11-1 -> 0.099791
B23: Memo (inside Cyclicals)
B24: Cyclicals ex-WEG & Embraer | D24: ='DCF by Box'!$D$251 -> -0.094200435 | E24: ='Multiples by Box'!$D$29/$C$13-1 -> 0.57091995 | F24: ='Multiples by Box'!$D$41/$C$13-1 -> 0.78305043 | G24: ='Multiples by Box'!$D$52/$C$13-1 -> 0.24208357 | H24: ='Multiples by Box'!$D$63/$C$13-1 -> 0.37546338 | I24: =$I$80/$C$13-1 -> 0.62781467
B25: WEG & Embraer | D25: ='DCF by Box'!$D$298 -> -0.4307139 | E25: ='Multiples by Box'!$D$30/$C$14-1 -> 0.2765069 | F25: ='Multiples by Box'!$D$42/$C$14-1 -> 0.024257311 | G25: ='Multiples by Box'!$D$53/$C$14-1 -> 0.11546831 | H25: ='Multiples by Box'!$D$64/$C$14-1 -> -0.0036203445 | I25: =$J$80/$C$14-1 -> 0.25783362
B26: Average absolute gap to the multiples model, four boxes | D26: =AVERAGE(ABS(D18-I18),ABS(D19-I19),ABS(D20-I20),ABS(D21-I21)) -> 0.29238308 | E26: =AVERAGE(ABS(E18-I18),ABS(E19-I19),ABS(E20-I20),ABS(E21-I21)) -> 0.054542919 | F26: =AVERAGE(ABS(F18-I18),ABS(F19-I19),ABS(F20-I20),ABS(F21-I21)) -> 0.10520732 | G26: =AVERAGE(ABS(G18-I18),ABS(G19-I19),ABS(G20-I20),ABS(G21-I21)) -> 0.077237085 | H26: =AVERAGE(ABS(H18-I18),ABS(H19-I19),ABS(H20-I20),ABS(H21-I21)) -> 0.05763824
B28: 3. DCF by box (CAPM, box cash flows, Gordon after 2031 as the house; not scaled: the Ibovespa is the sum of the boxes)
B29: Group | C29: Index points | D29: Bear | E29: Base | F29: Bull | H29: Upside: Bear | I29: Base | J29: Bull
B30: Financials | C30: ='Box Shares'!C7 -> 60927.304 | D30: ='DCF by Box'!C62 -> 39337.863 | E30: ='DCF by Box'!D62 -> 57179.67 | F30: ='DCF by Box'!E62 -> 78479.292 | H30: =D30/$C30-1 -> -0.35434755 | I30: =E30/$C30-1 -> -0.061509922 | J30: =F30/$C30-1 -> 0.28808083
B31: Defensives | C31: ='Box Shares'!C8 -> 55822.367 | D31: ='DCF by Box'!C109 -> 32906.129 | E31: ='DCF by Box'!D109 -> 48179.749 | F31: ='DCF by Box'!E109 -> 67069.6 | H31: =D31/$C31-1 -> -0.41052071 | I31: =E31/$C31-1 -> -0.13690961 | J31: =F31/$C31-1 -> 0.20148255
B32: Cyclicals | C32: ='Box Shares'!C9 -> 26271.075 | D32: ='DCF by Box'!C156 -> 11003.825 | E32: ='DCF by Box'!D156 -> 20445.272 | F32: ='DCF by Box'!E156 -> 32356.929 | H32: =D32/$C32-1 -> -0.58114295 | I32: =E32/$C32-1 -> -0.2217573 | J32: =F32/$C32-1 -> 0.2316561
B33: Commodities | C33: ='Box Shares'!C10 -> 65411.174 | D33: ='DCF by Box'!C203 -> 58771.759 | E33: ='DCF by Box'!D203 -> 98013.826 | F33: ='DCF by Box'!E203 -> 149230.1 | H33: =D33/$C33-1 -> -0.10150277 | I33: =E33/$C33-1 -> 0.49842633 | J33: =F33/$C33-1 -> 1.281416
B34: Ibovespa | C34: =SUM(C30:C33) -> 208431.92 | D34: =SUM(D30:D33) -> 142019.58 | E34: =SUM(E30:E33) -> 223818.52 | F34: =SUM(F30:F33) -> 327135.92 | H34: =D34/$C34-1 -> -0.31862847 | I34: =E34/$C34-1 -> 0.073820729 | J34: =F34/$C34-1 -> 0.56950969
B35: Memo (inside Cyclicals; not additive)
B36: Cyclicals ex-WEG & Embraer | C36: ='Box Shares'!C14 -> 16066.52 | D36: ='DCF by Box'!C250 -> 7911.5043 | E36: ='DCF by Box'!D250 -> 14553.046 | F36: ='DCF by Box'!E250 -> 22722.518 | H36: =D36/$C36-1 -> -0.50757821 | I36: =E36/$C36-1 -> -0.094200435 | J36: =F36/$C36-1 -> 0.41427753
B37: WEG & Embraer | C37: ='Box Shares'!C15 -> 10204.555 | D37: ='DCF by Box'!C297 -> 4393.0221 | E37: ='DCF by Box'!D297 -> 5809.3114 | F37: ='DCF by Box'!E297 -> 7506.9963 | H37: =D37/$C37-1 -> -0.56950381 | I37: =E37/$C37-1 -> -0.4307139 | J37: =F37/$C37-1 -> -0.2643485
B39: 4. Discount rate by box (Box Rates)
B40: Group | C40: Relative cash yield | D40: Rate: Bear | E40: Base | F40: Bull | G40: CAPM beta | H40: Risk premium: Bear | I40: Base | J40: Bull
B41: Financials | C41: ='Box Rates'!G7 -> 0.9245176 | D41: ='Box Rates'!C21 -> 0.15394382 | E41: ='Box Rates'!D21 -> 0.13654382 | F41: ='Box Rates'!E21 -> 0.12394382 | G41: ='Box Betas'!I7 -> 1.1490637 | H41: ='Box Rates'!G21 -> 0.068943819 | I41: ='Box Rates'!H21 -> 0.068943819 | J41: ='Box Rates'!I21 -> 0.068943819
B42: Defensives | C42: ='Box Rates'!G8 -> 0.63524349 | D42: ='Box Rates'!C22 -> 0.14072044 | E42: ='Box Rates'!D22 -> 0.12332044 | F42: ='Box Rates'!E22 -> 0.11072044 | G42: ='Box Betas'!I8 -> 0.92867396 | H42: ='Box Rates'!G22 -> 0.055720438 | I42: ='Box Rates'!H22 -> 0.055720438 | J42: ='Box Rates'!I22 -> 0.055720438
B43: Cyclicals | C43: ='Box Rates'!G9 -> 0.29730445 | D43: ='Box Rates'!C23 -> 0.15402707 | E43: ='Box Rates'!D23 -> 0.13662707 | F43: ='Box Rates'!E23 -> 0.12402707 | G43: ='Box Betas'!I9 -> 1.1504511 | H43: ='Box Rates'!G23 -> 0.069027066 | I43: ='Box Rates'!H23 -> 0.069027066 | J43: ='Box Rates'!I23 -> 0.069027066
B44: Commodities | C44: ='Box Rates'!G10 -> 1.53528 | D44: ='Box Rates'!C24 -> 0.13730115 | E44: ='Box Rates'!D24 -> 0.11990115 | F44: ='Box Rates'!E24 -> 0.10730115 | G44: ='Box Betas'!I10 -> 0.87168584 | H44: ='Box Rates'!G24 -> 0.05230115 | I44: ='Box Rates'!H24 -> 0.05230115 | J44: ='Box Rates'!I24 -> 0.05230115
B45: Ibovespa (house rate) | C45: ='Box Rates'!G11 -> 1 | D45: ='Box Rates'!C19 -> 0.145 | E45: ='Box Rates'!D19 -> 0.1276 | F45: ='Box Rates'!E19 -> 0.115 | G45: ='Box Betas'!I11 -> 1 | H45: ='Box Rates'!G19 -> 0.06 | I45: ='Box Rates'!H19 -> 0.06 | J45: ='Box Rates'!I19 -> 0.06
B46: Memo (inside Cyclicals)
B47: Cyclicals ex-WEG & Embraer | C47: ='Box Rates'!G13 -> 0.32038362 | D47: ='Box Rates'!C26 -> 0.16412287 | E47: ='Box Rates'!D26 -> 0.14672287 | F47: ='Box Rates'!E26 -> 0.13412287 | G47: ='Box Betas'!I13 -> 1.3187146 | H47: ='Box Rates'!G26 -> 0.079122874 | I47: ='Box Rates'!H26 -> 0.079122874 | J47: ='Box Rates'!I26 -> 0.079122874
B48: WEG & Embraer | C48: ='Box Rates'!G14 -> 0.23199022 | D48: ='Box Rates'!C27 -> 0.12807007 | E48: ='Box Rates'!D27 -> 0.11067007 | F48: ='Box Rates'!E27 -> 0.098070071 | G48: ='Box Betas'!I14 -> 0.71783452 | H48: ='Box Rates'!G27 -> 0.043070071 | I48: ='Box Rates'!H27 -> 0.043070071 | J48: ='Box Rates'!I27 -> 0.043070071
B49: Rates in use (BoxRate in Assumptions; default 2 = CAPM, real rate + box beta x the house ERP). Betas: Box Betas.
B51: 5. DCF: each box with its own value, before scaling (Financials by FCFE)
D52: Bear | E52: Base | F52: Bull | H52: Upside: Bear | I52: Base | J52: Bull
B53: Financials | D53: ='DCF by Box'!C59 -> 39337.863 | E53: ='DCF by Box'!D59 -> 57179.67 | F53: ='DCF by Box'!E59 -> 78479.292 | H53: ='DCF by Box'!C61 -> -0.35434755 | I53: ='DCF by Box'!D61 -> -0.061509922 | J53: ='DCF by Box'!E61 -> 0.28808083
B54: Defensives | D54: ='DCF by Box'!C106 -> 32906.129 | E54: ='DCF by Box'!D106 -> 48179.749 | F54: ='DCF by Box'!E106 -> 67069.6 | H54: ='DCF by Box'!C108 -> -0.41052071 | I54: ='DCF by Box'!D108 -> -0.13690961 | J54: ='DCF by Box'!E108 -> 0.20148255
B55: Cyclicals | D55: ='DCF by Box'!C153 -> 11003.825 | E55: ='DCF by Box'!D153 -> 20445.272 | F55: ='DCF by Box'!E153 -> 32356.929 | H55: ='DCF by Box'!C155 -> -0.58114295 | I55: ='DCF by Box'!D155 -> -0.2217573 | J55: ='DCF by Box'!E155 -> 0.2316561
B56: Commodities | D56: ='DCF by Box'!C200 -> 58771.759 | E56: ='DCF by Box'!D200 -> 98013.826 | F56: ='DCF by Box'!E200 -> 149230.1 | H56: ='DCF by Box'!C202 -> -0.10150277 | I56: ='DCF by Box'!D202 -> 0.49842633 | J56: ='DCF by Box'!E202 -> 1.281416
B57: Sum of the boxes | D57: ='DCF by Box'!C7 -> 142019.58 | E57: ='DCF by Box'!D7 -> 223818.52 | F57: ='DCF by Box'!E7 -> 327135.92
B58: House DCF fair value, Ibovespa (DCF sheet) | D58: ='DCF by Box'!C8 -> 191722.24 | E58: ='DCF by Box'!D8 -> 235695.44 | F58: ='DCF by Box'!E8 -> 281862.98
B59: Scale factor = house / sum of the boxes | D59: ='DCF by Box'!C9 -> 1.3499705 | E59: ='DCF by Box'!D9 -> 1.053065 | F59: ='DCF by Box'!E9 -> 0.86160818
B60: Factor applied (ScaleScen = 1: the base factor in every scenario) | D60: ='DCF by Box'!C10 -> 1 | E60: ='DCF by Box'!D10 -> 1 | F60: ='DCF by Box'!E10 -> 1
B61: 6. Scenario parameters and settings (Assumptions)
D62: Bear | E62: Base | F62: Bull
B63: 5-year real rate (NTN-B) | D63: =DCF!C46 -> 0.085 | E63: =DCF!D46 -> 0.0676 | F63: =DCF!E46 -> 0.055
B64: ERP (house) | D64: =DCF!C47 -> 0.06 | E64: =DCF!D47 -> 0.06 | F64: =DCF!E47 -> 0.06
B65: House discount rate | D65: =DCF!C48 -> 0.145 | E65: =DCF!D48 -> 0.1276 | F65: =DCF!E48 -> 0.115
B66: Target P/E on 2027 EPS | D66: =Assumptions!C53 -> 7.5 | E66: =Assumptions!D53 -> 10 | F66: =Assumptions!E53 -> 12
B67: Target EV/EBITDA on 2027 EBITDA | D67: =Assumptions!C54 -> 4.5 | E67: =Assumptions!D54 -> 5.5 | F67: =Assumptions!E54 -> 6
B68: Bottom-up change | D68: =Assumptions!C55 -> -0.2 | E68: =Assumptions!D55 -> 0 | F68: =Assumptions!E55 -> 0.2
B69: Corrections to the house aggregate (Assumptions section 4) | D69: =IF(FixNWC+FixND+FixTV+FixInfl=0,"none: as the house","on: "&IF(FixNWC=1,"NWC change ","")&IF(FixND=1,"net debt ","")&IF(FixTV=1,"TV timing ","")&IF(FixInfl=1,"inflation","")) -> none: as the house
B70: 7. Box shares of the house lines (Box Shares; last consensus year)
B71: Line | D71: Financials | E71: Defensives | F71: Cyclicals | G71: Commodities
B72: Sales 2027 | D72: ='Box Shares'!E19 -> 0.1642579 | E72: ='Box Shares'!E20 -> 0.26048992 | F72: ='Box Shares'!E21 -> 0.11218492 | G72: ='Box Shares'!E22 -> 0.46306726
B73: EBIT 2028 | D73: ='Box Shares'!I19 -> 0.22985575 | E73: ='Box Shares'!I20 -> 0.24415677 | F73: ='Box Shares'!I21 -> 0.105999 | G73: ='Box Shares'!I22 -> 0.41998848
B74: EBITDA 2028 | D74: ='Box Shares'!L19 -> 0.2555345 | E74: ='Box Shares'!L20 -> 0.22223939 | F74: ='Box Shares'!L21 -> 0.097444816 | G74: ='Box Shares'!L22 -> 0.42478129
B75: Net income 2028 | D75: ='Box Shares'!O19 -> 0.3064974 | E75: ='Box Shares'!O20 -> 0.19377661 | F75: ='Box Shares'!O21 -> 0.098542148 | G75: ='Box Shares'!O22 -> 0.40118384
B76: Capex 2027 | D76: ='Box Shares'!Q19 -> 0.24938824 | E76: ='Box Shares'!Q20 -> 0.24129138 | F76: ='Box Shares'!Q21 -> 0.14132059 | G76: ='Box Shares'!Q22 -> 0.36799979
B77: 8. Reference (not linked): multiples model and our DCF by box (index pts)
B78: Model | D78: Financials | E78: Defensives | F78: Cyclicals | G78: Commodities | H78: Ibovespa | I78: Cyc. ex-WEG & EMB | J78: WEG & Embraer
B79: Multiples model, average of methods (Oct-6 table): Bear | D79: 44915.644 | E79: 48306.986 | F79: 26679.456 | G79: 54511.78 | H79: 174413.87 | I79: 18223.149 | J79: 7588.3271
B80: Multiples model, average of methods (Oct-6 table): Base | D80: 56329.564 | E80: 59767.572 | F80: 36688.016 | G80: 76446.398 | H80: 229231.55 | I80: 26153.316 | J80: 12835.632
B81: Multiples model, average of methods (Oct-6 table): Bull | D81: 71678.724 | E81: 73390.376 | F81: 48520.494 | G81: 101241.91 | H81: 294831.51 | I81: 35580.997 | J81: 18587.73
B82: DCF by box (Ibov_DCF_by_box_XP.xlsx, 12 months): Base | D82: 70757 | E82: 42152 | F82: 24906 | G82: 85903 | H82: 223718 | I82: 17780 | J82: 7140
B83: Multiples model: Ibov_valuation_by_box_model_XP.xlsx (prices of Oct-5; each box at its own 10y average multiples, plus bottom-up).
B85: 9. Scenarios of the DCF by box: shocks, rates and the change vs. the base (multiples model for comparison)
B86: Group | C86: Earnings beta, domestic (normalized) | D86: Commodity price elasticity | E86: Earnings shock: Bear | F86: Bull | G86: Rate: Bear | H86: Bull | I86: DCF vs. base: Bear | J86: Bull | K86: Multiples model vs. base: Bear | L86: Bull
B87: Financials | C87: ='Box Earnings'!I7*'Box Earnings'!$I$16 -> 0.86968171 | D87: ='Box Earnings'!J7 -> 0 | E87: ='Box Earnings'!C21 -> -0.17393634 | F87: ='Box Earnings'!E21 -> 0.17393634 | G87: ='Box Rates'!C21 -> 0.15394382 | H87: ='Box Rates'!E21 -> 0.12394382 | I87: ='DCF by Box'!C62/'DCF by Box'!D62-1 -> -0.31203061 | J87: ='DCF by Box'!E62/'DCF by Box'!D62-1 -> 0.37250341 | K87: =$D$79/$D$80-1 -> -0.20262753 | L87: =$D$81/$D$80-1 -> 0.27248853
B88: Defensives | C88: ='Box Earnings'!I8*'Box Earnings'!$I$16 -> 0.78019054 | D88: ='Box Earnings'!J8 -> 0 | E88: ='Box Earnings'!C22 -> -0.15603811 | F88: ='Box Earnings'!E22 -> 0.15603811 | G88: ='Box Rates'!C22 -> 0.14072044 | H88: ='Box Rates'!E22 -> 0.11072044 | I88: ='DCF by Box'!C109/'DCF by Box'!D109-1 -> -0.31701326 | J88: ='DCF by Box'!E109/'DCF by Box'!D109-1 -> 0.39207036 | K88: =$E$79/$E$80-1 -> -0.19175258 | L88: =$E$81/$E$80-1 -> 0.22792968
B89: Cyclicals | C89: ='Box Earnings'!I9*'Box Earnings'!$I$16 -> 1.7692958 | D89: ='Box Earnings'!J9 -> 0 | E89: ='Box Earnings'!C23 -> -0.35385915 | F89: ='Box Earnings'!E23 -> 0.35385915 | G89: ='Box Rates'!C23 -> 0.15402707 | H89: ='Box Rates'!E23 -> 0.12402707 | I89: ='DCF by Box'!C156/'DCF by Box'!D156-1 -> -0.46179122 | J89: ='DCF by Box'!E156/'DCF by Box'!D156-1 -> 0.58261184 | K89: =$F$79/$F$80-1 -> -0.27280189 | L89: =$F$81/$F$80-1 -> 0.32251616
B90: Commodities | C90: ='Box Earnings'!I10*'Box Earnings'!$I$16 -> 0 | D90: ='Box Earnings'!J10 -> 1.2620302 | E90: ='Box Earnings'!C24 -> -0.25240604 | F90: ='Box Earnings'!E24 -> 0.25240604 | G90: ='Box Rates'!C24 -> 0.13730115 | H90: ='Box Rates'!E24 -> 0.10730115 | I90: ='DCF by Box'!C203/'DCF by Box'!D203-1 -> -0.40037277 | J90: ='DCF by Box'!E203/'DCF by Box'!D203-1 -> 0.52254129 | K90: =$G$79/$G$80-1 -> -0.28692808 | L90: =$G$81/$G$80-1 -> 0.32435168
B91: Ibovespa | C91: ='Box Earnings'!I15*'Box Earnings'!I16 -> 1 | D91: =0 -> 0 | E91: ='Box Earnings'!C25 -> -0.21644633 | F91: ='Box Earnings'!E25 -> 0.21644633 | G91: ='Box Rates'!C19 -> 0.145 | H91: ='Box Rates'!E19 -> 0.115 | I91: ='DCF by Box'!C11/'DCF by Box'!D11-1 -> -0.36546994 | J91: ='DCF by Box'!E11/'DCF by Box'!D11-1 -> 0.4616124 | K91: =$H$79/$H$80-1 -> -0.23913673 | L91: =$H$81/$H$80-1 -> 0.28617334
B92: Memo (inside Cyclicals)
B93: Cyclicals ex-WEG & Embraer | C93: ='Box Earnings'!I13*'Box Earnings'!$I$16 -> 1.7924675 | D93: ='Box Earnings'!J13 -> 0 | E93: ='Box Earnings'!C27 -> -0.3584935 | F93: ='Box Earnings'!E27 -> 0.3584935 | G93: ='Box Rates'!C26 -> 0.16412287 | H93: ='Box Rates'!E26 -> 0.13412287 | I93: ='DCF by Box'!C250/'DCF by Box'!D250-1 -> -0.45636782 | J93: ='DCF by Box'!E250/'DCF by Box'!D250-1 -> 0.56135815 | K93: =$I$79/$I$80-1 -> -0.30321843 | L93: =$I$81/$I$80-1 -> 0.36047744
B94: WEG & Embraer | C94: ='Box Earnings'!I14*'Box Earnings'!$I$16 -> 0.15083352 | D94: ='Box Earnings'!J14 -> 0 | E94: ='Box Earnings'!C28 -> -0.030166704 | F94: ='Box Earnings'!E28 -> 0.030166704 | G94: ='Box Rates'!C27 -> 0.12807007 | H94: ='Box Rates'!E27 -> 0.098070071 | I94: ='DCF by Box'!C297/'DCF by Box'!D297-1 -> -0.24379641 | J94: ='DCF by Box'!E297/'DCF by Box'!D297-1 -> 0.29223514 | K94: =$J$79/$J$80-1 -> -0.4088077 | L94: =$J$81/$J$80-1 -> 0.44813511
B95: Bear / bull: the house real-rate scenarios through each box's beta (RateShock) and the earnings shocks of Assumptions section 8 x each box's earnings beta (Commodities: the commodity shock). Multiples model: the Oct-6 table (section 8).
B97: 10. DCF by box: expected value (scenario probabilities) and the growth priced in today
B98: Group | C98: Expected value (pts) | D98: Expected upside | E98: Upside: Bear | F98: Base | G98: Bull | H98: Bull gain / bear loss vs. base | I98: Consensus growth 2026-28 | J98: Starting growth used (base) | K98: Growth priced in today (reverse DCF)
B99: Financials | C99: =(Assumptions!$C$63*'DCF by Box'!C62+Assumptions!$D$63*'DCF by Box'!D62+Assumptions!$E$63*'DCF by Box'!E62)/SUM(Assumptions!$C$63:$E$63) -> 58044.124 | D99: =C99/$C$30-1 -> -0.04732164 | E99: ='DCF by Box'!C62/$C$30-1 -> -0.35434755 | F99: ='DCF by Box'!D62/$C$30-1 -> -0.061509922 | G99: ='DCF by Box'!E62/$C$30-1 -> 0.28808083 | H99: =('DCF by Box'!E62-'DCF by Box'!D62)/('DCF by Box'!D62-'DCF by Box'!C62) -> 1.1938041 | I99: ='Box Shares'!H44 -> 0.12053515 | J99: ='DCF by Box'!D45 -> 0.047 | K99: ='DCF by Box'!D64 -> 0.066659715
B100: Defensives | C100: =(Assumptions!$C$63*'DCF by Box'!C109+Assumptions!$D$63*'DCF by Box'!D109+Assumptions!$E$63*'DCF by Box'!E109)/SUM(Assumptions!$C$63:$E$63) -> 49083.807 | D100: =C100/$C$31-1 -> -0.12071435 | E100: ='DCF by Box'!C109/$C$31-1 -> -0.41052071 | F100: ='DCF by Box'!D109/$C$31-1 -> -0.13690961 | G100: ='DCF by Box'!E109/$C$31-1 -> 0.20148255 | H100: =('DCF by Box'!E109-'DCF by Box'!D109)/('DCF by Box'!D109-'DCF by Box'!C109) -> 1.2367633 | I100: ='Box Shares'!H45 -> 0.233901 | J100: ='DCF by Box'!D97 -> 0.047 | K100: ='DCF by Box'!D111 -> 0.09209628
B101: Cyclicals | C101: =(Assumptions!$C$63*'DCF by Box'!C156+Assumptions!$D$63*'DCF by Box'!D156+Assumptions!$E$63*'DCF by Box'!E156)/SUM(Assumptions!$C$63:$E$63) -> 21062.825 | D101: =C101/$C$32-1 -> -0.19825036 | E101: ='DCF by Box'!C156/$C$32-1 -> -0.58114295 | F101: ='DCF by Box'!D156/$C$32-1 -> -0.2217573 | G101: ='DCF by Box'!E156/$C$32-1 -> 0.2316561 | H101: =('DCF by Box'!E156-'DCF by Box'!D156)/('DCF by Box'!D156-'DCF by Box'!C156) -> 1.2616347 | I101: ='Box Shares'!H46 -> 0.19744475 | J101: ='DCF by Box'!D144 -> 0.047 | K101: ='DCF by Box'!D158 -> 0.13250103
B102: Commodities | C102: =(Assumptions!$C$63*'DCF by Box'!C203+Assumptions!$D$63*'DCF by Box'!D203+Assumptions!$E$63*'DCF by Box'!E203)/SUM(Assumptions!$C$63:$E$63) -> 101007.38 | D102: =C102/$C$33-1 -> 0.54419146 | E102: ='DCF by Box'!C203/$C$33-1 -> -0.10150277 | F102: ='DCF by Box'!D203/$C$33-1 -> 0.49842633 | G102: ='DCF by Box'!E203/$C$33-1 -> 1.281416 | H102: =('DCF by Box'!E203-'DCF by Box'!D203)/('DCF by Box'!D203-'DCF by Box'!C203) -> 1.305137 | I102: ='Box Shares'!H47 -> -0.062420891 | J102: ='DCF by Box'!D191 -> 0.047 | K102: ='DCF by Box'!D205 -> -0.046262871
B103: Ibovespa | C103: =(Assumptions!$C$63*'DCF by Box'!C11+Assumptions!$D$63*'DCF by Box'!D11+Assumptions!$E$63*'DCF by Box'!E11)/SUM(Assumptions!$C$63:$E$63) -> 229198.13 | D103: =C103/$C$34-1 -> 0.099630671 | E103: ='DCF by Box'!C11/$C$34-1 -> -0.31862847 | F103: ='DCF by Box'!D11/$C$34-1 -> 0.073820729 | G103: ='DCF by Box'!E11/$C$34-1 -> 0.56950969 | H103: =('DCF by Box'!E11-'DCF by Box'!D11)/('DCF by Box'!D11-'DCF by Box'!C11) -> 1.2630653
B104: Memo (inside Cyclicals)
B105: Cyclicals ex-WEG & Embraer | C105: =(Assumptions!$C$63*'DCF by Box'!C250+Assumptions!$D$63*'DCF by Box'!D250+Assumptions!$E$63*'DCF by Box'!E250)/SUM(Assumptions!$C$63:$E$63) -> 14935.029 | D105: =C105/$C$36-1 -> -0.070425387 | E105: ='DCF by Box'!C250/$C$36-1 -> -0.50757821 | F105: ='DCF by Box'!D250/$C$36-1 -> -0.094200435 | G105: ='DCF by Box'!E250/$C$36-1 -> 0.41427753 | H105: =('DCF by Box'!E250-'DCF by Box'!D250)/('DCF by Box'!D250-'DCF by Box'!C250) -> 1.2300564 | I105: ='Box Shares'!H49 -> 0.19770284 | J105: ='DCF by Box'!D238 -> 0.047 | K105: ='DCF by Box'!D252 -> 0.079510601
B106: WEG & Embraer | C106: =(Assumptions!$C$63*'DCF by Box'!C297+Assumptions!$D$63*'DCF by Box'!D297+Assumptions!$E$63*'DCF by Box'!E297)/SUM(Assumptions!$C$63:$E$63) -> 5879.6603 | D106: =C106/$C$37-1 -> -0.42382003 | E106: ='DCF by Box'!C297/$C$37-1 -> -0.56950381 | F106: ='DCF by Box'!D297/$C$37-1 -> -0.4307139 | G106: ='DCF by Box'!E297/$C$37-1 -> -0.2643485 | H106: =('DCF by Box'!E297-'DCF by Box'!D297)/('DCF by Box'!D297-'DCF by Box'!C297) -> 1.1986852 | I106: ='Box Shares'!H50 -> 0.19659811 | J106: ='DCF by Box'!D285 -> 0.047 | K106: ='DCF by Box'!D299 -> 0.25134561
...

Sheet Assumptions
B1: Ibovespa - DCF assumptions (house model by box, end-2027)
B2: Change the pink cells; the DCF sheet recalculates. Projection rules for 2028-2031 are pink cells in the DCF sheet.
B3: Legend: | C3: input | D3: assumption | E3: formula
B5: 1. Market data
B6: Item | C6: House file | D6: Oct-5-2026 | E6: Used | G6: Source
B7: Ibovespa (index pts) | C7: 182419.73 | D7: 208431.92 | E7: =CHOOSE(Vintage,C7,D7) -> 208431.92 | G7: House file: Target!B61 (BDP IBOV Index, as saved). Oct-5: Bloomberg IBOV Index PX_LAST.
B8: 5-year real rate (NTN-B) | C8: 0.0742 | D8: 0.0676 | E8: =CHOOSE(Vintage,C8,D8) -> 0.0676 | G8: House file: Target!C56 (BZRFB5PY Index, 7.42%). Oct-5: ANBIMA 5-year NTN-B (Bloomberg was down; check BZRFB5PY before publishing).
B9: Market data used: 1 = house file, 2 = Oct-5-2026 | C9: 2 | G9: Consensus and history are the house file's in both cases (not refreshed: the consensus moved little).
B11: 2. Valuation parameters (house Target sheet)
B12: Parameter | C12: Value | G12: Source
B13: Long-term growth of the FCFF (g) | C13: 0.047 | G13: Target!B54 (4.7%).
B14: Long-term inflation (Fisher switch and the implied-return block) | C14: 0.04 | G14: Target!B63 (4.0%).
B15: Working capital, % of sales | C15: 0.04 | G15: Target row 43: NWC = -4% of sales.
B16: Net debt / EBITDA of two years before (net debt switch) | C16: 1.6 | G16: Target rows 70-71 (EV/EBITDA method): net debt = 1.6x the EBITDA of two years before the value date.
B18: 3. Scenarios (fair value at the end of 2027)
B19: Lever | C19: Bear | D19: Base | E19: Bull | G19: Source
B20: 5-year real rate (NTN-B) | C20: 0.085 | D20: =RRUsed -> 0.0676 | E20: 0.055 | G20: House (Target rows 131-151): bear 8.5%, base = the market rate, bull 6.0%. Bull here at 5.5% (a row of the house's real-rate table).
B21: ERP | C21: 0.06 | D21: 0.06 | E21: 0.06 | G21: Target!B57 (6.0%), the same in every scenario.
B22: Discount rate (house: real rate + ERP) | C22: =IF(FixInfl=1,(1+C20+C21)*(1+InflLT)-1,C20+C21) -> 0.145 | D22: =IF(FixInfl=1,(1+D20+D21)*(1+InflLT)-1,D20+D21) -> 0.1276 | E22: =IF(FixInfl=1,(1+E20+E21)*(1+InflLT)-1,E20+E21) -> 0.115 | G22: Target!B55 = BZRFB5PY + ERP. With the inflation switch on: (1 + real rate + ERP) x (1 + inflation) - 1.
B24: 4. Corrections to the house mechanics (0 = as the house, 1 = corrected)
B25: Switch | C25: Value | G25: What it changes
B26: Working capital: 0 = level (house), 1 = change | C26: 0 | G26: House row 44 adds the whole NWC level (-4% of sales) every year; the cash flow is the change in NWC.
B27: Net debt: 0 = not subtracted (house), 1 = subtracted | C27: 0 | G27: FCFF values the firm; equity = firm value - net debt (1.6x EBITDA two years before, as the house's EV/EBITDA method).
B28: Terminal value: 0 = one period after the last flow (house), 1 = with the last flow | C28: 0 | G28: NPV(rate, flows, TV) puts the TV one year after the last explicit year; it is a value at the end of that year.
B29: Inflation in the rate: 0 = real rate + ERP (house), 1 = Fisher | C29: 0 | G29: The flows are nominal (sales grow with nominal GDP); real rate + ERP is a real rate.
B31: 5. Projection rules (pink cells in the DCF sheet, 2028-2031 columns)
B32: Real GDP and inflation 2028-2031: 2.0% and 4.0% (house); sales grow with nominal GDP x ratio (1.0).
B33: EBITDA margin 2029-2031: 30% (house). EBIT margin, interest and gross margin: held at the 2028 level (house: same % as the year before).
B34: Capex % of sales: 11% in 2028-2029, 9% from 2030 (house); 2031, the year added here, keeps 2030's 9%.
B35: Consensus: sales and capex to 2027, EBIT, EBITDA and EPS to 2028 (IBOV Index, as in the house file).
B37: 6. By box
B38: Setting | C38: Value | G38: What it does
B39: Scale the boxes to the house's Ibovespa value: 1 = yes, 0 = no | C39: 0 | G39: 1: each box x (house Ibovespa value / sum of the boxes), so the boxes add up to the house number. 0: each box with its own value.
B40: Financials ROE for the FCFE (blank = consensus FY28, Box Shares) | G40: FCFE = net income x (1 - g / ROE): the earnings left after keeping the bank's equity growing at g.
B41: Index points of the members: Ibovespa on Oct-5-2026 (Assumptions D7) x price-drifted Sep-30 weights.
B42: Box discount rates: 0 = house rate, 1 = relative to history, 2 = CAPM (box beta) | C42: 2 | G42: 0: every box at the house rate. 1: box rate - g = (house rate - g) x the box's 10y cash yield relative to the Ibovespa (Box Rates), as the multiples. 2: CAPM, real rate + box beta x ERP (Box Betas).
B43: Lowest risk premium of a box (box rate >= real rate + this) | C43: 0 | G43: Keeps a box's risk premium from going below this; at 0% it binds only for Cyclicals in the bear.
B44: CAPM beta window (years of weekly returns: 2, 5 or 10) | C44: 5 | G44: Weekly total returns of the box indices up to Sep-25-2026 (Box Betas).
B45: CAPM beta: 1 = raw, 2 = Blume adjusted (0.67 x raw + 0.33) | C45: 1 | G45: The adjustment pulls the betas toward 1 (Bloomberg's default adjusted beta).
B46: Box cash-flow rules: 1 = capex funding growth and NWC by change, 0 = the house rules | C46: 1 | G46: 1: capex = D&A + growth x NOPAT / ROE (Box Shares section 5) and working capital by its change, in the box values only; the house aggregate is untouched.
B47: Growth in the terminal value: 1 = consensus growth fading to g, 0 = g (house) | C47: 0 | G47: 1: the box's consensus net income growth 2026-28 (capped) fades to g over FadeYears after 2031; 0: the fade starts at g. Valued year by year or by the H-model formula (FadeMode, section 8).
B48: Years over which the growth fades to g (after 2031) | C48: 10 | G48: At most 10 with the year-by-year fade (Box Fade).
B49: Cap on the starting growth (+/-) | C49: 0.15 | G49: Defensives (+23%) and Cyclicals (+20%) are capped.
B51: 7. Target by box: average of the methods (house Target rows 83-90)
B52: Lever | C52: Bear | D52: Base | E52: Bull | G52: Source
B53: Target P/E on 2027 EPS | C53: 7.5 | D53: 10 | E53: 12 | G53: House: 10.0x for 2027 (Target!F76); bear / bull 7.5x / 12x (Target rows 134 / 148).
B54: Target EV/EBITDA on 2027 EBITDA | C54: 4.5 | D54: 5.5 | E54: 6 | G54: House: 5.5x for 2027 (Target!F67); bear / bull 4.5x / 6.0x (rows 135 / 149). Net debt = 1.6x EBITDA 2025.
B55: Bottom-up: change vs. the analysts' target prices | C55: -0.2 | D55: 0 | E55: 0.2 | G55: House: -20% / +20% in the bear / bull (rows 136 / 150); 2027 without the / 1.15 of 2026.
B56: Box multiples: 1 = relative to history, 0 = house multiple | C56: 1 | G56: 1: the boxes keep their historical premium or discount to the Ibovespa, calibrated so they add up to the house value (Multiples by Box).
B57: Weights of the methods: DCF, P/E, EV/EBITDA, bottom-up | C57: 1 | D57: 1 | E57: 1 | F57: 1 | G57: House: simple average of the four methods (Target row 88).
B59: 8. Scenarios of the DCF by box: the house's two levers (real rate, section 3; earnings level, below)
B60: Lever | C60: Bear | D60: Base | E60: Bull | G60: What it does
B61: Earnings level of the Ibovespa ex-Commodities vs. consensus | C61: -0.2 | D61: 0 | E61: 0.2 | G61: As the house's EPS / EBITDA lower / higher, symmetric: every year's earnings and flows x (1 + shock). Split by each domestic box's earnings beta (Box Earnings), normalized so the three domestic boxes average this shock.
B62: Commodity prices vs. base | C62: -0.2 | D62: 0 | E62: 0.2 | G62: Commodities' own method: its earnings level moves by its earnings elasticity to commodity prices (Box Earnings, estimated 2007-26) x this change.
B63: Probability of the scenario | C63: 0.25 | D63: 0.5 | E63: 0.25 | G63: Expected value by box (Summary section 10); normalized by their sum.
B64: Rate shock: 1 = x box beta, 0 = the same for every box (house) | C64: 0 | G64: 1: box rate = base box rate + beta x (scenario house rate - base house rate), a shock to the market's required return; 0: the real-rate change moves every box equally. CAPM rates only (BoxRate = 2).
B65: Normalize the domestic earnings betas: 1 = yes, 0 = raw | C65: 1 | G65: 1: the betas are scaled so the index-point-weighted average of Financials, Defensives and Cyclicals is 1 (the domestic boxes get the shock on average).
B66: Ibovespa bear / bull: 1 = sum of the boxes, 0 = house DCF | C66: 1 | G66: 1: every scenario keeps the base-case scale factor (DCF by Box), so the shocks open the Ibovespa's bear / bull; 0: each scenario is scaled to the house DCF.
B67: Fade after 2031: 0 = H-model, 1 = year by year, 2 = growth paid | C67: 0 | G67: 1: the flow grows year by year from the starting growth to g (Box Fade); the H-model formula approximates it and undervalues negative growth (Commodities). 2: flow = earnings x (1 - growth / ROE): growth costs reinvestment at the box's FY28 ROE.
B68: Earnings betas: first month of the window | C68: 39386 | G68: Window from this month to Sep-26; Oct-07 is the first 12-month change (the whole history).

Sheet DCF by Box
B1: Ibovespa - DCF by box (end-2027)
B2: Each box gets its share of every house line (Box Shares); box rules for capex and NWC, consensus growth fading in the TV, CAPM rates (Box Rates). FCFE for Financials.
B3: Legend: | C3: input | D3: assumption | E3: formula
B5: Ibovespa = sum of the four boxes (end-2027)
C6: Bear | D6: Base | E6: Bull
B7: Sum of the box values, own mechanics and box rates (Financials by FCFE) | C7: =C59+C106+C153+C200 -> 142019.58 | D7: =D59+D106+D153+D200 -> 223818.52 | E7: =E59+E106+E153+E200 -> 327135.92 | J7: Defensives + Cyclicals + Commodities (FCFF) + Financials (FCFE), each at its box rate (Box Rates).
B8: House DCF fair value for the Ibovespa (DCF sheet) | C8: =DCF!C57 -> 191722.24 | D8: =DCF!D57 -> 235695.44 | E8: =DCF!E57 -> 281862.98
B9: Scale factor = house value / sum of the boxes | C9: =C8/C7 -> 1.3499705 | D9: =D8/D7 -> 1.053065 | E9: =E8/E7 -> 0.86160818 | J9: Close to 1: the boxes' own values add up to about the house number.
B10: Factor applied (ScaleBox; ScaleScen = 1: the base factor in every scenario) | C10: =IF(ScaleBox=1,IF(ScaleScen=1,$D$9,C9),1) -> 1 | D10: =IF(ScaleBox=1,IF(ScaleScen=1,$D$9,D9),1) -> 1 | E10: =IF(ScaleBox=1,IF(ScaleScen=1,$D$9,E9),1) -> 1 | J10: ScaleScen = 1: the bear / bull keep the base factor, so the earnings shocks (Box Earnings) open the Ibovespa's bear / bull; 0: every scenario = house DCF.
B11: Sum of the box fair values = the Ibovespa by box | C11: =C62+C109+C156+C203 -> 142019.58 | D11: =D62+D109+D156+D203 -> 223818.52 | E11: =E62+E109+E156+E203 -> 327135.92
B12: Memo: sum of the FCFF pieces at the house rate (house mechanics) = house value | C12: =C66+C113+C160+C207 -> 191722.24 | D12: =D66+D113+D160+D207 -> 235695.44 | E12: =E66+E113+E160+E207 -> 281862.98 | J12: The split itself is exact: with every box on the house mechanics and the house rate, the boxes add up to the house value.
B13: Memo: sum of the box values at the house rate (Financials by FCFE) | C13: =C67+C114+C161+C208 -> 185570.93 | D13: =D67+D114+D161+D208 -> 227874.08 | E13: =E67+E114+E161+E208 -> 272279.65 | J13: The boxes as in the house (one rate), for comparison.
B14: Memo: scale factor at the house rate | C14: =C8/C13 -> 1.033148 | D14: =D8/D13 -> 1.0343232 | E14: =E8/E13 -> 1.0351967
B15: Ibovespa by box vs. the house DCF (sum / house - 1) | C15: =C11/C8-1 -> -0.25924308 | D15: =D11/D8-1 -> -0.050390968 | E15: =E11/E8-1 -> 0.16062036
B16: Financials (FCFE)
C17: 2026 | D17: 2027 | E17: 2028 | F17: 2029 | G17: 2030 | H17: 2031 | J17: How it is calculated
B18: Share of sales | C18: ='Box Shares'!D19 -> 0.16009415 | D18: ='Box Shares'!E19 -> 0.1642579 | E18: =D18 -> 0.1642579 | F18: =E18 -> 0.1642579 | G18: =F18 -> 0.1642579 | H18: =G18 -> 0.1642579 | J18: Box Shares: 2026-27 consensus; 2028+ as 2027 (the house projects sales from 2027).
B19: Sales | C19: =DCF!N13*C18 -> 25442.323 | D19: =DCF!O13*D18 -> 26900.352 | E19: =DCF!P13*E18 -> 28535.894 | F19: =DCF!Q13*F18 -> 30270.876 | G19: =DCF!R13*G18 -> 32111.345 | H19: =DCF!S13*H18 -> 34063.715 | J19: House sales (DCF sheet) x share.
B20: Share of EBIT | C20: ='Box Shares'!G19 -> 0.20683299 | D20: ='Box Shares'!H19 -> 0.22119544 | E20: ='Box Shares'!I19 -> 0.22985575 | F20: =E20 -> 0.22985575 | G20: =F20 -> 0.22985575 | H20: =G20 -> 0.22985575 | J20: Box Shares: 2026-28 consensus; 2029+ as 2028.
B21: EBIT | C21: =DCF!N19*C20 -> 6842.0354 | D21: =DCF!O19*D20 -> 7715.9607 | E21: =DCF!P19*E20 -> 8578.6786 | F21: =DCF!Q19*F20 -> 9100.2623 | G21: =DCF!R19*G20 -> 9653.5582 | H21: =DCF!S19*H20 -> 10240.495
B22: Share of EBITDA | C22: ='Box Shares'!J19 -> 0.25196485 | D22: ='Box Shares'!K19 -> 0.25096616 | E22: ='Box Shares'!L19 -> 0.2555345 | F22: =E22 -> 0.2555345 | G22: =F22 -> 0.2555345 | H22: =G22 -> 0.2555345 | J22: Box Shares: 2026-28; 2029+ as 2028. Financials includes the EBITDA the index imputes to banks.
B23: EBITDA | C23: =DCF!N21*C22 -> 12427.914 | D23: =DCF!O21*D22 -> 12728.251 | E23: =DCF!P21*E22 -> 13287.025 | F23: =DCF!Q21*F22 -> 14127.636 | G23: =DCF!R21*G22 -> 14986.597 | H23: =DCF!S21*H22 -> 15897.782
B24: Share of capex | C24: ='Box Shares'!P19 -> 0.24802703 | D24: ='Box Shares'!Q19 -> 0.24938824 | E24: =D24 -> 0.24938824 | F24: =E24 -> 0.24938824 | G24: =F24 -> 0.24938824 | H24: =G24 -> 0.24938824 | J24: Box Shares: 2026-27; 2028+ as 2027.
B25: Capex | C25: =DCF!N33*C24 -> -4751.9498 | D25: =DCF!O33*D24 -> -4821.4228 | E25: =DCF!P33*E24 -> -4765.7786 | F25: =DCF!Q33*F24 -> -5055.5379 | G25: =DCF!R33*G24 -> -4387.8392 | H25: =DCF!S33*H24 -> -4654.6199
B26: Share of net income | C26: ='Box Shares'!M19 -> 0.27229092 | D26: ='Box Shares'!N19 -> 0.29478935 | E26: ='Box Shares'!O19 -> 0.3064974 | F26: =E26 -> 0.3064974 | G26: =F26 -> 0.3064974 | H26: =G26 -> 0.3064974 | J26: Box Shares: 2026-28; 2029+ as 2028.
B27: Net income | C27: =DCF!N29*C26 -> 5706.6731 | D27: =DCF!O29*D26 -> 6386.9061 | E27: =DCF!P29*E26 -> 7103.6903 | F27: =DCF!Q29*F26 -> 7535.5947 | G27: =DCF!R29*G26 -> 7993.7588 | H27: =DCF!S29*H26 -> 8479.7794
B28: D&A = EBITDA - EBIT | C28: =C23-C21 -> 5585.8788 | D28: =D23-D21 -> 5012.2903 | E28: =E23-E21 -> 4708.346 | F28: =F23-F21 -> 5027.3741 | G28: =G23-G21 -> 5333.0385 | H28: =H23-H21 -> 5657.2872
B29: Tax rate (house) | C29: =DCF!N25 -> -0.24 | D29: =DCF!O25 -> -0.24 | E29: =DCF!P25 -> -0.24 | F29: =DCF!Q25 -> -0.24 | G29: =DCF!R25 -> -0.24 | H29: =DCF!S25 -> -0.24 | J29: DCF sheet (house, -24%).
B30: NOPAT = EBIT x (1 + tax rate) | C30: =C21*(1+C29) -> 5199.9469 | D30: =D21*(1+D29) -> 5864.1301 | E30: =E21*(1+E29) -> 6519.7958 | F30: =F21*(1+F29) -> 6916.1993 | G30: =G21*(1+G29) -> 7336.7043 | H30: =H21*(1+H29) -> 7782.7759
B31: Working capital (NWC) = -NWC % x sales | C31: =-NWCpct*C19 -> -1017.6929 | D31: =-NWCpct*D19 -> -1076.0141 | E31: =-NWCpct*E19 -> -1141.4357 | F31: =-NWCpct*F19 -> -1210.835 | G31: =-NWCpct*G19 -> -1284.4538 | H31: =-NWCpct*H19 -> -1362.5486
B32: Change in NWC | D32: =D31-C31 -> -58.321171 | E32: =E31-D31 -> -65.421657 | F32: =F31-E31 -> -69.399293 | G32: =G31-F31 -> -73.61877 | H32: =H31-G31 -> -78.094792
B33: FCFF, house = D&A + NOPAT + capex + NWC (level) | C33: =C28+C30+C25+C31 -> 5016.1829 | D33: =D28+D30+D25+D31 -> 4978.9835 | E33: =E28+E30+E25+E31 -> 5320.9274 | F33: =F28+F30+F25+F31 -> 5677.2005 | G33: =G28+G30+G25+G31 -> 6997.4497 | H33: =H28+H30+H25+H31 -> 7422.8946
B34: FCFF with the change in NWC | D34: =D28+D30+D25+D32 -> 5996.6764 | E34: =E28+E30+E25+E32 -> 6396.9415 | F34: =F28+F30+F25+F32 -> 6818.6362 | G34: =G28+G30+G25+G32 -> 8208.2847 | H34: =H28+H30+H25+H32 -> 8707.3484
B35: FCFF, house mechanics (switch FixNWC) | C35: =C33 -> 5016.1829 | D35: =IF(FixNWC=1,D34,D33) -> 4978.9835 | E35: =IF(FixNWC=1,E34,E33) -> 5320.9274 | F35: =IF(FixNWC=1,F34,F33) -> 5677.2005 | G35: =IF(FixNWC=1,G34,G33) -> 6997.4497 | H35: =IF(FixNWC=1,H34,H33) -> 7422.8946 | J35: FixNWC = 0: house row; 1: corrected row. Sum of the boxes = house FCFF (Checks); used for the house-rate memo.
B36: Capex funding growth = -(D&A + growth x NOPAT / ROE) | C36: =C25 -> -4751.9498 | D36: =D25 -> -4821.4228 | E36: =-(E28+DCF!P11*E30/'Box Shares'!$E$44) -> -6703.2692 | F36: =-(F28+DCF!Q11*F30/'Box Shares'!$E$44) -> -7143.5887 | G36: =-(G28+DCF!R11*G30/'Box Shares'!$E$44) -> -7577.9189 | H36: =-(H28+DCF!S11*H30/'Box Shares'!$E$44) -> -8038.6564 | J36: 2028+: D&A + the reinvestment that funds the year's growth (house sales growth) at the box's FY28 ROE (Box Shares section 5); 2026-27: consensus.
B37: FCFF, box rules = D&A + NOPAT + capex funding growth + change in NWC | C37: =C33 -> 5016.1829 | D37: =D28+D30+D36+D32 -> 5996.6764 | E37: =E28+E30+E36+E32 -> 4459.4508 | F37: =F28+F30+F36+F32 -> 4730.5854 | G37: =G28+G30+G36+G32 -> 5018.205 | H37: =H28+H30+H36+H32 -> 5323.3119
B38: FCFF used for the box value (switch BoxCF) | C38: =IF(BoxCF=1,C37,C35) -> 5016.1829 | D38: =IF(BoxCF=1,D37,D35) -> 5996.6764 | E38: =IF(BoxCF=1,E37,E35) -> 4459.4508 | F38: =IF(BoxCF=1,F37,F35) -> 4730.5854 | G38: =IF(BoxCF=1,G37,G35) -> 5018.205 | H38: =IF(BoxCF=1,H37,H35) -> 5323.3119 | J38: BoxCF = 1: box rules (row above); 0: the house mechanics.
B39: ROE (Financials, Box Shares section 4) | C39: =FinROE -> 0.19870618 | D39: =FinROE -> 0.19870618 | E39: =FinROE -> 0.19870618 | F39: =FinROE -> 0.19870618 | G39: =FinROE -> 0.19870618 | H39: =FinROE -> 0.19870618
B40: FCFE = net income x (1 - g / ROE) | C40: =C27*(1-gLT/C39) -> 4356.8729 | D40: =D27*(1-gLT/D39) -> 4876.2103 | E40: =E27*(1-gLT/E39) -> 5423.4535 | F40: =F27*(1-gLT/F39) -> 5753.1994 | G40: =G27*(1-gLT/G39) -> 6102.994 | H40: =H27*(1-gLT/H39) -> 6474.056 | J40: Financials only: the value used for the box (same g as the house).
B42: Valuation at the end of 2027 | C42: Bear | D42: Base | E42: Bull
B43: Discount rate of the box (Box Rates) | C43: ='Box Rates'!C21 -> 0.15394382 | D43: ='Box Rates'!D21 -> 0.13654382 | E43: ='Box Rates'!E21 -> 0.12394382 | J43: BoxRate 0: the house rate; 1: g + (house rate - g) x the box's relative cash yield, at least real rate + floor; 2: CAPM, real rate + beta x ERP.
B44: Earnings level shock of the scenario (Box Earnings) | C44: ='Box Earnings'!C21 -> -0.17393634 | D44: ='Box Earnings'!D21 -> 0 | E44: ='Box Earnings'!E21 -> 0.17393634 | J44: Domestic boxes: normalized earnings beta x the Ibovespa ex-Commodities shock; Commodities: price elasticity x commodity prices (Assumptions section 8). Zero in the base.
B45: Starting growth of the fade = consensus 2026-28 (capped; g if BoxGrowth = 0) | C45: =IF(BoxGrowth=1,'Box Shares'!$I$44,gLT) -> 0.047 | D45: =IF(BoxGrowth=1,'Box Shares'!$I$44,gLT) -> 0.047 | E45: =IF(BoxGrowth=1,'Box Shares'!$I$44,gLT) -> 0.047 | J45: Growth fades from this to g over FadeYears after 2031 (H = FadeYears / 2); the same in every scenario.
B46: FCFF 2031 in the scenario = FCFF 2031 x (1 + shock) | C46: =$H$38*(1+C44) -> 4397.3945 | D46: =$H$38*(1+D44) -> 5323.3119 | E46: =$H$38*(1+E44) -> 6249.2293
B47: Value at end-2031 of the FCFF after 2031 (FadeMode 0: H-model formula; 1-2: Box Fade) | C47: =C46*((1+gLT)+FadeYears/2*(C45-gLT))/(C43-gLT) -> 43051.315 | D47: =D46*((1+gLT)+FadeYears/2*(D45-gLT))/(D43-gLT) -> 62243.353 | E47: =E46*((1+gLT)+FadeYears/2*(E45-gLT))/(E43-gLT) -> 85035.33 | J47: FadeMode 0: flow 2031 x [(1 + g) + H x (starting growth - g)] / (rate - g). 1: year by year; 2: year by year with growth paid (Box Fade).
B48: Periods the TV is discounted | C48: =5-FixTV -> 5 | D48: =5-FixTV -> 5 | E48: =5-FixTV -> 5
B49: Present value of FCFF 2028-2031 (each year x (1 + shock)) | C49: =(1+C44)*NPV(C43,$E$38:$H$38) -> 11304.834 | D49: =(1+D44)*NPV(D43,$E$38:$H$38) -> 14194.38 | E49: =(1+E44)*NPV(E43,$E$38:$H$38) -> 17119.131
B50: Present value of the terminal value | C50: =C47/(1+C43)^C48 -> 21040.841 | D50: =D47/(1+D43)^D48 -> 32821.774 | E50: =E47/(1+E43)^E48 -> 47410.702
B51: Value of the FCFF | C51: =C49+C50 -> 32345.675 | D51: =D49+D50 -> 47016.154 | E51: =E49+E50 -> 64529.832
B52: Net debt subtracted (switch FixND) | C52: =IF(FixND=1,NDmult*DCF!$M$21*$C$22,0) -> 0 | D52: =IF(FixND=1,NDmult*DCF!$M$21*$C$22,0) -> 0 | E52: =IF(FixND=1,NDmult*DCF!$M$21*$C$22,0) -> 0 | J52: 1.6x the house EBITDA of 2025 x the box's 2026 EBITDA share, only with FixND = 1.
B53: Value by the house mechanics (FCFF) | C53: =C51-C52 -> 32345.675 | D53: =D51-D52 -> 47016.154 | E53: =E51-E52 -> 64529.832 | J53: Financials: shown for the reconciliation with the house value; not used.
B54: FCFE 2031 in the scenario = FCFE 2031 x (1 + shock) | C54: =$H$40*(1+C44) -> 5347.9824 | D54: =$H$40*(1+D44) -> 6474.056 | E54: =$H$40*(1+E44) -> 7600.1296
B55: Value at end-2031 of the FCFE after 2031 (FadeMode 0: H-model formula; 1-2: Box Fade) | C55: =IF(FadeMode=0,C54*((1+gLT)+FadeYears/2*(C45-gLT))/(C43-gLT),'Box Fade'!$C$26) -> 52357.748 | D55: =IF(FadeMode=0,D54*((1+gLT)+FadeYears/2*(D45-gLT))/(D43-gLT),'Box Fade'!$C$36) -> 75698.543 | E55: =IF(FadeMode=0,E54*((1+gLT)+FadeYears/2*(E45-gLT))/(E43-gLT),'Box Fade'!$C$46) -> 103417.48
B56: Present value of FCFE 2028-2031 (each year x (1 + shock)) | C56: =(1+C44)*NPV(C43,$E$40:$H$40) -> 13748.608 | D56: =(1+D44)*NPV(D43,$E$40:$H$40) -> 17262.789 | E56: =(1+E44)*NPV(E43,$E$40:$H$40) -> 20819.785
B57: Present value of the FCFE terminal value | C57: =C55/(1+C43)^C48 -> 25589.254 | D57: =D55/(1+D43)^D48 -> 39916.881 | E57: =E55/(1+E43)^E48 -> 57659.507
B58: Value by FCFE | C58: =C56+C57 -> 39337.863 | D58: =D56+D57 -> 57179.67 | E58: =E56+E57 -> 78479.292
B59: Box value, own mechanics | C59: =C58 -> 39337.863 | D59: =D58 -> 57179.67 | E59: =E58 -> 78479.292 | J59: FCFF value (Financials: FCFE value).
B60: Index points today | C60: ='Box Shares'!$C$7 -> 60927.304 | D60: ='Box Shares'!$C$7 -> 60927.304 | E60: ='Box Shares'!$C$7 -> 60927.304
B61: Upside, own value | C61: =C59/C60-1 -> -0.35434755 | D61: =D59/D60-1 -> -0.061509922 | E61: =E59/E60-1 -> 0.28808083
B62: Fair value at the end of 2027 (scaled) | C62: =C59*C$10 -> 39337.863 | D62: =D59*D$10 -> 57179.67 | E62: =E59*E$10 -> 78479.292 | J62: Own value x factor applied (top of the sheet).
B63: Upside | C63: =C62/C60-1 -> -0.35434755 | D63: =D62/D60-1 -> -0.061509922 | E63: =E62/E60-1 -> 0.28808083
B64: Starting growth priced in by today's index points (reverse DCF) | C64: =C45+(C60-C59)/(C54*FadeYears/2/((C43-gLT)*(1+C43)^C48)) -> 0.22366904 | D64: =D45+(D60-D59)/(D54*FadeYears/2/((D43-gLT)*(1+D43)^D48)) -> 0.066659715 | E64: =E45+(E60-E59)/(E54*FadeYears/2/((E43-gLT)*(1+E43)^E48)) -> -0.016742938 | J64: Starting growth + (points - own value) / (flow 2031 x H / ((rate - g) x (1 + rate)^periods)): exact with the H-model formula, first order with the year-by-year fade.
B65: Memo: house discount rate (DCF sheet) | C65: =DCF!C48 -> 0.145 | D65: =DCF!D48 -> 0.1276 | E65: =DCF!E48 -> 0.115
B66: Memo: value of the FCFF at the house rate (house mechanics) | C66: =NPV(C65,$E$35:$H$35)+$H$35*(1+gLT)/(C65-gLT)/(1+C65)^C48-C52 -> 58254.029 | D66: =NPV(D65,$E$35:$H$35)+$H$35*(1+gLT)/(D65-gLT)/(1+D65)^D48-D52 -> 71550.322 | E66: =NPV(E65,$E$35:$H$35)+$H$35*(1+gLT)/(E65-gLT)/(1+E65)^E48-E52 -> 85507.976 | J66: Same FCFF at the house rate: the four boxes add up to the house value exactly (Checks).
B67: Memo: box value at the house rate (Financials by FCFE) | C67: =NPV(C65,$E$40:$H$40)+$H$40*(1+gLT)/(C65-gLT)/(1+C65)^C48 -> 52102.715 | D67: =NPV(D65,$E$40:$H$40)+$H$40*(1+gLT)/(D65-gLT)/(1+D65)^D48 -> 63728.962 | E67: =NPV(E65,$E$40:$H$40)+$H$40*(1+gLT)/(E65-gLT)/(1+E65)^E48 -> 75924.641 | J67: The box as in the house (one rate); Summary compares it with the box-rate value.
B70: Defensives (house FCFF)
C71: 2026 | D71: 2027 | E71: 2028 | F71: 2029 | G71: 2030 | H71: 2031 | J71: How it is calculated
B72: Share of sales | C72: ='Box Shares'!D20 -> 0.25320998 | D72: ='Box Shares'!E20 -> 0.26048992 | E72: =D72 -> 0.26048992 | F72: =E72 -> 0.26048992 | G72: =F72 -> 0.26048992 | H72: =G72 -> 0.26048992 | J72: Box Shares: 2026-27 consensus; 2028+ as 2027 (the house projects sales from 2027).
B73: Sales | C73: =DCF!N13*C72 -> 40240.383 | D73: =DCF!O13*D72 -> 42660.173 | E73: =DCF!P13*E72 -> 45253.912 | F73: =DCF!Q13*F72 -> 48005.35 | G73: =DCF!R13*G72 -> 50924.075 | H73: =DCF!S13*H72 -> 54020.259 | J73: House sales (DCF sheet) x share.
B74: Share of EBIT | C74: ='Box Shares'!G20 -> 0.20945024 | D74: ='Box Shares'!H20 -> 0.23407448 | E74: ='Box Shares'!I20 -> 0.24415677 | F74: =E74 -> 0.24415677 | G74: =F74 -> 0.24415677 | H74: =G74 -> 0.24415677 | J74: Box Shares: 2026-28 consensus; 2029+ as 2028.
B75: EBIT | C75: =DCF!N19*C74 -> 6928.614 | D75: =DCF!O19*D74 -> 8165.2202 | E75: =DCF!P19*E74 -> 9112.4215 | F75: =DCF!Q19*F74 -> 9666.4567 | G75: =DCF!R19*G74 -> 10254.177 | H75: =DCF!S19*H74 -> 10877.631
B76: Share of EBITDA | C76: ='Box Shares'!J20 -> 0.19172465 | D76: ='Box Shares'!K20 -> 0.21119668 | E76: ='Box Shares'!L20 -> 0.22223939 | F76: =E76 -> 0.22223939 | G76: =F76 -> 0.22223939 | H76: =G76 -> 0.22223939 | J76: Box Shares: 2026-28; 2029+ as 2028. Financials includes the EBITDA the index imputes to banks.
B77: EBITDA | C77: =DCF!N21*C76 -> 9456.6268 | D77: =DCF!O21*D76 -> 10711.262 | E77: =DCF!P21*E76 -> 11555.78 | F77: =DCF!Q21*F76 -> 12286.863 | G77: =DCF!R21*G76 -> 13033.904 | H77: =DCF!S21*H76 -> 13826.366
B78: Share of capex | C78: ='Box Shares'!P20 -> 0.2478664 | D78: ='Box Shares'!Q20 -> 0.24129138 | E78: =D78 -> 0.24129138 | F78: =E78 -> 0.24129138 | G78: =F78 -> 0.24129138 | H78: =G78 -> 0.24129138 | J78: Box Shares: 2026-27; 2028+ as 2027.
B79: Capex | C79: =DCF!N33*C78 -> -4748.8724 | D79: =DCF!O33*D78 -> -4664.8863 | E79: =DCF!P33*E78 -> -4611.0486 | F79: =DCF!Q33*F78 -> -4891.4004 | G79: =DCF!R33*G78 -> -4245.3798 | H79: =DCF!S33*H78 -> -4503.4989
B80: Share of net income | C80: ='Box Shares'!M20 -> 0.14197048 | D80: ='Box Shares'!N20 -> 0.17585707 | E80: ='Box Shares'!O20 -> 0.19377661 | F80: =E80 -> 0.19377661 | G80: =F80 -> 0.19377661 | H80: =G80 -> 0.19377661 | J80: Box Shares: 2026-28; 2029+ as 2028.
B81: Net income | C81: =DCF!N29*C80 -> 2975.4173 | D81: =DCF!O29*D80 -> 3810.1192 | E81: =DCF!P29*E80 -> 4491.1605 | F81: =DCF!Q29*F80 -> 4764.2231 | G81: =DCF!R29*G80 -> 5053.8878 | H81: =DCF!S29*H80 -> 5361.1642
B82: D&A = EBITDA - EBIT | C82: =C77-C75 -> 2528.0128 | D82: =D77-D75 -> 2546.0418 | E82: =E77-E75 -> 2443.3581 | F82: =F77-F75 -> 2620.4064 | G82: =G77-G75 -> 2779.7271 | H82: =H77-H75 -> 2948.7345
B83: Tax rate (house) | C83: =DCF!N25 -> -0.24 | D83: =DCF!O25 -> -0.24 | E83: =DCF!P25 -> -0.24 | F83: =DCF!Q25 -> -0.24 | G83: =DCF!R25 -> -0.24 | H83: =DCF!S25 -> -0.24 | J83: DCF sheet (house, -24%).
B84: NOPAT = EBIT x (1 + tax rate) | C84: =C75*(1+C83) -> 5265.7466 | D84: =D75*(1+D83) -> 6205.5673 | E84: =E75*(1+E83) -> 6925.4403 | F84: =F75*(1+F83) -> 7346.5071 | G84: =G75*(1+G83) -> 7793.1747 | H84: =H75*(1+H83) -> 8266.9998
B85: Working capital (NWC) = -NWC % x sales | C85: =-NWCpct*C73 -> -1609.6153 | D85: =-NWCpct*D73 -> -1706.4069 | E85: =-NWCpct*E73 -> -1810.1565 | F85: =-NWCpct*F73 -> -1920.214 | G85: =-NWCpct*G73 -> -2036.963 | H85: =-NWCpct*H73 -> -2160.8103
B86: Change in NWC | D86: =D85-C85 -> -96.791621 | E86: =E85-D85 -> -103.74954 | F86: =F85-E85 -> -110.05751 | G86: =G85-F85 -> -116.74901 | H86: =H85-G85 -> -123.84735
B87: FCFF, house = D&A + NOPAT + capex + NWC (level) | C87: =C82+C84+C79+C85 -> 1435.2717 | D87: =D82+D84+D79+D85 -> 2380.3159 | E87: =E82+E84+E79+E85 -> 2947.5933 | F87: =F82+F84+F79+F85 -> 3155.2991 | G87: =G82+G84+G79+G85 -> 4290.559 | H87: =H82+H84+H79+H85 -> 4551.425
B88: FCFF with the change in NWC | D88: =D82+D84+D79+D86 -> 3989.9312 | E88: =E82+E84+E79+E86 -> 4654.0003 | F88: =F82+F84+F79+F86 -> 4965.4556 | G88: =G82+G84+G79+G86 -> 6210.773 | H88: =H82+H84+H79+H86 -> 6588.388
B89: FCFF, house mechanics (switch FixNWC) | C89: =C87 -> 1435.2717 | D89: =IF(FixNWC=1,D88,D87) -> 2380.3159 | E89: =IF(FixNWC=1,E88,E87) -> 2947.5933 | F89: =IF(FixNWC=1,F88,F87) -> 3155.2991 | G89: =IF(FixNWC=1,G88,G87) -> 4290.559 | H89: =IF(FixNWC=1,H88,H87) -> 4551.425 | J89: FixNWC = 0: house row; 1: corrected row. Sum of the boxes = house FCFF (Checks); used for the house-rate memo.
B90: Capex funding growth = -(D&A + growth x NOPAT / ROE) | C90: =C79 -> -4748.8724 | D90: =D79 -> -4664.8863 | E90: =-(E82+DCF!P11*E84/'Box Shares'!$E$45) -> -5388.9925 | F90: =-(F82+DCF!Q11*F84/'Box Shares'!$E$45) -> -5745.1353 | G90: =-(G82+DCF!R11*G84/'Box Shares'!$E$45) -> -6094.4396 | H90: =-(H82+DCF!S11*H84/'Box Shares'!$E$45) -> -6464.9815 | J90: 2028+: D&A + the reinvestment that funds the year's growth (house sales growth) at the box's FY28 ROE (Box Shares section 5); 2026-27: consensus.
B91: FCFF, box rules = D&A + NOPAT + capex funding growth + change in NWC | C91: =C87 -> 1435.2717 | D91: =D82+D84+D90+D86 -> 3989.9312 | E91: =E82+E84+E90+E86 -> 3876.0564 | F91: =F82+F84+F90+F86 -> 4111.7206 | G91: =G82+G84+G90+G86 -> 4361.7132 | H91: =H82+H84+H90+H86 -> 4626.9054
B92: FCFF used for the box value (switch BoxCF) | C92: =IF(BoxCF=1,C91,C89) -> 1435.2717 | D92: =IF(BoxCF=1,D91,D89) -> 3989.9312 | E92: =IF(BoxCF=1,E91,E89) -> 3876.0564 | F92: =IF(BoxCF=1,F91,F89) -> 4111.7206 | G92: =IF(BoxCF=1,G91,G89) -> 4361.7132 | H92: =IF(BoxCF=1,H91,H89) -> 4626.9054 | J92: BoxCF = 1: box rules (row above); 0: the house mechanics.
B94: Valuation at the end of 2027 | C94: Bear | D94: Base | E94: Bull
B95: Discount rate of the box (Box Rates) | C95: ='Box Rates'!C22 -> 0.14072044 | D95: ='Box Rates'!D22 -> 0.12332044 | E95: ='Box Rates'!E22 -> 0.11072044 | J95: BoxRate 0: the house rate; 1: g + (house rate - g) x the box's relative cash yield, at least real rate + floor; 2: CAPM, real rate + beta x ERP.
B96: Earnings level shock of the scenario (Box Earnings) | C96: ='Box Earnings'!C22 -> -0.15603811 | D96: ='Box Earnings'!D22 -> 0 | E96: ='Box Earnings'!E22 -> 0.15603811 | J96: Domestic boxes: normalized earnings beta x the Ibovespa ex-Commodities shock; Commodities: price elasticity x commodity prices (Assumptions section 8). Zero in the base.
B97: Starting growth of the fade = consensus 2026-28 (capped; g if BoxGrowth = 0) | C97: =IF(BoxGrowth=1,'Box Shares'!$I$45,gLT) -> 0.047 | D97: =IF(BoxGrowth=1,'Box Shares'!$I$45,gLT) -> 0.047 | E97: =IF(BoxGrowth=1,'Box Shares'!$I$45,gLT) -> 0.047 | J97: Growth fades from this to g over FadeYears after 2031 (H = FadeYears / 2); the same in every scenario.
B98: FCFF 2031 in the scenario = FCFF 2031 x (1 + shock) | C98: =$H$92*(1+C96) -> 3904.9318 | D98: =$H$92*(1+D96) -> 4626.9054 | E98: =$H$92*(1+E96) -> 5348.879
B99: Value at end-2031 of the FCFF after 2031 (FadeMode 0: H-model formula; 1-2: Box Fade) | C99: =IF(FadeMode=0,C98*((1+gLT)+FadeYears/2*(C97-gLT))/(C95-gLT),'Box Fade'!$C$56) -> 43624.035 | D99: =IF(FadeMode=0,D98*((1+gLT)+FadeYears/2*(D97-gLT))/(D95-gLT),'Box Fade'!$C$66) -> 63474.085 | E99: =IF(FadeMode=0,E98*((1+gLT)+FadeYears/2*(E97-gLT))/(E95-gLT),'Box Fade'!$C$76) -> 87888.227 | J99: FadeMode 0: flow 2031 x [(1 + g) + H x (starting growth - g)] / (rate - g). 1: year by year; 2: year by year with growth paid (Box Fade).
B100: Periods the TV is discounted | C100: =5-FixTV -> 5 | D100: =5-FixTV -> 5 | E100: =5-FixTV -> 5
B101: Present value of FCFF 2028-2031 (each year x (1 + shock)) | C101: =(1+C96)*NPV(C95,$E$92:$H$92) -> 10320.629 | D101: =(1+D96)*NPV(D95,$E$92:$H$92) -> 12692.025 | E101: =(1+E96)*NPV(E95,$E$92:$H$92) -> 15081.148
B102: Present value of the terminal value | C102: =C99/(1+C95)^C100 -> 22585.5 | D102: =D99/(1+D95)^D100 -> 35487.724 | E102: =E99/(1+E95)^E100 -> 51988.452
B103: Value of the FCFF | C103: =C101+C102 -> 32906.129 | D103: =D101+D102 -> 48179.749 | E103: =E101+E102 -> 67069.6
B104: Net debt subtracted (switch FixND) | C104: =IF(FixND=1,NDmult*DCF!$M$21*$C$76,0) -> 0 | D104: =IF(FixND=1,NDmult*DCF!$M$21*$C$76,0) -> 0 | E104: =IF(FixND=1,NDmult*DCF!$M$21*$C$76,0) -> 0 | J104: 1.6x the house EBITDA of 2025 x the box's 2026 EBITDA share, only with FixND = 1.
B105: Value by the house mechanics (FCFF) | C105: =C103-C104 -> 32906.129 | D105: =D103-D104 -> 48179.749 | E105: =E103-E104 -> 67069.6 | J105: Financials: shown for the reconciliation with the house value; not used.
...

Sheet Multiples by Box
B1: Ibovespa - Target by box: house multiples, bottom-up and the average of the methods (end-2027)
B2: House Target methods for 2027 split by box: P/E and EV/EBITDA at each box's 10y relative multiple (calibrated to the house value), bottom-up from the analysts' TPs.
B3: Legend: | C3: input | D3: assumption | E3: formula
B5: 1. House methods for the Ibovespa, end-2027 (Target rows 67-90)
C6: Bear | D6: Base | E6: Bull
B7: Target P/E on 2027 EPS (Assumptions) | C7: =Assumptions!C53 -> 7.5 | D7: =Assumptions!D53 -> 10 | E7: =Assumptions!E53 -> 12
B8: EPS 2027, house (DCF sheet) | C8: =DCF!$O$29 -> 21666 | D8: =DCF!$O$29 -> 21666 | E8: =DCF!$O$29 -> 21666
B9: P/E method = target P/E x EPS 2027 | C9: =C7*C8 -> 162495 | D9: =D7*D8 -> 216660 | E9: =E7*E8 -> 259992
B10: Target EV/EBITDA on 2027 EBITDA (Assumptions) | C10: =Assumptions!C54 -> 4.5 | D10: =Assumptions!D54 -> 5.5 | E10: =Assumptions!E54 -> 6
B11: EBITDA 2027, house (DCF sheet) | C11: =DCF!$O$21 -> 50717 | D11: =DCF!$O$21 -> 50717 | E11: =DCF!$O$21 -> 50717
B12: Net debt = 1.6x EBITDA 2025 (house) | C12: =NDmult*DCF!$M$21 -> 54081.6 | D12: =NDmult*DCF!$M$21 -> 54081.6 | E12: =NDmult*DCF!$M$21 -> 54081.6
B13: EV/EBITDA method = target x EBITDA 2027 - net debt | C13: =C10*C11-C12 -> 174144.9 | D13: =D10*D11-D12 -> 224861.9 | E13: =E10*E11-E12 -> 250220.4
B14: Bottom-up: members at the analysts' target prices (section 4) | C14: =C50 -> 179149.45 | D14: =D50 -> 223936.81 | E14: =E50 -> 268724.17
B15: DCF: Ibovespa by box (DCF by Box; = the house DCF in the base) | C15: ='DCF by Box'!C11 -> 142019.58 | D15: ='DCF by Box'!D11 -> 223818.52 | E15: ='DCF by Box'!E11 -> 327135.92
B16: Average of the methods (weights in Assumptions) | C16: =(WDCF*C15+WPE*C9+WEV*C13+WBU*C14)/(WDCF+WPE+WEV+WBU) -> 164452.23 | D16: =(WDCF*D15+WPE*D9+WEV*D13+WBU*D14)/(WDCF+WPE+WEV+WBU) -> 222319.31 | E16: =(WDCF*E15+WPE*E9+WEV*E13+WBU*E14)/(WDCF+WPE+WEV+WBU) -> 276518.12
B17: Ibovespa used | C17: =IbovUsed -> 208431.92 | D17: =IbovUsed -> 208431.92 | E17: =IbovUsed -> 208431.92
B18: Upside of the average | C18: =C16/C17-1 -> -0.21100266 | D18: =D16/D17-1 -> 0.066627924 | E18: =E16/E17-1 -> 0.32665919
B20: 2. P/E method by box: house P/E x the box's 10y relative P/E, calibrated to the house value
B21: Group | C21: Bear | D21: Base | E21: Bull | G21: Relative P/E (10y average) | H21: EPS 2027 (pts) | I21: P/E today on 2027 EPS | J21: Target P/E, base
B22: Calibration: house P/E value / sum of (relative P/E x box EPS) | C22: =C9/SUMPRODUCT($G$23:$G$26,$H$23:$H$26) -> 7.131865 | D22: =D9/SUMPRODUCT($G$23:$G$26,$H$23:$H$26) -> 9.5091533 | E22: =E9/SUMPRODUCT($G$23:$G$26,$H$23:$H$26) -> 11.410984
B23: Financials | C23: =C$22*$G23*$H23 -> 42231.483 | D23: =D$22*$G23*$H23 -> 56308.644 | E23: =E$22*$G23*$H23 -> 67570.373 | G23: =IF(RelMult=1,$P$68,1) -> 0.9271344 | H23: =DCF!$O$29*'Box Shares'!N19 -> 6386.9061 | I23: ='Box Shares'!$C$7/H23 -> 9.5394081 | J23: =D$22*G23 -> 8.8162631
B24: Defensives | C24: =C$22*$G24*$H24 -> 40701.435 | D24: =D$22*$G24*$H24 -> 54268.581 | E24: =E$22*$G24*$H24 -> 65122.297 | G24: =IF(RelMult=1,$Q$68,1) -> 1.4978491 | H24: =DCF!$O$29*'Box Shares'!N20 -> 3810.1192 | I24: ='Box Shares'!$C$8/H24 -> 14.651082 | J24: =D$22*G24 -> 14.243276
B25: Cyclicals | C25: =C$22*$G25*$H25 -> 27136.85 | D25: =D$22*$G25*$H25 -> 36182.467 | E25: =E$22*$G25*$H25 -> 43418.96 | G25: =IF(RelMult=1,$R$68,1) -> 1.9750615 | H25: =DCF!$O$29*'Box Shares'!N21 -> 1926.5297 | I25: ='Box Shares'!$C$9/H25 -> 13.636476 | J25: =D$22*G25 -> 18.781163
B26: Commodities | C26: =C$22*$G26*$H26 -> 52425.231 | D26: =D$22*$G26*$H26 -> 69900.308 | E26: =E$22*$G26*$H26 -> 83880.37 | G26: =IF(RelMult=1,$S$68,1) -> 0.77033136 | H26: =DCF!$O$29*'Box Shares'!N22 -> 9542.4451 | I26: ='Box Shares'!$C$10/H26 -> 6.8547604 | J26: =D$22*G26 -> 7.3251989
B27: Ibovespa | C27: =SUM(C23:C26) -> 162495 | D27: =SUM(D23:D26) -> 216660 | E27: =SUM(E23:E26) -> 259992 | H27: =SUM(H23:H26) -> 21666 | I27: ='Box Shares'!$C$11/H27 -> 9.6202308
B28: Memo (inside Cyclicals; own relative multiple, not additive)
B29: Cyclicals ex-WEG & Embraer | C29: =C$22*$G29*$H29 -> 18929.412 | D29: =D$22*$G29*$H29 -> 25239.216 | E29: =E$22*$G29*$H29 -> 30287.059 | G29: =IF(RelMult=1,$T$68,1) -> 1.7945678 | H29: =DCF!$O$29*'Box Shares'!N25 -> 1479.0203 | I29: ='Box Shares'!$C$14/H29 -> 10.862947 | J29: =D$22*G29 -> 17.06482
B30: WEG & Embraer | C30: =C$22*$G30*$H30 -> 9769.6387 | D30: =D$22*$G30*$H30 -> 13026.185 | E30: =E$22*$G30*$H30 -> 15631.422 | G30: =IF(RelMult=1,$U$68,1) -> 3.0610703 | H30: =DCF!$O$29*'Box Shares'!N26 -> 447.50933 | I30: ='Box Shares'!$C$15/H30 -> 22.803 | J30: =D$22*G30 -> 29.108186
B32: 3. EV/EBITDA method by box: house multiple x the box's 10y relative EV/EBITDA, calibrated (Financials: P/E value)
B33: Group | C33: Bear | D33: Base | E33: Bull | G33: Relative EV/EBITDA (10y average) | H33: EBITDA 2027 (pts) | I33: Net debt (pts) | J33: Target EV/EBITDA, base
B34: Calibration: (house value - Financials + others' net debt) / boxes' EV | C34: =(C13-C35+SUM($I$36:$I$38))/(C10*SUMPRODUCT($G$36:$G$38,$H$36:$H$38)) -> 0.96889776 | D34: =(D13-D35+SUM($I$36:$I$38))/(D10*SUMPRODUCT($G$36:$G$38,$H$36:$H$38)) -> 0.9612438 | E34: =(E13-E35+SUM($I$36:$I$38))/(E10*SUMPRODUCT($G$36:$G$38,$H$36:$H$38)) -> 0.94056955
B35: Financials (P/E value: EV/EBITDA does not apply) | C35: =C23 -> 42231.483 | D35: =D23 -> 56308.644 | E35: =E23 -> 67570.373
B36: Defensives | C36: =C$34*C$10*$G36*$H36-$I36 -> 53979.19 | D36: =D$34*D$10*$G36*$H36-$I36 -> 67657.449 | E36: =E$34*E$10*$G36*$H36-$I36 -> 72920.008 | G36: =IF(RelMult=1,$V$68,1) -> 1.3778556 | H36: =DCF!$O$21*'Box Shares'!K20 -> 10711.262 | I36: =NDmult*DCF!$M$21*'Box Shares'!J20 -> 10368.776 | J36: =D$34*D$10*G36 -> 7.2845035
B37: Cyclicals | C37: =C$34*C$10*$G37*$H37-$I37 -> 30868.834 | D37: =D$34*D$10*$G37*$H37-$I37 -> 38413.223 | E37: =E$34*E$10*$G37*$H37-$I37 -> 41315.843 | G37: =IF(RelMult=1,$W$68,1) -> 1.7471493 | H37: =DCF!$O$21*'Box Shares'!K21 -> 4659.1593 | I37: =NDmult*DCF!$M$21*'Box Shares'!J21 -> 4622.9672 | J37: =D$34*D$10*G37 -> 9.2369003
B38: Commodities | C38: =C$34*C$10*$G38*$H38-$I38 -> 47065.393 | D38: =D$34*D$10*$G38*$H38-$I38 -> 62482.584 | E38: =E$34*E$10*$G38*$H38-$I38 -> 68414.177 | G38: =IF(RelMult=1,$X$68,1) -> 0.73545865 | H38: =DCF!$O$21*'Box Shares'!K22 -> 22618.328 | I38: =NDmult*DCF!$M$21*'Box Shares'!J22 -> 25463.195 | J38: =D$34*D$10*G38 -> 3.8882529
B39: Ibovespa | C39: =SUM(C35:C38) -> 174144.9 | D39: =SUM(D35:D38) -> 224861.9 | E39: =SUM(E35:E38) -> 250220.4 | H39: =SUM(H35:H38) -> 37988.749 | I39: =SUM(I35:I38) -> 40454.938
B40: Memo (inside Cyclicals; own relative multiple, not additive)
B41: Cyclicals ex-WEG & Embraer | C41: =C$34*C$10*$G41*$H41-$I41 -> 22936.909 | D41: =D$34*D$10*$G41*$H41-$I41 -> 28647.415 | E41: =E$34*E$10*$G41*$H41-$I41 -> 30844.468 | G41: =IF(RelMult=1,$Y$68,1) -> 1.567039 | H41: =DCF!$O$21*'Box Shares'!K25 -> 3931.9528 | I41: =NDmult*DCF!$M$21*'Box Shares'!J25 -> 3927.5796 | J41: =D$34*D$10*G41 -> 8.2846859
B42: WEG & Embraer | C42: =C$34*C$10*$G42*$H42-$I42 -> 8497.8998 | D42: =D$34*D$10*$G42*$H42-$I42 -> 10452.09 | E42: =E$34*E$10*$G42*$H42-$I42 -> 11203.943 | G42: =IF(RelMult=1,$Z$68,1) -> 2.8994967 | H42: =DCF!$O$21*'Box Shares'!K26 -> 727.20651 | I42: =NDmult*DCF!$M$21*'Box Shares'!J26 -> 695.38762 | J42: =D$34*D$10*G42 -> 15.329178
B44: 4. Bottom-up by box: the members at the analysts' 12m target prices (Members), x (1 + change) in the bear / bull
B45: Group | C45: Bear | D45: Base | E45: Bull | G45: Index points with a target price | H45: Index points at the target price | I45: Upside of the covered members
B46: Financials | C46: ='Box Shares'!$C$7*(1+$I46)*(1+Assumptions!C$55) -> 44914.963 | D46: ='Box Shares'!$C$7*(1+$I46)*(1+Assumptions!D$55) -> 56143.703 | E46: ='Box Shares'!$C$7*(1+$I46)*(1+Assumptions!E$55) -> 67372.444 | G46: =SUMIFS(Members!$AV$6:$AV$81,Members!$C$6:$C$81,"Financials") -> 60927.304 | H46: =SUMIFS(Members!$AW$6:$AW$81,Members!$C$6:$C$81,"Financials") -> 56143.703 | I46: =H46/G46-1 -> -0.078513243
B47: Defensives | C47: ='Box Shares'!$C$8*(1+$I47)*(1+Assumptions!C$55) -> 50367.076 | D47: ='Box Shares'!$C$8*(1+$I47)*(1+Assumptions!D$55) -> 62958.845 | E47: ='Box Shares'!$C$8*(1+$I47)*(1+Assumptions!E$55) -> 75550.614 | G47: =SUMIFS(Members!$AV$6:$AV$81,Members!$C$6:$C$81,"Defensives") -> 55822.367 | H47: =SUMIFS(Members!$AW$6:$AW$81,Members!$C$6:$C$81,"Defensives") -> 62958.845 | I47: =H47/G47-1 -> 0.12784261
B48: Cyclicals | C48: ='Box Shares'!$C$9*(1+$I48)*(1+Assumptions!C$55) -> 25071.054 | D48: ='Box Shares'!$C$9*(1+$I48)*(1+Assumptions!D$55) -> 31338.818 | E48: ='Box Shares'!$C$9*(1+$I48)*(1+Assumptions!E$55) -> 37606.581 | G48: =SUMIFS(Members!$AV$6:$AV$81,Members!$C$6:$C$81,"Cyclicals") -> 26271.075 | H48: =SUMIFS(Members!$AW$6:$AW$81,Members!$C$6:$C$81,"Cyclicals") -> 31338.818 | I48: =H48/G48-1 -> 0.19290201
B49: Commodities | C49: ='Box Shares'!$C$10*(1+$I49)*(1+Assumptions!C$55) -> 58796.353 | D49: ='Box Shares'!$C$10*(1+$I49)*(1+Assumptions!D$55) -> 73495.442 | E49: ='Box Shares'!$C$10*(1+$I49)*(1+Assumptions!E$55) -> 88194.53 | G49: =SUMIFS(Members!$AV$6:$AV$81,Members!$C$6:$C$81,"Commodities") -> 65411.174 | H49: =SUMIFS(Members!$AW$6:$AW$81,Members!$C$6:$C$81,"Commodities") -> 73495.442 | I49: =H49/G49-1 -> 0.12359153
B50: Ibovespa | C50: =SUM(C46:C49) -> 179149.45 | D50: =SUM(D46:D49) -> 223936.81 | E50: =SUM(E46:E49) -> 268724.17 | G50: =SUM(G46:G49) -> 208431.92 | H50: =SUM(H46:H49) -> 223936.81 | I50: =H50/G50-1 -> 0.074388259
B51: Memo (inside Cyclicals)
B52: Cyclicals ex-WEG & Embraer | C52: ='Box Shares'!$C$14*(1+$I52)*(1+Assumptions!C$55) -> 15964.768 | D52: ='Box Shares'!$C$14*(1+$I52)*(1+Assumptions!D$55) -> 19955.96 | E52: ='Box Shares'!$C$14*(1+$I52)*(1+Assumptions!E$55) -> 23947.152 | G52: =SUMIFS(Members!$AV$6:$AV$81,Members!$D$6:$D$81,"Cyclicals ex-WEG & Embraer") -> 16066.52 | H52: =SUMIFS(Members!$AW$6:$AW$81,Members!$D$6:$D$81,"Cyclicals ex-WEG & Embraer") -> 19955.96 | I52: =H52/G52-1 -> 0.24208357
B53: WEG & Embraer | C53: ='Box Shares'!$C$15*(1+$I53)*(1+Assumptions!C$55) -> 9106.2863 | D53: ='Box Shares'!$C$15*(1+$I53)*(1+Assumptions!D$55) -> 11382.858 | E53: ='Box Shares'!$C$15*(1+$I53)*(1+Assumptions!E$55) -> 13659.429 | G53: =SUMIFS(Members!$AV$6:$AV$81,Members!$D$6:$D$81,"WEG & Embraer") -> 10204.555 | H53: =SUMIFS(Members!$AW$6:$AW$81,Members!$D$6:$D$81,"WEG & Embraer") -> 11382.858 | I53: =H53/G53-1 -> 0.11546831
B55: 5. Average of the methods by box (DCF by Box + sections 2-4; weights in Assumptions)
B56: Group | C56: Bear | D56: Base | E56: Bull | G56: Upside: Bear | H56: Base | I56: Bull
B57: Financials | C57: =(WDCF*'DCF by Box'!C62+WPE*C23+WEV*C35+WBU*C46)/(WDCF+WPE+WEV+WBU) -> 42178.948 | D57: =(WDCF*'DCF by Box'!D62+WPE*D23+WEV*D35+WBU*D46)/(WDCF+WPE+WEV+WBU) -> 56485.165 | E57: =(WDCF*'DCF by Box'!E62+WPE*E23+WEV*E35+WBU*E46)/(WDCF+WPE+WEV+WBU) -> 70248.12 | G57: =C57/'Box Shares'!$C$7-1 -> -0.30771681 | H57: =D57/'Box Shares'!$C$7-1 -> -0.072908827 | I57: =E57/'Box Shares'!$C$7-1 -> 0.15298259
B58: Defensives | C58: =(WDCF*'DCF by Box'!C109+WPE*C24+WEV*C36+WBU*C47)/(WDCF+WPE+WEV+WBU) -> 44488.458 | D58: =(WDCF*'DCF by Box'!D109+WPE*D24+WEV*D36+WBU*D47)/(WDCF+WPE+WEV+WBU) -> 58266.156 | E58: =(WDCF*'DCF by Box'!E109+WPE*E24+WEV*E36+WBU*E47)/(WDCF+WPE+WEV+WBU) -> 70165.63 | G58: =C58/'Box Shares'!$C$8-1 -> -0.20303528 | H58: =D58/'Box Shares'!$C$8-1 -> 0.043777943 | I58: =E58/'Box Shares'!$C$8-1 -> 0.25694471
B59: Cyclicals | C59: =(WDCF*'DCF by Box'!C156+WPE*C25+WEV*C37+WBU*C48)/(WDCF+WPE+WEV+WBU) -> 23520.141 | D59: =(WDCF*'DCF by Box'!D156+WPE*D25+WEV*D37+WBU*D48)/(WDCF+WPE+WEV+WBU) -> 31594.945 | E59: =(WDCF*'DCF by Box'!E156+WPE*E25+WEV*E37+WBU*E48)/(WDCF+WPE+WEV+WBU) -> 38674.578 | G59: =C59/'Box Shares'!$C$9-1 -> -0.10471341 | H59: =D59/'Box Shares'!$C$9-1 -> 0.20265141 | I59: =E59/'Box Shares'!$C$9-1 -> 0.47213538
B60: Commodities | C60: =(WDCF*'DCF by Box'!C203+WPE*C26+WEV*C38+WBU*C49)/(WDCF+WPE+WEV+WBU) -> 54264.684 | D60: =(WDCF*'DCF by Box'!D203+WPE*D26+WEV*D38+WBU*D49)/(WDCF+WPE+WEV+WBU) -> 75973.04 | E60: =(WDCF*'DCF by Box'!E203+WPE*E26+WEV*E38+WBU*E49)/(WDCF+WPE+WEV+WBU) -> 97429.794 | G60: =C60/'Box Shares'!$C$10-1 -> -0.17040651 | H60: =D60/'Box Shares'!$C$10-1 -> 0.16146883 | I60: =E60/'Box Shares'!$C$10-1 -> 0.48949769
B61: Ibovespa | C61: =SUM(C57:C60) -> 164452.23 | D61: =SUM(D57:D60) -> 222319.31 | E61: =SUM(E57:E60) -> 276518.12 | G61: =C61/'Box Shares'!$C$11-1 -> -0.21100266 | H61: =D61/'Box Shares'!$C$11-1 -> 0.066627924 | I61: =E61/'Box Shares'!$C$11-1 -> 0.32665919
B62: Memo (inside Cyclicals; not additive)
B63: Cyclicals ex-WEG & Embraer | C63: =(WDCF*'DCF by Box'!C250+WPE*C29+WEV*C41+WBU*C52)/(WDCF+WPE+WEV+WBU) -> 16435.648 | D63: =(WDCF*'DCF by Box'!D250+WPE*D29+WEV*D41+WBU*D52)/(WDCF+WPE+WEV+WBU) -> 22098.909 | E63: =(WDCF*'DCF by Box'!E250+WPE*E29+WEV*E41+WBU*E52)/(WDCF+WPE+WEV+WBU) -> 26950.299 | G63: =C63/'Box Shares'!$C$14-1 -> 0.022975024 | H63: =D63/'Box Shares'!$C$14-1 -> 0.37546338 | I63: =E63/'Box Shares'!$C$14-1 -> 0.67741988
B64: WEG & Embraer | C64: =(WDCF*'DCF by Box'!C297+WPE*C30+WEV*C42+WBU*C53)/(WDCF+WPE+WEV+WBU) -> 7941.7118 | D64: =(WDCF*'DCF by Box'!D297+WPE*D30+WEV*D42+WBU*D53)/(WDCF+WPE+WEV+WBU) -> 10167.611 | E64: =(WDCF*'DCF by Box'!E297+WPE*E30+WEV*E42+WBU*E53)/(WDCF+WPE+WEV+WBU) -> 12000.448 | G64: =C64/'Box Shares'!$C$15-1 -> -0.22174836 | H64: =D64/'Box Shares'!$C$15-1 -> -0.0036203445 | I64: =E64/'Box Shares'!$C$15-1 -> 0.17598931
B66: 6. Monthly 12m fwd P/E and EV/EBITDA (harmonic means of the month's members; Bloomberg panel of the multiples model) and the relative multiples
B67: Month-end | C67: P/E Financials | D67: P/E Defensives | E67: P/E Cyclicals | F67: P/E Commodities | G67: P/E Ibovespa | H67: P/E Cyclicals ex-WEG & Embraer | I67: P/E WEG & Embraer | J67: EV/EBITDA Defensives | K67: EV/EBITDA Cyclicals | L67: EV/EBITDA Commodities | M67: EV/EBITDA Ibovespa ex-Financials | N67: EV/EBITDA Cyclicals ex-WEG & Embraer | O67: EV/EBITDA WEG & Embraer | P67: Relative P/E Financials | Q67: Relative P/E Defensives | R67: Relative P/E Cyclicals | S67: Relative P/E Commodities | T67: Relative P/E Cyclicals ex-WEG & Embraer | U67: Relative P/E WEG & Embraer | V67: Relative EV/EBITDA Defensives | W67: Relative EV/EBITDA Cyclicals | X67: Relative EV/EBITDA Commodities | Y67: Relative EV/EBITDA Cyclicals ex-WEG & Embraer | Z67: Relative EV/EBITDA WEG & Embraer
B68: 10-year average (Oct-16..Sep-26) | C68: =AVERAGE(C70:C189) -> 8.5586988 | D68: =AVERAGE(D70:D189) -> 13.800757 | E68: =AVERAGE(E70:E189) -> 17.91549 | F68: =AVERAGE(F70:F189) -> 7.3723808 | G68: =AVERAGE(G70:G189) -> 9.3601514 | H68: =AVERAGE(H70:H189) -> 16.39791 | I68: =AVERAGE(I70:I189) -> 27.895548 | J68: =AVERAGE(J70:J189) -> 7.7766128 | ... Z68: =AVERAGE(Z70:Z189) -> 2.8994967
B70: 42674 | C70: 10.295554 | D70: 18.503755 | E70: 16.387868 | F70: 16.806755 | G70: 13.902538 | H70: 16.743502 | I70: 14.625264 | J70: 8.9247546 | K70: 10.08616 | L70: 6.796984 | M70: 8.1044439 | N70: 10.349286 | O70: 8.8145667 | P70: =C70/G70 -> 0.74055213 | Q70: =D70/G70 -> 1.3309624 | R70: =E70/G70 -> 1.178768 | S70: =F70/G70 -> 1.2088983 | T70: =H70/G70 -> 1.2043486 | U70: =I70/G70 -> 1.0519852 | V70: =IFERROR(J70/M70,"") -> 1.1012174 | W70: =IFERROR(K70/M70,"") -> 1.2445221 | X70: =IFERROR(L70/M70,"") -> 0.83867371 | Y70: =IFERROR(N70/M70,"") -> 1.276989 | Z70: =IFERROR(O70/M70,"") -> 1.0876214
B71: 42704 | C71: 9.0911916 | D71: 16.929441 | E71: 14.519825 | F71: 17.568017 | G71: 12.919309 | H71: 14.784773 | I71: 13.249618 | J71: 8.3949386 | K71: 9.2537111 | L71: 6.7297213 | M71: 7.6869613 | N71: 9.51532 | O71: 8.0671879 | P71: =C71/G71 -> 0.70369023 | Q71: =D71/G71 -> 1.3103983 | R71: =E71/G71 -> 1.1238855 | S71: =F71/G71 -> 1.3598264 | T71: =H71/G71 -> 1.1443935 | U71: =I71/G71 -> 1.0255671 | V71: =IFERROR(J71/M71,"") -> 1.0921011 | W71: =IFERROR(K71/M71,"") -> 1.2038191 | X71: =IFERROR(L71/M71,"") -> 0.87547224 | Y71: =IFERROR(N71/M71,"") -> 1.2378519 | Z71: =IFERROR(O71/M71,"") -> 1.0494638
B72: 42735 | C72: 8.7867066 | D72: 16.406791 | E72: 14.432757 | F72: 13.410483 | G72: 11.852446 | H72: 14.77012 | I72: 12.79034 | J72: 8.2101124 | K72: 9.0283596 | L72: 5.8648987 | M72: 7.1320866 | N72: 9.3200401 | O72: 7.6775338 | P72: =C72/G72 -> 0.74134121 | Q72: =D72/G72 -> 1.3842536 | R72: =E72/G72 -> 1.2177028 | S72: =F72/G72 -> 1.1314528 | T72: =H72/G72 -> 1.2461664 | U72: =I72/G72 -> 1.0791309 | V72: =IFERROR(J72/M72,"") -> 1.1511515 | W72: =IFERROR(K72/M72,"") -> 1.2658791 | X72: =IFERROR(L72/M72,"") -> 0.82232577 | Y72: =IFERROR(N72/M72,"") -> 1.3067761 | Z72: =IFERROR(O72/M72,"") -> 1.0764779
B73: 42766 | C73: 9.5839387 | D73: 17.03897 | E73: 14.867785 | F73: 12.896921 | G73: 12.272067 | H73: 15.049156 | I73: 13.974026 | J73: 8.4453178 | K73: 9.2599139 | L73: 5.8768438 | M73: 7.1815854 | N73: 9.4961517 | O73: 8.179982 | P73: =C73/G73 -> 0.78095551 | Q73: =D73/G73 -> 1.3884352 | R73: =E73/G73 -> 1.2115143 | S73: =F73/G73 -> 1.0509167 | T73: =H73/G73 -> 1.2262934 | U73: =I73/G73 -> 1.1386856 | V73: =IFERROR(J73/M73,"") -> 1.1759684 | W73: =IFERROR(K73/M73,"") -> 1.2893969 | X73: =IFERROR(L73/M73,"") -> 0.81832123 | Y73: =IFERROR(N73/M73,"") -> 1.3222918 | Z73: =IFERROR(O73/M73,"") -> 1.1390218
B74: 42794 | C74: 9.9421974 | D74: 17.151264 | E74: 15.53076 | F74: 11.590751 | G74: 12.170459 | H74: 15.721988 | I74: 14.536796 | J74: 8.6194787 | K74: 9.682191 | L74: 5.809881 | M74: 7.2558077 | N74: 9.9359435 | O74: 8.4666431 | P74: =C74/G74 -> 0.81691228 | Q74: =D74/G74 -> 1.4092536 | R74: =E74/G74 -> 1.2761031 | S74: =F74/G74 -> 0.95236758 | T74: =H74/G74 -> 1.2918155 | U74: =I74/G74 -> 1.1944328 | V74: =IFERROR(J74/M74,"") -> 1.187942 | W74: =IFERROR(K74/M74,"") -> 1.3344057 | X74: =IFERROR(L74/M74,"") -> 0.80072147 | Y74: =IFERROR(N74/M74,"") -> 1.369378 | Z74: =IFERROR(O74/M74,"") -> 1.1668781
B75: 42825 | C75: 9.3905224 | D75: 16.844488 | E75: 15.552675 | F75: 9.7907642 | G75: 11.322715 | H75: 15.698228 | I75: 14.732187 | J75: 8.590388 | K75: 9.7373335 | L75: 5.2092576 | M75: 6.9003284 | N75: 9.9790045 | O75: 8.500732 | P75: =C75/G75 -> 0.82935252 | Q75: =D75/G75 -> 1.4876721 | R75: =E75/G75 -> 1.3735818 | S75: =F75/G75 -> 0.86470109 | T75: =H75/G75 -> 1.3864367 | U75: =I75/G75 -> 1.3011178 | V75: =IFERROR(J75/M75,"") -> 1.2449245 | W75: =IFERROR(K75/M75,"") -> 1.4111406 | X75: =IFERROR(L75/M75,"") -> 0.75492893 | Y75: =IFERROR(N75/M75,"") -> 1.4461637 | Z75: =IFERROR(O75/M75,"") -> 1.2319315
B76: 42855 | C76: 9.5480429 | D76: 17.046795 | E76: 15.985985 | F76: 9.7546359 | G76: 11.511245 | H76: 16.227679 | I76: 14.522848 | J76: 8.7145421 | K76: 9.9683964 | L76: 5.1015667 | M76: 6.9673345 | N76: 10.308468 | O76: 8.1497657 | P76: =C76/G76 -> 0.82945356 | Q76: =D76/G76 -> 1.480882 | R76: =E76/G76 -> 1.3887277 | S76: =F76/G76 -> 0.84740063 | T76: =H76/G76 -> 1.4097241 | U76: =I76/G76 -> 1.2616228 | V76: =IFERROR(J76/M76,"") -> 1.2507713 | W76: =IFERROR(K76/M76,"") -> 1.4307331 | X76: =IFERROR(L76/M76,"") -> 0.73221211 | Y76: =IFERROR(N76/M76,"") -> 1.4795425 | Z76: =IFERROR(O76/M76,"") -> 1.1697107
B77: 42886 | C77: 8.7583796 | D77: 17.896979 | E77: 14.810392 | F77: 8.5899172 | G77: 10.709331 | H77: 14.674589 | I77: 15.620449 | J77: 8.9159821 | K77: 9.574987 | L77: 5.0578492 | M77: 6.9311929 | N77: 9.8210463 | O77: 8.3458816 | P77: =C77/G77 -> 0.81782697 | Q77: =D77/G77 -> 1.6711575 | R77: =E77/G77 -> 1.3829428 | S77: =F77/G77 -> 0.80209654 | T77: =H77/G77 -> 1.370262 | U77: =I77/G77 -> 1.4585831 | V77: =IFERROR(J77/M77,"") -> 1.2863561 | W77: =IFERROR(K77/M77,"") -> 1.3814342 | X77: =IFERROR(L77/M77,"") -> 0.72972276 | Y77: =IFERROR(N77/M77,"") -> 1.4169345 | Z77: =IFERROR(O77/M77,"") -> 1.2041047
B78: 42916 | C78: 8.8736474 | D78: 15.872327 | E78: 14.778719 | F78: 9.0330284 | G78: 10.689413 | H78: 14.797177 | I78: 14.666508 | J78: 8.6079648 | K78: 9.6685815 | L78: 5.2694978 | M78: 7.0022093 | N78: 9.971557 | O78: 8.0864229 | P78: =C78/G78 -> 0.83013423 | Q78: =D78/G78 -> 1.4848642 | R78: =E78/G78 -> 1.3825567 | S78: =F78/G78 -> 0.8450444 | T78: =H78/G78 -> 1.3842835 | U78: =I78/G78 -> 1.3720593 | V78: =IFERROR(J78/M78,"") -> 1.2293213 | W78: =IFERROR(K78/M78,"") -> 1.3807901 | X78: =IFERROR(L78/M78,"") -> 0.75254789 | Y78: =IFERROR(N78/M78,"") -> 1.4240587 | Z78: =IFERROR(O78/M78,"") -> 1.1548388
B79: 42947 | C79: 9.153209 | D79: 16.571862 | E79: 15.690977 | F79: 9.908881 | G79: 11.296153 | H79: 15.737527 | I79: 15.403791 | J79: 8.9409138 | K79: 10.188725 | L79: 5.463072 | M79: 7.3014904 | N79: 10.440005 | O79: 8.783287 | P79: =C79/G79 -> 0.81029434 | Q79: =D79/G79 -> 1.4670359 | R79: =E79/G79 -> 1.3890549 | S79: =F79/G79 -> 0.87719074 | T79: =H79/G79 -> 1.3931758 | U79: =I79/G79 -> 1.3636316 | V79: =IFERROR(J79/M79,"") -> 1.2245327 | W79: =IFERROR(K79/M79,"") -> 1.3954309 | X79: =IFERROR(L79/M79,"") -> 0.74821327 | Y79: =IFERROR(N79/M79,"") -> 1.4298458 | Z79: =IFERROR(O79/M79,"") -> 1.2029444
B80: 42978 | C80: 9.8801359 | D80: 17.459196 | E80: 16.972938 | F80: 11.368151 | G80: 12.337653 | H80: 16.826837 | I80: 17.939062 | J80: 9.2751196 | K80: 10.769657 | L80: 5.7439362 | M80: 7.5961596 | N80: 10.927394 | O80: 9.8846217 | P80: =C80/G80 -> 0.80081162 | Q80: =D80/G80 -> 1.4151149 | R80: =E80/G80 -> 1.3757023 | S80: =F80/G80 -> 0.92141924 | T80: =H80/G80 -> 1.3638604 | U80: =I80/G80 -> 1.4540093 | V80: =IFERROR(J80/M80,"") -> 1.2210275 | W80: =IFERROR(K80/M80,"") -> 1.4177766 | X80: =IFERROR(L80/M80,"") -> 0.75616317 | Y80: =IFERROR(N80/M80,"") -> 1.4385419 | Z80: =IFERROR(O80/M80,"") -> 1.3012657
B81: 43008 | C81: 10.624548 | D81: 17.702882 | E81: 18.268507 | F81: 11.023204 | G81: 12.806873 | H81: 18.23046 | I81: 18.524961 | J81: 9.496485 | K81: 11.241041 | L81: 5.5978272 | M81: 7.7032809 | N81: 11.466177 | O81: 9.9456689 | P81: =C81/G81 -> 0.82959737 | Q81: =D81/G81 -> 1.3822955 | R81: =E81/G81 -> 1.4264612 | S81: =F81/G81 -> 0.8607257 | T81: =H81/G81 -> 1.4234904 | U81: =I81/G81 -> 1.4464859 | V81: =IFERROR(J81/M81,"") -> 1.2327845 | W81: =IFERROR(K81/M81,"") -> 1.4592537 | X81: =IFERROR(L81/M81,"") -> 0.72668091 | Y81: =IFERROR(N81/M81,"") -> 1.4884796 | Z81: =IFERROR(O81/M81,"") -> 1.2910952
... B189: 46295 | C189: 8.4445573 | D189: 13.12243 | E189: 11.449812 | F189: 6.2908541 | G189: 8.5945966 | H189: 9.1889975 | I189: 17.117457 | J189: 7.0794718 | K189: 7.2365014 | L189: 3.7565986 | M189: 5.0686316 | N189: 5.2964058 | O189: 14.271946 | P189: =C189/G189 -> 0.9825426 | Q189: =D189/G189 -> 1.5268233 | R189: =E189/G189 -> 1.3322106 | S189: =F189/G189 -> 0.73195455 | T189: =H189/G189 -> 1.0691598 | U189: =I189/G189 -> 1.9916533 | V189: =IFERROR(J189/M189,"") -> 1.3967225 | W189: =IFERROR(K189/M189,"") -> 1.4277032 | X189: =IFERROR(L189/M189,"") -> 0.7411465 | Y189: =IFERROR(N189/M189,"") -> 1.044938 | Z189: =IFERROR(O189/M189,"") -> 2.8157395

Sheet DCF
B1: Ibovespa - DCF (house model rolled to end-2027)
B2: Replica of Target rows 17-65 of DCF Ibov 2026_Out.xlsx, in Ibovespa points, extended to 2031. Blue = house file input; pink = projection rule.
B3: Legend: | C3: input | D3: assumption | E3: formula
B5: Projections (index points)
C6: 2015 | D6: 2016 | E6: 2017 | F6: 2018 | G6: 2019 | H6: 2020 | I6: 2021 | J6: 2022 | K6: 2023 | L6: 2024 | M6: 2025 | N6: 2026 | O6: 2027 | P6: 2028 | Q6: 2029 | R6: 2030 | S6: 2031 | U6: How it is calculated (house Target row)
C7: Actual | D7: Actual | E7: Actual | F7: Actual | G7: Actual | H7: Actual | I7: Actual | J7: Actual | K7: Actual | L7: Actual | M7: Actual | N7: Consensus | O7: Consensus | P7: Consensus | Q7: Projection | R7: Projection | S7: Projection
B8: Real GDP | J8: 0.029 | K8: 0.029 | L8: 0.031 | M8: 0.021 | N8: 0.018 | O8: 0.01 | P8: 0.02 | Q8: 0.02 | R8: 0.02 | S8: 0.02
B9: Inflation | C9: 0.1067 | D9: 0.0629 | E9: 0.0295 | F9: 0.0375 | G9: 0.0431 | H9: 0.045 | I9: 0.101 | J9: 0.058 | K9: 0.046 | L9: 0.046 | M9: 0.045 | N9: 0.038 | O9: 0.04 | P9: 0.04 | Q9: 0.04 | R9: 0.04 | S9: 0.04
B10: Nominal GDP | C10: =(1+C8)*(1+C9)-1 -> 0.1067 | D10: =(1+D8)*(1+D9)-1 -> 0.0629 | E10: =(1+E8)*(1+E9)-1 -> 0.0295 | F10: =(1+F8)*(1+F9)-1 -> 0.0375 | G10: =(1+G8)*(1+G9)-1 -> 0.0431 | H10: =(1+H8)*(1+H9)-1 -> 0.045 | I10: =(1+I8)*(1+I9)-1 -> 0.101 | J10: =(1+J8)*(1+J9)-1 -> 0.088682 | ... S10: =(1+S8)*(1+S9)-1 -> 0.0608 | U10: (1 + real GDP) x (1 + inflation) - 1 (row 20).
B11: Sales growth | D11: =D13/C13-1 -> 0.031809353 | E11: =E13/D13-1 -> 0.014830489 | F11: =F13/E13-1 -> 0.16663413 | G11: =G13/F13-1 -> 0.12933978 | H11: =H13/G13-1 -> 0.081369435 | I11: =I13/H13-1 -> 0.33636272 | J11: =J13/I13-1 -> 0.20564508 | K11: =K13/J13-1 -> 0.058209825 | ... O11: =O13/N13-1 -> 0.030505723 | P11: =P10*P12 -> 0.0608 | Q11: =Q10*Q12 -> 0.0608 | R11: =R10*R12 -> 0.0608 | S11: =S10*S12 -> 0.0608 | U11: Actual/consensus: sales / previous - 1. Projection: nominal GDP x ratio (row 21).
B12: Ratio (sales growth / nominal GDP) | D12: =D11/D10 -> 0.50571309 | E12: =E11/E10 -> 0.50272844 | F12: =F11/F10 -> 4.4435767 | G12: =G11/G10 -> 3.0009229 | H12: =H11/H10 -> 1.8082097 | I12: =I11/I10 -> 3.3303239 | J12: =J11/J10 -> 2.3189044 | K12: =K11/K10 -> 0.76256746 | ... O12: =O11/O10 -> 0.60527228 | P12: 1 | Q12: 1 | R12: 1 | S12: 1
B13: Sales | C13: 51357.85 | D13: 52991.51 | E13: 53777.4 | F13: 62738.55 | G13: 70853.14 | H13: 76618.42 | I13: 102390 | J13: 123446 | K13: 130631.77 | L13: 138166 | M13: 150140 | N13: 158921 | O13: 163769 | P13: =O13*(1+P11) -> 173726.16 | Q13: =P13*(1+Q11) -> 184288.71 | R13: =Q13*(1+R11) -> 195493.46 | S13: =R13*(1+S11) -> 207379.46 | U13: To 2027: house file (consensus 2026-27). 2028+: previous x (1 + growth) (row 25).
B14: COGS | C14: =C13*(C15-1) -> -38374.586 | D14: =D13*(D15-1) -> -39865.513 | E14: =E13*(E15-1) -> -38940.215 | F14: =F13*(F15-1) -> -44801.599 | G14: =G13*(G15-1) -> -50192.364 | H14: =H13*(H15-1) -> -53939.368 | I14: =I13*(I15-1) -> -65529.6 | J14: =J13*(J15-1) -> -82708.82 | ... S14: =S13*(S15-1) -> -133199.83 | U14: Sales x (gross margin - 1) (row 26).
B15: Gross margin % | C15: 0.2528 | D15: 0.2477 | E15: 0.2759 | F15: 0.2859 | G15: 0.2916 | H15: 0.296 | I15: 0.36 | J15: 0.33 | K15: 0.2757 | L15: 0.2514 | M15: 0.2737 | N15: 0.388 | O15: 0.3827 | P15: 0.3577 | Q15: =P15 -> 0.3577 | R15: =Q15 -> 0.3577 | S15: =R15 -> 0.3577 | U15: To 2028: house file. 2029+: previous year (row 27).
B16: Gross profit | C16: =C13+C14 -> 12983.264 | D16: =D13+D14 -> 13125.997 | E16: =E13+E14 -> 14837.185 | F16: =F13+F14 -> 17936.951 | G16: =G13+G14 -> 20660.776 | H16: =H13+H14 -> 22679.052 | I16: =I13+I14 -> 36860.4 | J16: =J13+J14 -> 40737.18 | ... S16: =S13+S14 -> 74179.633
B17: SG&A | C17: =C19-C16 -> -11461.954 | D17: =D19-D16 -> -6806.437 | E17: =E19-E16 -> -7556.5447 | F17: =F19-F16 -> -8126.6114 | G17: =G19-G16 -> -11860.076 | H17: =H19-H16 -> -11988.992 | I17: =I19-I16 -> -13266.4 | J17: =J19-J16 -> -14963.67 | ... P17: =P19-P16 -> -24819.836 | Q17: =Q13*Q18 -> -26328.882 | R17: =R13*R18 -> -27929.678 | S17: =S13*S18 -> -29627.802 | U17: To 2028: EBIT - gross profit. 2029+: sales x SG&A % (row 29).
B18: SG&A % of sales | C18: =C17/C13 -> -0.22317824 | D18: =D17/D13 -> -0.12844392 | E18: =E17/E13 -> -0.14051525 | F18: =F17/F13 -> -0.12953139 | G18: =G17/G13 -> -0.16738956 | H18: =H17/H13 -> -0.15647663 | I18: =I17/I13 -> -0.12956734 | J18: =J17/J13 -> -0.12121632 | ... P18: =P17/P13 -> -0.14286758 | Q18: =P18 -> -0.14286758 | R18: =Q18 -> -0.14286758 | S18: =R18 -> -0.14286758 | U18: 2029+: previous year's % (row 30).
B19: EBIT | C19: 1521.31 | D19: 6319.56 | E19: 7280.64 | F19: 9810.34 | G19: 8800.7 | H19: 10690.06 | I19: 23594 | J19: 25773.51 | K19: 21324.34 | L19: 25291.3 | M19: 20846 | N19: 33080 | O19: 34883 | P19: 37322.01 | Q19: =Q16+Q17 -> 39591.188 | R19: =R16+R17 -> 41998.332 | S19: =S16+S17 -> 44551.831 | U19: To 2028: house file (consensus). 2029+: gross profit + SG&A (row 31).
B20: EBIT margin % | C20: =C19/C13 -> 0.029621762 | D20: =D19/D13 -> 0.11925608 | E20: =E19/E13 -> 0.13538475 | F20: =F19/F13 -> 0.15636861 | G20: =G19/G13 -> 0.12421044 | H20: =H19/H13 -> 0.13952337 | I20: =I19/I13 -> 0.23043266 | J20: =J19/J13 -> 0.20878368 | ... S20: =S19/S13 -> 0.21483242
B21: EBITDA | C21: 11322.26 | D21: 11803.92 | E21: 13642.8 | F21: 17850.25 | G21: 18979.35 | H21: 19022.66 | I21: 31545 | J21: 36387.17 | K21: 32032.37 | L21: 37339 | M21: 33801 | N21: 49324 | O21: 50717 | P21: 51996.99 | Q21: =Q13*Q22 -> 55286.612 | R21: =R13*R22 -> 58648.038 | S21: =S13*S22 -> 62213.838 | U21: To 2028: house file (consensus). 2029+: sales x EBITDA margin (row 33).
B22: EBITDA margin % | C22: =C21/C13 -> 0.22045822 | D22: =D21/D13 -> 0.22275115 | E22: =E21/E13 -> 0.25369021 | F22: =F21/F13 -> 0.28451805 | G22: =G21/G13 -> 0.26786886 | H22: =H21/H13 -> 0.24827789 | I22: =I21/I13 -> 0.30808673 | J22: =J21/J13 -> 0.29476184 | ... P22: =P21/P13 -> 0.29930433 | Q22: 0.3 | R22: 0.3 | S22: 0.3 | U22: 2029+: 30% (house, row 34).
B23: D&A | C23: =C21-C19 -> 9800.95 | D23: =D21-D19 -> 5484.36 | E23: =E21-E19 -> 6362.16 | F23: =F21-F19 -> 8039.91 | G23: =G21-G19 -> 10178.65 | H23: =H21-H19 -> 8332.6 | I23: =I21-I19 -> 7951 | J23: =J21-J19 -> 10613.66 | ... S23: =S21-S19 -> 17662.007 | U23: EBITDA - EBIT (row 35).
B24: D&A % of sales | C24: =C23/C13 -> 0.19083645 | D24: =D23/D13 -> 0.10349507 | E24: =E23/E13 -> 0.11830546 | F24: =F23/F13 -> 0.12814944 | G24: =G23/G13 -> 0.14365842 | H24: =H23/H13 -> 0.10875453 | I24: =I23/I13 -> 0.077654068 | J24: =J23/J13 -> 0.08597816 | ... S24: =S23/S13 -> 0.085167582
B25: Tax rate | C25: -0.25 | D25: =C25 -> -0.25 | E25: =D25 -> -0.25 | F25: =E25 -> -0.25 | G25: =F25 -> -0.25 | H25: =G25 -> -0.25 | I25: =H25 -> -0.25 | J25: =I25 -> -0.25 | K25: =J25 -> -0.25 | L25: -0.24 | M25: =L25 -> -0.24 | N25: =M25 -> -0.24 | O25: =N25 -> -0.24 | P25: =O25 -> -0.24 | Q25: =P25 -> -0.24 | R25: =Q25 -> -0.24 | S25: =R25 -> -0.24 | U25: -25% to 2023, -24% from 2024 (row 37).
B26: NOPAT | C26: =C19*(1+C25) -> 1140.9825 | D26: =D19*(1+D25) -> 4739.67 | E26: =E19*(1+E25) -> 5460.48 | F26: =F19*(1+F25) -> 7357.755 | G26: =G19*(1+G25) -> 6600.525 | H26: =H19*(1+H25) -> 8017.545 | I26: =I19*(1+I25) -> 17695.5 | J26: =J19*(1+J25) -> 19330.132 | ... S26: =S19*(1+S25) -> 33859.392 | U26: EBIT x (1 + tax rate) (row 38).
B27: Net interest expense | C27: =C29-C26 -> -1992.7125 | D27: =D29-D26 -> -1693.5 | E27: =E29-E26 -> -1553.31 | F27: =F29-F26 -> -1433.345 | G27: =G29-G26 -> -1239.105 | H27: =H29-H26 -> -4140.545 | I27: =I29-I26 -> -2007.5 | J27: =J29-J26 -> -561.0525 | ... P27: =P29-P26 -> -5187.7276 | Q27: =Q13*Q28 -> -5503.1414 | R27: =R13*R28 -> -5837.7324 | S27: =S13*S28 -> -6192.6666 | U27: To 2028: net income - NOPAT. 2029+: sales x interest % (row 39).
B28: Interest % of sales | C28: =C27/C13 -> -0.038800544 | D28: =D27/D13 -> -0.031957949 | E28: =E27/E13 -> -0.028884067 | F28: =F27/F13 -> -0.02284632 | G28: =G27/G13 -> -0.017488357 | H28: =H27/H13 -> -0.054041117 | I28: =I27/I13 -> -0.019606407 | J28: =J27/J13 -> -0.0045449225 | ... P28: =P27/P13 -> -0.029861523 | Q28: =P28 -> -0.029861523 | R28: =Q28 -> -0.029861523 | S28: =R28 -> -0.029861523 | U28: 2029+: previous year's % (row 40).
B29: Net income (EPS, index pts) | C29: -851.73 | D29: 3046.17 | E29: 3907.17 | F29: 5924.41 | G29: 5361.42 | H29: 3877 | I29: 15688 | J29: 18769.08 | K29: 13729.57 | L29: 14944 | M29: 13889 | N29: 20958 | O29: 21666 | P29: 23177 | Q29: =Q26+Q27 -> 24586.162 | R29: =R26+R27 -> 26081 | S29: =S26+S27 -> 27666.725 | U29: To 2028: house file (consensus EPS). 2029+: NOPAT + net interest (row 41).
B30: Net margin % | C30: =C29/C13 -> -0.016584222 | D30: =D29/D13 -> 0.057484114 | E30: =E29/E13 -> 0.072654498 | F30: =F29/F13 -> 0.094430139 | G30: =G29/G13 -> 0.075669476 | H30: =H29/H13 -> 0.050601409 | I30: =I29/I13 -> 0.15321809 | J30: =J29/J13 -> 0.15204284 | ... S30: =S29/S13 -> 0.13341111
B31: Working capital (NWC) | C31: =-NWCpct*C13 -> -2054.314 | D31: =-NWCpct*D13 -> -2119.6604 | E31: =-NWCpct*E13 -> -2151.096 | F31: =-NWCpct*F13 -> -2509.542 | G31: =-NWCpct*G13 -> -2834.1256 | H31: =-NWCpct*H13 -> -3064.7368 | I31: =-NWCpct*I13 -> -4095.6 | J31: =-NWCpct*J13 -> -4937.84 | ... S31: =-NWCpct*S13 -> -8295.1784 | U31: -NWC % x sales (Assumptions; row 43).
B32: Change in NWC | D32: =D31-C31 -> -65.3464 | E32: =E31-D31 -> -31.4356 | F32: =F31-E31 -> -358.446 | G32: =G31-F31 -> -324.5836 | H32: =H31-G31 -> -230.6112 | I32: =I31-H31 -> -1030.8632 | J32: =J31-I31 -> -842.24 | K32: =K31-J31 -> -287.4308 | ... S32: =S31-R31 -> -475.44009
B33: Capex | C33: -5294.22 | D33: -3805.46 | E33: -3278.37 | F33: -3699.48 | G33: -3779.44 | H33: -3672 | I33: -4618.18 | J33: -6641.75 | K33: -8753.81 | L33: -10938 | M33: -18822 | N33: -19159 | O33: -19333 | P33: =P13*P34 -> -19109.877 | Q33: =Q13*Q34 -> -20271.758 | R33: =R13*R34 -> -17594.411 | S33: =S13*S34 -> -18664.151 | U33: To 2027: house file. 2028+: sales x capex % (row 46).
B34: Capex % of sales | C34: =C33/C13 -> -0.10308492 | D34: =D33/D13 -> -0.071812636 | E34: =E33/E13 -> -0.060961854 | F34: =F33/F13 -> -0.058966616 | G34: =G33/G13 -> -0.053341884 | H34: =H33/H13 -> -0.047925812 | I34: =I33/I13 -> -0.045103819 | J34: =J33/J13 -> -0.053802877 | ... O34: =O33/O13 -> -0.11805042 | P34: -0.11 | Q34: =P34 -> -0.11 | R34: -0.09 | S34: =R34 -> -0.09 | U34: 2028-29: -11%; 2030: -9% (house); 2031: as 2030 (row 47).
B35: FCFF, house = D&A + NOPAT + capex + NWC (level) | C35: =C23+C26+C33+C31 -> 3593.3985 | D35: =D23+D26+D33+D31 -> 4298.9096 | E35: =E23+E26+E33+E31 -> 6393.174 | F35: =F23+F26+F33+F31 -> 9188.643 | G35: =G23+G26+G33+G31 -> 10165.609 | H35: =H23+H26+H33+H31 -> 9613.4082 | I35: =I23+I26+I33+I31 -> 16932.72 | J35: =J23+J26+J33+J31 -> 18364.202 | ... S35: =S23+S26+S33+S31 -> 24562.069 | U35: D&A + NOPAT + capex + NWC level (row 44): what the house discounts.
B36: FCFF with the change in NWC | D36: =D23+D26+D33+D32 -> 6353.2236 | E36: =E23+E26+E33+E32 -> 8512.8344 | F36: =F23+F26+F33+F32 -> 11339.739 | G36: =G23+G26+G33+G32 -> 12675.151 | H36: =H23+H26+H33+H32 -> 12447.534 | I36: =I23+I26+I33+I32 -> 19997.457 | J36: =J23+J26+J33+J32 -> 22459.802 | K36: =K23+K26+K33+K32 -> 17660.044 | ... S36: =S23+S26+S33+S32 -> 32381.807 | U36: D&A + NOPAT + capex + change in NWC.
B37: FCFF used in the valuation (switch FixNWC) | C37: =C35 -> 3593.3985 | D37: =IF(FixNWC=1,D36,D35) -> 4298.9096 | E37: =IF(FixNWC=1,E36,E35) -> 6393.174 | F37: =IF(FixNWC=1,F36,F35) -> 9188.643 | G37: =IF(FixNWC=1,G36,G35) -> 10165.609 | H37: =IF(FixNWC=1,H36,H35) -> 9613.4082 | I37: =IF(FixNWC=1,I36,I35) -> 16932.72 | J37: =IF(FixNWC=1,J36,J35) -> 18364.202 | K37: =IF(FixNWC=1,K36,K35) -> 12722.204 | ... S37: =IF(FixNWC=1,S36,S35) -> 24562.069 | U37: FixNWC = 0: the house row; 1: the corrected row.
B38: memo: FCFF = EBITDA x (1 - tax) + capex | C38: 3875.1 | D38: 3414.98 | E38: 3131.8 | F38: 5798.58 | G38: 7840.38 | H38: 10543 | I38: 15220 | J38: 21728 | K38: 10626.16 | L38: 12342 | M38: 13051 | N38: =N21*(1+N25)+N33 -> 18327.24 | O38: =O21*(1+O25)+O33 -> 19211.92 | P38: =P21*(1+P25)+P33 -> 20407.835 | Q38: =Q21*(1+Q25)+Q33 -> 21746.067 | R38: =R21*(1+R25)+R33 -> 26978.097 | S38: =S21*(1+S25)+S33 -> 28618.366 | U38: To 2025: house file. 2026+: EBITDA x (1 + tax) + capex (row 49).
B39: memo: Ibovespa (average to 2020, then the price used) | C39: 49828 | D39: 53350 | E39: 67784 | F39: 81677 | G39: 101000 | H39: 99143 | I39: =IbovUsed -> 208431.92 | J39: =IbovUsed -> 208431.92 | K39: =IbovUsed -> 208431.92 | L39: =IbovUsed -> 208431.92 | M39: =IbovUsed -> 208431.92 | N39: =IbovUsed -> 208431.92 | O39: =IbovUsed -> 208431.92 | P39: =IbovUsed -> 208431.92 | ... S39: =IbovUsed -> 208431.92 | U39: Row 50: average to 2020 (house file), then the Ibovespa price used.
B40: memo: FCF yield | C40: =C38/C39 -> 0.077769527 | D40: =D38/D39 -> 0.064010872 | E40: =E38/E39 -> 0.046202644 | F40: =F38/F39 -> 0.070994037 | G40: =G38/G39 -> 0.077627525 | H40: =H38/H39 -> 0.10634135 | I40: =I38/I39 -> 0.073021445 | J40: =J38/J39 -> 0.10424507 | ... S40: =S38/S39 -> 0.13730318 | U40: Simple FCFF / Ibovespa (row 51).
B42: Valuation: fair value at the end of the year (house Target rows 53-59)
C43: Bear | D43: Base | E43: Bull | G43: Base 2026 | H43: How it is calculated
B44: Value date (end of year) | C44: 2027 | D44: 2027 | E44: 2027 | G44: 2026
B45: Explicit FCFF years | C45: 2028-2031 | D45: 2028-2031 | E45: 2028-2031 | G45: 2027-2030
B46: 5-year real rate (NTN-B) | C46: =Assumptions!C20 -> 0.085 | D46: =Assumptions!D20 -> 0.0676 | E46: =Assumptions!E20 -> 0.055 | G46: =Assumptions!D20 -> 0.0676
B47: ERP | C47: =Assumptions!C21 -> 0.06 | D47: =Assumptions!D21 -> 0.06 | E47: =Assumptions!E21 -> 0.06 | G47: =Assumptions!D21 -> 0.06
B48: Discount rate (house 'WACC') | C48: =IF(FixInfl=1,(1+C46+C47)*(1+InflLT)-1,C46+C47) -> 0.145 | D48: =IF(FixInfl=1,(1+D46+D47)*(1+InflLT)-1,D46+D47) -> 0.1276 | E48: =IF(FixInfl=1,(1+E46+E47)*(1+InflLT)-1,E46+E47) -> 0.115 | G48: =IF(FixInfl=1,(1+G46+G47)*(1+InflLT)-1,G46+G47) -> 0.1276 | H48: Real rate + ERP (Target!B55); Fisher with FixInfl = 1.
B49: Long-term growth (g) | C49: =gLT -> 0.047 | D49: =gLT -> 0.047 | E49: =gLT -> 0.047 | G49: =gLT -> 0.047
B50: FCFF of the last explicit year | C50: =S37 -> 24562.069 | D50: =S37 -> 24562.069 | E50: =S37 -> 24562.069 | G50: =R37 -> 23154.288
B51: Terminal value = last FCFF x (1 + g) / (rate - g) | C51: =C50*(1+C49)/(C48-C49) -> 262413.12 | D51: =D50*(1+D49)/(D48-D49) -> 319063.1 | E51: =E50*(1+E49)/(E48-E49) -> 378183.62 | G51: =G50*(1+G49)/(G48-G49) -> 300775.93 | H51: Target!R44.
B52: Periods the terminal value is discounted | C52: =5-FixTV -> 5 | D52: =5-FixTV -> 5 | E52: =5-FixTV -> 5 | G52: =5-FixTV -> 5 | H52: 4 explicit years + 1 (house NPV puts the TV one period later); 4 with FixTV = 1.
B53: Present value of the explicit FCFF | C53: =NPV(C48,P37:S37) -> 58382.957 | D53: =NPV(D48,P37:S37) -> 60669.969 | E53: =NPV(E48,P37:S37) -> 62416.626 | G53: =NPV(G48,O37:R37) -> 54929.274 | H53: Excel NPV of the explicit FCFF (Target row 59).
B54: Present value of the terminal value | C54: =C51/(1+C48)^C52 -> 133339.28 | D54: =D51/(1+D48)^D52 -> 175025.47 | E54: =E51/(1+E48)^E52 -> 219446.36 | G54: =G51/(1+G48)^G52 -> 164993.84
B55: Value of the cash flows | C55: =C53+C54 -> 191722.24 | D55: =D53+D54 -> 235695.44 | E55: =E53+E54 -> 281862.98 | G55: =G53+G54 -> 219923.12
B56: Net debt subtracted (switch FixND) | C56: =IF(FixND=1,NDmult*M21,0) -> 0 | D56: =IF(FixND=1,NDmult*M21,0) -> 0 | E56: =IF(FixND=1,NDmult*M21,0) -> 0 | G56: =IF(FixND=1,NDmult*L21,0) -> 0 | H56: 1.6x the EBITDA two years before the value date (Target rows 70-71), only with FixND = 1.
B57: Fair value (index pts) | C57: =C55-C56 -> 191722.24 | D57: =D55-D56 -> 235695.44 | E57: =E55-E56 -> 281862.98 | G57: =G55-G56 -> 219923.12 | H57: Value of the cash flows - net debt subtracted.
B58: Ibovespa used | C58: =IbovUsed -> 208431.92 | D58: =IbovUsed -> 208431.92 | E58: =IbovUsed -> 208431.92 | G58: =IbovUsed -> 208431.92
B59: Upside | C59: =C57/C58-1 -> -0.080168523 | D59: =D57/D58-1 -> 0.13080299 | E59: =E57/E58-1 -> 0.35230239 | G59: =G57/G58-1 -> 0.055131656
B60: Terminal value / value of the cash flows | C60: =C54/C55 -> 0.69548156 | D60: =D54/D55 -> 0.74259167 | E60: =E54/E55 -> 0.77855685 | G60: =G54/G55 -> 0.7502342
B61: Implied P/E on next year's EPS | C61: =C57/P29 -> 8.2720905 | D61: =D57/P29 -> 10.169368 | E61: =E57/P29 -> 12.161323 | G61: =G57/O29 -> 10.15061 | H61: Fair value / net income of the year after the value date.
B63: Implied return at the Ibovespa price used (house Target rows 61-65, rolled one year)
C64: Today | D64: 2027 | E64: 2028 | F64: 2029 | G64: Terminal
B65: Cash flows | C65: =-IbovUsed -> -208431.92 | D65: =O37 -> 16461.32 | E65: =P37 -> 16980.784 | F65: =Q37 -> 18141.421 | G65: =D51 -> 319063.1 | H65: As the house: price today, three yearly FCFF and the base terminal value as the fourth flow. An indicator, not a full DCF return.
B66: IRR | C66: =IRR(C65:G65) -> 0.16943777
B67: Inflation | C67: =InflLT -> 0.04
B68: Real IRR = IRR - inflation | C68: =C66-C67 -> 0.12943777
B69: Implied ERP = real IRR - 5-year real rate (base) | C69: =C68-D46 -> 0.061837772

Sheet Sensitivity
B1: Ibovespa - Sensitivity: real rate and ERP
B2: The house's real-rate table (tie-out) and a real rate x ERP grid for the end-2027 fair value with the current settings.
B3: Legend: | C3: input | D3: assumption | E3: formula
B5: House table: 5-year real rate vs DCF value (Target rows 120-129)
B6: 5-year real rate | C6: House file, end-2026 | D6: Replica, end-2026 (house settings) | E6: Difference | G6: End-2027, current settings
B7: 0.055 | C7: 263358.81 | D7: =NPV(($B7+0.06),DCF!$O$35:$R$35)+DCF!$R$35*(1+0.047)/(($B7+0.06)-0.047)/(1+($B7+0.06))^5-0 -> 263358.81 | E7: =D7-C7 -> 0 | G7: =NPV(IF(FixInfl=1,(1+$B7+Assumptions!$D$21)*(1+InflLT)-1,$B7+Assumptions!$D$21),DCF!$P$37:$S$37)+DCF!$S$37*(1+gLT)/(IF(FixInfl=1,(1+$B7+Assumptions!$D$21)*(1+InflLT)-1,$B7+Assumptions!$D$21)-gLT)/(1+IF(FixInfl=1,(1+$B7+Assumptions!$D$21)*(1+InflLT)-1,$B7+Assumptions!$D$21))^(4+1-FixTV)-IF(FixND=1,NDmult*DCF!$M$21,0) -> 281862.98
B8: 0.06 | C8: 244298.81 | D8: =NPV(($B8+0.06),DCF!$O$35:$R$35)+DCF!$R$35*(1+0.047)/(($B8+0.06)-0.047)/(1+($B8+0.06))^5-0 -> 244298.81 | E8: =D8-C8 -> 0 | G8: =NPV(IF(FixInfl=1,(1+$B8+Assumptions!$D$21)*(1+InflLT)-1,$B8+Assumptions!$D$21),DCF!$P$37:$S$37)+DCF!$S$37*(1+gLT)/(IF(FixInfl=1,(1+$B8+Assumptions!$D$21)*(1+InflLT)-1,$B8+Assumptions!$D$21)-gLT)/(1+IF(FixInfl=1,(1+$B8+Assumptions!$D$21)*(1+InflLT)-1,$B8+Assumptions!$D$21))^(4+1-FixTV)-IF(FixND=1,NDmult*DCF!$M$21,0) -> 261607.54
B9: 0.07 | C9: 213168.52 | D9: =NPV(($B9+0.06),DCF!$O$35:$R$35)+DCF!$R$35*(1+0.047)/(($B9+0.06)-0.047)/(1+($B9+0.06))^5-0 -> 213168.52 | E9: =D9-C9 -> 0 | G9: =NPV(IF(FixInfl=1,(1+$B9+Assumptions!$D$21)*(1+InflLT)-1,$B9+Assumptions!$D$21),DCF!$P$37:$S$37)+DCF!$S$37*(1+gLT)/(IF(FixInfl=1,(1+$B9+Assumptions!$D$21)*(1+InflLT)-1,$B9+Assumptions!$D$21)-gLT)/(1+IF(FixInfl=1,(1+$B9+Assumptions!$D$21)*(1+InflLT)-1,$B9+Assumptions!$D$21))^(4+1-FixTV)-IF(FixND=1,NDmult*DCF!$M$21,0) -> 228513.31
B10: 0.0742 | C10: 202259.17 | D10: =NPV(($B10+0.06),DCF!$O$35:$R$35)+DCF!$R$35*(1+0.047)/(($B10+0.06)-0.047)/(1+($B10+0.06))^5-0 -> 202259.17 | E10: =D10-C10 -> 0 | G10: =NPV(IF(FixInfl=1,(1+$B10+Assumptions!$D$21)*(1+InflLT)-1,$B10+Assumptions!$D$21),DCF!$P$37:$S$37)+DCF!$S$37*(1+gLT)/(IF(FixInfl=1,(1+$B10+Assumptions!$D$21)*(1+InflLT)-1,$B10+Assumptions!$D$21)-gLT)/(1+IF(FixInfl=1,(1+$B10+Assumptions!$D$21)*(1+InflLT)-1,$B10+Assumptions!$D$21))^(4+1-FixTV)-IF(FixND=1,NDmult*DCF!$M$21,0) -> 216911.5
B11: 0.075 | C11: 200301.58 | D11: =NPV(($B11+0.06),DCF!$O$35:$R$35)+DCF!$R$35*(1+0.047)/(($B11+0.06)-0.047)/(1+($B11+0.06))^5-0 -> 200301.58 | E11: =D11-C11 -> 0 | G11: =NPV(IF(FixInfl=1,(1+$B11+Assumptions!$D$21)*(1+InflLT)-1,$B11+Assumptions!$D$21),DCF!$P$37:$S$37)+DCF!$S$37*(1+gLT)/(IF(FixInfl=1,(1+$B11+Assumptions!$D$21)*(1+InflLT)-1,$B11+Assumptions!$D$21)-gLT)/(1+IF(FixInfl=1,(1+$B11+Assumptions!$D$21)*(1+InflLT)-1,$B11+Assumptions!$D$21))^(4+1-FixTV)-IF(FixND=1,NDmult*DCF!$M$21,0) -> 214829.39
B12: 0.08 | C12: 188845.17 | D12: =NPV(($B12+0.06),DCF!$O$35:$R$35)+DCF!$R$35*(1+0.047)/(($B12+0.06)-0.047)/(1+($B12+0.06))^5-0 -> 188845.17 | E12: =D12-C12 -> 0 | G12: =NPV(IF(FixInfl=1,(1+$B12+Assumptions!$D$21)*(1+InflLT)-1,$B12+Assumptions!$D$21),DCF!$P$37:$S$37)+DCF!$S$37*(1+gLT)/(IF(FixInfl=1,(1+$B12+Assumptions!$D$21)*(1+InflLT)-1,$B12+Assumptions!$D$21)-gLT)/(1+IF(FixInfl=1,(1+$B12+Assumptions!$D$21)*(1+InflLT)-1,$B12+Assumptions!$D$21))^(4+1-FixTV)-IF(FixND=1,NDmult*DCF!$M$21,0) -> 202642.39
B13: 0.085 | C13: 178582.43 | D13: =NPV(($B13+0.06),DCF!$O$35:$R$35)+DCF!$R$35*(1+0.047)/(($B13+0.06)-0.047)/(1+($B13+0.06))^5-0 -> 178582.43 | E13: =D13-C13 -> 0 | G13: =NPV(IF(FixInfl=1,(1+$B13+Assumptions!$D$21)*(1+InflLT)-1,$B13+Assumptions!$D$21),DCF!$P$37:$S$37)+DCF!$S$37*(1+gLT)/(IF(FixInfl=1,(1+$B13+Assumptions!$D$21)*(1+InflLT)-1,$B13+Assumptions!$D$21)-gLT)/(1+IF(FixInfl=1,(1+$B13+Assumptions!$D$21)*(1+InflLT)-1,$B13+Assumptions!$D$21))^(4+1-FixTV)-IF(FixND=1,NDmult*DCF!$M$21,0) -> 191722.24
B14: 0.09 | C14: 169338.66 | D14: =NPV(($B14+0.06),DCF!$O$35:$R$35)+DCF!$R$35*(1+0.047)/(($B14+0.06)-0.047)/(1+($B14+0.06))^5-0 -> 169338.66 | E14: =D14-C14 -> 0 | G14: =NPV(IF(FixInfl=1,(1+$B14+Assumptions!$D$21)*(1+InflLT)-1,$B14+Assumptions!$D$21),DCF!$P$37:$S$37)+DCF!$S$37*(1+gLT)/(IF(FixInfl=1,(1+$B14+Assumptions!$D$21)*(1+InflLT)-1,$B14+Assumptions!$D$21)-gLT)/(1+IF(FixInfl=1,(1+$B14+Assumptions!$D$21)*(1+InflLT)-1,$B14+Assumptions!$D$21))^(4+1-FixTV)-IF(FixND=1,NDmult*DCF!$M$21,0) -> 181883.6
B15: House settings: ERP 6.0%, g 4.7%, no corrections, house FCFF. The house table is an Excel data table on Target!C56.
B18: End-2027 fair value (index pts), current settings
B19: Real rate \ ERP | C19: 0.04 | D19: 0.05 | E19: 0.06 | F19: 0.07 | G19: 0.08
B20: 0.05 | C20: =NPV(IF(FixInfl=1,(1+$B20+C$19)*(1+InflLT)-1,$B20+C$19),DCF!$P$37:$S$37)+DCF!$S$37*(1+gLT)/(IF(FixInfl=1,(1+$B20+C$19)*(1+InflLT)-1,$B20+C$19)-gLT)/(1+IF(FixInfl=1,(1+$B20+C$19)*(1+InflLT)-1,$B20+C$19))^(4+1-FixTV)-IF(FixND=1,NDmult*DCF!$M$21,0) -> 454824.27 | D20: =NPV(IF(FixInfl=1,(1+$B20+D$19)*(1+InflLT)-1,$B20+D$19),DCF!$P$37:$S$37)+DCF!$S$37*(1+gLT)/(IF(FixInfl=1,(1+$B20+D$19)*(1+InflLT)-1,$B20+D$19)-gLT)/(1+IF(FixInfl=1,(1+$B20+D$19)*(1+InflLT)-1,$B20+D$19))^(4+1-FixTV)-IF(FixND=1,NDmult*DCF!$M$21,0) -> 365883.78 | E20: =NPV(IF(FixInfl=1,(1+$B20+E$19)*(1+InflLT)-1,$B20+E$19),DCF!$P$37:$S$37)+DCF!$S$37*(1+gLT)/(IF(FixInfl=1,(1+$B20+E$19)*(1+InflLT)-1,$B20+E$19)-gLT)/(1+IF(FixInfl=1,(1+$B20+E$19)*(1+InflLT)-1,$B20+E$19))^(4+1-FixTV)-IF(FixND=1,NDmult*DCF!$M$21,0) -> 305377.76 | F20: =NPV(IF(FixInfl=1,(1+$B20+F$19)*(1+InflLT)-1,$B20+F$19),DCF!$P$37:$S$37)+DCF!$S$37*(1+gLT)/(IF(FixInfl=1,(1+$B20+F$19)*(1+InflLT)-1,$B20+F$19)-gLT)/(1+IF(FixInfl=1,(1+$B20+F$19)*(1+InflLT)-1,$B20+F$19))^(4+1-FixTV)-IF(FixND=1,NDmult*DCF!$M$21,0) -> 261607.54 | G20: =NPV(IF(FixInfl=1,(1+$B20+G$19)*(1+InflLT)-1,$B20+G$19),DCF!$P$37:$S$37)+DCF!$S$37*(1+gLT)/(IF(FixInfl=1,(1+$B20+G$19)*(1+InflLT)-1,$B20+G$19)-gLT)/(1+IF(FixInfl=1,(1+$B20+G$19)*(1+InflLT)-1,$B20+G$19))^(4+1-FixTV)-IF(FixND=1,NDmult*DCF!$M$21,0) -> 228513.31
B21: 0.055 | C21: =NPV(IF(FixInfl=1,(1+$B21+C$19)*(1+InflLT)-1,$B21+C$19),DCF!$P$37:$S$37)+DCF!$S$37*(1+gLT)/(IF(FixInfl=1,(1+$B21+C$19)*(1+InflLT)-1,$B21+C$19)-gLT)/(1+IF(FixInfl=1,(1+$B21+C$19)*(1+InflLT)-1,$B21+C$19))^(4+1-FixTV)-IF(FixND=1,NDmult*DCF!$M$21,0) -> 405687.66 | D21: =NPV(IF(FixInfl=1,(1+$B21+D$19)*(1+InflLT)-1,$B21+D$19),DCF!$P$37:$S$37)+DCF!$S$37*(1+gLT)/(IF(FixInfl=1,(1+$B21+D$19)*(1+InflLT)-1,$B21+D$19)-gLT)/(1+IF(FixInfl=1,(1+$B21+D$19)*(1+InflLT)-1,$B21+D$19))^(4+1-FixTV)-IF(FixND=1,NDmult*DCF!$M$21,0) -> 332996.75 | E21: =NPV(IF(FixInfl=1,(1+$B21+E$19)*(1+InflLT)-1,$B21+E$19),DCF!$P$37:$S$37)+DCF!$S$37*(1+gLT)/(IF(FixInfl=1,(1+$B21+E$19)*(1+InflLT)-1,$B21+E$19)-gLT)/(1+IF(FixInfl=1,(1+$B21+E$19)*(1+InflLT)-1,$B21+E$19))^(4+1-FixTV)-IF(FixND=1,NDmult*DCF!$M$21,0) -> 281862.98 | F21: =NPV(IF(FixInfl=1,(1+$B21+F$19)*(1+InflLT)-1,$B21+F$19),DCF!$P$37:$S$37)+DCF!$S$37*(1+gLT)/(IF(FixInfl=1,(1+$B21+F$19)*(1+InflLT)-1,$B21+F$19)-gLT)/(1+IF(FixInfl=1,(1+$B21+F$19)*(1+InflLT)-1,$B21+F$19))^(4+1-FixTV)-IF(FixND=1,NDmult*DCF!$M$21,0) -> 243983.24 | G21: =NPV(IF(FixInfl=1,(1+$B21+G$19)*(1+InflLT)-1,$B21+G$19),DCF!$P$37:$S$37)+DCF!$S$37*(1+gLT)/(IF(FixInfl=1,(1+$B21+G$19)*(1+InflLT)-1,$B21+G$19)-gLT)/(1+IF(FixInfl=1,(1+$B21+G$19)*(1+InflLT)-1,$B21+G$19))^(4+1-FixTV)-IF(FixND=1,NDmult*DCF!$M$21,0) -> 214829.39
B22: 0.06 | C22: =NPV(IF(FixInfl=1,(1+$B22+C$19)*(1+InflLT)-1,$B22+C$19),DCF!$P$37:$S$37)+DCF!$S$37*(1+gLT)/(IF(FixInfl=1,(1+$B22+C$19)*(1+InflLT)-1,$B22+C$19)-gLT)/(1+IF(FixInfl=1,(1+$B22+C$19)*(1+InflLT)-1,$B22+C$19))^(4+1-FixTV)-IF(FixND=1,NDmult*DCF!$M$21,0) -> 365883.78 | D22: =NPV(IF(FixInfl=1,(1+$B22+D$19)*(1+InflLT)-1,$B22+D$19),DCF!$P$37:$S$37)+DCF!$S$37*(1+gLT)/(IF(FixInfl=1,(1+$B22+D$19)*(1+InflLT)-1,$B22+D$19)-gLT)/(1+IF(FixInfl=1,(1+$B22+D$19)*(1+InflLT)-1,$B22+D$19))^(4+1-FixTV)-IF(FixND=1,NDmult*DCF!$M$21,0) -> 305377.76 | E22: =NPV(IF(FixInfl=1,(1+$B22+E$19)*(1+InflLT)-1,$B22+E$19),DCF!$P$37:$S$37)+DCF!$S$37*(1+gLT)/(IF(FixInfl=1,(1+$B22+E$19)*(1+InflLT)-1,$B22+E$19)-gLT)/(1+IF(FixInfl=1,(1+$B22+E$19)*(1+InflLT)-1,$B22+E$19))^(4+1-FixTV)-IF(FixND=1,NDmult*DCF!$M$21,0) -> 261607.54 | F22: =NPV(IF(FixInfl=1,(1+$B22+F$19)*(1+InflLT)-1,$B22+F$19),DCF!$P$37:$S$37)+DCF!$S$37*(1+gLT)/(IF(FixInfl=1,(1+$B22+F$19)*(1+InflLT)-1,$B22+F$19)-gLT)/(1+IF(FixInfl=1,(1+$B22+F$19)*(1+InflLT)-1,$B22+F$19))^(4+1-FixTV)-IF(FixND=1,NDmult*DCF!$M$21,0) -> 228513.31 | G22: =NPV(IF(FixInfl=1,(1+$B22+G$19)*(1+InflLT)-1,$B22+G$19),DCF!$P$37:$S$37)+DCF!$S$37*(1+gLT)/(IF(FixInfl=1,(1+$B22+G$19)*(1+InflLT)-1,$B22+G$19)-gLT)/(1+IF(FixInfl=1,(1+$B22+G$19)*(1+InflLT)-1,$B22+G$19))^(4+1-FixTV)-IF(FixND=1,NDmult*DCF!$M$21,0) -> 202642.39
B23: 0.065 | C23: =NPV(IF(FixInfl=1,(1+$B23+C$19)*(1+InflLT)-1,$B23+C$19),DCF!$P$37:$S$37)+DCF!$S$37*(1+gLT)/(IF(FixInfl=1,(1+$B23+C$19)*(1+InflLT)-1,$B23+C$19)-gLT)/(1+IF(FixInfl=1,(1+$B23+C$19)*(1+InflLT)-1,$B23+C$19))^(4+1-FixTV)-IF(FixND=1,NDmult*DCF!$M$21,0) -> 332996.75 | D23: =NPV(IF(FixInfl=1,(1+$B23+D$19)*(1+InflLT)-1,$B23+D$19),DCF!$P$37:$S$37)+DCF!$S$37*(1+gLT)/(IF(FixInfl=1,(1+$B23+D$19)*(1+InflLT)-1,$B23+D$19)-gLT)/(1+IF(FixInfl=1,(1+$B23+D$19)*(1+InflLT)-1,$B23+D$19))^(4+1-FixTV)-IF(FixND=1,NDmult*DCF!$M$21,0) -> 281862.98 | E23: =NPV(IF(FixInfl=1,(1+$B23+E$19)*(1+InflLT)-1,$B23+E$19),DCF!$P$37:$S$37)+DCF!$S$37*(1+gLT)/(IF(FixInfl=1,(1+$B23+E$19)*(1+InflLT)-1,$B23+E$19)-gLT)/(1+IF(FixInfl=1,(1+$B23+E$19)*(1+InflLT)-1,$B23+E$19))^(4+1-FixTV)-IF(FixND=1,NDmult*DCF!$M$21,0) -> 243983.24 | F23: =NPV(IF(FixInfl=1,(1+$B23+F$19)*(1+InflLT)-1,$B23+F$19),DCF!$P$37:$S$37)+DCF!$S$37*(1+gLT)/(IF(FixInfl=1,(1+$B23+F$19)*(1+InflLT)-1,$B23+F$19)-gLT)/(1+IF(FixInfl=1,(1+$B23+F$19)*(1+InflLT)-1,$B23+F$19))^(4+1-FixTV)-IF(FixND=1,NDmult*DCF!$M$21,0) -> 214829.39 | G23: =NPV(IF(FixInfl=1,(1+$B23+G$19)*(1+InflLT)-1,$B23+G$19),DCF!$P$37:$S$37)+DCF!$S$37*(1+gLT)/(IF(FixInfl=1,(1+$B23+G$19)*(1+InflLT)-1,$B23+G$19)-gLT)/(1+IF(FixInfl=1,(1+$B23+G$19)*(1+InflLT)-1,$B23+G$19))^(4+1-FixTV)-IF(FixND=1,NDmult*DCF!$M$21,0) -> 191722.24
B24: 0.0676 | C24: =NPV(IF(FixInfl=1,(1+$B24+C$19)*(1+InflLT)-1,$B24+C$19),DCF!$P$37:$S$37)+DCF!$S$37*(1+gLT)/(IF(FixInfl=1,(1+$B24+C$19)*(1+InflLT)-1,$B24+C$19)-gLT)/(1+IF(FixInfl=1,(1+$B24+C$19)*(1+InflLT)-1,$B24+C$19))^(4+1-FixTV)-IF(FixND=1,NDmult*DCF!$M$21,0) -> 318060.01 | D24: =NPV(IF(FixInfl=1,(1+$B24+D$19)*(1+InflLT)-1,$B24+D$19),DCF!$P$37:$S$37)+DCF!$S$37*(1+gLT)/(IF(FixInfl=1,(1+$B24+D$19)*(1+InflLT)-1,$B24+D$19)-gLT)/(1+IF(FixInfl=1,(1+$B24+D$19)*(1+InflLT)-1,$B24+D$19))^(4+1-FixTV)-IF(FixND=1,NDmult*DCF!$M$21,0) -> 270967.27 | E24: =NPV(IF(FixInfl=1,(1+$B24+E$19)*(1+InflLT)-1,$B24+E$19),DCF!$P$37:$S$37)+DCF!$S$37*(1+gLT)/(IF(FixInfl=1,(1+$B24+E$19)*(1+InflLT)-1,$B24+E$19)-gLT)/(1+IF(FixInfl=1,(1+$B24+E$19)*(1+InflLT)-1,$B24+E$19))^(4+1-FixTV)-IF(FixND=1,NDmult*DCF!$M$21,0) -> 235695.44 | F24: =NPV(IF(FixInfl=1,(1+$B24+F$19)*(1+InflLT)-1,$B24+F$19),DCF!$P$37:$S$37)+DCF!$S$37*(1+gLT)/(IF(FixInfl=1,(1+$B24+F$19)*(1+InflLT)-1,$B24+F$19)-gLT)/(1+IF(FixInfl=1,(1+$B24+F$19)*(1+InflLT)-1,$B24+F$19))^(4+1-FixTV)-IF(FixND=1,NDmult*DCF!$M$21,0) -> 208321.07 | G24: =NPV(IF(FixInfl=1,(1+$B24+G$19)*(1+InflLT)-1,$B24+G$19),DCF!$P$37:$S$37)+DCF!$S$37*(1+gLT)/(IF(FixInfl=1,(1+$B24+G$19)*(1+InflLT)-1,$B24+G$19)-gLT)/(1+IF(FixInfl=1,(1+$B24+G$19)*(1+InflLT)-1,$B24+G$19))^(4+1-FixTV)-IF(FixND=1,NDmult*DCF!$M$21,0) -> 186481.43
B25: 0.07 | C25: =NPV(IF(FixInfl=1,(1+$B25+C$19)*(1+InflLT)-1,$B25+C$19),DCF!$P$37:$S$37)+DCF!$S$37*(1+gLT)/(IF(FixInfl=1,(1+$B25+C$19)*(1+InflLT)-1,$B25+C$19)-gLT)/(1+IF(FixInfl=1,(1+$B25+C$19)*(1+InflLT)-1,$B25+C$19))^(4+1-FixTV)-IF(FixND=1,NDmult*DCF!$M$21,0) -> 305377.76 | D25: =NPV(IF(FixInfl=1,(1+$B25+D$19)*(1+InflLT)-1,$B25+D$19),DCF!$P$37:$S$37)+DCF!$S$37*(1+gLT)/(IF(FixInfl=1,(1+$B25+D$19)*(1+InflLT)-1,$B25+D$19)-gLT)/(1+IF(FixInfl=1,(1+$B25+D$19)*(1+InflLT)-1,$B25+D$19))^(4+1-FixTV)-IF(FixND=1,NDmult*DCF!$M$21,0) -> 261607.54 | E25: =NPV(IF(FixInfl=1,(1+$B25+E$19)*(1+InflLT)-1,$B25+E$19),DCF!$P$37:$S$37)+DCF!$S$37*(1+gLT)/(IF(FixInfl=1,(1+$B25+E$19)*(1+InflLT)-1,$B25+E$19)-gLT)/(1+IF(FixInfl=1,(1+$B25+E$19)*(1+InflLT)-1,$B25+E$19))^(4+1-FixTV)-IF(FixND=1,NDmult*DCF!$M$21,0) -> 228513.31 | F25: =NPV(IF(FixInfl=1,(1+$B25+F$19)*(1+InflLT)-1,$B25+F$19),DCF!$P$37:$S$37)+DCF!$S$37*(1+gLT)/(IF(FixInfl=1,(1+$B25+F$19)*(1+InflLT)-1,$B25+F$19)-gLT)/(1+IF(FixInfl=1,(1+$B25+F$19)*(1+InflLT)-1,$B25+F$19))^(4+1-FixTV)-IF(FixND=1,NDmult*DCF!$M$21,0) -> 202642.39 | G25: =NPV(IF(FixInfl=1,(1+$B25+G$19)*(1+InflLT)-1,$B25+G$19),DCF!$P$37:$S$37)+DCF!$S$37*(1+gLT)/(IF(FixInfl=1,(1+$B25+G$19)*(1+InflLT)-1,$B25+G$19)-gLT)/(1+IF(FixInfl=1,(1+$B25+G$19)*(1+InflLT)-1,$B25+G$19))^(4+1-FixTV)-IF(FixND=1,NDmult*DCF!$M$21,0) -> 181883.6
B26: 0.075 | C26: =NPV(IF(FixInfl=1,(1+$B26+C$19)*(1+InflLT)-1,$B26+C$19),DCF!$P$37:$S$37)+DCF!$S$37*(1+gLT)/(IF(FixInfl=1,(1+$B26+C$19)*(1+InflLT)-1,$B26+C$19)-gLT)/(1+IF(FixInfl=1,(1+$B26+C$19)*(1+InflLT)-1,$B26+C$19))^(4+1-FixTV)-IF(FixND=1,NDmult*DCF!$M$21,0) -> 281862.98 | D26: =NPV(IF(FixInfl=1,(1+$B26+D$19)*(1+InflLT)-1,$B26+D$19),DCF!$P$37:$S$37)+DCF!$S$37*(1+gLT)/(IF(FixInfl=1,(1+$B26+D$19)*(1+InflLT)-1,$B26+D$19)-gLT)/(1+IF(FixInfl=1,(1+$B26+D$19)*(1+InflLT)-1,$B26+D$19))^(4+1-FixTV)-IF(FixND=1,NDmult*DCF!$M$21,0) -> 243983.24 | E26: =NPV(IF(FixInfl=1,(1+$B26+E$19)*(1+InflLT)-1,$B26+E$19),DCF!$P$37:$S$37)+DCF!$S$37*(1+gLT)/(IF(FixInfl=1,(1+$B26+E$19)*(1+InflLT)-1,$B26+E$19)-gLT)/(1+IF(FixInfl=1,(1+$B26+E$19)*(1+InflLT)-1,$B26+E$19))^(4+1-FixTV)-IF(FixND=1,NDmult*DCF!$M$21,0) -> 214829.39 | F26: =NPV(IF(FixInfl=1,(1+$B26+F$19)*(1+InflLT)-1,$B26+F$19),DCF!$P$37:$S$37)+DCF!$S$37*(1+gLT)/(IF(FixInfl=1,(1+$B26+F$19)*(1+InflLT)-1,$B26+F$19)-gLT)/(1+IF(FixInfl=1,(1+$B26+F$19)*(1+InflLT)-1,$B26+F$19))^(4+1-FixTV)-IF(FixND=1,NDmult*DCF!$M$21,0) -> 191722.24 | G26: =NPV(IF(FixInfl=1,(1+$B26+G$19)*(1+InflLT)-1,$B26+G$19),DCF!$P$37:$S$37)+DCF!$S$37*(1+gLT)/(IF(FixInfl=1,(1+$B26+G$19)*(1+InflLT)-1,$B26+G$19)-gLT)/(1+IF(FixInfl=1,(1+$B26+G$19)*(1+InflLT)-1,$B26+G$19))^(4+1-FixTV)-IF(FixND=1,NDmult*DCF!$M$21,0) -> 172975.46
B27: 0.08 | C27: =NPV(IF(FixInfl=1,(1+$B27+C$19)*(1+InflLT)-1,$B27+C$19),DCF!$P$37:$S$37)+DCF!$S$37*(1+gLT)/(IF(FixInfl=1,(1+$B27+C$19)*(1+InflLT)-1,$B27+C$19)-gLT)/(1+IF(FixInfl=1,(1+$B27+C$19)*(1+InflLT)-1,$B27+C$19))^(4+1-FixTV)-IF(FixND=1,NDmult*DCF!$M$21,0) -> 261607.54 | D27: =NPV(IF(FixInfl=1,(1+$B27+D$19)*(1+InflLT)-1,$B27+D$19),DCF!$P$37:$S$37)+DCF!$S$37*(1+gLT)/(IF(FixInfl=1,(1+$B27+D$19)*(1+InflLT)-1,$B27+D$19)-gLT)/(1+IF(FixInfl=1,(1+$B27+D$19)*(1+InflLT)-1,$B27+D$19))^(4+1-FixTV)-IF(FixND=1,NDmult*DCF!$M$21,0) -> 228513.31 | E27: =NPV(IF(FixInfl=1,(1+$B27+E$19)*(1+InflLT)-1,$B27+E$19),DCF!$P$37:$S$37)+DCF!$S$37*(1+gLT)/(IF(FixInfl=1,(1+$B27+E$19)*(1+InflLT)-1,$B27+E$19)-gLT)/(1+IF(FixInfl=1,(1+$B27+E$19)*(1+InflLT)-1,$B27+E$19))^(4+1-FixTV)-IF(FixND=1,NDmult*DCF!$M$21,0) -> 202642.39 | F27: =NPV(IF(FixInfl=1,(1+$B27+F$19)*(1+InflLT)-1,$B27+F$19),DCF!$P$37:$S$37)+DCF!$S$37*(1+gLT)/(IF(FixInfl=1,(1+$B27+F$19)*(1+InflLT)-1,$B27+F$19)-gLT)/(1+IF(FixInfl=1,(1+$B27+F$19)*(1+InflLT)-1,$B27+F$19))^(4+1-FixTV)-IF(FixND=1,NDmult*DCF!$M$21,0) -> 181883.6 | G27: =NPV(IF(FixInfl=1,(1+$B27+G$19)*(1+InflLT)-1,$B27+G$19),DCF!$P$37:$S$37)+DCF!$S$37*(1+gLT)/(IF(FixInfl=1,(1+$B27+G$19)*(1+InflLT)-1,$B27+G$19)-gLT)/(1+IF(FixInfl=1,(1+$B27+G$19)*(1+InflLT)-1,$B27+G$19))^(4+1-FixTV)-IF(FixND=1,NDmult*DCF!$M$21,0) -> 164873.6
B28: 0.085 | C28: =NPV(IF(FixInfl=1,(1+$B28+C$19)*(1+InflLT)-1,$B28+C$19),DCF!$P$37:$S$37)+DCF!$S$37*(1+gLT)/(IF(FixInfl=1,(1+$B28+C$19)*(1+InflLT)-1,$B28+C$19)-gLT)/(1+IF(FixInfl=1,(1+$B28+C$19)*(1+InflLT)-1,$B28+C$19))^(4+1-FixTV)-IF(FixND=1,NDmult*DCF!$M$21,0) -> 243983.24 | D28: =NPV(IF(FixInfl=1,(1+$B28+D$19)*(1+InflLT)-1,$B28+D$19),DCF!$P$37:$S$37)+DCF!$S$37*(1+gLT)/(IF(FixInfl=1,(1+$B28+D$19)*(1+InflLT)-1,$B28+D$19)-gLT)/(1+IF(FixInfl=1,(1+$B28+D$19)*(1+InflLT)-1,$B28+D$19))^(4+1-FixTV)-IF(FixND=1,NDmult*DCF!$M$21,0) -> 214829.39 | E28: =NPV(IF(FixInfl=1,(1+$B28+E$19)*(1+InflLT)-1,$B28+E$19),DCF!$P$37:$S$37)+DCF!$S$37*(1+gLT)/(IF(FixInfl=1,(1+$B28+E$19)*(1+InflLT)-1,$B28+E$19)-gLT)/(1+IF(FixInfl=1,(1+$B28+E$19)*(1+InflLT)-1,$B28+E$19))^(4+1-FixTV)-IF(FixND=1,NDmult*DCF!$M$21,0) -> 191722.24 | F28: =NPV(IF(FixInfl=1,(1+$B28+F$19)*(1+InflLT)-1,$B28+F$19),DCF!$P$37:$S$37)+DCF!$S$37*(1+gLT)/(IF(FixInfl=1,(1+$B28+F$19)*(1+InflLT)-1,$B28+F$19)-gLT)/(1+IF(FixInfl=1,(1+$B28+F$19)*(1+InflLT)-1,$B28+F$19))^(4+1-FixTV)-IF(FixND=1,NDmult*DCF!$M$21,0) -> 172975.46 | G28: =NPV(IF(FixInfl=1,(1+$B28+G$19)*(1+InflLT)-1,$B28+G$19),DCF!$P$37:$S$37)+DCF!$S$37*(1+gLT)/(IF(FixInfl=1,(1+$B28+G$19)*(1+InflLT)-1,$B28+G$19)-gLT)/(1+IF(FixInfl=1,(1+$B28+G$19)*(1+InflLT)-1,$B28+G$19))^(4+1-FixTV)-IF(FixND=1,NDmult*DCF!$M$21,0) -> 157474.85
B29: 0.09 | C29: =NPV(IF(FixInfl=1,(1+$B29+C$19)*(1+InflLT)-1,$B29+C$19),DCF!$P$37:$S$37)+DCF!$S$37*(1+gLT)/(IF(FixInfl=1,(1+$B29+C$19)*(1+InflLT)-1,$B29+C$19)-gLT)/(1+IF(FixInfl=1,(1+$B29+C$19)*(1+InflLT)-1,$B29+C$19))^(4+1-FixTV)-IF(FixND=1,NDmult*DCF!$M$21,0) -> 228513.31 | D29: =NPV(IF(FixInfl=1,(1+$B29+D$19)*(1+InflLT)-1,$B29+D$19),DCF!$P$37:$S$37)+DCF!$S$37*(1+gLT)/(IF(FixInfl=1,(1+$B29+D$19)*(1+InflLT)-1,$B29+D$19)-gLT)/(1+IF(FixInfl=1,(1+$B29+D$19)*(1+InflLT)-1,$B29+D$19))^(4+1-FixTV)-IF(FixND=1,NDmult*DCF!$M$21,0) -> 202642.39 | E29: =NPV(IF(FixInfl=1,(1+$B29+E$19)*(1+InflLT)-1,$B29+E$19),DCF!$P$37:$S$37)+DCF!$S$37*(1+gLT)/(IF(FixInfl=1,(1+$B29+E$19)*(1+InflLT)-1,$B29+E$19)-gLT)/(1+IF(FixInfl=1,(1+$B29+E$19)*(1+InflLT)-1,$B29+E$19))^(4+1-FixTV)-IF(FixND=1,NDmult*DCF!$M$21,0) -> 181883.6 | F29: =NPV(IF(FixInfl=1,(1+$B29+F$19)*(1+InflLT)-1,$B29+F$19),DCF!$P$37:$S$37)+DCF!$S$37*(1+gLT)/(IF(FixInfl=1,(1+$B29+F$19)*(1+InflLT)-1,$B29+F$19)-gLT)/(1+IF(FixInfl=1,(1+$B29+F$19)*(1+InflLT)-1,$B29+F$19))^(4+1-FixTV)-IF(FixND=1,NDmult*DCF!$M$21,0) -> 164873.6 | G29: =NPV(IF(FixInfl=1,(1+$B29+G$19)*(1+InflLT)-1,$B29+G$19),DCF!$P$37:$S$37)+DCF!$S$37*(1+gLT)/(IF(FixInfl=1,(1+$B29+G$19)*(1+InflLT)-1,$B29+G$19)-gLT)/(1+IF(FixInfl=1,(1+$B29+G$19)*(1+InflLT)-1,$B29+G$19))^(4+1-FixTV)-IF(FixND=1,NDmult*DCF!$M$21,0) -> 150692.86
B30: 0.095 | C30: =NPV(IF(FixInfl=1,(1+$B30+C$19)*(1+InflLT)-1,$B30+C$19),DCF!$P$37:$S$37)+DCF!$S$37*(1+gLT)/(IF(FixInfl=1,(1+$B30+C$19)*(1+InflLT)-1,$B30+C$19)-gLT)/(1+IF(FixInfl=1,(1+$B30+C$19)*(1+InflLT)-1,$B30+C$19))^(4+1-FixTV)-IF(FixND=1,NDmult*DCF!$M$21,0) -> 214829.39 | D30: =NPV(IF(FixInfl=1,(1+$B30+D$19)*(1+InflLT)-1,$B30+D$19),DCF!$P$37:$S$37)+DCF!$S$37*(1+gLT)/(IF(FixInfl=1,(1+$B30+D$19)*(1+InflLT)-1,$B30+D$19)-gLT)/(1+IF(FixInfl=1,(1+$B30+D$19)*(1+InflLT)-1,$B30+D$19))^(4+1-FixTV)-IF(FixND=1,NDmult*DCF!$M$21,0) -> 191722.24 | E30: =NPV(IF(FixInfl=1,(1+$B30+E$19)*(1+InflLT)-1,$B30+E$19),DCF!$P$37:$S$37)+DCF!$S$37*(1+gLT)/(IF(FixInfl=1,(1+$B30+E$19)*(1+InflLT)-1,$B30+E$19)-gLT)/(1+IF(FixInfl=1,(1+$B30+E$19)*(1+InflLT)-1,$B30+E$19))^(4+1-FixTV)-IF(FixND=1,NDmult*DCF!$M$21,0) -> 172975.46 | F30: =NPV(IF(FixInfl=1,(1+$B30+F$19)*(1+InflLT)-1,$B30+F$19),DCF!$P$37:$S$37)+DCF!$S$37*(1+gLT)/(IF(FixInfl=1,(1+$B30+F$19)*(1+InflLT)-1,$B30+F$19)-gLT)/(1+IF(FixInfl=1,(1+$B30+F$19)*(1+InflLT)-1,$B30+F$19))^(4+1-FixTV)-IF(FixND=1,NDmult*DCF!$M$21,0) -> 157474.85 | G30: =NPV(IF(FixInfl=1,(1+$B30+G$19)*(1+InflLT)-1,$B30+G$19),DCF!$P$37:$S$37)+DCF!$S$37*(1+gLT)/(IF(FixInfl=1,(1+$B30+G$19)*(1+InflLT)-1,$B30+G$19)-gLT)/(1+IF(FixInfl=1,(1+$B30+G$19)*(1+InflLT)-1,$B30+G$19))^(4+1-FixTV)-IF(FixND=1,NDmult*DCF!$M$21,0) -> 144454.79
B34: Upside vs the Ibovespa used
B35: Real rate \ ERP | C35: =C$19 -> 0.04 | D35: =D$19 -> 0.05 | E35: =E$19 -> 0.06 | F35: =F$19 -> 0.07 | G35: =G$19 -> 0.08
B36: =$B$20 -> 0.05 | C36: =C20/IbovUsed-1 -> 1.1821239 | D36: =D20/IbovUsed-1 -> 0.75541144 | E36: =E20/IbovUsed-1 -> 0.46511993 | F36: =F20/IbovUsed-1 -> 0.25512225 | G36: =G20/IbovUsed-1 -> 0.096345059
B37: =$B$21 -> 0.055 | C37: =C21/IbovUsed-1 -> 0.94637972 | D37: =D21/IbovUsed-1 -> 0.5976284 | E37: =E21/IbovUsed-1 -> 0.35230239 | F37: =F21/IbovUsed-1 -> 0.1705656 | G37: =G21/IbovUsed-1 -> 0.030693331
B38: =$B$22 -> 0.06 | C38: =C22/IbovUsed-1 -> 0.75541144 | D38: =D22/IbovUsed-1 -> 0.46511993 | E38: =E22/IbovUsed-1 -> 0.25512225 | F38: =F22/IbovUsed-1 -> 0.096345059 | G38: =G22/IbovUsed-1 -> -0.027776609
B39: =$B$23 -> 0.065 | C39: =C23/IbovUsed-1 -> 0.5976284 | D39: =D23/IbovUsed-1 -> 0.35230239 | E39: =E23/IbovUsed-1 -> 0.1705656 | F39: =F23/IbovUsed-1 -> 0.030693331 | G39: =G23/IbovUsed-1 -> -0.080168523
B40: =$B$24 -> 0.0676 | C40: =C24/IbovUsed-1 -> 0.52596591 | D40: =D24/IbovUsed-1 -> 0.30002773 | E40: =E24/IbovUsed-1 -> 0.13080299 | F40: =F24/IbovUsed-1 -> -0.00053182661 | G40: =G24/IbovUsed-1 -> -0.10531254
B41: =$B$25 -> 0.07 | C41: =C25/IbovUsed-1 -> 0.46511993 | D41: =D25/IbovUsed-1 -> 0.25512225 | E41: =E25/IbovUsed-1 -> 0.096345059 | F41: =F25/IbovUsed-1 -> -0.027776609 | G41: =G25/IbovUsed-1 -> -0.12737168
B42: =$B$26 -> 0.075 | C42: =C26/IbovUsed-1 -> 0.35230239 | D42: =D26/IbovUsed-1 -> 0.1705656 | E42: =E26/IbovUsed-1 -> 0.030693331 | F42: =F26/IbovUsed-1 -> -0.080168523 | G42: =G26/IbovUsed-1 -> -0.1701105
B43: =$B$27 -> 0.08 | C43: =C27/IbovUsed-1 -> 0.25512225 | D43: =D27/IbovUsed-1 -> 0.096345059 | E43: =E27/IbovUsed-1 -> -0.027776609 | F43: =F27/IbovUsed-1 -> -0.12737168 | G43: =G27/IbovUsed-1 -> -0.20898106
B44: =$B$28 -> 0.085 | C44: =C28/IbovUsed-1 -> 0.1705656 | D44: =D28/IbovUsed-1 -> 0.030693331 | E44: =E28/IbovUsed-1 -> -0.080168523 | F44: =F28/IbovUsed-1 -> -0.1701105 | G44: =G28/IbovUsed-1 -> -0.24447826
B45: =$B$29 -> 0.09 | C45: =C29/IbovUsed-1 -> 0.096345059 | D45: =D29/IbovUsed-1 -> -0.027776609 | E45: =E29/IbovUsed-1 -> -0.12737168 | F45: =F29/IbovUsed-1 -> -0.20898106 | G45: =G29/IbovUsed-1 -> -0.27701641
B46: =$B$30 -> 0.095 | C46: =C30/IbovUsed-1 -> 0.030693331 | D46: =D30/IbovUsed-1 -> -0.080168523 | E46: =E30/IbovUsed-1 -> -0.1701105 | F46: =F30/IbovUsed-1 -> -0.24447826 | G46: =G30/IbovUsed-1 -> -0.30694497
B51: Framed cell = base real rate and base ERP. The grid uses the switches in Assumptions section 4.

Sheet Support >

Sheet Box Rates
B1: Ibovespa - Box discount rates: house, relative to history or CAPM
B2: Box rate - g = (house rate - g) x relative cash yield; relative cash yield = (10y average earnings yield x cash conversion) / the same for the Ibovespa.
B3: Legend: | C3: input | D3: assumption | E3: formula
B5: 1. Historical cash yield relative to the Ibovespa (12m fwd, Oct-16..Sep-26)
B6: Group | C6: Cash conversion 2031 (FCFF or FCFE / net income) | D6: Average earnings yield (section 3) | E6: Average P/E = 1 / yield | F6: Cash yield = conversion x earnings yield | G6: Relative to the Ibovespa | H6: CAPM beta used (Box Betas)
B7: Financials | C7: ='DCF by Box'!$H$40/'DCF by Box'!$H$27 -> 0.76346986 | D7: =AVERAGE(C$32:C$151) -> 0.12075605 | E7: =1/D7 -> 8.2811588 | F7: =C7*D7 -> 0.092193602 | G7: =F7/$F$11 -> 0.9245176 | H7: ='Box Betas'!I7 -> 1.1490637
B8: Defensives | C8: ='DCF by Box'!$H$89/'DCF by Box'!$H$81 -> 0.84896206 | D8: =AVERAGE(D$32:D$151) -> 0.074616957 | E8: =1/D8 -> 13.401779 | F8: =C8*D8 -> 0.063346966 | G8: =F8/$F$11 -> 0.63524349 | H8: ='Box Betas'!I8 -> 0.92867396
B9: Cyclicals | C9: ='DCF by Box'!$H$136/'DCF by Box'!$H$128 -> 0.49913291 | D9: =AVERAGE(E$32:E$151) -> 0.059397862 | E9: =1/D9 -> 16.835623 | F9: =C9*D9 -> 0.029647427 | G9: =F9/$F$11 -> 0.29730445 | H9: ='Box Betas'!I9 -> 1.1504511
B10: Commodities | C10: ='DCF by Box'!$H$183/'DCF by Box'!$H$175 -> 1.0114872 | D10: =AVERAGE(F$32:F$151) -> 0.15136059 | E10: =1/D10 -> 6.6067396 | F10: =C10*D10 -> 0.15309929 | G10: =F10/$F$11 -> 1.53528 | H10: ='Box Betas'!I10 -> 0.87168584
B11: Ibovespa | C11: =DCF!$S$37/DCF!$S$29 -> 0.88778375 | D11: =AVERAGE(G$32:G$151) -> 0.11232551 | E11: =1/D11 -> 8.902697 | F11: =C11*D11 -> 0.099720765 | G11: =F11/$F$11 -> 1 | H11: ='Box Betas'!I11 -> 1
B12: Memo (inside Cyclicals)
B13: Cyclicals ex-WEG & Embraer | C13: ='DCF by Box'!$H$230/'DCF by Box'!$H$222 -> 0.48381774 | D13: =AVERAGE(H$32:H$151) -> 0.06603499 | E13: =1/D13 -> 15.143487 | F13: =C13*D13 -> 0.031948899 | G13: =F13/$F$11 -> 0.32038362 | H13: ='Box Betas'!I13 -> 1.3187146
B14: WEG & Embraer | C14: ='DCF by Box'!$H$277/'DCF by Box'!$H$269 -> 0.54944199 | D14: =AVERAGE(I$32:I$151) -> 0.042104976 | E14: =1/D14 -> 23.750162 | F14: =C14*D14 -> 0.023134242 | G14: =F14/$F$11 -> 0.23199022 | H14: ='Box Betas'!I14 -> 0.71783452
B15: Cash conversion: the box's FCFF (Financials: FCFE) / net income in 2031, the year the terminal value grows from (DCF by Box; Ibovespa: DCF sheet).
B17: 2. Discount rate by box (fair value at the end of 2027)
C18: Bear | D18: Base | E18: Bull | G18: Risk premium: Bear | H18: Base | I18: Bull
B19: House discount rate (DCF sheet) | C19: =DCF!C48 -> 0.145 | D19: =DCF!D48 -> 0.1276 | E19: =DCF!E48 -> 0.115 | G19: =C19-C20 -> 0.06 | H19: =D19-D20 -> 0.06 | I19: =E19-E20 -> 0.06
B20: 5-year real rate (DCF sheet) | C20: =DCF!C46 -> 0.085 | D20: =DCF!D46 -> 0.0676 | E20: =DCF!E46 -> 0.055
B21: Financials | C21: =CHOOSE(BoxRate+1,C$19,MAX(gLT+(C$19-gLT)*$G$7,C$20+ERPfloor),IF(FixInfl=1,(1+C$20+$H$7*DCF!C$47+RateShock*($H$7-1)*(C$20-$D$20))*(1+InflLT)-1,C$20+$H$7*DCF!C$47+RateShock*($H$7-1)*(C$20-$D$20))) -> 0.15394382 | D21: =CHOOSE(BoxRate+1,D$19,MAX(gLT+(D$19-gLT)*$G$7,D$20+ERPfloor),IF(FixInfl=1,(1+D$20+$H$7*DCF!D$47+RateShock*($H$7-1)*(D$20-$D$20))*(1+InflLT)-1,D$20+$H$7*DCF!D$47+RateShock*($H$7-1)*(D$20-$D$20))) -> 0.13654382 | E21: =CHOOSE(BoxRate+1,E$19,MAX(gLT+(E$19-gLT)*$G$7,E$20+ERPfloor),IF(FixInfl=1,(1+E$20+$H$7*DCF!E$47+RateShock*($H$7-1)*(E$20-$D$20))*(1+InflLT)-1,E$20+$H$7*DCF!E$47+RateShock*($H$7-1)*(E$20-$D$20))) -> 0.12394382 | G21: =C21-C$20 -> 0.068943819 | H21: =D21-D$20 -> 0.068943819 | I21: =E21-E$20 -> 0.068943819
B22: Defensives | C22: =CHOOSE(BoxRate+1,C$19,MAX(gLT+(C$19-gLT)*$G$8,C$20+ERPfloor),IF(FixInfl=1,(1+C$20+$H$8*DCF!C$47+RateShock*($H$8-1)*(C$20-$D$20))*(1+InflLT)-1,C$20+$H$8*DCF!C$47+RateShock*($H$8-1)*(C$20-$D$20))) -> 0.14072044 | D22: =CHOOSE(BoxRate+1,D$19,MAX(gLT+(D$19-gLT)*$G$8,D$20+ERPfloor),IF(FixInfl=1,(1+D$20+$H$8*DCF!D$47+RateShock*($H$8-1)*(D$20-$D$20))*(1+InflLT)-1,D$20+$H$8*DCF!D$47+RateShock*($H$8-1)*(D$20-$D$20))) -> 0.12332044 | E22: =CHOOSE(BoxRate+1,E$19,MAX(gLT+(E$19-gLT)*$G$8,E$20+ERPfloor),IF(FixInfl=1,(1+E$20+$H$8*DCF!E$47+RateShock*($H$8-1)*(E$20-$D$20))*(1+InflLT)-1,E$20+$H$8*DCF!E$47+RateShock*($H$8-1)*(E$20-$D$20))) -> 0.11072044 | G22: =C22-C$20 -> 0.055720438 | H22: =D22-D$20 -> 0.055720438 | I22: =E22-E$20 -> 0.055720438
B23: Cyclicals | C23: =CHOOSE(BoxRate+1,C$19,MAX(gLT+(C$19-gLT)*$G$9,C$20+ERPfloor),IF(FixInfl=1,(1+C$20+$H$9*DCF!C$47+RateShock*($H$9-1)*(C$20-$D$20))*(1+InflLT)-1,C$20+$H$9*DCF!C$47+RateShock*($H$9-1)*(C$20-$D$20))) -> 0.15402707 | D23: =CHOOSE(BoxRate+1,D$19,MAX(gLT+(D$19-gLT)*$G$9,D$20+ERPfloor),IF(FixInfl=1,(1+D$20+$H$9*DCF!D$47+RateShock*($H$9-1)*(D$20-$D$20))*(1+InflLT)-1,D$20+$H$9*DCF!D$47+RateShock*($H$9-1)*(D$20-$D$20))) -> 0.13662707 | E23: =CHOOSE(BoxRate+1,E$19,MAX(gLT+(E$19-gLT)*$G$9,E$20+ERPfloor),IF(FixInfl=1,(1+E$20+$H$9*DCF!E$47+RateShock*($H$9-1)*(E$20-$D$20))*(1+InflLT)-1,E$20+$H$9*DCF!E$47+RateShock*($H$9-1)*(E$20-$D$20))) -> 0.12402707 | G23: =C23-C$20 -> 0.069027066 | H23: =D23-D$20 -> 0.069027066 | I23: =E23-E$20 -> 0.069027066
B24: Commodities | C24: =CHOOSE(BoxRate+1,C$19,MAX(gLT+(C$19-gLT)*$G$10,C$20+ERPfloor),IF(FixInfl=1,(1+C$20+$H$10*DCF!C$47+RateShock*($H$10-1)*(C$20-$D$20))*(1+InflLT)-1,C$20+$H$10*DCF!C$47+RateShock*($H$10-1)*(C$20-$D$20))) -> 0.13730115 | D24: =CHOOSE(BoxRate+1,D$19,MAX(gLT+(D$19-gLT)*$G$10,D$20+ERPfloor),IF(FixInfl=1,(1+D$20+$H$10*DCF!D$47+RateShock*($H$10-1)*(D$20-$D$20))*(1+InflLT)-1,D$20+$H$10*DCF!D$47+RateShock*($H$10-1)*(D$20-$D$20))) -> 0.11990115 | E24: =CHOOSE(BoxRate+1,E$19,MAX(gLT+(E$19-gLT)*$G$10,E$20+ERPfloor),IF(FixInfl=1,(1+E$20+$H$10*DCF!E$47+RateShock*($H$10-1)*(E$20-$D$20))*(1+InflLT)-1,E$20+$H$10*DCF!E$47+RateShock*($H$10-1)*(E$20-$D$20))) -> 0.10730115 | G24: =C24-C$20 -> 0.05230115 | H24: =D24-D$20 -> 0.05230115 | I24: =E24-E$20 -> 0.05230115
B25: Memo (inside Cyclicals)
B26: Cyclicals ex-WEG & Embraer | C26: =CHOOSE(BoxRate+1,C$19,MAX(gLT+(C$19-gLT)*$G$13,C$20+ERPfloor),IF(FixInfl=1,(1+C$20+$H$13*DCF!C$47+RateShock*($H$13-1)*(C$20-$D$20))*(1+InflLT)-1,C$20+$H$13*DCF!C$47+RateShock*($H$13-1)*(C$20-$D$20))) -> 0.16412287 | D26: =CHOOSE(BoxRate+1,D$19,MAX(gLT+(D$19-gLT)*$G$13,D$20+ERPfloor),IF(FixInfl=1,(1+D$20+$H$13*DCF!D$47+RateShock*($H$13-1)*(D$20-$D$20))*(1+InflLT)-1,D$20+$H$13*DCF!D$47+RateShock*($H$13-1)*(D$20-$D$20))) -> 0.14672287 | E26: =CHOOSE(BoxRate+1,E$19,MAX(gLT+(E$19-gLT)*$G$13,E$20+ERPfloor),IF(FixInfl=1,(1+E$20+$H$13*DCF!E$47+RateShock*($H$13-1)*(E$20-$D$20))*(1+InflLT)-1,E$20+$H$13*DCF!E$47+RateShock*($H$13-1)*(E$20-$D$20))) -> 0.13412287 | G26: =C26-C$20 -> 0.079122874 | H26: =D26-D$20 -> 0.079122874 | I26: =E26-E$20 -> 0.079122874
B27: WEG & Embraer | C27: =CHOOSE(BoxRate+1,C$19,MAX(gLT+(C$19-gLT)*$G$14,C$20+ERPfloor),IF(FixInfl=1,(1+C$20+$H$14*DCF!C$47+RateShock*($H$14-1)*(C$20-$D$20))*(1+InflLT)-1,C$20+$H$14*DCF!C$47+RateShock*($H$14-1)*(C$20-$D$20))) -> 0.12807007 | D27: =CHOOSE(BoxRate+1,D$19,MAX(gLT+(D$19-gLT)*$G$14,D$20+ERPfloor),IF(FixInfl=1,(1+D$20+$H$14*DCF!D$47+RateShock*($H$14-1)*(D$20-$D$20))*(1+InflLT)-1,D$20+$H$14*DCF!D$47+RateShock*($H$14-1)*(D$20-$D$20))) -> 0.11067007 | E27: =CHOOSE(BoxRate+1,E$19,MAX(gLT+(E$19-gLT)*$G$14,E$20+ERPfloor),IF(FixInfl=1,(1+E$20+$H$14*DCF!E$47+RateShock*($H$14-1)*(E$20-$D$20))*(1+InflLT)-1,E$20+$H$14*DCF!E$47+RateShock*($H$14-1)*(E$20-$D$20))) -> 0.098070071 | G27: =C27-C$20 -> 0.043070071 | H27: =D27-D$20 -> 0.043070071 | I27: =E27-E$20 -> 0.043070071
B28: BoxRate 0: the house rate. 1: g + (house rate - g) x relative cash yield, at least real rate + floor. 2: CAPM, real rate + beta x house ERP (Fisher if FixInfl = 1); with RateShock = 1 the scenario's real-rate change passes through the beta: + (beta - 1) x change. Risk premium = rate - real rate.
B30: 3. Monthly 12m fwd earnings yield by box (1 / harmonic P/E of the month's members; Bloomberg panel of the multiples model)
B31: Month-end | C31: Financials | D31: Defensives | E31: Cyclicals | F31: Commodities | G31: Ibovespa | H31: Cyclicals ex-WEG & Embraer | I31: WEG & Embraer
B32: 42674 | C32: 0.097129301 | D32: 0.054043084 | E32: 0.061020751 | F32: 0.059499887 | G32: 0.071929311 | H32: 0.059724662 | I32: 0.068374833
B33: 42704 | C33: 0.10999658 | D33: 0.059068695 | E33: 0.068871355 | F33: 0.056921621 | G33: 0.07740352 | H33: 0.067637157 | I33: 0.075473874
B34: 42735 | C34: 0.11380828 | D34: 0.060950372 | E34: 0.069286831 | F34: 0.074568531 | G34: 0.084370771 | H34: 0.067704258 | I34: 0.078184002
B35: 42766 | C35: 0.10434124 | D35: 0.058688993 | E35: 0.067259516 | F35: 0.077537889 | G35: 0.081485863 | H35: 0.06644891 | I35: 0.071561336
B36: 42794 | C36: 0.10058139 | D36: 0.058304742 | E36: 0.064388348 | F36: 0.08627569 | G36: 0.08216617 | H36: 0.063605189 | I36: 0.06879095
B37: 42825 | C37: 0.10649035 | D37: 0.059366601 | E37: 0.064297621 | F37: 0.10213707 | G37: 0.088318039 | H37: 0.063701459 | I37: 0.067878586
B38: 42855 | C38: 0.1047335 | D38: 0.058662053 | E38: 0.062554795 | F38: 0.10251536 | G38: 0.086871579 | H38: 0.061623108 | I38: 0.068857016
B39: 42886 | C39: 0.11417637 | D39: 0.055875353 | E39: 0.067520158 | F39: 0.11641556 | G39: 0.093376516 | H39: 0.068145011 | I39: 0.064018648
B40: 42916 | C40: 0.11269323 | D40: 0.063002736 | E40: 0.067664863 | F40: 0.11070484 | G40: 0.093550509 | H40: 0.067580456 | I40: 0.068182556
B41: 42947 | C41: 0.1092513 | D41: 0.060343248 | E41: 0.063730894 | F41: 0.10091957 | G41: 0.088525712 | H41: 0.063542383 | I41: 0.064919083
B42: 42978 | C42: 0.10121318 | D42: 0.057276405 | E42: 0.05891732 | F42: 0.087965053 | G42: 0.081052692 | H42: 0.059428875 | I42: 0.055744274
B43: 43008 | C43: 0.094121653 | D43: 0.056487977 | E43: 0.054739012 | F43: 0.090717724 | G43: 0.078083076 | H43: 0.054853251 | I43: 0.05398122
... B151: 46295 | C151: 0.11841947 | D151: 0.076205395 | E151: 0.087337675 | F151: 0.15896093 | G151: 0.11635217 | H151: 0.1088258 | I151: 0.058419893

Sheet Box Betas
B1: Ibovespa - Box betas vs the Ibovespa (CAPM)
B2: Beta = covariance of the box's weekly total return with the Ibovespa's / variance of the Ibovespa's, over the window in Assumptions.
B3: Legend: | C3: input | D3: assumption | E3: formula
B5: 1. Beta of each box vs the Ibovespa (weekly total returns, window in Assumptions)
B6: Group | C6: Weeks in the window | D6: Average weekly return | E6: Covariance with the Ibovespa | F6: Variance of the Ibovespa | G6: Beta (raw) | H6: Beta (Blume adjusted) | I6: Beta used
B7: Financials | C7: =SUM($C$23:$C$544) -> 261 | D7: =SUMPRODUCT($C$23:$C$544,K$23:K$544)/C7 -> 0.0030820715 | E7: =(SUMPRODUCT($C$23:$C$544,K$23:K$544,O$23:O$544)-C7*D7*$D$11)/(C7-1) -> 0.00063674946 | F7: =(SUMPRODUCT($C$23:$C$544,O$23:O$544,O$23:O$544)-C7*$D$11^2)/(C7-1) -> 0.00055414638 | G7: =E7/F7 -> 1.1490637 | H7: =0.67*G7+0.33 -> 1.0998727 | I7: =IF(BetaAdj=2,H7,G7) -> 1.1490637
B8: Defensives | C8: =SUM($C$23:$C$544) -> 261 | D8: =SUMPRODUCT($C$23:$C$544,L$23:L$544)/C8 -> 0.0012762594 | E8: =(SUMPRODUCT($C$23:$C$544,L$23:L$544,O$23:O$544)-C8*D8*$D$11)/(C8-1) -> 0.00051462131 | F8: =(SUMPRODUCT($C$23:$C$544,O$23:O$544,O$23:O$544)-C8*$D$11^2)/(C8-1) -> 0.00055414638 | G8: =E8/F8 -> 0.92867396 | H8: =0.67*G8+0.33 -> 0.95221156 | I8: =IF(BetaAdj=2,H8,G8) -> 0.92867396
B9: Cyclicals | C9: =SUM($C$23:$C$544) -> 261 | D9: =SUMPRODUCT($C$23:$C$544,M$23:M$544)/C9 -> -1.0469226e-05 | E9: =(SUMPRODUCT($C$23:$C$544,M$23:M$544,O$23:O$544)-C9*D9*$D$11)/(C9-1) -> 0.00063751831 | F9: =(SUMPRODUCT($C$23:$C$544,O$23:O$544,O$23:O$544)-C9*$D$11^2)/(C9-1) -> 0.00055414638 | G9: =E9/F9 -> 1.1504511 | H9: =0.67*G9+0.33 -> 1.1008022 | I9: =IF(BetaAdj=2,H9,G9) -> 1.1504511
B10: Commodities | C10: =SUM($C$23:$C$544) -> 261 | D10: =SUMPRODUCT($C$23:$C$544,N$23:N$544)/C10 -> 0.0035658949 | E10: =(SUMPRODUCT($C$23:$C$544,N$23:N$544,O$23:O$544)-C10*D10*$D$11)/(C10-1) -> 0.00048304155 | F10: =(SUMPRODUCT($C$23:$C$544,O$23:O$544,O$23:O$544)-C10*$D$11^2)/(C10-1) -> 0.00055414638 | G10: =E10/F10 -> 0.87168584 | H10: =0.67*G10+0.33 -> 0.91402951 | I10: =IF(BetaAdj=2,H10,G10) -> 0.87168584
B11: Ibovespa | C11: =SUM($C$23:$C$544) -> 261 | D11: =SUMPRODUCT($C$23:$C$544,O$23:O$544)/C11 -> 0.0022357788 | E11: =(SUMPRODUCT($C$23:$C$544,O$23:O$544,O$23:O$544)-C11*D11*$D$11)/(C11-1) -> 0.00055414638 | F11: =(SUMPRODUCT($C$23:$C$544,O$23:O$544,O$23:O$544)-C11*$D$11^2)/(C11-1) -> 0.00055414638 | G11: =E11/F11 -> 1 | H11: =0.67*G11+0.33 -> 1 | I11: =IF(BetaAdj=2,H11,G11) -> 1
B12: Memo (inside Cyclicals)
B13: Cyclicals ex-WEG & Embraer | C13: =SUM($C$23:$C$544) -> 261 | D13: =SUMPRODUCT($C$23:$C$544,P$23:P$544)/C13 -> -0.0014397436 | E13: =(SUMPRODUCT($C$23:$C$544,P$23:P$544,O$23:O$544)-C13*D13*$D$11)/(C13-1) -> 0.0007307609 | F13: =(SUMPRODUCT($C$23:$C$544,O$23:O$544,O$23:O$544)-C13*$D$11^2)/(C13-1) -> 0.00055414638 | G13: =E13/F13 -> 1.3187146 | H13: =0.67*G13+0.33 -> 1.2135388 | I13: =IF(BetaAdj=2,H13,G13) -> 1.3187146
B14: WEG & Embraer | C14: =SUM($C$23:$C$544) -> 261 | D14: =SUMPRODUCT($C$23:$C$544,Q$23:Q$544)/C14 -> 0.0035937116 | E14: =(SUMPRODUCT($C$23:$C$544,Q$23:Q$544,O$23:O$544)-C14*D14*$D$11)/(C14-1) -> 0.0003977854 | F14: =(SUMPRODUCT($C$23:$C$544,O$23:O$544,O$23:O$544)-C14*$D$11^2)/(C14-1) -> 0.00055414638 | G14: =E14/F14 -> 0.71783452 | H14: =0.67*G14+0.33 -> 0.81094913 | I14: =IF(BetaAdj=2,H14,G14) -> 0.71783452
B16: Weighted average of the four box betas (~1) | C16: =SUMPRODUCT(I7:I10,'Box Shares'!C7:C10)/SUM('Box Shares'!C7:C10) -> 1.0031655
B17: Window: weeks after | C17: =EDATE($B$544,-12*BetaYears) -> 44464
B18: Source: box total-return indices (Economatica adjusted close, members at the previous month-end index weights; Oct-5 performance study, box_daily.parquet). The Ibovespa here is the sum of the four boxes.
B20: 2. Weekly data (Friday closes): index levels (inputs) and returns (formulas)
B21: Week | C21: In window (1/0) | D21: Financials, level | E21: Defensives, level | F21: Cyclicals, level | G21: Commodities, level | H21: Ibovespa, level | I21: Cyclicals ex-WEG & Embraer, level | J21: WEG & Embraer, level | K21: Financials, return | L21: Defensives, return | M21: Cyclicals, return | N21: Commodities, return | O21: Ibovespa, return | P21: Cyclicals ex-WEG & Embraer, return | Q21: WEG & Embraer, return
B22: 42636 | D22: 2.8362212 | E22: 2.4029919 | F22: 0.90378628 | G22: 0.84339519 | H22: 1.5783635 | I22: 0.95267186 | J22: 1.1819149
B23: 42643 | C23: =IF(B23>$C$17,1,0) -> 0 | D23: 2.8001254 | E23: 2.3817054 | F23: 0.89890386 | G23: 0.84952528 | H23: 1.5690736 | I23: 0.95185448 | J23: 1.1423026 | K23: =D23/D22-1 -> -0.012726725 | L23: =E23/E22-1 -> -0.0088583086 | M23: =F23/F22-1 -> -0.0054021796 | N23: =G23/G22-1 -> 0.007268344 | O23: =H23/H22-1 -> -0.0058857491 | P23: =I23/I22-1 -> -0.00085798315 | Q23: =J23/J22-1 -> -0.033515325
B24: 42650 | C24: =IF(B24>$C$17,1,0) -> 0 | D24: 2.9766966 | E24: 2.4208488 | F24: 0.92884678 | G24: 0.90979039 | H24: 1.6437996 | I24: 0.98455911 | J24: 1.1727671 | K24: =D24/D23-1 -> 0.063058329 | L24: =E24/E23-1 -> 0.016435028 | M24: =F24/F23-1 -> 0.033310483 | N24: =G24/G23-1 -> 0.070939752 | O24: =H24/H23-1 -> 0.047624242 | P24: =I24/I23-1 -> 0.034358849 | Q24: =J24/J23-1 -> 0.026669316
B25: 42657 | C25: =IF(B25>$C$17,1,0) -> 0 | D25: 3.0309802 | E25: 2.4025779 | F25: 0.92309053 | G25: 0.93843968 | H25: 1.6617599 | I25: 0.9783263 | J25: 1.1664974 | K25: =D25/D24-1 -> 0.018236173 | L25: =E25/E24-1 -> -0.0075473366 | M25: =F25/F24-1 -> -0.0061972024 | N25: =G25/G24-1 -> 0.031489991 | O25: =H25/H24-1 -> 0.010926088 | P25: =I25/I24-1 -> -0.0063305612 | Q25: =J25/J24-1 -> -0.0053460766
B26: 42664 | C26: =IF(B26>$C$17,1,0) -> 0 | D26: 3.1368775 | E26: 2.4129921 | F26: 0.95430764 | G26: 1.0139571 | H26: 1.7249901 | I26: 1.0097588 | J26: 1.2185095 | K26: =D26/D25-1 -> 0.034938297 | L26: =E26/E25-1 -> 0.0043345804 | M26: =F26/F25-1 -> 0.033818038 | N26: =G26/G25-1 -> 0.080471297 | O26: =H26/H25-1 -> 0.038050185 | P26: =I26/I25-1 -> 0.032128832 | Q26: =J26/J25-1 -> 0.044588256
B27: 42671 | C27: =IF(B27>$C$17,1,0) -> 0 | D27: 3.1533524 | E27: 2.370798 | F27: 0.93318344 | G27: 1.0493576 | H27: 1.7303738 | I27: 0.98437897 | J27: 1.2145578 | K27: =D27/D26-1 -> 0.0052520316 | L27: =E27/E26-1 -> -0.017486206 | M27: =F27/F26-1 -> -0.022135637 | N27: =G27/G26-1 -> 0.034913135 | O27: =H27/H26-1 -> 0.0031209749 | P27: =I27/I26-1 -> -0.025134529 | Q27: =J27/J26-1 -> -0.0032430408
B28: 42678 | C28: =IF(B28>$C$17,1,0) -> 0 | D28: 3.0921265 | E28: 2.2585034 | F28: 0.89988788 | G28: 0.97700476 | H28: 1.6580507 | I28: 0.93744822 | J28: 1.2587786 | K28: =D28/D27-1 -> -0.019416132 | L28: =E28/E27-1 -> -0.047365717 | M28: =F28/F27-1 -> -0.035679545 | N28: =G28/G27-1 -> -0.068949616 | O28: =H28/H27-1 -> -0.041796192 | P28: =I28/I27-1 -> -0.047675482 | Q28: =J28/J27-1 -> 0.036409028
B29: 42685 | C29: =IF(B29>$C$17,1,0) -> 0 | D29: 2.888352 | E29: 2.150716 | F29: 0.83820132 | G29: 1.0017697 | H29: 1.5945633 | I29: 0.86316304 | J29: 1.2453824 | K29: =D29/D28-1 -> -0.065901082 | L29: =E29/E28-1 -> -0.04772514 | M29: =F29/F28-1 -> -0.068549152 | N29: =G29/G28-1 -> 0.025347828 | O29: =H29/H28-1 -> -0.03829043 | P29: =I29/I28-1 -> -0.07924191 | Q29: =J29/J28-1 -> -0.010642291
B30: 42692 | C30: =IF(B30>$C$17,1,0) -> 0 | D30: 2.9567279 | E30: 2.2120121 | F30: 0.83408751 | G30: 0.9960464 | H30: 1.6149506 | I30: 0.85752472 | J30: 1.2494651 | K30: =D30/D29-1 -> 0.023672966 | L30: =E30/E29-1 -> 0.028500294 | M30: =F30/F29-1 -> -0.0049079116 | N30: =G30/G29-1 -> -0.0057131992 | O30: =H30/H29-1 -> 0.012785535 | P30: =I30/I29-1 -> -0.0065321595 | Q30: =J30/J29-1 -> 0.0032783344
B31: 42699 | C31: =IF(B31>$C$17,1,0) -> 0 | D31: 2.9596254 | E31: 2.2131989 | F31: 0.83893724 | G31: 1.0907753 | H31: 1.6583623 | I31: 0.87130813 | J31: 1.192757 | K31: =D31/D30-1 -> 0.0009799777 | L31: =E31/E30-1 -> 0.00053655115 | M31: =F31/F30-1 -> 0.005814415 | N31: =G31/G30-1 -> 0.095104864 | O31: =H31/H30-1 -> 0.026881138 | P31: =I31/I30-1 -> 0.016073482 | Q31: =J31/J30-1 -> -0.04538591
B32: 42706 | C32: =IF(B32>$C$17,1,0) -> 0 | D32: 2.8701871 | E32: 2.1193881 | F32: 0.81019204 | G32: 1.110478 | H32: 1.6259416 | I32: 0.8381695 | J32: 1.1755638 | K32: =D32/D31-1 -> -0.030219484 | L32: =E32/E31-1 -> -0.042387004 | M32: =F32/F31-1 -> -0.034263826 | N32: =G32/G31-1 -> 0.018063094 | O32: =H32/H31-1 -> -0.019549822 | P32: =I32/I31-1 -> -0.038033186 | Q32: =J32/J31-1 -> -0.0144147
B33: 42713 | C33: =IF(B33>$C$17,1,0) -> 0 | D33: 2.8782633 | E33: 2.1529599 | F33: 0.81053728 | G33: 1.1034389 | H33: 1.6304638 | I33: 0.84246307 | J33: 1.1476038 | K33: =D33/D32-1 -> 0.0028138319 | L33: =E33/E32-1 -> 0.015840343 | M33: =F33/F32-1 -> 0.00042612385 | N33: =G33/G32-1 -> -0.0063388709 | O33: =H33/H32-1 -> 0.0027812863 | P33: =I33/I32-1 -> 0.0051225561 | Q33: =J33/J32-1 -> -0.023784312
B34: 42720 | C34: =IF(B34>$C$17,1,0) -> 0 | D34: 2.7625784 | E34: 2.1299047 | F34: 0.78496025 | G34: 1.0481401 | H34: 1.5733805 | I34: 0.8160108 | J34: 1.1104346 | K34: =D34/D33-1 -> -0.040192591 | L34: =E34/E33-1 -> -0.010708592 | M34: =F34/F33-1 -> -0.031555649 | N34: =G34/G33-1 -> -0.050114968 | O34: =H34/H33-1 -> -0.035010507 | P34: =I34/I33-1 -> -0.031398736 | Q34: =J34/J33-1 -> -0.032388499
... B544: 46290 | C544: =IF(B544>$C$17,1,0) -> 1 | D544: 9.5756116 | E544: 4.4061862 | F544: 1.2196401 | G544: 6.3449697 | H544: 5.2095645 | I544: 0.71292613 | J544: 9.8330559 | K544: =D544/D543-1 -> -0.0047055902 | L544: =E544/E543-1 -> -0.0057913546 | M544: =F544/F543-1 -> 0.024536683 | N544: =G544/G543-1 -> -0.028530005 | O544: =H544/H543-1 -> -0.0092774246 | P544: =I544/I543-1 -> 0.031134181 | Q544: =J544/J543-1 -> 0.016586627

Sheet Box Earnings
B1: Ibovespa - Box earnings: sensitivity to the domestic and commodity cycles (DCF scenarios)
B2: Earnings beta = covariance of the box's 12-month EPS growth with the domestic cycle's (Ibovespa ex-Commodities) / variance of the domestic cycle's, over the window in Assumptions.
B3: Legend: | C3: input | D3: assumption | E3: formula
B5: 1. Earnings beta of each box to the domestic cycle (12-month change of the 12m fwd EPS, log; window in Assumptions)
B6: Group | C6: Months in the window | D6: Average 12-month growth | E6: Std. dev. of 12-month growth | F6: Covariance with the domestic cycle | G6: Earnings beta, estimated | H6: Override (blank = estimated) | I6: Domestic beta used | J6: Commodity price elasticity | K6: Correlation with the domestic cycle | L6: Std. dev. of 4-year growth, a year
B7: Financials | C7: =SUM($C$44:$C$271) -> 228 | D7: =SUMPRODUCT($C$44:$C$271,M$44:M$271)/C7 -> 0.13109332 | E7: =SQRT((SUMPRODUCT($C$44:$C$271,M$44:M$271,M$44:M$271)-C7*D7^2)/(C7-1)) -> 0.093001739 | F7: =(SUMPRODUCT($C$44:$C$271,M$44:M$271,T$44:T$271)-C7*D7*$D$11)/(C7-1) -> 0.0076044919 | G7: =F7/$E$11^2 -> 0.73275922 | I7: =IF(ISNUMBER(H7),H7,G7) -> 0.73275922 | J7: 0 | K7: =F7/(E7*$E$11) -> 0.80264716 | L7: =SQRT((SUMPRODUCT($D$80:$D$271,U$80:U$271,U$80:U$271)-SUM($D$80:$D$271)*(SUMPRODUCT($D$80:$D$271,U$80:U$271)/SUM($D$80:$D$271))^2)/(SUM($D$80:$D$271)-1)) -> 0.021496371
B8: Defensives | C8: =SUM($C$44:$C$271) -> 228 | D8: =SUMPRODUCT($C$44:$C$271,N$44:N$271)/C8 -> 0.065858105 | E8: =SQRT((SUMPRODUCT($C$44:$C$271,N$44:N$271,N$44:N$271)-C8*D8^2)/(C8-1)) -> 0.10492219 | F8: =(SUMPRODUCT($C$44:$C$271,N$44:N$271,T$44:T$271)-C8*D8*$D$11)/(C8-1) -> 0.0068219816 | G8: =F8/$E$11^2 -> 0.65735752 | I8: =IF(ISNUMBER(H8),H8,G8) -> 0.65735752 | J8: 0 | K8: =F8/(E8*$E$11) -> 0.63824696 | L8: =SQRT((SUMPRODUCT($D$80:$D$271,V$80:V$271,V$80:V$271)-SUM($D$80:$D$271)*(SUMPRODUCT($D$80:$D$271,V$80:V$271)/SUM($D$80:$D$271))^2)/(SUM($D$80:$D$271)-1)) -> 0.058633029
B9: Cyclicals | C9: =SUM($C$44:$C$271) -> 228 | D9: =SUMPRODUCT($C$44:$C$271,O$44:O$271)/C9 -> 0.023327758 | E9: =SQRT((SUMPRODUCT($C$44:$C$271,O$44:O$271,O$44:O$271)-C9*D9^2)/(C9-1)) -> 0.17668787 | F9: =(SUMPRODUCT($C$44:$C$271,O$44:O$271,T$44:T$271)-C9*D9*$D$11)/(C9-1) -> 0.015470712 | G9: =F9/$E$11^2 -> 1.4907382 | I9: =IF(ISNUMBER(H9),H9,G9) -> 1.4907382 | J9: 0 | K9: =F9/(E9*$E$11) -> 0.85950641 | L9: =SQRT((SUMPRODUCT($D$80:$D$271,W$80:W$271,W$80:W$271)-SUM($D$80:$D$271)*(SUMPRODUCT($D$80:$D$271,W$80:W$271)/SUM($D$80:$D$271))^2)/(SUM($D$80:$D$271)-1)) -> 0.099740475
B10: Commodities | C10: =SUM($C$44:$C$271) -> 228 | D10: =SUMPRODUCT($C$44:$C$271,P$44:P$271)/C10 -> 0.11669997 | E10: =SQRT((SUMPRODUCT($C$44:$C$271,P$44:P$271,P$44:P$271)-C10*D10^2)/(C10-1)) -> 0.4375436 | F10: =(SUMPRODUCT($C$44:$C$271,P$44:P$271,T$44:T$271)-C10*D10*$D$11)/(C10-1) -> 0.020727233 | G10: =F10/$E$11^2 -> 1.9972499 | H10: 0 | I10: =IF(ISNUMBER(H10),H10,G10) -> 0 | J10: =(SUMPRODUCT($C$44:$C$271,P$44:P$271,AD$44:AD$271)-C10*D10*SUMPRODUCT($C$44:$C$271,AD$44:AD$271)/C10)/(SUMPRODUCT($C$44:$C$271,AD$44:AD$271,AD$44:AD$271)-C10*(SUMPRODUCT($C$44:$C$271,AD$44:AD$271)/C10)^2) -> 1.2620302 | K10: =F10/(E10*$E$11) -> 0.46501347 | L10: =SQRT((SUMPRODUCT($D$80:$D$271,X$80:X$271,X$80:X$271)-SUM($D$80:$D$271)*(SUMPRODUCT($D$80:$D$271,X$80:X$271)/SUM($D$80:$D$271))^2)/(SUM($D$80:$D$271)-1)) -> 0.22639297
B11: Domestic cycle: Ibovespa ex-Commodities | C11: =SUM($C$44:$C$271) -> 228 | D11: =SUMPRODUCT($C$44:$C$271,T$44:T$271)/C11 -> 0.085143315 | E11: =SQRT((SUMPRODUCT($C$44:$C$271,T$44:T$271,T$44:T$271)-C11*D11^2)/(C11-1)) -> 0.10187191 | F11: =(SUMPRODUCT($C$44:$C$271,T$44:T$271,T$44:T$271)-C11*D11*$D$11)/(C11-1) -> 0.010377886 | G11: =F11/$E$11^2 -> 1 | I11: =G11 -> 1 | J11: 0 | K11: =F11/(E11*$E$11) -> 1 | L11: =SQRT((SUMPRODUCT($D$80:$D$271,AB$80:AB$271,AB$80:AB$271)-SUM($D$80:$D$271)*(SUMPRODUCT($D$80:$D$271,AB$80:AB$271)/SUM($D$80:$D$271))^2)/(SUM($D$80:$D$271)-1)) -> 0.051104047
B12: Memo (inside Cyclicals)
B13: Cyclicals ex-WEG & Embraer | C13: =SUM($C$44:$C$271) -> 228 | D13: =SUMPRODUCT($C$44:$C$271,Q$44:Q$271)/C13 -> 0.013987526 | E13: =SQRT((SUMPRODUCT($C$44:$C$271,Q$44:Q$271,Q$44:Q$271)-C13*D13^2)/(C13-1)) -> 0.17719263 | F13: =(SUMPRODUCT($C$44:$C$271,Q$44:Q$271,T$44:T$271)-C13*D13*$D$11)/(C13-1) -> 0.015673325 | G13: =F13/$E$11^2 -> 1.5102618 | I13: =IF(ISNUMBER(H13),H13,G13) -> 1.5102618 | J13: 0 | K13: =F13/(E13*$E$11) -> 0.8682825 | L13: =SQRT((SUMPRODUCT($D$80:$D$271,Y$80:Y$271,Y$80:Y$271)-SUM($D$80:$D$271)*(SUMPRODUCT($D$80:$D$271,Y$80:Y$271)/SUM($D$80:$D$271))^2)/(SUM($D$80:$D$271)-1)) -> 0.096112498
B14: WEG & Embraer | C14: =SUM($C$44:$C$271) -> 228 | D14: =SUMPRODUCT($C$44:$C$271,R$44:R$271)/C14 -> 0.10655144 | E14: =SQRT((SUMPRODUCT($C$44:$C$271,R$44:R$271,R$44:R$271)-C14*D14^2)/(C14-1)) -> 0.32902461 | F14: =(SUMPRODUCT($C$44:$C$271,R$44:R$271,T$44:T$271)-C14*D14*$D$11)/(C14-1) -> 0.0013188874 | G14: =F14/$E$11^2 -> 0.12708633 | I14: =IF(ISNUMBER(H14),H14,G14) -> 0.12708633 | J14: 0 | K14: =F14/(E14*$E$11) -> 0.039348203 | L14: =SQRT((SUMPRODUCT($D$80:$D$271,Z$80:Z$271,Z$80:Z$271)-SUM($D$80:$D$271)*(SUMPRODUCT($D$80:$D$271,Z$80:Z$271)/SUM($D$80:$D$271))^2)/(SUM($D$80:$D$271)-1)) -> 0.19263655
B15: Weighted average of the domestic boxes (Financials, Defensives, Cyclicals; index points) | I15: =SUMPRODUCT(I7:I9,'Box Shares'!$C$7:$C$9)/SUM('Box Shares'!$C$7:$C$9) -> 0.84256023
B16: Normalization factor of the domestic betas (EBNorm) | I16: =IF(EBNorm=1,1/I15,1) -> 1.1868588
B17: Window: 12-month changes from | C17: =EBStart -> 39386
B18: Commodities follow commodity prices (correlation ~0.5 with the domestic cycle): domestic beta 0; its earnings move by the elasticity to commodity prices (column J, 12-month changes vs. the DJP commodity ETN). WEG & Embraer barely move with the domestic cycle.
B19: 2. Earnings level shock by box and scenario: normalized domestic beta x Ibovespa ex-Commodities shock + price elasticity x commodity prices
B20: Group | C20: Bear | D20: Base | E20: Bull
B21: Financials | C21: =$I$7*$I$16*Assumptions!C$61+$J$7*Assumptions!C$62 -> -0.17393634 | D21: =$I$7*$I$16*Assumptions!D$61+$J$7*Assumptions!D$62 -> 0 | E21: =$I$7*$I$16*Assumptions!E$61+$J$7*Assumptions!E$62 -> 0.17393634
B22: Defensives | C22: =$I$8*$I$16*Assumptions!C$61+$J$8*Assumptions!C$62 -> -0.15603811 | D22: =$I$8*$I$16*Assumptions!D$61+$J$8*Assumptions!D$62 -> 0 | E22: =$I$8*$I$16*Assumptions!E$61+$J$8*Assumptions!E$62 -> 0.15603811
B23: Cyclicals | C23: =$I$9*$I$16*Assumptions!C$61+$J$9*Assumptions!C$62 -> -0.35385915 | D23: =$I$9*$I$16*Assumptions!D$61+$J$9*Assumptions!D$62 -> 0 | E23: =$I$9*$I$16*Assumptions!E$61+$J$9*Assumptions!E$62 -> 0.35385915
B24: Commodities | C24: =$I$10*$I$16*Assumptions!C$61+$J$10*Assumptions!C$62 -> -0.25240604 | D24: =$I$10*$I$16*Assumptions!D$61+$J$10*Assumptions!D$62 -> 0 | E24: =$I$10*$I$16*Assumptions!E$61+$J$10*Assumptions!E$62 -> 0.25240604
B25: Ibovespa (weighted by index points) | C25: =SUMPRODUCT(C21:C24,'Box Shares'!$C$7:$C$10)/SUM('Box Shares'!$C$7:$C$10) -> -0.21644633 | D25: =SUMPRODUCT(D21:D24,'Box Shares'!$C$7:$C$10)/SUM('Box Shares'!$C$7:$C$10) -> 0 | E25: =SUMPRODUCT(E21:E24,'Box Shares'!$C$7:$C$10)/SUM('Box Shares'!$C$7:$C$10) -> 0.21644633
B26: Memo (inside Cyclicals)
B27: Cyclicals ex-WEG & Embraer | C27: =$I$13*$I$16*Assumptions!C$61+$J$13*Assumptions!C$62 -> -0.3584935 | D27: =$I$13*$I$16*Assumptions!D$61+$J$13*Assumptions!D$62 -> 0 | E27: =$I$13*$I$16*Assumptions!E$61+$J$13*Assumptions!E$62 -> 0.3584935
B28: WEG & Embraer | C28: =$I$14*$I$16*Assumptions!C$61+$J$14*Assumptions!C$62 -> -0.030166704 | D28: =$I$14*$I$16*Assumptions!D$61+$J$14*Assumptions!D$62 -> 0 | E28: =$I$14*$I$16*Assumptions!E$61+$J$14*Assumptions!E$62 -> 0.030166704
B29: The shock moves the level of the box's earnings and flows in every year, 2028 onward (DCF by Box, Box Fade); growth is unchanged. Zero in the base.
B30: 3. Monthly 12m fwd EPS index by group (matched sample, chain-linked; inputs) and its growth (formulas); commodity prices (DJP)
B31: Month-end | C31: In window, 12-month (1/0) | D31: In window, 4-year (1/0) | E31: Financials, EPS index | F31: Defensives, EPS index | G31: Cyclicals, EPS index | H31: Commodities, EPS index | I31: Cyclicals ex-WEG & Embraer, EPS index | J31: WEG & Embraer, EPS index | K31: Ibovespa, EPS index | L31: Ibovespa ex-Commodities, EPS index | M31: Financials, 12-month growth (log) | N31: Defensives, 12-month growth (log) | O31: Cyclicals, 12-month growth (log) | P31: Commodities, 12-month growth (log) | Q31: Cyclicals ex-WEG & Embraer, 12-month growth (log) | R31: WEG & Embraer, 12-month growth (log) | S31: Ibovespa, 12-month growth (log) | T31: Ibovespa ex-Commodities, 12-month growth (log) | U31: Financials, 4-year growth a year (log) | V31: Defensives, 4-year growth a year (log) | W31: Cyclicals, 4-year growth a year (log) | X31: Commodities, 4-year growth a year (log) | Y31: Cyclicals ex-WEG & Embraer, 4-year growth a year (log) | Z31: WEG & Embraer, 4-year growth a year (log) | AA31: Ibovespa, 4-year growth a year (log) | AB31: Ibovespa ex-Commodities, 4-year growth a year (log) | AC31: Commodity prices (DJP ETN) | AD31: Commodity prices, 12-month change (log)
B32: 39021 | E32: 1 | F32: 1 | G32: 1 | H32: 1 | I32: 1 | J32: 1 | K32: 1 | L32: 1 | AC32: 48.52
B33: 39051 | E33: 1.0213507 | F33: 1.0358144 | G33: 0.95387592 | H33: 1.0044656 | I33: 0.94564245 | J33: 0.96972199 | K33: 1.0100874 | L33: 1.0229905 | AC33: 51.169998
B34: 39082 | E34: 1.0353201 | F34: 1.0300169 | G34: 0.97893508 | H34: 1.079711 | I34: 0.98049659 | J34: 0.97589881 | K34: 1.0638685 | L34: 1.0281412 | AC34: 48.939999
B35: 39113 | E35: 1.0445816 | F35: 1.0297168 | G35: 0.99291534 | H35: 1.0597605 | I35: 0.9915976 | J35: 0.99916371 | K35: 1.0517953 | L35: 1.0337209 | AC35: 48.950001
B36: 39141 | E36: 1.0539609 | F36: 1.0186604 | G36: 0.95407147 | H36: 1.0614282 | I36: 0.93691413 | J36: 1.0103243 | K36: 1.0509531 | L36: 1.0272538 | AC36: 50.52
B37: 39172 | E37: 1.0746079 | F37: 1.0318365 | G37: 0.9795959 | H37: 1.0630335 | I37: 0.97366861 | J37: 1.0013893 | K37: 1.0576523 | L37: 1.0452462 | AC37: 50.82
B38: 39202 | E38: 1.080667 | F38: 1.0193609 | G38: 0.95101559 | H38: 1.1047361 | I38: 0.94660018 | J38: 0.96806663 | K38: 1.0843615 | L38: 1.0381744 | AC38: 51.400002
B39: 39233 | E39: 1.1109037 | F39: 1.0424692 | G39: 0.98750898 | H39: 1.1625919 | I39: 0.98823753 | J39: 0.97598789 | K39: 1.132684 | L39: 1.0668006 | AC39: 51.549999
B40: 39263 | E40: 1.1386189 | F40: 1.0968163 | G40: 1.0024702 | H40: 1.3094714 | I40: 1.0100226 | J40: 0.9534425 | K40: 1.2417462 | L40: 1.1051585 | AC40: 50.759998
B41: 39294 | E41: 1.1594703 | F41: 1.1654854 | G41: 0.91388027 | H41: 1.2949903 | I41: 0.90236703 | J41: 0.96920251 | K41: 1.2440562 | L41: 1.1343401 | AC41: 51.689999
B42: 39325 | E42: 1.1854266 | F42: 1.1967447 | G42: 0.95495245 | H42: 1.293188 | I42: 0.94813163 | J42: 0.9852722 | K42: 1.2550758 | L42: 1.1652007 | AC42: 49.82
B43: 39355 | E43: 1.1853752 | F43: 1.2046515 | G43: 0.98283098 | H43: 1.2247326 | I43: 0.97972406 | J43: 0.98151322 | K43: 1.2204833 | L43: 1.1746891 | AC43: 53.779999
B44: 39386 | C44: =IF(B44>=EBStart,1,0) -> 1 | E44: 1.1881695 | F44: 1.2191141 | G44: 1.0082653 | H44: 1.2949114 | I44: 1.0068297 | J44: 0.99309439 | K44: 1.2664159 | L44: 1.1879242 | M44: =LN(E44/E32) -> 0.1724139 | N44: =LN(F44/F32) -> 0.19812446 | O44: =LN(G44/G32) -> 0.0082313482 | P44: =LN(H44/H32) -> 0.25844225 | Q44: =LN(I44/I32) -> 0.0068065195 | R44: =LN(J44/J32) -> -0.0069295617 | S44: =LN(K44/K32) -> 0.23619075 | T44: =LN(L44/L32) -> 0.17220743 | AC44: 55.639999 | AD44: =LN(AC44/AC32) -> 0.13692626
B45: 39416 | C45: =IF(B45>=EBStart,1,0) -> 1 | E45: 1.2031992 | F45: 1.23545 | G45: 1.0120463 | H45: 1.2620146 | I45: 1.0236915 | J45: 0.89391132 | K45: 1.2539671 | L45: 1.2017025 | M45: =LN(E45/E33) -> 0.163858 | N45: =LN(F45/F33) -> 0.17624728 | O45: =LN(G45/G33) -> 0.059195957 | P45: =LN(H45/H33) -> 0.22825368 | Q45: =LN(I45/I33) -> 0.079305929 | R45: =LN(J45/J33) -> -0.08140285 | S45: =LN(K45/K33) -> 0.21627539 | T45: =LN(L45/L33) -> 0.16100907 | AC45: 53.869999 | AD45: =LN(AC45/AC33) -> 0.05142033
B46: 39447 | C46: =IF(B46>=EBStart,1,0) -> 1 | E46: 1.2111089 | F46: 1.2794174 | G46: 0.96151023 | H46: 1.2947396 | I46: 0.96370048 | J46: 0.920734 | K46: 1.2796139 | L46: 1.2177829 | M46: =LN(E46/E34) -> 0.15682578 | N46: =LN(F46/F34) -> 0.21682968 | O46: =LN(G46/G34) -> -0.017960117 | P46: =LN(H46/H34) -> 0.18161618 | Q46: =LN(I46/I34) -> -0.017278622 | R46: =LN(J46/J34) -> -0.05818772 | S46: =LN(K46/K34) -> 0.18464662 | T46: =LN(L46/L34) -> 0.16927939 | AC46: 56.23 | AD46: =LN(AC46/AC34) -> 0.13885538
B47: 39478 | C47: =IF(B47>=EBStart,1,0) -> 1 | E47: 1.2217282 | F47: 1.2764842 | G47: 0.99053157 | H47: 1.3246484 | I47: 0.9932365 | J47: 0.94491481 | K47: 1.2984076 | L47: 1.2250384 | M47: =LN(E47/E35) -> 0.15665001 | N47: =LN(F47/F35) -> 0.21482582 | O47: =LN(G47/G35) -> -0.0024036656 | P47: =LN(H47/H35) -> 0.22310419 | Q47: =LN(I47/I35) -> 0.001651423 | R47: =LN(J47/J35) -> -0.055823865 | S47: =LN(K47/K35) -> 0.21064006 | T47: =LN(L47/L35) -> 0.16980733 | AC47: 58.549999 | AD47: =LN(AC47/AC35) -> 0.17908169
B48: 39507 | C48: =IF(B48>=EBStart,1,0) -> 1 | E48: 1.3172267 | F48: 1.2747284 | G48: 1.0275939 | H48: 1.4059032 | I48: 1.0320564 | J48: 0.96686314 | K48: 1.3575832 | L48: 1.2597733 | M48: =LN(E48/E36) -> 0.22297319 | N48: =LN(F48/F36) -> 0.22424467 | O48: =LN(G48/G36) -> 0.074236704 | P48: =LN(H48/H36) -> 0.28106459 | Q48: =LN(I48/I36) -> 0.096716979 | R48: =LN(J48/J36) -> -0.043969671 | S48: =LN(K48/K36) -> 0.25600856 | T48: =LN(L48/L36) -> 0.20404272 | AC48: 65.669998 | AD48: =LN(AC48/AC36) -> 0.26227287
B49: 39538 | C49: =IF(B49>=EBStart,1,0) -> 1 | E49: 1.3689343 | F49: 1.2696524 | G49: 1.0506283 | H49: 1.4358254 | I49: 1.0607396 | J49: 0.94116286 | K49: 1.38169 | L49: 1.2773495 | M49: =LN(E49/E37) -> 0.2420767 | N49: =LN(F49/F37) -> 0.20740287 | O49: =LN(G49/G37) -> 0.070003548 | P49: =LN(H49/H37) -> 0.30061326 | Q49: =LN(I49/I37) -> 0.085650712 | R49: =LN(J49/J37) -> -0.062027441 | S49: =LN(K49/K37) -> 0.26725569 | T49: =LN(L49/L37) -> 0.20053478 | AC49: 61.400002 | AD49: =LN(AC49/AC37) -> 0.18911989
B50: 39568 | C50: =IF(B50>=EBStart,1,0) -> 1 | E50: 1.409744 | F50: 1.3165557 | G50: 1.0423845 | H50: 1.5110309 | I50: 1.0546584 | J50: 0.91491453 | K50: 1.4376578 | L50: 1.3124656 | M50: =LN(E50/E38) -> 0.26582974 | N50: =LN(F50/F38) -> 0.2558432 | O50: =LN(G50/G38) -> 0.091735729 | P50: =LN(H50/H38) -> 0.31318564 | Q50: =LN(I50/I38) -> 0.10809541 | R50: =LN(J50/J38) -> -0.056470264 | S50: =LN(K50/K38) -> 0.28202391 | T50: =LN(L50/L38) -> 0.23444368 | AC50: 64.129997 | AD50: =LN(AC50/AC38) -> 0.22127403
B51: 39599 | C51: =IF(B51>=EBStart,1,0) -> 1 | E51: 1.420257 | F51: 1.3187509 | G51: 1.0727291 | H51: 1.5172068 | I51: 1.0894939 | J51: 0.90438774 | K51: 1.4466397 | L51: 1.3238547 | M51: =LN(E51/E39) -> 0.24566405 | N51: =LN(F51/F39) -> 0.23509289 | O51: =LN(G51/G39) -> 0.082775642 | P51: =LN(H51/H39) -> 0.2662191 | Q51: =LN(I51/I39) -> 0.097545428 | R51: =LN(J51/J39) -> -0.076191996 | S51: =LN(K51/K39) -> 0.24465337 | T51: =LN(L51/L39) -> 0.21588369 | AC51: 65.5 | AD51: =LN(AC51/AC39) -> 0.23949795
B52: 39629 | C52: =IF(B52>=EBStart,1,0) -> 1 | E52: 1.4241253 | F52: 1.3004112 | G52: 1.0578855 | H52: 1.5416649 | I52: 1.0771564 | J52: 0.86891062 | K52: 1.4540608 | L52: 1.3134635 | M52: =LN(E52/E40) -> 0.22374178 | N52: =LN(F52/F40) -> 0.17026876 | O52: =LN(G52/G40) -> 0.053804928 | P52: =LN(H52/H40) -> 0.1632394 | Q52: =LN(I52/I40) -> 0.064351958 | R52: =LN(J52/J40) -> -0.092838853 | S52: =LN(K52/K40) -> 0.15784154 | T52: =LN(L52/L40) -> 0.17267876 | AC52: 71.510002 | AD52: =LN(AC52/AC40) -> 0.34272872
B53: 39660 | C53: =IF(B53>=EBStart,1,0) -> 1 | E53: 1.4478184 | F53: 1.3265079 | G53: 1.044004 | H53: 1.5325744 | I53: 1.0671709 | J53: 0.82408667 | K53: 1.4580983 | L53: 1.3306476 | M53: =LN(E53/E41) -> 0.22209465 | N53: =LN(F53/F41) -> 0.12941223 | O53: =LN(G53/G41) -> 0.13311902 | P53: =LN(H53/H41) -> 0.16844567 | Q53: =LN(I53/I41) -> 0.16774502 | R53: =LN(J53/J41) -> -0.16219788 | S53: =LN(K53/K41) -> 0.15875587 | T53: =LN(L53/L41) -> 0.15961467 | AC53: 62.799999 | AD53: =LN(AC53/AC41) -> 0.19469075
B54: 39691 | C54: =IF(B54>=EBStart,1,0) -> 1 | E54: 1.432747 | F54: 1.3368902 | G54: 1.0326333 | H54: 1.554508 | I54: 1.0512397 | J54: 0.84966919 | K54: 1.4677532 | L54: 1.3276206 | M54: =LN(E54/E42) -> 0.18949092 | N54: =LN(F54/F42) -> 0.11074105 | O54: =LN(G54/G42) -> 0.078205883 | P54: =LN(H54/H42) -> 0.18404867 | Q54: =LN(I54/I42) -> 0.10323205 | R54: =LN(J54/J42) -> -0.14807087 | S54: =LN(K54/K42) -> 0.15653683 | T54: =LN(L54/L42) -> 0.13049497 | AC54: 58.169998 | AD54: =LN(AC54/AC42) -> 0.15495322
B55: 39721 | C55: =IF(B55>=EBStart,1,0) -> 1 | E55: 1.4574972 | F55: 1.3307227 | G55: 1.0606479 | H55: 1.5920038 | I55: 1.0768392 | J55: 0.90017342 | K55: 1.4953527 | L55: 1.3424104 | M55: =LN(E55/E43) -> 0.20666135 | N55: =LN(F55/F43) -> 0.099531837 | O55: =LN(G55/G43) -> 0.076198016 | P55: =LN(H55/H43) -> 0.26227094 | Q55: =LN(I55/I43) -> 0.094514406 | R55: =LN(J55/J43) -> -0.086508051 | S55: =LN(K55/K43) -> 0.20311512 | T55: =LN(L55/L43) -> 0.13346333 | AC55: 51.540001 | AD55: =LN(AC55/AC43) -> -0.042543405
... B79: 40451 | C79: =IF(B79>=EBStart,1,0) -> 1 | E79: 1.8403593 | F79: 1.7569326 | G79: 1.1133218 | H79: 1.5567762 | I79: 1.1849799 | J79: 0.4521594 | K79: 1.5803475 | L79: 1.6264614 | M79: =LN(E79/E67) -> 0.25500251 | N79: =LN(F79/F67) -> 0.093845281 | O79: =LN(G79/G67) -> 0.12041822 | P79: =LN(H79/H67) -> 0.35268884 | Q79: =LN(I79/I67) -> 0.15210085 | R79: =LN(J79/J67) -> -0.36009126 | S79: =LN(K79/K67) -> 0.25642665 | T79: =LN(L79/L67) -> 0.1568182 | AC79: 42.279999 | AD79: =LN(AC79/AC67) -> 0.092098627
B80: 40482 | C80: =IF(B80>=EBStart,1,0) -> 1 | D80: =IF(B80>=EBStart,1,0) -> 1 | E80: 1.8596136 | F80: 1.7648035 | G80: 1.145779 | H80: 1.5168932 | I80: 1.2151784 | J80: 0.52667623 | K80: 1.5704988 | L80: 1.6507762 | M80: =LN(E80/E68) -> 0.2403719 | N80: =LN(F80/F68) -> 0.20504219 | O80: =LN(G80/G68) -> 0.14804752 | P80: =LN(H80/H68) -> 0.41028886 | Q80: =LN(I80/I68) -> 0.16097543 | R80: =LN(J80/J68) -> -0.025257848 | S80: =LN(K80/K68) -> 0.30922483 | T80: =LN(L80/L68) -> 0.20406091 | U80: =LN(E80/E32)/4 -> 0.15509218 | V80: =LN(F80/F32)/4 -> 0.14200983 | W80: =LN(G80/G32)/4 -> 0.034021192 | X80: =LN(H80/H32)/4 -> 0.10416607 | Y80: =LN(I80/I32)/4 -> 0.048722729 | Z80: =LN(J80/J32)/4 -> -0.16029232 | AA80: =LN(K80/K32)/4 -> 0.11284832 | AB80: =LN(L80/L32)/4 -> 0.12531141 | AC80: 44.470001 | AD80: =LN(AC80/AC68) -> 0.10818792
B81: 40512 | C81: =IF(B81>=EBStart,1,0) -> 1 | D81: =IF(B81>=EBStart,1,0) -> 1 | E81: 1.9350388 | F81: 1.7912298 | G81: 1.1593774 | H81: 1.5309511 | I81: 1.2280126 | J81: 0.55456898 | K81: 1.5950519 | L81: 1.6876731 | M81: =LN(E81/E69) -> 0.24787483 | N81: =LN(F81/F69) -> 0.21019889 | O81: =LN(G81/G69) -> 0.15304612 | P81: =LN(H81/H69) -> 0.39693071 | Q81: =LN(I81/I69) -> 0.15154915 | R81: =LN(J81/J69) -> 0.21828184 | S81: =LN(K81/K69) -> 0.30396741 | T81: =LN(L81/L69) -> 0.20736329 | U81: =LN(E81/E33)/4 -> 0.15975034 | V81: =LN(F81/F33)/4 -> 0.13692862 | W81: =LN(G81/G33)/4 -> 0.048776203 | X81: =LN(H81/H33)/4 -> 0.10535838 | Y81: =LN(I81/I33)/4 -> 0.065321961 | Z81: =LN(J81/J33)/4 -> -0.13970456 | AA81: =LN(K81/K33)/4 -> 0.11421736 | AB81: =LN(L81/L33)/4 -> 0.12515512 | AC81: 44.27 | AD81: =LN(AC81/AC69) -> 0.068718584
B82: 40543 | C82: =IF(B82>=EBStart,1,0) -> 1 | D82: =IF(B82>=EBStart,1,0) -> 1 | E82: 1.9672787 | F82: 1.8023775 | G82: 1.1830581 | H82: 1.5499772 | I82: 1.25227 | J82: 0.5776317 | K82: 1.6165856 | L82: 1.7123402 | M82: =LN(E82/E70) -> 0.24027111 | N82: =LN(F82/F70) -> 0.21347518 | O82: =LN(G82/G70) -> 0.16515582 | P82: =LN(H82/H70) -> 0.37021659 | Q82: =LN(I82/I70) -> 0.16364018 | R82: =LN(J82/J70) -> 0.24024183 | S82: =LN(K82/K70) -> 0.29069538 | T82: =LN(L82/L70) -> 0.20891771 | U82: =LN(E82/E34)/4 -> 0.16048516 | V82: =LN(F82/F34)/4 -> 0.13988287 | W82: =LN(G82/G34)/4 -> 0.047348168 | X82: =LN(H82/H34)/4 -> 0.090386698 | Y82: =LN(I82/I34)/4 -> 0.061163499 | Z82: =LN(J82/J34)/4 -> -0.13110561 | AA82: =LN(K82/K34)/4 -> 0.10460111 | AB82: =LN(L82/L34)/4 -> 0.1275271 | AC82: 49.119999 | AD82: =LN(AC82/AC70) -> 0.15042529
B83: 40574 | C83: =IF(B83>=EBStart,1,0) -> 1 | D83: =IF(B83>=EBStart,1,0) -> 1 | E83: 1.9898493 | F83: 1.7979783 | G83: 1.2176297 | H83: 1.5943739 | I83: 1.2885907 | J83: 0.59974874 | K83: 1.6505226 | L83: 1.7350607 | M83: =LN(E83/E71) -> 0.22584757 | N83: =LN(F83/F71) -> 0.21023626 | O83: =LN(G83/G71) -> 0.18252532 | P83: =LN(H83/H71) -> 0.34667055 | Q83: =LN(I83/I71) -> 0.1830958 | R83: =LN(J83/J71) -> 0.23426398 | S83: =LN(K83/K71) -> 0.27880091 | T83: =LN(L83/L71) -> 0.20850628 | U83: =LN(E83/E35)/4 -> 0.16111062 | V83: =LN(F83/F35)/4 -> 0.13934477 | W83: =LN(G83/G35)/4 -> 0.051003991 | X83: =LN(H83/H35)/4 -> 0.10210955 | Y83: =LN(I83/I35)/4 -> 0.065496761 | Z83: =LN(J83/J35)/4 -> -0.12760196 | AA83: =LN(K83/K35)/4 -> 0.11264835 | AB83: =LN(L83/L35)/4 -> 0.12946939 | AC83: 49.540001 | AD83: =LN(AC83/AC71) -> 0.24127223
B84: 40602 | C84: =IF(B84>=EBStart,1,0) -> 1 | D84: =IF(B84>=EBStart,1,0) -> 1 | E84: 2.0024455 | F84: 1.838778 | G84: 1.2331471 | H84: 1.6232086 | I84: 1.3048013 | J84: 0.61152917 | K84: 1.6767857 | L84: 1.7587912 | M84: =LN(E84/E72) -> 0.2084401 | N84: =LN(F84/F72) -> 0.18625648 | O84: =LN(G84/G72) -> 0.19567983 | P84: =LN(H84/H72) -> 0.36548844 | Q84: =LN(I84/I72) -> 0.19334332 | R84: =LN(J84/J72) -> 0.29676623 | S84: =LN(K84/K72) -> 0.2825147 | T84: =LN(L84/L72) -> 0.19696946 | U84: =LN(E84/E36)/4 -> 0.16045346 | V84: =LN(F84/F36)/4 -> 0.14765319 | W84: =LN(G84/G36)/4 -> 0.064146552 | X84: =LN(H84/H36)/4 -> 0.10619736 | Y84: =LN(I84/I36)/4 -> 0.082803595 | Z84: =LN(J84/J36)/4 -> -0.12551599 | AA84: =LN(K84/K36)/4 -> 0.11679529 | AB84: =LN(L84/L36)/4 -> 0.13443443 | AC84: 50.330002 | AD84: =LN(AC84/AC72) -> 0.21828755
B85: 40633 | C85: =IF(B85>=EBStart,1,0) -> 1 | D85: =IF(B85>=EBStart,1,0) -> 1 | E85: 2.0237681 | F85: 1.8131837 | G85: 1.2244769 | H85: 1.6600259 | I85: 1.2942437 | J85: 0.63374654 | K85: 1.6932762 | L85: 1.7528126 | M85: =LN(E85/E73) -> 0.18970464 | N85: =LN(F85/F73) -> 0.10670233 | O85: =LN(G85/G73) -> 0.15288744 | P85: =LN(H85/H73) -> 0.26786745 | Q85: =LN(I85/I73) -> 0.14914497 | R85: =LN(J85/J73) -> 0.30187529 | S85: =LN(K85/K73) -> 0.20988147 | T85: =LN(L85/L73) -> 0.14983415 | U85: =LN(E85/E37)/4 -> 0.15825132 | V85: =LN(F85/F37)/4 -> 0.140936 | W85: =LN(G85/G37)/4 -> 0.055782225 | X85: =LN(H85/H37)/4 -> 0.11142665 | Y85: =LN(I85/I37)/4 -> 0.071152691 | Z85: =LN(J85/J37)/4 -> -0.11437364 | AA85: =LN(K85/K37)/4 -> 0.11765339 | AB85: =LN(L85/L37)/4 -> 0.12924231 | AC85: 51.349998 | AD85: =LN(AC85/AC73) -> 0.25329158
B86: 40663 | C86: =IF(B86>=EBStart,1,0) -> 1 | D86: =IF(B86>=EBStart,1,0) -> 1 | E86: 2.0102455 | F86: 1.8410536 | G86: 1.2146151 | H86: 1.652632 | I86: 1.2862153 | J86: 0.58207326 | K86: 1.6891553 | L86: 1.7522036 | M86: =LN(E86/E74) -> 0.17154133 | N86: =LN(F86/F74) -> 0.11592577 | O86: =LN(G86/G74) -> 0.12541196 | P86: =LN(H86/H74) -> 0.17031938 | Q86: =LN(I86/I74) -> 0.12310659 | R86: =LN(J86/J74) -> 0.20408472 | S86: =LN(K86/K74) -> 0.15280963 | T86: =LN(L86/L74) -> 0.13790405 | U86: =LN(E86/E38)/4 -> 0.15516961 | V86: =LN(F86/F38)/4 -> 0.14779056 | W86: =LN(G86/G38)/4 -> 0.061163017 | X86: =LN(H86/H38)/4 -> 0.10069067 | Y86: =LN(I86/I38)/4 -> 0.076645624 | Z86: =LN(J86/J38)/4 -> -0.12717615 | AA86: =LN(K86/K38)/4 -> 0.11080931 | AB86: =LN(L86/L38)/4 -> 0.13085259 | AC86: 53.110001 | AD86: =LN(AC86/AC74) -> 0.26810472
B87: 40694 | C87: =IF(B87>=EBStart,1,0) -> 1 | D87: =IF(B87>=EBStart,1,0) -> 1 | E87: 2.0454059 | F87: 1.8282217 | G87: 1.2399242 | H87: 1.6463926 | I87: 1.3116979 | J87: 0.62385796 | K87: 1.6961284 | L87: 1.7736834 | M87: =LN(E87/E75) -> 0.16590701 | N87: =LN(F87/F75) -> 0.10293401 | O87: =LN(G87/G75) -> 0.14184452 | P87: =LN(H87/H75) -> 0.122785 | Q87: =LN(I87/I75) -> 0.13813424 | R87: =LN(J87/J75) -> 0.28020113 | S87: =LN(K87/K75) -> 0.1305535 | T87: =LN(L87/L75) -> 0.13942485 | U87: =LN(E87/E39)/4 -> 0.15260562 | V87: =LN(F87/F39)/4 -> 0.14043792 | W87: =LN(G87/G39)/4 -> 0.056904987 | X87: =LN(H87/H39)/4 -> 0.086983667 | Y87: =LN(I87/I39)/4 -> 0.070788643 | Z87: =LN(J87/J39)/4 -> -0.11188187 | AA87: =LN(K87/K39)/4 -> 0.10093955 | AB87: =LN(L87/L39)/4 -> 0.12709858 | AC87: 50.330002 | AD87: =LN(AC87/AC75) -> 0.28761588
B88: 40724 | C88: =IF(B88>=EBStart,1,0) -> 1 | D88: =IF(B88>=EBStart,1,0) -> 1 | E88: 2.0918578 | F88: 1.8572966 | G88: 1.2499175 | H88: 1.6113164 | I88: 1.3224911 | J88: 0.62398196 | K88: 1.6905204 | L88: 1.8010718 | M88: =LN(E88/E76) -> 0.17494078 | N88: =LN(F88/F76) -> 0.095223574 | O88: =LN(G88/G76) -> 0.14448128 | P88: =LN(H88/H76) -> 0.10133253 | Q88: =LN(I88/I76) -> 0.1396396 | R88: =LN(J88/J76) -> 0.30791206 | S88: =LN(K88/K76) -> 0.12002317 | T88: =LN(L88/L76) -> 0.14049458 | U88: =LN(E88/E40)/4 -> 0.15205914 | V88: =LN(F88/F40)/4 -> 0.13167756 | W88: =LN(G88/G40)/4 -> 0.055152611 | X88: =LN(H88/H40)/4 -> 0.05185698 | Y88: =LN(I88/I40)/4 -> 0.067386126 | Z88: =LN(J88/J40)/4 -> -0.10598941 | AA88: =LN(K88/K40)/4 -> 0.077129439 | AB88: =LN(L88/L40)/4 -> 0.12209829 | AC88: 47.23 | AD88: =LN(AC88/AC76) -> 0.22696198
B89: 40755 | C89: =IF(B89>=EBStart,1,0) -> 1 | D89: =IF(B89>=EBStart,1,0) -> 1 | E89: 2.0859168 | F89: 1.8384478 | G89: 1.2439616 | H89: 1.6082988 | I89: 1.3149389 | J89: 0.64972532 | K89: 1.6843527 | L89: 1.7912927 | M89: =LN(E89/E77) -> 0.14824032 | N89: =LN(F89/F77) -> 0.074987195 | O89: =LN(G89/G77) -> 0.14028218 | P89: =LN(H89/H77) -> 0.085170023 | Q89: =LN(I89/I77) -> 0.13874148 | R89: =LN(J89/J77) -> 0.23965855 | S89: =LN(K89/K77) -> 0.10375852 | T89: =LN(L89/L77) -> 0.12401242 | U89: =LN(E89/E41)/4 -> 0.14681131 | V89: =LN(F89/F41)/4 -> 0.113946 | W89: =LN(G89/G41)/4 -> 0.077089206 | X89: =LN(H89/H41)/4 -> 0.054168426 | Y89: =LN(I89/I41)/4 -> 0.094131032 | Z89: =LN(J89/J41)/4 -> -0.099980971 | AA89: =LN(K89/K41)/4 -> 0.075751039 | AB89: =LN(L89/L41)/4 -> 0.11422161 | AC89: 49.130001 | AD89: =LN(AC89/AC77) -> 0.19712633
B90: 40786 | C90: =IF(B90>=EBStart,1,0) -> 1 | D90: =IF(B90>=EBStart,1,0) -> 1 | E90: 2.0714175 | F90: 1.8221431 | G90: 1.2442688 | H90: 1.5773904 | I90: 1.3136081 | J90: 0.68714668 | K90: 1.6641698 | L90: 1.7828721 | M90: =LN(E90/E78) -> 0.13618348 | N90: =LN(F90/F78) -> 0.040267146 | O90: =LN(G90/G78) -> 0.13467455 | P90: =LN(H90/H78) -> 0.033139916 | Q90: =LN(I90/I78) -> 0.12799642 | R90: =LN(J90/J78) -> 0.39107932 | S90: =LN(K90/K78) -> 0.069351688 | T90: =LN(L90/L78) -> 0.10694504 | U90: =LN(E90/E42)/4 -> 0.13953262 | V90: =LN(F90/F42)/4 -> 0.10510206 | W90: =LN(G90/G42)/4 -> 0.06616045 | X90: =LN(H90/H42)/4 -> 0.049665352 | Y90: =LN(I90/I42)/4 -> 0.081509883 | Z90: =LN(J90/J42)/4 -> -0.090092545 | AA90: =LN(K90/K42)/4 -> 0.070532611 | AB90: =LN(L90/L42)/4 -> 0.10633306 | AC90: 49.470001 | AD90: =LN(AC90/AC78) -> 0.22861636
B91: 40816 | C91: =IF(B91>=EBStart,1,0) -> 1 | D91: =IF(B91>=EBStart,1,0) -> 1 | E91: 2.0979845 | F91: 1.7728802 | G91: 1.2535105 | H91: 1.6029402 | I91: 1.3217473 | J91: 0.73106975 | K91: 1.6781707 | L91: 1.7847486 | M91: =LN(E91/E79) -> 0.1310163 | N91: =LN(F91/F79) -> 0.0090360417 | O91: =LN(G91/G79) -> 0.11859983 | P91: =LN(H91/H79) -> 0.029222446 | Q91: =LN(I91/I79) -> 0.10922869 | R91: =LN(J91/J79) -> 0.48047409 | S91: =LN(K91/K79) -> 0.060059574 | T91: =LN(L91/L79) -> 0.092870791 | U91: =LN(E91/E43)/4 -> 0.14272943 | V91: =LN(F91/F43)/4 -> 0.096603784 | W91: =LN(G91/G43)/4 -> 0.060816534 | X91: =LN(H91/H43)/4 -> 0.067279261 | Y91: =LN(I91/I43)/4 -> 0.074859713 | Z91: =LN(J91/J43)/4 -> -0.073646655 | AA91: =LN(K91/K43)/4 -> 0.079614339 | AB91: =LN(L91/L43)/4 -> 0.10456851 | AC91: 41.740002 | AD91: =LN(AC91/AC79) -> -0.01285419
... B271: 46295 | C271: =IF(B271>=EBStart,1,0) -> 1 | D271: =IF(B271>=EBStart,1,0) -> 1 | E271: 13.78604 | F271: 3.9068387 | G271: 1.6060508 | H271: 12.339481 | I271: 1.3191681 | J271: 8.2295893 | K271: 8.4294062 | L271: 5.6549564 | M271: =LN(E271/E259) -> 0.14585151 | N271: =LN(F271/F259) -> 0.13784404 | O271: =LN(G271/G259) -> 0.19686109 | P271: =LN(H271/H259) -> 0.32925526 | Q271: =LN(I271/I259) -> 0.14491237 | R271: =LN(J271/J259) -> 0.34065098 | S271: =LN(K271/K259) -> 0.22982502 | T271: =LN(L271/L259) -> 0.15189172 | U271: =LN(E271/E223)/4 -> 0.13351704 | V271: =LN(F271/F223)/4 -> 0.10983444 | W271: =LN(G271/G223)/4 -> 0.18067362 | X271: =LN(H271/H223)/4 -> 0.076142727 | Y271: =LN(I271/I223)/4 -> 0.13632738 | Z271: =LN(J271/J223)/4 -> 0.34187851 | AA271: =LN(K271/K223)/4 -> 0.10279797 | AB271: =LN(L271/L223)/4 -> 0.1320624 | AC271: 51.52 | AD271: =LN(AC271/AC259) -> 0.374129

Sheet Box Fade
B1: Ibovespa - Fade after 2031, year by year (FadeMode 1 and 2)
B2: Growth steps down from the starting growth to g over FadeYears (mid-year steps: the H-model's area), then the Gordon formula; values at end-2031.
B3: Legend: | C3: input | D3: assumption | E3: formula
B5: 1. Value at end-2031 of the flows after 2031: year by year vs. the H-model formula
B6: Group | C6: Year by year: Bear | D6: Base | E6: Bull | F6: H-model formula: Bear | G6: Base | H6: Bull | I6: Base: year by year / H-model - 1
B7: Financials (FCFE) | C7: =$C$26 -> 52357.748 | D7: =$C$36 -> 75698.543 | E7: =$C$46 -> 103417.48 | F7: ='DCF by Box'!C54*((1+gLT)+FadeYears/2*('DCF by Box'!C45-gLT))/('DCF by Box'!C43-gLT) -> 52357.748 | G7: ='DCF by Box'!D54*((1+gLT)+FadeYears/2*('DCF by Box'!D45-gLT))/('DCF by Box'!D43-gLT) -> 75698.543 | H7: ='DCF by Box'!E54*((1+gLT)+FadeYears/2*('DCF by Box'!E45-gLT))/('DCF by Box'!E43-gLT) -> 103417.48 | I7: =D7/G7-1 -> -9.9920072e-16
B8: Defensives | C8: =$C$56 -> 43624.035 | D8: =$C$66 -> 63474.085 | E8: =$C$76 -> 87888.227 | F8: ='DCF by Box'!C98*((1+gLT)+FadeYears/2*('DCF by Box'!C97-gLT))/('DCF by Box'!C95-gLT) -> 43624.035 | G8: ='DCF by Box'!D98*((1+gLT)+FadeYears/2*('DCF by Box'!D97-gLT))/('DCF by Box'!D95-gLT) -> 63474.085 | H8: ='DCF by Box'!E98*((1+gLT)+FadeYears/2*('DCF by Box'!E97-gLT))/('DCF by Box'!E95-gLT) -> 87888.227 | I8: =D8/G8-1 -> 0
B9: Cyclicals | C9: =$C$86 -> 14646.162 | D9: =$C$96 -> 27067.683 | E9: =$C$106 -> 42640.314 | F9: ='DCF by Box'!C145*((1+gLT)+FadeYears/2*('DCF by Box'!C144-gLT))/('DCF by Box'!C142-gLT) -> 14646.162 | G9: ='DCF by Box'!D145*((1+gLT)+FadeYears/2*('DCF by Box'!D144-gLT))/('DCF by Box'!D142-gLT) -> 27067.683 | H9: ='DCF by Box'!E145*((1+gLT)+FadeYears/2*('DCF by Box'!E144-gLT))/('DCF by Box'!E142-gLT) -> 42640.314 | I9: =D9/G9-1 -> 0
B10: Commodities | C10: =$C$116 -> 77826.258 | D10: =$C$126 -> 128949.38 | E10: =$C$136 -> 195241.98 | F10: ='DCF by Box'!C192*((1+gLT)+FadeYears/2*('DCF by Box'!C191-gLT))/('DCF by Box'!C189-gLT) -> 77826.258 | G10: ='DCF by Box'!D192*((1+gLT)+FadeYears/2*('DCF by Box'!D191-gLT))/('DCF by Box'!D189-gLT) -> 128949.38 | H10: ='DCF by Box'!E192*((1+gLT)+FadeYears/2*('DCF by Box'!E191-gLT))/('DCF by Box'!E189-gLT) -> 195241.98 | I10: =D10/G10-1 -> 0
B11: Memo (inside Cyclicals)
B12: Cyclicals ex-WEG & Embraer | C12: =$C$146 -> 10557.787 | D12: =$C$156 -> 19329.418 | E12: =$C$166 -> 30056.536 | F12: ='DCF by Box'!C239*((1+gLT)+FadeYears/2*('DCF by Box'!C238-gLT))/('DCF by Box'!C236-gLT) -> 10557.787 | G12: ='DCF by Box'!D239*((1+gLT)+FadeYears/2*('DCF by Box'!D238-gLT))/('DCF by Box'!D236-gLT) -> 19329.418 | H12: ='DCF by Box'!E239*((1+gLT)+FadeYears/2*('DCF by Box'!E238-gLT))/('DCF by Box'!E236-gLT) -> 30056.536 | I12: =D12/G12-1 -> 0
B13: WEG & Embraer | C13: =$C$176 -> 5798.1781 | D13: =$C$186 -> 7612.3664 | E13: =$C$196 -> 9776.785 | F13: ='DCF by Box'!C286*((1+gLT)+FadeYears/2*('DCF by Box'!C285-gLT))/('DCF by Box'!C283-gLT) -> 5798.1781 | G13: ='DCF by Box'!D286*((1+gLT)+FadeYears/2*('DCF by Box'!D285-gLT))/('DCF by Box'!D283-gLT) -> 7612.3664 | H13: ='DCF by Box'!E286*((1+gLT)+FadeYears/2*('DCF by Box'!E285-gLT))/('DCF by Box'!E283-gLT) -> 9776.785 | I13: =D13/G13-1 -> 0
B14: Fade in use (Assumptions section 8) | C14: =CHOOSE(FadeMode+1,"0: H-model formula (this sheet is not used)","1: year by year","2: year by year, growth paid by reinvestment") -> 0: H-model formula (this sheet is not used)
B15: FadeMode 1: the 2031 flow grows year by year. FadeMode 2: flow = earnings x (1 - growth / ROE) - NWC % x change in sales (Financials: net income x (1 - growth / ROE)): growth costs reinvestment at the box's FY28 ROE (Box Shares section 5).
B18: Financials · Bear | C18: 2031 | D18: 2032 | E18: 2033 | F18: 2034 | G18: 2035 | H18: 2036 | I18: 2037 | J18: 2038 | K18: 2039 | L18: 2040 | M18: 2041 | N18: 2042: g
B19: Year of the fade | D19: 1 | E19: 2 | F19: 3 | G19: 4 | H19: 5 | I19: 6 | J19: 7 | K19: 8 | L19: 9 | M19: 10 | N19: 11
B20: Growth: starting growth (DCF by Box) stepping down to g over FadeYears | D20: =IF(D19<=FadeYears,'DCF by Box'!$C$45-('DCF by Box'!$C$45-gLT)*(D19-0.5)/FadeYears,gLT) -> 0.047 | E20: =IF(E19<=FadeYears,'DCF by Box'!$C$45-('DCF by Box'!$C$45-gLT)*(E19-0.5)/FadeYears,gLT) -> 0.047 | F20: =IF(F19<=FadeYears,'DCF by Box'!$C$45-('DCF by Box'!$C$45-gLT)*(F19-0.5)/FadeYears,gLT) -> 0.047 | G20: =IF(G19<=FadeYears,'DCF by Box'!$C$45-('DCF by Box'!$C$45-gLT)*(G19-0.5)/FadeYears,gLT) -> 0.047 | H20: =IF(H19<=FadeYears,'DCF by Box'!$C$45-('DCF by Box'!$C$45-gLT)*(H19-0.5)/FadeYears,gLT) -> 0.047 | I20: =IF(I19<=FadeYears,'DCF by Box'!$C$45-('DCF by Box'!$C$45-gLT)*(I19-0.5)/FadeYears,gLT) -> 0.047 | J20: =IF(J19<=FadeYears,'DCF by Box'!$C$45-('DCF by Box'!$C$45-gLT)*(J19-0.5)/FadeYears,gLT) -> 0.047 | K20: =IF(K19<=FadeYears,'DCF by Box'!$C$45-('DCF by Box'!$C$45-gLT)*(K19-0.5)/FadeYears,gLT) -> 0.047 | ... N20: =IF(N19<=FadeYears,'DCF by Box'!$C$45-('DCF by Box'!$C$45-gLT)*(N19-0.5)/FadeYears,gLT) -> 0.047
B21: Net income 2031 x (1 + shock), then x (1 + growth) | C21: ='DCF by Box'!$H$27*(1+'DCF by Box'!$C$44) -> 7004.8376 | D21: =C21*(1+D20) -> 7334.0649 | E21: =D21*(1+E20) -> 7678.766 | F21: =E21*(1+F20) -> 8039.668 | G21: =F21*(1+G20) -> 8417.5324 | H21: =G21*(1+H20) -> 8813.1564 | I21: =H21*(1+I20) -> 9227.3748 | J21: =I21*(1+J20) -> 9661.0614 | K21: =J21*(1+K20) -> 10115.131 | ... N21: =M21*(1+N20) -> 11609.448
B22: Sales (not used: FCFE)
B23: Flow: FadeMode 1 = 2031 flow x (1 + growth); 2 = earnings x (1 - growth / ROE) | C23: ='DCF by Box'!$C$54 -> 5347.9824 | D23: =IF(FadeMode=2,D21*(1-D20/FinROE),C23*(1+D20)) -> 5599.3376 | E23: =IF(FadeMode=2,E21*(1-E20/FinROE),D23*(1+E20)) -> 5862.5064 | F23: =IF(FadeMode=2,F21*(1-F20/FinROE),E23*(1+F20)) -> 6138.0442 | G23: =IF(FadeMode=2,G21*(1-G20/FinROE),F23*(1+G20)) -> 6426.5323 | H23: =IF(FadeMode=2,H21*(1-H20/FinROE),G23*(1+H20)) -> 6728.5793 | I23: =IF(FadeMode=2,I21*(1-I20/FinROE),H23*(1+I20)) -> 7044.8225 | J23: =IF(FadeMode=2,J21*(1-J20/FinROE),I23*(1+J20)) -> 7375.9292 | K23: =IF(FadeMode=2,K21*(1-K20/FinROE),J23*(1+K20)) -> 7722.5979 | ... N23: =IF(FadeMode=2,N21*(1-N20/FinROE),M23*(1+N20)) -> 8863.4636
B24: Discount factor from end-2031 at the box rate | D24: =1/(1+'DCF by Box'!$C$43)^D19 -> 0.86659332 | E24: =1/(1+'DCF by Box'!$C$43)^E19 -> 0.75098397 | F24: =1/(1+'DCF by Box'!$C$43)^F19 -> 0.65079769 | G24: =1/(1+'DCF by Box'!$C$43)^G19 -> 0.56397693 | H24: =1/(1+'DCF by Box'!$C$43)^H19 -> 0.48873864 | I24: =1/(1+'DCF by Box'!$C$43)^I19 -> 0.42353764 | J24: =1/(1+'DCF by Box'!$C$43)^J19 -> 0.36703488 | K24: =1/(1+'DCF by Box'!$C$43)^K19 -> 0.31806998 | ... M24: =1/(1+'DCF by Box'!$C$43)^M19 -> 0.23886545
B25: Present value at end-2031 | D25: =D23*D24 -> 4852.3485 | E25: =E23*E24 -> 4402.6484 | F25: =F23*F24 -> 3994.625 | G25: =G23*G24 -> 3624.416 | H25: =H23*H24 -> 3288.5167 | I25: =I23*I24 -> 2983.7475 | J25: =J23*J24 -> 2707.2233 | K25: =K23*K24 -> 2456.3265 | ... M25: =M23*M24 -> 2022.1349
B26: Value at end-2031 = PV 2032-41 + flow 2042 / (rate - g), discounted | C26: =SUM(D25:M25)+N23/('DCF by Box'!$C$43-gLT)*M24 -> 52357.748
B28: Financials · Base | C28: 2031 | D28: 2032 | E28: 2033 | F28: 2034 | G28: 2035 | H28: 2036 | I28: 2037 | J28: 2038 | K28: 2039 | L28: 2040 | M28: 2041 | N28: 2042: g
B29: Year of the fade | D29: 1 | E29: 2 | F29: 3 | G29: 4 | H29: 5 | I29: 6 | J29: 7 | K29: 8 | L29: 9 | M29: 10 | N29: 11
B30: Growth: starting growth (DCF by Box) stepping down to g over FadeYears | D30: =IF(D29<=FadeYears,'DCF by Box'!$D$45-('DCF by Box'!$D$45-gLT)*(D29-0.5)/FadeYears,gLT) -> 0.047 | E30: =IF(E29<=FadeYears,'DCF by Box'!$D$45-('DCF by Box'!$D$45-gLT)*(E29-0.5)/FadeYears,gLT) -> 0.047 | F30: =IF(F29<=FadeYears,'DCF by Box'!$D$45-('DCF by Box'!$D$45-gLT)*(F29-0.5)/FadeYears,gLT) -> 0.047 | G30: =IF(G29<=FadeYears,'DCF by Box'!$D$45-('DCF by Box'!$D$45-gLT)*(G29-0.5)/FadeYears,gLT) -> 0.047 | H30: =IF(H29<=FadeYears,'DCF by Box'!$D$45-('DCF by Box'!$D$45-gLT)*(H29-0.5)/FadeYears,gLT) -> 0.047 | I30: =IF(I29<=FadeYears,'DCF by Box'!$D$45-('DCF by Box'!$D$45-gLT)*(I29-0.5)/FadeYears,gLT) -> 0.047 | J30: =IF(J29<=FadeYears,'DCF by Box'!$D$45-('DCF by Box'!$D$45-gLT)*(J29-0.5)/FadeYears,gLT) -> 0.047 | K30: =IF(K29<=FadeYears,'DCF by Box'!$D$45-('DCF by Box'!$D$45-gLT)*(K29-0.5)/FadeYears,gLT) -> 0.047 | ... N30: =IF(N29<=FadeYears,'DCF by Box'!$D$45-('DCF by Box'!$D$45-gLT)*(N29-0.5)/FadeYears,gLT) -> 0.047
B31: Net income 2031 x (1 + shock), then x (1 + growth) | C31: ='DCF by Box'!$H$27*(1+'DCF by Box'!$D$44) -> 8479.7794 | D31: =C31*(1+D30) -> 8878.329 | E31: =D31*(1+E30) -> 9295.6105 | F31: =E31*(1+F30) -> 9732.5042 | G31: =F31*(1+G30) -> 10189.932 | H31: =G31*(1+H30) -> 10668.859 | I31: =H31*(1+I30) -> 11170.295 | J31: =I31*(1+J30) -> 11695.299 | K31: =J31*(1+K30) -> 12244.978 | ... N31: =M31*(1+N30) -> 14053.939
B32: Sales (not used: FCFE)
B33: Flow: FadeMode 1 = 2031 flow x (1 + growth); 2 = earnings x (1 - growth / ROE) | C33: ='DCF by Box'!$D$54 -> 6474.056 | D33: =IF(FadeMode=2,D31*(1-D30/FinROE),C33*(1+D30)) -> 6778.3366 | E33: =IF(FadeMode=2,E31*(1-E30/FinROE),D33*(1+E30)) -> 7096.9185 | F33: =IF(FadeMode=2,F31*(1-F30/FinROE),E33*(1+F30)) -> 7430.4736 | G33: =IF(FadeMode=2,G31*(1-G30/FinROE),F33*(1+G30)) -> 7779.7059 | H33: =IF(FadeMode=2,H31*(1-H30/FinROE),G33*(1+H30)) -> 8145.3521 | I33: =IF(FadeMode=2,I31*(1-I30/FinROE),H33*(1+I30)) -> 8528.1836 | J33: =IF(FadeMode=2,J31*(1-J30/FinROE),I33*(1+J30)) -> 8929.0082 | K33: =IF(FadeMode=2,K31*(1-K30/FinROE),J33*(1+K30)) -> 9348.6716 | ... N33: =IF(FadeMode=2,N31*(1-N30/FinROE),M33*(1+N30)) -> 10729.759
B34: Discount factor from end-2031 at the box rate | D34: =1/(1+'DCF by Box'!$D$43)^D29 -> 0.87986049 | E34: =1/(1+'DCF by Box'!$D$43)^E29 -> 0.77415448 | F34: =1/(1+'DCF by Box'!$D$43)^F29 -> 0.68114794 | G34: =1/(1+'DCF by Box'!$D$43)^G29 -> 0.59931516 | H34: =1/(1+'DCF by Box'!$D$43)^H29 -> 0.52731373 | I34: =1/(1+'DCF by Box'!$D$43)^I29 -> 0.46396251 | J34: =1/(1+'DCF by Box'!$D$43)^J29 -> 0.40822228 | K34: =1/(1+'DCF by Box'!$D$43)^K29 -> 0.35917866 | ... M34: =1/(1+'DCF by Box'!$D$43)^M29 -> 0.27805977
B35: Present value at end-2031 | D35: =D33*D34 -> 5963.9906 | E35: =E33*E34 -> 5494.1112 | F35: =F33*F34 -> 5061.2518 | G35: =G33*G34 -> 4662.4957 | H35: =H33*H34 -> 4295.156 | I35: =I33*I34 -> 3956.7575 | J35: =J33*J34 -> 3645.0201 | K35: =K33*K34 -> 3357.8433 | ... M35: =M33*M34 -> 2849.5837
B36: Value at end-2031 = PV 2032-41 + flow 2042 / (rate - g), discounted | C36: =SUM(D35:M35)+N33/('DCF by Box'!$D$43-gLT)*M34 -> 75698.543
B38: Financials · Bull | C38: 2031 | D38: 2032 | E38: 2033 | F38: 2034 | G38: 2035 | H38: 2036 | I38: 2037 | J38: 2038 | K38: 2039 | L38: 2040 | M38: 2041 | N38: 2042: g
B39: Year of the fade | D39: 1 | E39: 2 | F39: 3 | G39: 4 | H39: 5 | I39: 6 | J39: 7 | K39: 8 | L39: 9 | M39: 10 | N39: 11
B40: Growth: starting growth (DCF by Box) stepping down to g over FadeYears | D40: =IF(D39<=FadeYears,'DCF by Box'!$E$45-('DCF by Box'!$E$45-gLT)*(D39-0.5)/FadeYears,gLT) -> 0.047 | E40: =IF(E39<=FadeYears,'DCF by Box'!$E$45-('DCF by Box'!$E$45-gLT)*(E39-0.5)/FadeYears,gLT) -> 0.047 | F40: =IF(F39<=FadeYears,'DCF by Box'!$E$45-('DCF by Box'!$E$45-gLT)*(F39-0.5)/FadeYears,gLT) -> 0.047 | G40: =IF(G39<=FadeYears,'DCF by Box'!$E$45-('DCF by Box'!$E$45-gLT)*(G39-0.5)/FadeYears,gLT) -> 0.047 | H40: =IF(H39<=FadeYears,'DCF by Box'!$E$45-('DCF by Box'!$E$45-gLT)*(H39-0.5)/FadeYears,gLT) -> 0.047 | I40: =IF(I39<=FadeYears,'DCF by Box'!$E$45-('DCF by Box'!$E$45-gLT)*(I39-0.5)/FadeYears,gLT) -> 0.047 | J40: =IF(J39<=FadeYears,'DCF by Box'!$E$45-('DCF by Box'!$E$45-gLT)*(J39-0.5)/FadeYears,gLT) -> 0.047 | K40: =IF(K39<=FadeYears,'DCF by Box'!$E$45-('DCF by Box'!$E$45-gLT)*(K39-0.5)/FadeYears,gLT) -> 0.047 | ... N40: =IF(N39<=FadeYears,'DCF by Box'!$E$45-('DCF by Box'!$E$45-gLT)*(N39-0.5)/FadeYears,gLT) -> 0.047
B41: Net income 2031 x (1 + shock), then x (1 + growth) | C41: ='DCF by Box'!$H$27*(1+'DCF by Box'!$E$44) -> 9954.7212 | D41: =C41*(1+D40) -> 10422.593 | E41: =D41*(1+E40) -> 10912.455 | F41: =E41*(1+F40) -> 11425.34 | G41: =F41*(1+G40) -> 11962.331 | H41: =G41*(1+H40) -> 12524.561 | I41: =H41*(1+I40) -> 13113.215 | J41: =I41*(1+J40) -> 13729.536 | K41: =J41*(1+K40) -> 14374.825 | ... N41: =M41*(1+N40) -> 16498.429
B42: Sales (not used: FCFE)
B43: Flow: FadeMode 1 = 2031 flow x (1 + growth); 2 = earnings x (1 - growth / ROE) | C43: ='DCF by Box'!$E$54 -> 7600.1296 | D43: =IF(FadeMode=2,D41*(1-D40/FinROE),C43*(1+D40)) -> 7957.3357 | E43: =IF(FadeMode=2,E41*(1-E40/FinROE),D43*(1+E40)) -> 8331.3305 | F43: =IF(FadeMode=2,F41*(1-F40/FinROE),E43*(1+F40)) -> 8722.903 | G43: =IF(FadeMode=2,G41*(1-G40/FinROE),F43*(1+G40)) -> 9132.8795 | H43: =IF(FadeMode=2,H41*(1-H40/FinROE),G43*(1+H40)) -> 9562.1248 | I43: =IF(FadeMode=2,I41*(1-I40/FinROE),H43*(1+I40)) -> 10011.545 | J43: =IF(FadeMode=2,J41*(1-J40/FinROE),I43*(1+J40)) -> 10482.087 | K43: =IF(FadeMode=2,K41*(1-K40/FinROE),J43*(1+K40)) -> 10974.745 | ... N43: =IF(FadeMode=2,N41*(1-N40/FinROE),M43*(1+N40)) -> 12596.054
B44: Discount factor from end-2031 at the box rate | D44: =1/(1+'DCF by Box'!$E$43)^D39 -> 0.88972419 | E44: =1/(1+'DCF by Box'!$E$43)^E39 -> 0.79160913 | F44: =1/(1+'DCF by Box'!$E$43)^F39 -> 0.70431379 | G44: =1/(1+'DCF by Box'!$E$43)^G39 -> 0.62664501 | H44: =1/(1+'DCF by Box'!$E$43)^H39 -> 0.55754122 | I44: =1/(1+'DCF by Box'!$E$43)^I39 -> 0.49605791 | J44: =1/(1+'DCF by Box'!$E$43)^J39 -> 0.44135472 | K44: =1/(1+'DCF by Box'!$E$43)^K39 -> 0.39268397 | ... M44: =1/(1+'DCF by Box'!$E$43)^M39 -> 0.31085221
B45: Present value at end-2031 | D45: =D43*D44 -> 7079.834 | E45: =E43*E44 -> 6595.1573 | F45: =F43*F44 -> 6143.6609 | G45: =G43*G44 -> 5723.0734 | H45: =H43*H44 -> 5331.2788 | I45: =I43*I44 -> 4966.3059 | J45: =J43*J44 -> 4626.3187 | K45: =K43*K44 -> 4309.6066 | ... M45: =M43*M44 -> 3739.7432
B46: Value at end-2031 = PV 2032-41 + flow 2042 / (rate - g), discounted | C46: =SUM(D45:M45)+N43/('DCF by Box'!$E$43-gLT)*M44 -> 103417.48
B48: Defensives · Bear | C48: 2031 | D48: 2032 | E48: 2033 | F48: 2034 | G48: 2035 | H48: 2036 | I48: 2037 | J48: 2038 | K48: 2039 | L48: 2040 | M48: 2041 | N48: 2042: g
B49: Year of the fade | D49: 1 | E49: 2 | F49: 3 | G49: 4 | H49: 5 | I49: 6 | J49: 7 | K49: 8 | L49: 9 | M49: 10 | N49: 11
B50: Growth: starting growth (DCF by Box) stepping down to g over FadeYears | D50: =IF(D49<=FadeYears,'DCF by Box'!$C$97-('DCF by Box'!$C$97-gLT)*(D49-0.5)/FadeYears,gLT) -> 0.047 | E50: =IF(E49<=FadeYears,'DCF by Box'!$C$97-('DCF by Box'!$C$97-gLT)*(E49-0.5)/FadeYears,gLT) -> 0.047 | F50: =IF(F49<=FadeYears,'DCF by Box'!$C$97-('DCF by Box'!$C$97-gLT)*(F49-0.5)/FadeYears,gLT) -> 0.047 | G50: =IF(G49<=FadeYears,'DCF by Box'!$C$97-('DCF by Box'!$C$97-gLT)*(G49-0.5)/FadeYears,gLT) -> 0.047 | H50: =IF(H49<=FadeYears,'DCF by Box'!$C$97-('DCF by Box'!$C$97-gLT)*(H49-0.5)/FadeYears,gLT) -> 0.047 | I50: =IF(I49<=FadeYears,'DCF by Box'!$C$97-('DCF by Box'!$C$97-gLT)*(I49-0.5)/FadeYears,gLT) -> 0.047 | J50: =IF(J49<=FadeYears,'DCF by Box'!$C$97-('DCF by Box'!$C$97-gLT)*(J49-0.5)/FadeYears,gLT) -> 0.047 | K50: =IF(K49<=FadeYears,'DCF by Box'!$C$97-('DCF by Box'!$C$97-gLT)*(K49-0.5)/FadeYears,gLT) -> 0.047 | ... N50: =IF(N49<=FadeYears,'DCF by Box'!$C$97-('DCF by Box'!$C$97-gLT)*(N49-0.5)/FadeYears,gLT) -> 0.047
B51: NOPAT 2031 x (1 + shock), then x (1 + growth) | C51: ='DCF by Box'!$H$84*(1+'DCF by Box'!$C$96) -> 6977.0328 | D51: =C51*(1+D50) -> 7304.9533 | E51: =D51*(1+E50) -> 7648.2861 | F51: =E51*(1+F50) -> 8007.7556 | G51: =F51*(1+G50) -> 8384.1201 | H51: =G51*(1+H50) -> 8778.1737 | I51: =H51*(1+I50) -> 9190.7479 | J51: =I51*(1+J50) -> 9622.713 | K51: =J51*(1+K50) -> 10074.981 | ... N51: =M51*(1+N50) -> 11563.366
B52: Sales 2031 x (1 + shock), then x (1 + growth) | C52: ='DCF by Box'!$H$73*(1+'DCF by Box'!$C$96) -> 45591.04 | D52: =C52*(1+D50) -> 47733.818 | E52: =D52*(1+E50) -> 49977.308 | F52: =E52*(1+F50) -> 52326.241 | G52: =F52*(1+G50) -> 54785.575 | H52: =G52*(1+H50) -> 57360.497 | I52: =H52*(1+I50) -> 60056.44 | J52: =I52*(1+J50) -> 62879.093 | K52: =J52*(1+K50) -> 65834.41 | ... N52: =M52*(1+N50) -> 75560.182
B53: Flow: FadeMode 1 = 2031 flow x (1 + growth); 2 = earnings x (1 - growth / ROE) - NWC % x change in sales | C53: ='DCF by Box'!$C$98 -> 3904.9318 | D53: =IF(FadeMode=2,D51*(1-D50/'Box Shares'!$E$45)-NWCpct*(D52-C52),C53*(1+D50)) -> 4088.4636 | E53: =IF(FadeMode=2,E51*(1-E50/'Box Shares'!$E$45)-NWCpct*(E52-D52),D53*(1+E50)) -> 4280.6214 | F53: =IF(FadeMode=2,F51*(1-F50/'Box Shares'!$E$45)-NWCpct*(F52-E52),E53*(1+F50)) -> 4481.8106 | G53: =IF(FadeMode=2,G51*(1-G50/'Box Shares'!$E$45)-NWCpct*(G52-F52),F53*(1+G50)) -> 4692.4557 | H53: =IF(FadeMode=2,H51*(1-H50/'Box Shares'!$E$45)-NWCpct*(H52-G52),G53*(1+H50)) -> 4913.0012 | I53: =IF(FadeMode=2,I51*(1-I50/'Box Shares'!$E$45)-NWCpct*(I52-H52),H53*(1+I50)) -> 5143.9122 | J53: =IF(FadeMode=2,J51*(1-J50/'Box Shares'!$E$45)-NWCpct*(J52-I52),I53*(1+J50)) -> 5385.6761 | K53: =IF(FadeMode=2,K51*(1-K50/'Box Shares'!$E$45)-NWCpct*(K52-J52),J53*(1+K50)) -> 5638.8029 | ... N53: =IF(FadeMode=2,N51*(1-N50/'Box Shares'!$E$45)-NWCpct*(N52-M52),M53*(1+N50)) -> 6471.8279
B54: Discount factor from end-2031 at the box rate | D54: =1/(1+'DCF by Box'!$C$95)^D49 -> 0.87663898 | E54: =1/(1+'DCF by Box'!$C$95)^E49 -> 0.7684959 | F54: =1/(1+'DCF by Box'!$C$95)^F49 -> 0.67369346 | G54: =1/(1+'DCF by Box'!$C$95)^G49 -> 0.59058595 | H54: =1/(1+'DCF by Box'!$C$95)^H49 -> 0.51773066 | I54: =1/(1+'DCF by Box'!$C$95)^I49 -> 0.45386288 | J54: =1/(1+'DCF by Box'!$C$95)^J49 -> 0.39787389 | K54: =1/(1+'DCF by Box'!$C$95)^K49 -> 0.34879176 | ... M54: =1/(1+'DCF by Box'!$C$95)^M49 -> 0.26804504
B55: Present value at end-2031 | D55: =D53*D54 -> 3584.1066 | E55: =E53*E54 -> 3289.64 | F55: =F53*F54 -> 3019.3665 | G55: =G53*G54 -> 2771.2984 | H55: =H53*H54 -> 2543.6113 | I55: =I53*I54 -> 2334.6308 | J55: =J53*J54 -> 2142.8199 | K55: =K53*K54 -> 1966.768 | ... M55: =M53*M54 -> 1656.8685
B56: Value at end-2031 = PV 2032-41 + flow 2042 / (rate - g), discounted | C56: =SUM(D55:M55)+N53/('DCF by Box'!$C$95-gLT)*M54 -> 43624.035
B58: Defensives · Base | C58: 2031 | D58: 2032 | E58: 2033 | F58: 2034 | G58: 2035 | H58: 2036 | I58: 2037 | J58: 2038 | K58: 2039 | L58: 2040 | M58: 2041 | N58: 2042: g
B59: Year of the fade | D59: 1 | E59: 2 | F59: 3 | G59: 4 | H59: 5 | I59: 6 | J59: 7 | K59: 8 | L59: 9 | M59: 10 | N59: 11
B60: Growth: starting growth (DCF by Box) stepping down to g over FadeYears | D60: =IF(D59<=FadeYears,'DCF by Box'!$D$97-('DCF by Box'!$D$97-gLT)*(D59-0.5)/FadeYears,gLT) -> 0.047 | E60: =IF(E59<=FadeYears,'DCF by Box'!$D$97-('DCF by Box'!$D$97-gLT)*(E59-0.5)/FadeYears,gLT) -> 0.047 | F60: =IF(F59<=FadeYears,'DCF by Box'!$D$97-('DCF by Box'!$D$97-gLT)*(F59-0.5)/FadeYears,gLT) -> 0.047 | G60: =IF(G59<=FadeYears,'DCF by Box'!$D$97-('DCF by Box'!$D$97-gLT)*(G59-0.5)/FadeYears,gLT) -> 0.047 | H60: =IF(H59<=FadeYears,'DCF by Box'!$D$97-('DCF by Box'!$D$97-gLT)*(H59-0.5)/FadeYears,gLT) -> 0.047 | I60: =IF(I59<=FadeYears,'DCF by Box'!$D$97-('DCF by Box'!$D$97-gLT)*(I59-0.5)/FadeYears,gLT) -> 0.047 | J60: =IF(J59<=FadeYears,'DCF by Box'!$D$97-('DCF by Box'!$D$97-gLT)*(J59-0.5)/FadeYears,gLT) -> 0.047 | K60: =IF(K59<=FadeYears,'DCF by Box'!$D$97-('DCF by Box'!$D$97-gLT)*(K59-0.5)/FadeYears,gLT) -> 0.047 | ... N60: =IF(N59<=FadeYears,'DCF by Box'!$D$97-('DCF by Box'!$D$97-gLT)*(N59-0.5)/FadeYears,gLT) -> 0.047
B61: NOPAT 2031 x (1 + shock), then x (1 + growth) | C61: ='DCF by Box'!$H$84*(1+'DCF by Box'!$D$96) -> 8266.9998 | D61: =C61*(1+D60) -> 8655.5487 | E61: =D61*(1+E60) -> 9062.3595 | F61: =E61*(1+F60) -> 9488.2904 | G61: =F61*(1+G60) -> 9934.2401 | H61: =G61*(1+H60) -> 10401.149 | I61: =H61*(1+I60) -> 10890.003 | J61: =I61*(1+J60) -> 11401.834 | K61: =J61*(1+K60) -> 11937.72 | ... N61: =M61*(1+N60) -> 13701.289
B62: Sales 2031 x (1 + shock), then x (1 + growth) | C62: ='DCF by Box'!$H$73*(1+'DCF by Box'!$D$96) -> 54020.259 | D62: =C62*(1+D60) -> 56559.211 | E62: =D62*(1+E60) -> 59217.494 | F62: =E62*(1+F60) -> 62000.716 | G62: =F62*(1+G60) -> 64914.749 | H62: =G62*(1+H60) -> 67965.743 | I62: =H62*(1+I60) -> 71160.133 | J62: =I62*(1+J60) -> 74504.659 | K62: =J62*(1+K60) -> 78006.378 | ... N62: =M62*(1+N60) -> 89530.324
B63: Flow: FadeMode 1 = 2031 flow x (1 + growth); 2 = earnings x (1 - growth / ROE) - NWC % x change in sales | C63: ='DCF by Box'!$D$98 -> 4626.9054 | D63: =IF(FadeMode=2,D61*(1-D60/'Box Shares'!$E$45)-NWCpct*(D62-C62),C63*(1+D60)) -> 4844.37 | E63: =IF(FadeMode=2,E61*(1-E60/'Box Shares'!$E$45)-NWCpct*(E62-D62),D63*(1+E60)) -> 5072.0554 | F63: =IF(FadeMode=2,F61*(1-F60/'Box Shares'!$E$45)-NWCpct*(F62-E62),E63*(1+F60)) -> 5310.442 | G63: =IF(FadeMode=2,G61*(1-G60/'Box Shares'!$E$45)-NWCpct*(G62-F62),F63*(1+G60)) -> 5560.0327 | H63: =IF(FadeMode=2,H61*(1-H60/'Box Shares'!$E$45)-NWCpct*(H62-G62),G63*(1+H60)) -> 5821.3543 | I63: =IF(FadeMode=2,I61*(1-I60/'Box Shares'!$E$45)-NWCpct*(I62-H62),H63*(1+I60)) -> 6094.9579 | J63: =IF(FadeMode=2,J61*(1-J60/'Box Shares'!$E$45)-NWCpct*(J62-I62),I63*(1+J60)) -> 6381.4209 | K63: =IF(FadeMode=2,K61*(1-K60/'Box Shares'!$E$45)-NWCpct*(K62-J62),J63*(1+K60)) -> 6681.3477 | ... N63: =IF(FadeMode=2,N61*(1-N60/'Box Shares'!$E$45)-NWCpct*(N62-M62),M63*(1+N60)) -> 7668.3887
B64: Discount factor from end-2031 at the box rate | D64: =1/(1+'DCF by Box'!$D$95)^D59 -> 0.89021793 | E64: =1/(1+'DCF by Box'!$D$95)^E59 -> 0.79248797 | F64: =1/(1+'DCF by Box'!$D$95)^F59 -> 0.705487 | G64: =1/(1+'DCF by Box'!$D$95)^G59 -> 0.62803718 | H64: =1/(1+'DCF by Box'!$D$95)^H59 -> 0.55908996 | I64: =1/(1+'DCF by Box'!$D$95)^I59 -> 0.49771191 | J64: =1/(1+'DCF by Box'!$D$95)^J59 -> 0.44307207 | K64: =1/(1+'DCF by Box'!$D$95)^K59 -> 0.3944307 | ... M64: =1/(1+'DCF by Box'!$D$95)^M59 -> 0.31258159
B65: Present value at end-2031 | D65: =D63*D64 -> 4312.545 | E65: =E63*E64 -> 4019.5429 | F65: =F63*F64 -> 3746.4478 | G65: =G63*G64 -> 3491.9073 | H65: =H63*H64 -> 3254.6608 | I65: =I63*I64 -> 3033.5332 | J65: =J63*J64 -> 2827.4294 | K65: =K63*K64 -> 2635.3287 | ... M65: =M63*M64 -> 2289.3955
B66: Value at end-2031 = PV 2032-41 + flow 2042 / (rate - g), discounted | C66: =SUM(D65:M65)+N63/('DCF by Box'!$D$95-gLT)*M64 -> 63474.085
B68: Defensives · Bull | C68: 2031 | D68: 2032 | E68: 2033 | F68: 2034 | G68: 2035 | H68: 2036 | I68: 2037 | J68: 2038 | K68: 2039 | L68: 2040 | M68: 2041 | N68: 2042: g
B69: Year of the fade | D69: 1 | E69: 2 | F69: 3 | G69: 4 | H69: 5 | I69: 6 | J69: 7 | K69: 8 | L69: 9 | M69: 10 | N69: 11
B70: Growth: starting growth (DCF by Box) stepping down to g over FadeYears | D70: =IF(D69<=FadeYears,'DCF by Box'!$E$97-('DCF by Box'!$E$97-gLT)*(D69-0.5)/FadeYears,gLT) -> 0.047 | E70: =IF(E69<=FadeYears,'DCF by Box'!$E$97-('DCF by Box'!$E$97-gLT)*(E69-0.5)/FadeYears,gLT) -> 0.047 | F70: =IF(F69<=FadeYears,'DCF by Box'!$E$97-('DCF by Box'!$E$97-gLT)*(F69-0.5)/FadeYears,gLT) -> 0.047 | G70: =IF(G69<=FadeYears,'DCF by Box'!$E$97-('DCF by Box'!$E$97-gLT)*(G69-0.5)/FadeYears,gLT) -> 0.047 | H70: =IF(H69<=FadeYears,'DCF by Box'!$E$97-('DCF by Box'!$E$97-gLT)*(H69-0.5)/FadeYears,gLT) -> 0.047 | I70: =IF(I69<=FadeYears,'DCF by Box'!$E$97-('DCF by Box'!$E$97-gLT)*(I69-0.5)/FadeYears,gLT) -> 0.047 | J70: =IF(J69<=FadeYears,'DCF by Box'!$E$97-('DCF by Box'!$E$97-gLT)*(J69-0.5)/FadeYears,gLT) -> 0.047 | K70: =IF(K69<=FadeYears,'DCF by Box'!$E$97-('DCF by Box'!$E$97-gLT)*(K69-0.5)/FadeYears,gLT) -> 0.047 | ... N70: =IF(N69<=FadeYears,'DCF by Box'!$E$97-('DCF by Box'!$E$97-gLT)*(N69-0.5)/FadeYears,gLT) -> 0.047
B71: NOPAT 2031 x (1 + shock), then x (1 + growth) | C71: ='DCF by Box'!$H$84*(1+'DCF by Box'!$E$96) -> 9556.9668 | D71: =C71*(1+D70) -> 10006.144 | E71: =D71*(1+E70) -> 10476.433 | F71: =E71*(1+F70) -> 10968.825 | G71: =F71*(1+G70) -> 11484.36 | H71: =G71*(1+H70) -> 12024.125 | I71: =H71*(1+I70) -> 12589.259 | J71: =I71*(1+J70) -> 13180.954 | K71: =J71*(1+K70) -> 13800.459 | ... N71: =M71*(1+N70) -> 15839.212
B72: Sales 2031 x (1 + shock), then x (1 + growth) | C72: ='DCF by Box'!$H$73*(1+'DCF by Box'!$E$96) -> 62449.478 | D72: =C72*(1+D70) -> 65384.603 | E72: =D72*(1+E70) -> 68457.679 | F72: =E72*(1+F70) -> 71675.19 | G72: =F72*(1+G70) -> 75043.924 | H72: =G72*(1+H70) -> 78570.989 | I72: =H72*(1+I70) -> 82263.825 | J72: =I72*(1+J70) -> 86130.225 | K72: =J72*(1+K70) -> 90178.345 | ... N72: =M72*(1+N70) -> 103500.47
B73: Flow: FadeMode 1 = 2031 flow x (1 + growth); 2 = earnings x (1 - growth / ROE) - NWC % x change in sales | C73: ='DCF by Box'!$E$98 -> 5348.879 | D73: =IF(FadeMode=2,D71*(1-D70/'Box Shares'!$E$45)-NWCpct*(D72-C72),C73*(1+D70)) -> 5600.2763 | E73: =IF(FadeMode=2,E71*(1-E70/'Box Shares'!$E$45)-NWCpct*(E72-D72),D73*(1+E70)) -> 5863.4893 | F73: =IF(FadeMode=2,F71*(1-F70/'Box Shares'!$E$45)-NWCpct*(F72-E72),E73*(1+F70)) -> 6139.0733 | G73: =IF(FadeMode=2,G71*(1-G70/'Box Shares'!$E$45)-NWCpct*(G72-F72),F73*(1+G70)) -> 6427.6097 | H73: =IF(FadeMode=2,H71*(1-H70/'Box Shares'!$E$45)-NWCpct*(H72-G72),G73*(1+H70)) -> 6729.7074 | I73: =IF(FadeMode=2,I71*(1-I70/'Box Shares'!$E$45)-NWCpct*(I72-H72),H73*(1+I70)) -> 7046.0036 | J73: =IF(FadeMode=2,J71*(1-J70/'Box Shares'!$E$45)-NWCpct*(J72-I72),I73*(1+J70)) -> 7377.1658 | K73: =IF(FadeMode=2,K71*(1-K70/'Box Shares'!$E$45)-NWCpct*(K72-J72),J73*(1+K70)) -> 7723.8926 | ... N73: =IF(FadeMode=2,N71*(1-N70/'Box Shares'!$E$45)-NWCpct*(N72-M72),M73*(1+N70)) -> 8864.9496
B74: Discount factor from end-2031 at the box rate | D74: =1/(1+'DCF by Box'!$E$95)^D69 -> 0.90031656 | E74: =1/(1+'DCF by Box'!$E$95)^E69 -> 0.8105699 | F74: =1/(1+'DCF by Box'!$E$95)^F69 -> 0.7297695 | G74: =1/(1+'DCF by Box'!$E$95)^G69 -> 0.65702357 | H74: =1/(1+'DCF by Box'!$E$95)^H69 -> 0.59152919 | I74: =1/(1+'DCF by Box'!$E$95)^I69 -> 0.53256353 | J74: =1/(1+'DCF by Box'!$E$95)^J69 -> 0.47947576 | K74: =1/(1+'DCF by Box'!$E$95)^K69 -> 0.43167997 | ... M74: =1/(1+'DCF by Box'!$E$95)^M69 -> 0.34990679
B75: Present value at end-2031 | D75: =D73*D74 -> 5042.0215 | E75: =E73*E74 -> 4752.7679 | F75: =F73*F74 -> 4480.1085 | G75: =G73*G74 -> 4223.0911 | H75: =H73*H74 -> 3980.8184 | I75: =I73*I74 -> 3752.4445 | J75: =J73*J74 -> 3537.1722 | K75: =K73*K74 -> 3334.2497 | ... M75: =M73*M74 -> 2962.661
B76: Value at end-2031 = PV 2032-41 + flow 2042 / (rate - g), discounted | C76: =SUM(D75:M75)+N73/('DCF by Box'!$E$95-gLT)*M74 -> 87888.227
B78: Cyclicals · Bear | C78: 2031 | D78: 2032 | E78: 2033 | F78: 2034 | G78: 2035 | H78: 2036 | I78: 2037 | J78: 2038 | K78: 2039 | L78: 2040 | M78: 2041 | N78: 2042: g
B79: Year of the fade | D79: 1 | E79: 2 | F79: 3 | G79: 4 | H79: 5 | I79: 6 | J79: 7 | K79: 8 | L79: 9 | M79: 10 | N79: 11
B80: Growth: starting growth (DCF by Box) stepping down to g over FadeYears | D80: =IF(D79<=FadeYears,'DCF by Box'!$C$144-('DCF by Box'!$C$144-gLT)*(D79-0.5)/FadeYears,gLT) -> 0.047 | E80: =IF(E79<=FadeYears,'DCF by Box'!$C$144-('DCF by Box'!$C$144-gLT)*(E79-0.5)/FadeYears,gLT) -> 0.047 | F80: =IF(F79<=FadeYears,'DCF by Box'!$C$144-('DCF by Box'!$C$144-gLT)*(F79-0.5)/FadeYears,gLT) -> 0.047 | G80: =IF(G79<=FadeYears,'DCF by Box'!$C$144-('DCF by Box'!$C$144-gLT)*(G79-0.5)/FadeYears,gLT) -> 0.047 | H80: =IF(H79<=FadeYears,'DCF by Box'!$C$144-('DCF by Box'!$C$144-gLT)*(H79-0.5)/FadeYears,gLT) -> 0.047 | I80: =IF(I79<=FadeYears,'DCF by Box'!$C$144-('DCF by Box'!$C$144-gLT)*(I79-0.5)/FadeYears,gLT) -> 0.047 | J80: =IF(J79<=FadeYears,'DCF by Box'!$C$144-('DCF by Box'!$C$144-gLT)*(J79-0.5)/FadeYears,gLT) -> 0.047 | K80: =IF(K79<=FadeYears,'DCF by Box'!$C$144-('DCF by Box'!$C$144-gLT)*(K79-0.5)/FadeYears,gLT) -> 0.047 | ... N80: =IF(N79<=FadeYears,'DCF by Box'!$C$144-('DCF by Box'!$C$144-gLT)*(N79-0.5)/FadeYears,gLT) -> 0.047
B81: NOPAT 2031 x (1 + shock), then x (1 + growth) | C81: ='DCF by Box'!$H$131*(1+'DCF by Box'!$C$143) -> 2319.0394 | D81: =C81*(1+D80) -> 2428.0342 | E81: =D81*(1+E80) -> 2542.1518 | F81: =E81*(1+F80) -> 2661.633 | G81: =F81*(1+G80) -> 2786.7297 | H81: =G81*(1+H80) -> 2917.706 | I81: =H81*(1+I80) -> 3054.8382 | J81: =I81*(1+J80) -> 3198.4156 | K81: =J81*(1+K80) -> 3348.7411 | ... N81: =M81*(1+N80) -> 3843.4534
B82: Sales 2031 x (1 + shock), then x (1 + growth) | C82: ='DCF by Box'!$H$120*(1+'DCF by Box'!$C$143) -> 15032.369 | D82: =C82*(1+D80) -> 15738.89 | E82: =D82*(1+E80) -> 16478.618 | F82: =E82*(1+F80) -> 17253.113 | G82: =F82*(1+G80) -> 18064.01 | H82: =G82*(1+H80) -> 18913.018 | I82: =H82*(1+I80) -> 19801.93 | J82: =I82*(1+J80) -> 20732.621 | K82: =J82*(1+K80) -> 21707.054 | ... N82: =M82*(1+N80) -> 24913.855
B83: Flow: FadeMode 1 = 2031 flow x (1 + growth); 2 = earnings x (1 - growth / ROE) - NWC % x change in sales | C83: ='DCF by Box'!$C$145 -> 1497.1688 | D83: =IF(FadeMode=2,D81*(1-D80/'Box Shares'!$E$46)-NWCpct*(D82-C82),C83*(1+D80)) -> 1567.5358 | E83: =IF(FadeMode=2,E81*(1-E80/'Box Shares'!$E$46)-NWCpct*(E82-D82),D83*(1+E80)) -> 1641.2099 | F83: =IF(FadeMode=2,F81*(1-F80/'Box Shares'!$E$46)-NWCpct*(F82-E82),E83*(1+F80)) -> 1718.3468 | G83: =IF(FadeMode=2,G81*(1-G80/'Box Shares'!$E$46)-NWCpct*(G82-F82),F83*(1+G80)) -> 1799.1091 | H83: =IF(FadeMode=2,H81*(1-H80/'Box Shares'!$E$46)-NWCpct*(H82-G82),G83*(1+H80)) -> 1883.6672 | I83: =IF(FadeMode=2,I81*(1-I80/'Box Shares'!$E$46)-NWCpct*(I82-H82),H83*(1+I80)) -> 1972.1996 | J83: =IF(FadeMode=2,J81*(1-J80/'Box Shares'!$E$46)-NWCpct*(J82-I82),I83*(1+J80)) -> 2064.893 | K83: =IF(FadeMode=2,K81*(1-K80/'Box Shares'!$E$46)-NWCpct*(K82-J82),J83*(1+K80)) -> 2161.943 | ... N83: =IF(FadeMode=2,N81*(1-N80/'Box Shares'!$E$46)-NWCpct*(N82-M82),M83*(1+N80)) -> 2481.3286
B84: Discount factor from end-2031 at the box rate | D84: =1/(1+'DCF by Box'!$C$142)^D79 -> 0.8665308 | E84: =1/(1+'DCF by Box'!$C$142)^E79 -> 0.75087563 | F84: =1/(1+'DCF by Box'!$C$142)^F79 -> 0.65065686 | G84: =1/(1+'DCF by Box'!$C$142)^G79 -> 0.56381422 | H84: =1/(1+'DCF by Box'!$C$142)^H79 -> 0.48856238 | I84: =1/(1+'DCF by Box'!$C$142)^I79 -> 0.42335436 | J84: =1/(1+'DCF by Box'!$C$142)^J79 -> 0.36684959 | K84: =1/(1+'DCF by Box'!$C$142)^K79 -> 0.31788647 | ... M84: =1/(1+'DCF by Box'!$C$142)^M79 -> 0.2386932
B85: Present value at end-2031 | D85: =D83*D84 -> 1358.318 | E85: =E83*E84 -> 1232.3446 | F85: =F83*F84 -> 1118.0541 | G85: =G83*G84 -> 1014.3633 | H85: =H83*H84 -> 920.28896 | I85: =I83*I84 -> 834.93929 | J85: =J83*J84 -> 757.50514 | K85: =K83*K84 -> 687.25241 | ... M85: =M83*M84 -> 565.68889
B86: Value at end-2031 = PV 2032-41 + flow 2042 / (rate - g), discounted | C86: =SUM(D85:M85)+N83/('DCF by Box'!$C$142-gLT)*M84 -> 14646.162
B88: Cyclicals · Base | C88: 2031 | D88: 2032 | E88: 2033 | F88: 2034 | G88: 2035 | H88: 2036 | I88: 2037 | J88: 2038 | K88: 2039 | L88: 2040 | M88: 2041 | N88: 2042: g
B89: Year of the fade | D89: 1 | E89: 2 | F89: 3 | G89: 4 | H89: 5 | I89: 6 | J89: 7 | K89: 8 | L89: 9 | M89: 10 | N89: 11
